Workbook

Sheet INDICE
A1: MATRIZ DE GESTIÓN DE RIESGOS EN LA EJECUCIÓN DE LA OBRA
A2: PROYECTO: MEJORAMIENTO DEL SERVICIO DE TRANSITABILIDAD VIAL INTERURBANA EN LA VÍA DEPARTAMENTAL SM-107, TRAMO TINGO DE PONASA - SHAMBOYACU, DISTRITO DE SHAMBOYACU, PROVINCIA DE PICOTA, DEPARTAMENTO DE SAN MARTÍN - CUI N.° 2673852
A4: N° | B4: HOJA | C4: CONTENIDO
A5: 1 | B5: DATOS | C5: Datos del proyecto y costo diario de ampliación en porcentaje
A6: 2 | B6: ESCALAS | C6: Escalas de probabilidad e impacto, umbrales y matriz P x I
A7: 3 | B7: IDENTIFICACION | C7: Registro de riesgos: evento, causa, efecto, ubicación y evidencia
A8: 4 | B8: ANALISIS CUALITATIVO | C8: Probabilidad, impacto en costo y plazo, P x I y nivel (inherente y residual)
A9: 5 | B9: ANALISIS CUANTITATIVO | C9: Efecto en costo (%) y plazo triangulares, valor esperado y exposición de la Entidad
A10: 6 | B10: MONTE CARLO | C10: Resultados de la simulación (20,000 iteraciones), inherente y residual
A11: 7 | B11: MAPA DE CALOR | C11: Ubicación de cada riesgo en la matriz P x I, antes y después de la respuesta
A12: 8 | B12: PLAN DE RESPUESTA | C12: Estrategia, acciones, responsable, partida, momento y alerta temprana
A13: 9 | B13: ASIGNACION | C13: Parte que asume cada riesgo y criterio
A14: 10 | B14: OPORTUNIDADES | C14: Oportunidades y su estrategia
A15: 11 | B15: SEGUIMIENTO | C15: Formato de seguimiento mensual para el comité de gestión de riesgos
A16: 12 | B16: CALENDARIO | C16: Lluvias mensuales de referencia y programación recomendada
B19: Celda amarilla = dato; celda verde = fórmula.
B20: Los efectos en costo se expresan en porcentaje (%) del presupuesto de obra.

Sheet DATOS
A1: DATOS DEL PROYECTO
A2: PROYECTO: MEJORAMIENTO DEL SERVICIO DE TRANSITABILIDAD VIAL INTERURBANA EN LA VÍA DEPARTAMENTAL SM-107, TRAMO TINGO DE PONASA - SHAMBOYACU, DISTRITO DE SHAMBOYACU, PROVINCIA DE PICOTA, DEPARTAMENTO DE SAN MARTÍN - CUI N.° 2673852
A4: CONCEPTO | B4: VALOR | C4: FUENTE
A5: Código único de inversiones (CUI) | B5: 2673852 | C5: Inventario vial / FTE
A6: Entidad | B6: Gobierno Regional San Martín - Dirección Regional de Transportes y Comunicaciones | C6: FTE
A7: Unidad ejecutora presupuestal | B7: 925 - Región San Martín - Transportes | C7: FTE
A8: Ubicación | B8: Distrito de Shamboyacu, provincia de Picota, departamento de San Martín | C8: FTE
A9: Progresiva inicial | B9: 19+343.39 | C9: Inventario vial
A10: Progresiva final | B10: 44+693.39 | C10: Inventario vial
A11: Longitud del tramo (km) | B11: 25.35 | C11: Inventario vial
A12: Plazo de ejecución (días calendario) | B12: 720 | C12: Resumen ejecutivo
A13: Modalidad de ejecución | B13: Administración indirecta - por contrata | C13: FTE 19
A14: Fuente de financiamiento | B14: Recursos determinados | C14: FTE 20
A15: IMDA actual (veh/día) | B15: 254 | C15: FTE 9.1
A16: Población beneficiaria directa (hab) | B16: 11960 | C16: FTE 6
A17: Costo de un día de ampliación (gastos generales y supervisión), en % del presupuesto de obra por día | B17: 0.0179 | C17: Se reconoce cuando el retraso es atribuible a la Entidad

Sheet ESCALAS
A1: ESCALAS DE PROBABILIDAD E IMPACTO Y MATRIZ P x I
A2: PROYECTO: MEJORAMIENTO DEL SERVICIO DE TRANSITABILIDAD VIAL INTERURBANA EN LA VÍA DEPARTAMENTAL SM-107, TRAMO TINGO DE PONASA - SHAMBOYACU, DISTRITO DE SHAMBOYACU, PROVINCIA DE PICOTA, DEPARTAMENTO DE SAN MARTÍN - CUI N.° 2673852
A4: PROBABILIDAD | B4: VALOR | C4: DESCRIPCIÓN
A5: Muy baja | B5: 0.1 | C5: Puede ocurrir solo en circunstancias excepcionales
A6: Baja | B6: 0.3 | C6: Podría ocurrir alguna vez durante la obra
A7: Moderada | B7: 0.5 | C7: Puede ocurrir durante la obra
A8: Alta | B8: 0.7 | C8: Es probable que ocurra durante la obra
A9: Muy alta | B9: 0.9 | C9: Se espera que ocurra, casi con certeza
A11: IMPACTO | B11: VALOR | C11: DESCRIPCIÓN | D11: COSTO HASTA (% DEL PRESUPUESTO DE OBRA) | E11: PLAZO HASTA (días)
A12: Muy bajo | B12: 0.05 | C12: Efecto mínimo; se absorbe con la holgura del frente | D12: 0.1 | E12: 7
A13: Bajo | B13: 0.1 | C13: Afecta un frente; se recupera dentro del mes | D13: 0.5 | E13: 21
A14: Moderado | B14: 0.2 | C14: Afecta varios frentes o un hito; requiere reprogramar | D14: 1.5 | E14: 45
A15: Alto | B15: 0.4 | C15: Afecta la ruta crítica o el presupuesto de forma significativa | D15: 4 | E15: 90
A16: Muy alto | B16: 0.8 | C16: Compromete el plazo total, el financiamiento o la viabilidad | D16: mayor | E16: mayor
A17: El nivel de impacto es el mayor entre el de costo y el de plazo, evaluados con el valor más probable.
A19: UMBRAL | B19: P x I | C19: INTERPRETACIÓN
A20: ALTO | B20: 0.18 | C20: P x I >= 0.18: respuesta obligatoria antes del inicio, seguimiento mensual del comité
A21: MODERADO | B21: 0.05 | C21: 0.05 <= P x I < 0.18: respuesta planificada y seguimiento por el residente y el supervisor
A22: BAJO | B22: < 0.05 | C22: Se acepta y se vigila con el registro
A24: MATRIZ P x I
A25: P \ I | B25: =A12&" ("&TEXT(B12,"0.00")&")" | C25: =A13&" ("&TEXT(B13,"0.00")&")" | D25: =A14&" ("&TEXT(B14,"0.00")&")" | E25: =A15&" ("&TEXT(B15,"0.00")&")" | F25: =A16&" ("&TEXT(B16,"0.00")&")"
A26: =A9&" ("&TEXT(B9,"0.00")&")" | B26: =$B9*$B12 | C26: =$B9*$B13 | D26: =$B9*$B14 | E26: =$B9*$B15 | F26: =$B9*$B16
A27: =A8&" ("&TEXT(B8,"0.00")&")" | B27: =$B8*$B12 | C27: =$B8*$B13 | D27: =$B8*$B14 | E27: =$B8*$B15 | F27: =$B8*$B16
A28: =A7&" ("&TEXT(B7,"0.00")&")" | B28: =$B7*$B12 | C28: =$B7*$B13 | D28: =$B7*$B14 | E28: =$B7*$B15 | F28: =$B7*$B16
A29: =A6&" ("&TEXT(B6,"0.00")&")" | B29: =$B6*$B12 | C29: =$B6*$B13 | D29: =$B6*$B14 | E29: =$B6*$B15 | F29: =$B6*$B16
A30: =A5&" ("&TEXT(B5,"0.00")&")" | B30: =$B5*$B12 | C30: =$B5*$B13 | D30: =$B5*$B14 | E30: =$B5*$B15 | F30: =$B5*$B16

Sheet IDENTIFICACION
A1: IDENTIFICACIÓN DE RIESGOS
A2: PROYECTO: MEJORAMIENTO DEL SERVICIO DE TRANSITABILIDAD VIAL INTERURBANA EN LA VÍA DEPARTAMENTAL SM-107, TRAMO TINGO DE PONASA - SHAMBOYACU, DISTRITO DE SHAMBOYACU, PROVINCIA DE PICOTA, DEPARTAMENTO DE SAN MARTÍN - CUI N.° 2673852
A4: COD. | B4: CATEGORÍA | C4: RIESGO (EVENTO) | D4: CAUSA | E4: EFECTO | F4: UBICACIÓN / PROGRESIVA | G4: EVIDENCIA EN LOS DOCUMENTOS
A5: R-01 | B5: Clima y naturaleza | C5: Lluvias estacionales intensas (octubre a abril) que paralizan el movimiento de tierras, la pavimentación y los vaciados | D5: Clima cálido y húmedo con lluvias todo el año: 1,020 mm anuales en Tarapoto y 1,471 mm en Juanjuí (NOAA GHCN-Daily), con máximos en marzo y en octubre-noviembre; el plazo de 720 días abarca dos temporadas de lluvias. | E5: Días no trabajables, capas granulares saturadas que se deben reprocesar, retraso de la ruta crítica. | F5: Todo el tramo, 19+343 a 44+693 | G5: FTE: lluvias intensas SI, nivel medio. Inventario: empozamientos y pérdida de material por escorrentía.
A6: R-02 | B6: Clima y naturaleza | C6: Lluvias extraordinarias o anomalías climáticas (El Niño / La Niña) con desborde de quebradas y daños a la obra ejecutada | D6: Eventos de lluvia superiores a los de diseño, declarados por el ENFEN o con declaratoria de emergencia. | E6: Daños en terraplenes, alcantarillas y accesos de puentes; ampliación de plazo con gastos generales. | F6: Quebradas de los 5 puentes y sectores bajos 19+343 a 23+000 | G6: FTE 18.3: el área ha sido afectada por desastres. Inventario: inundación 20+360 a 21+170.
A7: R-03 | B7: Clima y naturaleza | C7: Crecidas de quebradas durante la construcción de estribos de los 5 puentes | D7: Demolición de estribos existentes y excavación bajo agua (806.94 m³ en cada puente de 40 m) en época de lluvias. | E7: Inundación de excavaciones, arrastre de encofrados y ataguías, reprogramación de la subestructura. | F7: Puentes Tingo de Ponasa 20+300, Barco 29+300, Paucarillo 37+870, Apangurayco 38+800, Chanchamayco 44+040 | G7: S10 1.10: excavación bajo agua, encauzamiento de quebrada y desvío temporal en cada puente.
A8: R-04 | B8: Geotecnia | C8: Inestabilidad de taludes y deslizamientos durante los cortes en ladera | D8: Taludes altos (h = 20 a 30 m) en suelos limosos y arcillosos saturables; pendientes del entorno de hasta 40° (modelo digital). | E8: Derrumbes sobre la plataforma, cortes adicionales, banquetas o muros no previstos, riesgo para el personal. | F8: 36+060 a 36+100 (h = 20 m, LI) y 37+520 a 37+780 (h = 30 m, LI); laderas 34+000 a 37+000 y 43+000 a 44+000 | G8: Inventario: zonas críticas por inestabilidad de talud.
A9: R-05 | B9: Geotecnia | C9: Erosión y socavación de la plataforma y de los terraplenes en construcción | D9: Escorrentía sin control y bordes con desnivel de 2 a 5 m; drenaje transversal colmatado. | E9: Pérdida de terraplén, reducción del ancho útil, reconstrucción de capas y protección adicional. | F9: 20+337 a 20+340; 34+766 a 34+786; 36+380 a 36+460; 39+380 a 39+840 (h = 3 a 5 m); 43+620 a 43+632 | G9: Inventario: zonas críticas por erosión y alcantarillas colmatadas o semicolmatadas.
A10: R-06 | B10: Clima y naturaleza | C10: Saturación de terraplenes por inundación de arrozales, canales de riego y empozamientos | D10: La vía cruza zonas de cultivo de arroz con riego por inundación y sectores sin elemento de descarga. | E10: Subrasante saturada, mayor mejoramiento de suelos, retraso de la compactación. | F10: 20+360 a 21+170; 22+270; 22+800 a 22+960; 26+924; 34+954; 40+380; 43+660 | G10: Inventario: inundación por cultivos de arroz y empozamientos sin descarga; cuadro 8 propone alcantarillas en 26+924, 34+954, 40+380 y 43+660.
A11: R-07 | B11: Geotecnia | C11: Subrasante de menor capacidad de soporte que la prevista en el expediente | D11: Suelos limosos y arcillosos variables; exploración con espaciamiento insuficiente. | E11: Mayor volumen de mejoramiento de suelos y geomalla (mayores metrados). | F11: Sectores de terreno natural y material de préstamo expuesto | G11: Inventario 10.2: terreno natural limoso y arcilloso. S10: mejoramiento 59,801 m³.
A12: R-08 | B12: Insumos y canteras | C12: Cantera insuficiente, sin calidad o sin autorización, con mayor distancia de transporte | D12: Unos 423,600 m³ de material granular (terraplén, mejoramiento, subbase y base) dependen de canteras de río; la distancia media es ~31 km. | E12: Cada kilómetro adicional de transporte equivale a cerca de 0.75 % del presupuesto de obra; retraso en la producción de agregados. | F12: Cantera de río (4.50 ha) y accesos (2.50 km) | G12: S10 1.07.02 Transporte de material granular > 1 km; 1.04.07 y 1.04.08 Cantera.
A13: R-09 | B13: Permisos | C13: Demora en autorizaciones de uso de agua y de extracción de material de cauce | D13: Trámites ante la Autoridad Local del Agua y la municipalidad no iniciados en la fase de formulación. | E13: Paralización de la producción de agregados, del riego y de los vaciados. | F13: Fuente de agua (acceso 1.70 km) y cantera de río | G13: S10 1.04.09 Acceso a fuente de agua; 1.04.08 Cantera de río.
A14: R-10 | B14: Social y predios | C14: Falta de libre disponibilidad del terreno para el ensanche de la plataforma | D14: El ancho pasa de 4.50-6.00 m a 7.00 m más cunetas; derecho de vía de 20 m inexistente; viviendas, cercos y cultivos en el borde. | E14: Frentes detenidos, compensaciones, rediseño de cunetas y del eje en zonas urbanas. | F14: Tingo de Ponasa 19+343 a 19+800; Aypena 21+940; Nuevo América 26+270; Leoncio Prado 28+080; San Antonio 31+420; Huañipo 33+780; Paucar 38+020; Alfonso Ugarte 38+730; Shamboyacu 44+300 a 44+693 | G14: FTE 11: acta de libre disponibilidad del terreno. Resumen ejecutivo: derecho de vía de 20 m como mínimo con proyecto.
A15: R-11 | B15: Interferencias | C15: Interferencias con redes eléctricas, de agua potable y de telecomunicaciones | D15: 73 postes a reubicar; pases de agua potable y tuberías de PVC bajo la vía. | E15: Cortes de servicio, reclamos, espera de la concesionaria, frentes detenidos. | F15: Pase de agua potable 22+425; PVC 21" 25+715; PVC 6" 34+688; postes en las 9 localidades | G15: S10 1.04.12 Reubicación de postes (73 und); inventario 11.3.
... A38: R-34 | B38: Expediente técnico | C38: Cambio de diseño de puentes por condiciones de cauce, socavación o cimentación distintas | D38: Puentes de 12 a 40 m en cauces con socavación y suelos de fundación variables. | E38: Mayores profundidades de cimentación o luces, adicionales y plazo. | F38: Puentes Tingo de Ponasa 20+300 y Barco 29+300 | G38: S10 1.10 Puentes; inventario vial 11.2 (puentes existentes).

Sheet ANALISIS CUALITATIVO
A1: ANÁLISIS CUALITATIVO (P x I)
A2: PROYECTO: MEJORAMIENTO DEL SERVICIO DE TRANSITABILIDAD VIAL INTERURBANA EN LA VÍA DEPARTAMENTAL SM-107, TRAMO TINGO DE PONASA - SHAMBOYACU, DISTRITO DE SHAMBOYACU, PROVINCIA DE PICOTA, DEPARTAMENTO DE SAN MARTÍN - CUI N.° 2673852
A4: COD. | B4: RIESGO | C4: PROBABILIDAD | D4: P | E4: COSTO MÁS PROBABLE (% PRESUPUESTO) | F4: NIVEL COSTO | G4: PLAZO MÁS PROBABLE (días) | H4: NIVEL PLAZO | I4: NIVEL IMPACTO | J4: IMPACTO | K4: I | L4: P x I | M4: NIVEL INHERENTE | N4: PROBABILIDAD RESIDUAL | O4: P RES. | P4: P x I RES. | Q4: NIVEL RESIDUAL
A5: =IDENTIFICACION!A5 | B5: =IDENTIFICACION!C5 | C5: Muy alta | D5: =VLOOKUP(C5,ESCALAS!$A$5:$B$9,2,FALSE) | E5: 0.3269 | F5: =1+(E5>ESCALAS!$D$12)+(E5>ESCALAS!$D$13)+(E5>ESCALAS!$D$14)+(E5>ESCALAS!$D$15) | G5: 25 | H5: =1+(G5>ESCALAS!$E$12)+(G5>ESCALAS!$E$13)+(G5>ESCALAS!$E$14)+(G5>ESCALAS!$E$15) | I5: =MAX(F5,H5) | J5: =INDEX(ESCALAS!$A$12:$A$16,I5) | K5: =INDEX(ESCALAS!$B$12:$B$16,I5) | L5: =D5*K5 | M5: =IF(L5>=ESCALAS!$B$20,"ALTO",IF(L5>=ESCALAS!$B$21,"MODERADO","BAJO")) | N5: Alta | O5: =VLOOKUP(N5,ESCALAS!$A$5:$B$9,2,FALSE) | P5: =O5*K5 | Q5: =IF(P5>=ESCALAS!$B$20,"ALTO",IF(P5>=ESCALAS!$B$21,"MODERADO","BAJO"))
A6: =IDENTIFICACION!A6 | B6: =IDENTIFICACION!C6 | C6: Baja | D6: =VLOOKUP(C6,ESCALAS!$A$5:$B$9,2,FALSE) | E6: 0.9806 | F6: =1+(E6>ESCALAS!$D$12)+(E6>ESCALAS!$D$13)+(E6>ESCALAS!$D$14)+(E6>ESCALAS!$D$15) | G6: 30 | H6: =1+(G6>ESCALAS!$E$12)+(G6>ESCALAS!$E$13)+(G6>ESCALAS!$E$14)+(G6>ESCALAS!$E$15) | I6: =MAX(F6,H6) | J6: =INDEX(ESCALAS!$A$12:$A$16,I6) | K6: =INDEX(ESCALAS!$B$12:$B$16,I6) | L6: =D6*K6 | M6: =IF(L6>=ESCALAS!$B$20,"ALTO",IF(L6>=ESCALAS!$B$21,"MODERADO","BAJO")) | N6: Baja | O6: =VLOOKUP(N6,ESCALAS!$A$5:$B$9,2,FALSE) | P6: =O6*K6 | Q6: =IF(P6>=ESCALAS!$B$20,"ALTO",IF(P6>=ESCALAS!$B$21,"MODERADO","BAJO"))
A7: =IDENTIFICACION!A7 | B7: =IDENTIFICACION!C7 | C7: Moderada | D7: =VLOOKUP(C7,ESCALAS!$A$5:$B$9,2,FALSE) | E7: 0.286 | F7: =1+(E7>ESCALAS!$D$12)+(E7>ESCALAS!$D$13)+(E7>ESCALAS!$D$14)+(E7>ESCALAS!$D$15) | G7: 20 | H7: =1+(G7>ESCALAS!$E$12)+(G7>ESCALAS!$E$13)+(G7>ESCALAS!$E$14)+(G7>ESCALAS!$E$15) | I7: =MAX(F7,H7) | J7: =INDEX(ESCALAS!$A$12:$A$16,I7) | K7: =INDEX(ESCALAS!$B$12:$B$16,I7) | L7: =D7*K7 | M7: =IF(L7>=ESCALAS!$B$20,"ALTO",IF(L7>=ESCALAS!$B$21,"MODERADO","BAJO")) | N7: Baja | O7: =VLOOKUP(N7,ESCALAS!$A$5:$B$9,2,FALSE) | P7: =O7*K7 | Q7: =IF(P7>=ESCALAS!$B$20,"ALTO",IF(P7>=ESCALAS!$B$21,"MODERADO","BAJO"))
A8: =IDENTIFICACION!A8 | B8: =IDENTIFICACION!C8 | C8: Moderada | D8: =VLOOKUP(C8,ESCALAS!$A$5:$B$9,2,FALSE) | E8: 0.572 | F8: =1+(E8>ESCALAS!$D$12)+(E8>ESCALAS!$D$13)+(E8>ESCALAS!$D$14)+(E8>ESCALAS!$D$15) | G8: 20 | H8: =1+(G8>ESCALAS!$E$12)+(G8>ESCALAS!$E$13)+(G8>ESCALAS!$E$14)+(G8>ESCALAS!$E$15) | I8: =MAX(F8,H8) | J8: =INDEX(ESCALAS!$A$12:$A$16,I8) | K8: =INDEX(ESCALAS!$B$12:$B$16,I8) | L8: =D8*K8 | M8: =IF(L8>=ESCALAS!$B$20,"ALTO",IF(L8>=ESCALAS!$B$21,"MODERADO","BAJO")) | N8: Baja | O8: =VLOOKUP(N8,ESCALAS!$A$5:$B$9,2,FALSE) | P8: =O8*K8 | Q8: =IF(P8>=ESCALAS!$B$20,"ALTO",IF(P8>=ESCALAS!$B$21,"MODERADO","BAJO"))
A9: =IDENTIFICACION!A9 | B9: =IDENTIFICACION!C9 | C9: Alta | D9: =VLOOKUP(C9,ESCALAS!$A$5:$B$9,2,FALSE) | E9: 0.4086 | F9: =1+(E9>ESCALAS!$D$12)+(E9>ESCALAS!$D$13)+(E9>ESCALAS!$D$14)+(E9>ESCALAS!$D$15) | G9: 15 | H9: =1+(G9>ESCALAS!$E$12)+(G9>ESCALAS!$E$13)+(G9>ESCALAS!$E$14)+(G9>ESCALAS!$E$15) | I9: =MAX(F9,H9) | J9: =INDEX(ESCALAS!$A$12:$A$16,I9) | K9: =INDEX(ESCALAS!$B$12:$B$16,I9) | L9: =D9*K9 | M9: =IF(L9>=ESCALAS!$B$20,"ALTO",IF(L9>=ESCALAS!$B$21,"MODERADO","BAJO")) | N9: Moderada | O9: =VLOOKUP(N9,ESCALAS!$A$5:$B$9,2,FALSE) | P9: =O9*K9 | Q9: =IF(P9>=ESCALAS!$B$20,"ALTO",IF(P9>=ESCALAS!$B$21,"MODERADO","BAJO"))
A10: =IDENTIFICACION!A10 | B10: =IDENTIFICACION!C10 | C10: Alta | D10: =VLOOKUP(C10,ESCALAS!$A$5:$B$9,2,FALSE) | E10: 0.4903 | F10: =1+(E10>ESCALAS!$D$12)+(E10>ESCALAS!$D$13)+(E10>ESCALAS!$D$14)+(E10>ESCALAS!$D$15) | G10: 20 | H10: =1+(G10>ESCALAS!$E$12)+(G10>ESCALAS!$E$13)+(G10>ESCALAS!$E$14)+(G10>ESCALAS!$E$15) | I10: =MAX(F10,H10) | J10: =INDEX(ESCALAS!$A$12:$A$16,I10) | K10: =INDEX(ESCALAS!$B$12:$B$16,I10) | L10: =D10*K10 | M10: =IF(L10>=ESCALAS!$B$20,"ALTO",IF(L10>=ESCALAS!$B$21,"MODERADO","BAJO")) | N10: Moderada | O10: =VLOOKUP(N10,ESCALAS!$A$5:$B$9,2,FALSE) | P10: =O10*K10 | Q10: =IF(P10>=ESCALAS!$B$20,"ALTO",IF(P10>=ESCALAS!$B$21,"MODERADO","BAJO"))
A11: =IDENTIFICACION!A11 | B11: =IDENTIFICACION!C11 | C11: Moderada | D11: =VLOOKUP(C11,ESCALAS!$A$5:$B$9,2,FALSE) | E11: 0.9969 | F11: =1+(E11>ESCALAS!$D$12)+(E11>ESCALAS!$D$13)+(E11>ESCALAS!$D$14)+(E11>ESCALAS!$D$15) | G11: 20 | H11: =1+(G11>ESCALAS!$E$12)+(G11>ESCALAS!$E$13)+(G11>ESCALAS!$E$14)+(G11>ESCALAS!$E$15) | I11: =MAX(F11,H11) | J11: =INDEX(ESCALAS!$A$12:$A$16,I11) | K11: =INDEX(ESCALAS!$B$12:$B$16,I11) | L11: =D11*K11 | M11: =IF(L11>=ESCALAS!$B$20,"ALTO",IF(L11>=ESCALAS!$B$21,"MODERADO","BAJO")) | N11: Baja | O11: =VLOOKUP(N11,ESCALAS!$A$5:$B$9,2,FALSE) | P11: =O11*K11 | Q11: =IF(P11>=ESCALAS!$B$20,"ALTO",IF(P11>=ESCALAS!$B$21,"MODERADO","BAJO"))
A12: =IDENTIFICACION!A12 | B12: =IDENTIFICACION!C12 | C12: Moderada | D12: =VLOOKUP(C12,ESCALAS!$A$5:$B$9,2,FALSE) | E12: 2.2635 | F12: =1+(E12>ESCALAS!$D$12)+(E12>ESCALAS!$D$13)+(E12>ESCALAS!$D$14)+(E12>ESCALAS!$D$15) | G12: 30 | H12: =1+(G12>ESCALAS!$E$12)+(G12>ESCALAS!$E$13)+(G12>ESCALAS!$E$14)+(G12>ESCALAS!$E$15) | I12: =MAX(F12,H12) | J12: =INDEX(ESCALAS!$A$12:$A$16,I12) | K12: =INDEX(ESCALAS!$B$12:$B$16,I12) | L12: =D12*K12 | M12: =IF(L12>=ESCALAS!$B$20,"ALTO",IF(L12>=ESCALAS!$B$21,"MODERADO","BAJO")) | N12: Muy baja | O12: =VLOOKUP(N12,ESCALAS!$A$5:$B$9,2,FALSE) | P12: =O12*K12 | Q12: =IF(P12>=ESCALAS!$B$20,"ALTO",IF(P12>=ESCALAS!$B$21,"MODERADO","BAJO"))
A13: =IDENTIFICACION!A13 | B13: =IDENTIFICACION!C13 | C13: Moderada | D13: =VLOOKUP(C13,ESCALAS!$A$5:$B$9,2,FALSE) | E13: 0.049 | F13: =1+(E13>ESCALAS!$D$12)+(E13>ESCALAS!$D$13)+(E13>ESCALAS!$D$14)+(E13>ESCALAS!$D$15) | G13: 30 | H13: =1+(G13>ESCALAS!$E$12)+(G13>ESCALAS!$E$13)+(G13>ESCALAS!$E$14)+(G13>ESCALAS!$E$15) | I13: =MAX(F13,H13) | J13: =INDEX(ESCALAS!$A$12:$A$16,I13) | K13: =INDEX(ESCALAS!$B$12:$B$16,I13) | L13: =D13*K13 | M13: =IF(L13>=ESCALAS!$B$20,"ALTO",IF(L13>=ESCALAS!$B$21,"MODERADO","BAJO")) | N13: Muy baja | O13: =VLOOKUP(N13,ESCALAS!$A$5:$B$9,2,FALSE) | P13: =O13*K13 | Q13: =IF(P13>=ESCALAS!$B$20,"ALTO",IF(P13>=ESCALAS!$B$21,"MODERADO","BAJO"))
A14: =IDENTIFICACION!A14 | B14: =IDENTIFICACION!C14 | C14: Alta | D14: =VLOOKUP(C14,ESCALAS!$A$5:$B$9,2,FALSE) | E14: 0.3269 | F14: =1+(E14>ESCALAS!$D$12)+(E14>ESCALAS!$D$13)+(E14>ESCALAS!$D$14)+(E14>ESCALAS!$D$15) | G14: 30 | H14: =1+(G14>ESCALAS!$E$12)+(G14>ESCALAS!$E$13)+(G14>ESCALAS!$E$14)+(G14>ESCALAS!$E$15) | I14: =MAX(F14,H14) | J14: =INDEX(ESCALAS!$A$12:$A$16,I14) | K14: =INDEX(ESCALAS!$B$12:$B$16,I14) | L14: =D14*K14 | M14: =IF(L14>=ESCALAS!$B$20,"ALTO",IF(L14>=ESCALAS!$B$21,"MODERADO","BAJO")) | N14: Baja | O14: =VLOOKUP(N14,ESCALAS!$A$5:$B$9,2,FALSE) | P14: =O14*K14 | Q14: =IF(P14>=ESCALAS!$B$20,"ALTO",IF(P14>=ESCALAS!$B$21,"MODERADO","BAJO"))
A15: =IDENTIFICACION!A15 | B15: =IDENTIFICACION!C15 | C15: Alta | D15: =VLOOKUP(C15,ESCALAS!$A$5:$B$9,2,FALSE) | E15: 0.1634 | F15: =1+(E15>ESCALAS!$D$12)+(E15>ESCALAS!$D$13)+(E15>ESCALAS!$D$14)+(E15>ESCALAS!$D$15) | G15: 20 | H15: =1+(G15>ESCALAS!$E$12)+(G15>ESCALAS!$E$13)+(G15>ESCALAS!$E$14)+(G15>ESCALAS!$E$15) | I15: =MAX(F15,H15) | J15: =INDEX(ESCALAS!$A$12:$A$16,I15) | K15: =INDEX(ESCALAS!$B$12:$B$16,I15) | L15: =D15*K15 | M15: =IF(L15>=ESCALAS!$B$20,"ALTO",IF(L15>=ESCALAS!$B$21,"MODERADO","BAJO")) | N15: Baja | O15: =VLOOKUP(N15,ESCALAS!$A$5:$B$9,2,FALSE) | P15: =O15*K15 | Q15: =IF(P15>=ESCALAS!$B$20,"ALTO",IF(P15>=ESCALAS!$B$21,"MODERADO","BAJO"))
A16: =IDENTIFICACION!A16 | B16: =IDENTIFICACION!C16 | C16: Moderada | D16: =VLOOKUP(C16,ESCALAS!$A$5:$B$9,2,FALSE) | E16: 0.1226 | F16: =1+(E16>ESCALAS!$D$12)+(E16>ESCALAS!$D$13)+(E16>ESCALAS!$D$14)+(E16>ESCALAS!$D$15) | G16: 15 | H16: =1+(G16>ESCALAS!$E$12)+(G16>ESCALAS!$E$13)+(G16>ESCALAS!$E$14)+(G16>ESCALAS!$E$15) | I16: =MAX(F16,H16) | J16: =INDEX(ESCALAS!$A$12:$A$16,I16) | K16: =INDEX(ESCALAS!$B$12:$B$16,I16) | L16: =D16*K16 | M16: =IF(L16>=ESCALAS!$B$20,"ALTO",IF(L16>=ESCALAS!$B$21,"MODERADO","BAJO")) | N16: Baja | O16: =VLOOKUP(N16,ESCALAS!$A$5:$B$9,2,FALSE) | P16: =O16*K16 | Q16: =IF(P16>=ESCALAS!$B$20,"ALTO",IF(P16>=ESCALAS!$B$21,"MODERADO","BAJO"))
... A38: =IDENTIFICACION!A38 | B38: =IDENTIFICACION!C38 | C38: Baja | D38: =VLOOKUP(C38,ESCALAS!$A$5:$B$9,2,FALSE) | E38: 0.6537 | F38: =1+(E38>ESCALAS!$D$12)+(E38>ESCALAS!$D$13)+(E38>ESCALAS!$D$14)+(E38>ESCALAS!$D$15) | G38: 30 | H38: =1+(G38>ESCALAS!$E$12)+(G38>ESCALAS!$E$13)+(G38>ESCALAS!$E$14)+(G38>ESCALAS!$E$15) | I38: =MAX(F38,H38) | J38: =INDEX(ESCALAS!$A$12:$A$16,I38) | K38: =INDEX(ESCALAS!$B$12:$B$16,I38) | L38: =D38*K38 | M38: =IF(L38>=ESCALAS!$B$20,"ALTO",IF(L38>=ESCALAS!$B$21,"MODERADO","BAJO")) | N38: Muy baja | O38: =VLOOKUP(N38,ESCALAS!$A$5:$B$9,2,FALSE) | P38: =O38*K38 | Q38: =IF(P38>=ESCALAS!$B$20,"ALTO",IF(P38>=ESCALAS!$B$21,"MODERADO","BAJO"))
B40: RESUMEN | M40: INHERENTE | Q40: RESIDUAL
B41: Riesgos de nivel ALTO | M41: =COUNTIF(M5:M38,"ALTO") | Q41: =COUNTIF(Q5:Q38,"ALTO")
B42: Riesgos de nivel MODERADO | M42: =COUNTIF(M5:M38,"MODERADO") | Q42: =COUNTIF(Q5:Q38,"MODERADO")
B43: Riesgos de nivel BAJO | M43: =COUNTIF(M5:M38,"BAJO") | Q43: =COUNTIF(Q5:Q38,"BAJO")

Sheet ANALISIS CUANTITATIVO
A1: ANÁLISIS CUANTITATIVO - VALOR ESPERADO (EFECTO EN COSTO EN % DEL PRESUPUESTO DE OBRA)
A2: PROYECTO: MEJORAMIENTO DEL SERVICIO DE TRANSITABILIDAD VIAL INTERURBANA EN LA VÍA DEPARTAMENTAL SM-107, TRAMO TINGO DE PONASA - SHAMBOYACU, DISTRITO DE SHAMBOYACU, PROVINCIA DE PICOTA, DEPARTAMENTO DE SAN MARTÍN - CUI N.° 2673852
A4: COD. | B4: RIESGO | C4: ASIGNADO A | D4: FACTOR ENTIDAD | E4: FACTOR PÓLIZA | F4: P | G4: COSTO MÍN. (%) | H4: COSTO MÁS PROB. (%) | I4: COSTO MÁX. (%) | J4: COSTO MEDIO (%) | K4: VALOR ESPERADO COSTO (%) | L4: PLAZO MÍN. | M4: PLAZO MÁS PROB. | N4: PLAZO MÁX. | O4: PLAZO MEDIO | P4: VME PLAZO (días) | Q4: RUTA CRÍTICA | R4: EXPOSICIÓN ENTIDAD INHERENTE (%) | S4: P RES. | T4: EXPOSICIÓN ENTIDAD RESIDUAL (%)
A5: =IDENTIFICACION!A5 | B5: =IDENTIFICACION!C5 | C5: Contratista | D5: =IF(C5="Entidad",1,IF(C5="Compartido",0.5,0)) | E5: 1 | F5: ='ANALISIS CUALITATIVO'!D5 | G5: 0.1226 | H5: ='ANALISIS CUALITATIVO'!E5 | I5: 0.7354 | J5: =AVERAGE(G5:I5) | K5: =F5*J5 | L5: 10 | M5: ='ANALISIS CUALITATIVO'!G5 | N5: 60 | O5: =AVERAGE(L5:N5) | P5: =F5*O5 | Q5: SI | R5: =F5*J5*D5*E5+IF(Q5="SI",F5*O5*D5*DATOS!$B$17,0) | S5: ='ANALISIS CUALITATIVO'!O5 | T5: =S5*J5*D5*E5+IF(Q5="SI",S5*O5*D5*DATOS!$B$17,0)
A6: =IDENTIFICACION!A6 | B6: =IDENTIFICACION!C6 | C6: Entidad | D6: =IF(C6="Entidad",1,IF(C6="Compartido",0.5,0)) | E6: 0.4 | F6: ='ANALISIS CUALITATIVO'!D6 | G6: 0.2451 | H6: ='ANALISIS CUALITATIVO'!E6 | I6: 2.86 | J6: =AVERAGE(G6:I6) | K6: =F6*J6 | L6: 15 | M6: ='ANALISIS CUALITATIVO'!G6 | N6: 60 | O6: =AVERAGE(L6:N6) | P6: =F6*O6 | Q6: SI | R6: =F6*J6*D6*E6+IF(Q6="SI",F6*O6*D6*DATOS!$B$17,0) | S6: ='ANALISIS CUALITATIVO'!O6 | T6: =S6*J6*D6*E6+IF(Q6="SI",S6*O6*D6*DATOS!$B$17,0)
A7: =IDENTIFICACION!A7 | B7: =IDENTIFICACION!C7 | C7: Contratista | D7: =IF(C7="Entidad",1,IF(C7="Compartido",0.5,0)) | E7: 1 | F7: ='ANALISIS CUALITATIVO'!D7 | G7: 0.0817 | H7: ='ANALISIS CUALITATIVO'!E7 | I7: 0.7354 | J7: =AVERAGE(G7:I7) | K7: =F7*J7 | L7: 7 | M7: ='ANALISIS CUALITATIVO'!G7 | N7: 45 | O7: =AVERAGE(L7:N7) | P7: =F7*O7 | Q7: SI | R7: =F7*J7*D7*E7+IF(Q7="SI",F7*O7*D7*DATOS!$B$17,0) | S7: ='ANALISIS CUALITATIVO'!O7 | T7: =S7*J7*D7*E7+IF(Q7="SI",S7*O7*D7*DATOS!$B$17,0)
A8: =IDENTIFICACION!A8 | B8: =IDENTIFICACION!C8 | C8: Compartido | D8: =IF(C8="Entidad",1,IF(C8="Compartido",0.5,0)) | E8: 1 | F8: ='ANALISIS CUALITATIVO'!D8 | G8: 0.1634 | H8: ='ANALISIS CUALITATIVO'!E8 | I8: 1.6343 | J8: =AVERAGE(G8:I8) | K8: =F8*J8 | L8: 7 | M8: ='ANALISIS CUALITATIVO'!G8 | N8: 45 | O8: =AVERAGE(L8:N8) | P8: =F8*O8 | Q8: SI | R8: =F8*J8*D8*E8+IF(Q8="SI",F8*O8*D8*DATOS!$B$17,0) | S8: ='ANALISIS CUALITATIVO'!O8 | T8: =S8*J8*D8*E8+IF(Q8="SI",S8*O8*D8*DATOS!$B$17,0)
A9: =IDENTIFICACION!A9 | B9: =IDENTIFICACION!C9 | C9: Contratista | D9: =IF(C9="Entidad",1,IF(C9="Compartido",0.5,0)) | E9: 1 | F9: ='ANALISIS CUALITATIVO'!D9 | G9: 0.1226 | H9: ='ANALISIS CUALITATIVO'!E9 | I9: 0.9806 | J9: =AVERAGE(G9:I9) | K9: =F9*J9 | L9: 5 | M9: ='ANALISIS CUALITATIVO'!G9 | N9: 40 | O9: =AVERAGE(L9:N9) | P9: =F9*O9 | Q9: NO | R9: =F9*J9*D9*E9+IF(Q9="SI",F9*O9*D9*DATOS!$B$17,0) | S9: ='ANALISIS CUALITATIVO'!O9 | T9: =S9*J9*D9*E9+IF(Q9="SI",S9*O9*D9*DATOS!$B$17,0)
A10: =IDENTIFICACION!A10 | B10: =IDENTIFICACION!C10 | C10: Compartido | D10: =IF(C10="Entidad",1,IF(C10="Compartido",0.5,0)) | E10: 1 | F10: ='ANALISIS CUALITATIVO'!D10 | G10: 0.1634 | H10: ='ANALISIS CUALITATIVO'!E10 | I10: 1.2257 | J10: =AVERAGE(G10:I10) | K10: =F10*J10 | L10: 10 | M10: ='ANALISIS CUALITATIVO'!G10 | N10: 45 | O10: =AVERAGE(L10:N10) | P10: =F10*O10 | Q10: NO | R10: =F10*J10*D10*E10+IF(Q10="SI",F10*O10*D10*DATOS!$B$17,0) | S10: ='ANALISIS CUALITATIVO'!O10 | T10: =S10*J10*D10*E10+IF(Q10="SI",S10*O10*D10*DATOS!$B$17,0)
A11: =IDENTIFICACION!A11 | B11: =IDENTIFICACION!C11 | C11: Entidad | D11: =IF(C11="Entidad",1,IF(C11="Compartido",0.5,0)) | E11: 1 | F11: ='ANALISIS CUALITATIVO'!D11 | G11: 0.4004 | H11: ='ANALISIS CUALITATIVO'!E11 | I11: 2.002 | J11: =AVERAGE(G11:I11) | K11: =F11*J11 | L11: 10 | M11: ='ANALISIS CUALITATIVO'!G11 | N11: 40 | O11: =AVERAGE(L11:N11) | P11: =F11*O11 | Q11: NO | R11: =F11*J11*D11*E11+IF(Q11="SI",F11*O11*D11*DATOS!$B$17,0) | S11: ='ANALISIS CUALITATIVO'!O11 | T11: =S11*J11*D11*E11+IF(Q11="SI",S11*O11*D11*DATOS!$B$17,0)
A12: =IDENTIFICACION!A12 | B12: =IDENTIFICACION!C12 | C12: Entidad | D12: =IF(C12="Entidad",1,IF(C12="Compartido",0.5,0)) | E12: 1 | F12: ='ANALISIS CUALITATIVO'!D12 | G12: 0.7518 | H12: ='ANALISIS CUALITATIVO'!E12 | I12: 6.0306 | J12: =AVERAGE(G12:I12) | K12: =F12*J12 | L12: 15 | M12: ='ANALISIS CUALITATIVO'!G12 | N12: 60 | O12: =AVERAGE(L12:N12) | P12: =F12*O12 | Q12: SI | R12: =F12*J12*D12*E12+IF(Q12="SI",F12*O12*D12*DATOS!$B$17,0) | S12: ='ANALISIS CUALITATIVO'!O12 | T12: =S12*J12*D12*E12+IF(Q12="SI",S12*O12*D12*DATOS!$B$17,0)
A13: =IDENTIFICACION!A13 | B13: =IDENTIFICACION!C13 | C13: Entidad | D13: =IF(C13="Entidad",1,IF(C13="Compartido",0.5,0)) | E13: 1 | F13: ='ANALISIS CUALITATIVO'!D13 | G13: 0.0163 | H13: ='ANALISIS CUALITATIVO'!E13 | I13: 0.1226 | J13: =AVERAGE(G13:I13) | K13: =F13*J13 | L13: 15 | M13: ='ANALISIS CUALITATIVO'!G13 | N13: 60 | O13: =AVERAGE(L13:N13) | P13: =F13*O13 | Q13: SI | R13: =F13*J13*D13*E13+IF(Q13="SI",F13*O13*D13*DATOS!$B$17,0) | S13: ='ANALISIS CUALITATIVO'!O13 | T13: =S13*J13*D13*E13+IF(Q13="SI",S13*O13*D13*DATOS!$B$17,0)
A14: =IDENTIFICACION!A14 | B14: =IDENTIFICACION!C14 | C14: Entidad | D14: =IF(C14="Entidad",1,IF(C14="Compartido",0.5,0)) | E14: 1 | F14: ='ANALISIS CUALITATIVO'!D14 | G14: 0.0817 | H14: ='ANALISIS CUALITATIVO'!E14 | I14: 0.9806 | J14: =AVERAGE(G14:I14) | K14: =F14*J14 | L14: 15 | M14: ='ANALISIS CUALITATIVO'!G14 | N14: 90 | O14: =AVERAGE(L14:N14) | P14: =F14*O14 | Q14: SI | R14: =F14*J14*D14*E14+IF(Q14="SI",F14*O14*D14*DATOS!$B$17,0) | S14: ='ANALISIS CUALITATIVO'!O14 | T14: =S14*J14*D14*E14+IF(Q14="SI",S14*O14*D14*DATOS!$B$17,0)
A15: =IDENTIFICACION!A15 | B15: =IDENTIFICACION!C15 | C15: Entidad | D15: =IF(C15="Entidad",1,IF(C15="Compartido",0.5,0)) | E15: 1 | F15: ='ANALISIS CUALITATIVO'!D15 | G15: 0.0409 | H15: ='ANALISIS CUALITATIVO'!E15 | I15: 0.4086 | J15: =AVERAGE(G15:I15) | K15: =F15*J15 | L15: 10 | M15: ='ANALISIS CUALITATIVO'!G15 | N15: 45 | O15: =AVERAGE(L15:N15) | P15: =F15*O15 | Q15: SI | R15: =F15*J15*D15*E15+IF(Q15="SI",F15*O15*D15*DATOS!$B$17,0) | S15: ='ANALISIS CUALITATIVO'!O15 | T15: =S15*J15*D15*E15+IF(Q15="SI",S15*O15*D15*DATOS!$B$17,0)
A16: =IDENTIFICACION!A16 | B16: =IDENTIFICACION!C16 | C16: Compartido | D16: =IF(C16="Entidad",1,IF(C16="Compartido",0.5,0)) | E16: 1 | F16: ='ANALISIS CUALITATIVO'!D16 | G16: 0.0409 | H16: ='ANALISIS CUALITATIVO'!E16 | I16: 0.3269 | J16: =AVERAGE(G16:I16) | K16: =F16*J16 | L16: 5 | M16: ='ANALISIS CUALITATIVO'!G16 | N16: 30 | O16: =AVERAGE(L16:N16) | P16: =F16*O16 | Q16: NO | R16: =F16*J16*D16*E16+IF(Q16="SI",F16*O16*D16*DATOS!$B$17,0) | S16: ='ANALISIS CUALITATIVO'!O16 | T16: =S16*J16*D16*E16+IF(Q16="SI",S16*O16*D16*DATOS!$B$17,0)
... A38: =IDENTIFICACION!A38 | B38: =IDENTIFICACION!C38 | C38: Entidad | D38: =IF(C38="Entidad",1,IF(C38="Compartido",0.5,0)) | E38: 1 | F38: ='ANALISIS CUALITATIVO'!D38 | G38: 0.1634 | H38: ='ANALISIS CUALITATIVO'!E38 | I38: 2.0429 | J38: =AVERAGE(G38:I38) | K38: =F38*J38 | L38: 15 | M38: ='ANALISIS CUALITATIVO'!G38 | N38: 90 | O38: =AVERAGE(L38:N38) | P38: =F38*O38 | Q38: SI | R38: =F38*J38*D38*E38+IF(Q38="SI",F38*O38*D38*DATOS!$B$17,0) | S38: ='ANALISIS CUALITATIVO'!O38 | T38: =S38*J38*D38*E38+IF(Q38="SI",S38*O38*D38*DATOS!$B$17,0)
B39: TOTAL (suma simple, sin concurrencia de plazos) | K39: =SUM(K5:K38) | P39: =SUM(P5:P38) | R39: =SUM(R5:R38) | T39: =SUM(T5:T38)
B42: Valor esperado = P x valor medio de la distribución triangular. Factor Entidad: 1 (Entidad), 0.5 (compartido), 0 (contratista); factor póliza: fracción que no cubre la póliza CAR. Los días de ruta crítica de la Entidad se valorizan con el costo diario de ampliación (hoja DATOS). La suma simple no considera que los retrasos se superponen; la hoja MONTE CARLO sí lo hace.

Sheet MONTE CARLO
A1: SIMULACIÓN DE MONTE CARLO (20,000 ITERACIONES)
A2: PROYECTO: MEJORAMIENTO DEL SERVICIO DE TRANSITABILIDAD VIAL INTERURBANA EN LA VÍA DEPARTAMENTAL SM-107, TRAMO TINGO DE PONASA - SHAMBOYACU, DISTRITO DE SHAMBOYACU, PROVINCIA DE PICOTA, DEPARTAMENTO DE SAN MARTÍN - CUI N.° 2673852
A4: RESULTADO | B4: P10 | C4: P50 | D4: P80 | E4: P90 | F4: MEDIA
A5: Efecto en costo para la Entidad - inherente (% del presupuesto de obra) | B5: 6.0770307 | C5: 9.4065084 | D5: 11.81694 | E5: 13.107372 | F5: 9.495593
A6: Efecto en costo para la Entidad - residual (% del presupuesto de obra) | B6: 2.2183017 | C6: 4.5407927 | D6: 6.4304925 | E6: 7.5733744 | F6: 4.7541559
A7: Retraso total de la obra - inherente (días) | B7: 143.62092 | C7: 195.9459 | D7: 230.09599 | E7: 247.54102 | F7: 195.74829
A8: Retraso total de la obra - residual (días) | B8: 61.790836 | C8: 113.21726 | D8: 147.96402 | E8: 167.39773 | F8: 114.15549
A9: Retraso atribuible a la Entidad - inherente (días) | B9: 96.489893 | C9: 149.34513 | D9: 185.21522 | E9: 203.86759 | F9: —
A10: Retraso atribuible a la Entidad - residual (días) | B10: 29.945496 | C10: 76.971523 | D10: 111.46779 | E10: 130.84257 | F10: —
A11: Efecto en costo de riesgos del contratista - inherente (%) | B11: 1.4137916 | C11: 2.1634914 | D11: 2.7008255 | E11: 2.9920822 | F11: 2.1853387
A12: Efecto en costo de riesgos del contratista - residual (%) | B12: 0.67392703 | C12: 1.3333203 | D12: 1.8353389 | E12: 2.1153888 | F12: 1.370143
A14: Reserva de contingencia recomendada (P80 residual, % del presupuesto de obra) | B14: 6.4304925
A16: Método:
A17: 1. Cada riesgo ocurre en una iteración con su probabilidad (inherente o residual, hoja ANALISIS CUALITATIVO).
A18: 2. Si ocurre, su costo y su retraso se toman de una distribución triangular (mínimo, más probable, máximo).
A19: 3. Efecto en costo para la Entidad (% del presupuesto de obra): riesgos de la Entidad, 50 % de los compartidos (descontando la póliza CAR donde aplica) y los días de ampliación que le corresponden por el costo diario.
A20: 4. Plazo: los riesgos de ruta crítica se agrupan por etapa (inicio, clima, terreno, gestión); en cada grupo se suma el mayor retraso y el 25 % de los demás, y los grupos se suman.
A21: 5. Residual: con las respuestas del PLAN DE RESPUESTA ejecutadas en el momento indicado.
A24: Histograma del efecto en costo para la Entidad (% del presupuesto de obra)
A25: CLASE (% PRESUPUESTO) | B25: INHERENTE (% ITERACIONES) | C25: RESIDUAL (% ITERACIONES)
A26: 0.29 | B26: 0 | C26: 0.6
A27: 0.86 | B27: 0 | C27: 1.8
A28: 1.43 | B28: 0.2 | C28: 3
A29: 2 | B29: 0 | C29: 5.6
A30: 2.58 | B30: 0.2 | C30: 7.8
A31: 3.15 | B31: 0.2 | C31: 10
A32: 3.72 | B32: 0.6 | C32: 11.2
A33: 4.29 | B33: 1.4 | C33: 11
A34: 4.87 | B34: 2 | C34: 10.6
A35: 5.44 | B35: 3.2 | C35: 9.4
A36: 6.01 | B36: 4 | C36: 7.6
A37: 6.58 | B37: 5.6 | C37: 6.2
... A55: 16.89 | B55: 0.2 | C55: 0

Sheet MAPA DE CALOR
A1: MAPA DE CALOR - UBICACIÓN DE LOS RIESGOS EN LA MATRIZ P x I
A2: PROYECTO: MEJORAMIENTO DEL SERVICIO DE TRANSITABILIDAD VIAL INTERURBANA EN LA VÍA DEPARTAMENTAL SM-107, TRAMO TINGO DE PONASA - SHAMBOYACU, DISTRITO DE SHAMBOYACU, PROVINCIA DE PICOTA, DEPARTAMENTO DE SAN MARTÍN - CUI N.° 2673852
A4: INHERENTE (antes de la respuesta)
A5: PROBABILIDAD \ IMPACTO | B5: Muy bajo | C5: Bajo | D5: Moderado | E5: Alto | F5: Muy alto
A6: Muy alta | D6: R-01, R-25
A7: Alta | C7: R-05, R-06, R-11 | D7: R-10, R-16, R-17
A8: Moderada | B8: R-20, R-31 | C8: R-03, R-12, R-13, R-18, R-19, R-24, R-27, R-29 | D8: R-04, R-07, R-09, R-23 | E8: R-08, R-15
A9: Baja | B9: R-32 | C9: R-21, R-26, R-28, R-30, R-33 | D9: R-02, R-14, R-34
A10: Muy baja | C10: R-22
A13: RESIDUAL (con la respuesta ejecutada)
A14: PROBABILIDAD \ IMPACTO | B14: Muy bajo | C14: Bajo | D14: Moderado | E14: Alto | F14: Muy alto
A15: Muy alta
A16: Alta | D16: R-01, R-17
A17: Moderada | C17: R-05, R-06
A18: Baja | B18: R-20, R-31, R-32 | C18: R-03, R-11, R-12, R-13, R-18, R-19, R-24, R-27, R-29, R-30 | D18: R-02, R-04, R-07, R-10, R-16, R-23, R-25
A19: Muy baja | C19: R-21, R-22, R-26, R-28, R-33 | D19: R-09, R-14, R-34 | E19: R-08, R-15

Sheet PLAN DE RESPUESTA
A1: PLAN DE RESPUESTA A LOS RIESGOS
A2: PROYECTO: MEJORAMIENTO DEL SERVICIO DE TRANSITABILIDAD VIAL INTERURBANA EN LA VÍA DEPARTAMENTAL SM-107, TRAMO TINGO DE PONASA - SHAMBOYACU, DISTRITO DE SHAMBOYACU, PROVINCIA DE PICOTA, DEPARTAMENTO DE SAN MARTÍN - CUI N.° 2673852
A4: COD. | B4: RIESGO | C4: NIVEL INHERENTE | D4: ESTRATEGIA | E4: ACCIONES DE RESPUESTA | F4: RESPONSABLE | G4: PARTIDA O RECURSO | H4: MOMENTO | I4: ALERTA TEMPRANA (DISPARADOR) | J4: NIVEL RESIDUAL
A5: =IDENTIFICACION!A5 | B5: =IDENTIFICACION!C5 | C5: ='ANALISIS CUALITATIVO'!M5 | D5: Mitigar | E5: Cronograma valorizado con calendario climático: terraplenes, bases y carpeta en mayo-setiembre; drenaje provisional y bombeo; protección de capas terminadas; frentes alternos (alcantarillas, cunetas) en temporada de lluvias. | F5: Residente de obra / Supervisor | G5: Gastos generales del contratista; 1.04.02 Mantenimiento de tránsito temporal | H5: Ejecución (oct-abr) | I5: Pronóstico y avisos meteorológicos del SENAMHI; lluvia > 30 mm/día; dos días seguidos sin trabajo en un frente. | J5: ='ANALISIS CUALITATIVO'!Q5
A6: =IDENTIFICACION!A6 | B6: =IDENTIFICACION!C6 | C6: ='ANALISIS CUALITATIVO'!M6 | D6: Transferir / Mitigar | E6: Exigir póliza Todo Riesgo Construcción (CAR) con cobertura de eventos de la naturaleza; plan de contingencias por lluvias; registro en el cuaderno de obra y comunicación inmediata para la ampliación de plazo. | F6: Entidad (DRTC) / Supervisor | G6: Póliza CAR del contratista; reserva de contingencia de la Entidad | H6: Ejecución | I6: Comunicado oficial del ENFEN; nivel de agua en las quebradas sobre la marca de alerta. | J6: ='ANALISIS CUALITATIVO'!Q6
A7: =IDENTIFICACION!A7 | B7: =IDENTIFICACION!C7 | C7: ='ANALISIS CUALITATIVO'!M7 | D7: Mitigar | E7: Programar cimentaciones y estribos en estiaje (junio-setiembre); ataguías y bombeo; desvío del cauce antes de excavar; monitoreo diario del nivel de agua. | F7: Residente / Especialista en puentes | G7: 1.04.10 Desvío provisional de curso de agua; 1.10.0x.01.05 Encauzamiento de quebrada | H7: Ejecución de puentes | I7: Subida del nivel de la quebrada > 0.50 m en 24 h; lluvias en la cuenca alta. | J7: ='ANALISIS CUALITATIVO'!Q7
A8: =IDENTIFICACION!A8 | B8: =IDENTIFICACION!C8 | C8: ='ANALISIS CUALITATIVO'!M8 | D8: Mitigar | E8: Antes del inicio: verificar la estabilidad de cortes (factor de seguridad estático y seudoestático) y el diseño de muros en esos sectores; durante la obra: cortes por banquetas de arriba hacia abajo, drenaje de coronación, hitos de control de desplazamiento. | F8: Entidad (diseño) / Contratista (método de corte) | G8: 1.05.02 a 1.05.04 Cortes; 1.08.03 Muros de contención | H8: Antes del inicio y ejecución | I8: Grietas de tracción en la corona, surgencias de agua, desplazamiento de hitos > 2 cm. | J8: ='ANALISIS CUALITATIVO'!Q8
A9: =IDENTIFICACION!A9 | B9: =IDENTIFICACION!C9 | C9: ='ANALISIS CUALITATIVO'!M9 | D9: Mitigar | E9: Ejecutar primero los gaviones y la protección de pie en esos sectores; limpieza de alcantarillas y salidas antes del movimiento de tierras; protección temporal con geobolsas. | F9: Residente / Especialista en geotecnia | G9: 1.08.04 Muros de gavión; 1.05.08 Geobolsas | H9: Ejecución | I9: Pérdida de material en el borde después de cada lluvia; socavación > 0.30 m al pie. | J9: ='ANALISIS CUALITATIVO'!Q9
A10: =IDENTIFICACION!A10 | B10: =IDENTIFICACION!C10 | C10: ='ANALISIS CUALITATIVO'!M10 | D10: Mitigar | E10: Acordar con la junta y comisiones de usuarios de riego los turnos y cortes de agua en los frentes; subdrenaje y geotextil; construir primero las alcantarillas de alivio proyectadas. | F10: Entidad (coordinación) / Contratista (ejecución) | G10: 1.05.06 Mejoramiento de suelos; 1.05.09 Geotextil; 1.05.11 a 1.05.13 Subdrenaje | H10: Ejecución | I10: Lámina de agua en los arrozales colindantes; humedad de la subrasante sobre la óptima + 2 %. | J10: ='ANALISIS CUALITATIVO'!Q10
A11: =IDENTIFICACION!A11 | B11: =IDENTIFICACION!C11 | C11: ='ANALISIS CUALITATIVO'!M11 | D11: Mitigar | E11: Completar calicatas y ensayos CBR cada 500 m antes de la convocatoria; definir criterios de reemplazo en el expediente. | F11: Entidad (expediente) / Supervisor | G11: 1.05.06 Mejoramiento de suelos; 1.05.07 Geomalla | H11: Antes de la convocatoria | I11: CBR de campo menor al de diseño en dos sectores consecutivos. | J11: ='ANALISIS CUALITATIVO'!Q11
A12: =IDENTIFICACION!A12 | B12: =IDENTIFICACION!C12 | C12: ='ANALISIS CUALITATIVO'!M12 | D12: Evitar | E12: Antes de convocar: ensayos de calidad y cálculo de potencia, autorización de la municipalidad y de la ANA para extracción en cauce, y una cantera alternativa con su distancia. | F12: Entidad (DRTC) | G12: 1.04.07, 1.04.08 Cantera; 1.07 Transporte | H12: Antes de la convocatoria | I12: Potencia útil menor al 120 % del volumen requerido; observación de la autoridad. | J12: ='ANALISIS CUALITATIVO'!Q12
A13: =IDENTIFICACION!A13 | B13: =IDENTIFICACION!C13 | C13: ='ANALISIS CUALITATIVO'!M13 | D13: Evitar | E13: Tramitar las autorizaciones antes del inicio de obra y entregarlas al contratista con el expediente. | F13: Entidad (DRTC) | G13: — | H13: Antes del inicio | I13: Autorización no emitida 30 días antes del inicio. | J13: ='ANALISIS CUALITATIVO'!Q13
A14: =IDENTIFICACION!A14 | B14: =IDENTIFICACION!C14 | C14: ='ANALISIS CUALITATIVO'!M14 | D14: Evitar | E14: Catastro de afectaciones por progresiva; actas de libre disponibilidad firmadas; evaluar el PACRI y el saneamiento físico-legal (Ley N.° 30025) antes de la convocatoria. | F14: Entidad (DRTC) / Municipalidades | G14: Fuera del presupuesto de obra (gestión de la Entidad) | H14: Antes de la convocatoria | I14: Predio sin acta a 60 días de su frente de trabajo. | J14: ='ANALISIS CUALITATIVO'!Q14
A15: =IDENTIFICACION!A15 | B15: =IDENTIFICACION!C15 | C15: ='ANALISIS CUALITATIVO'!M15 | D15: Mitigar | E15: Factibilidad y presupuesto aprobados por la concesionaria eléctrica y las JASS o EPS antes del inicio; cronograma de cortes programados. | F15: Entidad / Contratista | G15: 1.04.12 Reubicación de postes | H15: Antes del inicio | I15: Concesionaria sin respuesta a 30 días. | J15: ='ANALISIS CUALITATIVO'!Q15
A16: =IDENTIFICACION!A16 | B16: =IDENTIFICACION!C16 | C16: ='ANALISIS CUALITATIVO'!M16 | D16: Mitigar | E16: Plan de trabajo con la comisión de regantes; ejecutar cada cruce fuera de la campaña de riego o con derivación temporal. | F16: Entidad (relacionamiento) / Contratista | G16: 1.08.01 Alcantarillas TMC; 1.11.08 Plan de gestión social | H16: Ejecución | I16: Queja formal de la comisión de regantes; caudal cortado > 24 h. | J16: ='ANALISIS CUALITATIVO'!Q16
... A38: =IDENTIFICACION!A38 | B38: =IDENTIFICACION!C38 | C38: ='ANALISIS CUALITATIVO'!M38 | D38: Evitar | E38: Verificar por puente el estudio hidrológico, hidráulico, de socavación y geotécnico (Manual de Puentes del MTC) antes de convocar. | F38: Entidad / Proyectista | G38: 1.10 Puentes | H38: Antes de la convocatoria | I38: Perforación con estrato de apoyo más profundo que el de diseño. | J38: ='ANALISIS CUALITATIVO'!Q38

Sheet ASIGNACION
A1: ASIGNACIÓN DE RIESGOS ENTRE LAS PARTES
A2: PROYECTO: MEJORAMIENTO DEL SERVICIO DE TRANSITABILIDAD VIAL INTERURBANA EN LA VÍA DEPARTAMENTAL SM-107, TRAMO TINGO DE PONASA - SHAMBOYACU, DISTRITO DE SHAMBOYACU, PROVINCIA DE PICOTA, DEPARTAMENTO DE SAN MARTÍN - CUI N.° 2673852
A4: COD. | B4: RIESGO | C4: ASIGNADO A | D4: CRITERIO (se asigna a la parte que mejor puede gestionarlo y mitigarlo)
A5: =IDENTIFICACION!A5 | B5: =IDENTIFICACION!C5 | C5: ='ANALISIS CUANTITATIVO'!C5 | D5: Depende de la planificación, los métodos, los recursos y la seguridad de la obra, que controla el contratista; se cubre con sus gastos generales, sus pólizas y su programación.
A6: =IDENTIFICACION!A6 | B6: =IDENTIFICACION!C6 | C6: ='ANALISIS CUANTITATIVO'!C6 | D6: Depende de decisiones, permisos, predios, financiamiento o del contenido del expediente técnico, que controla la Entidad; si ocurre, procede la modificación contractual o la ampliación de plazo.
A7: =IDENTIFICACION!A7 | B7: =IDENTIFICACION!C7 | C7: ='ANALISIS CUANTITATIVO'!C7 | D7: Depende de la planificación, los métodos, los recursos y la seguridad de la obra, que controla el contratista; se cubre con sus gastos generales, sus pólizas y su programación.
A8: =IDENTIFICACION!A8 | B8: =IDENTIFICACION!C8 | C8: ='ANALISIS CUANTITATIVO'!C8 | D8: La causa tiene una parte de diseño o gestión de la Entidad y otra de ejecución del contratista; se reparte según la causa que se compruebe en obra (en el análisis se toma 50 %).
A9: =IDENTIFICACION!A9 | B9: =IDENTIFICACION!C9 | C9: ='ANALISIS CUANTITATIVO'!C9 | D9: Depende de la planificación, los métodos, los recursos y la seguridad de la obra, que controla el contratista; se cubre con sus gastos generales, sus pólizas y su programación.
A10: =IDENTIFICACION!A10 | B10: =IDENTIFICACION!C10 | C10: ='ANALISIS CUANTITATIVO'!C10 | D10: La causa tiene una parte de diseño o gestión de la Entidad y otra de ejecución del contratista; se reparte según la causa que se compruebe en obra (en el análisis se toma 50 %).
A11: =IDENTIFICACION!A11 | B11: =IDENTIFICACION!C11 | C11: ='ANALISIS CUANTITATIVO'!C11 | D11: Depende de decisiones, permisos, predios, financiamiento o del contenido del expediente técnico, que controla la Entidad; si ocurre, procede la modificación contractual o la ampliación de plazo.
A12: =IDENTIFICACION!A12 | B12: =IDENTIFICACION!C12 | C12: ='ANALISIS CUANTITATIVO'!C12 | D12: Depende de decisiones, permisos, predios, financiamiento o del contenido del expediente técnico, que controla la Entidad; si ocurre, procede la modificación contractual o la ampliación de plazo.
A13: =IDENTIFICACION!A13 | B13: =IDENTIFICACION!C13 | C13: ='ANALISIS CUANTITATIVO'!C13 | D13: Depende de decisiones, permisos, predios, financiamiento o del contenido del expediente técnico, que controla la Entidad; si ocurre, procede la modificación contractual o la ampliación de plazo.
A14: =IDENTIFICACION!A14 | B14: =IDENTIFICACION!C14 | C14: ='ANALISIS CUANTITATIVO'!C14 | D14: Depende de decisiones, permisos, predios, financiamiento o del contenido del expediente técnico, que controla la Entidad; si ocurre, procede la modificación contractual o la ampliación de plazo.
A15: =IDENTIFICACION!A15 | B15: =IDENTIFICACION!C15 | C15: ='ANALISIS CUANTITATIVO'!C15 | D15: Depende de decisiones, permisos, predios, financiamiento o del contenido del expediente técnico, que controla la Entidad; si ocurre, procede la modificación contractual o la ampliación de plazo.
A16: =IDENTIFICACION!A16 | B16: =IDENTIFICACION!C16 | C16: ='ANALISIS CUANTITATIVO'!C16 | D16: La causa tiene una parte de diseño o gestión de la Entidad y otra de ejecución del contratista; se reparte según la causa que se compruebe en obra (en el análisis se toma 50 %).
... A38: =IDENTIFICACION!A38 | B38: =IDENTIFICACION!C38 | C38: ='ANALISIS CUANTITATIVO'!C38 | D38: Depende de decisiones, permisos, predios, financiamiento o del contenido del expediente técnico, que controla la Entidad; si ocurre, procede la modificación contractual o la ampliación de plazo.
B40: Riesgos asignados a: Entidad | C40: =COUNTIF(C5:C38,"Entidad")
B41: Riesgos asignados a: Contratista | C41: =COUNTIF(C5:C38,"Contratista")
B42: Riesgos asignados a: Compartido | C42: =COUNTIF(C5:C38,"Compartido")

Sheet OPORTUNIDADES
A1: OPORTUNIDADES
A2: PROYECTO: MEJORAMIENTO DEL SERVICIO DE TRANSITABILIDAD VIAL INTERURBANA EN LA VÍA DEPARTAMENTAL SM-107, TRAMO TINGO DE PONASA - SHAMBOYACU, DISTRITO DE SHAMBOYACU, PROVINCIA DE PICOTA, DEPARTAMENTO DE SAN MARTÍN - CUI N.° 2673852
A4: COD. | B4: OPORTUNIDAD | C4: CAUSA | D4: PROBABILIDAD | E4: P | F4: AHORRO MÍN. (%) | G4: AHORRO MÁS PROB. (%) | H4: AHORRO MÁX. (%) | I4: VALOR ESPERADO (%) | J4: ESTRATEGIA | K4: ACCIONES | L4: RESPONSABLE
A5: O-01 | B5: Aprovechar el material de corte como relleno de terraplén | C5: 47,772 m³ de corte en material suelto y 3,337 m³ en roca. | D5: Moderada | E5: =VLOOKUP(D5,ESCALAS!$A$5:$B$9,2,FALSE) | F5: 0.0817 | G5: 0.2451 | H5: 0.572 | I5: =E5*AVERAGE(F5:H5) | J5: Explotar | K5: Clasificar el material de corte y usar el apto en terraplenes; reduce préstamo y transporte. | L5: Contratista / Supervisor
A6: O-02 | B6: Concentrar puentes, terraplenes y carpeta en el estiaje | C6: Las lluvias bajan en junio-agosto. | D6: Alta | E6: =VLOOKUP(D6,ESCALAS!$A$5:$B$9,2,FALSE) | F6: 0 | G6: 0 | H6: 0 | I6: =E6*AVERAGE(F6:H6) | J6: Mejorar | K6: Cronograma con hitos de estiaje y frentes paralelos; reduce la exposición a R-01 y R-03. | L6: Contratista / Entidad
A7: O-03 | B7: Compra anticipada de cemento asfáltico y alcantarillas TMC | C7: Precios volátiles y plazos de entrega largos. | D7: Baja | E7: =VLOOKUP(D7,ESCALAS!$A$5:$B$9,2,FALSE) | F7: 0.0409 | G7: 0.1226 | H7: 0.3269 | I7: =E7*AVERAGE(F7:H7) | J7: Mejorar | K7: Contratos de suministro al inicio de obra con entregas programadas. | L7: Contratista

Sheet SEGUIMIENTO
A1: FORMATO DE SEGUIMIENTO MENSUAL DE RIESGOS (COMITÉ DE GESTIÓN DE RIESGOS)
A2: PROYECTO: MEJORAMIENTO DEL SERVICIO DE TRANSITABILIDAD VIAL INTERURBANA EN LA VÍA DEPARTAMENTAL SM-107, TRAMO TINGO DE PONASA - SHAMBOYACU, DISTRITO DE SHAMBOYACU, PROVINCIA DE PICOTA, DEPARTAMENTO DE SAN MARTÍN - CUI N.° 2673852
A3: Mes de obra: ______ Fecha de revisión: ____/____/______ Valorización N.°: ______
A5: COD. | B5: RIESGO | C5: ESTADO | D5: PROBABILIDAD ACTUAL | E5: IMPACTO ACTUAL | F5: NIVEL ACTUAL | G5: ¿ALERTA ACTIVADA? | H5: ACCIÓN EJECUTADA / PENDIENTE | I5: RESPONSABLE | J5: COMENTARIOS
A6: R-01 | B6: Lluvias estacionales intensas (octubre a abril) que paralizan el movimiento de tierras, la pavimentación y los vaciados | C6: Activo | F6: =IF(OR(D6="",E6=""),"",IF(VLOOKUP(D6,ESCALAS!$A$5:$B$9,2,FALSE)*VLOOKUP(E6,ESCALAS!$A$12:$B$16,2,FALSE)>=ESCALAS!$B$20,"ALTO",IF(VLOOKUP(D6,ESCALAS!$A$5:$B$9,2,FALSE)*VLOOKUP(E6,ESCALAS!$A$12:$B$16,2,FALSE)>=ESCALAS!$B$21,"MODERADO","BAJO"))) | I6: Residente de obra / Supervisor
A7: R-02 | B7: Lluvias extraordinarias o anomalías climáticas (El Niño / La Niña) con desborde de quebradas y daños a la obra ejecutada | C7: Activo | F7: =IF(OR(D7="",E7=""),"",IF(VLOOKUP(D7,ESCALAS!$A$5:$B$9,2,FALSE)*VLOOKUP(E7,ESCALAS!$A$12:$B$16,2,FALSE)>=ESCALAS!$B$20,"ALTO",IF(VLOOKUP(D7,ESCALAS!$A$5:$B$9,2,FALSE)*VLOOKUP(E7,ESCALAS!$A$12:$B$16,2,FALSE)>=ESCALAS!$B$21,"MODERADO","BAJO"))) | I7: Entidad (DRTC) / Supervisor
A8: R-03 | B8: Crecidas de quebradas durante la construcción de estribos de los 5 puentes | C8: Activo | F8: =IF(OR(D8="",E8=""),"",IF(VLOOKUP(D8,ESCALAS!$A$5:$B$9,2,FALSE)*VLOOKUP(E8,ESCALAS!$A$12:$B$16,2,FALSE)>=ESCALAS!$B$20,"ALTO",IF(VLOOKUP(D8,ESCALAS!$A$5:$B$9,2,FALSE)*VLOOKUP(E8,ESCALAS!$A$12:$B$16,2,FALSE)>=ESCALAS!$B$21,"MODERADO","BAJO"))) | I8: Residente / Especialista en puentes
A9: R-04 | B9: Inestabilidad de taludes y deslizamientos durante los cortes en ladera | C9: Activo | F9: =IF(OR(D9="",E9=""),"",IF(VLOOKUP(D9,ESCALAS!$A$5:$B$9,2,FALSE)*VLOOKUP(E9,ESCALAS!$A$12:$B$16,2,FALSE)>=ESCALAS!$B$20,"ALTO",IF(VLOOKUP(D9,ESCALAS!$A$5:$B$9,2,FALSE)*VLOOKUP(E9,ESCALAS!$A$12:$B$16,2,FALSE)>=ESCALAS!$B$21,"MODERADO","BAJO"))) | I9: Entidad (diseño) / Contratista (método de corte)
A10: R-05 | B10: Erosión y socavación de la plataforma y de los terraplenes en construcción | C10: Activo | F10: =IF(OR(D10="",E10=""),"",IF(VLOOKUP(D10,ESCALAS!$A$5:$B$9,2,FALSE)*VLOOKUP(E10,ESCALAS!$A$12:$B$16,2,FALSE)>=ESCALAS!$B$20,"ALTO",IF(VLOOKUP(D10,ESCALAS!$A$5:$B$9,2,FALSE)*VLOOKUP(E10,ESCALAS!$A$12:$B$16,2,FALSE)>=ESCALAS!$B$21,"MODERADO","BAJO"))) | I10: Residente / Especialista en geotecnia
A11: R-06 | B11: Saturación de terraplenes por inundación de arrozales, canales de riego y empozamientos | C11: Activo | F11: =IF(OR(D11="",E11=""),"",IF(VLOOKUP(D11,ESCALAS!$A$5:$B$9,2,FALSE)*VLOOKUP(E11,ESCALAS!$A$12:$B$16,2,FALSE)>=ESCALAS!$B$20,"ALTO",IF(VLOOKUP(D11,ESCALAS!$A$5:$B$9,2,FALSE)*VLOOKUP(E11,ESCALAS!$A$12:$B$16,2,FALSE)>=ESCALAS!$B$21,"MODERADO","BAJO"))) | I11: Entidad (coordinación) / Contratista (ejecución)
A12: R-07 | B12: Subrasante de menor capacidad de soporte que la prevista en el expediente | C12: Activo | F12: =IF(OR(D12="",E12=""),"",IF(VLOOKUP(D12,ESCALAS!$A$5:$B$9,2,FALSE)*VLOOKUP(E12,ESCALAS!$A$12:$B$16,2,FALSE)>=ESCALAS!$B$20,"ALTO",IF(VLOOKUP(D12,ESCALAS!$A$5:$B$9,2,FALSE)*VLOOKUP(E12,ESCALAS!$A$12:$B$16,2,FALSE)>=ESCALAS!$B$21,"MODERADO","BAJO"))) | I12: Entidad (expediente) / Supervisor
A13: R-08 | B13: Cantera insuficiente, sin calidad o sin autorización, con mayor distancia de transporte | C13: Activo | F13: =IF(OR(D13="",E13=""),"",IF(VLOOKUP(D13,ESCALAS!$A$5:$B$9,2,FALSE)*VLOOKUP(E13,ESCALAS!$A$12:$B$16,2,FALSE)>=ESCALAS!$B$20,"ALTO",IF(VLOOKUP(D13,ESCALAS!$A$5:$B$9,2,FALSE)*VLOOKUP(E13,ESCALAS!$A$12:$B$16,2,FALSE)>=ESCALAS!$B$21,"MODERADO","BAJO"))) | I13: Entidad (DRTC)
A14: R-09 | B14: Demora en autorizaciones de uso de agua y de extracción de material de cauce | C14: Activo | F14: =IF(OR(D14="",E14=""),"",IF(VLOOKUP(D14,ESCALAS!$A$5:$B$9,2,FALSE)*VLOOKUP(E14,ESCALAS!$A$12:$B$16,2,FALSE)>=ESCALAS!$B$20,"ALTO",IF(VLOOKUP(D14,ESCALAS!$A$5:$B$9,2,FALSE)*VLOOKUP(E14,ESCALAS!$A$12:$B$16,2,FALSE)>=ESCALAS!$B$21,"MODERADO","BAJO"))) | I14: Entidad (DRTC)
A15: R-10 | B15: Falta de libre disponibilidad del terreno para el ensanche de la plataforma | C15: Activo | F15: =IF(OR(D15="",E15=""),"",IF(VLOOKUP(D15,ESCALAS!$A$5:$B$9,2,FALSE)*VLOOKUP(E15,ESCALAS!$A$12:$B$16,2,FALSE)>=ESCALAS!$B$20,"ALTO",IF(VLOOKUP(D15,ESCALAS!$A$5:$B$9,2,FALSE)*VLOOKUP(E15,ESCALAS!$A$12:$B$16,2,FALSE)>=ESCALAS!$B$21,"MODERADO","BAJO"))) | I15: Entidad (DRTC) / Municipalidades
A16: R-11 | B16: Interferencias con redes eléctricas, de agua potable y de telecomunicaciones | C16: Activo | F16: =IF(OR(D16="",E16=""),"",IF(VLOOKUP(D16,ESCALAS!$A$5:$B$9,2,FALSE)*VLOOKUP(E16,ESCALAS!$A$12:$B$16,2,FALSE)>=ESCALAS!$B$20,"ALTO",IF(VLOOKUP(D16,ESCALAS!$A$5:$B$9,2,FALSE)*VLOOKUP(E16,ESCALAS!$A$12:$B$16,2,FALSE)>=ESCALAS!$B$21,"MODERADO","BAJO"))) | I16: Entidad / Contratista
A17: R-12 | B17: Afectación de canales y cruces de riego con reclamos de los agricultores | C17: Activo | F17: =IF(OR(D17="",E17=""),"",IF(VLOOKUP(D17,ESCALAS!$A$5:$B$9,2,FALSE)*VLOOKUP(E17,ESCALAS!$A$12:$B$16,2,FALSE)>=ESCALAS!$B$20,"ALTO",IF(VLOOKUP(D17,ESCALAS!$A$5:$B$9,2,FALSE)*VLOOKUP(E17,ESCALAS!$A$12:$B$16,2,FALSE)>=ESCALAS!$B$21,"MODERADO","BAJO"))) | I17: Entidad (relacionamiento) / Contratista
... A39: R-34 | B39: Cambio de diseño de puentes por condiciones de cauce, socavación o cimentación distintas | C39: Activo | F39: =IF(OR(D39="",E39=""),"",IF(VLOOKUP(D39,ESCALAS!$A$5:$B$9,2,FALSE)*VLOOKUP(E39,ESCALAS!$A$12:$B$16,2,FALSE)>=ESCALAS!$B$20,"ALTO",IF(VLOOKUP(D39,ESCALAS!$A$5:$B$9,2,FALSE)*VLOOKUP(E39,ESCALAS!$A$12:$B$16,2,FALSE)>=ESCALAS!$B$21,"MODERADO","BAJO"))) | I39: Entidad / Proyectista
A40: R-35 | C40: Nuevo
A41: R-36 | C41: Nuevo
A42: R-37 | C42: Nuevo
A43: R-38 | C43: Nuevo
A44: R-39 | C44: Nuevo

Sheet CALENDARIO
A1: LLUVIA MENSUAL DE REFERENCIA Y PROGRAMACIÓN RECOMENDADA
A2: PROYECTO: MEJORAMIENTO DEL SERVICIO DE TRANSITABILIDAD VIAL INTERURBANA EN LA VÍA DEPARTAMENTAL SM-107, TRAMO TINGO DE PONASA - SHAMBOYACU, DISTRITO DE SHAMBOYACU, PROVINCIA DE PICOTA, DEPARTAMENTO DE SAN MARTÍN - CUI N.° 2673852
A3: Fuente: NOAA GHCN-Daily, estaciones TARAPOTO (PE000084455, 282 msnm, 1973-2005) y JUANJUI (PEM00084474, 350 msnm, 1973-1994); meses con al menos 90 % de datos. El tramo está entre ambas estaciones (56 y 60 km). Series cortas: usar el estudio hidrológico del expediente para el diseño.
A5: MES | B5: TARAPOTO (mm) | C5: JUANJUÍ (mm) | D5: PROMEDIO (mm) | E5: DÍAS >= 10 mm (prom.) | F5: TEMPORADA | G5: PROGRAMACIÓN RECOMENDADA
A6: Enero | B6: 71.5 | C6: 108.1 | D6: =AVERAGE(B6:C6) | E6: 2.6 | F6: =IF(D6>=110,"LLUVIOSA",IF(D6>=75,"TRANSICIÓN","ESTIAJE")) | G6: =IF(F6="LLUVIOSA","Alcantarillas, cunetas, gaviones, fabricación de vigas, campamento; evitar terraplenes en zonas de arrozal y cimentación de puentes",IF(F6="TRANSICIÓN","Cortes con drenaje de coronación, subbase y base con protección; preparar desvíos de cauce","Cimentación y estribos de puentes, terraplenes en zonas bajas, base y carpeta asfáltica"))
A7: Febrero | B7: 95.6 | C7: 60 | D7: =AVERAGE(B7:C7) | E7: 2.9 | F7: =IF(D7>=110,"LLUVIOSA",IF(D7>=75,"TRANSICIÓN","ESTIAJE")) | G7: =IF(F7="LLUVIOSA","Alcantarillas, cunetas, gaviones, fabricación de vigas, campamento; evitar terraplenes en zonas de arrozal y cimentación de puentes",IF(F7="TRANSICIÓN","Cortes con drenaje de coronación, subbase y base con protección; preparar desvíos de cauce","Cimentación y estribos de puentes, terraplenes en zonas bajas, base y carpeta asfáltica"))
A8: Marzo | B8: 153.3 | C8: 238.9 | D8: =AVERAGE(B8:C8) | E8: 5.2 | F8: =IF(D8>=110,"LLUVIOSA",IF(D8>=75,"TRANSICIÓN","ESTIAJE")) | G8: =IF(F8="LLUVIOSA","Alcantarillas, cunetas, gaviones, fabricación de vigas, campamento; evitar terraplenes en zonas de arrozal y cimentación de puentes",IF(F8="TRANSICIÓN","Cortes con drenaje de coronación, subbase y base con protección; preparar desvíos de cauce","Cimentación y estribos de puentes, terraplenes en zonas bajas, base y carpeta asfáltica"))
A9: Abril | B9: 86.3 | C9: 162.1 | D9: =AVERAGE(B9:C9) | E9: 3.3 | F9: =IF(D9>=110,"LLUVIOSA",IF(D9>=75,"TRANSICIÓN","ESTIAJE")) | G9: =IF(F9="LLUVIOSA","Alcantarillas, cunetas, gaviones, fabricación de vigas, campamento; evitar terraplenes en zonas de arrozal y cimentación de puentes",IF(F9="TRANSICIÓN","Cortes con drenaje de coronación, subbase y base con protección; preparar desvíos de cauce","Cimentación y estribos de puentes, terraplenes en zonas bajas, base y carpeta asfáltica"))
A10: Mayo | B10: 65.7 | C10: 145 | D10: =AVERAGE(B10:C10) | E10: 2.6 | F10: =IF(D10>=110,"LLUVIOSA",IF(D10>=75,"TRANSICIÓN","ESTIAJE")) | G10: =IF(F10="LLUVIOSA","Alcantarillas, cunetas, gaviones, fabricación de vigas, campamento; evitar terraplenes en zonas de arrozal y cimentación de puentes",IF(F10="TRANSICIÓN","Cortes con drenaje de coronación, subbase y base con protección; preparar desvíos de cauce","Cimentación y estribos de puentes, terraplenes en zonas bajas, base y carpeta asfáltica"))
A11: Junio | B11: 92.9 | C11: 113.2 | D11: =AVERAGE(B11:C11) | E11: 2.5 | F11: =IF(D11>=110,"LLUVIOSA",IF(D11>=75,"TRANSICIÓN","ESTIAJE")) | G11: =IF(F11="LLUVIOSA","Alcantarillas, cunetas, gaviones, fabricación de vigas, campamento; evitar terraplenes en zonas de arrozal y cimentación de puentes",IF(F11="TRANSICIÓN","Cortes con drenaje de coronación, subbase y base con protección; preparar desvíos de cauce","Cimentación y estribos de puentes, terraplenes en zonas bajas, base y carpeta asfáltica"))
A12: Julio | B12: 29.8 | C12: 82.3 | D12: =AVERAGE(B12:C12) | E12: 1.5 | F12: =IF(D12>=110,"LLUVIOSA",IF(D12>=75,"TRANSICIÓN","ESTIAJE")) | G12: =IF(F12="LLUVIOSA","Alcantarillas, cunetas, gaviones, fabricación de vigas, campamento; evitar terraplenes en zonas de arrozal y cimentación de puentes",IF(F12="TRANSICIÓN","Cortes con drenaje de coronación, subbase y base con protección; preparar desvíos de cauce","Cimentación y estribos de puentes, terraplenes en zonas bajas, base y carpeta asfáltica"))
A13: Agosto | B13: 74.7 | C13: 41.7 | D13: =AVERAGE(B13:C13) | E13: 1.8 | F13: =IF(D13>=110,"LLUVIOSA",IF(D13>=75,"TRANSICIÓN","ESTIAJE")) | G13: =IF(F13="LLUVIOSA","Alcantarillas, cunetas, gaviones, fabricación de vigas, campamento; evitar terraplenes en zonas de arrozal y cimentación de puentes",IF(F13="TRANSICIÓN","Cortes con drenaje de coronación, subbase y base con protección; preparar desvíos de cauce","Cimentación y estribos de puentes, terraplenes en zonas bajas, base y carpeta asfáltica"))
A14: Setiembre | B14: 74.1 | C14: 62.2 | D14: =AVERAGE(B14:C14) | E14: 2.3 | F14: =IF(D14>=110,"LLUVIOSA",IF(D14>=75,"TRANSICIÓN","ESTIAJE")) | G14: =IF(F14="LLUVIOSA","Alcantarillas, cunetas, gaviones, fabricación de vigas, campamento; evitar terraplenes en zonas de arrozal y cimentación de puentes",IF(F14="TRANSICIÓN","Cortes con drenaje de coronación, subbase y base con protección; preparar desvíos de cauce","Cimentación y estribos de puentes, terraplenes en zonas bajas, base y carpeta asfáltica"))
A15: Octubre | B15: 90.6 | C15: 161.5 | D15: =AVERAGE(B15:C15) | E15: 3.8 | F15: =IF(D15>=110,"LLUVIOSA",IF(D15>=75,"TRANSICIÓN","ESTIAJE")) | G15: =IF(F15="LLUVIOSA","Alcantarillas, cunetas, gaviones, fabricación de vigas, campamento; evitar terraplenes en zonas de arrozal y cimentación de puentes",IF(F15="TRANSICIÓN","Cortes con drenaje de coronación, subbase y base con protección; preparar desvíos de cauce","Cimentación y estribos de puentes, terraplenes en zonas bajas, base y carpeta asfáltica"))
A16: Noviembre | B16: 94.4 | C16: 177.1 | D16: =AVERAGE(B16:C16) | E16: 3.9 | F16: =IF(D16>=110,"LLUVIOSA",IF(D16>=75,"TRANSICIÓN","ESTIAJE")) | G16: =IF(F16="LLUVIOSA","Alcantarillas, cunetas, gaviones, fabricación de vigas, campamento; evitar terraplenes en zonas de arrozal y cimentación de puentes",IF(F16="TRANSICIÓN","Cortes con drenaje de coronación, subbase y base con protección; preparar desvíos de cauce","Cimentación y estribos de puentes, terraplenes en zonas bajas, base y carpeta asfáltica"))
A17: Diciembre | B17: 91.2 | C17: 119 | D17: =AVERAGE(B17:C17) | E17: 3 | F17: =IF(D17>=110,"LLUVIOSA",IF(D17>=75,"TRANSICIÓN","ESTIAJE")) | G17: =IF(F17="LLUVIOSA","Alcantarillas, cunetas, gaviones, fabricación de vigas, campamento; evitar terraplenes en zonas de arrozal y cimentación de puentes",IF(F17="TRANSICIÓN","Cortes con drenaje de coronación, subbase y base con protección; preparar desvíos de cauce","Cimentación y estribos de puentes, terraplenes en zonas bajas, base y carpeta asfáltica"))
A18: ANUAL | B18: =SUM(B6:B17) | C18: =SUM(C6:C17) | D18: =SUM(D6:D17)
