Workbook

Sheet MEMORIA
A1: MEMORIA DE CALCULO - COLECTOR PLUVIAL TRAMO HOGAR DE REFUGIO TEMPORAL MUJERES VIOLENTADAS
A2: Colector pluvial frontal - tramo Hogar de Refugio Temporal Mujeres Violentadas (CUI 2675514), Morales - San Martin. Hidroconsult, Oct. 2026
A4: 1. OBJETO | B4: Dimensionar el tramo del colector pluvial frontal que recibe el aporte del CAR Varones (CUI 2705619, dato de su memoria) y las seis cunetas del Hogar de Refugio Temporal Mujeres Violentadas (CUI 2675514), y lo entrega al registro R-01 del colector del CAR Mujeres (CUI 2717013). Longitud 73.39 m, de la caja de llegada (0+000, limite con CAR Varones) a la caja de caida en el limite con CAR Mujeres.
A5: 2. NORMATIVA | B5: RNE CE.040 Drenaje Pluvial (RM 126-2021-VIVIENDA); RNE E.020 Cargas; RNE E.060 Concreto Armado; AASHTO LRFD (rueda HL-93 en el cruce de camiones); Chow, Hidraulica de canales abiertos (paso estandar).
A6: 3. HIDROLOGIA | B6: Metodo Racional con los coeficientes y areas de las memorias HIDRO-CE040 de cada proyecto, TR = 25 anos, tc = 15 min, I = 155.66 mm/h, FS = 1.15. Q = 258.7 + 301.9 = 560.6 L/s.
A7: 4. HIDRAULICA | B7: Colector cubierto de concreto armado b = 0.80 m, S = 0.30 %, n = 0.015. El fondo inicial (259.10) queda bajo las cunetas de arquitectura (NCF 259.70 a 260.12) y el fondo final (258.89) sobre el R-01 del receptor (258.72). La entrega es por caja de caida con poza de disipacion deprimida 0.40 m, ahogada por el tirante del receptor; el control del perfil es el tirante critico en el brink y el flujo en el colector es subcritico (F <= 0.90). El aporte externo cae en una caja de llegada con colchon de agua.
A8: 5. ESTRUCTURAS | B8: Marco cerrado monolitico: losa superior e = 0.10, muros e = 0.15 (altura interior 1.40 a 1.65 m) y losa de fondo e = 0.15 con un solo marco 3/8" @0.20 en el eje de la seccion y longitudinales 3/8" @0.25 (una capa; E.060 14.3.4); cruce de motos marco 3/8" @0.15; cruce de camiones losas e = 0.25 y doble marco 1/2" @0.15 (una capa en cada cara). Tapas de registro 0.68 x 0.68 x 0.08.
A9: 6. RESULTADOS | B9: Ver cuadro resumen y la hoja CUMPLIMIENTO (requisito, norma, criterio, valor y resultado). Secciones, acero y detalles en las laminas DP-01 a DP-10 y DA-01 a DA-03.
A11: Caudal de diseno del tramo (L/s) | B11: =CAUDALES!B12
A12: Intensidad de diseno (mm/h) | B12: =DATOS!B11
A13: Ancho interior adoptado (m) | B13: =DATOS!B17
A14: Pendiente del fondo (%) | B14: =DATOS!B23*100
A15: Cota de fondo inicial / final del colector (msnm) | B15: =TEXT(DATOS!B22,"0.00")&" / "&TEXT(EMPALME!B8,"0.00")
A16: Llenado maximo y/h | B16: =PERFIL_FLUJO!B93
A17: Borde libre minimo bajo losa (m) | B17: =PERFIL_FLUJO!B94
A18: Froude maximo en el colector | B18: =PERFIL_FLUJO!B95
A19: Estaciones hidraulicas que no cumplen | B19: =PERFIL_FLUJO!B96
A20: Velocidades y autolimpieza (0.90 a 3.0 m/s; tau >= 0.15 kg/m2) | B20: =PERFIL_FLUJO!B200
A21: Cunetas con caida libre al colector (de 6) | B21: =COUNTIF(CUNETAS!L5:L10,"CAIDA LIBRE")
A22: Resalto en la poza de la caja de caida | B22: =EMPALME!B19
A23: Elementos estructurales que no cumplen | B23: =COUNTIF(ESTRUCTURAL!E:E,"NO CUMPLE")
A24: Requisitos normativos que no cumplen o por verificar (hoja CUMPLIMIENTO) | B24: =COUNTIF(CUMPLIMIENTO!E:E,"NO CUMPLE*")+COUNTIF(CUMPLIMIENTO!E:E,"VERIFICAR*")
A26: NOTAS
B27: La llegada del CAR Varones (CUI 2705619) queda definida por su expediente: colector b = 0.60 con fondo 259.884 en la cara este de la CL y cuneta Eje 01 directa a la CL; la CL lleva su tapa en +261.15 (piso de Varones) y ventanas este 0.60 x 1.17 y norte 0.40 x 0.66.
B28: La ubicacion UTM es referencial: el plano de arquitectura se georreferencio haciendo coincidir el R-01 del CAR Mujeres con la esquina sur-oeste del frente y el rumbo del lindero (azimut 49.54). Verificar en campo.
B29: Las cunetas de arquitectura se toman como dato (perfiles 01 a 12 del plano PLANTA GENERAL REFUGIO, version 03-10-2026).

Sheet DATOS
A1: 1. DATOS DE DISENO
A2: Colector pluvial frontal - tramo Hogar de Refugio Temporal Mujeres Violentadas (CUI 2675514), Morales - San Martin. Hidroconsult, Oct. 2026
A4: PARAMETRO | B4: VALOR | C4: UND | D4: FUENTE / CRITERIO | E4: SIMBOLO
A5: HIDROLOGIA
A6: Periodo de retorno | B6: 25 | C6: anos | D6: Analisis estadistico de precipitaciones (memoria HIDRO-CE040 del proyecto) | E6: TR
A7: Precipitacion de diseno D=10 min | B7: 35.163 | C7: mm | D7: Dick-Peschke, P24 = 121.81 mm | E7: P10
A8: Precipitacion de diseno D=20 min | B8: 41.816 | C8: mm | D8: Dick-Peschke | E8: P20
A9: Tiempo de concentracion en el colector | B9: 15 | C9: min | D9: 10 min de entrada + recorrido en cunetas y colector | E9: tc
A10: Exponente de la curva P-D | B10: =LN(B8/B7)/LN(2) | C10: - | D10: b = ln(P20/P10)/ln 2 | E10: bx
A11: Intensidad de diseno I | B11: =B7*(B9/10)^B10/(B9/60) | C11: mm/h | D11: I = P10 (tc/10)^b / (tc/60) | E11: I
A12: Factor de seguridad FS | B12: 1.15 | C12: - | D12: Memorias de calculo HIDRO-CE040 | E12: FS
A13: Intensidad para D = 10 min (cunetas y montantes del estudio hidrologico) | B13: =B7*60/10 | C13: mm/h | D13: I10 = P10 x 60 / 10 = 210.98 mm/h: es la misma lluvia de 35.163 mm en 10 min, expresada como intensidad (igual al estudio hidrologico) | E13: I10
A14: Intensidad para D = 20 min | B14: =B8*60/20 | C14: mm/h | D14: I20 = P20 x 60 / 20 = 125.45 mm/h (analisis estadistico, hoja C. P diseno) | E14: I20
A15: Nota: el colector tiene tc = 15 min (mayor que los 10 min de cada cuneta), por eso su intensidad es 155.66 mm/h, interpolada en la curva P-D entre 10 y 20 min; es el mismo criterio del colector del CAR Mujeres (3 proyectos).
A16: GEOMETRIA DEL COLECTOR (tramo Hogar de Refugio)
A17: Ancho interior b | B17: 0.8 | C17: m | D17: Adoptado: llenado <= 85 % y regimen subcritico (hoja PERFIL_FLUJO) | E17: b
A18: Espesor de muros | B18: 0.15 | C18: m | D18: Muros de 1.40 a 1.65 m de altura interior (hoja ESTRUCTURAL) | E18: em
A19: Espesor de losa de fondo | B19: 0.15 | C19: m | E19: ef
A20: Espesor de losa superior (tramo normal y porton de motos) | B20: 0.1 | C20: m | D20: Vaciada monoliticamente con los muros | E20: et
A21: Espesor de losa superior en cruce de camiones | B21: 0.25 | C21: m | D21: Ingreso vehicular OE-01 (cisterna al PTAR) | E21: ec
A22: Cota de fondo inicial (0+000, caja de llegada) | B22: 259.1 | C22: msnm | D22: Fijada por las cunetas de arquitectura: la mas baja llega con NCF 259.70 (Eje 02) | E22: CF0
A23: Pendiente S | B23: 0.003 | C23: m/m | D23: Adoptada 0.30 %: regimen subcritico (F = 0.60) y fondo sobre el R-01 del receptor | E23: S
A24: Progresiva del quiebre 1 (45 grados) | B24: 58.81 | C24: m | D24: Salida del frente hacia el lindero | E24: pq1
A25: Progresiva del quiebre 2 (45 grados) | B25: 66.89 | C25: m | E25: pq2
A26: Progresiva del brink de la caida (fin del colector b=0.80) | B26: 69.89 | C26: m | D26: Inicio de la poza de disipacion | E26: pb
A27: Progresiva de entrega (0+000 del tramo CAR Mujeres) | B27: 73.39 | C27: m | D27: Cara aguas arriba del registro R-01 del receptor | E27: pf
A28: Longitud total del tramo | B28: =B27 | C28: m | E28: L
A29: NPT del frente (cara superior de la losa) | B29: 260.6 | C29: msnm | D29: Arquitectura: NT 260.50 + NPT 0.10 (estacionamientos e ingresos) | E29: NPT
A30: Cruce de camiones: inicio | B30: 26.32 | C30: m | D30: Ingreso vehicular OE-01 (4.415 m) + 0.30 m a cada lado | E30: pc1
A31: Cruce de camiones: fin | B31: 31.33 | C31: m | E31: pc2
A32: Cruce de motos: inicio | B32: 39.04 | C32: m | D32: Porton de motos (1.77 m), tramo de 2.00 m | E32: pm1
A33: Cruce de motos: fin | B33: 41.04 | C33: m | E33: pm2
A34: Coeficiente de Manning n | B34: 0.015 | C34: - | D34: Concreto vaciado in situ (Chow) | E34: n
A35: CRITERIOS DE VERIFICACION HIDRAULICA
A36: Llenado maximo admisible y/h (conducto cubierto) | B36: 0.85 | C36: - | D36: Criterio de conducto cerrado a superficie libre | E36: llen
A37: Borde libre minimo bajo losa | B37: 0.05 | C37: m | D37: Complementario al criterio de llenado | E37: BLmin
A38: RECEPTOR: COLECTOR DEL CAR MUJERES (CUI 2717013)
A39: Cota de fondo del receptor en su 0+000 (R-01) | B39: 258.72 | C39: msnm | D39: Plano DP-01 del tramo CAR Mujeres | E39: CFr
A40: Nivel de agua del receptor en su 0+000 | B40: 259.062 | C40: msnm | D40: Memoria del tramo CAR Mujeres (Q = 626 L/s en 0+000) | E40: NAr
A41: Ancho interior del receptor | B41: 1.5 | C41: m | E41: br
A42: APORTE EXTERNO: COLECTOR DEL CAR VARONES (CUI 2705619)
A43: Cota de fondo de llegada del colector del CAR Varones (cara este de la CL) | B43: 259.884 | C43: msnm | D43: Expediente del CAR Varones (CUI 2705619): 260.20 - 0.3 % x 105.29 m; ventana este de la CL de 0.60 x 1.17 | E43: CFv
A44: Cota de la tapa de la caja CL (piso terminado del CAR Varones) | B44: 261.15 | C44: msnm | D44: La CL queda del lado del CAR Varones (x = 349162.00 a 349163.80); su tapa va al ras de ese piso (+261.15) | E44: CLt
A45: Cuneta Eje 01 del CAR Varones: cota de fondo en el muro norte de la CL | B45: 260.394 | C45: msnm | D45: Entra directamente a la CL por ventana 0.40 x 0.66 (37.0 L/s de los 258.7) | E45: E01
A46: CAJAS
A47: Caja de llegada CL: profundidad de poza bajo el fondo | B47: 0.3 | C47: m | D47: Colchon de agua para la caida del aporte externo | E47: pcl
A48: Caja de caida CC: profundidad de poza bajo el fondo del receptor | B48: 0.4 | C48: m | D48: Poza de disipacion deprimida | E48: pcc
A49: Caja de caida CC: longitud de poza | B49: 3.5 | C49: m | E49: Lcc
A50: Caja de caida CC: ancho de poza | B50: 1.5 | C50: m | D50: Igual al ancho del receptor | E50: bcc
A52: Azul = dato editable; negro = formula; verde = vinculo.

Sheet CAUDALES
A1: 2. CAUDALES DE DISENO - METODO RACIONAL Q = C I A FS
A2: Colector pluvial frontal - tramo Hogar de Refugio Temporal Mujeres Violentadas (CUI 2675514), Morales - San Martin. Hidroconsult, Oct. 2026
A4: PROYECTO | B4: AREA (m2) | C4: C x A (m2) | D4: C PONDERADO | E4: I (mm/h) | F4: Q (L/s) | G4: INGRESA AL COLECTOR EN | H4: FUENTE
A5: CAR Varones (CUI 2705619) - aporte externo | B5: 6752.03 | C5: 5203.3213 | D5: =C5/B5 | E5: =DATOS!$B$11 | F5: =C5*E5/3600000*DATOS!$B$12*1000 | G5: Caja de llegada CL (0+000) | H5: Memoria HIDRO-CE040 del proyecto, dato no validado
A6: Hogar de Refugio Temporal M. Violentadas (CUI 2675514) | B6: 7520.41 | C6: 6072.3596 | D6: =C6/B6 | E6: =DATOS!$B$11 | F6: =C6*E6/3600000*DATOS!$B$12*1000 | G6: Cunetas Ejes 01, 02, 06, 07, 11 y 12 | H6: Memoria HIDRO-CE040, 12 fichas
A7: TOTAL ENTREGADO AL CAR MUJERES | B7: =SUM(B5:B6) | C7: =SUM(C5:C6) | D7: =C7/B7 | F7: =SUM(F5:F6)
A9: Caudal de diseno adoptado (valores de las memorias de cada proyecto)
A10: CAR Varones | B10: 258.7 | C10: L/s
A11: Hogar de Refugio | B11: 301.9 | C11: L/s
A12: Q de diseno del tramo | B12: =B10+B11 | C12: L/s
A13: Q de diseno del tramo | B13: =B12/1000 | C13: m3/s
A15: Caudal que circula por el tramo (de aguas arriba hacia aguas abajo)
A16: PUNTO | B16: PROGRESIVA | C16: APORTE (L/s) | D16: Q ACUMULADO (L/s)
A17: Caja de llegada CL (CAR Varones) | B17: 0 | C17: =B10 | D17: =SUM($C$17:C17)
A18: Cuneta Eje 01 (perimetral este) - perfil 01 | B18: 1.07 | C18: =B11/6 | D18: =SUM($C$17:C18)
A19: Cuneta Eje 02 (estacionamiento) - perfil 02 | B19: 11.27 | C19: =B11/6 | D19: =SUM($C$17:C19)
A20: Cuneta Eje 06 (ingreso vehicular) - perfil 06 | B20: 32.5 | C20: =B11/6 | D20: =SUM($C$17:C20)
A21: Cuneta Eje 07 - perfil 07 | B21: 42.68 | C21: =B11/6 | D21: =SUM($C$17:C21)
A22: Cuneta Eje 11 - perfil 11 | B22: 60.89 | C22: =B11/6 | D22: =SUM($C$17:C22)
A23: Cuneta Eje 12 (perimetral oeste) - perfil 12 | B23: 69.56 | C23: =B11/6 | D23: =SUM($C$17:C23)
A25: Suma de picos sin desfase de tiempos y con FS = 1.15: hipotesis conservadora. El reparto del aporte del Refugio entre sus 6 cunetas es nominal; el perfil se verifica con el caudal total en todo el tramo.

Sheet CUNETAS
A1: 3. CUNETAS DE ARQUITECTURA QUE LLEGAN AL COLECTOR
A2: Colector pluvial frontal - tramo Hogar de Refugio Temporal Mujeres Violentadas (CUI 2675514), Morales - San Martin. Hidroconsult, Oct. 2026
A4: CUNETA (perfil de arquitectura) | B4: PERFIL | C4: PROGRESIVA (m) | D4: LONGITUD (m) | E4: NCT (msnm) | F4: NCF al cerco (msnm) | G4: H al cerco (m) | H4: PROLONG. (m) | I4: NCF en el muro (msnm) | J4: NA del colector (msnm) | K4: CAIDA LIBRE (m) | L4: VERIFICACION
A5: Eje 01 (perimetral este) | B5: 01 | C5: 1.07 | D5: 37.14 | E5: 260.6 | F5: 260.12 | G5: =E5-F5 | H5: 0.03 | I5: =F5-0.005*H5 | J5: =IFERROR(INDEX(PERFIL_FLUJO!$G$6:$G$200,MATCH(C5,PERFIL_FLUJO!$A$6:$A$200,0)),"") | K5: =I5-J5 | L5: =IF(K5>0,"CAIDA LIBRE","AHOGADA")
A6: Eje 02 (estacionamiento) | B6: 02 | C6: 11.27 | D6: 130.85 | E6: 260.6 | F6: 259.7 | G6: =E6-F6 | H6: 0.03 | I6: =F6-0.005*H6 | J6: =IFERROR(INDEX(PERFIL_FLUJO!$G$6:$G$200,MATCH(C6,PERFIL_FLUJO!$A$6:$A$200,0)),"") | K6: =I6-J6 | L6: =IF(K6>0,"CAIDA LIBRE","AHOGADA")
A7: Eje 06 (ingreso vehicular) | B7: 06 | C7: 32.5 | D7: 120.36 | E7: 260.6 | F7: 259.75 | G7: =E7-F7 | H7: 0.03 | I7: =F7-0.005*H7 | J7: =IFERROR(INDEX(PERFIL_FLUJO!$G$6:$G$200,MATCH(C7,PERFIL_FLUJO!$A$6:$A$200,0)),"") | K7: =I7-J7 | L7: =IF(K7>0,"CAIDA LIBRE","AHOGADA")
A8: Eje 07 | B8: 07 | C8: 42.68 | D8: 125.7 | E8: 260.6 | F8: 259.72 | G8: =E8-F8 | H8: 0.03 | I8: =F8-0.005*H8 | J8: =IFERROR(INDEX(PERFIL_FLUJO!$G$6:$G$200,MATCH(C8,PERFIL_FLUJO!$A$6:$A$200,0)),"") | K8: =I8-J8 | L8: =IF(K8>0,"CAIDA LIBRE","AHOGADA")
A9: Eje 11 | B9: 11 | C9: 60.89 | D9: 71.46 | E9: 260.6 | F9: 260 | G9: =E9-F9 | H9: 1.88 | I9: =F9-0.005*H9 | J9: =IFERROR(INDEX(PERFIL_FLUJO!$G$6:$G$200,MATCH(C9,PERFIL_FLUJO!$A$6:$A$200,0)),"") | K9: =I9-J9 | L9: =IF(K9>0,"CAIDA LIBRE","AHOGADA")
A10: Eje 12 (perimetral oeste) | B10: 12 | C10: 69.56 | D10: 109.12 | E10: 260.6 | F10: 259.8 | G10: =E10-F10 | H10: 5.39 | I10: =F10-0.005*H10 | J10: =IFERROR(INDEX(PERFIL_FLUJO!$G$6:$G$200,MATCH(C10,PERFIL_FLUJO!$A$6:$A$200,0)),"") | K10: =I10-J10 | L10: =IF(K10>0,"CAIDA LIBRE","AHOGADA")
A12: Seccion de las cunetas: 0.40 x H, muros 0.10, pendiente 0.5 % (plano de arquitectura, perfiles 01 a 12). Las prolongaciones fuera del cerco mantienen la misma pendiente. El empalme es por ventana 0.40 x H en el muro lado predio, con caida al fondo del colector y registro encima (lamina DP-06).

Sheet EMPALME
A1: 4. CAJA DE LLEGADA (0+000) Y CAJA DE CAIDA EN LA ENTREGA AL CAR MUJERES
A2: Colector pluvial frontal - tramo Hogar de Refugio Temporal Mujeres Violentadas (CUI 2675514), Morales - San Martin. Hidroconsult, Oct. 2026
A4: PARAMETRO | B4: VALOR | C4: UND | D4: FORMULA / CRITERIO
A5: A. CAJA DE CAIDA CC - ENTREGA AL REGISTRO R-01 DEL CAR MUJERES
A6: Caudal Q | B6: =CAUDALES!B13 | C6: m3/s
A7: Ancho del colector en el brink b | B7: =DATOS!B17 | C7: m
A8: Cota de fondo en el brink | B8: =DATOS!B22-DATOS!B23*DATOS!B26 | C8: msnm | D8: CF0 - S x pb
A9: Tirante critico en el brink yc | B9: =(B6^2/(9.81*B7^2))^(1/3) | C9: m | D9: yc = (Q2/(g b2))^(1/3): control de la caida libre
A10: Nivel de agua en el brink | B10: =B8+B9 | C10: msnm | D10: nivel de control del perfil de flujo (hoja PERFIL_FLUJO)
A11: Piso de la poza | B11: =DATOS!B39-DATOS!B48 | C11: msnm | D11: fondo del receptor - profundidad de poza
A12: Caida total (brink a piso de poza) | B12: =B8-B11 | C12: m
A13: Energia al pie respecto al piso E1 | B13: =B12+1.5*B9 | C13: m | D13: E1 = caida + 1.5 yc (sin perdidas, conservador)
A14: Tirante al pie y1 | B14: 0.1613 | C14: m | D14: y1 resuelto en Python (y1 + (Q/(b y1))^2/2g = E1); verificar: B14 + B15^2/19.62 = B13
A15: Velocidad al pie V1 | B15: =B6/(B7*B14) | C15: m/s | D15: V1 = Q/(b y1)
A16: Froude al pie F1 | B16: =B15/SQRT(9.81*B14) | C16: -
A17: Tirante conjugado y2 | B17: =B14/2*(SQRT(1+8*B16^2)-1) | C17: m | D17: resalto hidraulico en el ancho b (conservador: no considera la expansion a 1.50 m)
A18: Tirante disponible en la poza | B18: =DATOS!B40-B11 | C18: m | D18: NA del receptor - piso de la poza
A19: Verificacion del resalto | B19: =IF(B18>=B17,"RESALTO AHOGADO - CUMPLE","REVISAR PROFUNDIDAD DE POZA") | D19: el receptor ahoga el resalto dentro de la poza
A20: Longitud de resalto 6 y2 | B20: =6*B17 | C20: m | D20: referencia (resalto libre)
A21: Longitud de poza adoptada | B21: =DATOS!B49 | C21: m | D21: con umbral de salida de 0.40 m hasta el fondo del receptor; resalto ahogado
A22: Verificacion de longitud | B22: =IF(B21>=0.8*B20,"CUMPLE (resalto ahogado)","AMPLIAR POZA") | D22: poza >= 0.8 x 6 y2 para resalto ahogado (USBR)
A23: Nivel de agua en el receptor | B23: =DATOS!B40 | C23: msnm | D23: regimen subcritico aguas abajo del umbral (F = 0.67 en el receptor)
A25: B. CAJA DE LLEGADA CL (0+000) - CAIDA DEL APORTE DE CAR VARONES
A26: Cota de fondo de llegada del aporte externo | B26: =DATOS!B43 | C26: msnm | D26: expediente del CAR Varones (CUI 2705619): colector b = 0.60, fondo 259.884 en la cara este de la CL
A27: Piso de la poza de la caja | B27: =DATOS!B22-DATOS!B47 | C27: msnm | D27: CF0 - profundidad de poza
A28: Caida del aporte externo | B28: =B26-B27 | C28: m
A29: Nivel de agua en la caja (= inicio del colector) | B29: =PERFIL_FLUJO!G200 | C29: msnm | D29: nivel de agua en 0+000 (hoja PERFIL_FLUJO, ultima fila)
A30: Colchon de agua en la poza | B30: =B29-B27 | C30: m | D30: amortigua el chorro de 259 L/s
A31: Verificacion | B31: =IF(B30>=0.5,"CUMPLE (colchon >= 0.50 m)","REVISAR")
A32: Dimensiones interiores de la caja | B32: 1.50 x 1.00 | C32: m | D32: largo x ancho; profundidad hasta el piso de poza
A33: Verificacion de y1: y1 + V1^2/2g | B33: =B14+B15^2/(2*9.81) | C33: m | D33: debe ser igual a E1 (B13)

Sheet PERFIL_FLUJO
A1: 5. PERFIL DE FLUJO GRADUALMENTE VARIADO - METODO DEL PASO ESTANDAR (de aguas abajo hacia aguas arriba)
A2: Colector pluvial frontal - tramo Hogar de Refugio Temporal Mujeres Violentadas (CUI 2675514), Morales - San Martin. Hidroconsult, Oct. 2026
A3: Ecuacion de energia entre estaciones: y1 + V1^2/2g + z1 = y2 + V2^2/2g + z2 + dx (Sf1 + Sf2)/2 ; Sf = (n V / R^(2/3))^2 ; control: tirante critico en el brink de la caida (0+069.89)
P4: Biseccion del tirante y (lo, hi) en 30 iteraciones: f(y) = y + V^2/2g + z - E2 - dx (Sf + Sf2)/2
A5: PROGRESIVA (m) | B5: COTA FONDO | C5: Q (m3/s) | D5: b (m) | E5: yc (m) | F5: TIRANTE y (m) | G5: NIVEL DE AGUA | H5: VELOCIDAD (m/s) | I5: FROUDE | J5: COTA BAJO LOSA | K5: ALTURA INTERIOR h | L5: LLENADO y/h | M5: BORDE LIBRE (m) | N5: VERIFICACION | O5: ZONA
A6: 69.89 | B6: =DATOS!$B$22-DATOS!$B$23*A6 | C6: =CAUDALES!$B$13 | D6: =DATOS!$B$17 | E6: =(C6^2/(9.81*D6^2))^(1/3) | F6: =E6 | G6: =B6+F6 | H6: =C6/(D6*F6) | I6: =H6/SQRT(9.81*F6) | J6: =DATOS!$B$29-IF(AND(A6>=DATOS!$B$30,A6<DATOS!$B$31),DATOS!$B$21,DATOS!$B$20) | K6: =J6-B6 | L6: =F6/K6 | M6: =J6-G6 | N6: =IF(AND(L6<=DATOS!$B$36,M6>=DATOS!$B$37,I6<=1),"CUMPLE","NO CUMPLE") | O6: =IF(AND(A6>=DATOS!$B$30,A6<DATOS!$B$31),"cruce de camiones",IF(AND(A6>=DATOS!$B$32,A6<DATOS!$B$33),"cruce de motos","tramo normal"))
A7: 69.56 | B7: =DATOS!$B$22-DATOS!$B$23*A7 | C7: =CAUDALES!$B$13 | D7: =DATOS!$B$17 | E7: =(C7^2/(9.81*D7^2))^(1/3) | F7: =(BV7+BW7)/2 | G7: =B7+F7 | H7: =C7/(D7*F7) | I7: =H7/SQRT(9.81*F7) | J7: =DATOS!$B$29-IF(AND(A7>=DATOS!$B$30,A7<DATOS!$B$31),DATOS!$B$21,DATOS!$B$20) | K7: =J7-B7 | L7: =F7/K7 | M7: =J7-G7 | N7: =IF(AND(L7<=DATOS!$B$36,M7>=DATOS!$B$37,I7<=1),"CUMPLE","NO CUMPLE") | O7: =IF(AND(A7>=DATOS!$B$30,A7<DATOS!$B$31),"cruce de camiones",IF(AND(A7>=DATOS!$B$32,A7<DATOS!$B$33),"cruce de motos","tramo normal")) | P7: =E7*1.001 | Q7: 3 | R7: =IF((((P7+Q7)/2)+(C7/(D7*((P7+Q7)/2)))^2/(2*9.81)+B7-(G6+H6^2/(2*9.81))-(A6-A7)*(((DATOS!$B$34*(C7/(D7*((P7+Q7)/2)))/((D7*((P7+Q7)/2))/(D7+2*((P7+Q7)/2)))^(2/3))^2+((DATOS!$B$34*H6/((D6*F6)/(D6+2*F6))^(2/3))^2))/2))>0,P7,((P7+Q7)/2)) | S7: =IF((((P7+Q7)/2)+(C7/(D7*((P7+Q7)/2)))^2/(2*9.81)+B7-(G6+H6^2/(2*9.81))-(A6-A7)*(((DATOS!$B$34*(C7/(D7*((P7+Q7)/2)))/((D7*((P7+Q7)/2))/(D7+2*((P7+Q7)/2)))^(2/3))^2+((DATOS!$B$34*H6/((D6*F6)/(D6+2*F6))^(2/3))^2))/2))>0,((P7+Q7)/2),Q7) | T7: =IF((((R7+S7)/2)+(C7/(D7*((R7+S7)/2)))^2/(2*9.81)+B7-(G6+H6^2/(2*9.81))-(A6-A7)*(((DATOS!$B$34*(C7/(D7*((R7+S7)/2)))/((D7*((R7+S7)/2))/(D7+2*((R7+S7)/2)))^(2/3))^2+((DATOS!$B$34*H6/((D6*F6)/(D6+2*F6))^(2/3))^2))/2))>0,R7,((R7+S7)/2)) | U7: =IF((((R7+S7)/2)+(C7/(D7*((R7+S7)/2)))^2/(2*9.81)+B7-(G6+H6^2/(2*9.81))-(A6-A7)*(((DATOS!$B$34*(C7/(D7*((R7+S7)/2)))/((D7*((R7+S7)/2))/(D7+2*((R7+S7)/2)))^(2/3))^2+((DATOS!$B$34*H6/((D6*F6)/(D6+2*F6))^(2/3))^2))/2))>0,((R7+S7)/2),S7) | V7: =IF((((T7+U7)/2)+(C7/(D7*((T7+U7)/2)))^2/(2*9.81)+B7-(G6+H6^2/(2*9.81))-(A6-A7)*(((DATOS!$B$34*(C7/(D7*((T7+U7)/2)))/((D7*((T7+U7)/2))/(D7+2*((T7+U7)/2)))^(2/3))^2+((DATOS!$B$34*H6/((D6*F6)/(D6+2*F6))^(2/3))^2))/2))>0,T7,((T7+U7)/2)) | W7: =IF((((T7+U7)/2)+(C7/(D7*((T7+U7)/2)))^2/(2*9.81)+B7-(G6+H6^2/(2*9.81))-(A6-A7)*(((DATOS!$B$34*(C7/(D7*((T7+U7)/2)))/((D7*((T7+U7)/2))/(D7+2*((T7+U7)/2)))^(2/3))^2+((DATOS!$B$34*H6/((D6*F6)/(D6+2*F6))^(2/3))^2))/2))>0,((T7+U7)/2),U7) | X7: =IF((((V7+W7)/2)+(C7/(D7*((V7+W7)/2)))^2/(2*9.81)+B7-(G6+H6^2/(2*9.81))-(A6-A7)*(((DATOS!$B$34*(C7/(D7*((V7+W7)/2)))/((D7*((V7+W7)/2))/(D7+2*((V7+W7)/2)))^(2/3))^2+((DATOS!$B$34*H6/((D6*F6)/(D6+2*F6))^(2/3))^2))/2))>0,V7,((V7+W7)/2)) | Y7: =IF((((V7+W7)/2)+(C7/(D7*((V7+W7)/2)))^2/(2*9.81)+B7-(G6+H6^2/(2*9.81))-(A6-A7)*(((DATOS!$B$34*(C7/(D7*((V7+W7)/2)))/((D7*((V7+W7)/2))/(D7+2*((V7+W7)/2)))^(2/3))^2+((DATOS!$B$34*H6/((D6*F6)/(D6+2*F6))^(2/3))^2))/2))>0,((V7+W7)/2),W7) | Z7: =IF((((X7+Y7)/2)+(C7/(D7*((X7+Y7)/2)))^2/(2*9.81)+B7-(G6+H6^2/(2*9.81))-(A6-A7)*(((DATOS!$B$34*(C7/(D7*((X7+Y7)/2)))/((D7*((X7+Y7)/2))/(D7+2*((X7+Y7)/2)))^(2/3))^2+((DATOS!$B$34*H6/((D6*F6)/(D6+2*F6))^(2/3))^2))/2))>0,X7,((X7+Y7)/2)) | AA7: =IF((((X7+Y7)/2)+(C7/(D7*((X7+Y7)/2)))^2/(2*9.81)+B7-(G6+H6^2/(2*9.81))-(A6-A7)*(((DATOS!$B$34*(C7/(D7*((X7+Y7)/2)))/((D7*((X7+Y7)/2))/(D7+2*((X7+Y7)/2)))^(2/3))^2+((DATOS!$B$34*H6/((D6*F6)/(D6+2*F6))^(2/3))^2))/2))>0,((X7+Y7)/2),Y7) | AB7: =IF((((Z7+AA7)/2)+(C7/(D7*((Z7+AA7)/2)))^2/(2*9.81)+B7-(G6+H6^2/(2*9.81))-(A6-A7)*(((DATOS!$B$34*(C7/(D7*((Z7+AA7)/2)))/((D7*((Z7+AA7)/2))/(D7+2*((Z7+AA7)/2)))^(2/3))^2+((DATOS!$B$34*H6/((D6*F6)/(D6+2*F6))^(2/3))^2))/2))>0,Z7,((Z7+AA7)/2)) | AC7: =IF((((Z7+AA7)/2)+(C7/(D7*((Z7+AA7)/2)))^2/(2*9.81)+B7-(G6+H6^2/(2*9.81))-(A6-A7)*(((DATOS!$B$34*(C7/(D7*((Z7+AA7)/2)))/((D7*((Z7+AA7)/2))/(D7+2*((Z7+AA7)/2)))^(2/3))^2+((DATOS!$B$34*H6/((D6*F6)/(D6+2*F6))^(2/3))^2))/2))>0,((Z7+AA7)/2),AA7) | AD7: =IF((((AB7+AC7)/2)+(C7/(D7*((AB7+AC7)/2)))^2/(2*9.81)+B7-(G6+H6^2/(2*9.81))-(A6-A7)*(((DATOS!$B$34*(C7/(D7*((AB7+AC7)/2)))/((D7*((AB7+AC7)/2))/(D7+2*((AB7+AC7)/2)))^(2/3))^2+((DATOS!$B$34*H6/((D6*F6)/(D6+2*F6))^(2/3))^2))/2))>0,AB7,((AB7+AC7)/2)) | AE7: =IF((((AB7+AC7)/2)+(C7/(D7*((AB7+AC7)/2)))^2/(2*9.81)+B7-(G6+H6^2/(2*9.81))-(A6-A7)*(((DATOS!$B$34*(C7/(D7*((AB7+AC7)/2)))/((D7*((AB7+AC7)/2))/(D7+2*((AB7+AC7)/2)))^(2/3))^2+((DATOS!$B$34*H6/((D6*F6)/(D6+2*F6))^(2/3))^2))/2))>0,((AB7+AC7)/2),AC7) | AF7: =IF((((AD7+AE7)/2)+(C7/(D7*((AD7+AE7)/2)))^2/(2*9.81)+B7-(G6+H6^2/(2*9.81))-(A6-A7)*(((DATOS!$B$34*(C7/(D7*((AD7+AE7)/2)))/((D7*((AD7+AE7)/2))/(D7+2*((AD7+AE7)/2)))^(2/3))^2+((DATOS!$B$34*H6/((D6*F6)/(D6+2*F6))^(2/3))^2))/2))>0,AD7,((AD7+AE7)/2)) | AG7: =IF((((AD7+AE7)/2)+(C7/(D7*((AD7+AE7)/2)))^2/(2*9.81)+B7-(G6+H6^2/(2*9.81))-(A6-A7)*(((DATOS!$B$34*(C7/(D7*((AD7+AE7)/2)))/((D7*((AD7+AE7)/2))/(D7+2*((AD7+AE7)/2)))^(2/3))^2+((DATOS!$B$34*H6/((D6*F6)/(D6+2*F6))^(2/3))^2))/2))>0,((AD7+AE7)/2),AE7) | AH7: =IF((((AF7+AG7)/2)+(C7/(D7*((AF7+AG7)/2)))^2/(2*9.81)+B7-(G6+H6^2/(2*9.81))-(A6-A7)*(((DATOS!$B$34*(C7/(D7*((AF7+AG7)/2)))/((D7*((AF7+AG7)/2))/(D7+2*((AF7+AG7)/2)))^(2/3))^2+((DATOS!$B$34*H6/((D6*F6)/(D6+2*F6))^(2/3))^2))/2))>0,AF7,((AF7+AG7)/2)) | AI7: =IF((((AF7+AG7)/2)+(C7/(D7*((AF7+AG7)/2)))^2/(2*9.81)+B7-(G6+H6^2/(2*9.81))-(A6-A7)*(((DATOS!$B$34*(C7/(D7*((AF7+AG7)/2)))/((D7*((AF7+AG7)/2))/(D7+2*((AF7+AG7)/2)))^(2/3))^2+((DATOS!$B$34*H6/((D6*F6)/(D6+2*F6))^(2/3))^2))/2))>0,((AF7+AG7)/2),AG7) | AJ7: =IF((((AH7+AI7)/2)+(C7/(D7*((AH7+AI7)/2)))^2/(2*9.81)+B7-(G6+H6^2/(2*9.81))-(A6-A7)*(((DATOS!$B$34*(C7/(D7*((AH7+AI7)/2)))/((D7*((AH7+AI7)/2))/(D7+2*((AH7+AI7)/2)))^(2/3))^2+((DATOS!$B$34*H6/((D6*F6)/(D6+2*F6))^(2/3))^2))/2))>0,AH7,((AH7+AI7)/2)) | AK7: =IF((((AH7+AI7)/2)+(C7/(D7*((AH7+AI7)/2)))^2/(2*9.81)+B7-(G6+H6^2/(2*9.81))-(A6-A7)*(((DATOS!$B$34*(C7/(D7*((AH7+AI7)/2)))/((D7*((AH7+AI7)/2))/(D7+2*((AH7+AI7)/2)))^(2/3))^2+((DATOS!$B$34*H6/((D6*F6)/(D6+2*F6))^(2/3))^2))/2))>0,((AH7+AI7)/2),AI7) | AL7: =IF((((AJ7+AK7)/2)+(C7/(D7*((AJ7+AK7)/2)))^2/(2*9.81)+B7-(G6+H6^2/(2*9.81))-(A6-A7)*(((DATOS!$B$34*(C7/(D7*((AJ7+AK7)/2)))/((D7*((AJ7+AK7)/2))/(D7+2*((AJ7+AK7)/2)))^(2/3))^2+((DATOS!$B$34*H6/((D6*F6)/(D6+2*F6))^(2/3))^2))/2))>0,AJ7,((AJ7+AK7)/2)) | AM7: =IF((((AJ7+AK7)/2)+(C7/(D7*((AJ7+AK7)/2)))^2/(2*9.81)+B7-(G6+H6^2/(2*9.81))-(A6-A7)*(((DATOS!$B$34*(C7/(D7*((AJ7+AK7)/2)))/((D7*((AJ7+AK7)/2))/(D7+2*((AJ7+AK7)/2)))^(2/3))^2+((DATOS!$B$34*H6/((D6*F6)/(D6+2*F6))^(2/3))^2))/2))>0,((AJ7+AK7)/2),AK7) | AN7: =IF((((AL7+AM7)/2)+(C7/(D7*((AL7+AM7)/2)))^2/(2*9.81)+B7-(G6+H6^2/(2*9.81))-(A6-A7)*(((DATOS!$B$34*(C7/(D7*((AL7+AM7)/2)))/((D7*((AL7+AM7)/2))/(D7+2*((AL7+AM7)/2)))^(2/3))^2+((DATOS!$B$34*H6/((D6*F6)/(D6+2*F6))^(2/3))^2))/2))>0,AL7,((AL7+AM7)/2)) | AO7: =IF((((AL7+AM7)/2)+(C7/(D7*((AL7+AM7)/2)))^2/(2*9.81)+B7-(G6+H6^2/(2*9.81))-(A6-A7)*(((DATOS!$B$34*(C7/(D7*((AL7+AM7)/2)))/((D7*((AL7+AM7)/2))/(D7+2*((AL7+AM7)/2)))^(2/3))^2+((DATOS!$B$34*H6/((D6*F6)/(D6+2*F6))^(2/3))^2))/2))>0,((AL7+AM7)/2),AM7) | AP7: =IF((((AN7+AO7)/2)+(C7/(D7*((AN7+AO7)/2)))^2/(2*9.81)+B7-(G6+H6^2/(2*9.81))-(A6-A7)*(((DATOS!$B$34*(C7/(D7*((AN7+AO7)/2)))/((D7*((AN7+AO7)/2))/(D7+2*((AN7+AO7)/2)))^(2/3))^2+((DATOS!$B$34*H6/((D6*F6)/(D6+2*F6))^(2/3))^2))/2))>0,AN7,((AN7+AO7)/2)) | AQ7: =IF((((AN7+AO7)/2)+(C7/(D7*((AN7+AO7)/2)))^2/(2*9.81)+B7-(G6+H6^2/(2*9.81))-(A6-A7)*(((DATOS!$B$34*(C7/(D7*((AN7+AO7)/2)))/((D7*((AN7+AO7)/2))/(D7+2*((AN7+AO7)/2)))^(2/3))^2+((DATOS!$B$34*H6/((D6*F6)/(D6+2*F6))^(2/3))^2))/2))>0,((AN7+AO7)/2),AO7) | AR7: =IF((((AP7+AQ7)/2)+(C7/(D7*((AP7+AQ7)/2)))^2/(2*9.81)+B7-(G6+H6^2/(2*9.81))-(A6-A7)*(((DATOS!$B$34*(C7/(D7*((AP7+AQ7)/2)))/((D7*((AP7+AQ7)/2))/(D7+2*((AP7+AQ7)/2)))^(2/3))^2+((DATOS!$B$34*H6/((D6*F6)/(D6+2*F6))^(2/3))^2))/2))>0,AP7,((AP7+AQ7)/2)) | AS7: =IF((((AP7+AQ7)/2)+(C7/(D7*((AP7+AQ7)/2)))^2/(2*9.81)+B7-(G6+H6^2/(2*9.81))-(A6-A7)*(((DATOS!$B$34*(C7/(D7*((AP7+AQ7)/2)))/((D7*((AP7+AQ7)/2))/(D7+2*((AP7+AQ7)/2)))^(2/3))^2+((DATOS!$B$34*H6/((D6*F6)/(D6+2*F6))^(2/3))^2))/2))>0,((AP7+AQ7)/2),AQ7) | AT7: =IF((((AR7+AS7)/2)+(C7/(D7*((AR7+AS7)/2)))^2/(2*9.81)+B7-(G6+H6^2/(2*9.81))-(A6-A7)*(((DATOS!$B$34*(C7/(D7*((AR7+AS7)/2)))/((D7*((AR7+AS7)/2))/(D7+2*((AR7+AS7)/2)))^(2/3))^2+((DATOS!$B$34*H6/((D6*F6)/(D6+2*F6))^(2/3))^2))/2))>0,AR7,((AR7+AS7)/2)) | AU7: =IF((((AR7+AS7)/2)+(C7/(D7*((AR7+AS7)/2)))^2/(2*9.81)+B7-(G6+H6^2/(2*9.81))-(A6-A7)*(((DATOS!$B$34*(C7/(D7*((AR7+AS7)/2)))/((D7*((AR7+AS7)/2))/(D7+2*((AR7+AS7)/2)))^(2/3))^2+((DATOS!$B$34*H6/((D6*F6)/(D6+2*F6))^(2/3))^2))/2))>0,((AR7+AS7)/2),AS7) | AV7: =IF((((AT7+AU7)/2)+(C7/(D7*((AT7+AU7)/2)))^2/(2*9.81)+B7-(G6+H6^2/(2*9.81))-(A6-A7)*(((DATOS!$B$34*(C7/(D7*((AT7+AU7)/2)))/((D7*((AT7+AU7)/2))/(D7+2*((AT7+AU7)/2)))^(2/3))^2+((DATOS!$B$34*H6/((D6*F6)/(D6+2*F6))^(2/3))^2))/2))>0,AT7,((AT7+AU7)/2)) | AW7: =IF((((AT7+AU7)/2)+(C7/(D7*((AT7+AU7)/2)))^2/(2*9.81)+B7-(G6+H6^2/(2*9.81))-(A6-A7)*(((DATOS!$B$34*(C7/(D7*((AT7+AU7)/2)))/((D7*((AT7+AU7)/2))/(D7+2*((AT7+AU7)/2)))^(2/3))^2+((DATOS!$B$34*H6/((D6*F6)/(D6+2*F6))^(2/3))^2))/2))>0,((AT7+AU7)/2),AU7) | AX7: =IF((((AV7+AW7)/2)+(C7/(D7*((AV7+AW7)/2)))^2/(2*9.81)+B7-(G6+H6^2/(2*9.81))-(A6-A7)*(((DATOS!$B$34*(C7/(D7*((AV7+AW7)/2)))/((D7*((AV7+AW7)/2))/(D7+2*((AV7+AW7)/2)))^(2/3))^2+((DATOS!$B$34*H6/((D6*F6)/(D6+2*F6))^(2/3))^2))/2))>0,AV7,((AV7+AW7)/2)) | AY7: =IF((((AV7+AW7)/2)+(C7/(D7*((AV7+AW7)/2)))^2/(2*9.81)+B7-(G6+H6^2/(2*9.81))-(A6-A7)*(((DATOS!$B$34*(C7/(D7*((AV7+AW7)/2)))/((D7*((AV7+AW7)/2))/(D7+2*((AV7+AW7)/2)))^(2/3))^2+((DATOS!$B$34*H6/((D6*F6)/(D6+2*F6))^(2/3))^2))/2))>0,((AV7+AW7)/2),AW7) | AZ7: =IF((((AX7+AY7)/2)+(C7/(D7*((AX7+AY7)/2)))^2/(2*9.81)+B7-(G6+H6^2/(2*9.81))-(A6-A7)*(((DATOS!$B$34*(C7/(D7*((AX7+AY7)/2)))/((D7*((AX7+AY7)/2))/(D7+2*((AX7+AY7)/2)))^(2/3))^2+((DATOS!$B$34*H6/((D6*F6)/(D6+2*F6))^(2/3))^2))/2))>0,AX7,((AX7+AY7)/2)) | BA7: =IF((((AX7+AY7)/2)+(C7/(D7*((AX7+AY7)/2)))^2/(2*9.81)+B7-(G6+H6^2/(2*9.81))-(A6-A7)*(((DATOS!$B$34*(C7/(D7*((AX7+AY7)/2)))/((D7*((AX7+AY7)/2))/(D7+2*((AX7+AY7)/2)))^(2/3))^2+((DATOS!$B$34*H6/((D6*F6)/(D6+2*F6))^(2/3))^2))/2))>0,((AX7+AY7)/2),AY7) | BB7: =IF((((AZ7+BA7)/2)+(C7/(D7*((AZ7+BA7)/2)))^2/(2*9.81)+B7-(G6+H6^2/(2*9.81))-(A6-A7)*(((DATOS!$B$34*(C7/(D7*((AZ7+BA7)/2)))/((D7*((AZ7+BA7)/2))/(D7+2*((AZ7+BA7)/2)))^(2/3))^2+((DATOS!$B$34*H6/((D6*F6)/(D6+2*F6))^(2/3))^2))/2))>0,AZ7,((AZ7+BA7)/2)) | BC7: =IF((((AZ7+BA7)/2)+(C7/(D7*((AZ7+BA7)/2)))^2/(2*9.81)+B7-(G6+H6^2/(2*9.81))-(A6-A7)*(((DATOS!$B$34*(C7/(D7*((AZ7+BA7)/2)))/((D7*((AZ7+BA7)/2))/(D7+2*((AZ7+BA7)/2)))^(2/3))^2+((DATOS!$B$34*H6/((D6*F6)/(D6+2*F6))^(2/3))^2))/2))>0,((AZ7+BA7)/2),BA7) | BD7: =IF((((BB7+BC7)/2)+(C7/(D7*((BB7+BC7)/2)))^2/(2*9.81)+B7-(G6+H6^2/(2*9.81))-(A6-A7)*(((DATOS!$B$34*(C7/(D7*((BB7+BC7)/2)))/((D7*((BB7+BC7)/2))/(D7+2*((BB7+BC7)/2)))^(2/3))^2+((DATOS!$B$34*H6/((D6*F6)/(D6+2*F6))^(2/3))^2))/2))>0,BB7,((BB7+BC7)/2)) | BE7: =IF((((BB7+BC7)/2)+(C7/(D7*((BB7+BC7)/2)))^2/(2*9.81)+B7-(G6+H6^2/(2*9.81))-(A6-A7)*(((DATOS!$B$34*(C7/(D7*((BB7+BC7)/2)))/((D7*((BB7+BC7)/2))/(D7+2*((BB7+BC7)/2)))^(2/3))^2+((DATOS!$B$34*H6/((D6*F6)/(D6+2*F6))^(2/3))^2))/2))>0,((BB7+BC7)/2),BC7) | BF7: =IF((((BD7+BE7)/2)+(C7/(D7*((BD7+BE7)/2)))^2/(2*9.81)+B7-(G6+H6^2/(2*9.81))-(A6-A7)*(((DATOS!$B$34*(C7/(D7*((BD7+BE7)/2)))/((D7*((BD7+BE7)/2))/(D7+2*((BD7+BE7)/2)))^(2/3))^2+((DATOS!$B$34*H6/((D6*F6)/(D6+2*F6))^(2/3))^2))/2))>0,BD7,((BD7+BE7)/2)) | BG7: =IF((((BD7+BE7)/2)+(C7/(D7*((BD7+BE7)/2)))^2/(2*9.81)+B7-(G6+H6^2/(2*9.81))-(A6-A7)*(((DATOS!$B$34*(C7/(D7*((BD7+BE7)/2)))/((D7*((BD7+BE7)/2))/(D7+2*((BD7+BE7)/2)))^(2/3))^2+((DATOS!$B$34*H6/((D6*F6)/(D6+2*F6))^(2/3))^2))/2))>0,((BD7+BE7)/2),BE7) | BH7: =IF((((BF7+BG7)/2)+(C7/(D7*((BF7+BG7)/2)))^2/(2*9.81)+B7-(G6+H6^2/(2*9.81))-(A6-A7)*(((DATOS!$B$34*(C7/(D7*((BF7+BG7)/2)))/((D7*((BF7+BG7)/2))/(D7+2*((BF7+BG7)/2)))^(2/3))^2+((DATOS!$B$34*H6/((D6*F6)/(D6+2*F6))^(2/3))^2))/2))>0,BF7,((BF7+BG7)/2)) | BI7: =IF((((BF7+BG7)/2)+(C7/(D7*((BF7+BG7)/2)))^2/(2*9.81)+B7-(G6+H6^2/(2*9.81))-(A6-A7)*(((DATOS!$B$34*(C7/(D7*((BF7+BG7)/2)))/((D7*((BF7+BG7)/2))/(D7+2*((BF7+BG7)/2)))^(2/3))^2+((DATOS!$B$34*H6/((D6*F6)/(D6+2*F6))^(2/3))^2))/2))>0,((BF7+BG7)/2),BG7) | BJ7: =IF((((BH7+BI7)/2)+(C7/(D7*((BH7+BI7)/2)))^2/(2*9.81)+B7-(G6+H6^2/(2*9.81))-(A6-A7)*(((DATOS!$B$34*(C7/(D7*((BH7+BI7)/2)))/((D7*((BH7+BI7)/2))/(D7+2*((BH7+BI7)/2)))^(2/3))^2+((DATOS!$B$34*H6/((D6*F6)/(D6+2*F6))^(2/3))^2))/2))>0,BH7,((BH7+BI7)/2)) | BK7: =IF((((BH7+BI7)/2)+(C7/(D7*((BH7+BI7)/2)))^2/(2*9.81)+B7-(G6+H6^2/(2*9.81))-(A6-A7)*(((DATOS!$B$34*(C7/(D7*((BH7+BI7)/2)))/((D7*((BH7+BI7)/2))/(D7+2*((BH7+BI7)/2)))^(2/3))^2+((DATOS!$B$34*H6/((D6*F6)/(D6+2*F6))^(2/3))^2))/2))>0,((BH7+BI7)/2),BI7) | BL7: =IF((((BJ7+BK7)/2)+(C7/(D7*((BJ7+BK7)/2)))^2/(2*9.81)+B7-(G6+H6^2/(2*9.81))-(A6-A7)*(((DATOS!$B$34*(C7/(D7*((BJ7+BK7)/2)))/((D7*((BJ7+BK7)/2))/(D7+2*((BJ7+BK7)/2)))^(2/3))^2+((DATOS!$B$34*H6/((D6*F6)/(D6+2*F6))^(2/3))^2))/2))>0,BJ7,((BJ7+BK7)/2)) | BM7: =IF((((BJ7+BK7)/2)+(C7/(D7*((BJ7+BK7)/2)))^2/(2*9.81)+B7-(G6+H6^2/(2*9.81))-(A6-A7)*(((DATOS!$B$34*(C7/(D7*((BJ7+BK7)/2)))/((D7*((BJ7+BK7)/2))/(D7+2*((BJ7+BK7)/2)))^(2/3))^2+((DATOS!$B$34*H6/((D6*F6)/(D6+2*F6))^(2/3))^2))/2))>0,((BJ7+BK7)/2),BK7) | BN7: =IF((((BL7+BM7)/2)+(C7/(D7*((BL7+BM7)/2)))^2/(2*9.81)+B7-(G6+H6^2/(2*9.81))-(A6-A7)*(((DATOS!$B$34*(C7/(D7*((BL7+BM7)/2)))/((D7*((BL7+BM7)/2))/(D7+2*((BL7+BM7)/2)))^(2/3))^2+((DATOS!$B$34*H6/((D6*F6)/(D6+2*F6))^(2/3))^2))/2))>0,BL7,((BL7+BM7)/2)) | BO7: =IF((((BL7+BM7)/2)+(C7/(D7*((BL7+BM7)/2)))^2/(2*9.81)+B7-(G6+H6^2/(2*9.81))-(A6-A7)*(((DATOS!$B$34*(C7/(D7*((BL7+BM7)/2)))/((D7*((BL7+BM7)/2))/(D7+2*((BL7+BM7)/2)))^(2/3))^2+((DATOS!$B$34*H6/((D6*F6)/(D6+2*F6))^(2/3))^2))/2))>0,((BL7+BM7)/2),BM7) | BP7: =IF((((BN7+BO7)/2)+(C7/(D7*((BN7+BO7)/2)))^2/(2*9.81)+B7-(G6+H6^2/(2*9.81))-(A6-A7)*(((DATOS!$B$34*(C7/(D7*((BN7+BO7)/2)))/((D7*((BN7+BO7)/2))/(D7+2*((BN7+BO7)/2)))^(2/3))^2+((DATOS!$B$34*H6/((D6*F6)/(D6+2*F6))^(2/3))^2))/2))>0,BN7,((BN7+BO7)/2)) | BQ7: =IF((((BN7+BO7)/2)+(C7/(D7*((BN7+BO7)/2)))^2/(2*9.81)+B7-(G6+H6^2/(2*9.81))-(A6-A7)*(((DATOS!$B$34*(C7/(D7*((BN7+BO7)/2)))/((D7*((BN7+BO7)/2))/(D7+2*((BN7+BO7)/2)))^(2/3))^2+((DATOS!$B$34*H6/((D6*F6)/(D6+2*F6))^(2/3))^2))/2))>0,((BN7+BO7)/2),BO7) | BR7: =IF((((BP7+BQ7)/2)+(C7/(D7*((BP7+BQ7)/2)))^2/(2*9.81)+B7-(G6+H6^2/(2*9.81))-(A6-A7)*(((DATOS!$B$34*(C7/(D7*((BP7+BQ7)/2)))/((D7*((BP7+BQ7)/2))/(D7+2*((BP7+BQ7)/2)))^(2/3))^2+((DATOS!$B$34*H6/((D6*F6)/(D6+2*F6))^(2/3))^2))/2))>0,BP7,((BP7+BQ7)/2)) | BS7: =IF((((BP7+BQ7)/2)+(C7/(D7*((BP7+BQ7)/2)))^2/(2*9.81)+B7-(G6+H6^2/(2*9.81))-(A6-A7)*(((DATOS!$B$34*(C7/(D7*((BP7+BQ7)/2)))/((D7*((BP7+BQ7)/2))/(D7+2*((BP7+BQ7)/2)))^(2/3))^2+((DATOS!$B$34*H6/((D6*F6)/(D6+2*F6))^(2/3))^2))/2))>0,((BP7+BQ7)/2),BQ7) | BT7: =IF((((BR7+BS7)/2)+(C7/(D7*((BR7+BS7)/2)))^2/(2*9.81)+B7-(G6+H6^2/(2*9.81))-(A6-A7)*(((DATOS!$B$34*(C7/(D7*((BR7+BS7)/2)))/((D7*((BR7+BS7)/2))/(D7+2*((BR7+BS7)/2)))^(2/3))^2+((DATOS!$B$34*H6/((D6*F6)/(D6+2*F6))^(2/3))^2))/2))>0,BR7,((BR7+BS7)/2)) | BU7: =IF((((BR7+BS7)/2)+(C7/(D7*((BR7+BS7)/2)))^2/(2*9.81)+B7-(G6+H6^2/(2*9.81))-(A6-A7)*(((DATOS!$B$34*(C7/(D7*((BR7+BS7)/2)))/((D7*((BR7+BS7)/2))/(D7+2*((BR7+BS7)/2)))^(2/3))^2+((DATOS!$B$34*H6/((D6*F6)/(D6+2*F6))^(2/3))^2))/2))>0,((BR7+BS7)/2),BS7) | BV7: =IF((((BT7+BU7)/2)+(C7/(D7*((BT7+BU7)/2)))^2/(2*9.81)+B7-(G6+H6^2/(2*9.81))-(A6-A7)*(((DATOS!$B$34*(C7/(D7*((BT7+BU7)/2)))/((D7*((BT7+BU7)/2))/(D7+2*((BT7+BU7)/2)))^(2/3))^2+((DATOS!$B$34*H6/((D6*F6)/(D6+2*F6))^(2/3))^2))/2))>0,BT7,((BT7+BU7)/2)) | BW7: =IF((((BT7+BU7)/2)+(C7/(D7*((BT7+BU7)/2)))^2/(2*9.81)+B7-(G6+H6^2/(2*9.81))-(A6-A7)*(((DATOS!$B$34*(C7/(D7*((BT7+BU7)/2)))/((D7*((BT7+BU7)/2))/(D7+2*((BT7+BU7)/2)))^(2/3))^2+((DATOS!$B$34*H6/((D6*F6)/(D6+2*F6))^(2/3))^2))/2))>0,((BT7+BU7)/2),BU7)
A8: 69 | B8: =DATOS!$B$22-DATOS!$B$23*A8 | C8: =CAUDALES!$B$13 | D8: =DATOS!$B$17 | E8: =(C8^2/(9.81*D8^2))^(1/3) | F8: =(BV8+BW8)/2 | G8: =B8+F8 | H8: =C8/(D8*F8) | I8: =H8/SQRT(9.81*F8) | J8: =DATOS!$B$29-IF(AND(A8>=DATOS!$B$30,A8<DATOS!$B$31),DATOS!$B$21,DATOS!$B$20) | K8: =J8-B8 | L8: =F8/K8 | M8: =J8-G8 | N8: =IF(AND(L8<=DATOS!$B$36,M8>=DATOS!$B$37,I8<=1),"CUMPLE","NO CUMPLE") | O8: =IF(AND(A8>=DATOS!$B$30,A8<DATOS!$B$31),"cruce de camiones",IF(AND(A8>=DATOS!$B$32,A8<DATOS!$B$33),"cruce de motos","tramo normal")) | P8: =E8*1.001 | Q8: 3 | R8: =IF((((P8+Q8)/2)+(C8/(D8*((P8+Q8)/2)))^2/(2*9.81)+B8-(G7+H7^2/(2*9.81))-(A7-A8)*(((DATOS!$B$34*(C8/(D8*((P8+Q8)/2)))/((D8*((P8+Q8)/2))/(D8+2*((P8+Q8)/2)))^(2/3))^2+((DATOS!$B$34*H7/((D7*F7)/(D7+2*F7))^(2/3))^2))/2))>0,P8,((P8+Q8)/2)) | S8: =IF((((P8+Q8)/2)+(C8/(D8*((P8+Q8)/2)))^2/(2*9.81)+B8-(G7+H7^2/(2*9.81))-(A7-A8)*(((DATOS!$B$34*(C8/(D8*((P8+Q8)/2)))/((D8*((P8+Q8)/2))/(D8+2*((P8+Q8)/2)))^(2/3))^2+((DATOS!$B$34*H7/((D7*F7)/(D7+2*F7))^(2/3))^2))/2))>0,((P8+Q8)/2),Q8) | T8: =IF((((R8+S8)/2)+(C8/(D8*((R8+S8)/2)))^2/(2*9.81)+B8-(G7+H7^2/(2*9.81))-(A7-A8)*(((DATOS!$B$34*(C8/(D8*((R8+S8)/2)))/((D8*((R8+S8)/2))/(D8+2*((R8+S8)/2)))^(2/3))^2+((DATOS!$B$34*H7/((D7*F7)/(D7+2*F7))^(2/3))^2))/2))>0,R8,((R8+S8)/2)) | U8: =IF((((R8+S8)/2)+(C8/(D8*((R8+S8)/2)))^2/(2*9.81)+B8-(G7+H7^2/(2*9.81))-(A7-A8)*(((DATOS!$B$34*(C8/(D8*((R8+S8)/2)))/((D8*((R8+S8)/2))/(D8+2*((R8+S8)/2)))^(2/3))^2+((DATOS!$B$34*H7/((D7*F7)/(D7+2*F7))^(2/3))^2))/2))>0,((R8+S8)/2),S8) | V8: =IF((((T8+U8)/2)+(C8/(D8*((T8+U8)/2)))^2/(2*9.81)+B8-(G7+H7^2/(2*9.81))-(A7-A8)*(((DATOS!$B$34*(C8/(D8*((T8+U8)/2)))/((D8*((T8+U8)/2))/(D8+2*((T8+U8)/2)))^(2/3))^2+((DATOS!$B$34*H7/((D7*F7)/(D7+2*F7))^(2/3))^2))/2))>0,T8,((T8+U8)/2)) | W8: =IF((((T8+U8)/2)+(C8/(D8*((T8+U8)/2)))^2/(2*9.81)+B8-(G7+H7^2/(2*9.81))-(A7-A8)*(((DATOS!$B$34*(C8/(D8*((T8+U8)/2)))/((D8*((T8+U8)/2))/(D8+2*((T8+U8)/2)))^(2/3))^2+((DATOS!$B$34*H7/((D7*F7)/(D7+2*F7))^(2/3))^2))/2))>0,((T8+U8)/2),U8) | X8: =IF((((V8+W8)/2)+(C8/(D8*((V8+W8)/2)))^2/(2*9.81)+B8-(G7+H7^2/(2*9.81))-(A7-A8)*(((DATOS!$B$34*(C8/(D8*((V8+W8)/2)))/((D8*((V8+W8)/2))/(D8+2*((V8+W8)/2)))^(2/3))^2+((DATOS!$B$34*H7/((D7*F7)/(D7+2*F7))^(2/3))^2))/2))>0,V8,((V8+W8)/2)) | Y8: =IF((((V8+W8)/2)+(C8/(D8*((V8+W8)/2)))^2/(2*9.81)+B8-(G7+H7^2/(2*9.81))-(A7-A8)*(((DATOS!$B$34*(C8/(D8*((V8+W8)/2)))/((D8*((V8+W8)/2))/(D8+2*((V8+W8)/2)))^(2/3))^2+((DATOS!$B$34*H7/((D7*F7)/(D7+2*F7))^(2/3))^2))/2))>0,((V8+W8)/2),W8) | Z8: =IF((((X8+Y8)/2)+(C8/(D8*((X8+Y8)/2)))^2/(2*9.81)+B8-(G7+H7^2/(2*9.81))-(A7-A8)*(((DATOS!$B$34*(C8/(D8*((X8+Y8)/2)))/((D8*((X8+Y8)/2))/(D8+2*((X8+Y8)/2)))^(2/3))^2+((DATOS!$B$34*H7/((D7*F7)/(D7+2*F7))^(2/3))^2))/2))>0,X8,((X8+Y8)/2)) | AA8: =IF((((X8+Y8)/2)+(C8/(D8*((X8+Y8)/2)))^2/(2*9.81)+B8-(G7+H7^2/(2*9.81))-(A7-A8)*(((DATOS!$B$34*(C8/(D8*((X8+Y8)/2)))/((D8*((X8+Y8)/2))/(D8+2*((X8+Y8)/2)))^(2/3))^2+((DATOS!$B$34*H7/((D7*F7)/(D7+2*F7))^(2/3))^2))/2))>0,((X8+Y8)/2),Y8) | AB8: =IF((((Z8+AA8)/2)+(C8/(D8*((Z8+AA8)/2)))^2/(2*9.81)+B8-(G7+H7^2/(2*9.81))-(A7-A8)*(((DATOS!$B$34*(C8/(D8*((Z8+AA8)/2)))/((D8*((Z8+AA8)/2))/(D8+2*((Z8+AA8)/2)))^(2/3))^2+((DATOS!$B$34*H7/((D7*F7)/(D7+2*F7))^(2/3))^2))/2))>0,Z8,((Z8+AA8)/2)) | AC8: =IF((((Z8+AA8)/2)+(C8/(D8*((Z8+AA8)/2)))^2/(2*9.81)+B8-(G7+H7^2/(2*9.81))-(A7-A8)*(((DATOS!$B$34*(C8/(D8*((Z8+AA8)/2)))/((D8*((Z8+AA8)/2))/(D8+2*((Z8+AA8)/2)))^(2/3))^2+((DATOS!$B$34*H7/((D7*F7)/(D7+2*F7))^(2/3))^2))/2))>0,((Z8+AA8)/2),AA8) | AD8: =IF((((AB8+AC8)/2)+(C8/(D8*((AB8+AC8)/2)))^2/(2*9.81)+B8-(G7+H7^2/(2*9.81))-(A7-A8)*(((DATOS!$B$34*(C8/(D8*((AB8+AC8)/2)))/((D8*((AB8+AC8)/2))/(D8+2*((AB8+AC8)/2)))^(2/3))^2+((DATOS!$B$34*H7/((D7*F7)/(D7+2*F7))^(2/3))^2))/2))>0,AB8,((AB8+AC8)/2)) | AE8: =IF((((AB8+AC8)/2)+(C8/(D8*((AB8+AC8)/2)))^2/(2*9.81)+B8-(G7+H7^2/(2*9.81))-(A7-A8)*(((DATOS!$B$34*(C8/(D8*((AB8+AC8)/2)))/((D8*((AB8+AC8)/2))/(D8+2*((AB8+AC8)/2)))^(2/3))^2+((DATOS!$B$34*H7/((D7*F7)/(D7+2*F7))^(2/3))^2))/2))>0,((AB8+AC8)/2),AC8) | AF8: =IF((((AD8+AE8)/2)+(C8/(D8*((AD8+AE8)/2)))^2/(2*9.81)+B8-(G7+H7^2/(2*9.81))-(A7-A8)*(((DATOS!$B$34*(C8/(D8*((AD8+AE8)/2)))/((D8*((AD8+AE8)/2))/(D8+2*((AD8+AE8)/2)))^(2/3))^2+((DATOS!$B$34*H7/((D7*F7)/(D7+2*F7))^(2/3))^2))/2))>0,AD8,((AD8+AE8)/2)) | AG8: =IF((((AD8+AE8)/2)+(C8/(D8*((AD8+AE8)/2)))^2/(2*9.81)+B8-(G7+H7^2/(2*9.81))-(A7-A8)*(((DATOS!$B$34*(C8/(D8*((AD8+AE8)/2)))/((D8*((AD8+AE8)/2))/(D8+2*((AD8+AE8)/2)))^(2/3))^2+((DATOS!$B$34*H7/((D7*F7)/(D7+2*F7))^(2/3))^2))/2))>0,((AD8+AE8)/2),AE8) | AH8: =IF((((AF8+AG8)/2)+(C8/(D8*((AF8+AG8)/2)))^2/(2*9.81)+B8-(G7+H7^2/(2*9.81))-(A7-A8)*(((DATOS!$B$34*(C8/(D8*((AF8+AG8)/2)))/((D8*((AF8+AG8)/2))/(D8+2*((AF8+AG8)/2)))^(2/3))^2+((DATOS!$B$34*H7/((D7*F7)/(D7+2*F7))^(2/3))^2))/2))>0,AF8,((AF8+AG8)/2)) | AI8: =IF((((AF8+AG8)/2)+(C8/(D8*((AF8+AG8)/2)))^2/(2*9.81)+B8-(G7+H7^2/(2*9.81))-(A7-A8)*(((DATOS!$B$34*(C8/(D8*((AF8+AG8)/2)))/((D8*((AF8+AG8)/2))/(D8+2*((AF8+AG8)/2)))^(2/3))^2+((DATOS!$B$34*H7/((D7*F7)/(D7+2*F7))^(2/3))^2))/2))>0,((AF8+AG8)/2),AG8) | AJ8: =IF((((AH8+AI8)/2)+(C8/(D8*((AH8+AI8)/2)))^2/(2*9.81)+B8-(G7+H7^2/(2*9.81))-(A7-A8)*(((DATOS!$B$34*(C8/(D8*((AH8+AI8)/2)))/((D8*((AH8+AI8)/2))/(D8+2*((AH8+AI8)/2)))^(2/3))^2+((DATOS!$B$34*H7/((D7*F7)/(D7+2*F7))^(2/3))^2))/2))>0,AH8,((AH8+AI8)/2)) | AK8: =IF((((AH8+AI8)/2)+(C8/(D8*((AH8+AI8)/2)))^2/(2*9.81)+B8-(G7+H7^2/(2*9.81))-(A7-A8)*(((DATOS!$B$34*(C8/(D8*((AH8+AI8)/2)))/((D8*((AH8+AI8)/2))/(D8+2*((AH8+AI8)/2)))^(2/3))^2+((DATOS!$B$34*H7/((D7*F7)/(D7+2*F7))^(2/3))^2))/2))>0,((AH8+AI8)/2),AI8) | AL8: =IF((((AJ8+AK8)/2)+(C8/(D8*((AJ8+AK8)/2)))^2/(2*9.81)+B8-(G7+H7^2/(2*9.81))-(A7-A8)*(((DATOS!$B$34*(C8/(D8*((AJ8+AK8)/2)))/((D8*((AJ8+AK8)/2))/(D8+2*((AJ8+AK8)/2)))^(2/3))^2+((DATOS!$B$34*H7/((D7*F7)/(D7+2*F7))^(2/3))^2))/2))>0,AJ8,((AJ8+AK8)/2)) | AM8: =IF((((AJ8+AK8)/2)+(C8/(D8*((AJ8+AK8)/2)))^2/(2*9.81)+B8-(G7+H7^2/(2*9.81))-(A7-A8)*(((DATOS!$B$34*(C8/(D8*((AJ8+AK8)/2)))/((D8*((AJ8+AK8)/2))/(D8+2*((AJ8+AK8)/2)))^(2/3))^2+((DATOS!$B$34*H7/((D7*F7)/(D7+2*F7))^(2/3))^2))/2))>0,((AJ8+AK8)/2),AK8) | AN8: =IF((((AL8+AM8)/2)+(C8/(D8*((AL8+AM8)/2)))^2/(2*9.81)+B8-(G7+H7^2/(2*9.81))-(A7-A8)*(((DATOS!$B$34*(C8/(D8*((AL8+AM8)/2)))/((D8*((AL8+AM8)/2))/(D8+2*((AL8+AM8)/2)))^(2/3))^2+((DATOS!$B$34*H7/((D7*F7)/(D7+2*F7))^(2/3))^2))/2))>0,AL8,((AL8+AM8)/2)) | AO8: =IF((((AL8+AM8)/2)+(C8/(D8*((AL8+AM8)/2)))^2/(2*9.81)+B8-(G7+H7^2/(2*9.81))-(A7-A8)*(((DATOS!$B$34*(C8/(D8*((AL8+AM8)/2)))/((D8*((AL8+AM8)/2))/(D8+2*((AL8+AM8)/2)))^(2/3))^2+((DATOS!$B$34*H7/((D7*F7)/(D7+2*F7))^(2/3))^2))/2))>0,((AL8+AM8)/2),AM8) | AP8: =IF((((AN8+AO8)/2)+(C8/(D8*((AN8+AO8)/2)))^2/(2*9.81)+B8-(G7+H7^2/(2*9.81))-(A7-A8)*(((DATOS!$B$34*(C8/(D8*((AN8+AO8)/2)))/((D8*((AN8+AO8)/2))/(D8+2*((AN8+AO8)/2)))^(2/3))^2+((DATOS!$B$34*H7/((D7*F7)/(D7+2*F7))^(2/3))^2))/2))>0,AN8,((AN8+AO8)/2)) | AQ8: =IF((((AN8+AO8)/2)+(C8/(D8*((AN8+AO8)/2)))^2/(2*9.81)+B8-(G7+H7^2/(2*9.81))-(A7-A8)*(((DATOS!$B$34*(C8/(D8*((AN8+AO8)/2)))/((D8*((AN8+AO8)/2))/(D8+2*((AN8+AO8)/2)))^(2/3))^2+((DATOS!$B$34*H7/((D7*F7)/(D7+2*F7))^(2/3))^2))/2))>0,((AN8+AO8)/2),AO8) | AR8: =IF((((AP8+AQ8)/2)+(C8/(D8*((AP8+AQ8)/2)))^2/(2*9.81)+B8-(G7+H7^2/(2*9.81))-(A7-A8)*(((DATOS!$B$34*(C8/(D8*((AP8+AQ8)/2)))/((D8*((AP8+AQ8)/2))/(D8+2*((AP8+AQ8)/2)))^(2/3))^2+((DATOS!$B$34*H7/((D7*F7)/(D7+2*F7))^(2/3))^2))/2))>0,AP8,((AP8+AQ8)/2)) | AS8: =IF((((AP8+AQ8)/2)+(C8/(D8*((AP8+AQ8)/2)))^2/(2*9.81)+B8-(G7+H7^2/(2*9.81))-(A7-A8)*(((DATOS!$B$34*(C8/(D8*((AP8+AQ8)/2)))/((D8*((AP8+AQ8)/2))/(D8+2*((AP8+AQ8)/2)))^(2/3))^2+((DATOS!$B$34*H7/((D7*F7)/(D7+2*F7))^(2/3))^2))/2))>0,((AP8+AQ8)/2),AQ8) | AT8: =IF((((AR8+AS8)/2)+(C8/(D8*((AR8+AS8)/2)))^2/(2*9.81)+B8-(G7+H7^2/(2*9.81))-(A7-A8)*(((DATOS!$B$34*(C8/(D8*((AR8+AS8)/2)))/((D8*((AR8+AS8)/2))/(D8+2*((AR8+AS8)/2)))^(2/3))^2+((DATOS!$B$34*H7/((D7*F7)/(D7+2*F7))^(2/3))^2))/2))>0,AR8,((AR8+AS8)/2)) | AU8: =IF((((AR8+AS8)/2)+(C8/(D8*((AR8+AS8)/2)))^2/(2*9.81)+B8-(G7+H7^2/(2*9.81))-(A7-A8)*(((DATOS!$B$34*(C8/(D8*((AR8+AS8)/2)))/((D8*((AR8+AS8)/2))/(D8+2*((AR8+AS8)/2)))^(2/3))^2+((DATOS!$B$34*H7/((D7*F7)/(D7+2*F7))^(2/3))^2))/2))>0,((AR8+AS8)/2),AS8) | AV8: =IF((((AT8+AU8)/2)+(C8/(D8*((AT8+AU8)/2)))^2/(2*9.81)+B8-(G7+H7^2/(2*9.81))-(A7-A8)*(((DATOS!$B$34*(C8/(D8*((AT8+AU8)/2)))/((D8*((AT8+AU8)/2))/(D8+2*((AT8+AU8)/2)))^(2/3))^2+((DATOS!$B$34*H7/((D7*F7)/(D7+2*F7))^(2/3))^2))/2))>0,AT8,((AT8+AU8)/2)) | AW8: =IF((((AT8+AU8)/2)+(C8/(D8*((AT8+AU8)/2)))^2/(2*9.81)+B8-(G7+H7^2/(2*9.81))-(A7-A8)*(((DATOS!$B$34*(C8/(D8*((AT8+AU8)/2)))/((D8*((AT8+AU8)/2))/(D8+2*((AT8+AU8)/2)))^(2/3))^2+((DATOS!$B$34*H7/((D7*F7)/(D7+2*F7))^(2/3))^2))/2))>0,((AT8+AU8)/2),AU8) | AX8: =IF((((AV8+AW8)/2)+(C8/(D8*((AV8+AW8)/2)))^2/(2*9.81)+B8-(G7+H7^2/(2*9.81))-(A7-A8)*(((DATOS!$B$34*(C8/(D8*((AV8+AW8)/2)))/((D8*((AV8+AW8)/2))/(D8+2*((AV8+AW8)/2)))^(2/3))^2+((DATOS!$B$34*H7/((D7*F7)/(D7+2*F7))^(2/3))^2))/2))>0,AV8,((AV8+AW8)/2)) | AY8: =IF((((AV8+AW8)/2)+(C8/(D8*((AV8+AW8)/2)))^2/(2*9.81)+B8-(G7+H7^2/(2*9.81))-(A7-A8)*(((DATOS!$B$34*(C8/(D8*((AV8+AW8)/2)))/((D8*((AV8+AW8)/2))/(D8+2*((AV8+AW8)/2)))^(2/3))^2+((DATOS!$B$34*H7/((D7*F7)/(D7+2*F7))^(2/3))^2))/2))>0,((AV8+AW8)/2),AW8) | AZ8: =IF((((AX8+AY8)/2)+(C8/(D8*((AX8+AY8)/2)))^2/(2*9.81)+B8-(G7+H7^2/(2*9.81))-(A7-A8)*(((DATOS!$B$34*(C8/(D8*((AX8+AY8)/2)))/((D8*((AX8+AY8)/2))/(D8+2*((AX8+AY8)/2)))^(2/3))^2+((DATOS!$B$34*H7/((D7*F7)/(D7+2*F7))^(2/3))^2))/2))>0,AX8,((AX8+AY8)/2)) | BA8: =IF((((AX8+AY8)/2)+(C8/(D8*((AX8+AY8)/2)))^2/(2*9.81)+B8-(G7+H7^2/(2*9.81))-(A7-A8)*(((DATOS!$B$34*(C8/(D8*((AX8+AY8)/2)))/((D8*((AX8+AY8)/2))/(D8+2*((AX8+AY8)/2)))^(2/3))^2+((DATOS!$B$34*H7/((D7*F7)/(D7+2*F7))^(2/3))^2))/2))>0,((AX8+AY8)/2),AY8) | BB8: =IF((((AZ8+BA8)/2)+(C8/(D8*((AZ8+BA8)/2)))^2/(2*9.81)+B8-(G7+H7^2/(2*9.81))-(A7-A8)*(((DATOS!$B$34*(C8/(D8*((AZ8+BA8)/2)))/((D8*((AZ8+BA8)/2))/(D8+2*((AZ8+BA8)/2)))^(2/3))^2+((DATOS!$B$34*H7/((D7*F7)/(D7+2*F7))^(2/3))^2))/2))>0,AZ8,((AZ8+BA8)/2)) | BC8: =IF((((AZ8+BA8)/2)+(C8/(D8*((AZ8+BA8)/2)))^2/(2*9.81)+B8-(G7+H7^2/(2*9.81))-(A7-A8)*(((DATOS!$B$34*(C8/(D8*((AZ8+BA8)/2)))/((D8*((AZ8+BA8)/2))/(D8+2*((AZ8+BA8)/2)))^(2/3))^2+((DATOS!$B$34*H7/((D7*F7)/(D7+2*F7))^(2/3))^2))/2))>0,((AZ8+BA8)/2),BA8) | BD8: =IF((((BB8+BC8)/2)+(C8/(D8*((BB8+BC8)/2)))^2/(2*9.81)+B8-(G7+H7^2/(2*9.81))-(A7-A8)*(((DATOS!$B$34*(C8/(D8*((BB8+BC8)/2)))/((D8*((BB8+BC8)/2))/(D8+2*((BB8+BC8)/2)))^(2/3))^2+((DATOS!$B$34*H7/((D7*F7)/(D7+2*F7))^(2/3))^2))/2))>0,BB8,((BB8+BC8)/2)) | BE8: =IF((((BB8+BC8)/2)+(C8/(D8*((BB8+BC8)/2)))^2/(2*9.81)+B8-(G7+H7^2/(2*9.81))-(A7-A8)*(((DATOS!$B$34*(C8/(D8*((BB8+BC8)/2)))/((D8*((BB8+BC8)/2))/(D8+2*((BB8+BC8)/2)))^(2/3))^2+((DATOS!$B$34*H7/((D7*F7)/(D7+2*F7))^(2/3))^2))/2))>0,((BB8+BC8)/2),BC8) | BF8: =IF((((BD8+BE8)/2)+(C8/(D8*((BD8+BE8)/2)))^2/(2*9.81)+B8-(G7+H7^2/(2*9.81))-(A7-A8)*(((DATOS!$B$34*(C8/(D8*((BD8+BE8)/2)))/((D8*((BD8+BE8)/2))/(D8+2*((BD8+BE8)/2)))^(2/3))^2+((DATOS!$B$34*H7/((D7*F7)/(D7+2*F7))^(2/3))^2))/2))>0,BD8,((BD8+BE8)/2)) | BG8: =IF((((BD8+BE8)/2)+(C8/(D8*((BD8+BE8)/2)))^2/(2*9.81)+B8-(G7+H7^2/(2*9.81))-(A7-A8)*(((DATOS!$B$34*(C8/(D8*((BD8+BE8)/2)))/((D8*((BD8+BE8)/2))/(D8+2*((BD8+BE8)/2)))^(2/3))^2+((DATOS!$B$34*H7/((D7*F7)/(D7+2*F7))^(2/3))^2))/2))>0,((BD8+BE8)/2),BE8) | BH8: =IF((((BF8+BG8)/2)+(C8/(D8*((BF8+BG8)/2)))^2/(2*9.81)+B8-(G7+H7^2/(2*9.81))-(A7-A8)*(((DATOS!$B$34*(C8/(D8*((BF8+BG8)/2)))/((D8*((BF8+BG8)/2))/(D8+2*((BF8+BG8)/2)))^(2/3))^2+((DATOS!$B$34*H7/((D7*F7)/(D7+2*F7))^(2/3))^2))/2))>0,BF8,((BF8+BG8)/2)) | BI8: =IF((((BF8+BG8)/2)+(C8/(D8*((BF8+BG8)/2)))^2/(2*9.81)+B8-(G7+H7^2/(2*9.81))-(A7-A8)*(((DATOS!$B$34*(C8/(D8*((BF8+BG8)/2)))/((D8*((BF8+BG8)/2))/(D8+2*((BF8+BG8)/2)))^(2/3))^2+((DATOS!$B$34*H7/((D7*F7)/(D7+2*F7))^(2/3))^2))/2))>0,((BF8+BG8)/2),BG8) | BJ8: =IF((((BH8+BI8)/2)+(C8/(D8*((BH8+BI8)/2)))^2/(2*9.81)+B8-(G7+H7^2/(2*9.81))-(A7-A8)*(((DATOS!$B$34*(C8/(D8*((BH8+BI8)/2)))/((D8*((BH8+BI8)/2))/(D8+2*((BH8+BI8)/2)))^(2/3))^2+((DATOS!$B$34*H7/((D7*F7)/(D7+2*F7))^(2/3))^2))/2))>0,BH8,((BH8+BI8)/2)) | BK8: =IF((((BH8+BI8)/2)+(C8/(D8*((BH8+BI8)/2)))^2/(2*9.81)+B8-(G7+H7^2/(2*9.81))-(A7-A8)*(((DATOS!$B$34*(C8/(D8*((BH8+BI8)/2)))/((D8*((BH8+BI8)/2))/(D8+2*((BH8+BI8)/2)))^(2/3))^2+((DATOS!$B$34*H7/((D7*F7)/(D7+2*F7))^(2/3))^2))/2))>0,((BH8+BI8)/2),BI8) | BL8: =IF((((BJ8+BK8)/2)+(C8/(D8*((BJ8+BK8)/2)))^2/(2*9.81)+B8-(G7+H7^2/(2*9.81))-(A7-A8)*(((DATOS!$B$34*(C8/(D8*((BJ8+BK8)/2)))/((D8*((BJ8+BK8)/2))/(D8+2*((BJ8+BK8)/2)))^(2/3))^2+((DATOS!$B$34*H7/((D7*F7)/(D7+2*F7))^(2/3))^2))/2))>0,BJ8,((BJ8+BK8)/2)) | BM8: =IF((((BJ8+BK8)/2)+(C8/(D8*((BJ8+BK8)/2)))^2/(2*9.81)+B8-(G7+H7^2/(2*9.81))-(A7-A8)*(((DATOS!$B$34*(C8/(D8*((BJ8+BK8)/2)))/((D8*((BJ8+BK8)/2))/(D8+2*((BJ8+BK8)/2)))^(2/3))^2+((DATOS!$B$34*H7/((D7*F7)/(D7+2*F7))^(2/3))^2))/2))>0,((BJ8+BK8)/2),BK8) | BN8: =IF((((BL8+BM8)/2)+(C8/(D8*((BL8+BM8)/2)))^2/(2*9.81)+B8-(G7+H7^2/(2*9.81))-(A7-A8)*(((DATOS!$B$34*(C8/(D8*((BL8+BM8)/2)))/((D8*((BL8+BM8)/2))/(D8+2*((BL8+BM8)/2)))^(2/3))^2+((DATOS!$B$34*H7/((D7*F7)/(D7+2*F7))^(2/3))^2))/2))>0,BL8,((BL8+BM8)/2)) | BO8: =IF((((BL8+BM8)/2)+(C8/(D8*((BL8+BM8)/2)))^2/(2*9.81)+B8-(G7+H7^2/(2*9.81))-(A7-A8)*(((DATOS!$B$34*(C8/(D8*((BL8+BM8)/2)))/((D8*((BL8+BM8)/2))/(D8+2*((BL8+BM8)/2)))^(2/3))^2+((DATOS!$B$34*H7/((D7*F7)/(D7+2*F7))^(2/3))^2))/2))>0,((BL8+BM8)/2),BM8) | BP8: =IF((((BN8+BO8)/2)+(C8/(D8*((BN8+BO8)/2)))^2/(2*9.81)+B8-(G7+H7^2/(2*9.81))-(A7-A8)*(((DATOS!$B$34*(C8/(D8*((BN8+BO8)/2)))/((D8*((BN8+BO8)/2))/(D8+2*((BN8+BO8)/2)))^(2/3))^2+((DATOS!$B$34*H7/((D7*F7)/(D7+2*F7))^(2/3))^2))/2))>0,BN8,((BN8+BO8)/2)) | BQ8: =IF((((BN8+BO8)/2)+(C8/(D8*((BN8+BO8)/2)))^2/(2*9.81)+B8-(G7+H7^2/(2*9.81))-(A7-A8)*(((DATOS!$B$34*(C8/(D8*((BN8+BO8)/2)))/((D8*((BN8+BO8)/2))/(D8+2*((BN8+BO8)/2)))^(2/3))^2+((DATOS!$B$34*H7/((D7*F7)/(D7+2*F7))^(2/3))^2))/2))>0,((BN8+BO8)/2),BO8) | BR8: =IF((((BP8+BQ8)/2)+(C8/(D8*((BP8+BQ8)/2)))^2/(2*9.81)+B8-(G7+H7^2/(2*9.81))-(A7-A8)*(((DATOS!$B$34*(C8/(D8*((BP8+BQ8)/2)))/((D8*((BP8+BQ8)/2))/(D8+2*((BP8+BQ8)/2)))^(2/3))^2+((DATOS!$B$34*H7/((D7*F7)/(D7+2*F7))^(2/3))^2))/2))>0,BP8,((BP8+BQ8)/2)) | BS8: =IF((((BP8+BQ8)/2)+(C8/(D8*((BP8+BQ8)/2)))^2/(2*9.81)+B8-(G7+H7^2/(2*9.81))-(A7-A8)*(((DATOS!$B$34*(C8/(D8*((BP8+BQ8)/2)))/((D8*((BP8+BQ8)/2))/(D8+2*((BP8+BQ8)/2)))^(2/3))^2+((DATOS!$B$34*H7/((D7*F7)/(D7+2*F7))^(2/3))^2))/2))>0,((BP8+BQ8)/2),BQ8) | BT8: =IF((((BR8+BS8)/2)+(C8/(D8*((BR8+BS8)/2)))^2/(2*9.81)+B8-(G7+H7^2/(2*9.81))-(A7-A8)*(((DATOS!$B$34*(C8/(D8*((BR8+BS8)/2)))/((D8*((BR8+BS8)/2))/(D8+2*((BR8+BS8)/2)))^(2/3))^2+((DATOS!$B$34*H7/((D7*F7)/(D7+2*F7))^(2/3))^2))/2))>0,BR8,((BR8+BS8)/2)) | BU8: =IF((((BR8+BS8)/2)+(C8/(D8*((BR8+BS8)/2)))^2/(2*9.81)+B8-(G7+H7^2/(2*9.81))-(A7-A8)*(((DATOS!$B$34*(C8/(D8*((BR8+BS8)/2)))/((D8*((BR8+BS8)/2))/(D8+2*((BR8+BS8)/2)))^(2/3))^2+((DATOS!$B$34*H7/((D7*F7)/(D7+2*F7))^(2/3))^2))/2))>0,((BR8+BS8)/2),BS8) | BV8: =IF((((BT8+BU8)/2)+(C8/(D8*((BT8+BU8)/2)))^2/(2*9.81)+B8-(G7+H7^2/(2*9.81))-(A7-A8)*(((DATOS!$B$34*(C8/(D8*((BT8+BU8)/2)))/((D8*((BT8+BU8)/2))/(D8+2*((BT8+BU8)/2)))^(2/3))^2+((DATOS!$B$34*H7/((D7*F7)/(D7+2*F7))^(2/3))^2))/2))>0,BT8,((BT8+BU8)/2)) | BW8: =IF((((BT8+BU8)/2)+(C8/(D8*((BT8+BU8)/2)))^2/(2*9.81)+B8-(G7+H7^2/(2*9.81))-(A7-A8)*(((DATOS!$B$34*(C8/(D8*((BT8+BU8)/2)))/((D8*((BT8+BU8)/2))/(D8+2*((BT8+BU8)/2)))^(2/3))^2+((DATOS!$B$34*H7/((D7*F7)/(D7+2*F7))^(2/3))^2))/2))>0,((BT8+BU8)/2),BU8)
A9: 68 | B9: =DATOS!$B$22-DATOS!$B$23*A9 | C9: =CAUDALES!$B$13 | D9: =DATOS!$B$17 | E9: =(C9^2/(9.81*D9^2))^(1/3) | F9: =(BV9+BW9)/2 | G9: =B9+F9 | H9: =C9/(D9*F9) | I9: =H9/SQRT(9.81*F9) | J9: =DATOS!$B$29-IF(AND(A9>=DATOS!$B$30,A9<DATOS!$B$31),DATOS!$B$21,DATOS!$B$20) | K9: =J9-B9 | L9: =F9/K9 | M9: =J9-G9 | N9: =IF(AND(L9<=DATOS!$B$36,M9>=DATOS!$B$37,I9<=1),"CUMPLE","NO CUMPLE") | O9: =IF(AND(A9>=DATOS!$B$30,A9<DATOS!$B$31),"cruce de camiones",IF(AND(A9>=DATOS!$B$32,A9<DATOS!$B$33),"cruce de motos","tramo normal")) | P9: =E9*1.001 | Q9: 3 | R9: =IF((((P9+Q9)/2)+(C9/(D9*((P9+Q9)/2)))^2/(2*9.81)+B9-(G8+H8^2/(2*9.81))-(A8-A9)*(((DATOS!$B$34*(C9/(D9*((P9+Q9)/2)))/((D9*((P9+Q9)/2))/(D9+2*((P9+Q9)/2)))^(2/3))^2+((DATOS!$B$34*H8/((D8*F8)/(D8+2*F8))^(2/3))^2))/2))>0,P9,((P9+Q9)/2)) | S9: =IF((((P9+Q9)/2)+(C9/(D9*((P9+Q9)/2)))^2/(2*9.81)+B9-(G8+H8^2/(2*9.81))-(A8-A9)*(((DATOS!$B$34*(C9/(D9*((P9+Q9)/2)))/((D9*((P9+Q9)/2))/(D9+2*((P9+Q9)/2)))^(2/3))^2+((DATOS!$B$34*H8/((D8*F8)/(D8+2*F8))^(2/3))^2))/2))>0,((P9+Q9)/2),Q9) | T9: =IF((((R9+S9)/2)+(C9/(D9*((R9+S9)/2)))^2/(2*9.81)+B9-(G8+H8^2/(2*9.81))-(A8-A9)*(((DATOS!$B$34*(C9/(D9*((R9+S9)/2)))/((D9*((R9+S9)/2))/(D9+2*((R9+S9)/2)))^(2/3))^2+((DATOS!$B$34*H8/((D8*F8)/(D8+2*F8))^(2/3))^2))/2))>0,R9,((R9+S9)/2)) | U9: =IF((((R9+S9)/2)+(C9/(D9*((R9+S9)/2)))^2/(2*9.81)+B9-(G8+H8^2/(2*9.81))-(A8-A9)*(((DATOS!$B$34*(C9/(D9*((R9+S9)/2)))/((D9*((R9+S9)/2))/(D9+2*((R9+S9)/2)))^(2/3))^2+((DATOS!$B$34*H8/((D8*F8)/(D8+2*F8))^(2/3))^2))/2))>0,((R9+S9)/2),S9) | V9: =IF((((T9+U9)/2)+(C9/(D9*((T9+U9)/2)))^2/(2*9.81)+B9-(G8+H8^2/(2*9.81))-(A8-A9)*(((DATOS!$B$34*(C9/(D9*((T9+U9)/2)))/((D9*((T9+U9)/2))/(D9+2*((T9+U9)/2)))^(2/3))^2+((DATOS!$B$34*H8/((D8*F8)/(D8+2*F8))^(2/3))^2))/2))>0,T9,((T9+U9)/2)) | W9: =IF((((T9+U9)/2)+(C9/(D9*((T9+U9)/2)))^2/(2*9.81)+B9-(G8+H8^2/(2*9.81))-(A8-A9)*(((DATOS!$B$34*(C9/(D9*((T9+U9)/2)))/((D9*((T9+U9)/2))/(D9+2*((T9+U9)/2)))^(2/3))^2+((DATOS!$B$34*H8/((D8*F8)/(D8+2*F8))^(2/3))^2))/2))>0,((T9+U9)/2),U9) | X9: =IF((((V9+W9)/2)+(C9/(D9*((V9+W9)/2)))^2/(2*9.81)+B9-(G8+H8^2/(2*9.81))-(A8-A9)*(((DATOS!$B$34*(C9/(D9*((V9+W9)/2)))/((D9*((V9+W9)/2))/(D9+2*((V9+W9)/2)))^(2/3))^2+((DATOS!$B$34*H8/((D8*F8)/(D8+2*F8))^(2/3))^2))/2))>0,V9,((V9+W9)/2)) | Y9: =IF((((V9+W9)/2)+(C9/(D9*((V9+W9)/2)))^2/(2*9.81)+B9-(G8+H8^2/(2*9.81))-(A8-A9)*(((DATOS!$B$34*(C9/(D9*((V9+W9)/2)))/((D9*((V9+W9)/2))/(D9+2*((V9+W9)/2)))^(2/3))^2+((DATOS!$B$34*H8/((D8*F8)/(D8+2*F8))^(2/3))^2))/2))>0,((V9+W9)/2),W9) | Z9: =IF((((X9+Y9)/2)+(C9/(D9*((X9+Y9)/2)))^2/(2*9.81)+B9-(G8+H8^2/(2*9.81))-(A8-A9)*(((DATOS!$B$34*(C9/(D9*((X9+Y9)/2)))/((D9*((X9+Y9)/2))/(D9+2*((X9+Y9)/2)))^(2/3))^2+((DATOS!$B$34*H8/((D8*F8)/(D8+2*F8))^(2/3))^2))/2))>0,X9,((X9+Y9)/2)) | AA9: =IF((((X9+Y9)/2)+(C9/(D9*((X9+Y9)/2)))^2/(2*9.81)+B9-(G8+H8^2/(2*9.81))-(A8-A9)*(((DATOS!$B$34*(C9/(D9*((X9+Y9)/2)))/((D9*((X9+Y9)/2))/(D9+2*((X9+Y9)/2)))^(2/3))^2+((DATOS!$B$34*H8/((D8*F8)/(D8+2*F8))^(2/3))^2))/2))>0,((X9+Y9)/2),Y9) | AB9: =IF((((Z9+AA9)/2)+(C9/(D9*((Z9+AA9)/2)))^2/(2*9.81)+B9-(G8+H8^2/(2*9.81))-(A8-A9)*(((DATOS!$B$34*(C9/(D9*((Z9+AA9)/2)))/((D9*((Z9+AA9)/2))/(D9+2*((Z9+AA9)/2)))^(2/3))^2+((DATOS!$B$34*H8/((D8*F8)/(D8+2*F8))^(2/3))^2))/2))>0,Z9,((Z9+AA9)/2)) | AC9: =IF((((Z9+AA9)/2)+(C9/(D9*((Z9+AA9)/2)))^2/(2*9.81)+B9-(G8+H8^2/(2*9.81))-(A8-A9)*(((DATOS!$B$34*(C9/(D9*((Z9+AA9)/2)))/((D9*((Z9+AA9)/2))/(D9+2*((Z9+AA9)/2)))^(2/3))^2+((DATOS!$B$34*H8/((D8*F8)/(D8+2*F8))^(2/3))^2))/2))>0,((Z9+AA9)/2),AA9) | AD9: =IF((((AB9+AC9)/2)+(C9/(D9*((AB9+AC9)/2)))^2/(2*9.81)+B9-(G8+H8^2/(2*9.81))-(A8-A9)*(((DATOS!$B$34*(C9/(D9*((AB9+AC9)/2)))/((D9*((AB9+AC9)/2))/(D9+2*((AB9+AC9)/2)))^(2/3))^2+((DATOS!$B$34*H8/((D8*F8)/(D8+2*F8))^(2/3))^2))/2))>0,AB9,((AB9+AC9)/2)) | AE9: =IF((((AB9+AC9)/2)+(C9/(D9*((AB9+AC9)/2)))^2/(2*9.81)+B9-(G8+H8^2/(2*9.81))-(A8-A9)*(((DATOS!$B$34*(C9/(D9*((AB9+AC9)/2)))/((D9*((AB9+AC9)/2))/(D9+2*((AB9+AC9)/2)))^(2/3))^2+((DATOS!$B$34*H8/((D8*F8)/(D8+2*F8))^(2/3))^2))/2))>0,((AB9+AC9)/2),AC9) | AF9: =IF((((AD9+AE9)/2)+(C9/(D9*((AD9+AE9)/2)))^2/(2*9.81)+B9-(G8+H8^2/(2*9.81))-(A8-A9)*(((DATOS!$B$34*(C9/(D9*((AD9+AE9)/2)))/((D9*((AD9+AE9)/2))/(D9+2*((AD9+AE9)/2)))^(2/3))^2+((DATOS!$B$34*H8/((D8*F8)/(D8+2*F8))^(2/3))^2))/2))>0,AD9,((AD9+AE9)/2)) | AG9: =IF((((AD9+AE9)/2)+(C9/(D9*((AD9+AE9)/2)))^2/(2*9.81)+B9-(G8+H8^2/(2*9.81))-(A8-A9)*(((DATOS!$B$34*(C9/(D9*((AD9+AE9)/2)))/((D9*((AD9+AE9)/2))/(D9+2*((AD9+AE9)/2)))^(2/3))^2+((DATOS!$B$34*H8/((D8*F8)/(D8+2*F8))^(2/3))^2))/2))>0,((AD9+AE9)/2),AE9) | AH9: =IF((((AF9+AG9)/2)+(C9/(D9*((AF9+AG9)/2)))^2/(2*9.81)+B9-(G8+H8^2/(2*9.81))-(A8-A9)*(((DATOS!$B$34*(C9/(D9*((AF9+AG9)/2)))/((D9*((AF9+AG9)/2))/(D9+2*((AF9+AG9)/2)))^(2/3))^2+((DATOS!$B$34*H8/((D8*F8)/(D8+2*F8))^(2/3))^2))/2))>0,AF9,((AF9+AG9)/2)) | AI9: =IF((((AF9+AG9)/2)+(C9/(D9*((AF9+AG9)/2)))^2/(2*9.81)+B9-(G8+H8^2/(2*9.81))-(A8-A9)*(((DATOS!$B$34*(C9/(D9*((AF9+AG9)/2)))/((D9*((AF9+AG9)/2))/(D9+2*((AF9+AG9)/2)))^(2/3))^2+((DATOS!$B$34*H8/((D8*F8)/(D8+2*F8))^(2/3))^2))/2))>0,((AF9+AG9)/2),AG9) | AJ9: =IF((((AH9+AI9)/2)+(C9/(D9*((AH9+AI9)/2)))^2/(2*9.81)+B9-(G8+H8^2/(2*9.81))-(A8-A9)*(((DATOS!$B$34*(C9/(D9*((AH9+AI9)/2)))/((D9*((AH9+AI9)/2))/(D9+2*((AH9+AI9)/2)))^(2/3))^2+((DATOS!$B$34*H8/((D8*F8)/(D8+2*F8))^(2/3))^2))/2))>0,AH9,((AH9+AI9)/2)) | AK9: =IF((((AH9+AI9)/2)+(C9/(D9*((AH9+AI9)/2)))^2/(2*9.81)+B9-(G8+H8^2/(2*9.81))-(A8-A9)*(((DATOS!$B$34*(C9/(D9*((AH9+AI9)/2)))/((D9*((AH9+AI9)/2))/(D9+2*((AH9+AI9)/2)))^(2/3))^2+((DATOS!$B$34*H8/((D8*F8)/(D8+2*F8))^(2/3))^2))/2))>0,((AH9+AI9)/2),AI9) | AL9: =IF((((AJ9+AK9)/2)+(C9/(D9*((AJ9+AK9)/2)))^2/(2*9.81)+B9-(G8+H8^2/(2*9.81))-(A8-A9)*(((DATOS!$B$34*(C9/(D9*((AJ9+AK9)/2)))/((D9*((AJ9+AK9)/2))/(D9+2*((AJ9+AK9)/2)))^(2/3))^2+((DATOS!$B$34*H8/((D8*F8)/(D8+2*F8))^(2/3))^2))/2))>0,AJ9,((AJ9+AK9)/2)) | AM9: =IF((((AJ9+AK9)/2)+(C9/(D9*((AJ9+AK9)/2)))^2/(2*9.81)+B9-(G8+H8^2/(2*9.81))-(A8-A9)*(((DATOS!$B$34*(C9/(D9*((AJ9+AK9)/2)))/((D9*((AJ9+AK9)/2))/(D9+2*((AJ9+AK9)/2)))^(2/3))^2+((DATOS!$B$34*H8/((D8*F8)/(D8+2*F8))^(2/3))^2))/2))>0,((AJ9+AK9)/2),AK9) | AN9: =IF((((AL9+AM9)/2)+(C9/(D9*((AL9+AM9)/2)))^2/(2*9.81)+B9-(G8+H8^2/(2*9.81))-(A8-A9)*(((DATOS!$B$34*(C9/(D9*((AL9+AM9)/2)))/((D9*((AL9+AM9)/2))/(D9+2*((AL9+AM9)/2)))^(2/3))^2+((DATOS!$B$34*H8/((D8*F8)/(D8+2*F8))^(2/3))^2))/2))>0,AL9,((AL9+AM9)/2)) | AO9: =IF((((AL9+AM9)/2)+(C9/(D9*((AL9+AM9)/2)))^2/(2*9.81)+B9-(G8+H8^2/(2*9.81))-(A8-A9)*(((DATOS!$B$34*(C9/(D9*((AL9+AM9)/2)))/((D9*((AL9+AM9)/2))/(D9+2*((AL9+AM9)/2)))^(2/3))^2+((DATOS!$B$34*H8/((D8*F8)/(D8+2*F8))^(2/3))^2))/2))>0,((AL9+AM9)/2),AM9) | AP9: =IF((((AN9+AO9)/2)+(C9/(D9*((AN9+AO9)/2)))^2/(2*9.81)+B9-(G8+H8^2/(2*9.81))-(A8-A9)*(((DATOS!$B$34*(C9/(D9*((AN9+AO9)/2)))/((D9*((AN9+AO9)/2))/(D9+2*((AN9+AO9)/2)))^(2/3))^2+((DATOS!$B$34*H8/((D8*F8)/(D8+2*F8))^(2/3))^2))/2))>0,AN9,((AN9+AO9)/2)) | AQ9: =IF((((AN9+AO9)/2)+(C9/(D9*((AN9+AO9)/2)))^2/(2*9.81)+B9-(G8+H8^2/(2*9.81))-(A8-A9)*(((DATOS!$B$34*(C9/(D9*((AN9+AO9)/2)))/((D9*((AN9+AO9)/2))/(D9+2*((AN9+AO9)/2)))^(2/3))^2+((DATOS!$B$34*H8/((D8*F8)/(D8+2*F8))^(2/3))^2))/2))>0,((AN9+AO9)/2),AO9) | AR9: =IF((((AP9+AQ9)/2)+(C9/(D9*((AP9+AQ9)/2)))^2/(2*9.81)+B9-(G8+H8^2/(2*9.81))-(A8-A9)*(((DATOS!$B$34*(C9/(D9*((AP9+AQ9)/2)))/((D9*((AP9+AQ9)/2))/(D9+2*((AP9+AQ9)/2)))^(2/3))^2+((DATOS!$B$34*H8/((D8*F8)/(D8+2*F8))^(2/3))^2))/2))>0,AP9,((AP9+AQ9)/2)) | AS9: =IF((((AP9+AQ9)/2)+(C9/(D9*((AP9+AQ9)/2)))^2/(2*9.81)+B9-(G8+H8^2/(2*9.81))-(A8-A9)*(((DATOS!$B$34*(C9/(D9*((AP9+AQ9)/2)))/((D9*((AP9+AQ9)/2))/(D9+2*((AP9+AQ9)/2)))^(2/3))^2+((DATOS!$B$34*H8/((D8*F8)/(D8+2*F8))^(2/3))^2))/2))>0,((AP9+AQ9)/2),AQ9) | AT9: =IF((((AR9+AS9)/2)+(C9/(D9*((AR9+AS9)/2)))^2/(2*9.81)+B9-(G8+H8^2/(2*9.81))-(A8-A9)*(((DATOS!$B$34*(C9/(D9*((AR9+AS9)/2)))/((D9*((AR9+AS9)/2))/(D9+2*((AR9+AS9)/2)))^(2/3))^2+((DATOS!$B$34*H8/((D8*F8)/(D8+2*F8))^(2/3))^2))/2))>0,AR9,((AR9+AS9)/2)) | AU9: =IF((((AR9+AS9)/2)+(C9/(D9*((AR9+AS9)/2)))^2/(2*9.81)+B9-(G8+H8^2/(2*9.81))-(A8-A9)*(((DATOS!$B$34*(C9/(D9*((AR9+AS9)/2)))/((D9*((AR9+AS9)/2))/(D9+2*((AR9+AS9)/2)))^(2/3))^2+((DATOS!$B$34*H8/((D8*F8)/(D8+2*F8))^(2/3))^2))/2))>0,((AR9+AS9)/2),AS9) | AV9: =IF((((AT9+AU9)/2)+(C9/(D9*((AT9+AU9)/2)))^2/(2*9.81)+B9-(G8+H8^2/(2*9.81))-(A8-A9)*(((DATOS!$B$34*(C9/(D9*((AT9+AU9)/2)))/((D9*((AT9+AU9)/2))/(D9+2*((AT9+AU9)/2)))^(2/3))^2+((DATOS!$B$34*H8/((D8*F8)/(D8+2*F8))^(2/3))^2))/2))>0,AT9,((AT9+AU9)/2)) | AW9: =IF((((AT9+AU9)/2)+(C9/(D9*((AT9+AU9)/2)))^2/(2*9.81)+B9-(G8+H8^2/(2*9.81))-(A8-A9)*(((DATOS!$B$34*(C9/(D9*((AT9+AU9)/2)))/((D9*((AT9+AU9)/2))/(D9+2*((AT9+AU9)/2)))^(2/3))^2+((DATOS!$B$34*H8/((D8*F8)/(D8+2*F8))^(2/3))^2))/2))>0,((AT9+AU9)/2),AU9) | AX9: =IF((((AV9+AW9)/2)+(C9/(D9*((AV9+AW9)/2)))^2/(2*9.81)+B9-(G8+H8^2/(2*9.81))-(A8-A9)*(((DATOS!$B$34*(C9/(D9*((AV9+AW9)/2)))/((D9*((AV9+AW9)/2))/(D9+2*((AV9+AW9)/2)))^(2/3))^2+((DATOS!$B$34*H8/((D8*F8)/(D8+2*F8))^(2/3))^2))/2))>0,AV9,((AV9+AW9)/2)) | AY9: =IF((((AV9+AW9)/2)+(C9/(D9*((AV9+AW9)/2)))^2/(2*9.81)+B9-(G8+H8^2/(2*9.81))-(A8-A9)*(((DATOS!$B$34*(C9/(D9*((AV9+AW9)/2)))/((D9*((AV9+AW9)/2))/(D9+2*((AV9+AW9)/2)))^(2/3))^2+((DATOS!$B$34*H8/((D8*F8)/(D8+2*F8))^(2/3))^2))/2))>0,((AV9+AW9)/2),AW9) | AZ9: =IF((((AX9+AY9)/2)+(C9/(D9*((AX9+AY9)/2)))^2/(2*9.81)+B9-(G8+H8^2/(2*9.81))-(A8-A9)*(((DATOS!$B$34*(C9/(D9*((AX9+AY9)/2)))/((D9*((AX9+AY9)/2))/(D9+2*((AX9+AY9)/2)))^(2/3))^2+((DATOS!$B$34*H8/((D8*F8)/(D8+2*F8))^(2/3))^2))/2))>0,AX9,((AX9+AY9)/2)) | BA9: =IF((((AX9+AY9)/2)+(C9/(D9*((AX9+AY9)/2)))^2/(2*9.81)+B9-(G8+H8^2/(2*9.81))-(A8-A9)*(((DATOS!$B$34*(C9/(D9*((AX9+AY9)/2)))/((D9*((AX9+AY9)/2))/(D9+2*((AX9+AY9)/2)))^(2/3))^2+((DATOS!$B$34*H8/((D8*F8)/(D8+2*F8))^(2/3))^2))/2))>0,((AX9+AY9)/2),AY9) | BB9: =IF((((AZ9+BA9)/2)+(C9/(D9*((AZ9+BA9)/2)))^2/(2*9.81)+B9-(G8+H8^2/(2*9.81))-(A8-A9)*(((DATOS!$B$34*(C9/(D9*((AZ9+BA9)/2)))/((D9*((AZ9+BA9)/2))/(D9+2*((AZ9+BA9)/2)))^(2/3))^2+((DATOS!$B$34*H8/((D8*F8)/(D8+2*F8))^(2/3))^2))/2))>0,AZ9,((AZ9+BA9)/2)) | BC9: =IF((((AZ9+BA9)/2)+(C9/(D9*((AZ9+BA9)/2)))^2/(2*9.81)+B9-(G8+H8^2/(2*9.81))-(A8-A9)*(((DATOS!$B$34*(C9/(D9*((AZ9+BA9)/2)))/((D9*((AZ9+BA9)/2))/(D9+2*((AZ9+BA9)/2)))^(2/3))^2+((DATOS!$B$34*H8/((D8*F8)/(D8+2*F8))^(2/3))^2))/2))>0,((AZ9+BA9)/2),BA9) | BD9: =IF((((BB9+BC9)/2)+(C9/(D9*((BB9+BC9)/2)))^2/(2*9.81)+B9-(G8+H8^2/(2*9.81))-(A8-A9)*(((DATOS!$B$34*(C9/(D9*((BB9+BC9)/2)))/((D9*((BB9+BC9)/2))/(D9+2*((BB9+BC9)/2)))^(2/3))^2+((DATOS!$B$34*H8/((D8*F8)/(D8+2*F8))^(2/3))^2))/2))>0,BB9,((BB9+BC9)/2)) | BE9: =IF((((BB9+BC9)/2)+(C9/(D9*((BB9+BC9)/2)))^2/(2*9.81)+B9-(G8+H8^2/(2*9.81))-(A8-A9)*(((DATOS!$B$34*(C9/(D9*((BB9+BC9)/2)))/((D9*((BB9+BC9)/2))/(D9+2*((BB9+BC9)/2)))^(2/3))^2+((DATOS!$B$34*H8/((D8*F8)/(D8+2*F8))^(2/3))^2))/2))>0,((BB9+BC9)/2),BC9) | BF9: =IF((((BD9+BE9)/2)+(C9/(D9*((BD9+BE9)/2)))^2/(2*9.81)+B9-(G8+H8^2/(2*9.81))-(A8-A9)*(((DATOS!$B$34*(C9/(D9*((BD9+BE9)/2)))/((D9*((BD9+BE9)/2))/(D9+2*((BD9+BE9)/2)))^(2/3))^2+((DATOS!$B$34*H8/((D8*F8)/(D8+2*F8))^(2/3))^2))/2))>0,BD9,((BD9+BE9)/2)) | BG9: =IF((((BD9+BE9)/2)+(C9/(D9*((BD9+BE9)/2)))^2/(2*9.81)+B9-(G8+H8^2/(2*9.81))-(A8-A9)*(((DATOS!$B$34*(C9/(D9*((BD9+BE9)/2)))/((D9*((BD9+BE9)/2))/(D9+2*((BD9+BE9)/2)))^(2/3))^2+((DATOS!$B$34*H8/((D8*F8)/(D8+2*F8))^(2/3))^2))/2))>0,((BD9+BE9)/2),BE9) | BH9: =IF((((BF9+BG9)/2)+(C9/(D9*((BF9+BG9)/2)))^2/(2*9.81)+B9-(G8+H8^2/(2*9.81))-(A8-A9)*(((DATOS!$B$34*(C9/(D9*((BF9+BG9)/2)))/((D9*((BF9+BG9)/2))/(D9+2*((BF9+BG9)/2)))^(2/3))^2+((DATOS!$B$34*H8/((D8*F8)/(D8+2*F8))^(2/3))^2))/2))>0,BF9,((BF9+BG9)/2)) | BI9: =IF((((BF9+BG9)/2)+(C9/(D9*((BF9+BG9)/2)))^2/(2*9.81)+B9-(G8+H8^2/(2*9.81))-(A8-A9)*(((DATOS!$B$34*(C9/(D9*((BF9+BG9)/2)))/((D9*((BF9+BG9)/2))/(D9+2*((BF9+BG9)/2)))^(2/3))^2+((DATOS!$B$34*H8/((D8*F8)/(D8+2*F8))^(2/3))^2))/2))>0,((BF9+BG9)/2),BG9) | BJ9: =IF((((BH9+BI9)/2)+(C9/(D9*((BH9+BI9)/2)))^2/(2*9.81)+B9-(G8+H8^2/(2*9.81))-(A8-A9)*(((DATOS!$B$34*(C9/(D9*((BH9+BI9)/2)))/((D9*((BH9+BI9)/2))/(D9+2*((BH9+BI9)/2)))^(2/3))^2+((DATOS!$B$34*H8/((D8*F8)/(D8+2*F8))^(2/3))^2))/2))>0,BH9,((BH9+BI9)/2)) | BK9: =IF((((BH9+BI9)/2)+(C9/(D9*((BH9+BI9)/2)))^2/(2*9.81)+B9-(G8+H8^2/(2*9.81))-(A8-A9)*(((DATOS!$B$34*(C9/(D9*((BH9+BI9)/2)))/((D9*((BH9+BI9)/2))/(D9+2*((BH9+BI9)/2)))^(2/3))^2+((DATOS!$B$34*H8/((D8*F8)/(D8+2*F8))^(2/3))^2))/2))>0,((BH9+BI9)/2),BI9) | BL9: =IF((((BJ9+BK9)/2)+(C9/(D9*((BJ9+BK9)/2)))^2/(2*9.81)+B9-(G8+H8^2/(2*9.81))-(A8-A9)*(((DATOS!$B$34*(C9/(D9*((BJ9+BK9)/2)))/((D9*((BJ9+BK9)/2))/(D9+2*((BJ9+BK9)/2)))^(2/3))^2+((DATOS!$B$34*H8/((D8*F8)/(D8+2*F8))^(2/3))^2))/2))>0,BJ9,((BJ9+BK9)/2)) | BM9: =IF((((BJ9+BK9)/2)+(C9/(D9*((BJ9+BK9)/2)))^2/(2*9.81)+B9-(G8+H8^2/(2*9.81))-(A8-A9)*(((DATOS!$B$34*(C9/(D9*((BJ9+BK9)/2)))/((D9*((BJ9+BK9)/2))/(D9+2*((BJ9+BK9)/2)))^(2/3))^2+((DATOS!$B$34*H8/((D8*F8)/(D8+2*F8))^(2/3))^2))/2))>0,((BJ9+BK9)/2),BK9) | BN9: =IF((((BL9+BM9)/2)+(C9/(D9*((BL9+BM9)/2)))^2/(2*9.81)+B9-(G8+H8^2/(2*9.81))-(A8-A9)*(((DATOS!$B$34*(C9/(D9*((BL9+BM9)/2)))/((D9*((BL9+BM9)/2))/(D9+2*((BL9+BM9)/2)))^(2/3))^2+((DATOS!$B$34*H8/((D8*F8)/(D8+2*F8))^(2/3))^2))/2))>0,BL9,((BL9+BM9)/2)) | BO9: =IF((((BL9+BM9)/2)+(C9/(D9*((BL9+BM9)/2)))^2/(2*9.81)+B9-(G8+H8^2/(2*9.81))-(A8-A9)*(((DATOS!$B$34*(C9/(D9*((BL9+BM9)/2)))/((D9*((BL9+BM9)/2))/(D9+2*((BL9+BM9)/2)))^(2/3))^2+((DATOS!$B$34*H8/((D8*F8)/(D8+2*F8))^(2/3))^2))/2))>0,((BL9+BM9)/2),BM9) | BP9: =IF((((BN9+BO9)/2)+(C9/(D9*((BN9+BO9)/2)))^2/(2*9.81)+B9-(G8+H8^2/(2*9.81))-(A8-A9)*(((DATOS!$B$34*(C9/(D9*((BN9+BO9)/2)))/((D9*((BN9+BO9)/2))/(D9+2*((BN9+BO9)/2)))^(2/3))^2+((DATOS!$B$34*H8/((D8*F8)/(D8+2*F8))^(2/3))^2))/2))>0,BN9,((BN9+BO9)/2)) | BQ9: =IF((((BN9+BO9)/2)+(C9/(D9*((BN9+BO9)/2)))^2/(2*9.81)+B9-(G8+H8^2/(2*9.81))-(A8-A9)*(((DATOS!$B$34*(C9/(D9*((BN9+BO9)/2)))/((D9*((BN9+BO9)/2))/(D9+2*((BN9+BO9)/2)))^(2/3))^2+((DATOS!$B$34*H8/((D8*F8)/(D8+2*F8))^(2/3))^2))/2))>0,((BN9+BO9)/2),BO9) | BR9: =IF((((BP9+BQ9)/2)+(C9/(D9*((BP9+BQ9)/2)))^2/(2*9.81)+B9-(G8+H8^2/(2*9.81))-(A8-A9)*(((DATOS!$B$34*(C9/(D9*((BP9+BQ9)/2)))/((D9*((BP9+BQ9)/2))/(D9+2*((BP9+BQ9)/2)))^(2/3))^2+((DATOS!$B$34*H8/((D8*F8)/(D8+2*F8))^(2/3))^2))/2))>0,BP9,((BP9+BQ9)/2)) | BS9: =IF((((BP9+BQ9)/2)+(C9/(D9*((BP9+BQ9)/2)))^2/(2*9.81)+B9-(G8+H8^2/(2*9.81))-(A8-A9)*(((DATOS!$B$34*(C9/(D9*((BP9+BQ9)/2)))/((D9*((BP9+BQ9)/2))/(D9+2*((BP9+BQ9)/2)))^(2/3))^2+((DATOS!$B$34*H8/((D8*F8)/(D8+2*F8))^(2/3))^2))/2))>0,((BP9+BQ9)/2),BQ9) | BT9: =IF((((BR9+BS9)/2)+(C9/(D9*((BR9+BS9)/2)))^2/(2*9.81)+B9-(G8+H8^2/(2*9.81))-(A8-A9)*(((DATOS!$B$34*(C9/(D9*((BR9+BS9)/2)))/((D9*((BR9+BS9)/2))/(D9+2*((BR9+BS9)/2)))^(2/3))^2+((DATOS!$B$34*H8/((D8*F8)/(D8+2*F8))^(2/3))^2))/2))>0,BR9,((BR9+BS9)/2)) | BU9: =IF((((BR9+BS9)/2)+(C9/(D9*((BR9+BS9)/2)))^2/(2*9.81)+B9-(G8+H8^2/(2*9.81))-(A8-A9)*(((DATOS!$B$34*(C9/(D9*((BR9+BS9)/2)))/((D9*((BR9+BS9)/2))/(D9+2*((BR9+BS9)/2)))^(2/3))^2+((DATOS!$B$34*H8/((D8*F8)/(D8+2*F8))^(2/3))^2))/2))>0,((BR9+BS9)/2),BS9) | BV9: =IF((((BT9+BU9)/2)+(C9/(D9*((BT9+BU9)/2)))^2/(2*9.81)+B9-(G8+H8^2/(2*9.81))-(A8-A9)*(((DATOS!$B$34*(C9/(D9*((BT9+BU9)/2)))/((D9*((BT9+BU9)/2))/(D9+2*((BT9+BU9)/2)))^(2/3))^2+((DATOS!$B$34*H8/((D8*F8)/(D8+2*F8))^(2/3))^2))/2))>0,BT9,((BT9+BU9)/2)) | BW9: =IF((((BT9+BU9)/2)+(C9/(D9*((BT9+BU9)/2)))^2/(2*9.81)+B9-(G8+H8^2/(2*9.81))-(A8-A9)*(((DATOS!$B$34*(C9/(D9*((BT9+BU9)/2)))/((D9*((BT9+BU9)/2))/(D9+2*((BT9+BU9)/2)))^(2/3))^2+((DATOS!$B$34*H8/((D8*F8)/(D8+2*F8))^(2/3))^2))/2))>0,((BT9+BU9)/2),BU9)
A10: 67 | B10: =DATOS!$B$22-DATOS!$B$23*A10 | C10: =CAUDALES!$B$13 | D10: =DATOS!$B$17 | E10: =(C10^2/(9.81*D10^2))^(1/3) | F10: =(BV10+BW10)/2 | G10: =B10+F10 | H10: =C10/(D10*F10) | I10: =H10/SQRT(9.81*F10) | J10: =DATOS!$B$29-IF(AND(A10>=DATOS!$B$30,A10<DATOS!$B$31),DATOS!$B$21,DATOS!$B$20) | K10: =J10-B10 | L10: =F10/K10 | M10: =J10-G10 | N10: =IF(AND(L10<=DATOS!$B$36,M10>=DATOS!$B$37,I10<=1),"CUMPLE","NO CUMPLE") | O10: =IF(AND(A10>=DATOS!$B$30,A10<DATOS!$B$31),"cruce de camiones",IF(AND(A10>=DATOS!$B$32,A10<DATOS!$B$33),"cruce de motos","tramo normal")) | P10: =E10*1.001 | Q10: 3 | R10: =IF((((P10+Q10)/2)+(C10/(D10*((P10+Q10)/2)))^2/(2*9.81)+B10-(G9+H9^2/(2*9.81))-(A9-A10)*(((DATOS!$B$34*(C10/(D10*((P10+Q10)/2)))/((D10*((P10+Q10)/2))/(D10+2*((P10+Q10)/2)))^(2/3))^2+((DATOS!$B$34*H9/((D9*F9)/(D9+2*F9))^(2/3))^2))/2))>0,P10,((P10+Q10)/2)) | S10: =IF((((P10+Q10)/2)+(C10/(D10*((P10+Q10)/2)))^2/(2*9.81)+B10-(G9+H9^2/(2*9.81))-(A9-A10)*(((DATOS!$B$34*(C10/(D10*((P10+Q10)/2)))/((D10*((P10+Q10)/2))/(D10+2*((P10+Q10)/2)))^(2/3))^2+((DATOS!$B$34*H9/((D9*F9)/(D9+2*F9))^(2/3))^2))/2))>0,((P10+Q10)/2),Q10) | T10: =IF((((R10+S10)/2)+(C10/(D10*((R10+S10)/2)))^2/(2*9.81)+B10-(G9+H9^2/(2*9.81))-(A9-A10)*(((DATOS!$B$34*(C10/(D10*((R10+S10)/2)))/((D10*((R10+S10)/2))/(D10+2*((R10+S10)/2)))^(2/3))^2+((DATOS!$B$34*H9/((D9*F9)/(D9+2*F9))^(2/3))^2))/2))>0,R10,((R10+S10)/2)) | U10: =IF((((R10+S10)/2)+(C10/(D10*((R10+S10)/2)))^2/(2*9.81)+B10-(G9+H9^2/(2*9.81))-(A9-A10)*(((DATOS!$B$34*(C10/(D10*((R10+S10)/2)))/((D10*((R10+S10)/2))/(D10+2*((R10+S10)/2)))^(2/3))^2+((DATOS!$B$34*H9/((D9*F9)/(D9+2*F9))^(2/3))^2))/2))>0,((R10+S10)/2),S10) | V10: =IF((((T10+U10)/2)+(C10/(D10*((T10+U10)/2)))^2/(2*9.81)+B10-(G9+H9^2/(2*9.81))-(A9-A10)*(((DATOS!$B$34*(C10/(D10*((T10+U10)/2)))/((D10*((T10+U10)/2))/(D10+2*((T10+U10)/2)))^(2/3))^2+((DATOS!$B$34*H9/((D9*F9)/(D9+2*F9))^(2/3))^2))/2))>0,T10,((T10+U10)/2)) | W10: =IF((((T10+U10)/2)+(C10/(D10*((T10+U10)/2)))^2/(2*9.81)+B10-(G9+H9^2/(2*9.81))-(A9-A10)*(((DATOS!$B$34*(C10/(D10*((T10+U10)/2)))/((D10*((T10+U10)/2))/(D10+2*((T10+U10)/2)))^(2/3))^2+((DATOS!$B$34*H9/((D9*F9)/(D9+2*F9))^(2/3))^2))/2))>0,((T10+U10)/2),U10) | X10: =IF((((V10+W10)/2)+(C10/(D10*((V10+W10)/2)))^2/(2*9.81)+B10-(G9+H9^2/(2*9.81))-(A9-A10)*(((DATOS!$B$34*(C10/(D10*((V10+W10)/2)))/((D10*((V10+W10)/2))/(D10+2*((V10+W10)/2)))^(2/3))^2+((DATOS!$B$34*H9/((D9*F9)/(D9+2*F9))^(2/3))^2))/2))>0,V10,((V10+W10)/2)) | Y10: =IF((((V10+W10)/2)+(C10/(D10*((V10+W10)/2)))^2/(2*9.81)+B10-(G9+H9^2/(2*9.81))-(A9-A10)*(((DATOS!$B$34*(C10/(D10*((V10+W10)/2)))/((D10*((V10+W10)/2))/(D10+2*((V10+W10)/2)))^(2/3))^2+((DATOS!$B$34*H9/((D9*F9)/(D9+2*F9))^(2/3))^2))/2))>0,((V10+W10)/2),W10) | Z10: =IF((((X10+Y10)/2)+(C10/(D10*((X10+Y10)/2)))^2/(2*9.81)+B10-(G9+H9^2/(2*9.81))-(A9-A10)*(((DATOS!$B$34*(C10/(D10*((X10+Y10)/2)))/((D10*((X10+Y10)/2))/(D10+2*((X10+Y10)/2)))^(2/3))^2+((DATOS!$B$34*H9/((D9*F9)/(D9+2*F9))^(2/3))^2))/2))>0,X10,((X10+Y10)/2)) | AA10: =IF((((X10+Y10)/2)+(C10/(D10*((X10+Y10)/2)))^2/(2*9.81)+B10-(G9+H9^2/(2*9.81))-(A9-A10)*(((DATOS!$B$34*(C10/(D10*((X10+Y10)/2)))/((D10*((X10+Y10)/2))/(D10+2*((X10+Y10)/2)))^(2/3))^2+((DATOS!$B$34*H9/((D9*F9)/(D9+2*F9))^(2/3))^2))/2))>0,((X10+Y10)/2),Y10) | AB10: =IF((((Z10+AA10)/2)+(C10/(D10*((Z10+AA10)/2)))^2/(2*9.81)+B10-(G9+H9^2/(2*9.81))-(A9-A10)*(((DATOS!$B$34*(C10/(D10*((Z10+AA10)/2)))/((D10*((Z10+AA10)/2))/(D10+2*((Z10+AA10)/2)))^(2/3))^2+((DATOS!$B$34*H9/((D9*F9)/(D9+2*F9))^(2/3))^2))/2))>0,Z10,((Z10+AA10)/2)) | AC10: =IF((((Z10+AA10)/2)+(C10/(D10*((Z10+AA10)/2)))^2/(2*9.81)+B10-(G9+H9^2/(2*9.81))-(A9-A10)*(((DATOS!$B$34*(C10/(D10*((Z10+AA10)/2)))/((D10*((Z10+AA10)/2))/(D10+2*((Z10+AA10)/2)))^(2/3))^2+((DATOS!$B$34*H9/((D9*F9)/(D9+2*F9))^(2/3))^2))/2))>0,((Z10+AA10)/2),AA10) | AD10: =IF((((AB10+AC10)/2)+(C10/(D10*((AB10+AC10)/2)))^2/(2*9.81)+B10-(G9+H9^2/(2*9.81))-(A9-A10)*(((DATOS!$B$34*(C10/(D10*((AB10+AC10)/2)))/((D10*((AB10+AC10)/2))/(D10+2*((AB10+AC10)/2)))^(2/3))^2+((DATOS!$B$34*H9/((D9*F9)/(D9+2*F9))^(2/3))^2))/2))>0,AB10,((AB10+AC10)/2)) | AE10: =IF((((AB10+AC10)/2)+(C10/(D10*((AB10+AC10)/2)))^2/(2*9.81)+B10-(G9+H9^2/(2*9.81))-(A9-A10)*(((DATOS!$B$34*(C10/(D10*((AB10+AC10)/2)))/((D10*((AB10+AC10)/2))/(D10+2*((AB10+AC10)/2)))^(2/3))^2+((DATOS!$B$34*H9/((D9*F9)/(D9+2*F9))^(2/3))^2))/2))>0,((AB10+AC10)/2),AC10) | AF10: =IF((((AD10+AE10)/2)+(C10/(D10*((AD10+AE10)/2)))^2/(2*9.81)+B10-(G9+H9^2/(2*9.81))-(A9-A10)*(((DATOS!$B$34*(C10/(D10*((AD10+AE10)/2)))/((D10*((AD10+AE10)/2))/(D10+2*((AD10+AE10)/2)))^(2/3))^2+((DATOS!$B$34*H9/((D9*F9)/(D9+2*F9))^(2/3))^2))/2))>0,AD10,((AD10+AE10)/2)) | AG10: =IF((((AD10+AE10)/2)+(C10/(D10*((AD10+AE10)/2)))^2/(2*9.81)+B10-(G9+H9^2/(2*9.81))-(A9-A10)*(((DATOS!$B$34*(C10/(D10*((AD10+AE10)/2)))/((D10*((AD10+AE10)/2))/(D10+2*((AD10+AE10)/2)))^(2/3))^2+((DATOS!$B$34*H9/((D9*F9)/(D9+2*F9))^(2/3))^2))/2))>0,((AD10+AE10)/2),AE10) | AH10: =IF((((AF10+AG10)/2)+(C10/(D10*((AF10+AG10)/2)))^2/(2*9.81)+B10-(G9+H9^2/(2*9.81))-(A9-A10)*(((DATOS!$B$34*(C10/(D10*((AF10+AG10)/2)))/((D10*((AF10+AG10)/2))/(D10+2*((AF10+AG10)/2)))^(2/3))^2+((DATOS!$B$34*H9/((D9*F9)/(D9+2*F9))^(2/3))^2))/2))>0,AF10,((AF10+AG10)/2)) | AI10: =IF((((AF10+AG10)/2)+(C10/(D10*((AF10+AG10)/2)))^2/(2*9.81)+B10-(G9+H9^2/(2*9.81))-(A9-A10)*(((DATOS!$B$34*(C10/(D10*((AF10+AG10)/2)))/((D10*((AF10+AG10)/2))/(D10+2*((AF10+AG10)/2)))^(2/3))^2+((DATOS!$B$34*H9/((D9*F9)/(D9+2*F9))^(2/3))^2))/2))>0,((AF10+AG10)/2),AG10) | AJ10: =IF((((AH10+AI10)/2)+(C10/(D10*((AH10+AI10)/2)))^2/(2*9.81)+B10-(G9+H9^2/(2*9.81))-(A9-A10)*(((DATOS!$B$34*(C10/(D10*((AH10+AI10)/2)))/((D10*((AH10+AI10)/2))/(D10+2*((AH10+AI10)/2)))^(2/3))^2+((DATOS!$B$34*H9/((D9*F9)/(D9+2*F9))^(2/3))^2))/2))>0,AH10,((AH10+AI10)/2)) | AK10: =IF((((AH10+AI10)/2)+(C10/(D10*((AH10+AI10)/2)))^2/(2*9.81)+B10-(G9+H9^2/(2*9.81))-(A9-A10)*(((DATOS!$B$34*(C10/(D10*((AH10+AI10)/2)))/((D10*((AH10+AI10)/2))/(D10+2*((AH10+AI10)/2)))^(2/3))^2+((DATOS!$B$34*H9/((D9*F9)/(D9+2*F9))^(2/3))^2))/2))>0,((AH10+AI10)/2),AI10) | AL10: =IF((((AJ10+AK10)/2)+(C10/(D10*((AJ10+AK10)/2)))^2/(2*9.81)+B10-(G9+H9^2/(2*9.81))-(A9-A10)*(((DATOS!$B$34*(C10/(D10*((AJ10+AK10)/2)))/((D10*((AJ10+AK10)/2))/(D10+2*((AJ10+AK10)/2)))^(2/3))^2+((DATOS!$B$34*H9/((D9*F9)/(D9+2*F9))^(2/3))^2))/2))>0,AJ10,((AJ10+AK10)/2)) | AM10: =IF((((AJ10+AK10)/2)+(C10/(D10*((AJ10+AK10)/2)))^2/(2*9.81)+B10-(G9+H9^2/(2*9.81))-(A9-A10)*(((DATOS!$B$34*(C10/(D10*((AJ10+AK10)/2)))/((D10*((AJ10+AK10)/2))/(D10+2*((AJ10+AK10)/2)))^(2/3))^2+((DATOS!$B$34*H9/((D9*F9)/(D9+2*F9))^(2/3))^2))/2))>0,((AJ10+AK10)/2),AK10) | AN10: =IF((((AL10+AM10)/2)+(C10/(D10*((AL10+AM10)/2)))^2/(2*9.81)+B10-(G9+H9^2/(2*9.81))-(A9-A10)*(((DATOS!$B$34*(C10/(D10*((AL10+AM10)/2)))/((D10*((AL10+AM10)/2))/(D10+2*((AL10+AM10)/2)))^(2/3))^2+((DATOS!$B$34*H9/((D9*F9)/(D9+2*F9))^(2/3))^2))/2))>0,AL10,((AL10+AM10)/2)) | AO10: =IF((((AL10+AM10)/2)+(C10/(D10*((AL10+AM10)/2)))^2/(2*9.81)+B10-(G9+H9^2/(2*9.81))-(A9-A10)*(((DATOS!$B$34*(C10/(D10*((AL10+AM10)/2)))/((D10*((AL10+AM10)/2))/(D10+2*((AL10+AM10)/2)))^(2/3))^2+((DATOS!$B$34*H9/((D9*F9)/(D9+2*F9))^(2/3))^2))/2))>0,((AL10+AM10)/2),AM10) | AP10: =IF((((AN10+AO10)/2)+(C10/(D10*((AN10+AO10)/2)))^2/(2*9.81)+B10-(G9+H9^2/(2*9.81))-(A9-A10)*(((DATOS!$B$34*(C10/(D10*((AN10+AO10)/2)))/((D10*((AN10+AO10)/2))/(D10+2*((AN10+AO10)/2)))^(2/3))^2+((DATOS!$B$34*H9/((D9*F9)/(D9+2*F9))^(2/3))^2))/2))>0,AN10,((AN10+AO10)/2)) | AQ10: =IF((((AN10+AO10)/2)+(C10/(D10*((AN10+AO10)/2)))^2/(2*9.81)+B10-(G9+H9^2/(2*9.81))-(A9-A10)*(((DATOS!$B$34*(C10/(D10*((AN10+AO10)/2)))/((D10*((AN10+AO10)/2))/(D10+2*((AN10+AO10)/2)))^(2/3))^2+((DATOS!$B$34*H9/((D9*F9)/(D9+2*F9))^(2/3))^2))/2))>0,((AN10+AO10)/2),AO10) | AR10: =IF((((AP10+AQ10)/2)+(C10/(D10*((AP10+AQ10)/2)))^2/(2*9.81)+B10-(G9+H9^2/(2*9.81))-(A9-A10)*(((DATOS!$B$34*(C10/(D10*((AP10+AQ10)/2)))/((D10*((AP10+AQ10)/2))/(D10+2*((AP10+AQ10)/2)))^(2/3))^2+((DATOS!$B$34*H9/((D9*F9)/(D9+2*F9))^(2/3))^2))/2))>0,AP10,((AP10+AQ10)/2)) | AS10: =IF((((AP10+AQ10)/2)+(C10/(D10*((AP10+AQ10)/2)))^2/(2*9.81)+B10-(G9+H9^2/(2*9.81))-(A9-A10)*(((DATOS!$B$34*(C10/(D10*((AP10+AQ10)/2)))/((D10*((AP10+AQ10)/2))/(D10+2*((AP10+AQ10)/2)))^(2/3))^2+((DATOS!$B$34*H9/((D9*F9)/(D9+2*F9))^(2/3))^2))/2))>0,((AP10+AQ10)/2),AQ10) | AT10: =IF((((AR10+AS10)/2)+(C10/(D10*((AR10+AS10)/2)))^2/(2*9.81)+B10-(G9+H9^2/(2*9.81))-(A9-A10)*(((DATOS!$B$34*(C10/(D10*((AR10+AS10)/2)))/((D10*((AR10+AS10)/2))/(D10+2*((AR10+AS10)/2)))^(2/3))^2+((DATOS!$B$34*H9/((D9*F9)/(D9+2*F9))^(2/3))^2))/2))>0,AR10,((AR10+AS10)/2)) | AU10: =IF((((AR10+AS10)/2)+(C10/(D10*((AR10+AS10)/2)))^2/(2*9.81)+B10-(G9+H9^2/(2*9.81))-(A9-A10)*(((DATOS!$B$34*(C10/(D10*((AR10+AS10)/2)))/((D10*((AR10+AS10)/2))/(D10+2*((AR10+AS10)/2)))^(2/3))^2+((DATOS!$B$34*H9/((D9*F9)/(D9+2*F9))^(2/3))^2))/2))>0,((AR10+AS10)/2),AS10) | AV10: =IF((((AT10+AU10)/2)+(C10/(D10*((AT10+AU10)/2)))^2/(2*9.81)+B10-(G9+H9^2/(2*9.81))-(A9-A10)*(((DATOS!$B$34*(C10/(D10*((AT10+AU10)/2)))/((D10*((AT10+AU10)/2))/(D10+2*((AT10+AU10)/2)))^(2/3))^2+((DATOS!$B$34*H9/((D9*F9)/(D9+2*F9))^(2/3))^2))/2))>0,AT10,((AT10+AU10)/2)) | AW10: =IF((((AT10+AU10)/2)+(C10/(D10*((AT10+AU10)/2)))^2/(2*9.81)+B10-(G9+H9^2/(2*9.81))-(A9-A10)*(((DATOS!$B$34*(C10/(D10*((AT10+AU10)/2)))/((D10*((AT10+AU10)/2))/(D10+2*((AT10+AU10)/2)))^(2/3))^2+((DATOS!$B$34*H9/((D9*F9)/(D9+2*F9))^(2/3))^2))/2))>0,((AT10+AU10)/2),AU10) | AX10: =IF((((AV10+AW10)/2)+(C10/(D10*((AV10+AW10)/2)))^2/(2*9.81)+B10-(G9+H9^2/(2*9.81))-(A9-A10)*(((DATOS!$B$34*(C10/(D10*((AV10+AW10)/2)))/((D10*((AV10+AW10)/2))/(D10+2*((AV10+AW10)/2)))^(2/3))^2+((DATOS!$B$34*H9/((D9*F9)/(D9+2*F9))^(2/3))^2))/2))>0,AV10,((AV10+AW10)/2)) | AY10: =IF((((AV10+AW10)/2)+(C10/(D10*((AV10+AW10)/2)))^2/(2*9.81)+B10-(G9+H9^2/(2*9.81))-(A9-A10)*(((DATOS!$B$34*(C10/(D10*((AV10+AW10)/2)))/((D10*((AV10+AW10)/2))/(D10+2*((AV10+AW10)/2)))^(2/3))^2+((DATOS!$B$34*H9/((D9*F9)/(D9+2*F9))^(2/3))^2))/2))>0,((AV10+AW10)/2),AW10) | AZ10: =IF((((AX10+AY10)/2)+(C10/(D10*((AX10+AY10)/2)))^2/(2*9.81)+B10-(G9+H9^2/(2*9.81))-(A9-A10)*(((DATOS!$B$34*(C10/(D10*((AX10+AY10)/2)))/((D10*((AX10+AY10)/2))/(D10+2*((AX10+AY10)/2)))^(2/3))^2+((DATOS!$B$34*H9/((D9*F9)/(D9+2*F9))^(2/3))^2))/2))>0,AX10,((AX10+AY10)/2)) | BA10: =IF((((AX10+AY10)/2)+(C10/(D10*((AX10+AY10)/2)))^2/(2*9.81)+B10-(G9+H9^2/(2*9.81))-(A9-A10)*(((DATOS!$B$34*(C10/(D10*((AX10+AY10)/2)))/((D10*((AX10+AY10)/2))/(D10+2*((AX10+AY10)/2)))^(2/3))^2+((DATOS!$B$34*H9/((D9*F9)/(D9+2*F9))^(2/3))^2))/2))>0,((AX10+AY10)/2),AY10) | BB10: =IF((((AZ10+BA10)/2)+(C10/(D10*((AZ10+BA10)/2)))^2/(2*9.81)+B10-(G9+H9^2/(2*9.81))-(A9-A10)*(((DATOS!$B$34*(C10/(D10*((AZ10+BA10)/2)))/((D10*((AZ10+BA10)/2))/(D10+2*((AZ10+BA10)/2)))^(2/3))^2+((DATOS!$B$34*H9/((D9*F9)/(D9+2*F9))^(2/3))^2))/2))>0,AZ10,((AZ10+BA10)/2)) | BC10: =IF((((AZ10+BA10)/2)+(C10/(D10*((AZ10+BA10)/2)))^2/(2*9.81)+B10-(G9+H9^2/(2*9.81))-(A9-A10)*(((DATOS!$B$34*(C10/(D10*((AZ10+BA10)/2)))/((D10*((AZ10+BA10)/2))/(D10+2*((AZ10+BA10)/2)))^(2/3))^2+((DATOS!$B$34*H9/((D9*F9)/(D9+2*F9))^(2/3))^2))/2))>0,((AZ10+BA10)/2),BA10) | BD10: =IF((((BB10+BC10)/2)+(C10/(D10*((BB10+BC10)/2)))^2/(2*9.81)+B10-(G9+H9^2/(2*9.81))-(A9-A10)*(((DATOS!$B$34*(C10/(D10*((BB10+BC10)/2)))/((D10*((BB10+BC10)/2))/(D10+2*((BB10+BC10)/2)))^(2/3))^2+((DATOS!$B$34*H9/((D9*F9)/(D9+2*F9))^(2/3))^2))/2))>0,BB10,((BB10+BC10)/2)) | BE10: =IF((((BB10+BC10)/2)+(C10/(D10*((BB10+BC10)/2)))^2/(2*9.81)+B10-(G9+H9^2/(2*9.81))-(A9-A10)*(((DATOS!$B$34*(C10/(D10*((BB10+BC10)/2)))/((D10*((BB10+BC10)/2))/(D10+2*((BB10+BC10)/2)))^(2/3))^2+((DATOS!$B$34*H9/((D9*F9)/(D9+2*F9))^(2/3))^2))/2))>0,((BB10+BC10)/2),BC10) | BF10: =IF((((BD10+BE10)/2)+(C10/(D10*((BD10+BE10)/2)))^2/(2*9.81)+B10-(G9+H9^2/(2*9.81))-(A9-A10)*(((DATOS!$B$34*(C10/(D10*((BD10+BE10)/2)))/((D10*((BD10+BE10)/2))/(D10+2*((BD10+BE10)/2)))^(2/3))^2+((DATOS!$B$34*H9/((D9*F9)/(D9+2*F9))^(2/3))^2))/2))>0,BD10,((BD10+BE10)/2)) | BG10: =IF((((BD10+BE10)/2)+(C10/(D10*((BD10+BE10)/2)))^2/(2*9.81)+B10-(G9+H9^2/(2*9.81))-(A9-A10)*(((DATOS!$B$34*(C10/(D10*((BD10+BE10)/2)))/((D10*((BD10+BE10)/2))/(D10+2*((BD10+BE10)/2)))^(2/3))^2+((DATOS!$B$34*H9/((D9*F9)/(D9+2*F9))^(2/3))^2))/2))>0,((BD10+BE10)/2),BE10) | BH10: =IF((((BF10+BG10)/2)+(C10/(D10*((BF10+BG10)/2)))^2/(2*9.81)+B10-(G9+H9^2/(2*9.81))-(A9-A10)*(((DATOS!$B$34*(C10/(D10*((BF10+BG10)/2)))/((D10*((BF10+BG10)/2))/(D10+2*((BF10+BG10)/2)))^(2/3))^2+((DATOS!$B$34*H9/((D9*F9)/(D9+2*F9))^(2/3))^2))/2))>0,BF10,((BF10+BG10)/2)) | BI10: =IF((((BF10+BG10)/2)+(C10/(D10*((BF10+BG10)/2)))^2/(2*9.81)+B10-(G9+H9^2/(2*9.81))-(A9-A10)*(((DATOS!$B$34*(C10/(D10*((BF10+BG10)/2)))/((D10*((BF10+BG10)/2))/(D10+2*((BF10+BG10)/2)))^(2/3))^2+((DATOS!$B$34*H9/((D9*F9)/(D9+2*F9))^(2/3))^2))/2))>0,((BF10+BG10)/2),BG10) | BJ10: =IF((((BH10+BI10)/2)+(C10/(D10*((BH10+BI10)/2)))^2/(2*9.81)+B10-(G9+H9^2/(2*9.81))-(A9-A10)*(((DATOS!$B$34*(C10/(D10*((BH10+BI10)/2)))/((D10*((BH10+BI10)/2))/(D10+2*((BH10+BI10)/2)))^(2/3))^2+((DATOS!$B$34*H9/((D9*F9)/(D9+2*F9))^(2/3))^2))/2))>0,BH10,((BH10+BI10)/2)) | BK10: =IF((((BH10+BI10)/2)+(C10/(D10*((BH10+BI10)/2)))^2/(2*9.81)+B10-(G9+H9^2/(2*9.81))-(A9-A10)*(((DATOS!$B$34*(C10/(D10*((BH10+BI10)/2)))/((D10*((BH10+BI10)/2))/(D10+2*((BH10+BI10)/2)))^(2/3))^2+((DATOS!$B$34*H9/((D9*F9)/(D9+2*F9))^(2/3))^2))/2))>0,((BH10+BI10)/2),BI10) | BL10: =IF((((BJ10+BK10)/2)+(C10/(D10*((BJ10+BK10)/2)))^2/(2*9.81)+B10-(G9+H9^2/(2*9.81))-(A9-A10)*(((DATOS!$B$34*(C10/(D10*((BJ10+BK10)/2)))/((D10*((BJ10+BK10)/2))/(D10+2*((BJ10+BK10)/2)))^(2/3))^2+((DATOS!$B$34*H9/((D9*F9)/(D9+2*F9))^(2/3))^2))/2))>0,BJ10,((BJ10+BK10)/2)) | BM10: =IF((((BJ10+BK10)/2)+(C10/(D10*((BJ10+BK10)/2)))^2/(2*9.81)+B10-(G9+H9^2/(2*9.81))-(A9-A10)*(((DATOS!$B$34*(C10/(D10*((BJ10+BK10)/2)))/((D10*((BJ10+BK10)/2))/(D10+2*((BJ10+BK10)/2)))^(2/3))^2+((DATOS!$B$34*H9/((D9*F9)/(D9+2*F9))^(2/3))^2))/2))>0,((BJ10+BK10)/2),BK10) | BN10: =IF((((BL10+BM10)/2)+(C10/(D10*((BL10+BM10)/2)))^2/(2*9.81)+B10-(G9+H9^2/(2*9.81))-(A9-A10)*(((DATOS!$B$34*(C10/(D10*((BL10+BM10)/2)))/((D10*((BL10+BM10)/2))/(D10+2*((BL10+BM10)/2)))^(2/3))^2+((DATOS!$B$34*H9/((D9*F9)/(D9+2*F9))^(2/3))^2))/2))>0,BL10,((BL10+BM10)/2)) | BO10: =IF((((BL10+BM10)/2)+(C10/(D10*((BL10+BM10)/2)))^2/(2*9.81)+B10-(G9+H9^2/(2*9.81))-(A9-A10)*(((DATOS!$B$34*(C10/(D10*((BL10+BM10)/2)))/((D10*((BL10+BM10)/2))/(D10+2*((BL10+BM10)/2)))^(2/3))^2+((DATOS!$B$34*H9/((D9*F9)/(D9+2*F9))^(2/3))^2))/2))>0,((BL10+BM10)/2),BM10) | BP10: =IF((((BN10+BO10)/2)+(C10/(D10*((BN10+BO10)/2)))^2/(2*9.81)+B10-(G9+H9^2/(2*9.81))-(A9-A10)*(((DATOS!$B$34*(C10/(D10*((BN10+BO10)/2)))/((D10*((BN10+BO10)/2))/(D10+2*((BN10+BO10)/2)))^(2/3))^2+((DATOS!$B$34*H9/((D9*F9)/(D9+2*F9))^(2/3))^2))/2))>0,BN10,((BN10+BO10)/2)) | BQ10: =IF((((BN10+BO10)/2)+(C10/(D10*((BN10+BO10)/2)))^2/(2*9.81)+B10-(G9+H9^2/(2*9.81))-(A9-A10)*(((DATOS!$B$34*(C10/(D10*((BN10+BO10)/2)))/((D10*((BN10+BO10)/2))/(D10+2*((BN10+BO10)/2)))^(2/3))^2+((DATOS!$B$34*H9/((D9*F9)/(D9+2*F9))^(2/3))^2))/2))>0,((BN10+BO10)/2),BO10) | BR10: =IF((((BP10+BQ10)/2)+(C10/(D10*((BP10+BQ10)/2)))^2/(2*9.81)+B10-(G9+H9^2/(2*9.81))-(A9-A10)*(((DATOS!$B$34*(C10/(D10*((BP10+BQ10)/2)))/((D10*((BP10+BQ10)/2))/(D10+2*((BP10+BQ10)/2)))^(2/3))^2+((DATOS!$B$34*H9/((D9*F9)/(D9+2*F9))^(2/3))^2))/2))>0,BP10,((BP10+BQ10)/2)) | BS10: =IF((((BP10+BQ10)/2)+(C10/(D10*((BP10+BQ10)/2)))^2/(2*9.81)+B10-(G9+H9^2/(2*9.81))-(A9-A10)*(((DATOS!$B$34*(C10/(D10*((BP10+BQ10)/2)))/((D10*((BP10+BQ10)/2))/(D10+2*((BP10+BQ10)/2)))^(2/3))^2+((DATOS!$B$34*H9/((D9*F9)/(D9+2*F9))^(2/3))^2))/2))>0,((BP10+BQ10)/2),BQ10) | BT10: =IF((((BR10+BS10)/2)+(C10/(D10*((BR10+BS10)/2)))^2/(2*9.81)+B10-(G9+H9^2/(2*9.81))-(A9-A10)*(((DATOS!$B$34*(C10/(D10*((BR10+BS10)/2)))/((D10*((BR10+BS10)/2))/(D10+2*((BR10+BS10)/2)))^(2/3))^2+((DATOS!$B$34*H9/((D9*F9)/(D9+2*F9))^(2/3))^2))/2))>0,BR10,((BR10+BS10)/2)) | BU10: =IF((((BR10+BS10)/2)+(C10/(D10*((BR10+BS10)/2)))^2/(2*9.81)+B10-(G9+H9^2/(2*9.81))-(A9-A10)*(((DATOS!$B$34*(C10/(D10*((BR10+BS10)/2)))/((D10*((BR10+BS10)/2))/(D10+2*((BR10+BS10)/2)))^(2/3))^2+((DATOS!$B$34*H9/((D9*F9)/(D9+2*F9))^(2/3))^2))/2))>0,((BR10+BS10)/2),BS10) | BV10: =IF((((BT10+BU10)/2)+(C10/(D10*((BT10+BU10)/2)))^2/(2*9.81)+B10-(G9+H9^2/(2*9.81))-(A9-A10)*(((DATOS!$B$34*(C10/(D10*((BT10+BU10)/2)))/((D10*((BT10+BU10)/2))/(D10+2*((BT10+BU10)/2)))^(2/3))^2+((DATOS!$B$34*H9/((D9*F9)/(D9+2*F9))^(2/3))^2))/2))>0,BT10,((BT10+BU10)/2)) | BW10: =IF((((BT10+BU10)/2)+(C10/(D10*((BT10+BU10)/2)))^2/(2*9.81)+B10-(G9+H9^2/(2*9.81))-(A9-A10)*(((DATOS!$B$34*(C10/(D10*((BT10+BU10)/2)))/((D10*((BT10+BU10)/2))/(D10+2*((BT10+BU10)/2)))^(2/3))^2+((DATOS!$B$34*H9/((D9*F9)/(D9+2*F9))^(2/3))^2))/2))>0,((BT10+BU10)/2),BU10)
A11: 66.89 | B11: =DATOS!$B$22-DATOS!$B$23*A11 | C11: =CAUDALES!$B$13 | D11: =DATOS!$B$17 | E11: =(C11^2/(9.81*D11^2))^(1/3) | F11: =(BV11+BW11)/2 | G11: =B11+F11 | H11: =C11/(D11*F11) | I11: =H11/SQRT(9.81*F11) | J11: =DATOS!$B$29-IF(AND(A11>=DATOS!$B$30,A11<DATOS!$B$31),DATOS!$B$21,DATOS!$B$20) | K11: =J11-B11 | L11: =F11/K11 | M11: =J11-G11 | N11: =IF(AND(L11<=DATOS!$B$36,M11>=DATOS!$B$37,I11<=1),"CUMPLE","NO CUMPLE") | O11: =IF(AND(A11>=DATOS!$B$30,A11<DATOS!$B$31),"cruce de camiones",IF(AND(A11>=DATOS!$B$32,A11<DATOS!$B$33),"cruce de motos","tramo normal")) | P11: =E11*1.001 | Q11: 3 | R11: =IF((((P11+Q11)/2)+(C11/(D11*((P11+Q11)/2)))^2/(2*9.81)+B11-(G10+H10^2/(2*9.81))-(A10-A11)*(((DATOS!$B$34*(C11/(D11*((P11+Q11)/2)))/((D11*((P11+Q11)/2))/(D11+2*((P11+Q11)/2)))^(2/3))^2+((DATOS!$B$34*H10/((D10*F10)/(D10+2*F10))^(2/3))^2))/2))>0,P11,((P11+Q11)/2)) | S11: =IF((((P11+Q11)/2)+(C11/(D11*((P11+Q11)/2)))^2/(2*9.81)+B11-(G10+H10^2/(2*9.81))-(A10-A11)*(((DATOS!$B$34*(C11/(D11*((P11+Q11)/2)))/((D11*((P11+Q11)/2))/(D11+2*((P11+Q11)/2)))^(2/3))^2+((DATOS!$B$34*H10/((D10*F10)/(D10+2*F10))^(2/3))^2))/2))>0,((P11+Q11)/2),Q11) | T11: =IF((((R11+S11)/2)+(C11/(D11*((R11+S11)/2)))^2/(2*9.81)+B11-(G10+H10^2/(2*9.81))-(A10-A11)*(((DATOS!$B$34*(C11/(D11*((R11+S11)/2)))/((D11*((R11+S11)/2))/(D11+2*((R11+S11)/2)))^(2/3))^2+((DATOS!$B$34*H10/((D10*F10)/(D10+2*F10))^(2/3))^2))/2))>0,R11,((R11+S11)/2)) | U11: =IF((((R11+S11)/2)+(C11/(D11*((R11+S11)/2)))^2/(2*9.81)+B11-(G10+H10^2/(2*9.81))-(A10-A11)*(((DATOS!$B$34*(C11/(D11*((R11+S11)/2)))/((D11*((R11+S11)/2))/(D11+2*((R11+S11)/2)))^(2/3))^2+((DATOS!$B$34*H10/((D10*F10)/(D10+2*F10))^(2/3))^2))/2))>0,((R11+S11)/2),S11) | V11: =IF((((T11+U11)/2)+(C11/(D11*((T11+U11)/2)))^2/(2*9.81)+B11-(G10+H10^2/(2*9.81))-(A10-A11)*(((DATOS!$B$34*(C11/(D11*((T11+U11)/2)))/((D11*((T11+U11)/2))/(D11+2*((T11+U11)/2)))^(2/3))^2+((DATOS!$B$34*H10/((D10*F10)/(D10+2*F10))^(2/3))^2))/2))>0,T11,((T11+U11)/2)) | W11: =IF((((T11+U11)/2)+(C11/(D11*((T11+U11)/2)))^2/(2*9.81)+B11-(G10+H10^2/(2*9.81))-(A10-A11)*(((DATOS!$B$34*(C11/(D11*((T11+U11)/2)))/((D11*((T11+U11)/2))/(D11+2*((T11+U11)/2)))^(2/3))^2+((DATOS!$B$34*H10/((D10*F10)/(D10+2*F10))^(2/3))^2))/2))>0,((T11+U11)/2),U11) | X11: =IF((((V11+W11)/2)+(C11/(D11*((V11+W11)/2)))^2/(2*9.81)+B11-(G10+H10^2/(2*9.81))-(A10-A11)*(((DATOS!$B$34*(C11/(D11*((V11+W11)/2)))/((D11*((V11+W11)/2))/(D11+2*((V11+W11)/2)))^(2/3))^2+((DATOS!$B$34*H10/((D10*F10)/(D10+2*F10))^(2/3))^2))/2))>0,V11,((V11+W11)/2)) | Y11: =IF((((V11+W11)/2)+(C11/(D11*((V11+W11)/2)))^2/(2*9.81)+B11-(G10+H10^2/(2*9.81))-(A10-A11)*(((DATOS!$B$34*(C11/(D11*((V11+W11)/2)))/((D11*((V11+W11)/2))/(D11+2*((V11+W11)/2)))^(2/3))^2+((DATOS!$B$34*H10/((D10*F10)/(D10+2*F10))^(2/3))^2))/2))>0,((V11+W11)/2),W11) | Z11: =IF((((X11+Y11)/2)+(C11/(D11*((X11+Y11)/2)))^2/(2*9.81)+B11-(G10+H10^2/(2*9.81))-(A10-A11)*(((DATOS!$B$34*(C11/(D11*((X11+Y11)/2)))/((D11*((X11+Y11)/2))/(D11+2*((X11+Y11)/2)))^(2/3))^2+((DATOS!$B$34*H10/((D10*F10)/(D10+2*F10))^(2/3))^2))/2))>0,X11,((X11+Y11)/2)) | AA11: =IF((((X11+Y11)/2)+(C11/(D11*((X11+Y11)/2)))^2/(2*9.81)+B11-(G10+H10^2/(2*9.81))-(A10-A11)*(((DATOS!$B$34*(C11/(D11*((X11+Y11)/2)))/((D11*((X11+Y11)/2))/(D11+2*((X11+Y11)/2)))^(2/3))^2+((DATOS!$B$34*H10/((D10*F10)/(D10+2*F10))^(2/3))^2))/2))>0,((X11+Y11)/2),Y11) | AB11: =IF((((Z11+AA11)/2)+(C11/(D11*((Z11+AA11)/2)))^2/(2*9.81)+B11-(G10+H10^2/(2*9.81))-(A10-A11)*(((DATOS!$B$34*(C11/(D11*((Z11+AA11)/2)))/((D11*((Z11+AA11)/2))/(D11+2*((Z11+AA11)/2)))^(2/3))^2+((DATOS!$B$34*H10/((D10*F10)/(D10+2*F10))^(2/3))^2))/2))>0,Z11,((Z11+AA11)/2)) | AC11: =IF((((Z11+AA11)/2)+(C11/(D11*((Z11+AA11)/2)))^2/(2*9.81)+B11-(G10+H10^2/(2*9.81))-(A10-A11)*(((DATOS!$B$34*(C11/(D11*((Z11+AA11)/2)))/((D11*((Z11+AA11)/2))/(D11+2*((Z11+AA11)/2)))^(2/3))^2+((DATOS!$B$34*H10/((D10*F10)/(D10+2*F10))^(2/3))^2))/2))>0,((Z11+AA11)/2),AA11) | AD11: =IF((((AB11+AC11)/2)+(C11/(D11*((AB11+AC11)/2)))^2/(2*9.81)+B11-(G10+H10^2/(2*9.81))-(A10-A11)*(((DATOS!$B$34*(C11/(D11*((AB11+AC11)/2)))/((D11*((AB11+AC11)/2))/(D11+2*((AB11+AC11)/2)))^(2/3))^2+((DATOS!$B$34*H10/((D10*F10)/(D10+2*F10))^(2/3))^2))/2))>0,AB11,((AB11+AC11)/2)) | AE11: =IF((((AB11+AC11)/2)+(C11/(D11*((AB11+AC11)/2)))^2/(2*9.81)+B11-(G10+H10^2/(2*9.81))-(A10-A11)*(((DATOS!$B$34*(C11/(D11*((AB11+AC11)/2)))/((D11*((AB11+AC11)/2))/(D11+2*((AB11+AC11)/2)))^(2/3))^2+((DATOS!$B$34*H10/((D10*F10)/(D10+2*F10))^(2/3))^2))/2))>0,((AB11+AC11)/2),AC11) | AF11: =IF((((AD11+AE11)/2)+(C11/(D11*((AD11+AE11)/2)))^2/(2*9.81)+B11-(G10+H10^2/(2*9.81))-(A10-A11)*(((DATOS!$B$34*(C11/(D11*((AD11+AE11)/2)))/((D11*((AD11+AE11)/2))/(D11+2*((AD11+AE11)/2)))^(2/3))^2+((DATOS!$B$34*H10/((D10*F10)/(D10+2*F10))^(2/3))^2))/2))>0,AD11,((AD11+AE11)/2)) | AG11: =IF((((AD11+AE11)/2)+(C11/(D11*((AD11+AE11)/2)))^2/(2*9.81)+B11-(G10+H10^2/(2*9.81))-(A10-A11)*(((DATOS!$B$34*(C11/(D11*((AD11+AE11)/2)))/((D11*((AD11+AE11)/2))/(D11+2*((AD11+AE11)/2)))^(2/3))^2+((DATOS!$B$34*H10/((D10*F10)/(D10+2*F10))^(2/3))^2))/2))>0,((AD11+AE11)/2),AE11) | AH11: =IF((((AF11+AG11)/2)+(C11/(D11*((AF11+AG11)/2)))^2/(2*9.81)+B11-(G10+H10^2/(2*9.81))-(A10-A11)*(((DATOS!$B$34*(C11/(D11*((AF11+AG11)/2)))/((D11*((AF11+AG11)/2))/(D11+2*((AF11+AG11)/2)))^(2/3))^2+((DATOS!$B$34*H10/((D10*F10)/(D10+2*F10))^(2/3))^2))/2))>0,AF11,((AF11+AG11)/2)) | AI11: =IF((((AF11+AG11)/2)+(C11/(D11*((AF11+AG11)/2)))^2/(2*9.81)+B11-(G10+H10^2/(2*9.81))-(A10-A11)*(((DATOS!$B$34*(C11/(D11*((AF11+AG11)/2)))/((D11*((AF11+AG11)/2))/(D11+2*((AF11+AG11)/2)))^(2/3))^2+((DATOS!$B$34*H10/((D10*F10)/(D10+2*F10))^(2/3))^2))/2))>0,((AF11+AG11)/2),AG11) | AJ11: =IF((((AH11+AI11)/2)+(C11/(D11*((AH11+AI11)/2)))^2/(2*9.81)+B11-(G10+H10^2/(2*9.81))-(A10-A11)*(((DATOS!$B$34*(C11/(D11*((AH11+AI11)/2)))/((D11*((AH11+AI11)/2))/(D11+2*((AH11+AI11)/2)))^(2/3))^2+((DATOS!$B$34*H10/((D10*F10)/(D10+2*F10))^(2/3))^2))/2))>0,AH11,((AH11+AI11)/2)) | AK11: =IF((((AH11+AI11)/2)+(C11/(D11*((AH11+AI11)/2)))^2/(2*9.81)+B11-(G10+H10^2/(2*9.81))-(A10-A11)*(((DATOS!$B$34*(C11/(D11*((AH11+AI11)/2)))/((D11*((AH11+AI11)/2))/(D11+2*((AH11+AI11)/2)))^(2/3))^2+((DATOS!$B$34*H10/((D10*F10)/(D10+2*F10))^(2/3))^2))/2))>0,((AH11+AI11)/2),AI11) | AL11: =IF((((AJ11+AK11)/2)+(C11/(D11*((AJ11+AK11)/2)))^2/(2*9.81)+B11-(G10+H10^2/(2*9.81))-(A10-A11)*(((DATOS!$B$34*(C11/(D11*((AJ11+AK11)/2)))/((D11*((AJ11+AK11)/2))/(D11+2*((AJ11+AK11)/2)))^(2/3))^2+((DATOS!$B$34*H10/((D10*F10)/(D10+2*F10))^(2/3))^2))/2))>0,AJ11,((AJ11+AK11)/2)) | AM11: =IF((((AJ11+AK11)/2)+(C11/(D11*((AJ11+AK11)/2)))^2/(2*9.81)+B11-(G10+H10^2/(2*9.81))-(A10-A11)*(((DATOS!$B$34*(C11/(D11*((AJ11+AK11)/2)))/((D11*((AJ11+AK11)/2))/(D11+2*((AJ11+AK11)/2)))^(2/3))^2+((DATOS!$B$34*H10/((D10*F10)/(D10+2*F10))^(2/3))^2))/2))>0,((AJ11+AK11)/2),AK11) | AN11: =IF((((AL11+AM11)/2)+(C11/(D11*((AL11+AM11)/2)))^2/(2*9.81)+B11-(G10+H10^2/(2*9.81))-(A10-A11)*(((DATOS!$B$34*(C11/(D11*((AL11+AM11)/2)))/((D11*((AL11+AM11)/2))/(D11+2*((AL11+AM11)/2)))^(2/3))^2+((DATOS!$B$34*H10/((D10*F10)/(D10+2*F10))^(2/3))^2))/2))>0,AL11,((AL11+AM11)/2)) | AO11: =IF((((AL11+AM11)/2)+(C11/(D11*((AL11+AM11)/2)))^2/(2*9.81)+B11-(G10+H10^2/(2*9.81))-(A10-A11)*(((DATOS!$B$34*(C11/(D11*((AL11+AM11)/2)))/((D11*((AL11+AM11)/2))/(D11+2*((AL11+AM11)/2)))^(2/3))^2+((DATOS!$B$34*H10/((D10*F10)/(D10+2*F10))^(2/3))^2))/2))>0,((AL11+AM11)/2),AM11) | AP11: =IF((((AN11+AO11)/2)+(C11/(D11*((AN11+AO11)/2)))^2/(2*9.81)+B11-(G10+H10^2/(2*9.81))-(A10-A11)*(((DATOS!$B$34*(C11/(D11*((AN11+AO11)/2)))/((D11*((AN11+AO11)/2))/(D11+2*((AN11+AO11)/2)))^(2/3))^2+((DATOS!$B$34*H10/((D10*F10)/(D10+2*F10))^(2/3))^2))/2))>0,AN11,((AN11+AO11)/2)) | AQ11: =IF((((AN11+AO11)/2)+(C11/(D11*((AN11+AO11)/2)))^2/(2*9.81)+B11-(G10+H10^2/(2*9.81))-(A10-A11)*(((DATOS!$B$34*(C11/(D11*((AN11+AO11)/2)))/((D11*((AN11+AO11)/2))/(D11+2*((AN11+AO11)/2)))^(2/3))^2+((DATOS!$B$34*H10/((D10*F10)/(D10+2*F10))^(2/3))^2))/2))>0,((AN11+AO11)/2),AO11) | AR11: =IF((((AP11+AQ11)/2)+(C11/(D11*((AP11+AQ11)/2)))^2/(2*9.81)+B11-(G10+H10^2/(2*9.81))-(A10-A11)*(((DATOS!$B$34*(C11/(D11*((AP11+AQ11)/2)))/((D11*((AP11+AQ11)/2))/(D11+2*((AP11+AQ11)/2)))^(2/3))^2+((DATOS!$B$34*H10/((D10*F10)/(D10+2*F10))^(2/3))^2))/2))>0,AP11,((AP11+AQ11)/2)) | AS11: =IF((((AP11+AQ11)/2)+(C11/(D11*((AP11+AQ11)/2)))^2/(2*9.81)+B11-(G10+H10^2/(2*9.81))-(A10-A11)*(((DATOS!$B$34*(C11/(D11*((AP11+AQ11)/2)))/((D11*((AP11+AQ11)/2))/(D11+2*((AP11+AQ11)/2)))^(2/3))^2+((DATOS!$B$34*H10/((D10*F10)/(D10+2*F10))^(2/3))^2))/2))>0,((AP11+AQ11)/2),AQ11) | AT11: =IF((((AR11+AS11)/2)+(C11/(D11*((AR11+AS11)/2)))^2/(2*9.81)+B11-(G10+H10^2/(2*9.81))-(A10-A11)*(((DATOS!$B$34*(C11/(D11*((AR11+AS11)/2)))/((D11*((AR11+AS11)/2))/(D11+2*((AR11+AS11)/2)))^(2/3))^2+((DATOS!$B$34*H10/((D10*F10)/(D10+2*F10))^(2/3))^2))/2))>0,AR11,((AR11+AS11)/2)) | AU11: =IF((((AR11+AS11)/2)+(C11/(D11*((AR11+AS11)/2)))^2/(2*9.81)+B11-(G10+H10^2/(2*9.81))-(A10-A11)*(((DATOS!$B$34*(C11/(D11*((AR11+AS11)/2)))/((D11*((AR11+AS11)/2))/(D11+2*((AR11+AS11)/2)))^(2/3))^2+((DATOS!$B$34*H10/((D10*F10)/(D10+2*F10))^(2/3))^2))/2))>0,((AR11+AS11)/2),AS11) | AV11: =IF((((AT11+AU11)/2)+(C11/(D11*((AT11+AU11)/2)))^2/(2*9.81)+B11-(G10+H10^2/(2*9.81))-(A10-A11)*(((DATOS!$B$34*(C11/(D11*((AT11+AU11)/2)))/((D11*((AT11+AU11)/2))/(D11+2*((AT11+AU11)/2)))^(2/3))^2+((DATOS!$B$34*H10/((D10*F10)/(D10+2*F10))^(2/3))^2))/2))>0,AT11,((AT11+AU11)/2)) | AW11: =IF((((AT11+AU11)/2)+(C11/(D11*((AT11+AU11)/2)))^2/(2*9.81)+B11-(G10+H10^2/(2*9.81))-(A10-A11)*(((DATOS!$B$34*(C11/(D11*((AT11+AU11)/2)))/((D11*((AT11+AU11)/2))/(D11+2*((AT11+AU11)/2)))^(2/3))^2+((DATOS!$B$34*H10/((D10*F10)/(D10+2*F10))^(2/3))^2))/2))>0,((AT11+AU11)/2),AU11) | AX11: =IF((((AV11+AW11)/2)+(C11/(D11*((AV11+AW11)/2)))^2/(2*9.81)+B11-(G10+H10^2/(2*9.81))-(A10-A11)*(((DATOS!$B$34*(C11/(D11*((AV11+AW11)/2)))/((D11*((AV11+AW11)/2))/(D11+2*((AV11+AW11)/2)))^(2/3))^2+((DATOS!$B$34*H10/((D10*F10)/(D10+2*F10))^(2/3))^2))/2))>0,AV11,((AV11+AW11)/2)) | AY11: =IF((((AV11+AW11)/2)+(C11/(D11*((AV11+AW11)/2)))^2/(2*9.81)+B11-(G10+H10^2/(2*9.81))-(A10-A11)*(((DATOS!$B$34*(C11/(D11*((AV11+AW11)/2)))/((D11*((AV11+AW11)/2))/(D11+2*((AV11+AW11)/2)))^(2/3))^2+((DATOS!$B$34*H10/((D10*F10)/(D10+2*F10))^(2/3))^2))/2))>0,((AV11+AW11)/2),AW11) | AZ11: =IF((((AX11+AY11)/2)+(C11/(D11*((AX11+AY11)/2)))^2/(2*9.81)+B11-(G10+H10^2/(2*9.81))-(A10-A11)*(((DATOS!$B$34*(C11/(D11*((AX11+AY11)/2)))/((D11*((AX11+AY11)/2))/(D11+2*((AX11+AY11)/2)))^(2/3))^2+((DATOS!$B$34*H10/((D10*F10)/(D10+2*F10))^(2/3))^2))/2))>0,AX11,((AX11+AY11)/2)) | BA11: =IF((((AX11+AY11)/2)+(C11/(D11*((AX11+AY11)/2)))^2/(2*9.81)+B11-(G10+H10^2/(2*9.81))-(A10-A11)*(((DATOS!$B$34*(C11/(D11*((AX11+AY11)/2)))/((D11*((AX11+AY11)/2))/(D11+2*((AX11+AY11)/2)))^(2/3))^2+((DATOS!$B$34*H10/((D10*F10)/(D10+2*F10))^(2/3))^2))/2))>0,((AX11+AY11)/2),AY11) | BB11: =IF((((AZ11+BA11)/2)+(C11/(D11*((AZ11+BA11)/2)))^2/(2*9.81)+B11-(G10+H10^2/(2*9.81))-(A10-A11)*(((DATOS!$B$34*(C11/(D11*((AZ11+BA11)/2)))/((D11*((AZ11+BA11)/2))/(D11+2*((AZ11+BA11)/2)))^(2/3))^2+((DATOS!$B$34*H10/((D10*F10)/(D10+2*F10))^(2/3))^2))/2))>0,AZ11,((AZ11+BA11)/2)) | BC11: =IF((((AZ11+BA11)/2)+(C11/(D11*((AZ11+BA11)/2)))^2/(2*9.81)+B11-(G10+H10^2/(2*9.81))-(A10-A11)*(((DATOS!$B$34*(C11/(D11*((AZ11+BA11)/2)))/((D11*((AZ11+BA11)/2))/(D11+2*((AZ11+BA11)/2)))^(2/3))^2+((DATOS!$B$34*H10/((D10*F10)/(D10+2*F10))^(2/3))^2))/2))>0,((AZ11+BA11)/2),BA11) | BD11: =IF((((BB11+BC11)/2)+(C11/(D11*((BB11+BC11)/2)))^2/(2*9.81)+B11-(G10+H10^2/(2*9.81))-(A10-A11)*(((DATOS!$B$34*(C11/(D11*((BB11+BC11)/2)))/((D11*((BB11+BC11)/2))/(D11+2*((BB11+BC11)/2)))^(2/3))^2+((DATOS!$B$34*H10/((D10*F10)/(D10+2*F10))^(2/3))^2))/2))>0,BB11,((BB11+BC11)/2)) | BE11: =IF((((BB11+BC11)/2)+(C11/(D11*((BB11+BC11)/2)))^2/(2*9.81)+B11-(G10+H10^2/(2*9.81))-(A10-A11)*(((DATOS!$B$34*(C11/(D11*((BB11+BC11)/2)))/((D11*((BB11+BC11)/2))/(D11+2*((BB11+BC11)/2)))^(2/3))^2+((DATOS!$B$34*H10/((D10*F10)/(D10+2*F10))^(2/3))^2))/2))>0,((BB11+BC11)/2),BC11) | BF11: =IF((((BD11+BE11)/2)+(C11/(D11*((BD11+BE11)/2)))^2/(2*9.81)+B11-(G10+H10^2/(2*9.81))-(A10-A11)*(((DATOS!$B$34*(C11/(D11*((BD11+BE11)/2)))/((D11*((BD11+BE11)/2))/(D11+2*((BD11+BE11)/2)))^(2/3))^2+((DATOS!$B$34*H10/((D10*F10)/(D10+2*F10))^(2/3))^2))/2))>0,BD11,((BD11+BE11)/2)) | BG11: =IF((((BD11+BE11)/2)+(C11/(D11*((BD11+BE11)/2)))^2/(2*9.81)+B11-(G10+H10^2/(2*9.81))-(A10-A11)*(((DATOS!$B$34*(C11/(D11*((BD11+BE11)/2)))/((D11*((BD11+BE11)/2))/(D11+2*((BD11+BE11)/2)))^(2/3))^2+((DATOS!$B$34*H10/((D10*F10)/(D10+2*F10))^(2/3))^2))/2))>0,((BD11+BE11)/2),BE11) | BH11: =IF((((BF11+BG11)/2)+(C11/(D11*((BF11+BG11)/2)))^2/(2*9.81)+B11-(G10+H10^2/(2*9.81))-(A10-A11)*(((DATOS!$B$34*(C11/(D11*((BF11+BG11)/2)))/((D11*((BF11+BG11)/2))/(D11+2*((BF11+BG11)/2)))^(2/3))^2+((DATOS!$B$34*H10/((D10*F10)/(D10+2*F10))^(2/3))^2))/2))>0,BF11,((BF11+BG11)/2)) | BI11: =IF((((BF11+BG11)/2)+(C11/(D11*((BF11+BG11)/2)))^2/(2*9.81)+B11-(G10+H10^2/(2*9.81))-(A10-A11)*(((DATOS!$B$34*(C11/(D11*((BF11+BG11)/2)))/((D11*((BF11+BG11)/2))/(D11+2*((BF11+BG11)/2)))^(2/3))^2+((DATOS!$B$34*H10/((D10*F10)/(D10+2*F10))^(2/3))^2))/2))>0,((BF11+BG11)/2),BG11) | BJ11: =IF((((BH11+BI11)/2)+(C11/(D11*((BH11+BI11)/2)))^2/(2*9.81)+B11-(G10+H10^2/(2*9.81))-(A10-A11)*(((DATOS!$B$34*(C11/(D11*((BH11+BI11)/2)))/((D11*((BH11+BI11)/2))/(D11+2*((BH11+BI11)/2)))^(2/3))^2+((DATOS!$B$34*H10/((D10*F10)/(D10+2*F10))^(2/3))^2))/2))>0,BH11,((BH11+BI11)/2)) | BK11: =IF((((BH11+BI11)/2)+(C11/(D11*((BH11+BI11)/2)))^2/(2*9.81)+B11-(G10+H10^2/(2*9.81))-(A10-A11)*(((DATOS!$B$34*(C11/(D11*((BH11+BI11)/2)))/((D11*((BH11+BI11)/2))/(D11+2*((BH11+BI11)/2)))^(2/3))^2+((DATOS!$B$34*H10/((D10*F10)/(D10+2*F10))^(2/3))^2))/2))>0,((BH11+BI11)/2),BI11) | BL11: =IF((((BJ11+BK11)/2)+(C11/(D11*((BJ11+BK11)/2)))^2/(2*9.81)+B11-(G10+H10^2/(2*9.81))-(A10-A11)*(((DATOS!$B$34*(C11/(D11*((BJ11+BK11)/2)))/((D11*((BJ11+BK11)/2))/(D11+2*((BJ11+BK11)/2)))^(2/3))^2+((DATOS!$B$34*H10/((D10*F10)/(D10+2*F10))^(2/3))^2))/2))>0,BJ11,((BJ11+BK11)/2)) | BM11: =IF((((BJ11+BK11)/2)+(C11/(D11*((BJ11+BK11)/2)))^2/(2*9.81)+B11-(G10+H10^2/(2*9.81))-(A10-A11)*(((DATOS!$B$34*(C11/(D11*((BJ11+BK11)/2)))/((D11*((BJ11+BK11)/2))/(D11+2*((BJ11+BK11)/2)))^(2/3))^2+((DATOS!$B$34*H10/((D10*F10)/(D10+2*F10))^(2/3))^2))/2))>0,((BJ11+BK11)/2),BK11) | BN11: =IF((((BL11+BM11)/2)+(C11/(D11*((BL11+BM11)/2)))^2/(2*9.81)+B11-(G10+H10^2/(2*9.81))-(A10-A11)*(((DATOS!$B$34*(C11/(D11*((BL11+BM11)/2)))/((D11*((BL11+BM11)/2))/(D11+2*((BL11+BM11)/2)))^(2/3))^2+((DATOS!$B$34*H10/((D10*F10)/(D10+2*F10))^(2/3))^2))/2))>0,BL11,((BL11+BM11)/2)) | BO11: =IF((((BL11+BM11)/2)+(C11/(D11*((BL11+BM11)/2)))^2/(2*9.81)+B11-(G10+H10^2/(2*9.81))-(A10-A11)*(((DATOS!$B$34*(C11/(D11*((BL11+BM11)/2)))/((D11*((BL11+BM11)/2))/(D11+2*((BL11+BM11)/2)))^(2/3))^2+((DATOS!$B$34*H10/((D10*F10)/(D10+2*F10))^(2/3))^2))/2))>0,((BL11+BM11)/2),BM11) | BP11: =IF((((BN11+BO11)/2)+(C11/(D11*((BN11+BO11)/2)))^2/(2*9.81)+B11-(G10+H10^2/(2*9.81))-(A10-A11)*(((DATOS!$B$34*(C11/(D11*((BN11+BO11)/2)))/((D11*((BN11+BO11)/2))/(D11+2*((BN11+BO11)/2)))^(2/3))^2+((DATOS!$B$34*H10/((D10*F10)/(D10+2*F10))^(2/3))^2))/2))>0,BN11,((BN11+BO11)/2)) | BQ11: =IF((((BN11+BO11)/2)+(C11/(D11*((BN11+BO11)/2)))^2/(2*9.81)+B11-(G10+H10^2/(2*9.81))-(A10-A11)*(((DATOS!$B$34*(C11/(D11*((BN11+BO11)/2)))/((D11*((BN11+BO11)/2))/(D11+2*((BN11+BO11)/2)))^(2/3))^2+((DATOS!$B$34*H10/((D10*F10)/(D10+2*F10))^(2/3))^2))/2))>0,((BN11+BO11)/2),BO11) | BR11: =IF((((BP11+BQ11)/2)+(C11/(D11*((BP11+BQ11)/2)))^2/(2*9.81)+B11-(G10+H10^2/(2*9.81))-(A10-A11)*(((DATOS!$B$34*(C11/(D11*((BP11+BQ11)/2)))/((D11*((BP11+BQ11)/2))/(D11+2*((BP11+BQ11)/2)))^(2/3))^2+((DATOS!$B$34*H10/((D10*F10)/(D10+2*F10))^(2/3))^2))/2))>0,BP11,((BP11+BQ11)/2)) | BS11: =IF((((BP11+BQ11)/2)+(C11/(D11*((BP11+BQ11)/2)))^2/(2*9.81)+B11-(G10+H10^2/(2*9.81))-(A10-A11)*(((DATOS!$B$34*(C11/(D11*((BP11+BQ11)/2)))/((D11*((BP11+BQ11)/2))/(D11+2*((BP11+BQ11)/2)))^(2/3))^2+((DATOS!$B$34*H10/((D10*F10)/(D10+2*F10))^(2/3))^2))/2))>0,((BP11+BQ11)/2),BQ11) | BT11: =IF((((BR11+BS11)/2)+(C11/(D11*((BR11+BS11)/2)))^2/(2*9.81)+B11-(G10+H10^2/(2*9.81))-(A10-A11)*(((DATOS!$B$34*(C11/(D11*((BR11+BS11)/2)))/((D11*((BR11+BS11)/2))/(D11+2*((BR11+BS11)/2)))^(2/3))^2+((DATOS!$B$34*H10/((D10*F10)/(D10+2*F10))^(2/3))^2))/2))>0,BR11,((BR11+BS11)/2)) | BU11: =IF((((BR11+BS11)/2)+(C11/(D11*((BR11+BS11)/2)))^2/(2*9.81)+B11-(G10+H10^2/(2*9.81))-(A10-A11)*(((DATOS!$B$34*(C11/(D11*((BR11+BS11)/2)))/((D11*((BR11+BS11)/2))/(D11+2*((BR11+BS11)/2)))^(2/3))^2+((DATOS!$B$34*H10/((D10*F10)/(D10+2*F10))^(2/3))^2))/2))>0,((BR11+BS11)/2),BS11) | BV11: =IF((((BT11+BU11)/2)+(C11/(D11*((BT11+BU11)/2)))^2/(2*9.81)+B11-(G10+H10^2/(2*9.81))-(A10-A11)*(((DATOS!$B$34*(C11/(D11*((BT11+BU11)/2)))/((D11*((BT11+BU11)/2))/(D11+2*((BT11+BU11)/2)))^(2/3))^2+((DATOS!$B$34*H10/((D10*F10)/(D10+2*F10))^(2/3))^2))/2))>0,BT11,((BT11+BU11)/2)) | BW11: =IF((((BT11+BU11)/2)+(C11/(D11*((BT11+BU11)/2)))^2/(2*9.81)+B11-(G10+H10^2/(2*9.81))-(A10-A11)*(((DATOS!$B$34*(C11/(D11*((BT11+BU11)/2)))/((D11*((BT11+BU11)/2))/(D11+2*((BT11+BU11)/2)))^(2/3))^2+((DATOS!$B$34*H10/((D10*F10)/(D10+2*F10))^(2/3))^2))/2))>0,((BT11+BU11)/2),BU11)
A12: 66.89 | B12: =DATOS!$B$22-DATOS!$B$23*A12 | C12: =CAUDALES!$B$13 | D12: =DATOS!$B$17 | E12: =(C12^2/(9.81*D12^2))^(1/3) | F12: =(BV12+BW12)/2 | G12: =B12+F12 | H12: =C12/(D12*F12) | I12: =H12/SQRT(9.81*F12) | J12: =DATOS!$B$29-IF(AND(A12>=DATOS!$B$30,A12<DATOS!$B$31),DATOS!$B$21,DATOS!$B$20) | K12: =J12-B12 | L12: =F12/K12 | M12: =J12-G12 | N12: =IF(AND(L12<=DATOS!$B$36,M12>=DATOS!$B$37,I12<=1),"CUMPLE","NO CUMPLE") | O12: =IF(AND(A12>=DATOS!$B$30,A12<DATOS!$B$31),"cruce de camiones",IF(AND(A12>=DATOS!$B$32,A12<DATOS!$B$33),"cruce de motos","tramo normal")) | P12: =E12*1.001 | Q12: 3 | R12: =IF((((P12+Q12)/2)+(C12/(D12*((P12+Q12)/2)))^2/(2*9.81)+B12-(G11+H11^2/(2*9.81))-(A11-A12)*(((DATOS!$B$34*(C12/(D12*((P12+Q12)/2)))/((D12*((P12+Q12)/2))/(D12+2*((P12+Q12)/2)))^(2/3))^2+((DATOS!$B$34*H11/((D11*F11)/(D11+2*F11))^(2/3))^2))/2))>0,P12,((P12+Q12)/2)) | S12: =IF((((P12+Q12)/2)+(C12/(D12*((P12+Q12)/2)))^2/(2*9.81)+B12-(G11+H11^2/(2*9.81))-(A11-A12)*(((DATOS!$B$34*(C12/(D12*((P12+Q12)/2)))/((D12*((P12+Q12)/2))/(D12+2*((P12+Q12)/2)))^(2/3))^2+((DATOS!$B$34*H11/((D11*F11)/(D11+2*F11))^(2/3))^2))/2))>0,((P12+Q12)/2),Q12) | T12: =IF((((R12+S12)/2)+(C12/(D12*((R12+S12)/2)))^2/(2*9.81)+B12-(G11+H11^2/(2*9.81))-(A11-A12)*(((DATOS!$B$34*(C12/(D12*((R12+S12)/2)))/((D12*((R12+S12)/2))/(D12+2*((R12+S12)/2)))^(2/3))^2+((DATOS!$B$34*H11/((D11*F11)/(D11+2*F11))^(2/3))^2))/2))>0,R12,((R12+S12)/2)) | U12: =IF((((R12+S12)/2)+(C12/(D12*((R12+S12)/2)))^2/(2*9.81)+B12-(G11+H11^2/(2*9.81))-(A11-A12)*(((DATOS!$B$34*(C12/(D12*((R12+S12)/2)))/((D12*((R12+S12)/2))/(D12+2*((R12+S12)/2)))^(2/3))^2+((DATOS!$B$34*H11/((D11*F11)/(D11+2*F11))^(2/3))^2))/2))>0,((R12+S12)/2),S12) | V12: =IF((((T12+U12)/2)+(C12/(D12*((T12+U12)/2)))^2/(2*9.81)+B12-(G11+H11^2/(2*9.81))-(A11-A12)*(((DATOS!$B$34*(C12/(D12*((T12+U12)/2)))/((D12*((T12+U12)/2))/(D12+2*((T12+U12)/2)))^(2/3))^2+((DATOS!$B$34*H11/((D11*F11)/(D11+2*F11))^(2/3))^2))/2))>0,T12,((T12+U12)/2)) | W12: =IF((((T12+U12)/2)+(C12/(D12*((T12+U12)/2)))^2/(2*9.81)+B12-(G11+H11^2/(2*9.81))-(A11-A12)*(((DATOS!$B$34*(C12/(D12*((T12+U12)/2)))/((D12*((T12+U12)/2))/(D12+2*((T12+U12)/2)))^(2/3))^2+((DATOS!$B$34*H11/((D11*F11)/(D11+2*F11))^(2/3))^2))/2))>0,((T12+U12)/2),U12) | X12: =IF((((V12+W12)/2)+(C12/(D12*((V12+W12)/2)))^2/(2*9.81)+B12-(G11+H11^2/(2*9.81))-(A11-A12)*(((DATOS!$B$34*(C12/(D12*((V12+W12)/2)))/((D12*((V12+W12)/2))/(D12+2*((V12+W12)/2)))^(2/3))^2+((DATOS!$B$34*H11/((D11*F11)/(D11+2*F11))^(2/3))^2))/2))>0,V12,((V12+W12)/2)) | Y12: =IF((((V12+W12)/2)+(C12/(D12*((V12+W12)/2)))^2/(2*9.81)+B12-(G11+H11^2/(2*9.81))-(A11-A12)*(((DATOS!$B$34*(C12/(D12*((V12+W12)/2)))/((D12*((V12+W12)/2))/(D12+2*((V12+W12)/2)))^(2/3))^2+((DATOS!$B$34*H11/((D11*F11)/(D11+2*F11))^(2/3))^2))/2))>0,((V12+W12)/2),W12) | Z12: =IF((((X12+Y12)/2)+(C12/(D12*((X12+Y12)/2)))^2/(2*9.81)+B12-(G11+H11^2/(2*9.81))-(A11-A12)*(((DATOS!$B$34*(C12/(D12*((X12+Y12)/2)))/((D12*((X12+Y12)/2))/(D12+2*((X12+Y12)/2)))^(2/3))^2+((DATOS!$B$34*H11/((D11*F11)/(D11+2*F11))^(2/3))^2))/2))>0,X12,((X12+Y12)/2)) | AA12: =IF((((X12+Y12)/2)+(C12/(D12*((X12+Y12)/2)))^2/(2*9.81)+B12-(G11+H11^2/(2*9.81))-(A11-A12)*(((DATOS!$B$34*(C12/(D12*((X12+Y12)/2)))/((D12*((X12+Y12)/2))/(D12+2*((X12+Y12)/2)))^(2/3))^2+((DATOS!$B$34*H11/((D11*F11)/(D11+2*F11))^(2/3))^2))/2))>0,((X12+Y12)/2),Y12) | AB12: =IF((((Z12+AA12)/2)+(C12/(D12*((Z12+AA12)/2)))^2/(2*9.81)+B12-(G11+H11^2/(2*9.81))-(A11-A12)*(((DATOS!$B$34*(C12/(D12*((Z12+AA12)/2)))/((D12*((Z12+AA12)/2))/(D12+2*((Z12+AA12)/2)))^(2/3))^2+((DATOS!$B$34*H11/((D11*F11)/(D11+2*F11))^(2/3))^2))/2))>0,Z12,((Z12+AA12)/2)) | AC12: =IF((((Z12+AA12)/2)+(C12/(D12*((Z12+AA12)/2)))^2/(2*9.81)+B12-(G11+H11^2/(2*9.81))-(A11-A12)*(((DATOS!$B$34*(C12/(D12*((Z12+AA12)/2)))/((D12*((Z12+AA12)/2))/(D12+2*((Z12+AA12)/2)))^(2/3))^2+((DATOS!$B$34*H11/((D11*F11)/(D11+2*F11))^(2/3))^2))/2))>0,((Z12+AA12)/2),AA12) | AD12: =IF((((AB12+AC12)/2)+(C12/(D12*((AB12+AC12)/2)))^2/(2*9.81)+B12-(G11+H11^2/(2*9.81))-(A11-A12)*(((DATOS!$B$34*(C12/(D12*((AB12+AC12)/2)))/((D12*((AB12+AC12)/2))/(D12+2*((AB12+AC12)/2)))^(2/3))^2+((DATOS!$B$34*H11/((D11*F11)/(D11+2*F11))^(2/3))^2))/2))>0,AB12,((AB12+AC12)/2)) | AE12: =IF((((AB12+AC12)/2)+(C12/(D12*((AB12+AC12)/2)))^2/(2*9.81)+B12-(G11+H11^2/(2*9.81))-(A11-A12)*(((DATOS!$B$34*(C12/(D12*((AB12+AC12)/2)))/((D12*((AB12+AC12)/2))/(D12+2*((AB12+AC12)/2)))^(2/3))^2+((DATOS!$B$34*H11/((D11*F11)/(D11+2*F11))^(2/3))^2))/2))>0,((AB12+AC12)/2),AC12) | AF12: =IF((((AD12+AE12)/2)+(C12/(D12*((AD12+AE12)/2)))^2/(2*9.81)+B12-(G11+H11^2/(2*9.81))-(A11-A12)*(((DATOS!$B$34*(C12/(D12*((AD12+AE12)/2)))/((D12*((AD12+AE12)/2))/(D12+2*((AD12+AE12)/2)))^(2/3))^2+((DATOS!$B$34*H11/((D11*F11)/(D11+2*F11))^(2/3))^2))/2))>0,AD12,((AD12+AE12)/2)) | AG12: =IF((((AD12+AE12)/2)+(C12/(D12*((AD12+AE12)/2)))^2/(2*9.81)+B12-(G11+H11^2/(2*9.81))-(A11-A12)*(((DATOS!$B$34*(C12/(D12*((AD12+AE12)/2)))/((D12*((AD12+AE12)/2))/(D12+2*((AD12+AE12)/2)))^(2/3))^2+((DATOS!$B$34*H11/((D11*F11)/(D11+2*F11))^(2/3))^2))/2))>0,((AD12+AE12)/2),AE12) | AH12: =IF((((AF12+AG12)/2)+(C12/(D12*((AF12+AG12)/2)))^2/(2*9.81)+B12-(G11+H11^2/(2*9.81))-(A11-A12)*(((DATOS!$B$34*(C12/(D12*((AF12+AG12)/2)))/((D12*((AF12+AG12)/2))/(D12+2*((AF12+AG12)/2)))^(2/3))^2+((DATOS!$B$34*H11/((D11*F11)/(D11+2*F11))^(2/3))^2))/2))>0,AF12,((AF12+AG12)/2)) | AI12: =IF((((AF12+AG12)/2)+(C12/(D12*((AF12+AG12)/2)))^2/(2*9.81)+B12-(G11+H11^2/(2*9.81))-(A11-A12)*(((DATOS!$B$34*(C12/(D12*((AF12+AG12)/2)))/((D12*((AF12+AG12)/2))/(D12+2*((AF12+AG12)/2)))^(2/3))^2+((DATOS!$B$34*H11/((D11*F11)/(D11+2*F11))^(2/3))^2))/2))>0,((AF12+AG12)/2),AG12) | AJ12: =IF((((AH12+AI12)/2)+(C12/(D12*((AH12+AI12)/2)))^2/(2*9.81)+B12-(G11+H11^2/(2*9.81))-(A11-A12)*(((DATOS!$B$34*(C12/(D12*((AH12+AI12)/2)))/((D12*((AH12+AI12)/2))/(D12+2*((AH12+AI12)/2)))^(2/3))^2+((DATOS!$B$34*H11/((D11*F11)/(D11+2*F11))^(2/3))^2))/2))>0,AH12,((AH12+AI12)/2)) | AK12: =IF((((AH12+AI12)/2)+(C12/(D12*((AH12+AI12)/2)))^2/(2*9.81)+B12-(G11+H11^2/(2*9.81))-(A11-A12)*(((DATOS!$B$34*(C12/(D12*((AH12+AI12)/2)))/((D12*((AH12+AI12)/2))/(D12+2*((AH12+AI12)/2)))^(2/3))^2+((DATOS!$B$34*H11/((D11*F11)/(D11+2*F11))^(2/3))^2))/2))>0,((AH12+AI12)/2),AI12) | AL12: =IF((((AJ12+AK12)/2)+(C12/(D12*((AJ12+AK12)/2)))^2/(2*9.81)+B12-(G11+H11^2/(2*9.81))-(A11-A12)*(((DATOS!$B$34*(C12/(D12*((AJ12+AK12)/2)))/((D12*((AJ12+AK12)/2))/(D12+2*((AJ12+AK12)/2)))^(2/3))^2+((DATOS!$B$34*H11/((D11*F11)/(D11+2*F11))^(2/3))^2))/2))>0,AJ12,((AJ12+AK12)/2)) | AM12: =IF((((AJ12+AK12)/2)+(C12/(D12*((AJ12+AK12)/2)))^2/(2*9.81)+B12-(G11+H11^2/(2*9.81))-(A11-A12)*(((DATOS!$B$34*(C12/(D12*((AJ12+AK12)/2)))/((D12*((AJ12+AK12)/2))/(D12+2*((AJ12+AK12)/2)))^(2/3))^2+((DATOS!$B$34*H11/((D11*F11)/(D11+2*F11))^(2/3))^2))/2))>0,((AJ12+AK12)/2),AK12) | AN12: =IF((((AL12+AM12)/2)+(C12/(D12*((AL12+AM12)/2)))^2/(2*9.81)+B12-(G11+H11^2/(2*9.81))-(A11-A12)*(((DATOS!$B$34*(C12/(D12*((AL12+AM12)/2)))/((D12*((AL12+AM12)/2))/(D12+2*((AL12+AM12)/2)))^(2/3))^2+((DATOS!$B$34*H11/((D11*F11)/(D11+2*F11))^(2/3))^2))/2))>0,AL12,((AL12+AM12)/2)) | AO12: =IF((((AL12+AM12)/2)+(C12/(D12*((AL12+AM12)/2)))^2/(2*9.81)+B12-(G11+H11^2/(2*9.81))-(A11-A12)*(((DATOS!$B$34*(C12/(D12*((AL12+AM12)/2)))/((D12*((AL12+AM12)/2))/(D12+2*((AL12+AM12)/2)))^(2/3))^2+((DATOS!$B$34*H11/((D11*F11)/(D11+2*F11))^(2/3))^2))/2))>0,((AL12+AM12)/2),AM12) | AP12: =IF((((AN12+AO12)/2)+(C12/(D12*((AN12+AO12)/2)))^2/(2*9.81)+B12-(G11+H11^2/(2*9.81))-(A11-A12)*(((DATOS!$B$34*(C12/(D12*((AN12+AO12)/2)))/((D12*((AN12+AO12)/2))/(D12+2*((AN12+AO12)/2)))^(2/3))^2+((DATOS!$B$34*H11/((D11*F11)/(D11+2*F11))^(2/3))^2))/2))>0,AN12,((AN12+AO12)/2)) | AQ12: =IF((((AN12+AO12)/2)+(C12/(D12*((AN12+AO12)/2)))^2/(2*9.81)+B12-(G11+H11^2/(2*9.81))-(A11-A12)*(((DATOS!$B$34*(C12/(D12*((AN12+AO12)/2)))/((D12*((AN12+AO12)/2))/(D12+2*((AN12+AO12)/2)))^(2/3))^2+((DATOS!$B$34*H11/((D11*F11)/(D11+2*F11))^(2/3))^2))/2))>0,((AN12+AO12)/2),AO12) | AR12: =IF((((AP12+AQ12)/2)+(C12/(D12*((AP12+AQ12)/2)))^2/(2*9.81)+B12-(G11+H11^2/(2*9.81))-(A11-A12)*(((DATOS!$B$34*(C12/(D12*((AP12+AQ12)/2)))/((D12*((AP12+AQ12)/2))/(D12+2*((AP12+AQ12)/2)))^(2/3))^2+((DATOS!$B$34*H11/((D11*F11)/(D11+2*F11))^(2/3))^2))/2))>0,AP12,((AP12+AQ12)/2)) | AS12: =IF((((AP12+AQ12)/2)+(C12/(D12*((AP12+AQ12)/2)))^2/(2*9.81)+B12-(G11+H11^2/(2*9.81))-(A11-A12)*(((DATOS!$B$34*(C12/(D12*((AP12+AQ12)/2)))/((D12*((AP12+AQ12)/2))/(D12+2*((AP12+AQ12)/2)))^(2/3))^2+((DATOS!$B$34*H11/((D11*F11)/(D11+2*F11))^(2/3))^2))/2))>0,((AP12+AQ12)/2),AQ12) | AT12: =IF((((AR12+AS12)/2)+(C12/(D12*((AR12+AS12)/2)))^2/(2*9.81)+B12-(G11+H11^2/(2*9.81))-(A11-A12)*(((DATOS!$B$34*(C12/(D12*((AR12+AS12)/2)))/((D12*((AR12+AS12)/2))/(D12+2*((AR12+AS12)/2)))^(2/3))^2+((DATOS!$B$34*H11/((D11*F11)/(D11+2*F11))^(2/3))^2))/2))>0,AR12,((AR12+AS12)/2)) | AU12: =IF((((AR12+AS12)/2)+(C12/(D12*((AR12+AS12)/2)))^2/(2*9.81)+B12-(G11+H11^2/(2*9.81))-(A11-A12)*(((DATOS!$B$34*(C12/(D12*((AR12+AS12)/2)))/((D12*((AR12+AS12)/2))/(D12+2*((AR12+AS12)/2)))^(2/3))^2+((DATOS!$B$34*H11/((D11*F11)/(D11+2*F11))^(2/3))^2))/2))>0,((AR12+AS12)/2),AS12) | AV12: =IF((((AT12+AU12)/2)+(C12/(D12*((AT12+AU12)/2)))^2/(2*9.81)+B12-(G11+H11^2/(2*9.81))-(A11-A12)*(((DATOS!$B$34*(C12/(D12*((AT12+AU12)/2)))/((D12*((AT12+AU12)/2))/(D12+2*((AT12+AU12)/2)))^(2/3))^2+((DATOS!$B$34*H11/((D11*F11)/(D11+2*F11))^(2/3))^2))/2))>0,AT12,((AT12+AU12)/2)) | AW12: =IF((((AT12+AU12)/2)+(C12/(D12*((AT12+AU12)/2)))^2/(2*9.81)+B12-(G11+H11^2/(2*9.81))-(A11-A12)*(((DATOS!$B$34*(C12/(D12*((AT12+AU12)/2)))/((D12*((AT12+AU12)/2))/(D12+2*((AT12+AU12)/2)))^(2/3))^2+((DATOS!$B$34*H11/((D11*F11)/(D11+2*F11))^(2/3))^2))/2))>0,((AT12+AU12)/2),AU12) | AX12: =IF((((AV12+AW12)/2)+(C12/(D12*((AV12+AW12)/2)))^2/(2*9.81)+B12-(G11+H11^2/(2*9.81))-(A11-A12)*(((DATOS!$B$34*(C12/(D12*((AV12+AW12)/2)))/((D12*((AV12+AW12)/2))/(D12+2*((AV12+AW12)/2)))^(2/3))^2+((DATOS!$B$34*H11/((D11*F11)/(D11+2*F11))^(2/3))^2))/2))>0,AV12,((AV12+AW12)/2)) | AY12: =IF((((AV12+AW12)/2)+(C12/(D12*((AV12+AW12)/2)))^2/(2*9.81)+B12-(G11+H11^2/(2*9.81))-(A11-A12)*(((DATOS!$B$34*(C12/(D12*((AV12+AW12)/2)))/((D12*((AV12+AW12)/2))/(D12+2*((AV12+AW12)/2)))^(2/3))^2+((DATOS!$B$34*H11/((D11*F11)/(D11+2*F11))^(2/3))^2))/2))>0,((AV12+AW12)/2),AW12) | AZ12: =IF((((AX12+AY12)/2)+(C12/(D12*((AX12+AY12)/2)))^2/(2*9.81)+B12-(G11+H11^2/(2*9.81))-(A11-A12)*(((DATOS!$B$34*(C12/(D12*((AX12+AY12)/2)))/((D12*((AX12+AY12)/2))/(D12+2*((AX12+AY12)/2)))^(2/3))^2+((DATOS!$B$34*H11/((D11*F11)/(D11+2*F11))^(2/3))^2))/2))>0,AX12,((AX12+AY12)/2)) | BA12: =IF((((AX12+AY12)/2)+(C12/(D12*((AX12+AY12)/2)))^2/(2*9.81)+B12-(G11+H11^2/(2*9.81))-(A11-A12)*(((DATOS!$B$34*(C12/(D12*((AX12+AY12)/2)))/((D12*((AX12+AY12)/2))/(D12+2*((AX12+AY12)/2)))^(2/3))^2+((DATOS!$B$34*H11/((D11*F11)/(D11+2*F11))^(2/3))^2))/2))>0,((AX12+AY12)/2),AY12) | BB12: =IF((((AZ12+BA12)/2)+(C12/(D12*((AZ12+BA12)/2)))^2/(2*9.81)+B12-(G11+H11^2/(2*9.81))-(A11-A12)*(((DATOS!$B$34*(C12/(D12*((AZ12+BA12)/2)))/((D12*((AZ12+BA12)/2))/(D12+2*((AZ12+BA12)/2)))^(2/3))^2+((DATOS!$B$34*H11/((D11*F11)/(D11+2*F11))^(2/3))^2))/2))>0,AZ12,((AZ12+BA12)/2)) | BC12: =IF((((AZ12+BA12)/2)+(C12/(D12*((AZ12+BA12)/2)))^2/(2*9.81)+B12-(G11+H11^2/(2*9.81))-(A11-A12)*(((DATOS!$B$34*(C12/(D12*((AZ12+BA12)/2)))/((D12*((AZ12+BA12)/2))/(D12+2*((AZ12+BA12)/2)))^(2/3))^2+((DATOS!$B$34*H11/((D11*F11)/(D11+2*F11))^(2/3))^2))/2))>0,((AZ12+BA12)/2),BA12) | BD12: =IF((((BB12+BC12)/2)+(C12/(D12*((BB12+BC12)/2)))^2/(2*9.81)+B12-(G11+H11^2/(2*9.81))-(A11-A12)*(((DATOS!$B$34*(C12/(D12*((BB12+BC12)/2)))/((D12*((BB12+BC12)/2))/(D12+2*((BB12+BC12)/2)))^(2/3))^2+((DATOS!$B$34*H11/((D11*F11)/(D11+2*F11))^(2/3))^2))/2))>0,BB12,((BB12+BC12)/2)) | BE12: =IF((((BB12+BC12)/2)+(C12/(D12*((BB12+BC12)/2)))^2/(2*9.81)+B12-(G11+H11^2/(2*9.81))-(A11-A12)*(((DATOS!$B$34*(C12/(D12*((BB12+BC12)/2)))/((D12*((BB12+BC12)/2))/(D12+2*((BB12+BC12)/2)))^(2/3))^2+((DATOS!$B$34*H11/((D11*F11)/(D11+2*F11))^(2/3))^2))/2))>0,((BB12+BC12)/2),BC12) | BF12: =IF((((BD12+BE12)/2)+(C12/(D12*((BD12+BE12)/2)))^2/(2*9.81)+B12-(G11+H11^2/(2*9.81))-(A11-A12)*(((DATOS!$B$34*(C12/(D12*((BD12+BE12)/2)))/((D12*((BD12+BE12)/2))/(D12+2*((BD12+BE12)/2)))^(2/3))^2+((DATOS!$B$34*H11/((D11*F11)/(D11+2*F11))^(2/3))^2))/2))>0,BD12,((BD12+BE12)/2)) | BG12: =IF((((BD12+BE12)/2)+(C12/(D12*((BD12+BE12)/2)))^2/(2*9.81)+B12-(G11+H11^2/(2*9.81))-(A11-A12)*(((DATOS!$B$34*(C12/(D12*((BD12+BE12)/2)))/((D12*((BD12+BE12)/2))/(D12+2*((BD12+BE12)/2)))^(2/3))^2+((DATOS!$B$34*H11/((D11*F11)/(D11+2*F11))^(2/3))^2))/2))>0,((BD12+BE12)/2),BE12) | BH12: =IF((((BF12+BG12)/2)+(C12/(D12*((BF12+BG12)/2)))^2/(2*9.81)+B12-(G11+H11^2/(2*9.81))-(A11-A12)*(((DATOS!$B$34*(C12/(D12*((BF12+BG12)/2)))/((D12*((BF12+BG12)/2))/(D12+2*((BF12+BG12)/2)))^(2/3))^2+((DATOS!$B$34*H11/((D11*F11)/(D11+2*F11))^(2/3))^2))/2))>0,BF12,((BF12+BG12)/2)) | BI12: =IF((((BF12+BG12)/2)+(C12/(D12*((BF12+BG12)/2)))^2/(2*9.81)+B12-(G11+H11^2/(2*9.81))-(A11-A12)*(((DATOS!$B$34*(C12/(D12*((BF12+BG12)/2)))/((D12*((BF12+BG12)/2))/(D12+2*((BF12+BG12)/2)))^(2/3))^2+((DATOS!$B$34*H11/((D11*F11)/(D11+2*F11))^(2/3))^2))/2))>0,((BF12+BG12)/2),BG12) | BJ12: =IF((((BH12+BI12)/2)+(C12/(D12*((BH12+BI12)/2)))^2/(2*9.81)+B12-(G11+H11^2/(2*9.81))-(A11-A12)*(((DATOS!$B$34*(C12/(D12*((BH12+BI12)/2)))/((D12*((BH12+BI12)/2))/(D12+2*((BH12+BI12)/2)))^(2/3))^2+((DATOS!$B$34*H11/((D11*F11)/(D11+2*F11))^(2/3))^2))/2))>0,BH12,((BH12+BI12)/2)) | BK12: =IF((((BH12+BI12)/2)+(C12/(D12*((BH12+BI12)/2)))^2/(2*9.81)+B12-(G11+H11^2/(2*9.81))-(A11-A12)*(((DATOS!$B$34*(C12/(D12*((BH12+BI12)/2)))/((D12*((BH12+BI12)/2))/(D12+2*((BH12+BI12)/2)))^(2/3))^2+((DATOS!$B$34*H11/((D11*F11)/(D11+2*F11))^(2/3))^2))/2))>0,((BH12+BI12)/2),BI12) | BL12: =IF((((BJ12+BK12)/2)+(C12/(D12*((BJ12+BK12)/2)))^2/(2*9.81)+B12-(G11+H11^2/(2*9.81))-(A11-A12)*(((DATOS!$B$34*(C12/(D12*((BJ12+BK12)/2)))/((D12*((BJ12+BK12)/2))/(D12+2*((BJ12+BK12)/2)))^(2/3))^2+((DATOS!$B$34*H11/((D11*F11)/(D11+2*F11))^(2/3))^2))/2))>0,BJ12,((BJ12+BK12)/2)) | BM12: =IF((((BJ12+BK12)/2)+(C12/(D12*((BJ12+BK12)/2)))^2/(2*9.81)+B12-(G11+H11^2/(2*9.81))-(A11-A12)*(((DATOS!$B$34*(C12/(D12*((BJ12+BK12)/2)))/((D12*((BJ12+BK12)/2))/(D12+2*((BJ12+BK12)/2)))^(2/3))^2+((DATOS!$B$34*H11/((D11*F11)/(D11+2*F11))^(2/3))^2))/2))>0,((BJ12+BK12)/2),BK12) | BN12: =IF((((BL12+BM12)/2)+(C12/(D12*((BL12+BM12)/2)))^2/(2*9.81)+B12-(G11+H11^2/(2*9.81))-(A11-A12)*(((DATOS!$B$34*(C12/(D12*((BL12+BM12)/2)))/((D12*((BL12+BM12)/2))/(D12+2*((BL12+BM12)/2)))^(2/3))^2+((DATOS!$B$34*H11/((D11*F11)/(D11+2*F11))^(2/3))^2))/2))>0,BL12,((BL12+BM12)/2)) | BO12: =IF((((BL12+BM12)/2)+(C12/(D12*((BL12+BM12)/2)))^2/(2*9.81)+B12-(G11+H11^2/(2*9.81))-(A11-A12)*(((DATOS!$B$34*(C12/(D12*((BL12+BM12)/2)))/((D12*((BL12+BM12)/2))/(D12+2*((BL12+BM12)/2)))^(2/3))^2+((DATOS!$B$34*H11/((D11*F11)/(D11+2*F11))^(2/3))^2))/2))>0,((BL12+BM12)/2),BM12) | BP12: =IF((((BN12+BO12)/2)+(C12/(D12*((BN12+BO12)/2)))^2/(2*9.81)+B12-(G11+H11^2/(2*9.81))-(A11-A12)*(((DATOS!$B$34*(C12/(D12*((BN12+BO12)/2)))/((D12*((BN12+BO12)/2))/(D12+2*((BN12+BO12)/2)))^(2/3))^2+((DATOS!$B$34*H11/((D11*F11)/(D11+2*F11))^(2/3))^2))/2))>0,BN12,((BN12+BO12)/2)) | BQ12: =IF((((BN12+BO12)/2)+(C12/(D12*((BN12+BO12)/2)))^2/(2*9.81)+B12-(G11+H11^2/(2*9.81))-(A11-A12)*(((DATOS!$B$34*(C12/(D12*((BN12+BO12)/2)))/((D12*((BN12+BO12)/2))/(D12+2*((BN12+BO12)/2)))^(2/3))^2+((DATOS!$B$34*H11/((D11*F11)/(D11+2*F11))^(2/3))^2))/2))>0,((BN12+BO12)/2),BO12) | BR12: =IF((((BP12+BQ12)/2)+(C12/(D12*((BP12+BQ12)/2)))^2/(2*9.81)+B12-(G11+H11^2/(2*9.81))-(A11-A12)*(((DATOS!$B$34*(C12/(D12*((BP12+BQ12)/2)))/((D12*((BP12+BQ12)/2))/(D12+2*((BP12+BQ12)/2)))^(2/3))^2+((DATOS!$B$34*H11/((D11*F11)/(D11+2*F11))^(2/3))^2))/2))>0,BP12,((BP12+BQ12)/2)) | BS12: =IF((((BP12+BQ12)/2)+(C12/(D12*((BP12+BQ12)/2)))^2/(2*9.81)+B12-(G11+H11^2/(2*9.81))-(A11-A12)*(((DATOS!$B$34*(C12/(D12*((BP12+BQ12)/2)))/((D12*((BP12+BQ12)/2))/(D12+2*((BP12+BQ12)/2)))^(2/3))^2+((DATOS!$B$34*H11/((D11*F11)/(D11+2*F11))^(2/3))^2))/2))>0,((BP12+BQ12)/2),BQ12) | BT12: =IF((((BR12+BS12)/2)+(C12/(D12*((BR12+BS12)/2)))^2/(2*9.81)+B12-(G11+H11^2/(2*9.81))-(A11-A12)*(((DATOS!$B$34*(C12/(D12*((BR12+BS12)/2)))/((D12*((BR12+BS12)/2))/(D12+2*((BR12+BS12)/2)))^(2/3))^2+((DATOS!$B$34*H11/((D11*F11)/(D11+2*F11))^(2/3))^2))/2))>0,BR12,((BR12+BS12)/2)) | BU12: =IF((((BR12+BS12)/2)+(C12/(D12*((BR12+BS12)/2)))^2/(2*9.81)+B12-(G11+H11^2/(2*9.81))-(A11-A12)*(((DATOS!$B$34*(C12/(D12*((BR12+BS12)/2)))/((D12*((BR12+BS12)/2))/(D12+2*((BR12+BS12)/2)))^(2/3))^2+((DATOS!$B$34*H11/((D11*F11)/(D11+2*F11))^(2/3))^2))/2))>0,((BR12+BS12)/2),BS12) | BV12: =IF((((BT12+BU12)/2)+(C12/(D12*((BT12+BU12)/2)))^2/(2*9.81)+B12-(G11+H11^2/(2*9.81))-(A11-A12)*(((DATOS!$B$34*(C12/(D12*((BT12+BU12)/2)))/((D12*((BT12+BU12)/2))/(D12+2*((BT12+BU12)/2)))^(2/3))^2+((DATOS!$B$34*H11/((D11*F11)/(D11+2*F11))^(2/3))^2))/2))>0,BT12,((BT12+BU12)/2)) | BW12: =IF((((BT12+BU12)/2)+(C12/(D12*((BT12+BU12)/2)))^2/(2*9.81)+B12-(G11+H11^2/(2*9.81))-(A11-A12)*(((DATOS!$B$34*(C12/(D12*((BT12+BU12)/2)))/((D12*((BT12+BU12)/2))/(D12+2*((BT12+BU12)/2)))^(2/3))^2+((DATOS!$B$34*H11/((D11*F11)/(D11+2*F11))^(2/3))^2))/2))>0,((BT12+BU12)/2),BU12)
A13: 66 | B13: =DATOS!$B$22-DATOS!$B$23*A13 | C13: =CAUDALES!$B$13 | D13: =DATOS!$B$17 | E13: =(C13^2/(9.81*D13^2))^(1/3) | F13: =(BV13+BW13)/2 | G13: =B13+F13 | H13: =C13/(D13*F13) | I13: =H13/SQRT(9.81*F13) | J13: =DATOS!$B$29-IF(AND(A13>=DATOS!$B$30,A13<DATOS!$B$31),DATOS!$B$21,DATOS!$B$20) | K13: =J13-B13 | L13: =F13/K13 | M13: =J13-G13 | N13: =IF(AND(L13<=DATOS!$B$36,M13>=DATOS!$B$37,I13<=1),"CUMPLE","NO CUMPLE") | O13: =IF(AND(A13>=DATOS!$B$30,A13<DATOS!$B$31),"cruce de camiones",IF(AND(A13>=DATOS!$B$32,A13<DATOS!$B$33),"cruce de motos","tramo normal")) | P13: =E13*1.001 | Q13: 3 | R13: =IF((((P13+Q13)/2)+(C13/(D13*((P13+Q13)/2)))^2/(2*9.81)+B13-(G12+H12^2/(2*9.81))-(A12-A13)*(((DATOS!$B$34*(C13/(D13*((P13+Q13)/2)))/((D13*((P13+Q13)/2))/(D13+2*((P13+Q13)/2)))^(2/3))^2+((DATOS!$B$34*H12/((D12*F12)/(D12+2*F12))^(2/3))^2))/2))>0,P13,((P13+Q13)/2)) | S13: =IF((((P13+Q13)/2)+(C13/(D13*((P13+Q13)/2)))^2/(2*9.81)+B13-(G12+H12^2/(2*9.81))-(A12-A13)*(((DATOS!$B$34*(C13/(D13*((P13+Q13)/2)))/((D13*((P13+Q13)/2))/(D13+2*((P13+Q13)/2)))^(2/3))^2+((DATOS!$B$34*H12/((D12*F12)/(D12+2*F12))^(2/3))^2))/2))>0,((P13+Q13)/2),Q13) | T13: =IF((((R13+S13)/2)+(C13/(D13*((R13+S13)/2)))^2/(2*9.81)+B13-(G12+H12^2/(2*9.81))-(A12-A13)*(((DATOS!$B$34*(C13/(D13*((R13+S13)/2)))/((D13*((R13+S13)/2))/(D13+2*((R13+S13)/2)))^(2/3))^2+((DATOS!$B$34*H12/((D12*F12)/(D12+2*F12))^(2/3))^2))/2))>0,R13,((R13+S13)/2)) | U13: =IF((((R13+S13)/2)+(C13/(D13*((R13+S13)/2)))^2/(2*9.81)+B13-(G12+H12^2/(2*9.81))-(A12-A13)*(((DATOS!$B$34*(C13/(D13*((R13+S13)/2)))/((D13*((R13+S13)/2))/(D13+2*((R13+S13)/2)))^(2/3))^2+((DATOS!$B$34*H12/((D12*F12)/(D12+2*F12))^(2/3))^2))/2))>0,((R13+S13)/2),S13) | V13: =IF((((T13+U13)/2)+(C13/(D13*((T13+U13)/2)))^2/(2*9.81)+B13-(G12+H12^2/(2*9.81))-(A12-A13)*(((DATOS!$B$34*(C13/(D13*((T13+U13)/2)))/((D13*((T13+U13)/2))/(D13+2*((T13+U13)/2)))^(2/3))^2+((DATOS!$B$34*H12/((D12*F12)/(D12+2*F12))^(2/3))^2))/2))>0,T13,((T13+U13)/2)) | W13: =IF((((T13+U13)/2)+(C13/(D13*((T13+U13)/2)))^2/(2*9.81)+B13-(G12+H12^2/(2*9.81))-(A12-A13)*(((DATOS!$B$34*(C13/(D13*((T13+U13)/2)))/((D13*((T13+U13)/2))/(D13+2*((T13+U13)/2)))^(2/3))^2+((DATOS!$B$34*H12/((D12*F12)/(D12+2*F12))^(2/3))^2))/2))>0,((T13+U13)/2),U13) | X13: =IF((((V13+W13)/2)+(C13/(D13*((V13+W13)/2)))^2/(2*9.81)+B13-(G12+H12^2/(2*9.81))-(A12-A13)*(((DATOS!$B$34*(C13/(D13*((V13+W13)/2)))/((D13*((V13+W13)/2))/(D13+2*((V13+W13)/2)))^(2/3))^2+((DATOS!$B$34*H12/((D12*F12)/(D12+2*F12))^(2/3))^2))/2))>0,V13,((V13+W13)/2)) | Y13: =IF((((V13+W13)/2)+(C13/(D13*((V13+W13)/2)))^2/(2*9.81)+B13-(G12+H12^2/(2*9.81))-(A12-A13)*(((DATOS!$B$34*(C13/(D13*((V13+W13)/2)))/((D13*((V13+W13)/2))/(D13+2*((V13+W13)/2)))^(2/3))^2+((DATOS!$B$34*H12/((D12*F12)/(D12+2*F12))^(2/3))^2))/2))>0,((V13+W13)/2),W13) | Z13: =IF((((X13+Y13)/2)+(C13/(D13*((X13+Y13)/2)))^2/(2*9.81)+B13-(G12+H12^2/(2*9.81))-(A12-A13)*(((DATOS!$B$34*(C13/(D13*((X13+Y13)/2)))/((D13*((X13+Y13)/2))/(D13+2*((X13+Y13)/2)))^(2/3))^2+((DATOS!$B$34*H12/((D12*F12)/(D12+2*F12))^(2/3))^2))/2))>0,X13,((X13+Y13)/2)) | AA13: =IF((((X13+Y13)/2)+(C13/(D13*((X13+Y13)/2)))^2/(2*9.81)+B13-(G12+H12^2/(2*9.81))-(A12-A13)*(((DATOS!$B$34*(C13/(D13*((X13+Y13)/2)))/((D13*((X13+Y13)/2))/(D13+2*((X13+Y13)/2)))^(2/3))^2+((DATOS!$B$34*H12/((D12*F12)/(D12+2*F12))^(2/3))^2))/2))>0,((X13+Y13)/2),Y13) | AB13: =IF((((Z13+AA13)/2)+(C13/(D13*((Z13+AA13)/2)))^2/(2*9.81)+B13-(G12+H12^2/(2*9.81))-(A12-A13)*(((DATOS!$B$34*(C13/(D13*((Z13+AA13)/2)))/((D13*((Z13+AA13)/2))/(D13+2*((Z13+AA13)/2)))^(2/3))^2+((DATOS!$B$34*H12/((D12*F12)/(D12+2*F12))^(2/3))^2))/2))>0,Z13,((Z13+AA13)/2)) | AC13: =IF((((Z13+AA13)/2)+(C13/(D13*((Z13+AA13)/2)))^2/(2*9.81)+B13-(G12+H12^2/(2*9.81))-(A12-A13)*(((DATOS!$B$34*(C13/(D13*((Z13+AA13)/2)))/((D13*((Z13+AA13)/2))/(D13+2*((Z13+AA13)/2)))^(2/3))^2+((DATOS!$B$34*H12/((D12*F12)/(D12+2*F12))^(2/3))^2))/2))>0,((Z13+AA13)/2),AA13) | AD13: =IF((((AB13+AC13)/2)+(C13/(D13*((AB13+AC13)/2)))^2/(2*9.81)+B13-(G12+H12^2/(2*9.81))-(A12-A13)*(((DATOS!$B$34*(C13/(D13*((AB13+AC13)/2)))/((D13*((AB13+AC13)/2))/(D13+2*((AB13+AC13)/2)))^(2/3))^2+((DATOS!$B$34*H12/((D12*F12)/(D12+2*F12))^(2/3))^2))/2))>0,AB13,((AB13+AC13)/2)) | AE13: =IF((((AB13+AC13)/2)+(C13/(D13*((AB13+AC13)/2)))^2/(2*9.81)+B13-(G12+H12^2/(2*9.81))-(A12-A13)*(((DATOS!$B$34*(C13/(D13*((AB13+AC13)/2)))/((D13*((AB13+AC13)/2))/(D13+2*((AB13+AC13)/2)))^(2/3))^2+((DATOS!$B$34*H12/((D12*F12)/(D12+2*F12))^(2/3))^2))/2))>0,((AB13+AC13)/2),AC13) | AF13: =IF((((AD13+AE13)/2)+(C13/(D13*((AD13+AE13)/2)))^2/(2*9.81)+B13-(G12+H12^2/(2*9.81))-(A12-A13)*(((DATOS!$B$34*(C13/(D13*((AD13+AE13)/2)))/((D13*((AD13+AE13)/2))/(D13+2*((AD13+AE13)/2)))^(2/3))^2+((DATOS!$B$34*H12/((D12*F12)/(D12+2*F12))^(2/3))^2))/2))>0,AD13,((AD13+AE13)/2)) | AG13: =IF((((AD13+AE13)/2)+(C13/(D13*((AD13+AE13)/2)))^2/(2*9.81)+B13-(G12+H12^2/(2*9.81))-(A12-A13)*(((DATOS!$B$34*(C13/(D13*((AD13+AE13)/2)))/((D13*((AD13+AE13)/2))/(D13+2*((AD13+AE13)/2)))^(2/3))^2+((DATOS!$B$34*H12/((D12*F12)/(D12+2*F12))^(2/3))^2))/2))>0,((AD13+AE13)/2),AE13) | AH13: =IF((((AF13+AG13)/2)+(C13/(D13*((AF13+AG13)/2)))^2/(2*9.81)+B13-(G12+H12^2/(2*9.81))-(A12-A13)*(((DATOS!$B$34*(C13/(D13*((AF13+AG13)/2)))/((D13*((AF13+AG13)/2))/(D13+2*((AF13+AG13)/2)))^(2/3))^2+((DATOS!$B$34*H12/((D12*F12)/(D12+2*F12))^(2/3))^2))/2))>0,AF13,((AF13+AG13)/2)) | AI13: =IF((((AF13+AG13)/2)+(C13/(D13*((AF13+AG13)/2)))^2/(2*9.81)+B13-(G12+H12^2/(2*9.81))-(A12-A13)*(((DATOS!$B$34*(C13/(D13*((AF13+AG13)/2)))/((D13*((AF13+AG13)/2))/(D13+2*((AF13+AG13)/2)))^(2/3))^2+((DATOS!$B$34*H12/((D12*F12)/(D12+2*F12))^(2/3))^2))/2))>0,((AF13+AG13)/2),AG13) | AJ13: =IF((((AH13+AI13)/2)+(C13/(D13*((AH13+AI13)/2)))^2/(2*9.81)+B13-(G12+H12^2/(2*9.81))-(A12-A13)*(((DATOS!$B$34*(C13/(D13*((AH13+AI13)/2)))/((D13*((AH13+AI13)/2))/(D13+2*((AH13+AI13)/2)))^(2/3))^2+((DATOS!$B$34*H12/((D12*F12)/(D12+2*F12))^(2/3))^2))/2))>0,AH13,((AH13+AI13)/2)) | AK13: =IF((((AH13+AI13)/2)+(C13/(D13*((AH13+AI13)/2)))^2/(2*9.81)+B13-(G12+H12^2/(2*9.81))-(A12-A13)*(((DATOS!$B$34*(C13/(D13*((AH13+AI13)/2)))/((D13*((AH13+AI13)/2))/(D13+2*((AH13+AI13)/2)))^(2/3))^2+((DATOS!$B$34*H12/((D12*F12)/(D12+2*F12))^(2/3))^2))/2))>0,((AH13+AI13)/2),AI13) | AL13: =IF((((AJ13+AK13)/2)+(C13/(D13*((AJ13+AK13)/2)))^2/(2*9.81)+B13-(G12+H12^2/(2*9.81))-(A12-A13)*(((DATOS!$B$34*(C13/(D13*((AJ13+AK13)/2)))/((D13*((AJ13+AK13)/2))/(D13+2*((AJ13+AK13)/2)))^(2/3))^2+((DATOS!$B$34*H12/((D12*F12)/(D12+2*F12))^(2/3))^2))/2))>0,AJ13,((AJ13+AK13)/2)) | AM13: =IF((((AJ13+AK13)/2)+(C13/(D13*((AJ13+AK13)/2)))^2/(2*9.81)+B13-(G12+H12^2/(2*9.81))-(A12-A13)*(((DATOS!$B$34*(C13/(D13*((AJ13+AK13)/2)))/((D13*((AJ13+AK13)/2))/(D13+2*((AJ13+AK13)/2)))^(2/3))^2+((DATOS!$B$34*H12/((D12*F12)/(D12+2*F12))^(2/3))^2))/2))>0,((AJ13+AK13)/2),AK13) | AN13: =IF((((AL13+AM13)/2)+(C13/(D13*((AL13+AM13)/2)))^2/(2*9.81)+B13-(G12+H12^2/(2*9.81))-(A12-A13)*(((DATOS!$B$34*(C13/(D13*((AL13+AM13)/2)))/((D13*((AL13+AM13)/2))/(D13+2*((AL13+AM13)/2)))^(2/3))^2+((DATOS!$B$34*H12/((D12*F12)/(D12+2*F12))^(2/3))^2))/2))>0,AL13,((AL13+AM13)/2)) | AO13: =IF((((AL13+AM13)/2)+(C13/(D13*((AL13+AM13)/2)))^2/(2*9.81)+B13-(G12+H12^2/(2*9.81))-(A12-A13)*(((DATOS!$B$34*(C13/(D13*((AL13+AM13)/2)))/((D13*((AL13+AM13)/2))/(D13+2*((AL13+AM13)/2)))^(2/3))^2+((DATOS!$B$34*H12/((D12*F12)/(D12+2*F12))^(2/3))^2))/2))>0,((AL13+AM13)/2),AM13) | AP13: =IF((((AN13+AO13)/2)+(C13/(D13*((AN13+AO13)/2)))^2/(2*9.81)+B13-(G12+H12^2/(2*9.81))-(A12-A13)*(((DATOS!$B$34*(C13/(D13*((AN13+AO13)/2)))/((D13*((AN13+AO13)/2))/(D13+2*((AN13+AO13)/2)))^(2/3))^2+((DATOS!$B$34*H12/((D12*F12)/(D12+2*F12))^(2/3))^2))/2))>0,AN13,((AN13+AO13)/2)) | AQ13: =IF((((AN13+AO13)/2)+(C13/(D13*((AN13+AO13)/2)))^2/(2*9.81)+B13-(G12+H12^2/(2*9.81))-(A12-A13)*(((DATOS!$B$34*(C13/(D13*((AN13+AO13)/2)))/((D13*((AN13+AO13)/2))/(D13+2*((AN13+AO13)/2)))^(2/3))^2+((DATOS!$B$34*H12/((D12*F12)/(D12+2*F12))^(2/3))^2))/2))>0,((AN13+AO13)/2),AO13) | AR13: =IF((((AP13+AQ13)/2)+(C13/(D13*((AP13+AQ13)/2)))^2/(2*9.81)+B13-(G12+H12^2/(2*9.81))-(A12-A13)*(((DATOS!$B$34*(C13/(D13*((AP13+AQ13)/2)))/((D13*((AP13+AQ13)/2))/(D13+2*((AP13+AQ13)/2)))^(2/3))^2+((DATOS!$B$34*H12/((D12*F12)/(D12+2*F12))^(2/3))^2))/2))>0,AP13,((AP13+AQ13)/2)) | AS13: =IF((((AP13+AQ13)/2)+(C13/(D13*((AP13+AQ13)/2)))^2/(2*9.81)+B13-(G12+H12^2/(2*9.81))-(A12-A13)*(((DATOS!$B$34*(C13/(D13*((AP13+AQ13)/2)))/((D13*((AP13+AQ13)/2))/(D13+2*((AP13+AQ13)/2)))^(2/3))^2+((DATOS!$B$34*H12/((D12*F12)/(D12+2*F12))^(2/3))^2))/2))>0,((AP13+AQ13)/2),AQ13) | AT13: =IF((((AR13+AS13)/2)+(C13/(D13*((AR13+AS13)/2)))^2/(2*9.81)+B13-(G12+H12^2/(2*9.81))-(A12-A13)*(((DATOS!$B$34*(C13/(D13*((AR13+AS13)/2)))/((D13*((AR13+AS13)/2))/(D13+2*((AR13+AS13)/2)))^(2/3))^2+((DATOS!$B$34*H12/((D12*F12)/(D12+2*F12))^(2/3))^2))/2))>0,AR13,((AR13+AS13)/2)) | AU13: =IF((((AR13+AS13)/2)+(C13/(D13*((AR13+AS13)/2)))^2/(2*9.81)+B13-(G12+H12^2/(2*9.81))-(A12-A13)*(((DATOS!$B$34*(C13/(D13*((AR13+AS13)/2)))/((D13*((AR13+AS13)/2))/(D13+2*((AR13+AS13)/2)))^(2/3))^2+((DATOS!$B$34*H12/((D12*F12)/(D12+2*F12))^(2/3))^2))/2))>0,((AR13+AS13)/2),AS13) | AV13: =IF((((AT13+AU13)/2)+(C13/(D13*((AT13+AU13)/2)))^2/(2*9.81)+B13-(G12+H12^2/(2*9.81))-(A12-A13)*(((DATOS!$B$34*(C13/(D13*((AT13+AU13)/2)))/((D13*((AT13+AU13)/2))/(D13+2*((AT13+AU13)/2)))^(2/3))^2+((DATOS!$B$34*H12/((D12*F12)/(D12+2*F12))^(2/3))^2))/2))>0,AT13,((AT13+AU13)/2)) | AW13: =IF((((AT13+AU13)/2)+(C13/(D13*((AT13+AU13)/2)))^2/(2*9.81)+B13-(G12+H12^2/(2*9.81))-(A12-A13)*(((DATOS!$B$34*(C13/(D13*((AT13+AU13)/2)))/((D13*((AT13+AU13)/2))/(D13+2*((AT13+AU13)/2)))^(2/3))^2+((DATOS!$B$34*H12/((D12*F12)/(D12+2*F12))^(2/3))^2))/2))>0,((AT13+AU13)/2),AU13) | AX13: =IF((((AV13+AW13)/2)+(C13/(D13*((AV13+AW13)/2)))^2/(2*9.81)+B13-(G12+H12^2/(2*9.81))-(A12-A13)*(((DATOS!$B$34*(C13/(D13*((AV13+AW13)/2)))/((D13*((AV13+AW13)/2))/(D13+2*((AV13+AW13)/2)))^(2/3))^2+((DATOS!$B$34*H12/((D12*F12)/(D12+2*F12))^(2/3))^2))/2))>0,AV13,((AV13+AW13)/2)) | AY13: =IF((((AV13+AW13)/2)+(C13/(D13*((AV13+AW13)/2)))^2/(2*9.81)+B13-(G12+H12^2/(2*9.81))-(A12-A13)*(((DATOS!$B$34*(C13/(D13*((AV13+AW13)/2)))/((D13*((AV13+AW13)/2))/(D13+2*((AV13+AW13)/2)))^(2/3))^2+((DATOS!$B$34*H12/((D12*F12)/(D12+2*F12))^(2/3))^2))/2))>0,((AV13+AW13)/2),AW13) | AZ13: =IF((((AX13+AY13)/2)+(C13/(D13*((AX13+AY13)/2)))^2/(2*9.81)+B13-(G12+H12^2/(2*9.81))-(A12-A13)*(((DATOS!$B$34*(C13/(D13*((AX13+AY13)/2)))/((D13*((AX13+AY13)/2))/(D13+2*((AX13+AY13)/2)))^(2/3))^2+((DATOS!$B$34*H12/((D12*F12)/(D12+2*F12))^(2/3))^2))/2))>0,AX13,((AX13+AY13)/2)) | BA13: =IF((((AX13+AY13)/2)+(C13/(D13*((AX13+AY13)/2)))^2/(2*9.81)+B13-(G12+H12^2/(2*9.81))-(A12-A13)*(((DATOS!$B$34*(C13/(D13*((AX13+AY13)/2)))/((D13*((AX13+AY13)/2))/(D13+2*((AX13+AY13)/2)))^(2/3))^2+((DATOS!$B$34*H12/((D12*F12)/(D12+2*F12))^(2/3))^2))/2))>0,((AX13+AY13)/2),AY13) | BB13: =IF((((AZ13+BA13)/2)+(C13/(D13*((AZ13+BA13)/2)))^2/(2*9.81)+B13-(G12+H12^2/(2*9.81))-(A12-A13)*(((DATOS!$B$34*(C13/(D13*((AZ13+BA13)/2)))/((D13*((AZ13+BA13)/2))/(D13+2*((AZ13+BA13)/2)))^(2/3))^2+((DATOS!$B$34*H12/((D12*F12)/(D12+2*F12))^(2/3))^2))/2))>0,AZ13,((AZ13+BA13)/2)) | BC13: =IF((((AZ13+BA13)/2)+(C13/(D13*((AZ13+BA13)/2)))^2/(2*9.81)+B13-(G12+H12^2/(2*9.81))-(A12-A13)*(((DATOS!$B$34*(C13/(D13*((AZ13+BA13)/2)))/((D13*((AZ13+BA13)/2))/(D13+2*((AZ13+BA13)/2)))^(2/3))^2+((DATOS!$B$34*H12/((D12*F12)/(D12+2*F12))^(2/3))^2))/2))>0,((AZ13+BA13)/2),BA13) | BD13: =IF((((BB13+BC13)/2)+(C13/(D13*((BB13+BC13)/2)))^2/(2*9.81)+B13-(G12+H12^2/(2*9.81))-(A12-A13)*(((DATOS!$B$34*(C13/(D13*((BB13+BC13)/2)))/((D13*((BB13+BC13)/2))/(D13+2*((BB13+BC13)/2)))^(2/3))^2+((DATOS!$B$34*H12/((D12*F12)/(D12+2*F12))^(2/3))^2))/2))>0,BB13,((BB13+BC13)/2)) | BE13: =IF((((BB13+BC13)/2)+(C13/(D13*((BB13+BC13)/2)))^2/(2*9.81)+B13-(G12+H12^2/(2*9.81))-(A12-A13)*(((DATOS!$B$34*(C13/(D13*((BB13+BC13)/2)))/((D13*((BB13+BC13)/2))/(D13+2*((BB13+BC13)/2)))^(2/3))^2+((DATOS!$B$34*H12/((D12*F12)/(D12+2*F12))^(2/3))^2))/2))>0,((BB13+BC13)/2),BC13) | BF13: =IF((((BD13+BE13)/2)+(C13/(D13*((BD13+BE13)/2)))^2/(2*9.81)+B13-(G12+H12^2/(2*9.81))-(A12-A13)*(((DATOS!$B$34*(C13/(D13*((BD13+BE13)/2)))/((D13*((BD13+BE13)/2))/(D13+2*((BD13+BE13)/2)))^(2/3))^2+((DATOS!$B$34*H12/((D12*F12)/(D12+2*F12))^(2/3))^2))/2))>0,BD13,((BD13+BE13)/2)) | BG13: =IF((((BD13+BE13)/2)+(C13/(D13*((BD13+BE13)/2)))^2/(2*9.81)+B13-(G12+H12^2/(2*9.81))-(A12-A13)*(((DATOS!$B$34*(C13/(D13*((BD13+BE13)/2)))/((D13*((BD13+BE13)/2))/(D13+2*((BD13+BE13)/2)))^(2/3))^2+((DATOS!$B$34*H12/((D12*F12)/(D12+2*F12))^(2/3))^2))/2))>0,((BD13+BE13)/2),BE13) | BH13: =IF((((BF13+BG13)/2)+(C13/(D13*((BF13+BG13)/2)))^2/(2*9.81)+B13-(G12+H12^2/(2*9.81))-(A12-A13)*(((DATOS!$B$34*(C13/(D13*((BF13+BG13)/2)))/((D13*((BF13+BG13)/2))/(D13+2*((BF13+BG13)/2)))^(2/3))^2+((DATOS!$B$34*H12/((D12*F12)/(D12+2*F12))^(2/3))^2))/2))>0,BF13,((BF13+BG13)/2)) | BI13: =IF((((BF13+BG13)/2)+(C13/(D13*((BF13+BG13)/2)))^2/(2*9.81)+B13-(G12+H12^2/(2*9.81))-(A12-A13)*(((DATOS!$B$34*(C13/(D13*((BF13+BG13)/2)))/((D13*((BF13+BG13)/2))/(D13+2*((BF13+BG13)/2)))^(2/3))^2+((DATOS!$B$34*H12/((D12*F12)/(D12+2*F12))^(2/3))^2))/2))>0,((BF13+BG13)/2),BG13) | BJ13: =IF((((BH13+BI13)/2)+(C13/(D13*((BH13+BI13)/2)))^2/(2*9.81)+B13-(G12+H12^2/(2*9.81))-(A12-A13)*(((DATOS!$B$34*(C13/(D13*((BH13+BI13)/2)))/((D13*((BH13+BI13)/2))/(D13+2*((BH13+BI13)/2)))^(2/3))^2+((DATOS!$B$34*H12/((D12*F12)/(D12+2*F12))^(2/3))^2))/2))>0,BH13,((BH13+BI13)/2)) | BK13: =IF((((BH13+BI13)/2)+(C13/(D13*((BH13+BI13)/2)))^2/(2*9.81)+B13-(G12+H12^2/(2*9.81))-(A12-A13)*(((DATOS!$B$34*(C13/(D13*((BH13+BI13)/2)))/((D13*((BH13+BI13)/2))/(D13+2*((BH13+BI13)/2)))^(2/3))^2+((DATOS!$B$34*H12/((D12*F12)/(D12+2*F12))^(2/3))^2))/2))>0,((BH13+BI13)/2),BI13) | BL13: =IF((((BJ13+BK13)/2)+(C13/(D13*((BJ13+BK13)/2)))^2/(2*9.81)+B13-(G12+H12^2/(2*9.81))-(A12-A13)*(((DATOS!$B$34*(C13/(D13*((BJ13+BK13)/2)))/((D13*((BJ13+BK13)/2))/(D13+2*((BJ13+BK13)/2)))^(2/3))^2+((DATOS!$B$34*H12/((D12*F12)/(D12+2*F12))^(2/3))^2))/2))>0,BJ13,((BJ13+BK13)/2)) | BM13: =IF((((BJ13+BK13)/2)+(C13/(D13*((BJ13+BK13)/2)))^2/(2*9.81)+B13-(G12+H12^2/(2*9.81))-(A12-A13)*(((DATOS!$B$34*(C13/(D13*((BJ13+BK13)/2)))/((D13*((BJ13+BK13)/2))/(D13+2*((BJ13+BK13)/2)))^(2/3))^2+((DATOS!$B$34*H12/((D12*F12)/(D12+2*F12))^(2/3))^2))/2))>0,((BJ13+BK13)/2),BK13) | BN13: =IF((((BL13+BM13)/2)+(C13/(D13*((BL13+BM13)/2)))^2/(2*9.81)+B13-(G12+H12^2/(2*9.81))-(A12-A13)*(((DATOS!$B$34*(C13/(D13*((BL13+BM13)/2)))/((D13*((BL13+BM13)/2))/(D13+2*((BL13+BM13)/2)))^(2/3))^2+((DATOS!$B$34*H12/((D12*F12)/(D12+2*F12))^(2/3))^2))/2))>0,BL13,((BL13+BM13)/2)) | BO13: =IF((((BL13+BM13)/2)+(C13/(D13*((BL13+BM13)/2)))^2/(2*9.81)+B13-(G12+H12^2/(2*9.81))-(A12-A13)*(((DATOS!$B$34*(C13/(D13*((BL13+BM13)/2)))/((D13*((BL13+BM13)/2))/(D13+2*((BL13+BM13)/2)))^(2/3))^2+((DATOS!$B$34*H12/((D12*F12)/(D12+2*F12))^(2/3))^2))/2))>0,((BL13+BM13)/2),BM13) | BP13: =IF((((BN13+BO13)/2)+(C13/(D13*((BN13+BO13)/2)))^2/(2*9.81)+B13-(G12+H12^2/(2*9.81))-(A12-A13)*(((DATOS!$B$34*(C13/(D13*((BN13+BO13)/2)))/((D13*((BN13+BO13)/2))/(D13+2*((BN13+BO13)/2)))^(2/3))^2+((DATOS!$B$34*H12/((D12*F12)/(D12+2*F12))^(2/3))^2))/2))>0,BN13,((BN13+BO13)/2)) | BQ13: =IF((((BN13+BO13)/2)+(C13/(D13*((BN13+BO13)/2)))^2/(2*9.81)+B13-(G12+H12^2/(2*9.81))-(A12-A13)*(((DATOS!$B$34*(C13/(D13*((BN13+BO13)/2)))/((D13*((BN13+BO13)/2))/(D13+2*((BN13+BO13)/2)))^(2/3))^2+((DATOS!$B$34*H12/((D12*F12)/(D12+2*F12))^(2/3))^2))/2))>0,((BN13+BO13)/2),BO13) | BR13: =IF((((BP13+BQ13)/2)+(C13/(D13*((BP13+BQ13)/2)))^2/(2*9.81)+B13-(G12+H12^2/(2*9.81))-(A12-A13)*(((DATOS!$B$34*(C13/(D13*((BP13+BQ13)/2)))/((D13*((BP13+BQ13)/2))/(D13+2*((BP13+BQ13)/2)))^(2/3))^2+((DATOS!$B$34*H12/((D12*F12)/(D12+2*F12))^(2/3))^2))/2))>0,BP13,((BP13+BQ13)/2)) | BS13: =IF((((BP13+BQ13)/2)+(C13/(D13*((BP13+BQ13)/2)))^2/(2*9.81)+B13-(G12+H12^2/(2*9.81))-(A12-A13)*(((DATOS!$B$34*(C13/(D13*((BP13+BQ13)/2)))/((D13*((BP13+BQ13)/2))/(D13+2*((BP13+BQ13)/2)))^(2/3))^2+((DATOS!$B$34*H12/((D12*F12)/(D12+2*F12))^(2/3))^2))/2))>0,((BP13+BQ13)/2),BQ13) | BT13: =IF((((BR13+BS13)/2)+(C13/(D13*((BR13+BS13)/2)))^2/(2*9.81)+B13-(G12+H12^2/(2*9.81))-(A12-A13)*(((DATOS!$B$34*(C13/(D13*((BR13+BS13)/2)))/((D13*((BR13+BS13)/2))/(D13+2*((BR13+BS13)/2)))^(2/3))^2+((DATOS!$B$34*H12/((D12*F12)/(D12+2*F12))^(2/3))^2))/2))>0,BR13,((BR13+BS13)/2)) | BU13: =IF((((BR13+BS13)/2)+(C13/(D13*((BR13+BS13)/2)))^2/(2*9.81)+B13-(G12+H12^2/(2*9.81))-(A12-A13)*(((DATOS!$B$34*(C13/(D13*((BR13+BS13)/2)))/((D13*((BR13+BS13)/2))/(D13+2*((BR13+BS13)/2)))^(2/3))^2+((DATOS!$B$34*H12/((D12*F12)/(D12+2*F12))^(2/3))^2))/2))>0,((BR13+BS13)/2),BS13) | BV13: =IF((((BT13+BU13)/2)+(C13/(D13*((BT13+BU13)/2)))^2/(2*9.81)+B13-(G12+H12^2/(2*9.81))-(A12-A13)*(((DATOS!$B$34*(C13/(D13*((BT13+BU13)/2)))/((D13*((BT13+BU13)/2))/(D13+2*((BT13+BU13)/2)))^(2/3))^2+((DATOS!$B$34*H12/((D12*F12)/(D12+2*F12))^(2/3))^2))/2))>0,BT13,((BT13+BU13)/2)) | BW13: =IF((((BT13+BU13)/2)+(C13/(D13*((BT13+BU13)/2)))^2/(2*9.81)+B13-(G12+H12^2/(2*9.81))-(A12-A13)*(((DATOS!$B$34*(C13/(D13*((BT13+BU13)/2)))/((D13*((BT13+BU13)/2))/(D13+2*((BT13+BU13)/2)))^(2/3))^2+((DATOS!$B$34*H12/((D12*F12)/(D12+2*F12))^(2/3))^2))/2))>0,((BT13+BU13)/2),BU13)
A14: 65 | B14: =DATOS!$B$22-DATOS!$B$23*A14 | C14: =CAUDALES!$B$13 | D14: =DATOS!$B$17 | E14: =(C14^2/(9.81*D14^2))^(1/3) | F14: =(BV14+BW14)/2 | G14: =B14+F14 | H14: =C14/(D14*F14) | I14: =H14/SQRT(9.81*F14) | J14: =DATOS!$B$29-IF(AND(A14>=DATOS!$B$30,A14<DATOS!$B$31),DATOS!$B$21,DATOS!$B$20) | K14: =J14-B14 | L14: =F14/K14 | M14: =J14-G14 | N14: =IF(AND(L14<=DATOS!$B$36,M14>=DATOS!$B$37,I14<=1),"CUMPLE","NO CUMPLE") | O14: =IF(AND(A14>=DATOS!$B$30,A14<DATOS!$B$31),"cruce de camiones",IF(AND(A14>=DATOS!$B$32,A14<DATOS!$B$33),"cruce de motos","tramo normal")) | P14: =E14*1.001 | Q14: 3 | R14: =IF((((P14+Q14)/2)+(C14/(D14*((P14+Q14)/2)))^2/(2*9.81)+B14-(G13+H13^2/(2*9.81))-(A13-A14)*(((DATOS!$B$34*(C14/(D14*((P14+Q14)/2)))/((D14*((P14+Q14)/2))/(D14+2*((P14+Q14)/2)))^(2/3))^2+((DATOS!$B$34*H13/((D13*F13)/(D13+2*F13))^(2/3))^2))/2))>0,P14,((P14+Q14)/2)) | S14: =IF((((P14+Q14)/2)+(C14/(D14*((P14+Q14)/2)))^2/(2*9.81)+B14-(G13+H13^2/(2*9.81))-(A13-A14)*(((DATOS!$B$34*(C14/(D14*((P14+Q14)/2)))/((D14*((P14+Q14)/2))/(D14+2*((P14+Q14)/2)))^(2/3))^2+((DATOS!$B$34*H13/((D13*F13)/(D13+2*F13))^(2/3))^2))/2))>0,((P14+Q14)/2),Q14) | T14: =IF((((R14+S14)/2)+(C14/(D14*((R14+S14)/2)))^2/(2*9.81)+B14-(G13+H13^2/(2*9.81))-(A13-A14)*(((DATOS!$B$34*(C14/(D14*((R14+S14)/2)))/((D14*((R14+S14)/2))/(D14+2*((R14+S14)/2)))^(2/3))^2+((DATOS!$B$34*H13/((D13*F13)/(D13+2*F13))^(2/3))^2))/2))>0,R14,((R14+S14)/2)) | U14: =IF((((R14+S14)/2)+(C14/(D14*((R14+S14)/2)))^2/(2*9.81)+B14-(G13+H13^2/(2*9.81))-(A13-A14)*(((DATOS!$B$34*(C14/(D14*((R14+S14)/2)))/((D14*((R14+S14)/2))/(D14+2*((R14+S14)/2)))^(2/3))^2+((DATOS!$B$34*H13/((D13*F13)/(D13+2*F13))^(2/3))^2))/2))>0,((R14+S14)/2),S14) | V14: =IF((((T14+U14)/2)+(C14/(D14*((T14+U14)/2)))^2/(2*9.81)+B14-(G13+H13^2/(2*9.81))-(A13-A14)*(((DATOS!$B$34*(C14/(D14*((T14+U14)/2)))/((D14*((T14+U14)/2))/(D14+2*((T14+U14)/2)))^(2/3))^2+((DATOS!$B$34*H13/((D13*F13)/(D13+2*F13))^(2/3))^2))/2))>0,T14,((T14+U14)/2)) | W14: =IF((((T14+U14)/2)+(C14/(D14*((T14+U14)/2)))^2/(2*9.81)+B14-(G13+H13^2/(2*9.81))-(A13-A14)*(((DATOS!$B$34*(C14/(D14*((T14+U14)/2)))/((D14*((T14+U14)/2))/(D14+2*((T14+U14)/2)))^(2/3))^2+((DATOS!$B$34*H13/((D13*F13)/(D13+2*F13))^(2/3))^2))/2))>0,((T14+U14)/2),U14) | X14: =IF((((V14+W14)/2)+(C14/(D14*((V14+W14)/2)))^2/(2*9.81)+B14-(G13+H13^2/(2*9.81))-(A13-A14)*(((DATOS!$B$34*(C14/(D14*((V14+W14)/2)))/((D14*((V14+W14)/2))/(D14+2*((V14+W14)/2)))^(2/3))^2+((DATOS!$B$34*H13/((D13*F13)/(D13+2*F13))^(2/3))^2))/2))>0,V14,((V14+W14)/2)) | Y14: =IF((((V14+W14)/2)+(C14/(D14*((V14+W14)/2)))^2/(2*9.81)+B14-(G13+H13^2/(2*9.81))-(A13-A14)*(((DATOS!$B$34*(C14/(D14*((V14+W14)/2)))/((D14*((V14+W14)/2))/(D14+2*((V14+W14)/2)))^(2/3))^2+((DATOS!$B$34*H13/((D13*F13)/(D13+2*F13))^(2/3))^2))/2))>0,((V14+W14)/2),W14) | Z14: =IF((((X14+Y14)/2)+(C14/(D14*((X14+Y14)/2)))^2/(2*9.81)+B14-(G13+H13^2/(2*9.81))-(A13-A14)*(((DATOS!$B$34*(C14/(D14*((X14+Y14)/2)))/((D14*((X14+Y14)/2))/(D14+2*((X14+Y14)/2)))^(2/3))^2+((DATOS!$B$34*H13/((D13*F13)/(D13+2*F13))^(2/3))^2))/2))>0,X14,((X14+Y14)/2)) | AA14: =IF((((X14+Y14)/2)+(C14/(D14*((X14+Y14)/2)))^2/(2*9.81)+B14-(G13+H13^2/(2*9.81))-(A13-A14)*(((DATOS!$B$34*(C14/(D14*((X14+Y14)/2)))/((D14*((X14+Y14)/2))/(D14+2*((X14+Y14)/2)))^(2/3))^2+((DATOS!$B$34*H13/((D13*F13)/(D13+2*F13))^(2/3))^2))/2))>0,((X14+Y14)/2),Y14) | AB14: =IF((((Z14+AA14)/2)+(C14/(D14*((Z14+AA14)/2)))^2/(2*9.81)+B14-(G13+H13^2/(2*9.81))-(A13-A14)*(((DATOS!$B$34*(C14/(D14*((Z14+AA14)/2)))/((D14*((Z14+AA14)/2))/(D14+2*((Z14+AA14)/2)))^(2/3))^2+((DATOS!$B$34*H13/((D13*F13)/(D13+2*F13))^(2/3))^2))/2))>0,Z14,((Z14+AA14)/2)) | AC14: =IF((((Z14+AA14)/2)+(C14/(D14*((Z14+AA14)/2)))^2/(2*9.81)+B14-(G13+H13^2/(2*9.81))-(A13-A14)*(((DATOS!$B$34*(C14/(D14*((Z14+AA14)/2)))/((D14*((Z14+AA14)/2))/(D14+2*((Z14+AA14)/2)))^(2/3))^2+((DATOS!$B$34*H13/((D13*F13)/(D13+2*F13))^(2/3))^2))/2))>0,((Z14+AA14)/2),AA14) | AD14: =IF((((AB14+AC14)/2)+(C14/(D14*((AB14+AC14)/2)))^2/(2*9.81)+B14-(G13+H13^2/(2*9.81))-(A13-A14)*(((DATOS!$B$34*(C14/(D14*((AB14+AC14)/2)))/((D14*((AB14+AC14)/2))/(D14+2*((AB14+AC14)/2)))^(2/3))^2+((DATOS!$B$34*H13/((D13*F13)/(D13+2*F13))^(2/3))^2))/2))>0,AB14,((AB14+AC14)/2)) | AE14: =IF((((AB14+AC14)/2)+(C14/(D14*((AB14+AC14)/2)))^2/(2*9.81)+B14-(G13+H13^2/(2*9.81))-(A13-A14)*(((DATOS!$B$34*(C14/(D14*((AB14+AC14)/2)))/((D14*((AB14+AC14)/2))/(D14+2*((AB14+AC14)/2)))^(2/3))^2+((DATOS!$B$34*H13/((D13*F13)/(D13+2*F13))^(2/3))^2))/2))>0,((AB14+AC14)/2),AC14) | AF14: =IF((((AD14+AE14)/2)+(C14/(D14*((AD14+AE14)/2)))^2/(2*9.81)+B14-(G13+H13^2/(2*9.81))-(A13-A14)*(((DATOS!$B$34*(C14/(D14*((AD14+AE14)/2)))/((D14*((AD14+AE14)/2))/(D14+2*((AD14+AE14)/2)))^(2/3))^2+((DATOS!$B$34*H13/((D13*F13)/(D13+2*F13))^(2/3))^2))/2))>0,AD14,((AD14+AE14)/2)) | AG14: =IF((((AD14+AE14)/2)+(C14/(D14*((AD14+AE14)/2)))^2/(2*9.81)+B14-(G13+H13^2/(2*9.81))-(A13-A14)*(((DATOS!$B$34*(C14/(D14*((AD14+AE14)/2)))/((D14*((AD14+AE14)/2))/(D14+2*((AD14+AE14)/2)))^(2/3))^2+((DATOS!$B$34*H13/((D13*F13)/(D13+2*F13))^(2/3))^2))/2))>0,((AD14+AE14)/2),AE14) | AH14: =IF((((AF14+AG14)/2)+(C14/(D14*((AF14+AG14)/2)))^2/(2*9.81)+B14-(G13+H13^2/(2*9.81))-(A13-A14)*(((DATOS!$B$34*(C14/(D14*((AF14+AG14)/2)))/((D14*((AF14+AG14)/2))/(D14+2*((AF14+AG14)/2)))^(2/3))^2+((DATOS!$B$34*H13/((D13*F13)/(D13+2*F13))^(2/3))^2))/2))>0,AF14,((AF14+AG14)/2)) | AI14: =IF((((AF14+AG14)/2)+(C14/(D14*((AF14+AG14)/2)))^2/(2*9.81)+B14-(G13+H13^2/(2*9.81))-(A13-A14)*(((DATOS!$B$34*(C14/(D14*((AF14+AG14)/2)))/((D14*((AF14+AG14)/2))/(D14+2*((AF14+AG14)/2)))^(2/3))^2+((DATOS!$B$34*H13/((D13*F13)/(D13+2*F13))^(2/3))^2))/2))>0,((AF14+AG14)/2),AG14) | AJ14: =IF((((AH14+AI14)/2)+(C14/(D14*((AH14+AI14)/2)))^2/(2*9.81)+B14-(G13+H13^2/(2*9.81))-(A13-A14)*(((DATOS!$B$34*(C14/(D14*((AH14+AI14)/2)))/((D14*((AH14+AI14)/2))/(D14+2*((AH14+AI14)/2)))^(2/3))^2+((DATOS!$B$34*H13/((D13*F13)/(D13+2*F13))^(2/3))^2))/2))>0,AH14,((AH14+AI14)/2)) | AK14: =IF((((AH14+AI14)/2)+(C14/(D14*((AH14+AI14)/2)))^2/(2*9.81)+B14-(G13+H13^2/(2*9.81))-(A13-A14)*(((DATOS!$B$34*(C14/(D14*((AH14+AI14)/2)))/((D14*((AH14+AI14)/2))/(D14+2*((AH14+AI14)/2)))^(2/3))^2+((DATOS!$B$34*H13/((D13*F13)/(D13+2*F13))^(2/3))^2))/2))>0,((AH14+AI14)/2),AI14) | AL14: =IF((((AJ14+AK14)/2)+(C14/(D14*((AJ14+AK14)/2)))^2/(2*9.81)+B14-(G13+H13^2/(2*9.81))-(A13-A14)*(((DATOS!$B$34*(C14/(D14*((AJ14+AK14)/2)))/((D14*((AJ14+AK14)/2))/(D14+2*((AJ14+AK14)/2)))^(2/3))^2+((DATOS!$B$34*H13/((D13*F13)/(D13+2*F13))^(2/3))^2))/2))>0,AJ14,((AJ14+AK14)/2)) | AM14: =IF((((AJ14+AK14)/2)+(C14/(D14*((AJ14+AK14)/2)))^2/(2*9.81)+B14-(G13+H13^2/(2*9.81))-(A13-A14)*(((DATOS!$B$34*(C14/(D14*((AJ14+AK14)/2)))/((D14*((AJ14+AK14)/2))/(D14+2*((AJ14+AK14)/2)))^(2/3))^2+((DATOS!$B$34*H13/((D13*F13)/(D13+2*F13))^(2/3))^2))/2))>0,((AJ14+AK14)/2),AK14) | AN14: =IF((((AL14+AM14)/2)+(C14/(D14*((AL14+AM14)/2)))^2/(2*9.81)+B14-(G13+H13^2/(2*9.81))-(A13-A14)*(((DATOS!$B$34*(C14/(D14*((AL14+AM14)/2)))/((D14*((AL14+AM14)/2))/(D14+2*((AL14+AM14)/2)))^(2/3))^2+((DATOS!$B$34*H13/((D13*F13)/(D13+2*F13))^(2/3))^2))/2))>0,AL14,((AL14+AM14)/2)) | AO14: =IF((((AL14+AM14)/2)+(C14/(D14*((AL14+AM14)/2)))^2/(2*9.81)+B14-(G13+H13^2/(2*9.81))-(A13-A14)*(((DATOS!$B$34*(C14/(D14*((AL14+AM14)/2)))/((D14*((AL14+AM14)/2))/(D14+2*((AL14+AM14)/2)))^(2/3))^2+((DATOS!$B$34*H13/((D13*F13)/(D13+2*F13))^(2/3))^2))/2))>0,((AL14+AM14)/2),AM14) | AP14: =IF((((AN14+AO14)/2)+(C14/(D14*((AN14+AO14)/2)))^2/(2*9.81)+B14-(G13+H13^2/(2*9.81))-(A13-A14)*(((DATOS!$B$34*(C14/(D14*((AN14+AO14)/2)))/((D14*((AN14+AO14)/2))/(D14+2*((AN14+AO14)/2)))^(2/3))^2+((DATOS!$B$34*H13/((D13*F13)/(D13+2*F13))^(2/3))^2))/2))>0,AN14,((AN14+AO14)/2)) | AQ14: =IF((((AN14+AO14)/2)+(C14/(D14*((AN14+AO14)/2)))^2/(2*9.81)+B14-(G13+H13^2/(2*9.81))-(A13-A14)*(((DATOS!$B$34*(C14/(D14*((AN14+AO14)/2)))/((D14*((AN14+AO14)/2))/(D14+2*((AN14+AO14)/2)))^(2/3))^2+((DATOS!$B$34*H13/((D13*F13)/(D13+2*F13))^(2/3))^2))/2))>0,((AN14+AO14)/2),AO14) | AR14: =IF((((AP14+AQ14)/2)+(C14/(D14*((AP14+AQ14)/2)))^2/(2*9.81)+B14-(G13+H13^2/(2*9.81))-(A13-A14)*(((DATOS!$B$34*(C14/(D14*((AP14+AQ14)/2)))/((D14*((AP14+AQ14)/2))/(D14+2*((AP14+AQ14)/2)))^(2/3))^2+((DATOS!$B$34*H13/((D13*F13)/(D13+2*F13))^(2/3))^2))/2))>0,AP14,((AP14+AQ14)/2)) | AS14: =IF((((AP14+AQ14)/2)+(C14/(D14*((AP14+AQ14)/2)))^2/(2*9.81)+B14-(G13+H13^2/(2*9.81))-(A13-A14)*(((DATOS!$B$34*(C14/(D14*((AP14+AQ14)/2)))/((D14*((AP14+AQ14)/2))/(D14+2*((AP14+AQ14)/2)))^(2/3))^2+((DATOS!$B$34*H13/((D13*F13)/(D13+2*F13))^(2/3))^2))/2))>0,((AP14+AQ14)/2),AQ14) | AT14: =IF((((AR14+AS14)/2)+(C14/(D14*((AR14+AS14)/2)))^2/(2*9.81)+B14-(G13+H13^2/(2*9.81))-(A13-A14)*(((DATOS!$B$34*(C14/(D14*((AR14+AS14)/2)))/((D14*((AR14+AS14)/2))/(D14+2*((AR14+AS14)/2)))^(2/3))^2+((DATOS!$B$34*H13/((D13*F13)/(D13+2*F13))^(2/3))^2))/2))>0,AR14,((AR14+AS14)/2)) | AU14: =IF((((AR14+AS14)/2)+(C14/(D14*((AR14+AS14)/2)))^2/(2*9.81)+B14-(G13+H13^2/(2*9.81))-(A13-A14)*(((DATOS!$B$34*(C14/(D14*((AR14+AS14)/2)))/((D14*((AR14+AS14)/2))/(D14+2*((AR14+AS14)/2)))^(2/3))^2+((DATOS!$B$34*H13/((D13*F13)/(D13+2*F13))^(2/3))^2))/2))>0,((AR14+AS14)/2),AS14) | AV14: =IF((((AT14+AU14)/2)+(C14/(D14*((AT14+AU14)/2)))^2/(2*9.81)+B14-(G13+H13^2/(2*9.81))-(A13-A14)*(((DATOS!$B$34*(C14/(D14*((AT14+AU14)/2)))/((D14*((AT14+AU14)/2))/(D14+2*((AT14+AU14)/2)))^(2/3))^2+((DATOS!$B$34*H13/((D13*F13)/(D13+2*F13))^(2/3))^2))/2))>0,AT14,((AT14+AU14)/2)) | AW14: =IF((((AT14+AU14)/2)+(C14/(D14*((AT14+AU14)/2)))^2/(2*9.81)+B14-(G13+H13^2/(2*9.81))-(A13-A14)*(((DATOS!$B$34*(C14/(D14*((AT14+AU14)/2)))/((D14*((AT14+AU14)/2))/(D14+2*((AT14+AU14)/2)))^(2/3))^2+((DATOS!$B$34*H13/((D13*F13)/(D13+2*F13))^(2/3))^2))/2))>0,((AT14+AU14)/2),AU14) | AX14: =IF((((AV14+AW14)/2)+(C14/(D14*((AV14+AW14)/2)))^2/(2*9.81)+B14-(G13+H13^2/(2*9.81))-(A13-A14)*(((DATOS!$B$34*(C14/(D14*((AV14+AW14)/2)))/((D14*((AV14+AW14)/2))/(D14+2*((AV14+AW14)/2)))^(2/3))^2+((DATOS!$B$34*H13/((D13*F13)/(D13+2*F13))^(2/3))^2))/2))>0,AV14,((AV14+AW14)/2)) | AY14: =IF((((AV14+AW14)/2)+(C14/(D14*((AV14+AW14)/2)))^2/(2*9.81)+B14-(G13+H13^2/(2*9.81))-(A13-A14)*(((DATOS!$B$34*(C14/(D14*((AV14+AW14)/2)))/((D14*((AV14+AW14)/2))/(D14+2*((AV14+AW14)/2)))^(2/3))^2+((DATOS!$B$34*H13/((D13*F13)/(D13+2*F13))^(2/3))^2))/2))>0,((AV14+AW14)/2),AW14) | AZ14: =IF((((AX14+AY14)/2)+(C14/(D14*((AX14+AY14)/2)))^2/(2*9.81)+B14-(G13+H13^2/(2*9.81))-(A13-A14)*(((DATOS!$B$34*(C14/(D14*((AX14+AY14)/2)))/((D14*((AX14+AY14)/2))/(D14+2*((AX14+AY14)/2)))^(2/3))^2+((DATOS!$B$34*H13/((D13*F13)/(D13+2*F13))^(2/3))^2))/2))>0,AX14,((AX14+AY14)/2)) | BA14: =IF((((AX14+AY14)/2)+(C14/(D14*((AX14+AY14)/2)))^2/(2*9.81)+B14-(G13+H13^2/(2*9.81))-(A13-A14)*(((DATOS!$B$34*(C14/(D14*((AX14+AY14)/2)))/((D14*((AX14+AY14)/2))/(D14+2*((AX14+AY14)/2)))^(2/3))^2+((DATOS!$B$34*H13/((D13*F13)/(D13+2*F13))^(2/3))^2))/2))>0,((AX14+AY14)/2),AY14) | BB14: =IF((((AZ14+BA14)/2)+(C14/(D14*((AZ14+BA14)/2)))^2/(2*9.81)+B14-(G13+H13^2/(2*9.81))-(A13-A14)*(((DATOS!$B$34*(C14/(D14*((AZ14+BA14)/2)))/((D14*((AZ14+BA14)/2))/(D14+2*((AZ14+BA14)/2)))^(2/3))^2+((DATOS!$B$34*H13/((D13*F13)/(D13+2*F13))^(2/3))^2))/2))>0,AZ14,((AZ14+BA14)/2)) | BC14: =IF((((AZ14+BA14)/2)+(C14/(D14*((AZ14+BA14)/2)))^2/(2*9.81)+B14-(G13+H13^2/(2*9.81))-(A13-A14)*(((DATOS!$B$34*(C14/(D14*((AZ14+BA14)/2)))/((D14*((AZ14+BA14)/2))/(D14+2*((AZ14+BA14)/2)))^(2/3))^2+((DATOS!$B$34*H13/((D13*F13)/(D13+2*F13))^(2/3))^2))/2))>0,((AZ14+BA14)/2),BA14) | BD14: =IF((((BB14+BC14)/2)+(C14/(D14*((BB14+BC14)/2)))^2/(2*9.81)+B14-(G13+H13^2/(2*9.81))-(A13-A14)*(((DATOS!$B$34*(C14/(D14*((BB14+BC14)/2)))/((D14*((BB14+BC14)/2))/(D14+2*((BB14+BC14)/2)))^(2/3))^2+((DATOS!$B$34*H13/((D13*F13)/(D13+2*F13))^(2/3))^2))/2))>0,BB14,((BB14+BC14)/2)) | BE14: =IF((((BB14+BC14)/2)+(C14/(D14*((BB14+BC14)/2)))^2/(2*9.81)+B14-(G13+H13^2/(2*9.81))-(A13-A14)*(((DATOS!$B$34*(C14/(D14*((BB14+BC14)/2)))/((D14*((BB14+BC14)/2))/(D14+2*((BB14+BC14)/2)))^(2/3))^2+((DATOS!$B$34*H13/((D13*F13)/(D13+2*F13))^(2/3))^2))/2))>0,((BB14+BC14)/2),BC14) | BF14: =IF((((BD14+BE14)/2)+(C14/(D14*((BD14+BE14)/2)))^2/(2*9.81)+B14-(G13+H13^2/(2*9.81))-(A13-A14)*(((DATOS!$B$34*(C14/(D14*((BD14+BE14)/2)))/((D14*((BD14+BE14)/2))/(D14+2*((BD14+BE14)/2)))^(2/3))^2+((DATOS!$B$34*H13/((D13*F13)/(D13+2*F13))^(2/3))^2))/2))>0,BD14,((BD14+BE14)/2)) | BG14: =IF((((BD14+BE14)/2)+(C14/(D14*((BD14+BE14)/2)))^2/(2*9.81)+B14-(G13+H13^2/(2*9.81))-(A13-A14)*(((DATOS!$B$34*(C14/(D14*((BD14+BE14)/2)))/((D14*((BD14+BE14)/2))/(D14+2*((BD14+BE14)/2)))^(2/3))^2+((DATOS!$B$34*H13/((D13*F13)/(D13+2*F13))^(2/3))^2))/2))>0,((BD14+BE14)/2),BE14) | BH14: =IF((((BF14+BG14)/2)+(C14/(D14*((BF14+BG14)/2)))^2/(2*9.81)+B14-(G13+H13^2/(2*9.81))-(A13-A14)*(((DATOS!$B$34*(C14/(D14*((BF14+BG14)/2)))/((D14*((BF14+BG14)/2))/(D14+2*((BF14+BG14)/2)))^(2/3))^2+((DATOS!$B$34*H13/((D13*F13)/(D13+2*F13))^(2/3))^2))/2))>0,BF14,((BF14+BG14)/2)) | BI14: =IF((((BF14+BG14)/2)+(C14/(D14*((BF14+BG14)/2)))^2/(2*9.81)+B14-(G13+H13^2/(2*9.81))-(A13-A14)*(((DATOS!$B$34*(C14/(D14*((BF14+BG14)/2)))/((D14*((BF14+BG14)/2))/(D14+2*((BF14+BG14)/2)))^(2/3))^2+((DATOS!$B$34*H13/((D13*F13)/(D13+2*F13))^(2/3))^2))/2))>0,((BF14+BG14)/2),BG14) | BJ14: =IF((((BH14+BI14)/2)+(C14/(D14*((BH14+BI14)/2)))^2/(2*9.81)+B14-(G13+H13^2/(2*9.81))-(A13-A14)*(((DATOS!$B$34*(C14/(D14*((BH14+BI14)/2)))/((D14*((BH14+BI14)/2))/(D14+2*((BH14+BI14)/2)))^(2/3))^2+((DATOS!$B$34*H13/((D13*F13)/(D13+2*F13))^(2/3))^2))/2))>0,BH14,((BH14+BI14)/2)) | BK14: =IF((((BH14+BI14)/2)+(C14/(D14*((BH14+BI14)/2)))^2/(2*9.81)+B14-(G13+H13^2/(2*9.81))-(A13-A14)*(((DATOS!$B$34*(C14/(D14*((BH14+BI14)/2)))/((D14*((BH14+BI14)/2))/(D14+2*((BH14+BI14)/2)))^(2/3))^2+((DATOS!$B$34*H13/((D13*F13)/(D13+2*F13))^(2/3))^2))/2))>0,((BH14+BI14)/2),BI14) | BL14: =IF((((BJ14+BK14)/2)+(C14/(D14*((BJ14+BK14)/2)))^2/(2*9.81)+B14-(G13+H13^2/(2*9.81))-(A13-A14)*(((DATOS!$B$34*(C14/(D14*((BJ14+BK14)/2)))/((D14*((BJ14+BK14)/2))/(D14+2*((BJ14+BK14)/2)))^(2/3))^2+((DATOS!$B$34*H13/((D13*F13)/(D13+2*F13))^(2/3))^2))/2))>0,BJ14,((BJ14+BK14)/2)) | BM14: =IF((((BJ14+BK14)/2)+(C14/(D14*((BJ14+BK14)/2)))^2/(2*9.81)+B14-(G13+H13^2/(2*9.81))-(A13-A14)*(((DATOS!$B$34*(C14/(D14*((BJ14+BK14)/2)))/((D14*((BJ14+BK14)/2))/(D14+2*((BJ14+BK14)/2)))^(2/3))^2+((DATOS!$B$34*H13/((D13*F13)/(D13+2*F13))^(2/3))^2))/2))>0,((BJ14+BK14)/2),BK14) | BN14: =IF((((BL14+BM14)/2)+(C14/(D14*((BL14+BM14)/2)))^2/(2*9.81)+B14-(G13+H13^2/(2*9.81))-(A13-A14)*(((DATOS!$B$34*(C14/(D14*((BL14+BM14)/2)))/((D14*((BL14+BM14)/2))/(D14+2*((BL14+BM14)/2)))^(2/3))^2+((DATOS!$B$34*H13/((D13*F13)/(D13+2*F13))^(2/3))^2))/2))>0,BL14,((BL14+BM14)/2)) | BO14: =IF((((BL14+BM14)/2)+(C14/(D14*((BL14+BM14)/2)))^2/(2*9.81)+B14-(G13+H13^2/(2*9.81))-(A13-A14)*(((DATOS!$B$34*(C14/(D14*((BL14+BM14)/2)))/((D14*((BL14+BM14)/2))/(D14+2*((BL14+BM14)/2)))^(2/3))^2+((DATOS!$B$34*H13/((D13*F13)/(D13+2*F13))^(2/3))^2))/2))>0,((BL14+BM14)/2),BM14) | BP14: =IF((((BN14+BO14)/2)+(C14/(D14*((BN14+BO14)/2)))^2/(2*9.81)+B14-(G13+H13^2/(2*9.81))-(A13-A14)*(((DATOS!$B$34*(C14/(D14*((BN14+BO14)/2)))/((D14*((BN14+BO14)/2))/(D14+2*((BN14+BO14)/2)))^(2/3))^2+((DATOS!$B$34*H13/((D13*F13)/(D13+2*F13))^(2/3))^2))/2))>0,BN14,((BN14+BO14)/2)) | BQ14: =IF((((BN14+BO14)/2)+(C14/(D14*((BN14+BO14)/2)))^2/(2*9.81)+B14-(G13+H13^2/(2*9.81))-(A13-A14)*(((DATOS!$B$34*(C14/(D14*((BN14+BO14)/2)))/((D14*((BN14+BO14)/2))/(D14+2*((BN14+BO14)/2)))^(2/3))^2+((DATOS!$B$34*H13/((D13*F13)/(D13+2*F13))^(2/3))^2))/2))>0,((BN14+BO14)/2),BO14) | BR14: =IF((((BP14+BQ14)/2)+(C14/(D14*((BP14+BQ14)/2)))^2/(2*9.81)+B14-(G13+H13^2/(2*9.81))-(A13-A14)*(((DATOS!$B$34*(C14/(D14*((BP14+BQ14)/2)))/((D14*((BP14+BQ14)/2))/(D14+2*((BP14+BQ14)/2)))^(2/3))^2+((DATOS!$B$34*H13/((D13*F13)/(D13+2*F13))^(2/3))^2))/2))>0,BP14,((BP14+BQ14)/2)) | BS14: =IF((((BP14+BQ14)/2)+(C14/(D14*((BP14+BQ14)/2)))^2/(2*9.81)+B14-(G13+H13^2/(2*9.81))-(A13-A14)*(((DATOS!$B$34*(C14/(D14*((BP14+BQ14)/2)))/((D14*((BP14+BQ14)/2))/(D14+2*((BP14+BQ14)/2)))^(2/3))^2+((DATOS!$B$34*H13/((D13*F13)/(D13+2*F13))^(2/3))^2))/2))>0,((BP14+BQ14)/2),BQ14) | BT14: =IF((((BR14+BS14)/2)+(C14/(D14*((BR14+BS14)/2)))^2/(2*9.81)+B14-(G13+H13^2/(2*9.81))-(A13-A14)*(((DATOS!$B$34*(C14/(D14*((BR14+BS14)/2)))/((D14*((BR14+BS14)/2))/(D14+2*((BR14+BS14)/2)))^(2/3))^2+((DATOS!$B$34*H13/((D13*F13)/(D13+2*F13))^(2/3))^2))/2))>0,BR14,((BR14+BS14)/2)) | BU14: =IF((((BR14+BS14)/2)+(C14/(D14*((BR14+BS14)/2)))^2/(2*9.81)+B14-(G13+H13^2/(2*9.81))-(A13-A14)*(((DATOS!$B$34*(C14/(D14*((BR14+BS14)/2)))/((D14*((BR14+BS14)/2))/(D14+2*((BR14+BS14)/2)))^(2/3))^2+((DATOS!$B$34*H13/((D13*F13)/(D13+2*F13))^(2/3))^2))/2))>0,((BR14+BS14)/2),BS14) | BV14: =IF((((BT14+BU14)/2)+(C14/(D14*((BT14+BU14)/2)))^2/(2*9.81)+B14-(G13+H13^2/(2*9.81))-(A13-A14)*(((DATOS!$B$34*(C14/(D14*((BT14+BU14)/2)))/((D14*((BT14+BU14)/2))/(D14+2*((BT14+BU14)/2)))^(2/3))^2+((DATOS!$B$34*H13/((D13*F13)/(D13+2*F13))^(2/3))^2))/2))>0,BT14,((BT14+BU14)/2)) | BW14: =IF((((BT14+BU14)/2)+(C14/(D14*((BT14+BU14)/2)))^2/(2*9.81)+B14-(G13+H13^2/(2*9.81))-(A13-A14)*(((DATOS!$B$34*(C14/(D14*((BT14+BU14)/2)))/((D14*((BT14+BU14)/2))/(D14+2*((BT14+BU14)/2)))^(2/3))^2+((DATOS!$B$34*H13/((D13*F13)/(D13+2*F13))^(2/3))^2))/2))>0,((BT14+BU14)/2),BU14)
A15: 64 | B15: =DATOS!$B$22-DATOS!$B$23*A15 | C15: =CAUDALES!$B$13 | D15: =DATOS!$B$17 | E15: =(C15^2/(9.81*D15^2))^(1/3) | F15: =(BV15+BW15)/2 | G15: =B15+F15 | H15: =C15/(D15*F15) | I15: =H15/SQRT(9.81*F15) | J15: =DATOS!$B$29-IF(AND(A15>=DATOS!$B$30,A15<DATOS!$B$31),DATOS!$B$21,DATOS!$B$20) | K15: =J15-B15 | L15: =F15/K15 | M15: =J15-G15 | N15: =IF(AND(L15<=DATOS!$B$36,M15>=DATOS!$B$37,I15<=1),"CUMPLE","NO CUMPLE") | O15: =IF(AND(A15>=DATOS!$B$30,A15<DATOS!$B$31),"cruce de camiones",IF(AND(A15>=DATOS!$B$32,A15<DATOS!$B$33),"cruce de motos","tramo normal")) | P15: =E15*1.001 | Q15: 3 | R15: =IF((((P15+Q15)/2)+(C15/(D15*((P15+Q15)/2)))^2/(2*9.81)+B15-(G14+H14^2/(2*9.81))-(A14-A15)*(((DATOS!$B$34*(C15/(D15*((P15+Q15)/2)))/((D15*((P15+Q15)/2))/(D15+2*((P15+Q15)/2)))^(2/3))^2+((DATOS!$B$34*H14/((D14*F14)/(D14+2*F14))^(2/3))^2))/2))>0,P15,((P15+Q15)/2)) | S15: =IF((((P15+Q15)/2)+(C15/(D15*((P15+Q15)/2)))^2/(2*9.81)+B15-(G14+H14^2/(2*9.81))-(A14-A15)*(((DATOS!$B$34*(C15/(D15*((P15+Q15)/2)))/((D15*((P15+Q15)/2))/(D15+2*((P15+Q15)/2)))^(2/3))^2+((DATOS!$B$34*H14/((D14*F14)/(D14+2*F14))^(2/3))^2))/2))>0,((P15+Q15)/2),Q15) | T15: =IF((((R15+S15)/2)+(C15/(D15*((R15+S15)/2)))^2/(2*9.81)+B15-(G14+H14^2/(2*9.81))-(A14-A15)*(((DATOS!$B$34*(C15/(D15*((R15+S15)/2)))/((D15*((R15+S15)/2))/(D15+2*((R15+S15)/2)))^(2/3))^2+((DATOS!$B$34*H14/((D14*F14)/(D14+2*F14))^(2/3))^2))/2))>0,R15,((R15+S15)/2)) | U15: =IF((((R15+S15)/2)+(C15/(D15*((R15+S15)/2)))^2/(2*9.81)+B15-(G14+H14^2/(2*9.81))-(A14-A15)*(((DATOS!$B$34*(C15/(D15*((R15+S15)/2)))/((D15*((R15+S15)/2))/(D15+2*((R15+S15)/2)))^(2/3))^2+((DATOS!$B$34*H14/((D14*F14)/(D14+2*F14))^(2/3))^2))/2))>0,((R15+S15)/2),S15) | V15: =IF((((T15+U15)/2)+(C15/(D15*((T15+U15)/2)))^2/(2*9.81)+B15-(G14+H14^2/(2*9.81))-(A14-A15)*(((DATOS!$B$34*(C15/(D15*((T15+U15)/2)))/((D15*((T15+U15)/2))/(D15+2*((T15+U15)/2)))^(2/3))^2+((DATOS!$B$34*H14/((D14*F14)/(D14+2*F14))^(2/3))^2))/2))>0,T15,((T15+U15)/2)) | W15: =IF((((T15+U15)/2)+(C15/(D15*((T15+U15)/2)))^2/(2*9.81)+B15-(G14+H14^2/(2*9.81))-(A14-A15)*(((DATOS!$B$34*(C15/(D15*((T15+U15)/2)))/((D15*((T15+U15)/2))/(D15+2*((T15+U15)/2)))^(2/3))^2+((DATOS!$B$34*H14/((D14*F14)/(D14+2*F14))^(2/3))^2))/2))>0,((T15+U15)/2),U15) | X15: =IF((((V15+W15)/2)+(C15/(D15*((V15+W15)/2)))^2/(2*9.81)+B15-(G14+H14^2/(2*9.81))-(A14-A15)*(((DATOS!$B$34*(C15/(D15*((V15+W15)/2)))/((D15*((V15+W15)/2))/(D15+2*((V15+W15)/2)))^(2/3))^2+((DATOS!$B$34*H14/((D14*F14)/(D14+2*F14))^(2/3))^2))/2))>0,V15,((V15+W15)/2)) | Y15: =IF((((V15+W15)/2)+(C15/(D15*((V15+W15)/2)))^2/(2*9.81)+B15-(G14+H14^2/(2*9.81))-(A14-A15)*(((DATOS!$B$34*(C15/(D15*((V15+W15)/2)))/((D15*((V15+W15)/2))/(D15+2*((V15+W15)/2)))^(2/3))^2+((DATOS!$B$34*H14/((D14*F14)/(D14+2*F14))^(2/3))^2))/2))>0,((V15+W15)/2),W15) | Z15: =IF((((X15+Y15)/2)+(C15/(D15*((X15+Y15)/2)))^2/(2*9.81)+B15-(G14+H14^2/(2*9.81))-(A14-A15)*(((DATOS!$B$34*(C15/(D15*((X15+Y15)/2)))/((D15*((X15+Y15)/2))/(D15+2*((X15+Y15)/2)))^(2/3))^2+((DATOS!$B$34*H14/((D14*F14)/(D14+2*F14))^(2/3))^2))/2))>0,X15,((X15+Y15)/2)) | AA15: =IF((((X15+Y15)/2)+(C15/(D15*((X15+Y15)/2)))^2/(2*9.81)+B15-(G14+H14^2/(2*9.81))-(A14-A15)*(((DATOS!$B$34*(C15/(D15*((X15+Y15)/2)))/((D15*((X15+Y15)/2))/(D15+2*((X15+Y15)/2)))^(2/3))^2+((DATOS!$B$34*H14/((D14*F14)/(D14+2*F14))^(2/3))^2))/2))>0,((X15+Y15)/2),Y15) | AB15: =IF((((Z15+AA15)/2)+(C15/(D15*((Z15+AA15)/2)))^2/(2*9.81)+B15-(G14+H14^2/(2*9.81))-(A14-A15)*(((DATOS!$B$34*(C15/(D15*((Z15+AA15)/2)))/((D15*((Z15+AA15)/2))/(D15+2*((Z15+AA15)/2)))^(2/3))^2+((DATOS!$B$34*H14/((D14*F14)/(D14+2*F14))^(2/3))^2))/2))>0,Z15,((Z15+AA15)/2)) | AC15: =IF((((Z15+AA15)/2)+(C15/(D15*((Z15+AA15)/2)))^2/(2*9.81)+B15-(G14+H14^2/(2*9.81))-(A14-A15)*(((DATOS!$B$34*(C15/(D15*((Z15+AA15)/2)))/((D15*((Z15+AA15)/2))/(D15+2*((Z15+AA15)/2)))^(2/3))^2+((DATOS!$B$34*H14/((D14*F14)/(D14+2*F14))^(2/3))^2))/2))>0,((Z15+AA15)/2),AA15) | AD15: =IF((((AB15+AC15)/2)+(C15/(D15*((AB15+AC15)/2)))^2/(2*9.81)+B15-(G14+H14^2/(2*9.81))-(A14-A15)*(((DATOS!$B$34*(C15/(D15*((AB15+AC15)/2)))/((D15*((AB15+AC15)/2))/(D15+2*((AB15+AC15)/2)))^(2/3))^2+((DATOS!$B$34*H14/((D14*F14)/(D14+2*F14))^(2/3))^2))/2))>0,AB15,((AB15+AC15)/2)) | AE15: =IF((((AB15+AC15)/2)+(C15/(D15*((AB15+AC15)/2)))^2/(2*9.81)+B15-(G14+H14^2/(2*9.81))-(A14-A15)*(((DATOS!$B$34*(C15/(D15*((AB15+AC15)/2)))/((D15*((AB15+AC15)/2))/(D15+2*((AB15+AC15)/2)))^(2/3))^2+((DATOS!$B$34*H14/((D14*F14)/(D14+2*F14))^(2/3))^2))/2))>0,((AB15+AC15)/2),AC15) | AF15: =IF((((AD15+AE15)/2)+(C15/(D15*((AD15+AE15)/2)))^2/(2*9.81)+B15-(G14+H14^2/(2*9.81))-(A14-A15)*(((DATOS!$B$34*(C15/(D15*((AD15+AE15)/2)))/((D15*((AD15+AE15)/2))/(D15+2*((AD15+AE15)/2)))^(2/3))^2+((DATOS!$B$34*H14/((D14*F14)/(D14+2*F14))^(2/3))^2))/2))>0,AD15,((AD15+AE15)/2)) | AG15: =IF((((AD15+AE15)/2)+(C15/(D15*((AD15+AE15)/2)))^2/(2*9.81)+B15-(G14+H14^2/(2*9.81))-(A14-A15)*(((DATOS!$B$34*(C15/(D15*((AD15+AE15)/2)))/((D15*((AD15+AE15)/2))/(D15+2*((AD15+AE15)/2)))^(2/3))^2+((DATOS!$B$34*H14/((D14*F14)/(D14+2*F14))^(2/3))^2))/2))>0,((AD15+AE15)/2),AE15) | AH15: =IF((((AF15+AG15)/2)+(C15/(D15*((AF15+AG15)/2)))^2/(2*9.81)+B15-(G14+H14^2/(2*9.81))-(A14-A15)*(((DATOS!$B$34*(C15/(D15*((AF15+AG15)/2)))/((D15*((AF15+AG15)/2))/(D15+2*((AF15+AG15)/2)))^(2/3))^2+((DATOS!$B$34*H14/((D14*F14)/(D14+2*F14))^(2/3))^2))/2))>0,AF15,((AF15+AG15)/2)) | AI15: =IF((((AF15+AG15)/2)+(C15/(D15*((AF15+AG15)/2)))^2/(2*9.81)+B15-(G14+H14^2/(2*9.81))-(A14-A15)*(((DATOS!$B$34*(C15/(D15*((AF15+AG15)/2)))/((D15*((AF15+AG15)/2))/(D15+2*((AF15+AG15)/2)))^(2/3))^2+((DATOS!$B$34*H14/((D14*F14)/(D14+2*F14))^(2/3))^2))/2))>0,((AF15+AG15)/2),AG15) | AJ15: =IF((((AH15+AI15)/2)+(C15/(D15*((AH15+AI15)/2)))^2/(2*9.81)+B15-(G14+H14^2/(2*9.81))-(A14-A15)*(((DATOS!$B$34*(C15/(D15*((AH15+AI15)/2)))/((D15*((AH15+AI15)/2))/(D15+2*((AH15+AI15)/2)))^(2/3))^2+((DATOS!$B$34*H14/((D14*F14)/(D14+2*F14))^(2/3))^2))/2))>0,AH15,((AH15+AI15)/2)) | AK15: =IF((((AH15+AI15)/2)+(C15/(D15*((AH15+AI15)/2)))^2/(2*9.81)+B15-(G14+H14^2/(2*9.81))-(A14-A15)*(((DATOS!$B$34*(C15/(D15*((AH15+AI15)/2)))/((D15*((AH15+AI15)/2))/(D15+2*((AH15+AI15)/2)))^(2/3))^2+((DATOS!$B$34*H14/((D14*F14)/(D14+2*F14))^(2/3))^2))/2))>0,((AH15+AI15)/2),AI15) | AL15: =IF((((AJ15+AK15)/2)+(C15/(D15*((AJ15+AK15)/2)))^2/(2*9.81)+B15-(G14+H14^2/(2*9.81))-(A14-A15)*(((DATOS!$B$34*(C15/(D15*((AJ15+AK15)/2)))/((D15*((AJ15+AK15)/2))/(D15+2*((AJ15+AK15)/2)))^(2/3))^2+((DATOS!$B$34*H14/((D14*F14)/(D14+2*F14))^(2/3))^2))/2))>0,AJ15,((AJ15+AK15)/2)) | AM15: =IF((((AJ15+AK15)/2)+(C15/(D15*((AJ15+AK15)/2)))^2/(2*9.81)+B15-(G14+H14^2/(2*9.81))-(A14-A15)*(((DATOS!$B$34*(C15/(D15*((AJ15+AK15)/2)))/((D15*((AJ15+AK15)/2))/(D15+2*((AJ15+AK15)/2)))^(2/3))^2+((DATOS!$B$34*H14/((D14*F14)/(D14+2*F14))^(2/3))^2))/2))>0,((AJ15+AK15)/2),AK15) | AN15: =IF((((AL15+AM15)/2)+(C15/(D15*((AL15+AM15)/2)))^2/(2*9.81)+B15-(G14+H14^2/(2*9.81))-(A14-A15)*(((DATOS!$B$34*(C15/(D15*((AL15+AM15)/2)))/((D15*((AL15+AM15)/2))/(D15+2*((AL15+AM15)/2)))^(2/3))^2+((DATOS!$B$34*H14/((D14*F14)/(D14+2*F14))^(2/3))^2))/2))>0,AL15,((AL15+AM15)/2)) | AO15: =IF((((AL15+AM15)/2)+(C15/(D15*((AL15+AM15)/2)))^2/(2*9.81)+B15-(G14+H14^2/(2*9.81))-(A14-A15)*(((DATOS!$B$34*(C15/(D15*((AL15+AM15)/2)))/((D15*((AL15+AM15)/2))/(D15+2*((AL15+AM15)/2)))^(2/3))^2+((DATOS!$B$34*H14/((D14*F14)/(D14+2*F14))^(2/3))^2))/2))>0,((AL15+AM15)/2),AM15) | AP15: =IF((((AN15+AO15)/2)+(C15/(D15*((AN15+AO15)/2)))^2/(2*9.81)+B15-(G14+H14^2/(2*9.81))-(A14-A15)*(((DATOS!$B$34*(C15/(D15*((AN15+AO15)/2)))/((D15*((AN15+AO15)/2))/(D15+2*((AN15+AO15)/2)))^(2/3))^2+((DATOS!$B$34*H14/((D14*F14)/(D14+2*F14))^(2/3))^2))/2))>0,AN15,((AN15+AO15)/2)) | AQ15: =IF((((AN15+AO15)/2)+(C15/(D15*((AN15+AO15)/2)))^2/(2*9.81)+B15-(G14+H14^2/(2*9.81))-(A14-A15)*(((DATOS!$B$34*(C15/(D15*((AN15+AO15)/2)))/((D15*((AN15+AO15)/2))/(D15+2*((AN15+AO15)/2)))^(2/3))^2+((DATOS!$B$34*H14/((D14*F14)/(D14+2*F14))^(2/3))^2))/2))>0,((AN15+AO15)/2),AO15) | AR15: =IF((((AP15+AQ15)/2)+(C15/(D15*((AP15+AQ15)/2)))^2/(2*9.81)+B15-(G14+H14^2/(2*9.81))-(A14-A15)*(((DATOS!$B$34*(C15/(D15*((AP15+AQ15)/2)))/((D15*((AP15+AQ15)/2))/(D15+2*((AP15+AQ15)/2)))^(2/3))^2+((DATOS!$B$34*H14/((D14*F14)/(D14+2*F14))^(2/3))^2))/2))>0,AP15,((AP15+AQ15)/2)) | AS15: =IF((((AP15+AQ15)/2)+(C15/(D15*((AP15+AQ15)/2)))^2/(2*9.81)+B15-(G14+H14^2/(2*9.81))-(A14-A15)*(((DATOS!$B$34*(C15/(D15*((AP15+AQ15)/2)))/((D15*((AP15+AQ15)/2))/(D15+2*((AP15+AQ15)/2)))^(2/3))^2+((DATOS!$B$34*H14/((D14*F14)/(D14+2*F14))^(2/3))^2))/2))>0,((AP15+AQ15)/2),AQ15) | AT15: =IF((((AR15+AS15)/2)+(C15/(D15*((AR15+AS15)/2)))^2/(2*9.81)+B15-(G14+H14^2/(2*9.81))-(A14-A15)*(((DATOS!$B$34*(C15/(D15*((AR15+AS15)/2)))/((D15*((AR15+AS15)/2))/(D15+2*((AR15+AS15)/2)))^(2/3))^2+((DATOS!$B$34*H14/((D14*F14)/(D14+2*F14))^(2/3))^2))/2))>0,AR15,((AR15+AS15)/2)) | AU15: =IF((((AR15+AS15)/2)+(C15/(D15*((AR15+AS15)/2)))^2/(2*9.81)+B15-(G14+H14^2/(2*9.81))-(A14-A15)*(((DATOS!$B$34*(C15/(D15*((AR15+AS15)/2)))/((D15*((AR15+AS15)/2))/(D15+2*((AR15+AS15)/2)))^(2/3))^2+((DATOS!$B$34*H14/((D14*F14)/(D14+2*F14))^(2/3))^2))/2))>0,((AR15+AS15)/2),AS15) | AV15: =IF((((AT15+AU15)/2)+(C15/(D15*((AT15+AU15)/2)))^2/(2*9.81)+B15-(G14+H14^2/(2*9.81))-(A14-A15)*(((DATOS!$B$34*(C15/(D15*((AT15+AU15)/2)))/((D15*((AT15+AU15)/2))/(D15+2*((AT15+AU15)/2)))^(2/3))^2+((DATOS!$B$34*H14/((D14*F14)/(D14+2*F14))^(2/3))^2))/2))>0,AT15,((AT15+AU15)/2)) | AW15: =IF((((AT15+AU15)/2)+(C15/(D15*((AT15+AU15)/2)))^2/(2*9.81)+B15-(G14+H14^2/(2*9.81))-(A14-A15)*(((DATOS!$B$34*(C15/(D15*((AT15+AU15)/2)))/((D15*((AT15+AU15)/2))/(D15+2*((AT15+AU15)/2)))^(2/3))^2+((DATOS!$B$34*H14/((D14*F14)/(D14+2*F14))^(2/3))^2))/2))>0,((AT15+AU15)/2),AU15) | AX15: =IF((((AV15+AW15)/2)+(C15/(D15*((AV15+AW15)/2)))^2/(2*9.81)+B15-(G14+H14^2/(2*9.81))-(A14-A15)*(((DATOS!$B$34*(C15/(D15*((AV15+AW15)/2)))/((D15*((AV15+AW15)/2))/(D15+2*((AV15+AW15)/2)))^(2/3))^2+((DATOS!$B$34*H14/((D14*F14)/(D14+2*F14))^(2/3))^2))/2))>0,AV15,((AV15+AW15)/2)) | AY15: =IF((((AV15+AW15)/2)+(C15/(D15*((AV15+AW15)/2)))^2/(2*9.81)+B15-(G14+H14^2/(2*9.81))-(A14-A15)*(((DATOS!$B$34*(C15/(D15*((AV15+AW15)/2)))/((D15*((AV15+AW15)/2))/(D15+2*((AV15+AW15)/2)))^(2/3))^2+((DATOS!$B$34*H14/((D14*F14)/(D14+2*F14))^(2/3))^2))/2))>0,((AV15+AW15)/2),AW15) | AZ15: =IF((((AX15+AY15)/2)+(C15/(D15*((AX15+AY15)/2)))^2/(2*9.81)+B15-(G14+H14^2/(2*9.81))-(A14-A15)*(((DATOS!$B$34*(C15/(D15*((AX15+AY15)/2)))/((D15*((AX15+AY15)/2))/(D15+2*((AX15+AY15)/2)))^(2/3))^2+((DATOS!$B$34*H14/((D14*F14)/(D14+2*F14))^(2/3))^2))/2))>0,AX15,((AX15+AY15)/2)) | BA15: =IF((((AX15+AY15)/2)+(C15/(D15*((AX15+AY15)/2)))^2/(2*9.81)+B15-(G14+H14^2/(2*9.81))-(A14-A15)*(((DATOS!$B$34*(C15/(D15*((AX15+AY15)/2)))/((D15*((AX15+AY15)/2))/(D15+2*((AX15+AY15)/2)))^(2/3))^2+((DATOS!$B$34*H14/((D14*F14)/(D14+2*F14))^(2/3))^2))/2))>0,((AX15+AY15)/2),AY15) | BB15: =IF((((AZ15+BA15)/2)+(C15/(D15*((AZ15+BA15)/2)))^2/(2*9.81)+B15-(G14+H14^2/(2*9.81))-(A14-A15)*(((DATOS!$B$34*(C15/(D15*((AZ15+BA15)/2)))/((D15*((AZ15+BA15)/2))/(D15+2*((AZ15+BA15)/2)))^(2/3))^2+((DATOS!$B$34*H14/((D14*F14)/(D14+2*F14))^(2/3))^2))/2))>0,AZ15,((AZ15+BA15)/2)) | BC15: =IF((((AZ15+BA15)/2)+(C15/(D15*((AZ15+BA15)/2)))^2/(2*9.81)+B15-(G14+H14^2/(2*9.81))-(A14-A15)*(((DATOS!$B$34*(C15/(D15*((AZ15+BA15)/2)))/((D15*((AZ15+BA15)/2))/(D15+2*((AZ15+BA15)/2)))^(2/3))^2+((DATOS!$B$34*H14/((D14*F14)/(D14+2*F14))^(2/3))^2))/2))>0,((AZ15+BA15)/2),BA15) | BD15: =IF((((BB15+BC15)/2)+(C15/(D15*((BB15+BC15)/2)))^2/(2*9.81)+B15-(G14+H14^2/(2*9.81))-(A14-A15)*(((DATOS!$B$34*(C15/(D15*((BB15+BC15)/2)))/((D15*((BB15+BC15)/2))/(D15+2*((BB15+BC15)/2)))^(2/3))^2+((DATOS!$B$34*H14/((D14*F14)/(D14+2*F14))^(2/3))^2))/2))>0,BB15,((BB15+BC15)/2)) | BE15: =IF((((BB15+BC15)/2)+(C15/(D15*((BB15+BC15)/2)))^2/(2*9.81)+B15-(G14+H14^2/(2*9.81))-(A14-A15)*(((DATOS!$B$34*(C15/(D15*((BB15+BC15)/2)))/((D15*((BB15+BC15)/2))/(D15+2*((BB15+BC15)/2)))^(2/3))^2+((DATOS!$B$34*H14/((D14*F14)/(D14+2*F14))^(2/3))^2))/2))>0,((BB15+BC15)/2),BC15) | BF15: =IF((((BD15+BE15)/2)+(C15/(D15*((BD15+BE15)/2)))^2/(2*9.81)+B15-(G14+H14^2/(2*9.81))-(A14-A15)*(((DATOS!$B$34*(C15/(D15*((BD15+BE15)/2)))/((D15*((BD15+BE15)/2))/(D15+2*((BD15+BE15)/2)))^(2/3))^2+((DATOS!$B$34*H14/((D14*F14)/(D14+2*F14))^(2/3))^2))/2))>0,BD15,((BD15+BE15)/2)) | BG15: =IF((((BD15+BE15)/2)+(C15/(D15*((BD15+BE15)/2)))^2/(2*9.81)+B15-(G14+H14^2/(2*9.81))-(A14-A15)*(((DATOS!$B$34*(C15/(D15*((BD15+BE15)/2)))/((D15*((BD15+BE15)/2))/(D15+2*((BD15+BE15)/2)))^(2/3))^2+((DATOS!$B$34*H14/((D14*F14)/(D14+2*F14))^(2/3))^2))/2))>0,((BD15+BE15)/2),BE15) | BH15: =IF((((BF15+BG15)/2)+(C15/(D15*((BF15+BG15)/2)))^2/(2*9.81)+B15-(G14+H14^2/(2*9.81))-(A14-A15)*(((DATOS!$B$34*(C15/(D15*((BF15+BG15)/2)))/((D15*((BF15+BG15)/2))/(D15+2*((BF15+BG15)/2)))^(2/3))^2+((DATOS!$B$34*H14/((D14*F14)/(D14+2*F14))^(2/3))^2))/2))>0,BF15,((BF15+BG15)/2)) | BI15: =IF((((BF15+BG15)/2)+(C15/(D15*((BF15+BG15)/2)))^2/(2*9.81)+B15-(G14+H14^2/(2*9.81))-(A14-A15)*(((DATOS!$B$34*(C15/(D15*((BF15+BG15)/2)))/((D15*((BF15+BG15)/2))/(D15+2*((BF15+BG15)/2)))^(2/3))^2+((DATOS!$B$34*H14/((D14*F14)/(D14+2*F14))^(2/3))^2))/2))>0,((BF15+BG15)/2),BG15) | BJ15: =IF((((BH15+BI15)/2)+(C15/(D15*((BH15+BI15)/2)))^2/(2*9.81)+B15-(G14+H14^2/(2*9.81))-(A14-A15)*(((DATOS!$B$34*(C15/(D15*((BH15+BI15)/2)))/((D15*((BH15+BI15)/2))/(D15+2*((BH15+BI15)/2)))^(2/3))^2+((DATOS!$B$34*H14/((D14*F14)/(D14+2*F14))^(2/3))^2))/2))>0,BH15,((BH15+BI15)/2)) | BK15: =IF((((BH15+BI15)/2)+(C15/(D15*((BH15+BI15)/2)))^2/(2*9.81)+B15-(G14+H14^2/(2*9.81))-(A14-A15)*(((DATOS!$B$34*(C15/(D15*((BH15+BI15)/2)))/((D15*((BH15+BI15)/2))/(D15+2*((BH15+BI15)/2)))^(2/3))^2+((DATOS!$B$34*H14/((D14*F14)/(D14+2*F14))^(2/3))^2))/2))>0,((BH15+BI15)/2),BI15) | BL15: =IF((((BJ15+BK15)/2)+(C15/(D15*((BJ15+BK15)/2)))^2/(2*9.81)+B15-(G14+H14^2/(2*9.81))-(A14-A15)*(((DATOS!$B$34*(C15/(D15*((BJ15+BK15)/2)))/((D15*((BJ15+BK15)/2))/(D15+2*((BJ15+BK15)/2)))^(2/3))^2+((DATOS!$B$34*H14/((D14*F14)/(D14+2*F14))^(2/3))^2))/2))>0,BJ15,((BJ15+BK15)/2)) | BM15: =IF((((BJ15+BK15)/2)+(C15/(D15*((BJ15+BK15)/2)))^2/(2*9.81)+B15-(G14+H14^2/(2*9.81))-(A14-A15)*(((DATOS!$B$34*(C15/(D15*((BJ15+BK15)/2)))/((D15*((BJ15+BK15)/2))/(D15+2*((BJ15+BK15)/2)))^(2/3))^2+((DATOS!$B$34*H14/((D14*F14)/(D14+2*F14))^(2/3))^2))/2))>0,((BJ15+BK15)/2),BK15) | BN15: =IF((((BL15+BM15)/2)+(C15/(D15*((BL15+BM15)/2)))^2/(2*9.81)+B15-(G14+H14^2/(2*9.81))-(A14-A15)*(((DATOS!$B$34*(C15/(D15*((BL15+BM15)/2)))/((D15*((BL15+BM15)/2))/(D15+2*((BL15+BM15)/2)))^(2/3))^2+((DATOS!$B$34*H14/((D14*F14)/(D14+2*F14))^(2/3))^2))/2))>0,BL15,((BL15+BM15)/2)) | BO15: =IF((((BL15+BM15)/2)+(C15/(D15*((BL15+BM15)/2)))^2/(2*9.81)+B15-(G14+H14^2/(2*9.81))-(A14-A15)*(((DATOS!$B$34*(C15/(D15*((BL15+BM15)/2)))/((D15*((BL15+BM15)/2))/(D15+2*((BL15+BM15)/2)))^(2/3))^2+((DATOS!$B$34*H14/((D14*F14)/(D14+2*F14))^(2/3))^2))/2))>0,((BL15+BM15)/2),BM15) | BP15: =IF((((BN15+BO15)/2)+(C15/(D15*((BN15+BO15)/2)))^2/(2*9.81)+B15-(G14+H14^2/(2*9.81))-(A14-A15)*(((DATOS!$B$34*(C15/(D15*((BN15+BO15)/2)))/((D15*((BN15+BO15)/2))/(D15+2*((BN15+BO15)/2)))^(2/3))^2+((DATOS!$B$34*H14/((D14*F14)/(D14+2*F14))^(2/3))^2))/2))>0,BN15,((BN15+BO15)/2)) | BQ15: =IF((((BN15+BO15)/2)+(C15/(D15*((BN15+BO15)/2)))^2/(2*9.81)+B15-(G14+H14^2/(2*9.81))-(A14-A15)*(((DATOS!$B$34*(C15/(D15*((BN15+BO15)/2)))/((D15*((BN15+BO15)/2))/(D15+2*((BN15+BO15)/2)))^(2/3))^2+((DATOS!$B$34*H14/((D14*F14)/(D14+2*F14))^(2/3))^2))/2))>0,((BN15+BO15)/2),BO15) | BR15: =IF((((BP15+BQ15)/2)+(C15/(D15*((BP15+BQ15)/2)))^2/(2*9.81)+B15-(G14+H14^2/(2*9.81))-(A14-A15)*(((DATOS!$B$34*(C15/(D15*((BP15+BQ15)/2)))/((D15*((BP15+BQ15)/2))/(D15+2*((BP15+BQ15)/2)))^(2/3))^2+((DATOS!$B$34*H14/((D14*F14)/(D14+2*F14))^(2/3))^2))/2))>0,BP15,((BP15+BQ15)/2)) | BS15: =IF((((BP15+BQ15)/2)+(C15/(D15*((BP15+BQ15)/2)))^2/(2*9.81)+B15-(G14+H14^2/(2*9.81))-(A14-A15)*(((DATOS!$B$34*(C15/(D15*((BP15+BQ15)/2)))/((D15*((BP15+BQ15)/2))/(D15+2*((BP15+BQ15)/2)))^(2/3))^2+((DATOS!$B$34*H14/((D14*F14)/(D14+2*F14))^(2/3))^2))/2))>0,((BP15+BQ15)/2),BQ15) | BT15: =IF((((BR15+BS15)/2)+(C15/(D15*((BR15+BS15)/2)))^2/(2*9.81)+B15-(G14+H14^2/(2*9.81))-(A14-A15)*(((DATOS!$B$34*(C15/(D15*((BR15+BS15)/2)))/((D15*((BR15+BS15)/2))/(D15+2*((BR15+BS15)/2)))^(2/3))^2+((DATOS!$B$34*H14/((D14*F14)/(D14+2*F14))^(2/3))^2))/2))>0,BR15,((BR15+BS15)/2)) | BU15: =IF((((BR15+BS15)/2)+(C15/(D15*((BR15+BS15)/2)))^2/(2*9.81)+B15-(G14+H14^2/(2*9.81))-(A14-A15)*(((DATOS!$B$34*(C15/(D15*((BR15+BS15)/2)))/((D15*((BR15+BS15)/2))/(D15+2*((BR15+BS15)/2)))^(2/3))^2+((DATOS!$B$34*H14/((D14*F14)/(D14+2*F14))^(2/3))^2))/2))>0,((BR15+BS15)/2),BS15) | BV15: =IF((((BT15+BU15)/2)+(C15/(D15*((BT15+BU15)/2)))^2/(2*9.81)+B15-(G14+H14^2/(2*9.81))-(A14-A15)*(((DATOS!$B$34*(C15/(D15*((BT15+BU15)/2)))/((D15*((BT15+BU15)/2))/(D15+2*((BT15+BU15)/2)))^(2/3))^2+((DATOS!$B$34*H14/((D14*F14)/(D14+2*F14))^(2/3))^2))/2))>0,BT15,((BT15+BU15)/2)) | BW15: =IF((((BT15+BU15)/2)+(C15/(D15*((BT15+BU15)/2)))^2/(2*9.81)+B15-(G14+H14^2/(2*9.81))-(A14-A15)*(((DATOS!$B$34*(C15/(D15*((BT15+BU15)/2)))/((D15*((BT15+BU15)/2))/(D15+2*((BT15+BU15)/2)))^(2/3))^2+((DATOS!$B$34*H14/((D14*F14)/(D14+2*F14))^(2/3))^2))/2))>0,((BT15+BU15)/2),BU15)
A16: 63 | B16: =DATOS!$B$22-DATOS!$B$23*A16 | C16: =CAUDALES!$B$13 | D16: =DATOS!$B$17 | E16: =(C16^2/(9.81*D16^2))^(1/3) | F16: =(BV16+BW16)/2 | G16: =B16+F16 | H16: =C16/(D16*F16) | I16: =H16/SQRT(9.81*F16) | J16: =DATOS!$B$29-IF(AND(A16>=DATOS!$B$30,A16<DATOS!$B$31),DATOS!$B$21,DATOS!$B$20) | K16: =J16-B16 | L16: =F16/K16 | M16: =J16-G16 | N16: =IF(AND(L16<=DATOS!$B$36,M16>=DATOS!$B$37,I16<=1),"CUMPLE","NO CUMPLE") | O16: =IF(AND(A16>=DATOS!$B$30,A16<DATOS!$B$31),"cruce de camiones",IF(AND(A16>=DATOS!$B$32,A16<DATOS!$B$33),"cruce de motos","tramo normal")) | P16: =E16*1.001 | Q16: 3 | R16: =IF((((P16+Q16)/2)+(C16/(D16*((P16+Q16)/2)))^2/(2*9.81)+B16-(G15+H15^2/(2*9.81))-(A15-A16)*(((DATOS!$B$34*(C16/(D16*((P16+Q16)/2)))/((D16*((P16+Q16)/2))/(D16+2*((P16+Q16)/2)))^(2/3))^2+((DATOS!$B$34*H15/((D15*F15)/(D15+2*F15))^(2/3))^2))/2))>0,P16,((P16+Q16)/2)) | S16: =IF((((P16+Q16)/2)+(C16/(D16*((P16+Q16)/2)))^2/(2*9.81)+B16-(G15+H15^2/(2*9.81))-(A15-A16)*(((DATOS!$B$34*(C16/(D16*((P16+Q16)/2)))/((D16*((P16+Q16)/2))/(D16+2*((P16+Q16)/2)))^(2/3))^2+((DATOS!$B$34*H15/((D15*F15)/(D15+2*F15))^(2/3))^2))/2))>0,((P16+Q16)/2),Q16) | T16: =IF((((R16+S16)/2)+(C16/(D16*((R16+S16)/2)))^2/(2*9.81)+B16-(G15+H15^2/(2*9.81))-(A15-A16)*(((DATOS!$B$34*(C16/(D16*((R16+S16)/2)))/((D16*((R16+S16)/2))/(D16+2*((R16+S16)/2)))^(2/3))^2+((DATOS!$B$34*H15/((D15*F15)/(D15+2*F15))^(2/3))^2))/2))>0,R16,((R16+S16)/2)) | U16: =IF((((R16+S16)/2)+(C16/(D16*((R16+S16)/2)))^2/(2*9.81)+B16-(G15+H15^2/(2*9.81))-(A15-A16)*(((DATOS!$B$34*(C16/(D16*((R16+S16)/2)))/((D16*((R16+S16)/2))/(D16+2*((R16+S16)/2)))^(2/3))^2+((DATOS!$B$34*H15/((D15*F15)/(D15+2*F15))^(2/3))^2))/2))>0,((R16+S16)/2),S16) | V16: =IF((((T16+U16)/2)+(C16/(D16*((T16+U16)/2)))^2/(2*9.81)+B16-(G15+H15^2/(2*9.81))-(A15-A16)*(((DATOS!$B$34*(C16/(D16*((T16+U16)/2)))/((D16*((T16+U16)/2))/(D16+2*((T16+U16)/2)))^(2/3))^2+((DATOS!$B$34*H15/((D15*F15)/(D15+2*F15))^(2/3))^2))/2))>0,T16,((T16+U16)/2)) | W16: =IF((((T16+U16)/2)+(C16/(D16*((T16+U16)/2)))^2/(2*9.81)+B16-(G15+H15^2/(2*9.81))-(A15-A16)*(((DATOS!$B$34*(C16/(D16*((T16+U16)/2)))/((D16*((T16+U16)/2))/(D16+2*((T16+U16)/2)))^(2/3))^2+((DATOS!$B$34*H15/((D15*F15)/(D15+2*F15))^(2/3))^2))/2))>0,((T16+U16)/2),U16) | X16: =IF((((V16+W16)/2)+(C16/(D16*((V16+W16)/2)))^2/(2*9.81)+B16-(G15+H15^2/(2*9.81))-(A15-A16)*(((DATOS!$B$34*(C16/(D16*((V16+W16)/2)))/((D16*((V16+W16)/2))/(D16+2*((V16+W16)/2)))^(2/3))^2+((DATOS!$B$34*H15/((D15*F15)/(D15+2*F15))^(2/3))^2))/2))>0,V16,((V16+W16)/2)) | Y16: =IF((((V16+W16)/2)+(C16/(D16*((V16+W16)/2)))^2/(2*9.81)+B16-(G15+H15^2/(2*9.81))-(A15-A16)*(((DATOS!$B$34*(C16/(D16*((V16+W16)/2)))/((D16*((V16+W16)/2))/(D16+2*((V16+W16)/2)))^(2/3))^2+((DATOS!$B$34*H15/((D15*F15)/(D15+2*F15))^(2/3))^2))/2))>0,((V16+W16)/2),W16) | Z16: =IF((((X16+Y16)/2)+(C16/(D16*((X16+Y16)/2)))^2/(2*9.81)+B16-(G15+H15^2/(2*9.81))-(A15-A16)*(((DATOS!$B$34*(C16/(D16*((X16+Y16)/2)))/((D16*((X16+Y16)/2))/(D16+2*((X16+Y16)/2)))^(2/3))^2+((DATOS!$B$34*H15/((D15*F15)/(D15+2*F15))^(2/3))^2))/2))>0,X16,((X16+Y16)/2)) | AA16: =IF((((X16+Y16)/2)+(C16/(D16*((X16+Y16)/2)))^2/(2*9.81)+B16-(G15+H15^2/(2*9.81))-(A15-A16)*(((DATOS!$B$34*(C16/(D16*((X16+Y16)/2)))/((D16*((X16+Y16)/2))/(D16+2*((X16+Y16)/2)))^(2/3))^2+((DATOS!$B$34*H15/((D15*F15)/(D15+2*F15))^(2/3))^2))/2))>0,((X16+Y16)/2),Y16) | AB16: =IF((((Z16+AA16)/2)+(C16/(D16*((Z16+AA16)/2)))^2/(2*9.81)+B16-(G15+H15^2/(2*9.81))-(A15-A16)*(((DATOS!$B$34*(C16/(D16*((Z16+AA16)/2)))/((D16*((Z16+AA16)/2))/(D16+2*((Z16+AA16)/2)))^(2/3))^2+((DATOS!$B$34*H15/((D15*F15)/(D15+2*F15))^(2/3))^2))/2))>0,Z16,((Z16+AA16)/2)) | AC16: =IF((((Z16+AA16)/2)+(C16/(D16*((Z16+AA16)/2)))^2/(2*9.81)+B16-(G15+H15^2/(2*9.81))-(A15-A16)*(((DATOS!$B$34*(C16/(D16*((Z16+AA16)/2)))/((D16*((Z16+AA16)/2))/(D16+2*((Z16+AA16)/2)))^(2/3))^2+((DATOS!$B$34*H15/((D15*F15)/(D15+2*F15))^(2/3))^2))/2))>0,((Z16+AA16)/2),AA16) | AD16: =IF((((AB16+AC16)/2)+(C16/(D16*((AB16+AC16)/2)))^2/(2*9.81)+B16-(G15+H15^2/(2*9.81))-(A15-A16)*(((DATOS!$B$34*(C16/(D16*((AB16+AC16)/2)))/((D16*((AB16+AC16)/2))/(D16+2*((AB16+AC16)/2)))^(2/3))^2+((DATOS!$B$34*H15/((D15*F15)/(D15+2*F15))^(2/3))^2))/2))>0,AB16,((AB16+AC16)/2)) | AE16: =IF((((AB16+AC16)/2)+(C16/(D16*((AB16+AC16)/2)))^2/(2*9.81)+B16-(G15+H15^2/(2*9.81))-(A15-A16)*(((DATOS!$B$34*(C16/(D16*((AB16+AC16)/2)))/((D16*((AB16+AC16)/2))/(D16+2*((AB16+AC16)/2)))^(2/3))^2+((DATOS!$B$34*H15/((D15*F15)/(D15+2*F15))^(2/3))^2))/2))>0,((AB16+AC16)/2),AC16) | AF16: =IF((((AD16+AE16)/2)+(C16/(D16*((AD16+AE16)/2)))^2/(2*9.81)+B16-(G15+H15^2/(2*9.81))-(A15-A16)*(((DATOS!$B$34*(C16/(D16*((AD16+AE16)/2)))/((D16*((AD16+AE16)/2))/(D16+2*((AD16+AE16)/2)))^(2/3))^2+((DATOS!$B$34*H15/((D15*F15)/(D15+2*F15))^(2/3))^2))/2))>0,AD16,((AD16+AE16)/2)) | AG16: =IF((((AD16+AE16)/2)+(C16/(D16*((AD16+AE16)/2)))^2/(2*9.81)+B16-(G15+H15^2/(2*9.81))-(A15-A16)*(((DATOS!$B$34*(C16/(D16*((AD16+AE16)/2)))/((D16*((AD16+AE16)/2))/(D16+2*((AD16+AE16)/2)))^(2/3))^2+((DATOS!$B$34*H15/((D15*F15)/(D15+2*F15))^(2/3))^2))/2))>0,((AD16+AE16)/2),AE16) | AH16: =IF((((AF16+AG16)/2)+(C16/(D16*((AF16+AG16)/2)))^2/(2*9.81)+B16-(G15+H15^2/(2*9.81))-(A15-A16)*(((DATOS!$B$34*(C16/(D16*((AF16+AG16)/2)))/((D16*((AF16+AG16)/2))/(D16+2*((AF16+AG16)/2)))^(2/3))^2+((DATOS!$B$34*H15/((D15*F15)/(D15+2*F15))^(2/3))^2))/2))>0,AF16,((AF16+AG16)/2)) | AI16: =IF((((AF16+AG16)/2)+(C16/(D16*((AF16+AG16)/2)))^2/(2*9.81)+B16-(G15+H15^2/(2*9.81))-(A15-A16)*(((DATOS!$B$34*(C16/(D16*((AF16+AG16)/2)))/((D16*((AF16+AG16)/2))/(D16+2*((AF16+AG16)/2)))^(2/3))^2+((DATOS!$B$34*H15/((D15*F15)/(D15+2*F15))^(2/3))^2))/2))>0,((AF16+AG16)/2),AG16) | AJ16: =IF((((AH16+AI16)/2)+(C16/(D16*((AH16+AI16)/2)))^2/(2*9.81)+B16-(G15+H15^2/(2*9.81))-(A15-A16)*(((DATOS!$B$34*(C16/(D16*((AH16+AI16)/2)))/((D16*((AH16+AI16)/2))/(D16+2*((AH16+AI16)/2)))^(2/3))^2+((DATOS!$B$34*H15/((D15*F15)/(D15+2*F15))^(2/3))^2))/2))>0,AH16,((AH16+AI16)/2)) | AK16: =IF((((AH16+AI16)/2)+(C16/(D16*((AH16+AI16)/2)))^2/(2*9.81)+B16-(G15+H15^2/(2*9.81))-(A15-A16)*(((DATOS!$B$34*(C16/(D16*((AH16+AI16)/2)))/((D16*((AH16+AI16)/2))/(D16+2*((AH16+AI16)/2)))^(2/3))^2+((DATOS!$B$34*H15/((D15*F15)/(D15+2*F15))^(2/3))^2))/2))>0,((AH16+AI16)/2),AI16) | AL16: =IF((((AJ16+AK16)/2)+(C16/(D16*((AJ16+AK16)/2)))^2/(2*9.81)+B16-(G15+H15^2/(2*9.81))-(A15-A16)*(((DATOS!$B$34*(C16/(D16*((AJ16+AK16)/2)))/((D16*((AJ16+AK16)/2))/(D16+2*((AJ16+AK16)/2)))^(2/3))^2+((DATOS!$B$34*H15/((D15*F15)/(D15+2*F15))^(2/3))^2))/2))>0,AJ16,((AJ16+AK16)/2)) | AM16: =IF((((AJ16+AK16)/2)+(C16/(D16*((AJ16+AK16)/2)))^2/(2*9.81)+B16-(G15+H15^2/(2*9.81))-(A15-A16)*(((DATOS!$B$34*(C16/(D16*((AJ16+AK16)/2)))/((D16*((AJ16+AK16)/2))/(D16+2*((AJ16+AK16)/2)))^(2/3))^2+((DATOS!$B$34*H15/((D15*F15)/(D15+2*F15))^(2/3))^2))/2))>0,((AJ16+AK16)/2),AK16) | AN16: =IF((((AL16+AM16)/2)+(C16/(D16*((AL16+AM16)/2)))^2/(2*9.81)+B16-(G15+H15^2/(2*9.81))-(A15-A16)*(((DATOS!$B$34*(C16/(D16*((AL16+AM16)/2)))/((D16*((AL16+AM16)/2))/(D16+2*((AL16+AM16)/2)))^(2/3))^2+((DATOS!$B$34*H15/((D15*F15)/(D15+2*F15))^(2/3))^2))/2))>0,AL16,((AL16+AM16)/2)) | AO16: =IF((((AL16+AM16)/2)+(C16/(D16*((AL16+AM16)/2)))^2/(2*9.81)+B16-(G15+H15^2/(2*9.81))-(A15-A16)*(((DATOS!$B$34*(C16/(D16*((AL16+AM16)/2)))/((D16*((AL16+AM16)/2))/(D16+2*((AL16+AM16)/2)))^(2/3))^2+((DATOS!$B$34*H15/((D15*F15)/(D15+2*F15))^(2/3))^2))/2))>0,((AL16+AM16)/2),AM16) | AP16: =IF((((AN16+AO16)/2)+(C16/(D16*((AN16+AO16)/2)))^2/(2*9.81)+B16-(G15+H15^2/(2*9.81))-(A15-A16)*(((DATOS!$B$34*(C16/(D16*((AN16+AO16)/2)))/((D16*((AN16+AO16)/2))/(D16+2*((AN16+AO16)/2)))^(2/3))^2+((DATOS!$B$34*H15/((D15*F15)/(D15+2*F15))^(2/3))^2))/2))>0,AN16,((AN16+AO16)/2)) | AQ16: =IF((((AN16+AO16)/2)+(C16/(D16*((AN16+AO16)/2)))^2/(2*9.81)+B16-(G15+H15^2/(2*9.81))-(A15-A16)*(((DATOS!$B$34*(C16/(D16*((AN16+AO16)/2)))/((D16*((AN16+AO16)/2))/(D16+2*((AN16+AO16)/2)))^(2/3))^2+((DATOS!$B$34*H15/((D15*F15)/(D15+2*F15))^(2/3))^2))/2))>0,((AN16+AO16)/2),AO16) | AR16: =IF((((AP16+AQ16)/2)+(C16/(D16*((AP16+AQ16)/2)))^2/(2*9.81)+B16-(G15+H15^2/(2*9.81))-(A15-A16)*(((DATOS!$B$34*(C16/(D16*((AP16+AQ16)/2)))/((D16*((AP16+AQ16)/2))/(D16+2*((AP16+AQ16)/2)))^(2/3))^2+((DATOS!$B$34*H15/((D15*F15)/(D15+2*F15))^(2/3))^2))/2))>0,AP16,((AP16+AQ16)/2)) | AS16: =IF((((AP16+AQ16)/2)+(C16/(D16*((AP16+AQ16)/2)))^2/(2*9.81)+B16-(G15+H15^2/(2*9.81))-(A15-A16)*(((DATOS!$B$34*(C16/(D16*((AP16+AQ16)/2)))/((D16*((AP16+AQ16)/2))/(D16+2*((AP16+AQ16)/2)))^(2/3))^2+((DATOS!$B$34*H15/((D15*F15)/(D15+2*F15))^(2/3))^2))/2))>0,((AP16+AQ16)/2),AQ16) | AT16: =IF((((AR16+AS16)/2)+(C16/(D16*((AR16+AS16)/2)))^2/(2*9.81)+B16-(G15+H15^2/(2*9.81))-(A15-A16)*(((DATOS!$B$34*(C16/(D16*((AR16+AS16)/2)))/((D16*((AR16+AS16)/2))/(D16+2*((AR16+AS16)/2)))^(2/3))^2+((DATOS!$B$34*H15/((D15*F15)/(D15+2*F15))^(2/3))^2))/2))>0,AR16,((AR16+AS16)/2)) | AU16: =IF((((AR16+AS16)/2)+(C16/(D16*((AR16+AS16)/2)))^2/(2*9.81)+B16-(G15+H15^2/(2*9.81))-(A15-A16)*(((DATOS!$B$34*(C16/(D16*((AR16+AS16)/2)))/((D16*((AR16+AS16)/2))/(D16+2*((AR16+AS16)/2)))^(2/3))^2+((DATOS!$B$34*H15/((D15*F15)/(D15+2*F15))^(2/3))^2))/2))>0,((AR16+AS16)/2),AS16) | AV16: =IF((((AT16+AU16)/2)+(C16/(D16*((AT16+AU16)/2)))^2/(2*9.81)+B16-(G15+H15^2/(2*9.81))-(A15-A16)*(((DATOS!$B$34*(C16/(D16*((AT16+AU16)/2)))/((D16*((AT16+AU16)/2))/(D16+2*((AT16+AU16)/2)))^(2/3))^2+((DATOS!$B$34*H15/((D15*F15)/(D15+2*F15))^(2/3))^2))/2))>0,AT16,((AT16+AU16)/2)) | AW16: =IF((((AT16+AU16)/2)+(C16/(D16*((AT16+AU16)/2)))^2/(2*9.81)+B16-(G15+H15^2/(2*9.81))-(A15-A16)*(((DATOS!$B$34*(C16/(D16*((AT16+AU16)/2)))/((D16*((AT16+AU16)/2))/(D16+2*((AT16+AU16)/2)))^(2/3))^2+((DATOS!$B$34*H15/((D15*F15)/(D15+2*F15))^(2/3))^2))/2))>0,((AT16+AU16)/2),AU16) | AX16: =IF((((AV16+AW16)/2)+(C16/(D16*((AV16+AW16)/2)))^2/(2*9.81)+B16-(G15+H15^2/(2*9.81))-(A15-A16)*(((DATOS!$B$34*(C16/(D16*((AV16+AW16)/2)))/((D16*((AV16+AW16)/2))/(D16+2*((AV16+AW16)/2)))^(2/3))^2+((DATOS!$B$34*H15/((D15*F15)/(D15+2*F15))^(2/3))^2))/2))>0,AV16,((AV16+AW16)/2)) | AY16: =IF((((AV16+AW16)/2)+(C16/(D16*((AV16+AW16)/2)))^2/(2*9.81)+B16-(G15+H15^2/(2*9.81))-(A15-A16)*(((DATOS!$B$34*(C16/(D16*((AV16+AW16)/2)))/((D16*((AV16+AW16)/2))/(D16+2*((AV16+AW16)/2)))^(2/3))^2+((DATOS!$B$34*H15/((D15*F15)/(D15+2*F15))^(2/3))^2))/2))>0,((AV16+AW16)/2),AW16) | AZ16: =IF((((AX16+AY16)/2)+(C16/(D16*((AX16+AY16)/2)))^2/(2*9.81)+B16-(G15+H15^2/(2*9.81))-(A15-A16)*(((DATOS!$B$34*(C16/(D16*((AX16+AY16)/2)))/((D16*((AX16+AY16)/2))/(D16+2*((AX16+AY16)/2)))^(2/3))^2+((DATOS!$B$34*H15/((D15*F15)/(D15+2*F15))^(2/3))^2))/2))>0,AX16,((AX16+AY16)/2)) | BA16: =IF((((AX16+AY16)/2)+(C16/(D16*((AX16+AY16)/2)))^2/(2*9.81)+B16-(G15+H15^2/(2*9.81))-(A15-A16)*(((DATOS!$B$34*(C16/(D16*((AX16+AY16)/2)))/((D16*((AX16+AY16)/2))/(D16+2*((AX16+AY16)/2)))^(2/3))^2+((DATOS!$B$34*H15/((D15*F15)/(D15+2*F15))^(2/3))^2))/2))>0,((AX16+AY16)/2),AY16) | BB16: =IF((((AZ16+BA16)/2)+(C16/(D16*((AZ16+BA16)/2)))^2/(2*9.81)+B16-(G15+H15^2/(2*9.81))-(A15-A16)*(((DATOS!$B$34*(C16/(D16*((AZ16+BA16)/2)))/((D16*((AZ16+BA16)/2))/(D16+2*((AZ16+BA16)/2)))^(2/3))^2+((DATOS!$B$34*H15/((D15*F15)/(D15+2*F15))^(2/3))^2))/2))>0,AZ16,((AZ16+BA16)/2)) | BC16: =IF((((AZ16+BA16)/2)+(C16/(D16*((AZ16+BA16)/2)))^2/(2*9.81)+B16-(G15+H15^2/(2*9.81))-(A15-A16)*(((DATOS!$B$34*(C16/(D16*((AZ16+BA16)/2)))/((D16*((AZ16+BA16)/2))/(D16+2*((AZ16+BA16)/2)))^(2/3))^2+((DATOS!$B$34*H15/((D15*F15)/(D15+2*F15))^(2/3))^2))/2))>0,((AZ16+BA16)/2),BA16) | BD16: =IF((((BB16+BC16)/2)+(C16/(D16*((BB16+BC16)/2)))^2/(2*9.81)+B16-(G15+H15^2/(2*9.81))-(A15-A16)*(((DATOS!$B$34*(C16/(D16*((BB16+BC16)/2)))/((D16*((BB16+BC16)/2))/(D16+2*((BB16+BC16)/2)))^(2/3))^2+((DATOS!$B$34*H15/((D15*F15)/(D15+2*F15))^(2/3))^2))/2))>0,BB16,((BB16+BC16)/2)) | BE16: =IF((((BB16+BC16)/2)+(C16/(D16*((BB16+BC16)/2)))^2/(2*9.81)+B16-(G15+H15^2/(2*9.81))-(A15-A16)*(((DATOS!$B$34*(C16/(D16*((BB16+BC16)/2)))/((D16*((BB16+BC16)/2))/(D16+2*((BB16+BC16)/2)))^(2/3))^2+((DATOS!$B$34*H15/((D15*F15)/(D15+2*F15))^(2/3))^2))/2))>0,((BB16+BC16)/2),BC16) | BF16: =IF((((BD16+BE16)/2)+(C16/(D16*((BD16+BE16)/2)))^2/(2*9.81)+B16-(G15+H15^2/(2*9.81))-(A15-A16)*(((DATOS!$B$34*(C16/(D16*((BD16+BE16)/2)))/((D16*((BD16+BE16)/2))/(D16+2*((BD16+BE16)/2)))^(2/3))^2+((DATOS!$B$34*H15/((D15*F15)/(D15+2*F15))^(2/3))^2))/2))>0,BD16,((BD16+BE16)/2)) | BG16: =IF((((BD16+BE16)/2)+(C16/(D16*((BD16+BE16)/2)))^2/(2*9.81)+B16-(G15+H15^2/(2*9.81))-(A15-A16)*(((DATOS!$B$34*(C16/(D16*((BD16+BE16)/2)))/((D16*((BD16+BE16)/2))/(D16+2*((BD16+BE16)/2)))^(2/3))^2+((DATOS!$B$34*H15/((D15*F15)/(D15+2*F15))^(2/3))^2))/2))>0,((BD16+BE16)/2),BE16) | BH16: =IF((((BF16+BG16)/2)+(C16/(D16*((BF16+BG16)/2)))^2/(2*9.81)+B16-(G15+H15^2/(2*9.81))-(A15-A16)*(((DATOS!$B$34*(C16/(D16*((BF16+BG16)/2)))/((D16*((BF16+BG16)/2))/(D16+2*((BF16+BG16)/2)))^(2/3))^2+((DATOS!$B$34*H15/((D15*F15)/(D15+2*F15))^(2/3))^2))/2))>0,BF16,((BF16+BG16)/2)) | BI16: =IF((((BF16+BG16)/2)+(C16/(D16*((BF16+BG16)/2)))^2/(2*9.81)+B16-(G15+H15^2/(2*9.81))-(A15-A16)*(((DATOS!$B$34*(C16/(D16*((BF16+BG16)/2)))/((D16*((BF16+BG16)/2))/(D16+2*((BF16+BG16)/2)))^(2/3))^2+((DATOS!$B$34*H15/((D15*F15)/(D15+2*F15))^(2/3))^2))/2))>0,((BF16+BG16)/2),BG16) | BJ16: =IF((((BH16+BI16)/2)+(C16/(D16*((BH16+BI16)/2)))^2/(2*9.81)+B16-(G15+H15^2/(2*9.81))-(A15-A16)*(((DATOS!$B$34*(C16/(D16*((BH16+BI16)/2)))/((D16*((BH16+BI16)/2))/(D16+2*((BH16+BI16)/2)))^(2/3))^2+((DATOS!$B$34*H15/((D15*F15)/(D15+2*F15))^(2/3))^2))/2))>0,BH16,((BH16+BI16)/2)) | BK16: =IF((((BH16+BI16)/2)+(C16/(D16*((BH16+BI16)/2)))^2/(2*9.81)+B16-(G15+H15^2/(2*9.81))-(A15-A16)*(((DATOS!$B$34*(C16/(D16*((BH16+BI16)/2)))/((D16*((BH16+BI16)/2))/(D16+2*((BH16+BI16)/2)))^(2/3))^2+((DATOS!$B$34*H15/((D15*F15)/(D15+2*F15))^(2/3))^2))/2))>0,((BH16+BI16)/2),BI16) | BL16: =IF((((BJ16+BK16)/2)+(C16/(D16*((BJ16+BK16)/2)))^2/(2*9.81)+B16-(G15+H15^2/(2*9.81))-(A15-A16)*(((DATOS!$B$34*(C16/(D16*((BJ16+BK16)/2)))/((D16*((BJ16+BK16)/2))/(D16+2*((BJ16+BK16)/2)))^(2/3))^2+((DATOS!$B$34*H15/((D15*F15)/(D15+2*F15))^(2/3))^2))/2))>0,BJ16,((BJ16+BK16)/2)) | BM16: =IF((((BJ16+BK16)/2)+(C16/(D16*((BJ16+BK16)/2)))^2/(2*9.81)+B16-(G15+H15^2/(2*9.81))-(A15-A16)*(((DATOS!$B$34*(C16/(D16*((BJ16+BK16)/2)))/((D16*((BJ16+BK16)/2))/(D16+2*((BJ16+BK16)/2)))^(2/3))^2+((DATOS!$B$34*H15/((D15*F15)/(D15+2*F15))^(2/3))^2))/2))>0,((BJ16+BK16)/2),BK16) | BN16: =IF((((BL16+BM16)/2)+(C16/(D16*((BL16+BM16)/2)))^2/(2*9.81)+B16-(G15+H15^2/(2*9.81))-(A15-A16)*(((DATOS!$B$34*(C16/(D16*((BL16+BM16)/2)))/((D16*((BL16+BM16)/2))/(D16+2*((BL16+BM16)/2)))^(2/3))^2+((DATOS!$B$34*H15/((D15*F15)/(D15+2*F15))^(2/3))^2))/2))>0,BL16,((BL16+BM16)/2)) | BO16: =IF((((BL16+BM16)/2)+(C16/(D16*((BL16+BM16)/2)))^2/(2*9.81)+B16-(G15+H15^2/(2*9.81))-(A15-A16)*(((DATOS!$B$34*(C16/(D16*((BL16+BM16)/2)))/((D16*((BL16+BM16)/2))/(D16+2*((BL16+BM16)/2)))^(2/3))^2+((DATOS!$B$34*H15/((D15*F15)/(D15+2*F15))^(2/3))^2))/2))>0,((BL16+BM16)/2),BM16) | BP16: =IF((((BN16+BO16)/2)+(C16/(D16*((BN16+BO16)/2)))^2/(2*9.81)+B16-(G15+H15^2/(2*9.81))-(A15-A16)*(((DATOS!$B$34*(C16/(D16*((BN16+BO16)/2)))/((D16*((BN16+BO16)/2))/(D16+2*((BN16+BO16)/2)))^(2/3))^2+((DATOS!$B$34*H15/((D15*F15)/(D15+2*F15))^(2/3))^2))/2))>0,BN16,((BN16+BO16)/2)) | BQ16: =IF((((BN16+BO16)/2)+(C16/(D16*((BN16+BO16)/2)))^2/(2*9.81)+B16-(G15+H15^2/(2*9.81))-(A15-A16)*(((DATOS!$B$34*(C16/(D16*((BN16+BO16)/2)))/((D16*((BN16+BO16)/2))/(D16+2*((BN16+BO16)/2)))^(2/3))^2+((DATOS!$B$34*H15/((D15*F15)/(D15+2*F15))^(2/3))^2))/2))>0,((BN16+BO16)/2),BO16) | BR16: =IF((((BP16+BQ16)/2)+(C16/(D16*((BP16+BQ16)/2)))^2/(2*9.81)+B16-(G15+H15^2/(2*9.81))-(A15-A16)*(((DATOS!$B$34*(C16/(D16*((BP16+BQ16)/2)))/((D16*((BP16+BQ16)/2))/(D16+2*((BP16+BQ16)/2)))^(2/3))^2+((DATOS!$B$34*H15/((D15*F15)/(D15+2*F15))^(2/3))^2))/2))>0,BP16,((BP16+BQ16)/2)) | BS16: =IF((((BP16+BQ16)/2)+(C16/(D16*((BP16+BQ16)/2)))^2/(2*9.81)+B16-(G15+H15^2/(2*9.81))-(A15-A16)*(((DATOS!$B$34*(C16/(D16*((BP16+BQ16)/2)))/((D16*((BP16+BQ16)/2))/(D16+2*((BP16+BQ16)/2)))^(2/3))^2+((DATOS!$B$34*H15/((D15*F15)/(D15+2*F15))^(2/3))^2))/2))>0,((BP16+BQ16)/2),BQ16) | BT16: =IF((((BR16+BS16)/2)+(C16/(D16*((BR16+BS16)/2)))^2/(2*9.81)+B16-(G15+H15^2/(2*9.81))-(A15-A16)*(((DATOS!$B$34*(C16/(D16*((BR16+BS16)/2)))/((D16*((BR16+BS16)/2))/(D16+2*((BR16+BS16)/2)))^(2/3))^2+((DATOS!$B$34*H15/((D15*F15)/(D15+2*F15))^(2/3))^2))/2))>0,BR16,((BR16+BS16)/2)) | BU16: =IF((((BR16+BS16)/2)+(C16/(D16*((BR16+BS16)/2)))^2/(2*9.81)+B16-(G15+H15^2/(2*9.81))-(A15-A16)*(((DATOS!$B$34*(C16/(D16*((BR16+BS16)/2)))/((D16*((BR16+BS16)/2))/(D16+2*((BR16+BS16)/2)))^(2/3))^2+((DATOS!$B$34*H15/((D15*F15)/(D15+2*F15))^(2/3))^2))/2))>0,((BR16+BS16)/2),BS16) | BV16: =IF((((BT16+BU16)/2)+(C16/(D16*((BT16+BU16)/2)))^2/(2*9.81)+B16-(G15+H15^2/(2*9.81))-(A15-A16)*(((DATOS!$B$34*(C16/(D16*((BT16+BU16)/2)))/((D16*((BT16+BU16)/2))/(D16+2*((BT16+BU16)/2)))^(2/3))^2+((DATOS!$B$34*H15/((D15*F15)/(D15+2*F15))^(2/3))^2))/2))>0,BT16,((BT16+BU16)/2)) | BW16: =IF((((BT16+BU16)/2)+(C16/(D16*((BT16+BU16)/2)))^2/(2*9.81)+B16-(G15+H15^2/(2*9.81))-(A15-A16)*(((DATOS!$B$34*(C16/(D16*((BT16+BU16)/2)))/((D16*((BT16+BU16)/2))/(D16+2*((BT16+BU16)/2)))^(2/3))^2+((DATOS!$B$34*H15/((D15*F15)/(D15+2*F15))^(2/3))^2))/2))>0,((BT16+BU16)/2),BU16)
A17: 62 | B17: =DATOS!$B$22-DATOS!$B$23*A17 | C17: =CAUDALES!$B$13 | D17: =DATOS!$B$17 | E17: =(C17^2/(9.81*D17^2))^(1/3) | F17: =(BV17+BW17)/2 | G17: =B17+F17 | H17: =C17/(D17*F17) | I17: =H17/SQRT(9.81*F17) | J17: =DATOS!$B$29-IF(AND(A17>=DATOS!$B$30,A17<DATOS!$B$31),DATOS!$B$21,DATOS!$B$20) | K17: =J17-B17 | L17: =F17/K17 | M17: =J17-G17 | N17: =IF(AND(L17<=DATOS!$B$36,M17>=DATOS!$B$37,I17<=1),"CUMPLE","NO CUMPLE") | O17: =IF(AND(A17>=DATOS!$B$30,A17<DATOS!$B$31),"cruce de camiones",IF(AND(A17>=DATOS!$B$32,A17<DATOS!$B$33),"cruce de motos","tramo normal")) | P17: =E17*1.001 | Q17: 3 | R17: =IF((((P17+Q17)/2)+(C17/(D17*((P17+Q17)/2)))^2/(2*9.81)+B17-(G16+H16^2/(2*9.81))-(A16-A17)*(((DATOS!$B$34*(C17/(D17*((P17+Q17)/2)))/((D17*((P17+Q17)/2))/(D17+2*((P17+Q17)/2)))^(2/3))^2+((DATOS!$B$34*H16/((D16*F16)/(D16+2*F16))^(2/3))^2))/2))>0,P17,((P17+Q17)/2)) | S17: =IF((((P17+Q17)/2)+(C17/(D17*((P17+Q17)/2)))^2/(2*9.81)+B17-(G16+H16^2/(2*9.81))-(A16-A17)*(((DATOS!$B$34*(C17/(D17*((P17+Q17)/2)))/((D17*((P17+Q17)/2))/(D17+2*((P17+Q17)/2)))^(2/3))^2+((DATOS!$B$34*H16/((D16*F16)/(D16+2*F16))^(2/3))^2))/2))>0,((P17+Q17)/2),Q17) | T17: =IF((((R17+S17)/2)+(C17/(D17*((R17+S17)/2)))^2/(2*9.81)+B17-(G16+H16^2/(2*9.81))-(A16-A17)*(((DATOS!$B$34*(C17/(D17*((R17+S17)/2)))/((D17*((R17+S17)/2))/(D17+2*((R17+S17)/2)))^(2/3))^2+((DATOS!$B$34*H16/((D16*F16)/(D16+2*F16))^(2/3))^2))/2))>0,R17,((R17+S17)/2)) | U17: =IF((((R17+S17)/2)+(C17/(D17*((R17+S17)/2)))^2/(2*9.81)+B17-(G16+H16^2/(2*9.81))-(A16-A17)*(((DATOS!$B$34*(C17/(D17*((R17+S17)/2)))/((D17*((R17+S17)/2))/(D17+2*((R17+S17)/2)))^(2/3))^2+((DATOS!$B$34*H16/((D16*F16)/(D16+2*F16))^(2/3))^2))/2))>0,((R17+S17)/2),S17) | V17: =IF((((T17+U17)/2)+(C17/(D17*((T17+U17)/2)))^2/(2*9.81)+B17-(G16+H16^2/(2*9.81))-(A16-A17)*(((DATOS!$B$34*(C17/(D17*((T17+U17)/2)))/((D17*((T17+U17)/2))/(D17+2*((T17+U17)/2)))^(2/3))^2+((DATOS!$B$34*H16/((D16*F16)/(D16+2*F16))^(2/3))^2))/2))>0,T17,((T17+U17)/2)) | W17: =IF((((T17+U17)/2)+(C17/(D17*((T17+U17)/2)))^2/(2*9.81)+B17-(G16+H16^2/(2*9.81))-(A16-A17)*(((DATOS!$B$34*(C17/(D17*((T17+U17)/2)))/((D17*((T17+U17)/2))/(D17+2*((T17+U17)/2)))^(2/3))^2+((DATOS!$B$34*H16/((D16*F16)/(D16+2*F16))^(2/3))^2))/2))>0,((T17+U17)/2),U17) | X17: =IF((((V17+W17)/2)+(C17/(D17*((V17+W17)/2)))^2/(2*9.81)+B17-(G16+H16^2/(2*9.81))-(A16-A17)*(((DATOS!$B$34*(C17/(D17*((V17+W17)/2)))/((D17*((V17+W17)/2))/(D17+2*((V17+W17)/2)))^(2/3))^2+((DATOS!$B$34*H16/((D16*F16)/(D16+2*F16))^(2/3))^2))/2))>0,V17,((V17+W17)/2)) | Y17: =IF((((V17+W17)/2)+(C17/(D17*((V17+W17)/2)))^2/(2*9.81)+B17-(G16+H16^2/(2*9.81))-(A16-A17)*(((DATOS!$B$34*(C17/(D17*((V17+W17)/2)))/((D17*((V17+W17)/2))/(D17+2*((V17+W17)/2)))^(2/3))^2+((DATOS!$B$34*H16/((D16*F16)/(D16+2*F16))^(2/3))^2))/2))>0,((V17+W17)/2),W17) | Z17: =IF((((X17+Y17)/2)+(C17/(D17*((X17+Y17)/2)))^2/(2*9.81)+B17-(G16+H16^2/(2*9.81))-(A16-A17)*(((DATOS!$B$34*(C17/(D17*((X17+Y17)/2)))/((D17*((X17+Y17)/2))/(D17+2*((X17+Y17)/2)))^(2/3))^2+((DATOS!$B$34*H16/((D16*F16)/(D16+2*F16))^(2/3))^2))/2))>0,X17,((X17+Y17)/2)) | AA17: =IF((((X17+Y17)/2)+(C17/(D17*((X17+Y17)/2)))^2/(2*9.81)+B17-(G16+H16^2/(2*9.81))-(A16-A17)*(((DATOS!$B$34*(C17/(D17*((X17+Y17)/2)))/((D17*((X17+Y17)/2))/(D17+2*((X17+Y17)/2)))^(2/3))^2+((DATOS!$B$34*H16/((D16*F16)/(D16+2*F16))^(2/3))^2))/2))>0,((X17+Y17)/2),Y17) | AB17: =IF((((Z17+AA17)/2)+(C17/(D17*((Z17+AA17)/2)))^2/(2*9.81)+B17-(G16+H16^2/(2*9.81))-(A16-A17)*(((DATOS!$B$34*(C17/(D17*((Z17+AA17)/2)))/((D17*((Z17+AA17)/2))/(D17+2*((Z17+AA17)/2)))^(2/3))^2+((DATOS!$B$34*H16/((D16*F16)/(D16+2*F16))^(2/3))^2))/2))>0,Z17,((Z17+AA17)/2)) | AC17: =IF((((Z17+AA17)/2)+(C17/(D17*((Z17+AA17)/2)))^2/(2*9.81)+B17-(G16+H16^2/(2*9.81))-(A16-A17)*(((DATOS!$B$34*(C17/(D17*((Z17+AA17)/2)))/((D17*((Z17+AA17)/2))/(D17+2*((Z17+AA17)/2)))^(2/3))^2+((DATOS!$B$34*H16/((D16*F16)/(D16+2*F16))^(2/3))^2))/2))>0,((Z17+AA17)/2),AA17) | AD17: =IF((((AB17+AC17)/2)+(C17/(D17*((AB17+AC17)/2)))^2/(2*9.81)+B17-(G16+H16^2/(2*9.81))-(A16-A17)*(((DATOS!$B$34*(C17/(D17*((AB17+AC17)/2)))/((D17*((AB17+AC17)/2))/(D17+2*((AB17+AC17)/2)))^(2/3))^2+((DATOS!$B$34*H16/((D16*F16)/(D16+2*F16))^(2/3))^2))/2))>0,AB17,((AB17+AC17)/2)) | AE17: =IF((((AB17+AC17)/2)+(C17/(D17*((AB17+AC17)/2)))^2/(2*9.81)+B17-(G16+H16^2/(2*9.81))-(A16-A17)*(((DATOS!$B$34*(C17/(D17*((AB17+AC17)/2)))/((D17*((AB17+AC17)/2))/(D17+2*((AB17+AC17)/2)))^(2/3))^2+((DATOS!$B$34*H16/((D16*F16)/(D16+2*F16))^(2/3))^2))/2))>0,((AB17+AC17)/2),AC17) | AF17: =IF((((AD17+AE17)/2)+(C17/(D17*((AD17+AE17)/2)))^2/(2*9.81)+B17-(G16+H16^2/(2*9.81))-(A16-A17)*(((DATOS!$B$34*(C17/(D17*((AD17+AE17)/2)))/((D17*((AD17+AE17)/2))/(D17+2*((AD17+AE17)/2)))^(2/3))^2+((DATOS!$B$34*H16/((D16*F16)/(D16+2*F16))^(2/3))^2))/2))>0,AD17,((AD17+AE17)/2)) | AG17: =IF((((AD17+AE17)/2)+(C17/(D17*((AD17+AE17)/2)))^2/(2*9.81)+B17-(G16+H16^2/(2*9.81))-(A16-A17)*(((DATOS!$B$34*(C17/(D17*((AD17+AE17)/2)))/((D17*((AD17+AE17)/2))/(D17+2*((AD17+AE17)/2)))^(2/3))^2+((DATOS!$B$34*H16/((D16*F16)/(D16+2*F16))^(2/3))^2))/2))>0,((AD17+AE17)/2),AE17) | AH17: =IF((((AF17+AG17)/2)+(C17/(D17*((AF17+AG17)/2)))^2/(2*9.81)+B17-(G16+H16^2/(2*9.81))-(A16-A17)*(((DATOS!$B$34*(C17/(D17*((AF17+AG17)/2)))/((D17*((AF17+AG17)/2))/(D17+2*((AF17+AG17)/2)))^(2/3))^2+((DATOS!$B$34*H16/((D16*F16)/(D16+2*F16))^(2/3))^2))/2))>0,AF17,((AF17+AG17)/2)) | AI17: =IF((((AF17+AG17)/2)+(C17/(D17*((AF17+AG17)/2)))^2/(2*9.81)+B17-(G16+H16^2/(2*9.81))-(A16-A17)*(((DATOS!$B$34*(C17/(D17*((AF17+AG17)/2)))/((D17*((AF17+AG17)/2))/(D17+2*((AF17+AG17)/2)))^(2/3))^2+((DATOS!$B$34*H16/((D16*F16)/(D16+2*F16))^(2/3))^2))/2))>0,((AF17+AG17)/2),AG17) | AJ17: =IF((((AH17+AI17)/2)+(C17/(D17*((AH17+AI17)/2)))^2/(2*9.81)+B17-(G16+H16^2/(2*9.81))-(A16-A17)*(((DATOS!$B$34*(C17/(D17*((AH17+AI17)/2)))/((D17*((AH17+AI17)/2))/(D17+2*((AH17+AI17)/2)))^(2/3))^2+((DATOS!$B$34*H16/((D16*F16)/(D16+2*F16))^(2/3))^2))/2))>0,AH17,((AH17+AI17)/2)) | AK17: =IF((((AH17+AI17)/2)+(C17/(D17*((AH17+AI17)/2)))^2/(2*9.81)+B17-(G16+H16^2/(2*9.81))-(A16-A17)*(((DATOS!$B$34*(C17/(D17*((AH17+AI17)/2)))/((D17*((AH17+AI17)/2))/(D17+2*((AH17+AI17)/2)))^(2/3))^2+((DATOS!$B$34*H16/((D16*F16)/(D16+2*F16))^(2/3))^2))/2))>0,((AH17+AI17)/2),AI17) | AL17: =IF((((AJ17+AK17)/2)+(C17/(D17*((AJ17+AK17)/2)))^2/(2*9.81)+B17-(G16+H16^2/(2*9.81))-(A16-A17)*(((DATOS!$B$34*(C17/(D17*((AJ17+AK17)/2)))/((D17*((AJ17+AK17)/2))/(D17+2*((AJ17+AK17)/2)))^(2/3))^2+((DATOS!$B$34*H16/((D16*F16)/(D16+2*F16))^(2/3))^2))/2))>0,AJ17,((AJ17+AK17)/2)) | AM17: =IF((((AJ17+AK17)/2)+(C17/(D17*((AJ17+AK17)/2)))^2/(2*9.81)+B17-(G16+H16^2/(2*9.81))-(A16-A17)*(((DATOS!$B$34*(C17/(D17*((AJ17+AK17)/2)))/((D17*((AJ17+AK17)/2))/(D17+2*((AJ17+AK17)/2)))^(2/3))^2+((DATOS!$B$34*H16/((D16*F16)/(D16+2*F16))^(2/3))^2))/2))>0,((AJ17+AK17)/2),AK17) | AN17: =IF((((AL17+AM17)/2)+(C17/(D17*((AL17+AM17)/2)))^2/(2*9.81)+B17-(G16+H16^2/(2*9.81))-(A16-A17)*(((DATOS!$B$34*(C17/(D17*((AL17+AM17)/2)))/((D17*((AL17+AM17)/2))/(D17+2*((AL17+AM17)/2)))^(2/3))^2+((DATOS!$B$34*H16/((D16*F16)/(D16+2*F16))^(2/3))^2))/2))>0,AL17,((AL17+AM17)/2)) | AO17: =IF((((AL17+AM17)/2)+(C17/(D17*((AL17+AM17)/2)))^2/(2*9.81)+B17-(G16+H16^2/(2*9.81))-(A16-A17)*(((DATOS!$B$34*(C17/(D17*((AL17+AM17)/2)))/((D17*((AL17+AM17)/2))/(D17+2*((AL17+AM17)/2)))^(2/3))^2+((DATOS!$B$34*H16/((D16*F16)/(D16+2*F16))^(2/3))^2))/2))>0,((AL17+AM17)/2),AM17) | AP17: =IF((((AN17+AO17)/2)+(C17/(D17*((AN17+AO17)/2)))^2/(2*9.81)+B17-(G16+H16^2/(2*9.81))-(A16-A17)*(((DATOS!$B$34*(C17/(D17*((AN17+AO17)/2)))/((D17*((AN17+AO17)/2))/(D17+2*((AN17+AO17)/2)))^(2/3))^2+((DATOS!$B$34*H16/((D16*F16)/(D16+2*F16))^(2/3))^2))/2))>0,AN17,((AN17+AO17)/2)) | AQ17: =IF((((AN17+AO17)/2)+(C17/(D17*((AN17+AO17)/2)))^2/(2*9.81)+B17-(G16+H16^2/(2*9.81))-(A16-A17)*(((DATOS!$B$34*(C17/(D17*((AN17+AO17)/2)))/((D17*((AN17+AO17)/2))/(D17+2*((AN17+AO17)/2)))^(2/3))^2+((DATOS!$B$34*H16/((D16*F16)/(D16+2*F16))^(2/3))^2))/2))>0,((AN17+AO17)/2),AO17) | AR17: =IF((((AP17+AQ17)/2)+(C17/(D17*((AP17+AQ17)/2)))^2/(2*9.81)+B17-(G16+H16^2/(2*9.81))-(A16-A17)*(((DATOS!$B$34*(C17/(D17*((AP17+AQ17)/2)))/((D17*((AP17+AQ17)/2))/(D17+2*((AP17+AQ17)/2)))^(2/3))^2+((DATOS!$B$34*H16/((D16*F16)/(D16+2*F16))^(2/3))^2))/2))>0,AP17,((AP17+AQ17)/2)) | AS17: =IF((((AP17+AQ17)/2)+(C17/(D17*((AP17+AQ17)/2)))^2/(2*9.81)+B17-(G16+H16^2/(2*9.81))-(A16-A17)*(((DATOS!$B$34*(C17/(D17*((AP17+AQ17)/2)))/((D17*((AP17+AQ17)/2))/(D17+2*((AP17+AQ17)/2)))^(2/3))^2+((DATOS!$B$34*H16/((D16*F16)/(D16+2*F16))^(2/3))^2))/2))>0,((AP17+AQ17)/2),AQ17) | AT17: =IF((((AR17+AS17)/2)+(C17/(D17*((AR17+AS17)/2)))^2/(2*9.81)+B17-(G16+H16^2/(2*9.81))-(A16-A17)*(((DATOS!$B$34*(C17/(D17*((AR17+AS17)/2)))/((D17*((AR17+AS17)/2))/(D17+2*((AR17+AS17)/2)))^(2/3))^2+((DATOS!$B$34*H16/((D16*F16)/(D16+2*F16))^(2/3))^2))/2))>0,AR17,((AR17+AS17)/2)) | AU17: =IF((((AR17+AS17)/2)+(C17/(D17*((AR17+AS17)/2)))^2/(2*9.81)+B17-(G16+H16^2/(2*9.81))-(A16-A17)*(((DATOS!$B$34*(C17/(D17*((AR17+AS17)/2)))/((D17*((AR17+AS17)/2))/(D17+2*((AR17+AS17)/2)))^(2/3))^2+((DATOS!$B$34*H16/((D16*F16)/(D16+2*F16))^(2/3))^2))/2))>0,((AR17+AS17)/2),AS17) | AV17: =IF((((AT17+AU17)/2)+(C17/(D17*((AT17+AU17)/2)))^2/(2*9.81)+B17-(G16+H16^2/(2*9.81))-(A16-A17)*(((DATOS!$B$34*(C17/(D17*((AT17+AU17)/2)))/((D17*((AT17+AU17)/2))/(D17+2*((AT17+AU17)/2)))^(2/3))^2+((DATOS!$B$34*H16/((D16*F16)/(D16+2*F16))^(2/3))^2))/2))>0,AT17,((AT17+AU17)/2)) | AW17: =IF((((AT17+AU17)/2)+(C17/(D17*((AT17+AU17)/2)))^2/(2*9.81)+B17-(G16+H16^2/(2*9.81))-(A16-A17)*(((DATOS!$B$34*(C17/(D17*((AT17+AU17)/2)))/((D17*((AT17+AU17)/2))/(D17+2*((AT17+AU17)/2)))^(2/3))^2+((DATOS!$B$34*H16/((D16*F16)/(D16+2*F16))^(2/3))^2))/2))>0,((AT17+AU17)/2),AU17) | AX17: =IF((((AV17+AW17)/2)+(C17/(D17*((AV17+AW17)/2)))^2/(2*9.81)+B17-(G16+H16^2/(2*9.81))-(A16-A17)*(((DATOS!$B$34*(C17/(D17*((AV17+AW17)/2)))/((D17*((AV17+AW17)/2))/(D17+2*((AV17+AW17)/2)))^(2/3))^2+((DATOS!$B$34*H16/((D16*F16)/(D16+2*F16))^(2/3))^2))/2))>0,AV17,((AV17+AW17)/2)) | AY17: =IF((((AV17+AW17)/2)+(C17/(D17*((AV17+AW17)/2)))^2/(2*9.81)+B17-(G16+H16^2/(2*9.81))-(A16-A17)*(((DATOS!$B$34*(C17/(D17*((AV17+AW17)/2)))/((D17*((AV17+AW17)/2))/(D17+2*((AV17+AW17)/2)))^(2/3))^2+((DATOS!$B$34*H16/((D16*F16)/(D16+2*F16))^(2/3))^2))/2))>0,((AV17+AW17)/2),AW17) | AZ17: =IF((((AX17+AY17)/2)+(C17/(D17*((AX17+AY17)/2)))^2/(2*9.81)+B17-(G16+H16^2/(2*9.81))-(A16-A17)*(((DATOS!$B$34*(C17/(D17*((AX17+AY17)/2)))/((D17*((AX17+AY17)/2))/(D17+2*((AX17+AY17)/2)))^(2/3))^2+((DATOS!$B$34*H16/((D16*F16)/(D16+2*F16))^(2/3))^2))/2))>0,AX17,((AX17+AY17)/2)) | BA17: =IF((((AX17+AY17)/2)+(C17/(D17*((AX17+AY17)/2)))^2/(2*9.81)+B17-(G16+H16^2/(2*9.81))-(A16-A17)*(((DATOS!$B$34*(C17/(D17*((AX17+AY17)/2)))/((D17*((AX17+AY17)/2))/(D17+2*((AX17+AY17)/2)))^(2/3))^2+((DATOS!$B$34*H16/((D16*F16)/(D16+2*F16))^(2/3))^2))/2))>0,((AX17+AY17)/2),AY17) | BB17: =IF((((AZ17+BA17)/2)+(C17/(D17*((AZ17+BA17)/2)))^2/(2*9.81)+B17-(G16+H16^2/(2*9.81))-(A16-A17)*(((DATOS!$B$34*(C17/(D17*((AZ17+BA17)/2)))/((D17*((AZ17+BA17)/2))/(D17+2*((AZ17+BA17)/2)))^(2/3))^2+((DATOS!$B$34*H16/((D16*F16)/(D16+2*F16))^(2/3))^2))/2))>0,AZ17,((AZ17+BA17)/2)) | BC17: =IF((((AZ17+BA17)/2)+(C17/(D17*((AZ17+BA17)/2)))^2/(2*9.81)+B17-(G16+H16^2/(2*9.81))-(A16-A17)*(((DATOS!$B$34*(C17/(D17*((AZ17+BA17)/2)))/((D17*((AZ17+BA17)/2))/(D17+2*((AZ17+BA17)/2)))^(2/3))^2+((DATOS!$B$34*H16/((D16*F16)/(D16+2*F16))^(2/3))^2))/2))>0,((AZ17+BA17)/2),BA17) | BD17: =IF((((BB17+BC17)/2)+(C17/(D17*((BB17+BC17)/2)))^2/(2*9.81)+B17-(G16+H16^2/(2*9.81))-(A16-A17)*(((DATOS!$B$34*(C17/(D17*((BB17+BC17)/2)))/((D17*((BB17+BC17)/2))/(D17+2*((BB17+BC17)/2)))^(2/3))^2+((DATOS!$B$34*H16/((D16*F16)/(D16+2*F16))^(2/3))^2))/2))>0,BB17,((BB17+BC17)/2)) | BE17: =IF((((BB17+BC17)/2)+(C17/(D17*((BB17+BC17)/2)))^2/(2*9.81)+B17-(G16+H16^2/(2*9.81))-(A16-A17)*(((DATOS!$B$34*(C17/(D17*((BB17+BC17)/2)))/((D17*((BB17+BC17)/2))/(D17+2*((BB17+BC17)/2)))^(2/3))^2+((DATOS!$B$34*H16/((D16*F16)/(D16+2*F16))^(2/3))^2))/2))>0,((BB17+BC17)/2),BC17) | BF17: =IF((((BD17+BE17)/2)+(C17/(D17*((BD17+BE17)/2)))^2/(2*9.81)+B17-(G16+H16^2/(2*9.81))-(A16-A17)*(((DATOS!$B$34*(C17/(D17*((BD17+BE17)/2)))/((D17*((BD17+BE17)/2))/(D17+2*((BD17+BE17)/2)))^(2/3))^2+((DATOS!$B$34*H16/((D16*F16)/(D16+2*F16))^(2/3))^2))/2))>0,BD17,((BD17+BE17)/2)) | BG17: =IF((((BD17+BE17)/2)+(C17/(D17*((BD17+BE17)/2)))^2/(2*9.81)+B17-(G16+H16^2/(2*9.81))-(A16-A17)*(((DATOS!$B$34*(C17/(D17*((BD17+BE17)/2)))/((D17*((BD17+BE17)/2))/(D17+2*((BD17+BE17)/2)))^(2/3))^2+((DATOS!$B$34*H16/((D16*F16)/(D16+2*F16))^(2/3))^2))/2))>0,((BD17+BE17)/2),BE17) | BH17: =IF((((BF17+BG17)/2)+(C17/(D17*((BF17+BG17)/2)))^2/(2*9.81)+B17-(G16+H16^2/(2*9.81))-(A16-A17)*(((DATOS!$B$34*(C17/(D17*((BF17+BG17)/2)))/((D17*((BF17+BG17)/2))/(D17+2*((BF17+BG17)/2)))^(2/3))^2+((DATOS!$B$34*H16/((D16*F16)/(D16+2*F16))^(2/3))^2))/2))>0,BF17,((BF17+BG17)/2)) | BI17: =IF((((BF17+BG17)/2)+(C17/(D17*((BF17+BG17)/2)))^2/(2*9.81)+B17-(G16+H16^2/(2*9.81))-(A16-A17)*(((DATOS!$B$34*(C17/(D17*((BF17+BG17)/2)))/((D17*((BF17+BG17)/2))/(D17+2*((BF17+BG17)/2)))^(2/3))^2+((DATOS!$B$34*H16/((D16*F16)/(D16+2*F16))^(2/3))^2))/2))>0,((BF17+BG17)/2),BG17) | BJ17: =IF((((BH17+BI17)/2)+(C17/(D17*((BH17+BI17)/2)))^2/(2*9.81)+B17-(G16+H16^2/(2*9.81))-(A16-A17)*(((DATOS!$B$34*(C17/(D17*((BH17+BI17)/2)))/((D17*((BH17+BI17)/2))/(D17+2*((BH17+BI17)/2)))^(2/3))^2+((DATOS!$B$34*H16/((D16*F16)/(D16+2*F16))^(2/3))^2))/2))>0,BH17,((BH17+BI17)/2)) | BK17: =IF((((BH17+BI17)/2)+(C17/(D17*((BH17+BI17)/2)))^2/(2*9.81)+B17-(G16+H16^2/(2*9.81))-(A16-A17)*(((DATOS!$B$34*(C17/(D17*((BH17+BI17)/2)))/((D17*((BH17+BI17)/2))/(D17+2*((BH17+BI17)/2)))^(2/3))^2+((DATOS!$B$34*H16/((D16*F16)/(D16+2*F16))^(2/3))^2))/2))>0,((BH17+BI17)/2),BI17) | BL17: =IF((((BJ17+BK17)/2)+(C17/(D17*((BJ17+BK17)/2)))^2/(2*9.81)+B17-(G16+H16^2/(2*9.81))-(A16-A17)*(((DATOS!$B$34*(C17/(D17*((BJ17+BK17)/2)))/((D17*((BJ17+BK17)/2))/(D17+2*((BJ17+BK17)/2)))^(2/3))^2+((DATOS!$B$34*H16/((D16*F16)/(D16+2*F16))^(2/3))^2))/2))>0,BJ17,((BJ17+BK17)/2)) | BM17: =IF((((BJ17+BK17)/2)+(C17/(D17*((BJ17+BK17)/2)))^2/(2*9.81)+B17-(G16+H16^2/(2*9.81))-(A16-A17)*(((DATOS!$B$34*(C17/(D17*((BJ17+BK17)/2)))/((D17*((BJ17+BK17)/2))/(D17+2*((BJ17+BK17)/2)))^(2/3))^2+((DATOS!$B$34*H16/((D16*F16)/(D16+2*F16))^(2/3))^2))/2))>0,((BJ17+BK17)/2),BK17) | BN17: =IF((((BL17+BM17)/2)+(C17/(D17*((BL17+BM17)/2)))^2/(2*9.81)+B17-(G16+H16^2/(2*9.81))-(A16-A17)*(((DATOS!$B$34*(C17/(D17*((BL17+BM17)/2)))/((D17*((BL17+BM17)/2))/(D17+2*((BL17+BM17)/2)))^(2/3))^2+((DATOS!$B$34*H16/((D16*F16)/(D16+2*F16))^(2/3))^2))/2))>0,BL17,((BL17+BM17)/2)) | BO17: =IF((((BL17+BM17)/2)+(C17/(D17*((BL17+BM17)/2)))^2/(2*9.81)+B17-(G16+H16^2/(2*9.81))-(A16-A17)*(((DATOS!$B$34*(C17/(D17*((BL17+BM17)/2)))/((D17*((BL17+BM17)/2))/(D17+2*((BL17+BM17)/2)))^(2/3))^2+((DATOS!$B$34*H16/((D16*F16)/(D16+2*F16))^(2/3))^2))/2))>0,((BL17+BM17)/2),BM17) | BP17: =IF((((BN17+BO17)/2)+(C17/(D17*((BN17+BO17)/2)))^2/(2*9.81)+B17-(G16+H16^2/(2*9.81))-(A16-A17)*(((DATOS!$B$34*(C17/(D17*((BN17+BO17)/2)))/((D17*((BN17+BO17)/2))/(D17+2*((BN17+BO17)/2)))^(2/3))^2+((DATOS!$B$34*H16/((D16*F16)/(D16+2*F16))^(2/3))^2))/2))>0,BN17,((BN17+BO17)/2)) | BQ17: =IF((((BN17+BO17)/2)+(C17/(D17*((BN17+BO17)/2)))^2/(2*9.81)+B17-(G16+H16^2/(2*9.81))-(A16-A17)*(((DATOS!$B$34*(C17/(D17*((BN17+BO17)/2)))/((D17*((BN17+BO17)/2))/(D17+2*((BN17+BO17)/2)))^(2/3))^2+((DATOS!$B$34*H16/((D16*F16)/(D16+2*F16))^(2/3))^2))/2))>0,((BN17+BO17)/2),BO17) | BR17: =IF((((BP17+BQ17)/2)+(C17/(D17*((BP17+BQ17)/2)))^2/(2*9.81)+B17-(G16+H16^2/(2*9.81))-(A16-A17)*(((DATOS!$B$34*(C17/(D17*((BP17+BQ17)/2)))/((D17*((BP17+BQ17)/2))/(D17+2*((BP17+BQ17)/2)))^(2/3))^2+((DATOS!$B$34*H16/((D16*F16)/(D16+2*F16))^(2/3))^2))/2))>0,BP17,((BP17+BQ17)/2)) | BS17: =IF((((BP17+BQ17)/2)+(C17/(D17*((BP17+BQ17)/2)))^2/(2*9.81)+B17-(G16+H16^2/(2*9.81))-(A16-A17)*(((DATOS!$B$34*(C17/(D17*((BP17+BQ17)/2)))/((D17*((BP17+BQ17)/2))/(D17+2*((BP17+BQ17)/2)))^(2/3))^2+((DATOS!$B$34*H16/((D16*F16)/(D16+2*F16))^(2/3))^2))/2))>0,((BP17+BQ17)/2),BQ17) | BT17: =IF((((BR17+BS17)/2)+(C17/(D17*((BR17+BS17)/2)))^2/(2*9.81)+B17-(G16+H16^2/(2*9.81))-(A16-A17)*(((DATOS!$B$34*(C17/(D17*((BR17+BS17)/2)))/((D17*((BR17+BS17)/2))/(D17+2*((BR17+BS17)/2)))^(2/3))^2+((DATOS!$B$34*H16/((D16*F16)/(D16+2*F16))^(2/3))^2))/2))>0,BR17,((BR17+BS17)/2)) | BU17: =IF((((BR17+BS17)/2)+(C17/(D17*((BR17+BS17)/2)))^2/(2*9.81)+B17-(G16+H16^2/(2*9.81))-(A16-A17)*(((DATOS!$B$34*(C17/(D17*((BR17+BS17)/2)))/((D17*((BR17+BS17)/2))/(D17+2*((BR17+BS17)/2)))^(2/3))^2+((DATOS!$B$34*H16/((D16*F16)/(D16+2*F16))^(2/3))^2))/2))>0,((BR17+BS17)/2),BS17) | BV17: =IF((((BT17+BU17)/2)+(C17/(D17*((BT17+BU17)/2)))^2/(2*9.81)+B17-(G16+H16^2/(2*9.81))-(A16-A17)*(((DATOS!$B$34*(C17/(D17*((BT17+BU17)/2)))/((D17*((BT17+BU17)/2))/(D17+2*((BT17+BU17)/2)))^(2/3))^2+((DATOS!$B$34*H16/((D16*F16)/(D16+2*F16))^(2/3))^2))/2))>0,BT17,((BT17+BU17)/2)) | BW17: =IF((((BT17+BU17)/2)+(C17/(D17*((BT17+BU17)/2)))^2/(2*9.81)+B17-(G16+H16^2/(2*9.81))-(A16-A17)*(((DATOS!$B$34*(C17/(D17*((BT17+BU17)/2)))/((D17*((BT17+BU17)/2))/(D17+2*((BT17+BU17)/2)))^(2/3))^2+((DATOS!$B$34*H16/((D16*F16)/(D16+2*F16))^(2/3))^2))/2))>0,((BT17+BU17)/2),BU17)
