Workbook

Sheet RESUMEN
A2: RESUMEN METRADOS DE DRENAJE PLUVIAL
A4: ENTIDAD | B4: GERENCIA TERRITORIAL BAJO MAYO - TARAPOTO
A5: PROYECTO | B5: “CREACIÓN DEL SERVICIO DE PROTECCIÓN A MUJERES VÍCTIMAS DE VIOLENCIA EN SITUACIÓN DE RIESGO DE FEMINICIDIO O PELIGRE SU INTEGRIDAD Y/O SALUD FÍSICA Y/O MENTAL EN HOGAR DE REFUGIO TEMPORAL DISTRITO DE MORALES DE LA PROVINCIA DE SAN MARTÍN DEL DEPARTAMENTO DE SAN MARTÍN”, con CUI N.° 2675514
A6: UBICACIÓN | B6: SAN MARTIN - SAN MARTIN - MORALES
A7: FECHA | B7: 46266
A8: Item | B8: Descripción | C8: Unid. | D8: Total.
A9: 01.04.03 | B9: SISTEMA DE DRENAJE PLUVIAL
A10: 01.04.03.01 | B10: TRABAJOS PRELIMINARES
A11: 01.04.03.01.01 | B11: LIMPIEZA MANUAL DE TERRENO | C11: m² | D11: =+'PLANILLA GENERAL DE METRADOS'!K11 -> 956.872
A12: 01.04.03.01.02 | B12: TRAZO, NIVELES Y REPLANTEO PRELIMINAR | C12: m² | D12: =+'PLANILLA GENERAL DE METRADOS'!K24 -> 956.872
A13: 01.04.03.02 | B13: MOVIMIENTO DE TIERRAS
A14: 01.04.03.02.01 | B14: EXCAVACIÓN MANUAL DE ZANJAS P/CUNETAS | C14: m³ | D14: =+'PLANILLA GENERAL DE METRADOS'!K38 -> 619.79764
A15: 01.04.03.02.02 | B15: EXCAVACIÓN MANUAL DE ZANJAS P/DADOS DE CONCRETO | C15: m³ | D15: =+'PLANILLA GENERAL DE METRADOS'!K51 -> 2.912
A16: 01.04.03.02.03 | B16: REFINE, NIVELACIÓN Y COMPACTACIÓN EN TERRENO NORMAL | C16: m² | D16: =+'PLANILLA GENERAL DE METRADOS'!K54 -> 410.088
A17: 01.04.03.02.04 | B17: RELLENO COMPACTADO C/MATERIAL PROPIO SELECCIONADO | C17: m³ | D17: =+'PLANILLA GENERAL DE METRADOS'!K67 -> 343.77408
A18: 01.04.03.02.05 | B18: ELIMINACIÓN DE MATERIAL EXCEDENTE D<1Km | C18: m³ | D18: =+'PLANILLA GENERAL DE METRADOS'!K80 -> 331.22827
A19: 01.04.03.03 | B19: OBRAS DE CONCRETO SIMPLE
A20: 01.04.03.03.01 | B20: CONCRETO f'c=100 kg/cm2 PARA SOLADO E=4'' | C20: m² | D20: =+'PLANILLA GENERAL DE METRADOS'!K84 -> 410.088
A21: 01.04.03.03.02 | B21: CONCRETO f'c=140 Kg/cm2 PARA DADOS DE CONCRETO | C21: m³ | D21: =+'PLANILLA GENERAL DE METRADOS'!K97 -> 2.912
A22: 01.04.03.04 | B22: OBRAS DE CONCRETO ARMADO
A23: 01.04.03.04.02 | B23: CUNETAS
A24: 01.04.03.04.02.01 | B24: CONCRETO f'c=175 kg/cm2 PARA CUNETAS | C24: m³ | D24: =+'PLANILLA GENERAL DE METRADOS'!K101 -> 122.6458
A25: 01.04.03.04.02.02 | B25: ENCOFRADO Y DESENCOFRADO DE CUNETAS | C25: m² | D25: =+'PLANILLA GENERAL DE METRADOS'!K114 -> 1661.96
A26: 01.04.03.04.02.03 | B26: ACERO f'y=4200 kg/cm2 PARA CUNETA | C26: kg | D26: =+'PLANILLA GENERAL DE METRADOS'!K127 -> 4967.0517
A27: 01.04.03.04.02.04 | B27: CURADO DE CONCRETO EN CUNETA | C27: m² | D27: =+'METRADO DE CURADO'!M38 -> 1084.2059
A28: 01.04.03.04.03 | B28: VARIOS
A29: 01.04.03.04.03.01 | B29: REJILLA METALICA P/CUNETA C/PL 1''x 3/16'' Y ANGULO 1'' x 1'' x 3/16'', S/DETALLE | C29: m | D29: =+'PLANILLA GENERAL DE METRADOS'!K132 -> 510.11
A30: 01.04.03.04.03.02 | B30: TAPA DE INSPECCION 0.60m x 0.60m | C30: und | D30: =+'PLANILLA GENERAL DE METRADOS'!K133 -> 17
A31: 01.04.03.04.03.03 | B31: JUNTA DE DILATACION E=1" CON SELLADOR ASFALTO | C31: m | D31: =+'PLANILLA GENERAL DE METRADOS'!K134 -> 241.95954
A32: 01.04.03.04.03.04 | B32: LLORADERO DE TUBERIA PVC Ø3" C/FILTRO DE GRAVA Y GEOTEXTIL @1.50 m (CUNETA COLINDANTE CON AREA VERDE) | C32: und | D32: =+'PLANILLA GENERAL DE METRADOS'!K135 -> 157
A33: 01.04.03.05 | B33: RED DE COLECCIÓN
A34: 01.04.03.05.01 | B34: RED DE RECOLECCION TECHO
A35: 01.04.03.05.01.01 | B35: MONTANTE CON TUBERÍA PVC DE 4" | C35: m | D35: =+'PLANILLA GENERAL DE METRADOS'!K139 -> 380.86
A36: 01.04.03.05.01.02 | B36: FALSA COLUMNA P/MONTANTE DE 0.20m x 0.15m x 1.30m | C36: und | D36: =+'PLANILLA GENERAL DE METRADOS'!K140 -> 52
A37: 01.04.03.05.01.02.01 | B37: CONCRETO F´C=175 KG/CM2 EN FALSA COLUMNA | C37: m³ | D37: =+'PLANILLA GENERAL DE METRADOS'!K141 -> 2.028
A38: 01.04.03.05.01.02.02 | B38: ENCOFRADO Y DESENCOFRADO EN FALSA COLUMNA - MONTANTE PLUVIAL | C38: m² | D38: =+'PLANILLA GENERAL DE METRADOS'!K143 -> 33.8
A39: 01.04.03.05.01.02.03 | B39: ACERO FY=4200 KG/CM2 EN FALSA COLUMNA (MONTANTE PLUVIAL) | C39: kg | D39: =+'PLANILLA GENERAL DE METRADOS'!K146 -> 291.7824
A40: 01.04.03.05.01.03 | B40: CANALETA DE PLANCHA DE ACERO GALVANIZADO e=0.9mm, SECCIÓN 0.25m x 0.20m | C40: m | D40: =+'PLANILLA GENERAL DE METRADOS'!K149 -> 513.98
A41: 01.04.03.05.01.04 | B41: SOPORTE DE PLATINA F°G° 1" x 1/8" P/CANALETA | C41: und | D41: =+'PLANILLA GENERAL DE METRADOS'!K150 -> 884
A42: 01.04.03.05.01.05 | B42: TAPA LATERAL DE PLANCHA GALVANIZADA P/CANALETA | C42: und | D42: =+'PLANILLA GENERAL DE METRADOS'!K151 -> 40
A43: 01.04.03.05.01.06 | B43: BOQUILLA DE PLANCHA GALVANIZADA P/CONEXIÓN DE CANALETA A MONTANTE Ø4" | C43: und | D43: =+'PLANILLA GENERAL DE METRADOS'!K152 -> 52
A44: 01.04.03.05.02 | B44: RED DE RECOLECCION PISO
A45: 01.04.03.05.02.01 | B45: TUBERIA DESAGÜE PVC-CP Ø4" | C45: m | D45: =+'PLANILLA GENERAL DE METRADOS'!K155 -> 112.26
A46: 01.04.03.05.02.02 | B46: SUMIDERO METALICO C/PLATINA 1" X 3/16" | C46: und | D46: =+'PLANILLA GENERAL DE METRADOS'!K156 -> 30
A47: 01.04.03.05.02.03 | B47: CODO DESAGÜE PVC Ø4" x 90° | C47: und | D47: =+'PLANILLA GENERAL DE METRADOS'!K157 -> 24
A48: 01.04.03.05.02.04 | B48: TEE SANITARIA DESAGÜE PVC Ø4" | C48: und | D48: =+'PLANILLA GENERAL DE METRADOS'!K158 -> 4
A49: 01.04.03.05.03 | B49: ACCESORIOS
A50: 01.04.03.05.03.02 | B50: CODO DESAGÜE PVC Ø4" x 90° | C50: und | D50: =+'PLANILLA GENERAL DE METRADOS'!K161 -> 162
A51: 01.04.03.05.03.04 | B51: COLGADOR F°G° P/TUBERIA PVC Ø4" | C51: und | D51: =+'PLANILLA GENERAL DE METRADOS'!K162 -> 90
A52: 01.04.03.05.03.05 | B52: ABRAZADERA DE F°G° P/TUBERIA PVC Ø4" | C52: und | D52: =+'PLANILLA GENERAL DE METRADOS'!K163 -> 70
A54: 01.04.04 | B54: COLECTOR PLUVIAL FRONTAL (TRAMO HOGAR DE REFUGIO - EMPALME CON CAR MUJERES)
A55: 01.04.04.01 | B55: TRABAJOS PRELIMINARES
A56: 01.04.04.01.01 | B56: LIMPIEZA MANUAL DE TERRENO | C56: m² | D56: =+'PLANILLA GENERAL DE METRADOS'!K167 -> 125.854
A57: 01.04.04.01.02 | B57: TRAZO, NIVELES Y REPLANTEO PRELIMINAR | C57: m² | D57: =+'PLANILLA GENERAL DE METRADOS'!K177 -> 125.854
A58: 01.04.04.02 | B58: MOVIMIENTO DE TIERRAS
A59: 01.04.04.02.01 | B59: EXCAVACIÓN MANUAL DE ZANJAS P/COLECTOR | C59: m³ | D59: =+'PLANILLA GENERAL DE METRADOS'!K188 -> 164.89438
A60: 01.04.04.02.02 | B60: REFINE, NIVELACIÓN Y COMPACTACIÓN EN TERRENO NORMAL | C60: m² | D60: =+'PLANILLA GENERAL DE METRADOS'!K198 -> 93.938
A61: 01.04.04.02.03 | B61: RELLENO COMPACTADO C/MATERIAL PROPIO SELECCIONADO | C61: m³ | D61: =+'PLANILLA GENERAL DE METRADOS'!K208 -> 82.773335
A62: 01.04.04.02.04 | B62: ELIMINACIÓN DE MATERIAL EXCEDENTE D<1Km | C62: m³ | D62: =+'PLANILLA GENERAL DE METRADOS'!K225 -> 98.545249
A63: 01.04.04.03 | B63: OBRAS DE CONCRETO SIMPLE
A64: 01.04.04.03.01 | B64: CONCRETO f'c=100 kg/cm2 PARA SOLADO E=2'' | C64: m² | D64: =+'PLANILLA GENERAL DE METRADOS'!K229 -> 93.938
A65: 01.04.04.04 | B65: OBRAS DE CONCRETO ARMADO - COLECTOR Y CAJAS
A66: 01.04.04.04.01 | B66: CONCRETO f'c=210 kg/cm2 PARA COLECTOR | C66: m³ | D66: =+'PLANILLA GENERAL DE METRADOS'!K240 -> 58.313616
A67: 01.04.04.04.02 | B67: ENCOFRADO Y DESENCOFRADO DE COLECTOR | C67: m² | D67: =+'PLANILLA GENERAL DE METRADOS'!K272 -> 585.23188
A68: 01.04.04.04.03 | B68: ACERO f'y=4200 kg/cm2 PARA COLECTOR | C68: kg | D68: =+'PLANILLA GENERAL DE METRADOS'!K282 -> 3056.4464
A69: 01.04.04.04.04 | B69: ACABADO FROTACHADO DE LOSA SUPERIOR (VEREDA) | C69: m² | D69: =+'PLANILLA GENERAL DE METRADOS'!K292 -> 86.059
A70: 01.04.04.04.05 | B70: CURADO DE CONCRETO EN COLECTOR | C70: m² | D70: =+'PLANILLA GENERAL DE METRADOS'!K302 -> 390.60444
A71: 01.04.04.05 | B71: REGISTROS DE LIMPIEZA Y TAPAS
A72: 01.04.04.05.01 | B72: TAPA DE REGISTRO 0.68x0.68 C/MARCO Y CONTRAMARCO | C72: und | D72: =+'PLANILLA GENERAL DE METRADOS'!K313 -> 10
A73: 01.04.04.06 | B73: JUNTAS
A74: 01.04.04.06.01 | B74: JUNTA DE DILATACION E=1" CON TECNOPOR Y SELLADOR ASFALTICO EN COLECTOR | C74: m | D74: =+'PLANILLA GENERAL DE METRADOS'!K321 -> 100.64
A75: 01.04.04.06.02 | B75: JUNTA E=1" CON TECNOPOR Y SELLADOR ASFALTICO ENTRE COLECTOR Y CERCO PERIMETRICO | C75: m | D75: =+'PLANILLA GENERAL DE METRADOS'!K322 -> 210.979

Sheet PLANILLA GENERAL DE METRADOS
A2: RESUMEN METRADOS DE DRENAJE PLUVIAL
A3: ENTIDAD | B3: =+RESUMEN!B4 -> GERENCIA TERRITORIAL BAJO MAYO - TARAPOTO
A4: PROYECTO | B4: =+RESUMEN!B5 -> “CREACIÓN DEL SERVICIO DE PROTECCIÓN A MUJERES VÍCTIMAS DE VIOLENCIA EN SITUACIÓN DE RIESGO DE FEMINICIDIO O PELIGRE SU INTEGRIDAD Y/O SALUD FÍSICA Y/O MENTAL EN HOGAR DE REFUGIO TEMPORAL DISTRITO DE MORALES DE LA PROVINCIA DE SAN MARTÍN DEL DEPARTAMENTO DE SAN MARTÍN”, con CUI N.° 2675514
A5: UBICACIÓN | B5: =+RESUMEN!B6 -> SAN MARTIN - SAN MARTIN - MORALES
A6: FECHA | B6: =+RESUMEN!B7 -> 46266
A8: ITEM | B8: DESCRIPCION | C8: Nº DE VECES | D8: LARGO | E8: ANCHO | F8: ALTURA | G8: FACT. | H8: AREA | I8: VOLUMEN | J8: PARCIAL | K8: TOTAL | L8: UND
A9: 01.04.03 | B9: SISTEMA DE DRENAJE PLUVIAL
A10: 01.04.03.01 | B10: TRABAJOS PRELIMINARES
A11: 01.04.03.01.01 | B11: LIMPIEZA MANUAL DE TERRENO | K11: =SUM(J12:J23) -> 956.872 | L11: m²
B12: EJE 1 | C12: 1 | D12: 37.14 | E12: 1.4 | J12: =C12*D12*E12 -> 51.996
B13: EJE 2 | C13: 1 | D13: 130.85 | E13: 1.4 | J13: =C13*D13*E13 -> 183.19
B14: EJE 3 | C14: 1 | D14: 5.82 | E14: 1.4 | J14: =C14*D14*E14 -> 8.148
B15: EJE 4 | C15: 1 | D15: 8.6 | E15: 1.4 | J15: =C15*D15*E15 -> 12.04
B16: EJE 5 | C16: 1 | D16: 43.23 | E16: 1.4 | J16: =C16*D16*E16 -> 60.522
B17: EJE 6 | C17: 1 | D17: 120.36 | E17: 1.4 | J17: =C17*D17*E17 -> 168.504
B18: EJE 7 | C18: 1 | D18: 125.7 | E18: 1.4 | J18: =C18*D18*E18 -> 175.98
B19: EJE 8 | C19: 1 | D19: 8.2 | E19: 1.4 | J19: =C19*D19*E19 -> 11.48
B20: EJE 9 | C20: 1 | D20: 7 | E20: 1.4 | J20: =C20*D20*E20 -> 9.8
B21: EJE 10 | C21: 1 | D21: 16 | E21: 1.4 | J21: =C21*D21*E21 -> 22.4
B22: EJE 11 | C22: 1 | D22: 71.46 | E22: 1.4 | J22: =C22*D22*E22 -> 100.044
B23: EJE 12 | C23: 1 | D23: 109.12 | E23: 1.4 | J23: =C23*D23*E23 -> 152.768
A24: 01.04.03.01.02 | B24: TRAZO, NIVELES Y REPLANTEO PRELIMINAR | K24: =SUM(J25:J36) -> 956.872 | L24: m²
B25: EJE 1 | C25: 1 | D25: 37.14 | E25: 1.4 | J25: =C25*D25*E25 -> 51.996
B26: EJE 2 | C26: 1 | D26: 130.85 | E26: 1.4 | J26: =C26*D26*E26 -> 183.19
B27: EJE 3 | C27: 1 | D27: 5.82 | E27: 1.4 | J27: =C27*D27*E27 -> 8.148
B28: EJE 4 | C28: 1 | D28: 8.6 | E28: 1.4 | J28: =C28*D28*E28 -> 12.04
B29: EJE 5 | C29: 1 | D29: 43.23 | E29: 1.4 | J29: =C29*D29*E29 -> 60.522
B30: EJE 6 | C30: 1 | D30: 120.36 | E30: 1.4 | J30: =C30*D30*E30 -> 168.504
B31: EJE 7 | C31: 1 | D31: 125.7 | E31: 1.4 | J31: =C31*D31*E31 -> 175.98
B32: EJE 8 | C32: 1 | D32: 8.2 | E32: 1.4 | J32: =C32*D32*E32 -> 11.48
B33: EJE 9 | C33: 1 | D33: 7 | E33: 1.4 | J33: =C33*D33*E33 -> 9.8
B34: EJE 10 | C34: 1 | D34: 16 | E34: 1.4 | J34: =C34*D34*E34 -> 22.4
B35: EJE 11 | C35: 1 | D35: 71.46 | E35: 1.4 | J35: =C35*D35*E35 -> 100.044
B36: EJE 12 | C36: 1 | D36: 109.12 | E36: 1.4 | J36: =C36*D36*E36 -> 152.768
A37: 01.04.03.02 | B37: MOVIMIENTO DE TIERRAS
A38: 01.04.03.02.01 | B38: EXCAVACIÓN MANUAL DE ZANJAS P/CUNETAS | K38: =SUM(J39:J50) -> 619.79764 | L38: m³
B39: EJE 1 | C39: 1 | D39: 37.14 | E39: 1.4 | F39: 0.4 | J39: =C39*D39*E39*(F39+PARAMETROS!$B$15) -> 25.998
B40: EJE 2 | C40: 1 | D40: 130.85 | E40: 1.4 | F40: 0.62 | J40: =C40*D40*E40*(F40+PARAMETROS!$B$15) -> 131.8968
B41: EJE 3 | C41: 1 | D41: 5.82 | E41: 1.4 | F41: 0.3 | J41: =C41*D41*E41*(F41+PARAMETROS!$B$15) -> 3.2592
B42: EJE 4 | C42: 1 | D42: 8.6 | E42: 1.4 | F42: 0.32 | J42: =C42*D42*E42*(F42+PARAMETROS!$B$15) -> 5.0568
B43: EJE 5 | C43: 1 | D43: 43.23 | E43: 1.4 | F43: 0.4 | J43: =C43*D43*E43*(F43+PARAMETROS!$B$15) -> 30.261
B44: EJE 6 | C44: 1 | D44: 120.36 | E44: 1.4 | F44: 0.6 | J44: =C44*D44*E44*(F44+PARAMETROS!$B$15) -> 117.9528
B45: EJE 7 | C45: 1 | D45: 125.7 | E45: 1.4 | F45: 0.61 | J45: =C45*D45*E45*(F45+PARAMETROS!$B$15) -> 124.9458
B46: EJE 8 | C46: 1 | D46: 8.2 | E46: 1.4 | F46: 0.42 | J46: =C46*D46*E46*(F46+PARAMETROS!$B$15) -> 5.9696
B47: EJE 9 | C47: 1 | D47: 7 | E47: 1.4 | F47: 0.41 | J47: =C47*D47*E47*(F47+PARAMETROS!$B$15) -> 4.998
B48: EJE 10 | C48: 1 | D48: 16 | E48: 1.4 | F48: 0.35 | J48: =C48*D48*E48*(F48+PARAMETROS!$B$15) -> 10.08
B49: EJE 11 | C49: 1 | D49: 71.46 | E49: 1.4 | F49: 0.47 | J49: =C49*D49*E49*(F49+PARAMETROS!$B$15) -> 57.02508
B50: EJE 12 | C50: 1 | D50: 109.12 | E50: 1.4 | F50: 0.57 | J50: =C50*D50*E50*(F50+PARAMETROS!$B$15) -> 102.35456
A51: 01.04.03.02.02 | B51: EXCAVACIÓN MANUAL DE ZANJAS P/DADOS DE CONCRETO | C51: 52 | K51: =J52*C51 -> 2.912 | L51: m³
B52: DADO 0.40 X 0.40 | D52: 0.4 | E52: 0.35 | F52: 0.4 | J52: =D52*E52*F52 -> 0.056
A54: 01.04.03.02.03 | B54: REFINE, NIVELACIÓN Y COMPACTACIÓN EN TERRENO NORMAL | K54: =SUM(J55:J66) -> 410.088 | L54: m²
B55: EJE 1 | C55: 1 | D55: 37.14 | E55: 0.6 | J55: =C55*D55*E55 -> 22.284
B56: EJE 2 | C56: 1 | D56: 130.85 | E56: 0.6 | J56: =C56*D56*E56 -> 78.51
B57: EJE 3 | C57: 1 | D57: 5.82 | E57: 0.6 | J57: =C57*D57*E57 -> 3.492
B58: EJE 4 | C58: 1 | D58: 8.6 | E58: 0.6 | J58: =C58*D58*E58 -> 5.16
B59: EJE 5 | C59: 1 | D59: 43.23 | E59: 0.6 | J59: =C59*D59*E59 -> 25.938
B60: EJE 6 | C60: 1 | D60: 120.36 | E60: 0.6 | J60: =C60*D60*E60 -> 72.216
B61: EJE 7 | C61: 1 | D61: 125.7 | E61: 0.6 | J61: =C61*D61*E61 -> 75.42
B62: EJE 8 | C62: 1 | D62: 8.2 | E62: 0.6 | J62: =C62*D62*E62 -> 4.92
B63: EJE 9 | C63: 1 | D63: 7 | E63: 0.6 | J63: =C63*D63*E63 -> 4.2
B64: EJE 10 | C64: 1 | D64: 16 | E64: 0.6 | J64: =C64*D64*E64 -> 9.6
B65: EJE 11 | C65: 1 | D65: 71.46 | E65: 0.6 | J65: =C65*D65*E65 -> 42.876
B66: EJE 12 | C66: 1 | D66: 109.12 | E66: 0.6 | J66: =C66*D66*E66 -> 65.472
A67: 01.04.03.02.04 | B67: RELLENO COMPACTADO C/MATERIAL PROPIO SELECCIONADO | K67: =SUM(J68:J79) -> 343.77408 | L67: m³
B68: EJE 1 | C68: 1 | D68: 37.14 | E68: 0.8 | F68: 0.41 | J68: =C68*D68*E68*(F68+PARAMETROS!$B$15) -> 15.15312
B69: EJE 2 | C69: 1 | D69: 130.85 | E69: 0.8 | F69: 0.65 | J69: =C69*D69*E69*(F69+PARAMETROS!$B$15) -> 78.51
B70: EJE 3 | C70: 1 | D70: 5.82 | E70: 0.8 | F70: 0.37 | J70: =C70*D70*E70*(F70+PARAMETROS!$B$15) -> 2.18832
B71: EJE 4 | C71: 1 | D71: 8.6 | E71: 0.8 | F71: 0.33 | J71: =C71*D71*E71*(F71+PARAMETROS!$B$15) -> 2.9584
B72: EJE 5 | C72: 1 | D72: 43.23 | E72: 0.8 | F72: 0.37 | J72: =C72*D72*E72*(F72+PARAMETROS!$B$15) -> 16.25448
B73: EJE 6 | C73: 1 | D73: 120.36 | E73: 0.8 | F73: 0.56 | J73: =C73*D73*E73*(F73+PARAMETROS!$B$15) -> 63.55008
B74: EJE 7 | C74: 1 | D74: 125.7 | E74: 0.8 | F74: 0.62 | J74: =C74*D74*E74*(F74+PARAMETROS!$B$15) -> 72.4032
B75: EJE 8 | C75: 1 | D75: 8.2 | E75: 0.8 | F75: 0.35 | J75: =C75*D75*E75*(F75+PARAMETROS!$B$15) -> 2.952
B76: EJE 9 | C76: 1 | D76: 7 | E76: 0.8 | F76: 0.45 | J76: =C76*D76*E76*(F76+PARAMETROS!$B$15) -> 3.08
B77: EJE 10 | C77: 1 | D77: 16 | E77: 0.8 | F77: 0.55 | J77: =C77*D77*E77*(F77+PARAMETROS!$B$15) -> 8.32
B78: EJE 11 | C78: 1 | D78: 71.46 | E78: 0.8 | F78: 0.34 | J78: =C78*D78*E78*(F78+PARAMETROS!$B$15) -> 25.15392
B79: EJE 12 | C79: 1 | D79: 109.12 | E79: 0.8 | F79: 0.51 | J79: =C79*D79*E79*(F79+PARAMETROS!$B$15) -> 53.25056
A80: 01.04.03.02.05 | B80: ELIMINACIÓN DE MATERIAL EXCEDENTE D<1Km | G80: =PARAMETROS!$B$16 -> 1.2 | K80: =(J81+J82)*G80 -> 331.22827 | L80: m³
B81: EXCAVACIÓN MANUAL DE ZANJA PARA CUNETA | G81: 1 | I81: =+K38 -> 619.79764 | J81: =G81*I81 -> 619.79764
B82: RELLENO COMPACTADO CON MATERIAL PROPIO | G82: -1 | I82: =+K67 -> 343.77408 | J82: =G82*I82 -> -343.77408
A83: 01.04.03.03 | B83: OBRAS DE CONCRETO SIMPLE
A84: 01.04.03.03.01 | B84: CONCRETO f'c=100 kg/cm2 PARA SOLADO E=4'' | K84: =SUM(J85:J96) -> 410.088 | L84: m²
B85: EJE 1 | C85: 1 | D85: 37.14 | E85: 0.6 | J85: =C85*D85*E85 -> 22.284
B86: EJE 2 | C86: 1 | D86: 130.85 | E86: 0.6 | J86: =C86*D86*E86 -> 78.51
B87: EJE 3 | C87: 1 | D87: 5.82 | E87: 0.6 | J87: =C87*D87*E87 -> 3.492
B88: EJE 4 | C88: 1 | D88: 8.6 | E88: 0.6 | J88: =C88*D88*E88 -> 5.16
B89: EJE 5 | C89: 1 | D89: 43.23 | E89: 0.6 | J89: =C89*D89*E89 -> 25.938
B90: EJE 6 | C90: 1 | D90: 120.36 | E90: 0.6 | J90: =C90*D90*E90 -> 72.216
B91: EJE 7 | C91: 1 | D91: 125.7 | E91: 0.6 | J91: =C91*D91*E91 -> 75.42
B92: EJE 8 | C92: 1 | D92: 8.2 | E92: 0.6 | J92: =C92*D92*E92 -> 4.92
B93: EJE 9 | C93: 1 | D93: 7 | E93: 0.6 | J93: =C93*D93*E93 -> 4.2
B94: EJE 10 | C94: 1 | D94: 16 | E94: 0.6 | J94: =C94*D94*E94 -> 9.6
B95: EJE 11 | C95: 1 | D95: 71.46 | E95: 0.6 | J95: =C95*D95*E95 -> 42.876
B96: EJE 12 | C96: 1 | D96: 109.12 | E96: 0.6 | J96: =C96*D96*E96 -> 65.472
A97: 01.04.03.03.02 | B97: CONCRETO f'c=140 Kg/cm2 PARA DADOS DE CONCRETO | C97: 52 | K97: =J98*C97 -> 2.912 | L97: m³
B98: DADO 0.40 X 0.40 | D98: 0.4 | E98: 0.35 | F98: 0.4 | J98: =D98*E98*F98 -> 0.056
A99: 01.04.03.04 | B99: OBRAS DE CONCRETO ARMADO
A100: 01.04.03.04.02 | B100: CUNETAS
A101: 01.04.03.04.02.01 | B101: CONCRETO f'c=175 kg/cm2 PARA CUNETAS | K101: =SUM(J102:J113) -> 122.6458 | L101: m³
B102: EJE 1 | C102: 1 | J102: =+'CONCRETO EN CUNETAS'!G10 -> 5.3508
B103: EJE 2 | C103: 1 | J103: =+'CONCRETO EN CUNETAS'!G22 -> 25.4146
...

Sheet CONCRETO EN CUNETAS
B2: CONCRETO F´C=175 KG/CM2 PARA CUNETAS - DRENAJE PLUVIAL
B3: ENTIDAD | C3: =+RESUMEN!B4 -> GERENCIA TERRITORIAL BAJO MAYO - TARAPOTO
B4: PROYECTO | C4: =+RESUMEN!B5 -> “CREACIÓN DEL SERVICIO DE PROTECCIÓN A MUJERES VÍCTIMAS DE VIOLENCIA EN SITUACIÓN DE RIESGO DE FEMINICIDIO O PELIGRE SU INTEGRIDAD Y/O SALUD FÍSICA Y/O MENTAL EN HOGAR DE REFUGIO TEMPORAL DISTRITO DE MORALES DE LA PROVINCIA DE SAN MARTÍN DEL DEPARTAMENTO DE SAN MARTÍN”, con CUI N.° 2675514
B5: UBICACIÓN | C5: =+RESUMEN!B6 -> SAN MARTIN - SAN MARTIN - MORALES
B6: FECHA | C6: =+RESUMEN!B7 -> 46266
B7: OBRAS DE CONCRETO ARMADO
B9: LONGITUDES Y AREAS | E9: m3 | F9: Sub.TOTAL | G9: TOTAL (m3) | J9: LONGITUDES Y AREAS | M9: m3 | N9: Sub.TOTAL | O9: TOTAL (m3)
B10: CUNETA EJE 01 | C10: MUROS | D10: AREA | E10: 14.07 | F10: =E10*E11*E12 -> 2.814 | G10: =SUM(F10:F18) -> 5.3508 | J10: CUNETA EJE 07 | K10: MUROS | L10: AREA | M10: 74.5 | N10: =M10*M11*M12 -> 14.9 | O10: =SUM(N10:N18) -> 23.9066
D11: ESPESOR | E11: 0.1 | L11: ESPESOR | M11: 0.1
D12: CANT. | E12: 2 | L12: CANT. | M12: 2
C13: LOSA | D13: ESPESOR | E13: 0.1 | F13: =E13*E14*E15 -> 2.2284 | K13: LOSA | L13: ESPESOR | M13: 0.1 | N13: =M13*M14*M15 -> 7.542
D14: LONGITUD | E14: 37.14 | L14: LONGITUD | M14: 125.7
D15: ANCHO | E15: 0.6 | L15: ANCHO | M15: 0.6
C16: TAPA | D16: LONGITUD | E16: 5.14 | F16: =E16*E17*E18 -> 0.3084 | K16: TAPA | L16: LONGITUD | M16: 24.41 | N16: =M16*M17*M18 -> 1.4646
D17: ESPESOR | E17: 0.1 | L17: ESPESOR | M17: 0.1
D18: ANCHO | E18: 0.6 | L18: ANCHO | M18: 0.6
B21: LONGITUDES Y AREAS | E21: m3 | F21: Sub.TOTAL | G21: TOTAL (m3) | J21: LONGITUDES Y AREAS | M21: m3 | N21: Sub.TOTAL | O21: TOTAL (m3)
B22: CUNETA EJE 02 | C22: MUROS | D22: AREA | E22: 78.32 | F22: =E22*E23*E24 -> 15.664 | G22: =SUM(F22:F30) -> 25.4146 | J22: CUNETA EJE 08 | K22: MUROS | L22: AREA | M22: 2.62 | N22: =M22*M23*M24 -> 0.524 | O22: =SUM(N22:N30) -> 1.508
D23: ESPESOR | E23: 0.1 | L23: ESPESOR | M23: 0.1
D24: CANT. | E24: 2 | L24: CANT. | M24: 2
C25: LOSA | D25: ESPESOR | E25: 0.1 | F25: =E25*E26*E27 -> 7.851 | K25: LOSA | L25: ESPESOR | M25: 0.1 | N25: =M25*M26*M27 -> 0.492
D26: LONGITUD | E26: 130.85 | L26: LONGITUD | M26: 8.2
D27: ANCHO | E27: 0.6 | L27: ANCHO | M27: 0.6
C28: TAPA | D28: LONGITUD | E28: 31.66 | F28: =E28*E29*E30 -> 1.8996 | K28: TAPA | L28: LONGITUD | M28: 8.2 | N28: =M28*M29*M30 -> 0.492
D29: ESPESOR | E29: 0.1 | L29: ESPESOR | M29: 0.1
D30: ANCHO | E30: 0.6 | L30: ANCHO | M30: 0.6
B33: LONGITUDES Y AREAS | E33: m3 | F33: Sub.TOTAL | G33: TOTAL (m3) | J33: LONGITUDES Y AREAS | M33: m3 | N33: Sub.TOTAL | O33: TOTAL (m3)
B34: CUNETA EJE 03 | C34: MUROS | D34: AREA | E34: 1.83 | F34: =E34*E35*E36 -> 0.366 | G34: =SUM(F34:F42) -> 0.7152 | J34: CUNETA EJE 09 | K34: MUROS | L34: AREA | M34: 2.22 | N34: =M34*M35*M36 -> 0.444 | O34: =SUM(N34:N42) -> 1.284
D35: ESPESOR | E35: 0.1 | L35: ESPESOR | M35: 0.1
D36: CANT. | E36: 2 | L36: CANT. | M36: 2
C37: LOSA | D37: ESPESOR | E37: 0.1 | F37: =E37*E38*E39 -> 0.3492 | K37: LOSA | L37: ESPESOR | M37: 0.1 | N37: =M37*M38*M39 -> 0.42
D38: LONGITUD | E38: 5.82 | L38: LONGITUD | M38: 7
D39: ANCHO | E39: 0.6 | L39: ANCHO | M39: 0.6
C40: TAPA | D40: LONGITUD | E40: 0 | F40: =E40*E41*E42 -> 0 | K40: TAPA | L40: LONGITUD | M40: 7 | N40: =M40*M41*M42 -> 0.42
D41: ESPESOR | E41: 0.1 | L41: ESPESOR | M41: 0.1
D42: ANCHO | E42: 0.6 | L42: ANCHO | M42: 0.6
B45: LONGITUDES Y AREAS | E45: m3 | F45: Sub.TOTAL | G45: TOTAL (m3) | J45: LONGITUDES Y AREAS | M45: m3 | N45: Sub.TOTAL | O45: TOTAL (m3)
B46: CUNETA EJE 04 | C46: MUROS | D46: AREA | E46: 2.76 | F46: =E46*E47*E48 -> 0.552 | G46: =SUM(F46:F54) -> 1.068 | J46: CUNETA EJE 10 | K46: MUROS | L46: AREA | M46: 5.44 | N46: =M46*M47*M48 -> 1.088 | O46: =SUM(N46:N54) -> 2.048
D47: ESPESOR | E47: 0.1 | L47: ESPESOR | M47: 0.1
D48: CANT. | E48: 2 | L48: CANT. | M48: 2
C49: LOSA | D49: ESPESOR | E49: 0.1 | F49: =E49*E50*E51 -> 0.516 | K49: LOSA | L49: ESPESOR | M49: 0.1 | N49: =M49*M50*M51 -> 0.96
D50: LONGITUD | E50: 8.6 | L50: LONGITUD | M50: 16
D51: ANCHO | E51: 0.6 | L51: ANCHO | M51: 0.6
C52: TAPA | D52: LONGITUD | E52: 0 | F52: =E52*E53*E54 -> 0 | K52: TAPA | L52: LONGITUD | M52: 0 | N52: =M52*M53*M54 -> 0
D53: ESPESOR | E53: 0.1 | L53: ESPESOR | M53: 0.1
D54: ANCHO | E54: 0.6 | L54: ANCHO | M54: 0.6
B57: LONGITUDES Y AREAS | E57: m3 | F57: Sub.TOTAL | G57: TOTAL (m3) | J57: LONGITUDES Y AREAS | M57: m3 | N57: Sub.TOTAL | O57: TOTAL (m3)
B58: CUNETA EJE 05 | C58: MUROS | D58: AREA | E58: 17.7 | F58: =E58*E59*E60 -> 3.54 | G58: =SUM(F58:F66) -> 6.4758 | J58: CUNETA EJE 11 | K58: MUROS | L58: AREA | M58: 33 | N58: =M58*M59*M60 -> 6.6 | O58: =SUM(N58:N66) -> 11.4096
D59: ESPESOR | E59: 0.1 | L59: ESPESOR | M59: 0.1
D60: CANT. | E60: 2 | L60: CANT. | M60: 2
C61: LOSA | D61: ESPESOR | E61: 0.1 | F61: =E61*E62*E63 -> 2.5938 | K61: LOSA | L61: ESPESOR | M61: 0.1 | N61: =M61*M62*M63 -> 4.2876
D62: LONGITUD | E62: 43.23 | L62: LONGITUD | M62: 71.46
D63: ANCHO | E63: 0.6 | L63: ANCHO | M63: 0.6
C64: TAPA | D64: LONGITUD | E64: 5.7 | F64: =E64*E65*E66 -> 0.342 | K64: TAPA | L64: LONGITUD | M64: 8.7 | N64: =M64*M65*M66 -> 0.522
D65: ESPESOR | E65: 0.1 | L65: ESPESOR | M65: 0.1
D66: ANCHO | E66: 0.6 | L66: ANCHO | M66: 0.6
B69: LONGITUDES Y AREAS | E69: m3 | F69: Sub.TOTAL | G69: TOTAL (m3) | J69: LONGITUDES Y AREAS | M69: m3 | N69: Sub.TOTAL | O69: TOTAL (m3)
B70: CUNETA EJE 06 | C70: MUROS | D70: AREA | E70: 69.72 | F70: =E70*E71*E72 -> 13.944 | G70: =SUM(F70:F78) -> 22.7196 | J70: CUNETA EJE 12 | K70: MUROS | L70: AREA | M70: 54 | N70: =M70*M71*M72 -> 10.8 | O70: =SUM(N70:N78) -> 20.7456
D71: ESPESOR | E71: 0.1 | L71: ESPESOR | M71: 0.1
D72: CANT. | E72: 2 | L72: CANT. | M72: 2
C73: LOSA | D73: ESPESOR | E73: 0.1 | F73: =E73*E74*E75 -> 7.2216 | K73: LOSA | L73: ESPESOR | M73: 0.1 | N73: =M73*M74*M75 -> 6.5472
D74: LONGITUD | E74: 120.36 | L74: LONGITUD | M74: 109.12
D75: ANCHO | E75: 0.6 | L75: ANCHO | M75: 0.6
C76: TAPA | D76: LONGITUD | E76: 25.9 | F76: =E76*E77*E78 -> 1.554 | K76: TAPA | L76: LONGITUD | M76: 56.64 | N76: =M76*M77*M78 -> 3.3984
D77: ESPESOR | E77: 0.1 | L77: ESPESOR | M77: 0.1
D78: ANCHO | E78: 0.6 | L78: ANCHO | M78: 0.6

Sheet ENCOFRADO Y DESENCOFRADO
B2: ENCOFRADO Y DESENCOFRADO CUNETAS - DRENAJE PLUVIAL
B3: ENTIDAD | C3: =+RESUMEN!B4 -> GERENCIA TERRITORIAL BAJO MAYO - TARAPOTO
B4: PROYECTO | C4: =+RESUMEN!B5 -> “CREACIÓN DEL SERVICIO DE PROTECCIÓN A MUJERES VÍCTIMAS DE VIOLENCIA EN SITUACIÓN DE RIESGO DE FEMINICIDIO O PELIGRE SU INTEGRIDAD Y/O SALUD FÍSICA Y/O MENTAL EN HOGAR DE REFUGIO TEMPORAL DISTRITO DE MORALES DE LA PROVINCIA DE SAN MARTÍN DEL DEPARTAMENTO DE SAN MARTÍN”, con CUI N.° 2675514
B5: UBICACIÓN | C5: =+RESUMEN!B6 -> SAN MARTIN - SAN MARTIN - MORALES
B6: FECHA | C6: =+RESUMEN!B7 -> 46266
B8: OBRAS DE CONCRETO ARMADO - ENCOFRADO Y DESENCOFRADO CUNETAS
B11: LONGITUDES Y AREAS | G11: Sub.TOTAL | H11: TOTAL (m2) | J11: LONGITUDES Y AREAS | O11: Sub.TOTAL | P11: TOTAL (m2)
B12: EJE1 | C12: ABIERTA | D12: MUROS EXTERNO | E12: AREA | F12: 15.36 | G12: =F12*F13 -> 30.72 | H12: =SUM(G12:G20) -> 66.796 | J12: EJE 2 | K12: NORMAL | L12: MUROS EXTERNO | M12: AREA | N12: 68.67 | O12: =N12*N13 -> 137.34 | P12: =SUM(O12:O20) -> 358.444
E13: CANT. | F13: 2 | M13: CANT. | N13: 2
D14: MURO INTERNO | E14: AREA | F14: 12.16 | G14: =F14*F15 -> 24.32 | L14: MURO INTERNO | M14: AREA | N14: 58.75 | O14: =N14*N15 -> 117.5
E15: CANTIDAD | F15: 2 | M15: CANTIDAD | N15: 2
C16: TAPADO | D16: MURO EXTERNO | E16: AREA | F16: 2.94 | G16: =F16*F17 -> 5.88 | K16: TAPADO | L16: MURO EXTERNO | M16: AREA | N16: 25.9 | O16: =N16*N17 -> 51.8
E17: CANT. | F17: 2 | M17: CANT. | N17: 2
D18: MURO INTERNO | E18: AREA | F18: 1.91 | G18: =(F18*F19)+F20 -> 5.876 | L18: MURO INTERNO | M18: AREA | N18: 19.57 | O18: =N18*N19+N20 -> 51.804
E19: CANTIDAD | F19: 2 | M19: CANTIDAD | N19: 2
E20: TAPA | F20: =5.14*0.4 -> 2.056 | M20: TAPA | N20: =31.66*0.4 -> 12.664
B22: LONGITUDES Y AREAS | G22: Sub.TOTAL | H22: TOTAL (m2) | J22: LONGITUDES Y AREAS | O22: Sub.TOTAL | P22: TOTAL (m2)
B23: EJE 3 | C23: ABIERTA | D23: MUROS EXTERNO | E23: AREA | F23: 2.41 | G23: =F23*F24 -> 4.82 | H23: =SUM(G23:G31) -> 8.48 | J23: EJE 4 | K23: NORMAL | L23: MUROS EXTERNO | M23: AREA | N23: 3.62 | O23: =N23*N24 -> 7.24 | P23: =SUM(O23:O31) -> 12.76
E24: CANT. | F24: 2 | M24: CANT. | N24: 2
D25: MURO INTERNO | E25: AREA | F25: 1.83 | G25: =F25*F26 -> 3.66 | L25: MURO INTERNO | M25: AREA | N25: 2.76 | O25: =N25*N26 -> 5.52
E26: CANTIDAD | F26: 2 | M26: CANTIDAD | N26: 2
C27: TAPADO | D27: MURO EXTERNO | E27: AREA | F27: 0 | G27: =F27*F28 -> 0 | K27: TAPADO | L27: MURO EXTERNO | M27: AREA | N27: 0 | O27: =N27*N28 -> 0
E28: CANT. | F28: 2 | M28: CANT. | N28: 2
D29: MURO INTERNO | E29: AREA | F29: 0 | G29: =F29*F30+F31 -> 0 | L29: MURO INTERNO | M29: AREA | N29: 0 | O29: =N29*N30+N31 -> 0
E30: CANTIDAD | F30: 2 | M30: CANTIDAD | N30: 2
E31: TAPA | F31: 0 | M31: TAPA | N31: 0
B33: LONGITUDES Y AREAS | G33: Sub.TOTAL | H33: TOTAL (m2) | J33: LONGITUDES Y AREAS | O33: Sub.TOTAL | P33: TOTAL (m2)
B34: EJE 5 | C34: NORMAL | D34: MUROS EXTERNO | E34: AREA | F34: 18.53 | G34: =F34*F35 -> 37.06 | H34: =SUM(G34:G42) -> 80.36 | J34: EJE 6 | K34: NORMAL | L34: MUROS EXTERNO | M34: AREA | N34: 63.19 | O34: =N34*N35 -> 126.38 | P34: =SUM(O34:O42) -> 318.54
E35: CANT. | F35: 2 | M35: CANT. | N35: 2
D36: MURO INTERNO | E36: AREA | F36: 14.78 | G36: =F36*F37 -> 29.56 | L36: MURO INTERNO | M36: AREA | N36: 53.74 | O36: =N36*N37 -> 107.48
E37: CANTIDAD | F37: 2 | M37: CANTIDAD | N37: 2
C38: TAPADO | D38: MURO EXTERNO | E38: AREA | F38: 3.43 | G38: =F38*F39 -> 6.86 | K38: TAPADO | L38: MURO EXTERNO | M38: AREA | N38: 21.16 | O38: =N38*N39 -> 42.32
E39: CANT. | F39: 2 | M39: CANT. | N39: 2
D40: MURO INTERNO | E40: AREA | F40: 2.3 | G40: =F40*F41+F42 -> 6.88 | L40: MURO INTERNO | M40: AREA | N40: 16 | O40: =N40*N41+N42 -> 42.36
E41: CANTIDAD | F41: 2 | M41: CANTIDAD | N41: 2
E42: TAPA | F42: =5.7*0.4 -> 2.28 | M42: TAPA | N42: =25.9*0.4 -> 10.36
B44: LONGITUDES Y AREAS | G44: Sub.TOTAL | H44: TOTAL (m2) | J44: LONGITUDES Y AREAS | O44: Sub.TOTAL | P44: TOTAL (m2)
B45: EJE 7 | C45: NORMAL | D45: MUROS EXTERNO | E45: AREA | F45: 68.6 | G45: =F45*F46 -> 137.2 | H45: =SUM(G45:G53) -> 337.7 | J45: EJE 8 | K45: NORMAL | L45: MUROS EXTERNO | M45: AREA | N45: 0 | O45: =N45*N46 -> 0 | P45: =SUM(O45:O53) -> 17.04
E46: CANT. | F46: 2 | M46: CANT. | N46: 2
D47: MURO INTERNO | E47: AREA | F47: 58.46 | G47: =F47*F48 -> 116.92 | L47: MURO INTERNO | M47: AREA | N47: 0 | O47: =N47*N48 -> 0
E48: CANTIDAD | F48: 2 | M48: CANTIDAD | N48: 2
C49: TAPADO | D49: MURO EXTERNO | E49: AREA | F49: 20.91 | G49: =F49*F50 -> 41.82 | K49: TAPADO | L49: MURO EXTERNO | M49: AREA | N49: 4.26 | O49: =N49*N50 -> 8.52
E50: CANT. | F50: 2 | M50: CANT. | N50: 2
D51: MURO INTERNO | E51: AREA | F51: 16 | G51: =F51*F52+F53 -> 41.76 | L51: MURO INTERNO | M51: AREA | N51: 2.62 | O51: =N51*N52+N53 -> 8.52
E52: CANTIDAD | F52: 2 | M52: CANTIDAD | N52: 2
E53: TAPA | F53: =24.4*0.4 -> 9.76 | M53: TAPA | N53: =8.2*0.4 -> 3.28
B56: LONGITUDES Y AREAS | G56: Sub.TOTAL | H56: TOTAL (m2) | J56: LONGITUDES Y AREAS | O56: Sub.TOTAL | P56: TOTAL (m2)
B57: EJE 9 | C57: NORMAL | D57: MUROS EXTERNO | E57: AREA | F57: 0 | G57: =F57*F58 -> 0 | H57: =SUM(G57:G65) -> 14.48 | J57: EJE 10 | K57: NORMAL | L57: MUROS EXTERNO | M57: AREA | N57: 7.04 | O57: =N57*N58 -> 14.08 | P57: =SUM(O57:O65) -> 24.96
E58: CANT. | F58: 2 | M58: CANT. | N58: 2
D59: MURO INTERNO | E59: AREA | F59: 0 | G59: =F59*F60 -> 0 | L59: MURO INTERNO | M59: AREA | N59: 5.44 | O59: =N59*N60 -> 10.88
E60: CANTIDAD | F60: 2 | M60: CANTIDAD | N60: 2
C61: TAPADO | D61: MURO EXTERNO | E61: AREA | F61: 3.62 | G61: =F61*F62 -> 7.24 | K61: TAPADO | L61: MURO EXTERNO | M61: AREA | N61: 0 | O61: =N61*N62 -> 0
E62: CANT. | F62: 2 | M62: CANT. | N62: 2
D63: MURO INTERNO | E63: AREA | F63: 2.22 | G63: =F63*F64+F65 -> 7.24 | L63: MURO INTERNO | M63: AREA | N63: 0 | O63: =N63*N64+N65 -> 0
E64: CANTIDAD | F64: 2 | M64: CANTIDAD | N64: 2
E65: TAPA | F65: =7*0.4 -> 2.8 | M65: TAPA | N65: 0
B68: LONGITUDES Y AREAS | G68: Sub.TOTAL | H68: TOTAL (m2) | J68: LONGITUDES Y AREAS | O68: Sub.TOTAL | P68: TOTAL (m2)
B69: EJE 11 | C69: NORMAL | D69: MUROS EXTERNO | E69: AREA | F69: 34.95 | G69: =F69*F70 -> 69.9 | H69: =SUM(G69:G77) -> 150.624 | J69: EJE 12 | K69: NORMAL | L69: MUROS EXTERNO | M69: AREA | N69: 27.87 | O69: =N69*N70 -> 55.74 | P69: =SUM(O69:O77) -> 271.776
E70: CANT. | F70: 2 | M70: CANT. | N70: 2
D71: MURO INTERNO | E71: AREA | F71: 28.67 | G71: =F71*F72 -> 57.34 | L71: MURO INTERNO | M71: AREA | N71: 22.62 | O71: =N71*N72 -> 45.24
E72: CANTIDAD | F72: 2 | M72: CANTIDAD | N72: 2
C73: TAPADO | D73: MURO EXTERNO | E73: AREA | F73: 6.07 | G73: =F73*F74 -> 12.14 | K73: TAPADO | L73: MURO EXTERNO | M73: AREA | N73: 42.7 | O73: =N73*N74 -> 85.4
E74: CANT. | F74: 2 | M74: CANT. | N74: 2
D75: MURO INTERNO | E75: AREA | F75: 4.33 | G75: =F75*F76+F77 -> 11.244 | L75: MURO INTERNO | M75: AREA | N75: 31.37 | O75: =N75*N76+N77 -> 85.396
E76: CANTIDAD | F76: 2 | M76: CANTIDAD | N76: 2
E77: TAPA | F77: =6.46*0.4 -> 2.584 | M77: TAPA | N77: =56.64*0.4 -> 22.656

Sheet METRADO MONTANTES
B2: CALCULO DE MONTANTES POR EDIFICACION - DRENAJE PLUVIAL
B3: ENTIDAD | C3: =+RESUMEN!B4 -> GERENCIA TERRITORIAL BAJO MAYO - TARAPOTO
B4: PROYECTO | C4: =+RESUMEN!B5 -> “CREACIÓN DEL SERVICIO DE PROTECCIÓN A MUJERES VÍCTIMAS DE VIOLENCIA EN SITUACIÓN DE RIESGO DE FEMINICIDIO O PELIGRE SU INTEGRIDAD Y/O SALUD FÍSICA Y/O MENTAL EN HOGAR DE REFUGIO TEMPORAL DISTRITO DE MORALES DE LA PROVINCIA DE SAN MARTÍN DEL DEPARTAMENTO DE SAN MARTÍN”, con CUI N.° 2675514
B5: UBICACIÓN | C5: =+RESUMEN!B6 -> SAN MARTIN - SAN MARTIN - MORALES
B6: FECHA | C6: =+RESUMEN!B7 -> 46266
C9: MONTANTES | D9: LONG. TUBERIA PVC 4" | G9: CODO PVC 90° 4" | J9: ABRAZADERA 4" | M9: COLGADOR 4" | P9: CODO PVC 45° 4"
D10: VECES | E10: LONGITUD | F10: TOTAL (m) | G10: CANTIDAD | H10: VECES | I10: TOTAL (und) | J10: CANTIDAD | K10: VECES | L10: TOTAL (und) | M10: CANTIDAD | N10: VECES | O10: TOTAL (und) | P10: CANTIDAD | Q10: VECES | R10: TOTAL (und)
B11: EDIFICACION 01
B12: Lado A | C12: 3 | D12: =C12 -> 3 | E12: 5.9 | F12: =E12*D12 -> 17.7 | G12: 3 | H12: =C12 -> 3 | I12: =H12*G12 -> 9 | J12: =MAX(1,ROUNDDOWN(E12/4,0)) -> 1 | K12: =C12 -> 3 | L12: =K12*J12 -> 3 | M12: 2 | N12: =C12 -> 3 | O12: =N12*M12 -> 6 | R12: =Q12*P12 -> 0
B13: Lado B | C13: 3 | D13: =C13 -> 3 | E13: 5.9 | F13: =E13*D13 -> 17.7 | G13: 3 | H13: =C13 -> 3 | I13: =H13*G13 -> 9 | J13: =MAX(1,ROUNDDOWN(E13/4,0)) -> 1 | K13: =C13 -> 3 | L13: =K13*J13 -> 3 | M13: 2 | N13: =C13 -> 3 | O13: =N13*M13 -> 6 | R13: =Q13*P13 -> 0
B14: EDIFICACION 02
B15: Lado A | C15: 2 | D15: =C15 -> 2 | E15: 6.27 | F15: =E15*D15 -> 12.54 | G15: 3 | H15: =C15 -> 2 | I15: =H15*G15 -> 6 | J15: =MAX(1,ROUNDDOWN(E15/4,0)) -> 1 | K15: =C15 -> 2 | L15: =K15*J15 -> 2 | M15: 2 | N15: =C15 -> 2 | O15: =N15*M15 -> 4 | R15: =Q15*P15 -> 0
B16: Lado B | C16: 2 | D16: =C16 -> 2 | E16: 6.27 | F16: =E16*D16 -> 12.54 | G16: 3 | H16: =C16 -> 2 | I16: =H16*G16 -> 6 | J16: =MAX(1,ROUNDDOWN(E16/4,0)) -> 1 | K16: =C16 -> 2 | L16: =K16*J16 -> 2 | M16: 2 | N16: =C16 -> 2 | O16: =N16*M16 -> 4 | R16: =Q16*P16 -> 0
B17: EDIFICACION 03
B18: Lado A | C18: 2 | D18: =C18 -> 2 | E18: 6.35 | F18: =E18*D18 -> 12.7 | G18: 3 | H18: =C18 -> 2 | I18: =H18*G18 -> 6 | J18: =MAX(1,ROUNDDOWN(E18/4,0)) -> 1 | K18: =C18 -> 2 | L18: =K18*J18 -> 2 | M18: 2 | N18: =C18 -> 2 | O18: =N18*M18 -> 4 | R18: =Q18*P18 -> 0
B19: Lado B | C19: 2 | D19: =C19 -> 2 | E19: 6.35 | F19: =E19*D19 -> 12.7 | G19: 3 | H19: =C19 -> 2 | I19: =H19*G19 -> 6 | J19: =MAX(1,ROUNDDOWN(E19/4,0)) -> 1 | K19: =C19 -> 2 | L19: =K19*J19 -> 2 | M19: 2 | N19: =C19 -> 2 | O19: =N19*M19 -> 4 | R19: =Q19*P19 -> 0
B20: EDIFICACION 04
B21: Lado A | C21: 3 | D21: =C21 -> 3 | E21: 6.26 | F21: =E21*D21 -> 18.78 | G21: 3 | H21: =C21 -> 3 | I21: =H21*G21 -> 9 | J21: =MAX(1,ROUNDDOWN(E21/4,0)) -> 1 | K21: =C21 -> 3 | L21: =K21*J21 -> 3 | M21: 2 | N21: =C21 -> 3 | O21: =N21*M21 -> 6 | R21: =Q21*P21 -> 0
B22: Lado B | C22: 3 | D22: =C22 -> 3 | E22: 6.26 | F22: =E22*D22 -> 18.78 | G22: 3 | H22: =C22 -> 3 | I22: =H22*G22 -> 9 | J22: =MAX(1,ROUNDDOWN(E22/4,0)) -> 1 | K22: =C22 -> 3 | L22: =K22*J22 -> 3 | M22: 2 | N22: =C22 -> 3 | O22: =N22*M22 -> 6 | R22: =Q22*P22 -> 0
B23: EDIFICACION 05
B24: Lado A | C24: 3 | D24: =C24 -> 3 | E24: 7.53 | F24: =E24*D24 -> 22.59 | G24: 3 | H24: =C24 -> 3 | I24: =H24*G24 -> 9 | J24: =MAX(1,ROUNDDOWN(E24/4,0)) -> 1 | K24: =C24 -> 3 | L24: =K24*J24 -> 3 | M24: 2 | N24: =C24 -> 3 | O24: =N24*M24 -> 6 | R24: =Q24*P24 -> 0
B25: Lado B | C25: 3 | D25: =C25 -> 3 | E25: 7.53 | F25: =E25*D25 -> 22.59 | G25: 3 | H25: =C25 -> 3 | I25: =H25*G25 -> 9 | J25: =MAX(1,ROUNDDOWN(E25/4,0)) -> 1 | K25: =C25 -> 3 | L25: =K25*J25 -> 3 | M25: 2 | N25: =C25 -> 3 | O25: =N25*M25 -> 6 | R25: =Q25*P25 -> 0
B26: EDIFICACION 06
B27: Lado A | C27: 2 | D27: =C27 -> 2 | E27: 6.18 | F27: =E27*D27 -> 12.36 | G27: 3 | H27: =C27 -> 2 | I27: =H27*G27 -> 6 | J27: =MAX(1,ROUNDDOWN(E27/4,0)) -> 1 | K27: =C27 -> 2 | L27: =K27*J27 -> 2 | M27: 2 | N27: =C27 -> 2 | O27: =N27*M27 -> 4 | R27: =Q27*P27 -> 0
B28: Lado B | C28: 2 | D28: =C28 -> 2 | E28: 6.18 | F28: =E28*D28 -> 12.36 | G28: 3 | H28: =C28 -> 2 | I28: =H28*G28 -> 6 | J28: =MAX(1,ROUNDDOWN(E28/4,0)) -> 1 | K28: =C28 -> 2 | L28: =K28*J28 -> 2 | M28: 2 | N28: =C28 -> 2 | O28: =N28*M28 -> 4 | R28: =Q28*P28 -> 0
B29: EDIFICACION 07
B30: Lado A | C30: 3 | D30: =C30 -> 3 | E30: 6.24 | F30: =E30*D30 -> 18.72 | G30: 3 | H30: =C30 -> 3 | I30: =H30*G30 -> 9 | J30: =MAX(1,ROUNDDOWN(E30/4,0)) -> 1 | K30: =C30 -> 3 | L30: =K30*J30 -> 3 | M30: 2 | N30: =C30 -> 3 | O30: =N30*M30 -> 6 | R30: =Q30*P30 -> 0
B31: Lado B | C31: 3 | D31: =C31 -> 3 | E31: 6.24 | F31: =E31*D31 -> 18.72 | G31: 3 | H31: =C31 -> 3 | I31: =H31*G31 -> 9 | J31: =MAX(1,ROUNDDOWN(E31/4,0)) -> 1 | K31: =C31 -> 3 | L31: =K31*J31 -> 3 | M31: 2 | N31: =C31 -> 3 | O31: =N31*M31 -> 6 | R31: =Q31*P31 -> 0
B32: EDIFICACION 08
B33: Lado A | C33: 2 | D33: =C33 -> 2 | E33: 6.26 | F33: =E33*D33 -> 12.52 | G33: 3 | H33: =C33 -> 2 | I33: =H33*G33 -> 6 | J33: =MAX(1,ROUNDDOWN(E33/4,0)) -> 1 | K33: =C33 -> 2 | L33: =K33*J33 -> 2 | M33: 2 | N33: =C33 -> 2 | O33: =N33*M33 -> 4 | R33: =Q33*P33 -> 0
B34: Lado B | C34: 2 | D34: =C34 -> 2 | E34: 6.26 | F34: =E34*D34 -> 12.52 | G34: 3 | H34: =C34 -> 2 | I34: =H34*G34 -> 6 | J34: =MAX(1,ROUNDDOWN(E34/4,0)) -> 1 | K34: =C34 -> 2 | L34: =K34*J34 -> 2 | M34: 2 | N34: =C34 -> 2 | O34: =N34*M34 -> 4 | R34: =Q34*P34 -> 0
B35: EDIFICACION 09
B36: Lado A | C36: 2 | D36: =C36 -> 2 | E36: 6.26 | F36: =E36*D36 -> 12.52 | G36: 3 | H36: =C36 -> 2 | I36: =H36*G36 -> 6 | J36: =MAX(1,ROUNDDOWN(E36/4,0)) -> 1 | K36: =C36 -> 2 | L36: =K36*J36 -> 2 | M36: 2 | N36: =C36 -> 2 | O36: =N36*M36 -> 4 | R36: =Q36*P36 -> 0
B37: Lado B | C37: 2 | D37: =C37 -> 2 | E37: 6.26 | F37: =E37*D37 -> 12.52 | G37: 3 | H37: =C37 -> 2 | I37: =H37*G37 -> 6 | J37: =MAX(1,ROUNDDOWN(E37/4,0)) -> 1 | K37: =C37 -> 2 | L37: =K37*J37 -> 2 | M37: 2 | N37: =C37 -> 2 | O37: =N37*M37 -> 4 | R37: =Q37*P37 -> 0
B38: LOSA DEPORTIVA
B39: Lado A | C39: 4 | D39: =C39 -> 4 | E39: 11 | F39: =E39*D39 -> 44 | G39: 3 | H39: =C39 -> 4 | I39: =H39*G39 -> 12 | J39: 3 | K39: =C39 -> 4 | L39: =K39*J39 -> 12 | M39: 0 | N39: =C39 -> 4 | O39: =N39*M39 -> 0 | R39: =Q39*P39 -> 0
B40: Lado B | C40: 4 | D40: =C40 -> 4 | E40: 11 | F40: =E40*D40 -> 44 | G40: 3 | H40: =C40 -> 4 | I40: =H40*G40 -> 12 | J40: 3 | K40: =C40 -> 4 | L40: =K40*J40 -> 12 | M40: 0 | N40: =C40 -> 4 | O40: =N40*M40 -> 0 | R40: =Q40*P40 -> 0
B41: OBRA EXTERIOR 01 | C41: 1 | D41: =C41 -> 1 | E41: 6 | F41: =E41*D41 -> 6 | G41: 3 | H41: =C41 -> 1 | I41: =H41*G41 -> 3 | J41: 1 | K41: =C41 -> 1 | L41: =K41*J41 -> 1 | M41: 1 | N41: =C41 -> 1 | O41: =N41*M41 -> 1 | R41: =Q41*P41 -> 0
B42: OBRA EXTERIOR03 | C42: 1 | D42: =C42 -> 1 | E42: 6 | F42: =E42*D42 -> 6 | G42: 3 | H42: =C42 -> 1 | I42: =H42*G42 -> 3 | J42: 1 | K42: =C42 -> 1 | L42: =K42*J42 -> 1 | M42: 1 | N42: =C42 -> 1 | O42: =N42*M42 -> 1 | R42: =Q42*P42 -> 0
C43: =SUM(C11:C42) -> 54 | F43: =SUM(F11:F42) -> 380.86 | I43: =SUM(I11:I42) -> 162 | L43: =SUM(L11:L42) -> 70 | O43: =SUM(O11:O42) -> 90 | R43: =SUM(R11:R42) -> 0

Sheet METRADO CANALETAS
B2: METRADO DE CANALETAS DE TECHO - DRENAJE PLUVIAL
B3: ENTIDAD | C3: =+RESUMEN!B4 -> GERENCIA TERRITORIAL BAJO MAYO - TARAPOTO
B4: PROYECTO | C4: =+RESUMEN!B5 -> “CREACIÓN DEL SERVICIO DE PROTECCIÓN A MUJERES VÍCTIMAS DE VIOLENCIA EN SITUACIÓN DE RIESGO DE FEMINICIDIO O PELIGRE SU INTEGRIDAD Y/O SALUD FÍSICA Y/O MENTAL EN HOGAR DE REFUGIO TEMPORAL DISTRITO DE MORALES DE LA PROVINCIA DE SAN MARTÍN DEL DEPARTAMENTO DE SAN MARTÍN”, con CUI N.° 2675514
B5: UBICACIÓN | C5: =+RESUMEN!B6 -> SAN MARTIN - SAN MARTIN - MORALES
B6: FECHA | C6: =+RESUMEN!B7 -> 46266
B8: CANALETA DE PLANCHA DE ACERO GALVANIZADO - SECCIÓN INTERIOR 0.25 m (FONDO) x 0.20 m (ALTO) - TECHOS A DOS AGUAS: UNA CANALETA POR CADA LADO
B9: EDIFICACIÓN | C9: N° DE CANALETAS | D9: CANALETA 0.25 x 0.20 m | F9: SOPORTE PLATINA F°G° 1" x 1/8" | H9: TAPA LATERAL | J9: BOQUILLA A MONTANTE Ø4"
D10: LONGITUD (m) | E10: TOTAL (m) | F10: CANTIDAD | G10: TOTAL (und) | H10: CANTIDAD | I10: TOTAL (und) | J10: CANTIDAD | K10: TOTAL (und)
B11: EDIFICACION 01
B12: Lado 01 | C12: 1 | D12: 25.33 | E12: =C12*D12 -> 25.33 | F12: =IF(D12>0,ROUNDUP(D12/$F$50,0)+1,0) -> 44 | G12: =C12*F12 -> 44 | H12: =$F$51 -> 2 | I12: =C12*H12 -> 2 | J12: ='METRADO MONTANTES'!C12 -> 3 | K12: =C12*J12 -> 3
B13: Lado 02 | C13: 1 | D13: =D12 -> 25.33 | E13: =C13*D13 -> 25.33 | F13: =IF(D13>0,ROUNDUP(D13/$F$50,0)+1,0) -> 44 | G13: =C13*F13 -> 44 | H13: =$F$51 -> 2 | I13: =C13*H13 -> 2 | J13: ='METRADO MONTANTES'!C13 -> 3 | K13: =C13*J13 -> 3
B14: EDIFICACION 02
B15: Lado 01 | C15: 1 | D15: 14.33 | E15: =C15*D15 -> 14.33 | F15: =IF(D15>0,ROUNDUP(D15/$F$50,0)+1,0) -> 25 | G15: =C15*F15 -> 25 | H15: =$F$51 -> 2 | I15: =C15*H15 -> 2 | J15: ='METRADO MONTANTES'!C15 -> 2 | K15: =C15*J15 -> 2
B16: Lado 02 | C16: 1 | D16: =D15 -> 14.33 | E16: =C16*D16 -> 14.33 | F16: =IF(D16>0,ROUNDUP(D16/$F$50,0)+1,0) -> 25 | G16: =C16*F16 -> 25 | H16: =$F$51 -> 2 | I16: =C16*H16 -> 2 | J16: ='METRADO MONTANTES'!C16 -> 2 | K16: =C16*J16 -> 2
B17: EDIFICACION 03
B18: Lado 01 | C18: 1 | D18: 17.33 | E18: =C18*D18 -> 17.33 | F18: =IF(D18>0,ROUNDUP(D18/$F$50,0)+1,0) -> 30 | G18: =C18*F18 -> 30 | H18: =$F$51 -> 2 | I18: =C18*H18 -> 2 | J18: ='METRADO MONTANTES'!C18 -> 2 | K18: =C18*J18 -> 2
B19: Lado 02 | C19: 1 | D19: =D18 -> 17.33 | E19: =C19*D19 -> 17.33 | F19: =IF(D19>0,ROUNDUP(D19/$F$50,0)+1,0) -> 30 | G19: =C19*F19 -> 30 | H19: =$F$51 -> 2 | I19: =C19*H19 -> 2 | J19: ='METRADO MONTANTES'!C19 -> 2 | K19: =C19*J19 -> 2
B20: EDIFICACION 04
B21: Lado 01 | C21: 1 | D21: 38.13 | E21: =C21*D21 -> 38.13 | F21: =IF(D21>0,ROUNDUP(D21/$F$50,0)+1,0) -> 65 | G21: =C21*F21 -> 65 | H21: =$F$51 -> 2 | I21: =C21*H21 -> 2 | J21: ='METRADO MONTANTES'!C21 -> 3 | K21: =C21*J21 -> 3
B22: Lado 02 | C22: 1 | D22: =D21 -> 38.13 | E22: =C22*D22 -> 38.13 | F22: =IF(D22>0,ROUNDUP(D22/$F$50,0)+1,0) -> 65 | G22: =C22*F22 -> 65 | H22: =$F$51 -> 2 | I22: =C22*H22 -> 2 | J22: ='METRADO MONTANTES'!C22 -> 3 | K22: =C22*J22 -> 3
B23: EDIFICACION 05
B24: Lado 01 | C24: 1 | D24: 32.31 | E24: =C24*D24 -> 32.31 | F24: =IF(D24>0,ROUNDUP(D24/$F$50,0)+1,0) -> 55 | G24: =C24*F24 -> 55 | H24: =$F$51 -> 2 | I24: =C24*H24 -> 2 | J24: ='METRADO MONTANTES'!C24 -> 3 | K24: =C24*J24 -> 3
B25: Lado 02 | C25: 1 | D25: =D24 -> 32.31 | E25: =C25*D25 -> 32.31 | F25: =IF(D25>0,ROUNDUP(D25/$F$50,0)+1,0) -> 55 | G25: =C25*F25 -> 55 | H25: =$F$51 -> 2 | I25: =C25*H25 -> 2 | J25: ='METRADO MONTANTES'!C25 -> 3 | K25: =C25*J25 -> 3
B26: EDIFICACION 06
B27: Lado 01 | C27: 1 | D27: 20.73 | E27: =C27*D27 -> 20.73 | F27: =IF(D27>0,ROUNDUP(D27/$F$50,0)+1,0) -> 36 | G27: =C27*F27 -> 36 | H27: =$F$51 -> 2 | I27: =C27*H27 -> 2 | J27: ='METRADO MONTANTES'!C27 -> 2 | K27: =C27*J27 -> 2
B28: Lado 02 | C28: 1 | D28: =D27 -> 20.73 | E28: =C28*D28 -> 20.73 | F28: =IF(D28>0,ROUNDUP(D28/$F$50,0)+1,0) -> 36 | G28: =C28*F28 -> 36 | H28: =$F$51 -> 2 | I28: =C28*H28 -> 2 | J28: ='METRADO MONTANTES'!C28 -> 2 | K28: =C28*J28 -> 2
B29: EDIFICACION 07
B30: Lado 01 | C30: 1 | D30: 38.13 | E30: =C30*D30 -> 38.13 | F30: =IF(D30>0,ROUNDUP(D30/$F$50,0)+1,0) -> 65 | G30: =C30*F30 -> 65 | H30: =$F$51 -> 2 | I30: =C30*H30 -> 2 | J30: ='METRADO MONTANTES'!C30 -> 3 | K30: =C30*J30 -> 3
B31: Lado 02 | C31: 1 | D31: =D30 -> 38.13 | E31: =C31*D31 -> 38.13 | F31: =IF(D31>0,ROUNDUP(D31/$F$50,0)+1,0) -> 65 | G31: =C31*F31 -> 65 | H31: =$F$51 -> 2 | I31: =C31*H31 -> 2 | J31: ='METRADO MONTANTES'!C31 -> 3 | K31: =C31*J31 -> 3
B32: EDIFICACION 08
B33: Lado 01 | C33: 1 | D33: 20.73 | E33: =C33*D33 -> 20.73 | F33: =IF(D33>0,ROUNDUP(D33/$F$50,0)+1,0) -> 36 | G33: =C33*F33 -> 36 | H33: =$F$51 -> 2 | I33: =C33*H33 -> 2 | J33: ='METRADO MONTANTES'!C33 -> 2 | K33: =C33*J33 -> 2
B34: Lado 02 | C34: 1 | D34: =D33 -> 20.73 | E34: =C34*D34 -> 20.73 | F34: =IF(D34>0,ROUNDUP(D34/$F$50,0)+1,0) -> 36 | G34: =C34*F34 -> 36 | H34: =$F$51 -> 2 | I34: =C34*H34 -> 2 | J34: ='METRADO MONTANTES'!C34 -> 2 | K34: =C34*J34 -> 2
B35: EDIFICACION 09
B36: Lado 01 | C36: 1 | D36: 14.77 | E36: =C36*D36 -> 14.77 | F36: =IF(D36>0,ROUNDUP(D36/$F$50,0)+1,0) -> 26 | G36: =C36*F36 -> 26 | H36: =$F$51 -> 2 | I36: =C36*H36 -> 2 | J36: ='METRADO MONTANTES'!C36 -> 2 | K36: =C36*J36 -> 2
B37: Lado 02 | C37: 1 | D37: =D36 -> 14.77 | E37: =C37*D37 -> 14.77 | F37: =IF(D37>0,ROUNDUP(D37/$F$50,0)+1,0) -> 26 | G37: =C37*F37 -> 26 | H37: =$F$51 -> 2 | I37: =C37*H37 -> 2 | J37: ='METRADO MONTANTES'!C37 -> 2 | K37: =C37*J37 -> 2
B38: LOSA DEPORTIVA
B39: Lado 01 | C39: 1 | D39: 35.2 | E39: =C39*D39 -> 35.2 | F39: =IF(D39>0,ROUNDUP(D39/$F$50,0)+1,0) -> 60 | G39: =C39*F39 -> 60 | H39: =$F$51 -> 2 | I39: =C39*H39 -> 2 | J39: ='METRADO MONTANTES'!C39 -> 4 | K39: =C39*J39 -> 4
B40: Lado 02 | C40: 1 | D40: =D39 -> 35.2 | E40: =C40*D40 -> 35.2 | F40: =IF(D40>0,ROUNDUP(D40/$F$50,0)+1,0) -> 60 | G40: =C40*F40 -> 60 | H40: =$F$51 -> 2 | I40: =C40*H40 -> 2 | J40: ='METRADO MONTANTES'!C40 -> 4 | K40: =C40*J40 -> 4
B41: TOTAL | C41: =SUM(C11:C40) -> 20 | E41: =SUM(E11:E40) -> 513.98 | G41: =SUM(G11:G40) -> 884 | I41: =SUM(I11:I40) -> 40 | K41: =SUM(K11:K40) -> 52
B43: PARÁMETROS DE CÁLCULO - CANALETA
B44: DESCRIPCIÓN | F44: VALOR | G44: UNIDAD | H44: CRITERIO
B45: Fondo interior de canaleta | F45: 0.25 | G45: m | H45: Dato del proyecto
B46: Altura interior de canaleta | F46: 0.2 | G46: m | H46: Dato del proyecto
B47: Doblez o pestaña superior (por cada lado) | F47: 0.05 | G47: m | H47: Editable según detalle
B48: Desarrollo de plancha (fondo + 2 alturas + 2 dobleces) | F48: =F45+2*F46+2*F47 -> 0.75 | G48: m | H48: Calculado
B49: Espesor de plancha galvanizada | F49: 0.9 | G49: mm | H49: Editable según EE.TT. (cambiar también la descripción de la partida)
B50: Separación de soportes | F50: 0.6 | G50: m | H50: Editable. Soportes por canaleta = REDONDEAR.MAS(L / sep) + 1
B51: Tapas laterales por canaleta | F51: 2 | G51: und | H51: Una en cada extremo
B52: Área de plancha galvanizada (referencial) | F52: =E41*F48 -> 385.485 | G52: m² | H52: Total de canaleta x desarrollo. Solo referencia para el análisis de costos

Sheet METRADO  EN PISO (SUMIDERO)
A1: PLANILLA DE METRADOS - RED DE DRENAJE EN PISO Y SUMIDEROS
A2: ENTIDAD | B2: =+RESUMEN!B4 -> GERENCIA TERRITORIAL BAJO MAYO - TARAPOTO
A3: PROYECTO | B3: =+RESUMEN!B5 -> “CREACIÓN DEL SERVICIO DE PROTECCIÓN A MUJERES VÍCTIMAS DE VIOLENCIA EN SITUACIÓN DE RIESGO DE FEMINICIDIO O PELIGRE SU INTEGRIDAD Y/O SALUD FÍSICA Y/O MENTAL EN HOGAR DE REFUGIO TEMPORAL DISTRITO DE MORALES DE LA PROVINCIA DE SAN MARTÍN DEL DEPARTAMENTO DE SAN MARTÍN”, con CUI N.° 2675514
A4: UBICACIÓN | B4: =+RESUMEN!B6 -> SAN MARTIN - SAN MARTIN - MORALES
A5: FECHA | B5: =+RESUMEN!B7 -> 46266
A7: SECTOR | B7: TUBERÍA 4" PVC-U Desagüe Clase Pesada (m) | C7: SUMIDERO DE 4" (und) | D7: CODO 90° x 4" (und) | E7: CODO 45° x 4" (und) | F7: TEE° x 4" (und) | G7: OBSERVACIÓN
A8: SECTOR 01 | B8: 26.52 | C8: 6 | D8: 4 | E8: 0 | F8: 2 | G8: Según sector
A9: SECTOR 02 | B9: 27.18 | C9: 8 | D9: 4 | E9: 0 | F9: 2 | G9: Según sector
A10: SECTOR 03 | B10: 32 | C10: 6 | D10: 6 | E10: 0 | F10: 0 | G10: Según sector
A11: SECTOR 04 | B11: 26.56 | C11: 10 | D11: 10 | E11: 0 | F11: 0 | G11: Según sector
A12: TOTAL | B12: =SUM(B8:B11) -> 112.26 | C12: =SUM(C8:C11) -> 30 | D12: =SUM(D8:D11) -> 24 | E12: =SUM(E8:E11) -> 0 | F12: =SUM(F8:F11) -> 4

Sheet METRADO ACERO
A2: METRADO DE ACERO EN CUNETAS - DRENAJE PLUVIAL
A3: ENTIDAD | B3: =+RESUMEN!B4 -> GERENCIA TERRITORIAL BAJO MAYO - TARAPOTO
A4: PROYECTO | B4: =+RESUMEN!B5 -> “CREACIÓN DEL SERVICIO DE PROTECCIÓN A MUJERES VÍCTIMAS DE VIOLENCIA EN SITUACIÓN DE RIESGO DE FEMINICIDIO O PELIGRE SU INTEGRIDAD Y/O SALUD FÍSICA Y/O MENTAL EN HOGAR DE REFUGIO TEMPORAL DISTRITO DE MORALES DE LA PROVINCIA DE SAN MARTÍN DEL DEPARTAMENTO DE SAN MARTÍN”, con CUI N.° 2675514
A5: UBICACIÓN | B5: =+RESUMEN!B6 -> SAN MARTIN - SAN MARTIN - MORALES
A6: FECHA | B6: =+RESUMEN!B7 -> 46266
A8: METRADO DETALLADO POR EJE Y POR TRAMO
A9: IDENTIFICACIÓN Y GEOMETRÍA | H9: ACERO LONGITUDINAL DEL CUERPO U | P9: ACERO TRANSVERSAL DEL CUERPO U | X9: ACERO TRANSVERSAL DE LA TAPA (SOLO CUNETA TAPADA) | AG9: RESULTADO
A10: N° | B10: EJE | C10: TRAMO | D10: TIPO DE CUNETA | E10: SEC. INI | F10: SEC. FIN | G10: LONGITUD TRAMO (m) | H10: Ø CUERPO | I10: FACTOR CUERPO (kg/m) | J10: SEP. LONG. (m) | K10: BARRAS LONG. INI | L10: BARRAS LONG. FIN | M10: BARRAS PROM. | N10: LONG. ACERO LONG. (m) | O10: KG LONG. | P10: SEP. TRANSV. U (m) | Q10: DES. TRANSV. U INI (m) | R10: DES. TRANSV. U FIN (m) | S10: DES. PROM. U (m) | T10: CANT. TRANSV. U | U10: LONG. ACERO TRANSV. U (m) | V10: KG TRANSV. U | W10: TOTAL KG CUERPO U | X10: Ø TAPA | Y10: FACTOR TAPA (kg/m) | Z10: SEP. TRANSV. TAPA (m) | AA10: LONG. BARRA TAPA INI (m) | AB10: LONG. BARRA TAPA FIN (m) | AC10: LONG. PROM. TAPA (m) | AD10: CANT. BARRAS TAPA | AE10: LONG. ACERO TAPA (m) | AF10: KG ACERO TAPA | AG10: TOTAL KG TRAMO
A11: 1 | B11: EJE 01 | C11: TRAMO 01 | D11: ABIERTA | E11: SEC 02 | F11: SEC 03 | G11: 12 | H11: 3/8" | I11: =IF(H11="","",IFERROR(VLOOKUP(H11,Listas!$A$4:$B$11,2,FALSE()),"")) -> 0.56 | J11: 0.21 | K11: 7 | L11: 7 | M11: =IF(B11="","",(K11+L11)/2) -> 7 | N11: =IF(B11="","",G11*M11) -> 84 | O11: =IF(B11="","",N11*I11) -> 47.04 | P11: 0.25 | Q11: 1.42 | R11: 1.5 | S11: =IF(B11="","",(Q11+R11)/2) -> 1.46 | T11: =IF(B11="","",IFERROR(IF($X$1="ENTERO (redondeo arriba)",ROUNDUP(G11/P11,0)+1,G11/P11+1),0)) -> 49 | U11: =IF(B11="","",S11*T11) -> 71.54 | V11: =IF(B11="","",U11*I11) -> 40.0624 | W11: =IF(B11="","",O11+V11) -> 87.1024 | AC11: =IF(B11="","",IF(D11="TAPADA",(AA11+AB11)/2,0)) -> 0 | AD11: =IF(B11="","",IF(D11="TAPADA",IFERROR(IF($X$1="ENTERO (redondeo arriba)",ROUNDUP(G11/Z11,0)+1,G11/Z11+1),0),0)) -> 0 | AE11: =IF(B11="","",IF(D11="TAPADA",AC11*AD11,0)) -> 0 | AF11: =IF(B11="","",IF(D11="TAPADA",AE11*Y11,0)) -> 0 | AG11: =IF(B11="","",W11+AF11) -> 87.1024
A12: 2 | B12: EJE 01 | C12: TRAMO 02 | D12: TAPADA | E12: SEC 03 | F12: SEC 04 | G12: 5.14 | H12: 3/8" | I12: =IF(H12="","",IFERROR(VLOOKUP(H12,Listas!$A$4:$B$11,2,FALSE()),"")) -> 0.56 | J12: 0.23 | K12: 8 | L12: 8 | M12: =IF(B12="","",(K12+L12)/2) -> 8 | N12: =IF(B12="","",G12*M12) -> 41.12 | O12: =IF(B12="","",N12*I12) -> 23.0272 | P12: 0.25 | Q12: 1.5 | R12: 1.58 | S12: =IF(B12="","",(Q12+R12)/2) -> 1.54 | T12: =IF(B12="","",IFERROR(IF($X$1="ENTERO (redondeo arriba)",ROUNDUP(G12/P12,0)+1,G12/P12+1),0)) -> 21.56 | U12: =IF(B12="","",S12*T12) -> 33.2024 | V12: =IF(B12="","",U12*I12) -> 18.593344 | W12: =IF(B12="","",O12+V12) -> 41.620544 | X12: 3/8" | Y12: 0.56 | Z12: 0.25 | AA12: 0.56 | AB12: 0.56 | AC12: =IF(B12="","",IF(D12="TAPADA",(AA12+AB12)/2,0)) -> 0.56 | AD12: =IF(B12="","",IF(D12="TAPADA",IFERROR(IF($X$1="ENTERO (redondeo arriba)",ROUNDUP(G12/Z12,0)+1,G12/Z12+1),0),0)) -> 21.56 | AE12: =IF(B12="","",IF(D12="TAPADA",AC12*AD12,0)) -> 12.0736 | AF12: =IF(B12="","",IF(D12="TAPADA",AE12*Y12,0)) -> 6.761216 | AG12: =IF(B12="","",W12+AF12) -> 48.38176
A13: 3 | B13: EJE 02 | C13: TRAMO 01 | D13: ABIERTA | E13: SEC 06 | F13: SEC 07 | G13: 17.5 | H13: 3/8" | I13: =IF(H13="","",IFERROR(VLOOKUP(H13,Listas!$A$4:$B$11,2,FALSE()),"")) -> 0.56 | J13: 0.23 | K13: 7 | L13: 7 | M13: =IF(B13="","",(K13+L13)/2) -> 7 | N13: =IF(B13="","",G13*M13) -> 122.5 | O13: =IF(B13="","",N13*I13) -> 68.6 | P13: 0.25 | Q13: 1.42 | R13: 1.58 | S13: =IF(B13="","",(Q13+R13)/2) -> 1.5 | T13: =IF(B13="","",IFERROR(IF($X$1="ENTERO (redondeo arriba)",ROUNDUP(G13/P13,0)+1,G13/P13+1),0)) -> 71 | U13: =IF(B13="","",S13*T13) -> 106.5 | V13: =IF(B13="","",U13*I13) -> 59.64 | W13: =IF(B13="","",O13+V13) -> 128.24 | AC13: =IF(B13="","",IF(D13="TAPADA",(AA13+AB13)/2,0)) -> 0 | AD13: =IF(B13="","",IF(D13="TAPADA",IFERROR(IF($X$1="ENTERO (redondeo arriba)",ROUNDUP(G13/Z13,0)+1,G13/Z13+1),0),0)) -> 0 | AE13: =IF(B13="","",IF(D13="TAPADA",AC13*AD13,0)) -> 0 | AF13: =IF(B13="","",IF(D13="TAPADA",AE13*Y13,0)) -> 0 | AG13: =IF(B13="","",W13+AF13) -> 128.24
A14: 4 | B14: EJE 02 | C14: TRAMO 02 | D14: TAPADA | E14: SEC 07 | F14: SEC 08 | G14: 10.2 | H14: 3/8" | I14: =IF(H14="","",IFERROR(VLOOKUP(H14,Listas!$A$4:$B$11,2,FALSE()),"")) -> 0.56 | J14: 0.22 | K14: 8 | L14: 10 | M14: =IF(B14="","",(K14+L14)/2) -> 9 | N14: =IF(B14="","",G14*M14) -> 91.8 | O14: =IF(B14="","",N14*I14) -> 51.408 | P14: 0.25 | Q14: 1.58 | R14: 1.66 | S14: =IF(B14="","",(Q14+R14)/2) -> 1.62 | T14: =IF(B14="","",IFERROR(IF($X$1="ENTERO (redondeo arriba)",ROUNDUP(G14/P14,0)+1,G14/P14+1),0)) -> 41.8 | U14: =IF(B14="","",S14*T14) -> 67.716 | V14: =IF(B14="","",U14*I14) -> 37.92096 | W14: =IF(B14="","",O14+V14) -> 89.32896 | X14: 3/8" | Y14: 0.56 | Z14: 0.25 | AA14: 0.56 | AB14: 0.56 | AC14: =IF(B14="","",IF(D14="TAPADA",(AA14+AB14)/2,0)) -> 0.56 | AD14: =IF(B14="","",IF(D14="TAPADA",IFERROR(IF($X$1="ENTERO (redondeo arriba)",ROUNDUP(G14/Z14,0)+1,G14/Z14+1),0),0)) -> 41.8 | AE14: =IF(B14="","",IF(D14="TAPADA",AC14*AD14,0)) -> 23.408 | AF14: =IF(B14="","",IF(D14="TAPADA",AE14*Y14,0)) -> 13.10848 | AG14: =IF(B14="","",W14+AF14) -> 102.43744
A15: 5 | B15: EJE 02 | C15: TRAMO 03 | D15: ABIERTA | E15: SEC 08 | F15: SEC 09 | G15: 31.33 | H15: 3/8" | I15: =IF(H15="","",IFERROR(VLOOKUP(H15,Listas!$A$4:$B$11,2,FALSE()),"")) -> 0.56 | J15: 0.2 | K15: 9 | L15: 9 | M15: =IF(B15="","",(K15+L15)/2) -> 9 | N15: =IF(B15="","",G15*M15) -> 281.97 | O15: =IF(B15="","",N15*I15) -> 157.9032 | P15: 0.25 | Q15: 1.66 | R15: 2.02 | S15: =IF(B15="","",(Q15+R15)/2) -> 1.84 | T15: =IF(B15="","",IFERROR(IF($X$1="ENTERO (redondeo arriba)",ROUNDUP(G15/P15,0)+1,G15/P15+1),0)) -> 126.32 | U15: =IF(B15="","",S15*T15) -> 232.4288 | V15: =IF(B15="","",U15*I15) -> 130.16013 | W15: =IF(B15="","",O15+V15) -> 288.06333 | AC15: =IF(B15="","",IF(D15="TAPADA",(AA15+AB15)/2,0)) -> 0 | AD15: =IF(B15="","",IF(D15="TAPADA",IFERROR(IF($X$1="ENTERO (redondeo arriba)",ROUNDUP(G15/Z15,0)+1,G15/Z15+1),0),0)) -> 0 | AE15: =IF(B15="","",IF(D15="TAPADA",AC15*AD15,0)) -> 0 | AF15: =IF(B15="","",IF(D15="TAPADA",AE15*Y15,0)) -> 0 | AG15: =IF(B15="","",W15+AF15) -> 288.06333
A16: 6 | B16: EJE 02 | C16: TRAMO 04 | D16: TAPADA | E16: SEC 09 | F16: SEC 10 | G16: 8.36 | H16: 3/8" | I16: =IF(H16="","",IFERROR(VLOOKUP(H16,Listas!$A$4:$B$11,2,FALSE()),"")) -> 0.56 | J16: 0.23 | K16: 10 | L16: 10 | M16: =IF(B16="","",(K16+L16)/2) -> 10 | N16: =IF(B16="","",G16*M16) -> 83.6 | O16: =IF(B16="","",N16*I16) -> 46.816 | P16: 0.25 | Q16: 2.02 | R16: 2.08 | S16: =IF(B16="","",(Q16+R16)/2) -> 2.05 | T16: =IF(B16="","",IFERROR(IF($X$1="ENTERO (redondeo arriba)",ROUNDUP(G16/P16,0)+1,G16/P16+1),0)) -> 34.44 | U16: =IF(B16="","",S16*T16) -> 70.602 | V16: =IF(B16="","",U16*I16) -> 39.53712 | W16: =IF(B16="","",O16+V16) -> 86.35312 | X16: 3/8" | Y16: 0.56 | Z16: 0.25 | AA16: 0.56 | AB16: 0.56 | AC16: =IF(B16="","",IF(D16="TAPADA",(AA16+AB16)/2,0)) -> 0.56 | AD16: =IF(B16="","",IF(D16="TAPADA",IFERROR(IF($X$1="ENTERO (redondeo arriba)",ROUNDUP(G16/Z16,0)+1,G16/Z16+1),0),0)) -> 34.44 | AE16: =IF(B16="","",IF(D16="TAPADA",AC16*AD16,0)) -> 19.2864 | AF16: =IF(B16="","",IF(D16="TAPADA",AE16*Y16,0)) -> 10.800384 | AG16: =IF(B16="","",W16+AF16) -> 97.153504
A17: 7 | B17: EJE 02 | C17: TRAMO 05 | D17: ABIERTA | E17: SEC 10 | F17: SEC 11 | G17: 30.36 | H17: 3/8" | I17: =IF(H17="","",IFERROR(VLOOKUP(H17,Listas!$A$4:$B$11,2,FALSE()),"")) -> 0.56 | J17: 0.22 | K17: 9 | L17: 11 | M17: =IF(B17="","",(K17+L17)/2) -> 10 | N17: =IF(B17="","",G17*M17) -> 303.6 | O17: =IF(B17="","",N17*I17) -> 170.016 | P17: 0.25 | Q17: 2.08 | R17: 2.36 | S17: =IF(B17="","",(Q17+R17)/2) -> 2.22 | T17: =IF(B17="","",IFERROR(IF($X$1="ENTERO (redondeo arriba)",ROUNDUP(G17/P17,0)+1,G17/P17+1),0)) -> 122.44 | U17: =IF(B17="","",S17*T17) -> 271.8168 | V17: =IF(B17="","",U17*I17) -> 152.21741 | W17: =IF(B17="","",O17+V17) -> 322.23341 | AC17: =IF(B17="","",IF(D17="TAPADA",(AA17+AB17)/2,0)) -> 0 | AD17: =IF(B17="","",IF(D17="TAPADA",IFERROR(IF($X$1="ENTERO (redondeo arriba)",ROUNDUP(G17/Z17,0)+1,G17/Z17+1),0),0)) -> 0 | AE17: =IF(B17="","",IF(D17="TAPADA",AC17*AD17,0)) -> 0 | AF17: =IF(B17="","",IF(D17="TAPADA",AE17*Y17,0)) -> 0 | AG17: =IF(B17="","",W17+AF17) -> 322.23341
A18: 8 | B18: EJE 02 | C18: TRAMO 06 | D18: TAPADA | E18: SEC 11 | F18: SEC 12 | G18: 2.25 | H18: 3/8" | I18: =IF(H18="","",IFERROR(VLOOKUP(H18,Listas!$A$4:$B$11,2,FALSE()),"")) -> 0.56 | J18: 0.22 | K18: 12 | L18: 12 | M18: =IF(B18="","",(K18+L18)/2) -> 12 | N18: =IF(B18="","",G18*M18) -> 27 | O18: =IF(B18="","",N18*I18) -> 15.12 | P18: 0.25 | Q18: 2.36 | R18: 2.42 | S18: =IF(B18="","",(Q18+R18)/2) -> 2.39 | T18: =IF(B18="","",IFERROR(IF($X$1="ENTERO (redondeo arriba)",ROUNDUP(G18/P18,0)+1,G18/P18+1),0)) -> 10 | U18: =IF(B18="","",S18*T18) -> 23.9 | V18: =IF(B18="","",U18*I18) -> 13.384 | W18: =IF(B18="","",O18+V18) -> 28.504 | X18: 3/8" | Y18: 0.56 | Z18: 0.25 | AA18: 0.56 | AB18: 0.56 | AC18: =IF(B18="","",IF(D18="TAPADA",(AA18+AB18)/2,0)) -> 0.56 | AD18: =IF(B18="","",IF(D18="TAPADA",IFERROR(IF($X$1="ENTERO (redondeo arriba)",ROUNDUP(G18/Z18,0)+1,G18/Z18+1),0),0)) -> 10 | AE18: =IF(B18="","",IF(D18="TAPADA",AC18*AD18,0)) -> 5.6 | AF18: =IF(B18="","",IF(D18="TAPADA",AE18*Y18,0)) -> 3.136 | AG18: =IF(B18="","",W18+AF18) -> 31.64
A19: 9 | B19: EJE 02 | C19: TRAMO 07 | D19: TAPADA | E19: SEC 13 | F19: SEC 14 | G19: 10.85 | H19: 3/8" | I19: =IF(H19="","",IFERROR(VLOOKUP(H19,Listas!$A$4:$B$11,2,FALSE()),"")) -> 0.56 | J19: 0.21 | K19: 12 | L19: 12 | M19: =IF(B19="","",(K19+L19)/2) -> 12 | N19: =IF(B19="","",G19*M19) -> 130.2 | O19: =IF(B19="","",N19*I19) -> 72.912 | P19: 0.25 | Q19: 2.32 | R19: 2.42 | S19: =IF(B19="","",(Q19+R19)/2) -> 2.37 | T19: =IF(B19="","",IFERROR(IF($X$1="ENTERO (redondeo arriba)",ROUNDUP(G19/P19,0)+1,G19/P19+1),0)) -> 44.4 | U19: =IF(B19="","",S19*T19) -> 105.228 | V19: =IF(B19="","",U19*I19) -> 58.92768 | W19: =IF(B19="","",O19+V19) -> 131.83968 | X19: 3/8" | Y19: 0.56 | Z19: 0.25 | AA19: 0.56 | AB19: 0.56 | AC19: =IF(B19="","",IF(D19="TAPADA",(AA19+AB19)/2,0)) -> 0.56 | AD19: =IF(B19="","",IF(D19="TAPADA",IFERROR(IF($X$1="ENTERO (redondeo arriba)",ROUNDUP(G19/Z19,0)+1,G19/Z19+1),0),0)) -> 44.4 | AE19: =IF(B19="","",IF(D19="TAPADA",AC19*AD19,0)) -> 24.864 | AF19: =IF(B19="","",IF(D19="TAPADA",AE19*Y19,0)) -> 13.92384 | AG19: =IF(B19="","",W19+AF19) -> 145.76352
A20: 10 | B20: EJE 05 | C20: TRAMO 01 | D20: ABIERTA | E20: SEC 20 | F20: SEC 21 | G20: 17.53 | H20: 3/8" | I20: =IF(H20="","",IFERROR(VLOOKUP(H20,Listas!$A$4:$B$11,2,FALSE()),"")) -> 0.56 | J20: 0.22 | K20: 7 | L20: 7 | M20: =IF(B20="","",(K20+L20)/2) -> 7 | N20: =IF(B20="","",G20*M20) -> 122.71 | O20: =IF(B20="","",N20*I20) -> 68.7176 | P20: 0.25 | Q20: 1.42 | R20: 1.58 | S20: =IF(B20="","",(Q20+R20)/2) -> 1.5 | T20: =IF(B20="","",IFERROR(IF($X$1="ENTERO (redondeo arriba)",ROUNDUP(G20/P20,0)+1,G20/P20+1),0)) -> 71.12 | U20: =IF(B20="","",S20*T20) -> 106.68 | V20: =IF(B20="","",U20*I20) -> 59.7408 | W20: =IF(B20="","",O20+V20) -> 128.4584 | AC20: =IF(B20="","",IF(D20="TAPADA",(AA20+AB20)/2,0)) -> 0 | AD20: =IF(B20="","",IF(D20="TAPADA",IFERROR(IF($X$1="ENTERO (redondeo arriba)",ROUNDUP(G20/Z20,0)+1,G20/Z20+1),0),0)) -> 0 | AE20: =IF(B20="","",IF(D20="TAPADA",AC20*AD20,0)) -> 0 | AF20: =IF(B20="","",IF(D20="TAPADA",AE20*Y20,0)) -> 0 | AG20: =IF(B20="","",W20+AF20) -> 128.4584
A21: 11 | B21: EJE 05 | C21: TRAMO 02 | D21: TAPADA | E21: SEC 21 | F21: SEC 22 | G21: 5.7 | H21: 3/8" | I21: =IF(H21="","",IFERROR(VLOOKUP(H21,Listas!$A$4:$B$11,2,FALSE()),"")) -> 0.56 | J21: 0.21 | K21: 8 | L21: 10 | M21: =IF(B21="","",(K21+L21)/2) -> 9 | N21: =IF(B21="","",G21*M21) -> 51.3 | O21: =IF(B21="","",N21*I21) -> 28.728 | P21: 0.25 | Q21: 1.58 | R21: 1.62 | S21: =IF(B21="","",(Q21+R21)/2) -> 1.6 | T21: =IF(B21="","",IFERROR(IF($X$1="ENTERO (redondeo arriba)",ROUNDUP(G21/P21,0)+1,G21/P21+1),0)) -> 23.8 | U21: =IF(B21="","",S21*T21) -> 38.08 | V21: =IF(B21="","",U21*I21) -> 21.3248 | W21: =IF(B21="","",O21+V21) -> 50.0528 | X21: 3/8" | Y21: 0.56 | Z21: 0.25 | AA21: 0.56 | AB21: 0.56 | AC21: =IF(B21="","",IF(D21="TAPADA",(AA21+AB21)/2,0)) -> 0.56 | AD21: =IF(B21="","",IF(D21="TAPADA",IFERROR(IF($X$1="ENTERO (redondeo arriba)",ROUNDUP(G21/Z21,0)+1,G21/Z21+1),0),0)) -> 23.8 | AE21: =IF(B21="","",IF(D21="TAPADA",AC21*AD21,0)) -> 13.328 | AF21: =IF(B21="","",IF(D21="TAPADA",AE21*Y21,0)) -> 7.46368 | AG21: =IF(B21="","",W21+AF21) -> 57.51648
A22: 12 | B22: EJE 06 | C22: TRAMO 01 | D22: ABIERTA | E22: SEC 24 | F22: SEC 25 | G22: 17.53 | H22: 3/8" | I22: =IF(H22="","",IFERROR(VLOOKUP(H22,Listas!$A$4:$B$11,2,FALSE()),"")) -> 0.56 | J22: 0.22 | K22: 7 | L22: 7 | M22: =IF(B22="","",(K22+L22)/2) -> 7 | N22: =IF(B22="","",G22*M22) -> 122.71 | O22: =IF(B22="","",N22*I22) -> 68.7176 | P22: 0.25 | Q22: 1.42 | R22: 1.58 | S22: =IF(B22="","",(Q22+R22)/2) -> 1.5 | T22: =IF(B22="","",IFERROR(IF($X$1="ENTERO (redondeo arriba)",ROUNDUP(G22/P22,0)+1,G22/P22+1),0)) -> 71.12 | U22: =IF(B22="","",S22*T22) -> 106.68 | V22: =IF(B22="","",U22*I22) -> 59.7408 | W22: =IF(B22="","",O22+V22) -> 128.4584 | AC22: =IF(B22="","",IF(D22="TAPADA",(AA22+AB22)/2,0)) -> 0 | AD22: =IF(B22="","",IF(D22="TAPADA",IFERROR(IF($X$1="ENTERO (redondeo arriba)",ROUNDUP(G22/Z22,0)+1,G22/Z22+1),0),0)) -> 0 | AE22: =IF(B22="","",IF(D22="TAPADA",AC22*AD22,0)) -> 0 | AF22: =IF(B22="","",IF(D22="TAPADA",AE22*Y22,0)) -> 0 | AG22: =IF(B22="","",W22+AF22) -> 128.4584
A23: 13 | B23: EJE 06 | C23: TRAMO 02 | D23: TAPADA | E23: SEC 25 | F23: SEC 26 | G23: 10.9 | H23: 3/8" | I23: =IF(H23="","",IFERROR(VLOOKUP(H23,Listas!$A$4:$B$11,2,FALSE()),"")) -> 0.56 | J23: 0.22 | K23: 8 | L23: 10 | M23: =IF(B23="","",(K23+L23)/2) -> 9 | N23: =IF(B23="","",G23*M23) -> 98.1 | O23: =IF(B23="","",N23*I23) -> 54.936 | P23: 0.25 | Q23: 1.58 | R23: 1.7 | S23: =IF(B23="","",(Q23+R23)/2) -> 1.64 | T23: =IF(B23="","",IFERROR(IF($X$1="ENTERO (redondeo arriba)",ROUNDUP(G23/P23,0)+1,G23/P23+1),0)) -> 44.6 | U23: =IF(B23="","",S23*T23) -> 73.144 | V23: =IF(B23="","",U23*I23) -> 40.96064 | W23: =IF(B23="","",O23+V23) -> 95.89664 | X23: 3/8" | Y23: 0.56 | Z23: 0.25 | AA23: 0.56 | AB23: 0.56 | AC23: =IF(B23="","",IF(D23="TAPADA",(AA23+AB23)/2,0)) -> 0.56 | AD23: =IF(B23="","",IF(D23="TAPADA",IFERROR(IF($X$1="ENTERO (redondeo arriba)",ROUNDUP(G23/Z23,0)+1,G23/Z23+1),0),0)) -> 44.6 | AE23: =IF(B23="","",IF(D23="TAPADA",AC23*AD23,0)) -> 24.976 | AF23: =IF(B23="","",IF(D23="TAPADA",AE23*Y23,0)) -> 13.98656 | AG23: =IF(B23="","",W23+AF23) -> 109.8832
A24: 14 | B24: EJE 06 | C24: TRAMO 03 | D24: ABIERTA | E24: SEC 26 | F24: SEC 27 | G24: 56.93 | H24: 3/8" | I24: =IF(H24="","",IFERROR(VLOOKUP(H24,Listas!$A$4:$B$11,2,FALSE()),"")) -> 0.56 | J24: 0.2 | K24: 9 | L24: 11 | M24: =IF(B24="","",(K24+L24)/2) -> 10 | N24: =IF(B24="","",G24*M24) -> 569.3 | O24: =IF(B24="","",N24*I24) -> 318.808 | P24: 0.25 | Q24: 1.7 | R24: 2.26 | S24: =IF(B24="","",(Q24+R24)/2) -> 1.98 | T24: =IF(B24="","",IFERROR(IF($X$1="ENTERO (redondeo arriba)",ROUNDUP(G24/P24,0)+1,G24/P24+1),0)) -> 228.72 | U24: =IF(B24="","",S24*T24) -> 452.8656 | V24: =IF(B24="","",U24*I24) -> 253.60474 | W24: =IF(B24="","",O24+V24) -> 572.41274 | AC24: =IF(B24="","",IF(D24="TAPADA",(AA24+AB24)/2,0)) -> 0 | AD24: =IF(B24="","",IF(D24="TAPADA",IFERROR(IF($X$1="ENTERO (redondeo arriba)",ROUNDUP(G24/Z24,0)+1,G24/Z24+1),0),0)) -> 0 | AE24: =IF(B24="","",IF(D24="TAPADA",AC24*AD24,0)) -> 0 | AF24: =IF(B24="","",IF(D24="TAPADA",AE24*Y24,0)) -> 0 | AG24: =IF(B24="","",W24+AF24) -> 572.41274
A25: 15 | B25: EJE 06 | C25: TRAMO 04 | D25: TAPADA | E25: SEC 27 | F25: SEC 28 | G25: 15 | H25: 3/8" | I25: =IF(H25="","",IFERROR(VLOOKUP(H25,Listas!$A$4:$B$11,2,FALSE()),"")) -> 0.56 | J25: 0.21 | K25: 12 | L25: 12 | M25: =IF(B25="","",(K25+L25)/2) -> 12 | N25: =IF(B25="","",G25*M25) -> 180 | O25: =IF(B25="","",N25*I25) -> 100.8 | P25: 0.25 | Q25: 2.26 | R25: 2.42 | S25: =IF(B25="","",(Q25+R25)/2) -> 2.34 | T25: =IF(B25="","",IFERROR(IF($X$1="ENTERO (redondeo arriba)",ROUNDUP(G25/P25,0)+1,G25/P25+1),0)) -> 61 | U25: =IF(B25="","",S25*T25) -> 142.74 | V25: =IF(B25="","",U25*I25) -> 79.9344 | W25: =IF(B25="","",O25+V25) -> 180.7344 | X25: 3/8" | Y25: 0.56 | Z25: 0.25 | AA25: 0.56 | AB25: 0.56 | AC25: =IF(B25="","",IF(D25="TAPADA",(AA25+AB25)/2,0)) -> 0.56 | AD25: =IF(B25="","",IF(D25="TAPADA",IFERROR(IF($X$1="ENTERO (redondeo arriba)",ROUNDUP(G25/Z25,0)+1,G25/Z25+1),0),0)) -> 61 | AE25: =IF(B25="","",IF(D25="TAPADA",AC25*AD25,0)) -> 34.16 | AF25: =IF(B25="","",IF(D25="TAPADA",AE25*Y25,0)) -> 19.1296 | AG25: =IF(B25="","",W25+AF25) -> 199.864
A26: 16 | B26: EJE 07 | C26: TRAMO 01 | D26: ABIERTA | E26: SEC 30 | F26: SEC 31 | G26: 17.53 | H26: 3/8" | I26: =IF(H26="","",IFERROR(VLOOKUP(H26,Listas!$A$4:$B$11,2,FALSE()),"")) -> 0.56 | J26: 0.22 | K26: 7 | L26: 7 | M26: =IF(B26="","",(K26+L26)/2) -> 7 | N26: =IF(B26="","",G26*M26) -> 122.71 | O26: =IF(B26="","",N26*I26) -> 68.7176 | P26: 0.25 | Q26: 1.42 | R26: 1.58 | S26: =IF(B26="","",(Q26+R26)/2) -> 1.5 | T26: =IF(B26="","",IFERROR(IF($X$1="ENTERO (redondeo arriba)",ROUNDUP(G26/P26,0)+1,G26/P26+1),0)) -> 71.12 | U26: =IF(B26="","",S26*T26) -> 106.68 | V26: =IF(B26="","",U26*I26) -> 59.7408 | W26: =IF(B26="","",O26+V26) -> 128.4584 | AC26: =IF(B26="","",IF(D26="TAPADA",(AA26+AB26)/2,0)) -> 0 | AD26: =IF(B26="","",IF(D26="TAPADA",IFERROR(IF($X$1="ENTERO (redondeo arriba)",ROUNDUP(G26/Z26,0)+1,G26/Z26+1),0),0)) -> 0 | AE26: =IF(B26="","",IF(D26="TAPADA",AC26*AD26,0)) -> 0 | AF26: =IF(B26="","",IF(D26="TAPADA",AE26*Y26,0)) -> 0 | AG26: =IF(B26="","",W26+AF26) -> 128.4584
A27: 17 | B27: EJE 07 | C27: TRAMO 02 | D27: TAPADA | E27: SEC 31 | F27: SEC 32 | G27: 7.66 | H27: 3/8" | I27: =IF(H27="","",IFERROR(VLOOKUP(H27,Listas!$A$4:$B$11,2,FALSE()),"")) -> 0.56 | J27: 0.22 | K27: 8 | L27: 10 | M27: =IF(B27="","",(K27+L27)/2) -> 9 | N27: =IF(B27="","",G27*M27) -> 68.94 | O27: =IF(B27="","",N27*I27) -> 38.6064 | P27: 0.25 | Q27: 1.58 | R27: 1.66 | S27: =IF(B27="","",(Q27+R27)/2) -> 1.62 | T27: =IF(B27="","",IFERROR(IF($X$1="ENTERO (redondeo arriba)",ROUNDUP(G27/P27,0)+1,G27/P27+1),0)) -> 31.64 | U27: =IF(B27="","",S27*T27) -> 51.2568 | V27: =IF(B27="","",U27*I27) -> 28.703808 | W27: =IF(B27="","",O27+V27) -> 67.310208 | X27: 3/8" | Y27: 0.56 | Z27: 0.25 | AA27: 0.56 | AB27: 0.56 | AC27: =IF(B27="","",IF(D27="TAPADA",(AA27+AB27)/2,0)) -> 0.56 | AD27: =IF(B27="","",IF(D27="TAPADA",IFERROR(IF($X$1="ENTERO (redondeo arriba)",ROUNDUP(G27/Z27,0)+1,G27/Z27+1),0),0)) -> 31.64 | AE27: =IF(B27="","",IF(D27="TAPADA",AC27*AD27,0)) -> 17.7184 | AF27: =IF(B27="","",IF(D27="TAPADA",AE27*Y27,0)) -> 9.922304 | AG27: =IF(B27="","",W27+AF27) -> 77.232512
A28: 18 | B28: EJE 07 | C28: TRAMO 03 | D28: ABIERTA | E28: SEC 32 | F28: SEC 33 | G28: 63.75 | H28: 3/8" | I28: =IF(H28="","",IFERROR(VLOOKUP(H28,Listas!$A$4:$B$11,2,FALSE()),"")) -> 0.56 | J28: 0.19 | K28: 9 | L28: 11 | M28: =IF(B28="","",(K28+L28)/2) -> 10 | N28: =IF(B28="","",G28*M28) -> 637.5 | O28: =IF(B28="","",N28*I28) -> 357 | P28: 0.25 | Q28: 1.66 | R28: 2.32 | S28: =IF(B28="","",(Q28+R28)/2) -> 1.99 | T28: =IF(B28="","",IFERROR(IF($X$1="ENTERO (redondeo arriba)",ROUNDUP(G28/P28,0)+1,G28/P28+1),0)) -> 256 | U28: =IF(B28="","",S28*T28) -> 509.44 | V28: =IF(B28="","",U28*I28) -> 285.2864 | W28: =IF(B28="","",O28+V28) -> 642.2864 | AC28: =IF(B28="","",IF(D28="TAPADA",(AA28+AB28)/2,0)) -> 0 | AD28: =IF(B28="","",IF(D28="TAPADA",IFERROR(IF($X$1="ENTERO (redondeo arriba)",ROUNDUP(G28/Z28,0)+1,G28/Z28+1),0),0)) -> 0 | AE28: =IF(B28="","",IF(D28="TAPADA",AC28*AD28,0)) -> 0 | AF28: =IF(B28="","",IF(D28="TAPADA",AE28*Y28,0)) -> 0 | AG28: =IF(B28="","",W28+AF28) -> 642.2864
A29: 19 | B29: EJE 07 | C29: TRAMO 04 | D29: TAPADA | E29: SEC 33 | F29: SEC 34 | G29: 11.47 | H29: 3/8" | I29: =IF(H29="","",IFERROR(VLOOKUP(H29,Listas!$A$4:$B$11,2,FALSE()),"")) -> 0.56 | J29: 0.21 | K29: 12 | L29: 12 | M29: =IF(B29="","",(K29+L29)/2) -> 12 | N29: =IF(B29="","",G29*M29) -> 137.64 | O29: =IF(B29="","",N29*I29) -> 77.0784 | P29: 0.25 | Q29: 2.32 | R29: 2.42 | S29: =IF(B29="","",(Q29+R29)/2) -> 2.37 | T29: =IF(B29="","",IFERROR(IF($X$1="ENTERO (redondeo arriba)",ROUNDUP(G29/P29,0)+1,G29/P29+1),0)) -> 46.88 | U29: =IF(B29="","",S29*T29) -> 111.1056 | V29: =IF(B29="","",U29*I29) -> 62.219136 | W29: =IF(B29="","",O29+V29) -> 139.29754 | X29: 3/8" | Y29: 0.56 | Z29: 0.25 | AA29: 0.56 | AB29: 0.56 | AC29: =IF(B29="","",IF(D29="TAPADA",(AA29+AB29)/2,0)) -> 0.56 | AD29: =IF(B29="","",IF(D29="TAPADA",IFERROR(IF($X$1="ENTERO (redondeo arriba)",ROUNDUP(G29/Z29,0)+1,G29/Z29+1),0),0)) -> 46.88 | AE29: =IF(B29="","",IF(D29="TAPADA",AC29*AD29,0)) -> 26.2528 | AF29: =IF(B29="","",IF(D29="TAPADA",AE29*Y29,0)) -> 14.701568 | AG29: =IF(B29="","",W29+AF29) -> 153.9991
A30: 20 | B30: EJE 07 | C30: TRAMO 05 | D30: TAPADA | E30: SEC 35 | F30: SEC 36 | G30: 5.17 | H30: 3/8" | I30: =IF(H30="","",IFERROR(VLOOKUP(H30,Listas!$A$4:$B$11,2,FALSE()),"")) -> 0.56 | J30: 0.21 | K30: 12 | L30: 12 | M30: =IF(B30="","",(K30+L30)/2) -> 12 | N30: =IF(B30="","",G30*M30) -> 62.04 | O30: =IF(B30="","",N30*I30) -> 34.7424 | P30: 0.25 | Q30: 2.32 | R30: 2.36 | S30: =IF(B30="","",(Q30+R30)/2) -> 2.34 | T30: =IF(B30="","",IFERROR(IF($X$1="ENTERO (redondeo arriba)",ROUNDUP(G30/P30,0)+1,G30/P30+1),0)) -> 21.68 | U30: =IF(B30="","",S30*T30) -> 50.7312 | V30: =IF(B30="","",U30*I30) -> 28.409472 | W30: =IF(B30="","",O30+V30) -> 63.151872 | X30: 3/8" | Y30: 0.56 | Z30: 0.25 | AA30: 0.56 | AB30: 0.56 | AC30: =IF(B30="","",IF(D30="TAPADA",(AA30+AB30)/2,0)) -> 0.56 | AD30: =IF(B30="","",IF(D30="TAPADA",IFERROR(IF($X$1="ENTERO (redondeo arriba)",ROUNDUP(G30/Z30,0)+1,G30/Z30+1),0),0)) -> 21.68 | AE30: =IF(B30="","",IF(D30="TAPADA",AC30*AD30,0)) -> 12.1408 | AF30: =IF(B30="","",IF(D30="TAPADA",AE30*Y30,0)) -> 6.798848 | AG30: =IF(B30="","",W30+AF30) -> 69.95072
A31: 21 | B31: EJE 08 | C31: TRAMO 01 | D31: TAPADA | E31: SEC 37 | F31: SEC 38 | G31: 8.2 | H31: 3/8" | I31: =IF(H31="","",IFERROR(VLOOKUP(H31,Listas!$A$4:$B$11,2,FALSE()),"")) -> 0.56 | J31: 0.21 | K31: 8 | L31: 8 | M31: =IF(B31="","",(K31+L31)/2) -> 8 | N31: =IF(B31="","",G31*M31) -> 65.6 | O31: =IF(B31="","",N31*I31) -> 36.736 | P31: 0.25 | Q31: 1.42 | R31: 1.48 | S31: =IF(B31="","",(Q31+R31)/2) -> 1.45 | T31: =IF(B31="","",IFERROR(IF($X$1="ENTERO (redondeo arriba)",ROUNDUP(G31/P31,0)+1,G31/P31+1),0)) -> 33.8 | U31: =IF(B31="","",S31*T31) -> 49.01 | V31: =IF(B31="","",U31*I31) -> 27.4456 | W31: =IF(B31="","",O31+V31) -> 64.1816 | X31: 3/8" | Y31: 0.56 | Z31: 0.25 | AA31: 0.56 | AB31: 0.56 | AC31: =IF(B31="","",IF(D31="TAPADA",(AA31+AB31)/2,0)) -> 0.56 | AD31: =IF(B31="","",IF(D31="TAPADA",IFERROR(IF($X$1="ENTERO (redondeo arriba)",ROUNDUP(G31/Z31,0)+1,G31/Z31+1),0),0)) -> 33.8 | AE31: =IF(B31="","",IF(D31="TAPADA",AC31*AD31,0)) -> 18.928 | AF31: =IF(B31="","",IF(D31="TAPADA",AE31*Y31,0)) -> 10.59968 | AG31: =IF(B31="","",W31+AF31) -> 74.78128
A32: 22 | B32: EJE 09 | C32: TRAMO 01 | D32: TAPADA | E32: SEC 39 | F32: SEC 40 | G32: 7 | H32: 3/8" | I32: =IF(H32="","",IFERROR(VLOOKUP(H32,Listas!$A$4:$B$11,2,FALSE()),"")) -> 0.56 | J32: 0.21 | K32: 8 | L32: 8 | M32: =IF(B32="","",(K32+L32)/2) -> 8 | N32: =IF(B32="","",G32*M32) -> 56 | O32: =IF(B32="","",N32*I32) -> 31.36 | P32: 0.25 | Q32: 1.42 | R32: 1.48 | S32: =IF(B32="","",(Q32+R32)/2) -> 1.45 | T32: =IF(B32="","",IFERROR(IF($X$1="ENTERO (redondeo arriba)",ROUNDUP(G32/P32,0)+1,G32/P32+1),0)) -> 29 | U32: =IF(B32="","",S32*T32) -> 42.05 | V32: =IF(B32="","",U32*I32) -> 23.548 | W32: =IF(B32="","",O32+V32) -> 54.908 | X32: 3/8" | Y32: 0.56 | Z32: 0.25 | AA32: 0.56 | AB32: 0.56 | AC32: =IF(B32="","",IF(D32="TAPADA",(AA32+AB32)/2,0)) -> 0.56 | AD32: =IF(B32="","",IF(D32="TAPADA",IFERROR(IF($X$1="ENTERO (redondeo arriba)",ROUNDUP(G32/Z32,0)+1,G32/Z32+1),0),0)) -> 29 | AE32: =IF(B32="","",IF(D32="TAPADA",AC32*AD32,0)) -> 16.24 | AF32: =IF(B32="","",IF(D32="TAPADA",AE32*Y32,0)) -> 9.0944 | AG32: =IF(B32="","",W32+AF32) -> 64.0024
A33: 23 | B33: EJE 11 | C33: TRAMO 01 | D33: ABIERTA | E33: SEC 44 | F33: SEC 45 | G33: 42.76 | H33: 3/8" | I33: =IF(H33="","",IFERROR(VLOOKUP(H33,Listas!$A$4:$B$11,2,FALSE()),"")) -> 0.56 | J33: 0.2 | K33: 7 | L33: 9 | M33: =IF(B33="","",(K33+L33)/2) -> 8 | N33: =IF(B33="","",G33*M33) -> 342.08 | O33: =IF(B33="","",N33*I33) -> 191.5648 | P33: 0.25 | Q33: 1.42 | R33: 1.82 | S33: =IF(B33="","",(Q33+R33)/2) -> 1.62 | T33: =IF(B33="","",IFERROR(IF($X$1="ENTERO (redondeo arriba)",ROUNDUP(G33/P33,0)+1,G33/P33+1),0)) -> 172.04 | U33: =IF(B33="","",S33*T33) -> 278.7048 | V33: =IF(B33="","",U33*I33) -> 156.07469 | W33: =IF(B33="","",O33+V33) -> 347.63949 | AC33: =IF(B33="","",IF(D33="TAPADA",(AA33+AB33)/2,0)) -> 0 | AD33: =IF(B33="","",IF(D33="TAPADA",IFERROR(IF($X$1="ENTERO (redondeo arriba)",ROUNDUP(G33/Z33,0)+1,G33/Z33+1),0),0)) -> 0 | AE33: =IF(B33="","",IF(D33="TAPADA",AC33*AD33,0)) -> 0 | AF33: =IF(B33="","",IF(D33="TAPADA",AE33*Y33,0)) -> 0 | AG33: =IF(B33="","",W33+AF33) -> 347.63949
A34: 24 | B34: EJE 11 | C34: TRAMO 02 | D34: TAPADA | E34: SEC 45 | F34: SEC 46 | G34: 2.2 | H34: 3/8" | I34: =IF(H34="","",IFERROR(VLOOKUP(H34,Listas!$A$4:$B$11,2,FALSE()),"")) -> 0.56 | J34: 0.2 | K34: 10 | L34: 10 | M34: =IF(B34="","",(K34+L34)/2) -> 10 | N34: =IF(B34="","",G34*M34) -> 22 | O34: =IF(B34="","",N34*I34) -> 12.32 | P34: 0.25 | Q34: 1.82 | R34: 1.84 | S34: =IF(B34="","",(Q34+R34)/2) -> 1.83 | T34: =IF(B34="","",IFERROR(IF($X$1="ENTERO (redondeo arriba)",ROUNDUP(G34/P34,0)+1,G34/P34+1),0)) -> 9.8 | U34: =IF(B34="","",S34*T34) -> 17.934 | V34: =IF(B34="","",U34*I34) -> 10.04304 | W34: =IF(B34="","",O34+V34) -> 22.36304 | X34: 3/8" | Y34: 0.56 | Z34: 0.25 | AA34: 0.56 | AB34: 0.56 | AC34: =IF(B34="","",IF(D34="TAPADA",(AA34+AB34)/2,0)) -> 0.56 | AD34: =IF(B34="","",IF(D34="TAPADA",IFERROR(IF($X$1="ENTERO (redondeo arriba)",ROUNDUP(G34/Z34,0)+1,G34/Z34+1),0),0)) -> 9.8 | AE34: =IF(B34="","",IF(D34="TAPADA",AC34*AD34,0)) -> 5.488 | AF34: =IF(B34="","",IF(D34="TAPADA",AE34*Y34,0)) -> 3.07328 | AG34: =IF(B34="","",W34+AF34) -> 25.43632
A35: 25 | B35: EJE 11 | C35: TRAMO 03 | D35: TAPADA | E35: SEC 47 | F35: SEC 48 | G35: 6.5 | H35: 3/8" | I35: =IF(H35="","",IFERROR(VLOOKUP(H35,Listas!$A$4:$B$11,2,FALSE()),"")) -> 0.56 | J35: 0.21 | K35: 10 | L35: 10 | M35: =IF(B35="","",(K35+L35)/2) -> 10 | N35: =IF(B35="","",G35*M35) -> 65 | O35: =IF(B35="","",N35*I35) -> 36.4 | P35: 0.25 | Q35: 1.76 | R35: 1.82 | S35: =IF(B35="","",(Q35+R35)/2) -> 1.79 | T35: =IF(B35="","",IFERROR(IF($X$1="ENTERO (redondeo arriba)",ROUNDUP(G35/P35,0)+1,G35/P35+1),0)) -> 27 | U35: =IF(B35="","",S35*T35) -> 48.33 | V35: =IF(B35="","",U35*I35) -> 27.0648 | W35: =IF(B35="","",O35+V35) -> 63.4648 | X35: 3/8" | Y35: 0.56 | Z35: 0.25 | AA35: 0.56 | AB35: 0.56 | AC35: =IF(B35="","",IF(D35="TAPADA",(AA35+AB35)/2,0)) -> 0.56 | AD35: =IF(B35="","",IF(D35="TAPADA",IFERROR(IF($X$1="ENTERO (redondeo arriba)",ROUNDUP(G35/Z35,0)+1,G35/Z35+1),0),0)) -> 27 | AE35: =IF(B35="","",IF(D35="TAPADA",AC35*AD35,0)) -> 15.12 | AF35: =IF(B35="","",IF(D35="TAPADA",AE35*Y35,0)) -> 8.4672 | AG35: =IF(B35="","",W35+AF35) -> 71.932
A36: 26 | B36: EJE 12 | C36: TRAMO 01 | D36: ABIERTA | E36: SEC 50 | F36: SEC 51 | G36: 32.48 | H36: 3/8" | I36: =IF(H36="","",IFERROR(VLOOKUP(H36,Listas!$A$4:$B$11,2,FALSE()),"")) -> 0.56 | J36: 0.2 | K36: 7 | L36: 1.76 | M36: =IF(B36="","",(K36+L36)/2) -> 4.38 | N36: =IF(B36="","",G36*M36) -> 142.2624 | O36: =IF(B36="","",N36*I36) -> 79.666944 | P36: 0.25 | Q36: 1.42 | R36: 1.76 | S36: =IF(B36="","",(Q36+R36)/2) -> 1.59 | T36: =IF(B36="","",IFERROR(IF($X$1="ENTERO (redondeo arriba)",ROUNDUP(G36/P36,0)+1,G36/P36+1),0)) -> 130.92 | U36: =IF(B36="","",S36*T36) -> 208.1628 | V36: =IF(B36="","",U36*I36) -> 116.57117 | W36: =IF(B36="","",O36+V36) -> 196.23811 | AC36: =IF(B36="","",IF(D36="TAPADA",(AA36+AB36)/2,0)) -> 0 | AD36: =IF(B36="","",IF(D36="TAPADA",IFERROR(IF($X$1="ENTERO (redondeo arriba)",ROUNDUP(G36/Z36,0)+1,G36/Z36+1),0),0)) -> 0 | AE36: =IF(B36="","",IF(D36="TAPADA",AC36*AD36,0)) -> 0 | AF36: =IF(B36="","",IF(D36="TAPADA",AE36*Y36,0)) -> 0 | AG36: =IF(B36="","",W36+AF36) -> 196.23811
A37: 27 | B37: EJE 12 | C37: TRAMO 02 | D37: TAPADA | E37: SEC 52 | F37: SEC 53 | G37: 56.64 | H37: 3/8" | I37: =IF(H37="","",IFERROR(VLOOKUP(H37,Listas!$A$4:$B$11,2,FALSE()),"")) -> 0.56 | J37: 0.21 | K37: 10 | L37: 12 | M37: =IF(B37="","",(K37+L37)/2) -> 11 | N37: =IF(B37="","",G37*M37) -> 623.04 | O37: =IF(B37="","",N37*I37) -> 348.9024 | P37: 0.25 | Q37: 1.66 | R37: 2.22 | S37: =IF(B37="","",(Q37+R37)/2) -> 1.94 | T37: =IF(B37="","",IFERROR(IF($X$1="ENTERO (redondeo arriba)",ROUNDUP(G37/P37,0)+1,G37/P37+1),0)) -> 227.56 | U37: =IF(B37="","",S37*T37) -> 441.4664 | V37: =IF(B37="","",U37*I37) -> 247.22118 | W37: =IF(B37="","",O37+V37) -> 596.12358 | X37: 3/8" | Y37: 0.56 | Z37: 0.25 | AA37: 0.56 | AB37: 0.56 | AC37: =IF(B37="","",IF(D37="TAPADA",(AA37+AB37)/2,0)) -> 0.56 | AD37: =IF(B37="","",IF(D37="TAPADA",IFERROR(IF($X$1="ENTERO (redondeo arriba)",ROUNDUP(G37/Z37,0)+1,G37/Z37+1),0),0)) -> 227.56 | AE37: =IF(B37="","",IF(D37="TAPADA",AC37*AD37,0)) -> 127.4336 | AF37: =IF(B37="","",IF(D37="TAPADA",AE37*Y37,0)) -> 71.362816 | AG37: =IF(B37="","",W37+AF37) -> 667.4864
A38: TOTALES DE LA PLANILLA | G38: =SUM(G11:G37) -> 512.94 | N38: =SUM(N11:N37) -> 4654.7224 | O38: =SUM(O11:O37) -> 2606.6445 | U38: =SUM(U11:U37) -> 3817.9952 | V38: =SUM(V11:V37) -> 2138.0773 | W38: =SUM(W11:W37) -> 4744.7219 | AE38: =SUM(AE11:AE37) -> 397.0176 | AF38: =SUM(AF11:AF37) -> 222.32986 | AG38: =SUM(AG11:AG37) -> 4967.0517

Sheet METRADO DE CURADO
A1: METRADO DE CURADO DE CONCRETO EN CUNETAS
A2: ENTIDAD | C2: GERENCIA TERRITORIAL BAJO MAYO - TARAPOTO
A3: PROYECTO | C3: =+RESUMEN!B5 -> “CREACIÓN DEL SERVICIO DE PROTECCIÓN A MUJERES VÍCTIMAS DE VIOLENCIA EN SITUACIÓN DE RIESGO DE FEMINICIDIO O PELIGRE SU INTEGRIDAD Y/O SALUD FÍSICA Y/O MENTAL EN HOGAR DE REFUGIO TEMPORAL DISTRITO DE MORALES DE LA PROVINCIA DE SAN MARTÍN DEL DEPARTAMENTO DE SAN MARTÍN”, con CUI N.° 2675514
A4: UBICACIÓN | C4: =+RESUMEN!B6 -> SAN MARTIN - SAN MARTIN - MORALES | K4: FECHA | L4: =+RESUMEN!B7 -> 46266
A6: N° | B6: EJE | C6: TRAMO | D6: TIPO DE CUNETA | E6: LONGITUD (m) | F6: ANCHO INTERIOR (m) | G6: ALTURA INT. INI (m) | H6: ALTURA INT. FIN (m) | I6: ALTURA PROM. (m) | J6: ÁREA 2 MUROS (m²) | K6: ÁREA FONDO (m²) | L6: ÁREA TAPA / TECHO (m²) | M6: TOTAL CURADO (m²) | N6: N° CARAS | O6: UND.
A7: 1 | B7: EJE 01 | C7: TRAMO 01 | D7: ABIERTA | E7: 32 | F7: 0.4 | G7: 0.3 | H7: 0.46 | I7: =IF(B7="","",(G7+H7)/2) -> 0.38 | J7: =IF(B7="","",2*E7*I7) -> 24.32 | K7: =IF(B7="","",E7*F7) -> 12.8 | L7: =IF(B7="","",IF(D7="TAPADA",E7*F7,0)) -> 0 | M7: =SUM(J7:L7) -> 37.12 | N7: =IF(B7="","",IF(D7="TAPADA",4,3)) -> 3 | O7: m²
A8: 2 | B8: EJE 01 | C8: TRAMO 02 | D8: TAPADA | E8: 5.14 | F8: 0.4 | G8: 0.46 | H8: 0.48 | I8: =IF(B8="","",(G8+H8)/2) -> 0.47 | J8: =IF(B8="","",2*E8*I8) -> 4.8316 | K8: =IF(B8="","",E8*F8) -> 2.056 | L8: =IF(B8="","",IF(D8="TAPADA",E8*F8,0)) -> 2.056 | M8: =SUM(J8:L8) -> 8.9436 | N8: =IF(B8="","",IF(D8="TAPADA",4,3)) -> 4 | O8: m²
A9: 3 | B9: EJE 02 | C9: TRAMO 01 | D9: ABIERTA | E9: 37.5 | F9: 0.4 | G9: 0.3 | H9: 0.48 | I9: =IF(B9="","",(G9+H9)/2) -> 0.39 | J9: =IF(B9="","",2*E9*I9) -> 29.25 | K9: =IF(B9="","",E9*F9) -> 15 | L9: =IF(B9="","",IF(D9="TAPADA",E9*F9,0)) -> 0 | M9: =SUM(J9:L9) -> 44.25 | N9: =IF(B9="","",IF(D9="TAPADA",4,3)) -> 3 | O9: m²
A10: 4 | B10: EJE 02 | C10: TRAMO 02 | D10: TAPADA | E10: 10.2 | F10: 0.4 | G10: 0.48 | H10: 0.53 | I10: =IF(B10="","",(G10+H10)/2) -> 0.505 | J10: =IF(B10="","",2*E10*I10) -> 10.302 | K10: =IF(B10="","",E10*F10) -> 4.08 | L10: =IF(B10="","",IF(D10="TAPADA",E10*F10,0)) -> 4.08 | M10: =SUM(J10:L10) -> 18.462 | N10: =IF(B10="","",IF(D10="TAPADA",4,3)) -> 4 | O10: m²
A11: 5 | B11: EJE 02 | C11: TRAMO 03 | D11: ABIERTA | E11: 31.33 | F11: 0.4 | G11: 0.53 | H11: 0.7 | I11: =IF(B11="","",(G11+H11)/2) -> 0.615 | J11: =IF(B11="","",2*E11*I11) -> 38.5359 | K11: =IF(B11="","",E11*F11) -> 12.532 | L11: =IF(B11="","",IF(D11="TAPADA",E11*F11,0)) -> 0 | M11: =SUM(J11:L11) -> 51.0679 | N11: =IF(B11="","",IF(D11="TAPADA",4,3)) -> 3 | O11: m²
A12: 6 | B12: EJE 02 | C12: TRAMO 04 | D12: TAPADA | E12: 8.36 | F12: 0.4 | G12: 0.7 | H12: 0.73 | I12: =IF(B12="","",(G12+H12)/2) -> 0.715 | J12: =IF(B12="","",2*E12*I12) -> 11.9548 | K12: =IF(B12="","",E12*F12) -> 3.344 | L12: =IF(B12="","",IF(D12="TAPADA",E12*F12,0)) -> 3.344 | M12: =SUM(J12:L12) -> 18.6428 | N12: =IF(B12="","",IF(D12="TAPADA",4,3)) -> 4 | O12: m²
A13: 7 | B13: EJE 02 | C13: TRAMO 05 | D13: ABIERTA | E13: 30.36 | F13: 0.4 | G13: 0.73 | H13: 0.88 | I13: =IF(B13="","",(G13+H13)/2) -> 0.805 | J13: =IF(B13="","",2*E13*I13) -> 48.8796 | K13: =IF(B13="","",E13*F13) -> 12.144 | L13: =IF(B13="","",IF(D13="TAPADA",E13*F13,0)) -> 0 | M13: =SUM(J13:L13) -> 61.0236 | N13: =IF(B13="","",IF(D13="TAPADA",4,3)) -> 3 | O13: m²
A14: 8 | B14: EJE 02 | C14: TRAMO 06 | D14: TAPADA | E14: 2.25 | F14: 0.4 | G14: 0.88 | H14: 0.9 | I14: =IF(B14="","",(G14+H14)/2) -> 0.89 | J14: =IF(B14="","",2*E14*I14) -> 4.005 | K14: =IF(B14="","",E14*F14) -> 0.9 | L14: =IF(B14="","",IF(D14="TAPADA",E14*F14,0)) -> 0.9 | M14: =SUM(J14:L14) -> 5.805 | N14: =IF(B14="","",IF(D14="TAPADA",4,3)) -> 4 | O14: m²
A15: 9 | B15: EJE 02 | C15: TRAMO 07 | D15: TAPADA | E15: 10.85 | F15: 0.4 | G15: 0.85 | H15: 0.9 | I15: =IF(B15="","",(G15+H15)/2) -> 0.875 | J15: =IF(B15="","",2*E15*I15) -> 18.9875 | K15: =IF(B15="","",E15*F15) -> 4.34 | L15: =IF(B15="","",IF(D15="TAPADA",E15*F15,0)) -> 4.34 | M15: =SUM(J15:L15) -> 27.6675 | N15: =IF(B15="","",IF(D15="TAPADA",4,3)) -> 4 | O15: m²
A16: 10 | B16: EJE 03 | C16: TRAMO 01 | D16: ABIERTA | E16: 5.82 | F16: 0.4 | G16: 0.3 | H16: 0.32 | I16: =IF(B16="","",(G16+H16)/2) -> 0.31 | J16: =IF(B16="","",2*E16*I16) -> 3.6084 | K16: =IF(B16="","",E16*F16) -> 2.328 | L16: =IF(B16="","",IF(D16="TAPADA",E16*F16,0)) -> 0 | M16: =SUM(J16:L16) -> 5.9364 | N16: =IF(B16="","",IF(D16="TAPADA",4,3)) -> 3 | O16: m²
A17: 11 | B17: EJE 04 | C17: TRAMO 01 | D17: ABIERTA | E17: 8.6 | F17: 0.4 | G17: 0.3 | H17: 0.34 | I17: =IF(B17="","",(G17+H17)/2) -> 0.32 | J17: =IF(B17="","",2*E17*I17) -> 5.504 | K17: =IF(B17="","",E17*F17) -> 3.44 | L17: =IF(B17="","",IF(D17="TAPADA",E17*F17,0)) -> 0 | M17: =SUM(J17:L17) -> 8.944 | N17: =IF(B17="","",IF(D17="TAPADA",4,3)) -> 3 | O17: m²
A18: 12 | B18: EJE 05 | C18: TRAMO 01 | D18: ABIERTA | E18: 37.53 | F18: 0.4 | G18: 0.3 | H18: 0.48 | I18: =IF(B18="","",(G18+H18)/2) -> 0.39 | J18: =IF(B18="","",2*E18*I18) -> 29.2734 | K18: =IF(B18="","",E18*F18) -> 15.012 | L18: =IF(B18="","",IF(D18="TAPADA",E18*F18,0)) -> 0 | M18: =SUM(J18:L18) -> 44.2854 | N18: =IF(B18="","",IF(D18="TAPADA",4,3)) -> 3 | O18: m²
... A36: 30 | B36: EJE 12 | C36: TRAMO 02 | D36: TAPADA | E36: 56.64 | F36: 0.4 | G36: 0.51 | H36: 0.8 | I36: =IF(B36="","",(G36+H36)/2) -> 0.655 | J36: =IF(B36="","",2*E36*I36) -> 74.1984 | K36: =IF(B36="","",E36*F36) -> 22.656 | L36: =IF(B36="","",IF(D36="TAPADA",E36*F36,0)) -> 22.656 | M36: =SUM(J36:L36) -> 119.5104 | N36: =IF(B36="","",IF(D36="TAPADA",4,3)) -> 4 | O36: m²
A38: TOTAL DE CURADO DE CONCRETO EN CUNETAS | M38: =SUM(M7:M36) -> 1084.2059 | O38: m²

Sheet METRADO DE REJILLAS
A1: METRADO DE REJILLAS PARA CUNETAS
A2: ENTIDAD | C2: GERENCIA TERRITORIAL BAJO MAYO - TARAPOTO
A3: PROYECTO | C3: =+RESUMEN!B5 -> “CREACIÓN DEL SERVICIO DE PROTECCIÓN A MUJERES VÍCTIMAS DE VIOLENCIA EN SITUACIÓN DE RIESGO DE FEMINICIDIO O PELIGRE SU INTEGRIDAD Y/O SALUD FÍSICA Y/O MENTAL EN HOGAR DE REFUGIO TEMPORAL DISTRITO DE MORALES DE LA PROVINCIA DE SAN MARTÍN DEL DEPARTAMENTO DE SAN MARTÍN”, con CUI N.° 2675514
A4: UBICACIÓN | C4: =+RESUMEN!B6 -> SAN MARTIN - SAN MARTIN - MORALES | G4: FECHA | H4: =+RESUMEN!B7 -> 46266
A6: N° | B6: EJE | C6: TRAMO | D6: TIPO DE CUNETA | E6: LONGITUD DEL TRAMO (m) | F6: DESCUENTO SIN REJILLA (m) | G6: LONGITUD CON REJILLA (m) | H6: UND.
A7: 1 | B7: EJE 01 | C7: TRAMO 01 | D7: ABIERTA | E7: 32 | F7: 0 | G7: =IF(B7="","",IF(D7="ABIERTA",IF(E7-F7<0,0,E7-F7),0)) -> 32 | H7: m
A8: 2 | B8: EJE 01 | C8: TRAMO 02 | D8: TAPADA | E8: 5.14 | F8: 0 | G8: =IF(B8="","",IF(D8="ABIERTA",IF(E8-F8<0,0,E8-F8),0)) -> 0 | H8: m
A9: 3 | B9: EJE 02 | C9: TRAMO 01 | D9: ABIERTA | E9: 37.5 | F9: 0 | G9: =IF(B9="","",IF(D9="ABIERTA",IF(E9-F9<0,0,E9-F9),0)) -> 37.5 | H9: m
A10: 4 | B10: EJE 02 | C10: TRAMO 02 | D10: TAPADA | E10: 10.2 | F10: 0 | G10: =IF(B10="","",IF(D10="ABIERTA",IF(E10-F10<0,0,E10-F10),0)) -> 0 | H10: m
A11: 5 | B11: EJE 02 | C11: TRAMO 03 | D11: ABIERTA | E11: 31.33 | F11: 0 | G11: =IF(B11="","",IF(D11="ABIERTA",IF(E11-F11<0,0,E11-F11),0)) -> 31.33 | H11: m
A12: 6 | B12: EJE 02 | C12: TRAMO 04 | D12: TAPADA | E12: 8.36 | F12: 0 | G12: =IF(B12="","",IF(D12="ABIERTA",IF(E12-F12<0,0,E12-F12),0)) -> 0 | H12: m
A13: 7 | B13: EJE 02 | C13: TRAMO 05 | D13: ABIERTA | E13: 30.36 | F13: 0 | G13: =IF(B13="","",IF(D13="ABIERTA",IF(E13-F13<0,0,E13-F13),0)) -> 30.36 | H13: m
A14: 8 | B14: EJE 02 | C14: TRAMO 06 | D14: TAPADA | E14: 2.25 | F14: 0 | G14: =IF(B14="","",IF(D14="ABIERTA",IF(E14-F14<0,0,E14-F14),0)) -> 0 | H14: m
A15: 9 | B15: EJE 02 | C15: TRAMO 07 | D15: TAPADA | E15: 10.85 | F15: 0 | G15: =IF(B15="","",IF(D15="ABIERTA",IF(E15-F15<0,0,E15-F15),0)) -> 0 | H15: m
A16: 10 | B16: EJE 03 | C16: TRAMO 01 | D16: ABIERTA | E16: 5.82 | F16: 0 | G16: =IF(B16="","",IF(D16="ABIERTA",IF(E16-F16<0,0,E16-F16),0)) -> 5.82 | H16: m
A17: 11 | B17: EJE 04 | C17: TRAMO 01 | D17: ABIERTA | E17: 8.6 | F17: 0 | G17: =IF(B17="","",IF(D17="ABIERTA",IF(E17-F17<0,0,E17-F17),0)) -> 8.6 | H17: m
A18: 12 | B18: EJE 05 | C18: TRAMO 01 | D18: ABIERTA | E18: 37.53 | F18: 0 | G18: =IF(B18="","",IF(D18="ABIERTA",IF(E18-F18<0,0,E18-F18),0)) -> 37.53 | H18: m
... A36: 30 | B36: EJE 12 | C36: TRAMO 02 | D36: TAPADA | E36: 56.64 | F36: 0 | G36: =IF(B36="","",IF(D36="ABIERTA",IF(E36-F36<0,0,E36-F36),0)) -> 0 | H36: m
A38: TOTAL CALCULADO DE REJILLA EN CUNETAS ABIERTAS | G38: =SUM(G7:G36) -> 510.11 | H38: m

Sheet METRADO JUNTA DE DILATACION
A1: PLANILLA DE METRADOS - JUNTA DE DILATACIÓN E=1" CON SELLADOR ASFÁLTICO EN MUROS DE CUNETAS
A2: ENTIDAD | B2: GERENCIA TERRITORIAL BAJO MAYO - TARAPOTO
A3: PROYECTO | B3: =+RESUMEN!B5 -> “CREACIÓN DEL SERVICIO DE PROTECCIÓN A MUJERES VÍCTIMAS DE VIOLENCIA EN SITUACIÓN DE RIESGO DE FEMINICIDIO O PELIGRE SU INTEGRIDAD Y/O SALUD FÍSICA Y/O MENTAL EN HOGAR DE REFUGIO TEMPORAL DISTRITO DE MORALES DE LA PROVINCIA DE SAN MARTÍN DEL DEPARTAMENTO DE SAN MARTÍN”, con CUI N.° 2675514
A4: UBICACIÓN | B4: =+RESUMEN!B6 -> SAN MARTIN - SAN MARTIN - MORALES
A5: FECHA | B5: =+RESUMEN!B7 -> 46266
A7: PARÁMETROS
A8: Espaciamiento entre juntas (m) | B8: 3
A9: N° de muros con junta por cuneta | B9: 2
A10: Espesor de junta (referencial, no interviene en el metrado lineal) | B10: 1" = 0.0254 m
A11: ITEM | B11: EJE / DESCRIPCIÓN | C11: UND. | D11: LONGITUD EJE (m) | E11: ÁREA MURO (m²) | F11: ALTURA MURO (m) | G11: ESPACIAMIENTO (m) | H11: N° DE JUNTAS | I11: N° MUROS x JUNTA | J11: PARCIAL (ml)
A12: Descripccion | B12: JUNTA DE DILATACION E=1" CON SELLADOR ASFALTO | C12: ml | J12: =SUM(J13:J24) -> 241.95954
A13: 1 | B13: EJE 01 | D13: 37.14 | E13: =+'CONCRETO EN CUNETAS'!E10 -> 14.07 | F13: =E13/D13 -> 0.37883683 | G13: =B8 -> 3 | H13: =ROUNDUP(D13/G13,0) -> 13 | I13: =B9 -> 2 | J13: =H13*I13*F13 -> 9.8497577
A14: 2 | B14: EJE 02 | D14: 130.85 | E14: =+'CONCRETO EN CUNETAS'!E22 -> 78.32 | F14: =E14/D14 -> 0.59854796 | G14: =B8 -> 3 | H14: =ROUNDUP(D14/G14,0) -> 44 | I14: =B9 -> 2 | J14: =H14*I14*F14 -> 52.67222
A15: 3 | B15: EJE 03 | D15: 5.82 | E15: =+'CONCRETO EN CUNETAS'!E34 -> 1.83 | F15: =E15/D15 -> 0.31443299 | G15: =B8 -> 3 | H15: =ROUNDUP(D15/G15,0) -> 2 | I15: =B9 -> 2 | J15: =H15*I15*F15 -> 1.257732
A16: 4 | B16: EJE 04 | D16: 8.6 | E16: =+'CONCRETO EN CUNETAS'!E46 -> 2.76 | F16: =E16/D16 -> 0.32093023 | G16: =B8 -> 3 | H16: =ROUNDUP(D16/G16,0) -> 3 | I16: =B9 -> 2 | J16: =H16*I16*F16 -> 1.9255814
A17: 5 | B17: EJE 05 | D17: 43.23 | E17: =+'CONCRETO EN CUNETAS'!E58 -> 17.7 | F17: =E17/D17 -> 0.40943789 | G17: =B8 -> 3 | H17: =ROUNDUP(D17/G17,0) -> 15 | I17: =B9 -> 2 | J17: =H17*I17*F17 -> 12.283137
A18: 6 | B18: EJE 06 | D18: 120.36 | E18: =+'CONCRETO EN CUNETAS'!E70 -> 69.72 | F18: =E18/D18 -> 0.57926221 | G18: =B8 -> 3 | H18: =ROUNDUP(D18/G18,0) -> 41 | I18: =B9 -> 2 | J18: =H18*I18*F18 -> 47.499501
A19: 7 | B19: EJE 07 | D19: 125.7 | E19: =+'CONCRETO EN CUNETAS'!M10 -> 74.5 | F19: =E19/D19 -> 0.59268099 | G19: =B8 -> 3 | H19: =ROUNDUP(D19/G19,0) -> 42 | I19: =B9 -> 2 | J19: =H19*I19*F19 -> 49.785203
A20: 8 | B20: EJE 08 | D20: 8.2 | E20: =+'CONCRETO EN CUNETAS'!M22 -> 2.62 | F20: =E20/D20 -> 0.3195122 | G20: =B8 -> 3 | H20: =ROUNDUP(D20/G20,0) -> 3 | I20: =B9 -> 2 | J20: =H20*I20*F20 -> 1.9170732
A21: 9 | B21: EJE 09 | D21: 7 | E21: =+'CONCRETO EN CUNETAS'!M34 -> 2.22 | F21: =E21/D21 -> 0.31714286 | G21: =B8 -> 3 | H21: =ROUNDUP(D21/G21,0) -> 3 | I21: =B9 -> 2 | J21: =H21*I21*F21 -> 1.9028571
A22: 10 | B22: EJE 10 | D22: 16 | E22: =+'CONCRETO EN CUNETAS'!M46 -> 5.44 | F22: =E22/D22 -> 0.34 | G22: =B8 -> 3 | H22: =ROUNDUP(D22/G22,0) -> 6 | I22: =B9 -> 2 | J22: =H22*I22*F22 -> 4.08
A23: 11 | B23: EJE 11 | D23: 71.46 | E23: =+'CONCRETO EN CUNETAS'!M58 -> 33 | F23: =E23/D23 -> 0.46179681 | G23: =B8 -> 3 | H23: =ROUNDUP(D23/G23,0) -> 24 | I23: =B9 -> 2 | J23: =H23*I23*F23 -> 22.166247
A24: 12 | B24: EJE 12 | D24: 109.12 | E24: =+'CONCRETO EN CUNETAS'!M70 -> 54 | F24: =E24/D24 -> 0.49486804 | G24: =B8 -> 3 | H24: =ROUNDUP(D24/G24,0) -> 37 | I24: =B9 -> 2 | J24: =H24*I24*F24 -> 36.620235

Sheet METRADO LLORADEROS
A1: METRADO DE LLORADEROS DE PVC Ø3" EN MUROS DE CUNETA COLINDANTES CON ÁREA VERDE
A2: ENTIDAD | C2: GERENCIA TERRITORIAL BAJO MAYO - TARAPOTO
A3: PROYECTO | C3: =+RESUMEN!B5 -> “CREACIÓN DEL SERVICIO DE PROTECCIÓN A MUJERES VÍCTIMAS DE VIOLENCIA EN SITUACIÓN DE RIESGO DE FEMINICIDIO O PELIGRE SU INTEGRIDAD Y/O SALUD FÍSICA Y/O MENTAL EN HOGAR DE REFUGIO TEMPORAL DISTRITO DE MORALES DE LA PROVINCIA DE SAN MARTÍN DEL DEPARTAMENTO DE SAN MARTÍN”, con CUI N.° 2675514
A4: UBICACIÓN | C4: =+RESUMEN!B6 -> SAN MARTIN - SAN MARTIN - MORALES | G4: FECHA | H4: =+RESUMEN!B7 -> 46266
A6: N° | B6: EJE | C6: PROGRESIVA DEL TRAMO (desde - hasta) | D6: LADO DEL MURO | E6: LONGITUD JUNTO A ÁREA VERDE (m) | F6: ESPACIAMIENTO (m) | G6: N° DE LLORADEROS | H6: UND.
A7: 1 | B7: EJE 01 | C7: 0+000.00 a 0+037.00 | D7: LADO ESTE | E7: 37 | F7: 1.5 | G7: =IF(B7="","",ROUNDUP(E7/F7,0)) -> 25 | H7: und
A8: 2 | B8: EJE 01 | C8: 0+032.25 a 0+037.00 | D8: LADO OESTE | E8: 4.75 | F8: 1.5 | G8: =IF(B8="","",ROUNDUP(E8/F8,0)) -> 4 | H8: und
A9: 3 | B9: EJE 02 | C9: 0+040.62 a 0+045.37 | D9: LADO SUR | E9: 4.75 | F9: 1.5 | G9: =IF(B9="","",ROUNDUP(E9/F9,0)) -> 4 | H9: und
A10: 4 | B10: EJE 07 | C10: 0+040.62 a 0+042.87 | D10: LADO SUR | E10: 2.25 | F10: 1.5 | G10: =IF(B10="","",ROUNDUP(E10/F10,0)) -> 2 | H10: und
A11: 5 | B11: EJE 07 | C11: 0+123.97 a 0+125.70 | D11: LADO ESTE | E11: 1.73 | F11: 1.5 | G11: =IF(B11="","",ROUNDUP(E11/F11,0)) -> 2 | H11: und
A12: 6 | B12: EJE 07 | C12: 0+123.97 a 0+125.70 | D12: LADO OESTE | E12: 1.73 | F12: 1.5 | G12: =IF(B12="","",ROUNDUP(E12/F12,0)) -> 2 | H12: und
A13: 7 | B13: EJE 09 | C13: 0+000.50 a 0+005.00 | D13: LADO SUR | E13: 4.5 | F13: 1.5 | G13: =IF(B13="","",ROUNDUP(E13/F13,0)) -> 3 | H13: und
A14: 8 | B14: EJE 11 | C14: 0+069.05 a 0+071.30 | D14: LADO ESTE | E14: 2.25 | F14: 1.5 | G14: =IF(B14="","",ROUNDUP(E14/F14,0)) -> 2 | H14: und
A15: 9 | B15: EJE 11 | C15: 0+039.50 a 0+062.75 | D15: LADO OESTE | E15: 23.25 | F15: 1.5 | G15: =IF(B15="","",ROUNDUP(E15/F15,0)) -> 16 | H15: und
A16: 10 | B16: EJE 11 | C16: 0+066.80 a 0+071.30 | D16: LADO OESTE | E16: 4.5 | F16: 1.5 | G16: =IF(B16="","",ROUNDUP(E16/F16,0)) -> 3 | H16: und
A17: 11 | B17: EJE 12 | C17: 0+078.50 a 0+109.00 | D17: LADO ESTE | E17: 30.5 | F17: 1.5 | G17: =IF(B17="","",ROUNDUP(E17/F17,0)) -> 21 | H17: und
A18: 12 | B18: EJE 12 | C18: 0+000.00 a 0+109.00 | D18: LADO OESTE | E18: 109 | F18: 1.5 | G18: =IF(B18="","",ROUNDUP(E18/F18,0)) -> 73 | H18: und
A20: TOTAL DE LLORADEROS EN CUNETAS COLINDANTES CON ÁREA VERDE | E20: =SUM(E7:E18) -> 226.21 | G20: =SUM(G7:G18) -> 157 | H20: und
A22: CRITERIO DE METRADO
A23: 1. Solo llevan lloraderos los muros de cuneta colindantes con área verde (detalle de instalación de lloraderos en cunetas de evacuación pluvial y especificación técnica del plano de drenaje: lloraderos de tubería PVC Ø3", espaciamiento típico L = 1.50 m, en muros de contención de la cuneta colindantes con áreas verdes).
A24: 2. Tramos medidos en la planta general de drenaje: muro cuya franja exterior de 0.30 m queda dentro del achurado de área verde; no se cuentan tramos menores de 1.50 m. Progresivas desde el inicio de cada eje (igual que los perfiles), recortadas a la longitud del eje de este metrado.
A25: 3. N° de lloraderos por tramo = REDONDEAR.MAS(longitud / 1.50). Cada unidad comprende: pase de tubería PVC-U Ø3" (L = 0.30 m) a media altura del muro con pendiente S = 0.5 % hacia la cuneta; filtro localizado de grava 20-40 mm de 0.30 x 0.30 x 0.30 m (0.027 m³) envuelto en geotextil no tejido (0.60 m² con traslapes); excavación local y relleno del filtro.
A26: 4. Partida nueva: no modifica ninguna otra partida del metrado.

Sheet PLANILLA TAPAS REGISTRO INTERNO
A1: METRADO DE TAPAS DE REGISTRO EN CUNETAS TAPADAS
A2: ENTIDAD | B2: GERENCIA TERRITORIAL BAJO MAYO - TARAPOTO
A3: PROYECTO | B3: =+RESUMEN!B5 -> “CREACIÓN DEL SERVICIO DE PROTECCIÓN A MUJERES VÍCTIMAS DE VIOLENCIA EN SITUACIÓN DE RIESGO DE FEMINICIDIO O PELIGRE SU INTEGRIDAD Y/O SALUD FÍSICA Y/O MENTAL EN HOGAR DE REFUGIO TEMPORAL DISTRITO DE MORALES DE LA PROVINCIA DE SAN MARTÍN DEL DEPARTAMENTO DE SAN MARTÍN”, con CUI N.° 2675514
A4: UBICACIÓN | B4: =+RESUMEN!B6 -> SAN MARTIN - SAN MARTIN - MORALES
A5: FECHA | B5: =+RESUMEN!B7 -> 46266
A7: ITEM | B7: DESCRIPCIÓN | C7: Nº DE VECES | D7: DIMENSIONES | I7: PARCIAL | J7: TOTAL | K7: UND
D8: LARGO | E8: ANCHO | F8: ALTURA | G8: FACT. | H8: AREA | I8: VOLUMEN / PARCIAL
A9: 01.04.03.04.03.02 | B9: TAPA DE REGISTRO (DE CONCRETO) | J9: =+PARAMETROS!B4 -> 17 | K9: und
B11: CONCRETO F´C=210 KG/CM2 EN TAPA DE REGISTRO | I11: TOTAL
B12: TAPA 0.60 x 0.60 x 0.10 m | C12: =PARAMETROS!B4 -> 17 | D12: =PARAMETROS!B5 -> 0.6 | E12: =PARAMETROS!B6 -> 0.6 | F12: =PARAMETROS!B7 -> 0.1 | I12: =C12*D12*E12*F12 -> 0.612 | J12: =I12 -> 0.612 | K12: m3
B14: ENCOFRADO Y DESENCOFRADO EN TAPA DE REGISTRO | I14: TOTAL
B15: LATERALES DE TAPA | C15: =PARAMETROS!B4 -> 17 | D15: =2*(PARAMETROS!B5+PARAMETROS!B6) -> 2.4 | F15: =PARAMETROS!B7 -> 0.1 | H15: =D15*F15 -> 0.24 | I15: =C15*H15 -> 4.08 | J15: =I15 -> 4.08 | K15: m2
B16: FONDO DE MOLDE / BASE DE PREFABRICADO | C16: =PARAMETROS!B4 -> 17 | D16: =PARAMETROS!B5 -> 0.6 | E16: =PARAMETROS!B6 -> 0.6 | H16: =D16*E16 -> 0.36 | I16: =C16*H16 -> 6.12 | J16: =I16 -> 6.12 | K16: m2
B17: TOTAL ENCOFRADO FONDO + LATERALES | J17: =J15+J16 -> 10.2 | K17: m2
B19: ACERO FY=4200 KG/CM2 EN TAPA DE REGISTRO - VARILLA 3/8 | D19: LONGITUD DE CADA BARRA | E19: CANTIDAD DE BARRAS POR TAPA | I19: TOTAL
B20: Acero longitudinal 3/8 - parrilla simple | C20: =PARAMETROS!B4 -> 17 | D20: =PARAMETROS!B5-2*PARAMETROS!B8 -> 0.55 | E20: =ROUND((PARAMETROS!B6-2*PARAMETROS!B8)/PARAMETROS!B9,0)+1 -> 5 | G20: =PARAMETROS!B10 -> 0.56 | I20: =C20*D20*E20*G20 -> 26.18 | J20: =I20 -> 26.18 | K20: kg
B21: Acero transversal 3/8 - parrilla simple | C21: =PARAMETROS!B4 -> 17 | D21: =PARAMETROS!B6-2*PARAMETROS!B8 -> 0.55 | E21: =ROUND((PARAMETROS!B5-2*PARAMETROS!B8)/PARAMETROS!B9,0)+1 -> 5 | G21: =PARAMETROS!B10 -> 0.56 | I21: =C21*D21*E21*G21 -> 26.18 | J21: =I21 -> 26.18 | K21: kg
B22: TOTAL ACERO 3/8 | J22: =J20+J21 -> 52.36 | K22: kg

Sheet PARAMETROS
A1: PARÁMETROS - TAPA DE REGISTRO DE CONCRETO
A3: Descripción | B3: Valor | C3: Unidad | D3: Criterio
A4: Cantidad de tapas | B4: 17 | C4: und | D4: Según resumen: 10 tapas
A5: Largo de tapa | B5: 0.6 | C5: m | D5: Según detalle
A6: Ancho de tapa | B6: 0.6 | C6: m | D6: Según detalle
A7: Espesor de tapa | B7: 0.1 | C7: m | D7: Según detalle
A8: Recubrimiento considerado | B8: 0.025 | C8: m | D8: Editable según plano estructural
A9: Separación de varillas 3/8 | B9: 0.15 | C9: m | D9: Parrilla simple en ambos sentidos
A10: Peso varilla 3/8 | B10: 0.56 | C10: kg/m | D10: Peso unitario usado para metrado
A11: Longitud varilla comercial | B11: 9 | C11: m | D11: Solo equivalente de longitud, sin redondeo
A13: PARÁMETROS - MOVIMIENTO DE TIERRAS
A14: Descripción | B14: Valor | C14: Unidad | D14: Criterio
A15: Espesor de solado sumado a excavación y relleno | B15: 0.1 | C15: m | D15: Solado e=4" bajo la losa. Poner 0 si la altura ya lo incluye
A16: Factor de esponjamiento | B16: 1.2 | C16: - | D16: Eliminación = (excavación − relleno) × factor

Sheet Listas
A1: LISTAS, FACTORES Y PARÁMETROS EDITABLES
A3: DIÁMETRO | B3: FACTOR kg/m | D3: TIPO DE CUNETA | F3: CRITERIO DE CONTEO
A4: 6 mm | B4: 0.222 | D4: ABIERTA | F4: TEÓRICO (L/s+1)
A5: 8 mm | B5: 0.395 | D5: TAPADA | F5: ENTERO (redondeo arriba)
A6: 3/8" | B6: 0.56
A7: 12 mm | B7: 0.888
A8: 1/2" | B8: 0.994
A9: 5/8" | B9: 1.552
A10: 3/4" | B10: 2.235
A11: 1" | B11: 3.973
A13: NOTA
A14: Los factores kg/m son editables. Si el proyecto usa otro factor, cámbialo aquí.
A15: La opción TEÓRICO mantiene cantidades decimales: Longitud / separación + 1.
A16: La opción ENTERO redondea hacia arriba antes de sumar la barra final.

Sheet COLECTOR PARAMETROS
A1: COLECTOR PLUVIAL FRONTAL - PARAMETROS DE METRADO
A2: ENTIDAD | C2: =+RESUMEN!B4 -> GERENCIA TERRITORIAL BAJO MAYO - TARAPOTO
A3: PROYECTO | C3: =+RESUMEN!B5 -> “CREACIÓN DEL SERVICIO DE PROTECCIÓN A MUJERES VÍCTIMAS DE VIOLENCIA EN SITUACIÓN DE RIESGO DE FEMINICIDIO O PELIGRE SU INTEGRIDAD Y/O SALUD FÍSICA Y/O MENTAL EN HOGAR DE REFUGIO TEMPORAL DISTRITO DE MORALES DE LA PROVINCIA DE SAN MARTÍN DEL DEPARTAMENTO DE SAN MARTÍN”, con CUI N.° 2675514
A4: UBICACIÓN | C4: =+RESUMEN!B6 -> SAN MARTIN - SAN MARTIN - MORALES
A5: FECHA | C5: =+RESUMEN!B7 -> 46266
A7: Tramo Hogar de Refugio Temporal (CUI 2675514), empalme con el colector de CAR Mujeres (CUI 2717013). Valores tomados de los planos DP-01 a DP-10 y DA-01 a DA-03 y de la memoria de calculo del colector. Celda amarilla = dato; verde = formula.
A9: N° | B9: PARAMETRO | C9: VALOR | D9: UND | E9: SUSTENTO (lamina / norma / criterio)
A10: 1 | B10: Ancho interior del colector b | C10: 0.8 | D10: m | E10: Lamina DP-04 (secciones); memoria de calculo, hoja DATOS
A11: 2 | B11: Espesor de muros | C11: 0.15 | D11: m | E11: Lamina DP-04; memoria, hoja ESTRUCTURAL
A12: 3 | B12: Espesor de losa de fondo | C12: 0.15 | D12: m | E12: Lamina DP-04
A13: 4 | B13: Espesor de losa superior (tramo normal y cruce de motos) | C13: 0.1 | D13: m | E13: Lamina DP-04 (secciones A y B)
A14: 5 | B14: Espesor de losa superior (cruce de camiones) | C14: 0.25 | D14: m | E14: Lamina DP-04 (seccion C); memoria, hoja ESTRUCTURAL (carga HL-93)
A15: 6 | B15: Espesor de solado | C15: 0.05 | D15: m | E15: Lamina DP-04 y DA-02
A16: 7 | B16: Nivel de piso terminado del frente (cara superior de la losa) | C16: 260.6 | D16: msnm | E16: Lamina DP-02 (perfil) y plano de arquitectura
A17: 8 | B17: Sobreancho de excavacion a cada lado del colector | C17: 0.25 | D17: m | E17: Lamina DA-01: zanja de 1.60 m (1.10 + 2 x 0.25)
A18: 9 | B18: Franja de relleno de nivelacion del retiro, lado via | C18: 1 | D18: m | E18: Lamina DA-01, nota 2
A19: 10 | B19: Recubrimiento del acero | C19: 0.04 | D19: m | E19: Norma E.060, tabla 7.7.1 (concreto en contacto con el suelo)
A20: 11 | B20: Peso de la barra de 3/8" | C20: 0.56 | D20: kg/m | E20: Igual a PARAMETROS!B10 de esta planilla
A21: 12 | B21: Peso de la barra de 1/2" | C21: 0.994 | D21: kg/m | E21: Catalogo del fabricante (0.994 kg/m)
... A24: 15 | B24: Ganchos de cierre del marco (2 x 0.15) | C24: 0.3 | D24: m | E24: Lamina DP-08, cuadro de doblado
A25: 16 | B25: Factor de esponjamiento | C25: =PARAMETROS!$B$16 -> 1.2 | D25: - | E25: Igual a PARAMETROS!B16 de esta planilla
A26: 17 | B26: Espaciamiento de marcos en tramo normal | C26: 0.2 | D26: m | E26: Lamina DP-04 (seccion A) y DP-08
A27: 18 | B27: Espaciamiento de marcos en cruces (motos y camiones) | C27: 0.15 | D27: m | E27: Lamina DP-04 (secciones B y C) y DP-08
A28: 19 | B28: Espaciamiento de barras longitudinales (normal y motos) | C28: 0.25 | D28: m | E28: Lamina DP-04 y DP-08
A29: 20 | B29: Espaciamiento de barras longitudinales (camiones) | C29: 0.2 | D29: m | E29: Lamina DP-04 (seccion C) y DP-08
A30: 21 | B30: Malla de las cajas: espaciamiento 3/8" ambas caras | C30: 0.2 | D30: m | E30: Lamina DP-07
A31: 22 | B31: Factor por traslapes y ganchos de la malla | C31: 1.1 | D31: - | E31: 10 % (traslape 0.40 cada 9.00 m y ganchos de esquina 0.40)
A32: 23 | B32: Numero de registros de limpieza con tapa | C32: 10 | D32: und | E32: Lamina DP-01 (RS-01 a RS-07) + 1 en CL + 2 en CC = 10; hoja COLECTOR REGISTROS Y TAPAS
A33: 24 | B33: Lado de la tapa de concreto | C33: 0.68 | D33: m | E33: Lamina DP-06B
A34: 25 | B34: Espesor de la tapa | C34: 0.08 | D34: m | E34: Lamina DP-06B
A35: 26 | B35: Lado de la abertura en la losa (luz del contramarco) | C35: 0.7 | D35: m | E35: Lamina DP-06B
A36: 27 | B36: Perimetro del contramarco L 1 1/2"x1 1/2"x1/8" (4 x 0.70) | C36: 2.8 | D36: m | E36: Lamina DP-06B
A37: 28 | B37: Perimetro del marco de tapa L 1 1/2"x1 1/2"x1/8" (4 x 0.68) | C37: 2.72 | D37: m | E37: Lamina DP-06B
... A65: 56 | B65: Progresiva del primer quiebre (fin del tramo pegado al cerco) | C65: 58.805 | D65: m | E65: Lamina DP-01

Sheet COLECTOR MOV. TIERRAS
A1: COLECTOR PLUVIAL FRONTAL - METRADO DE MOVIMIENTO DE TIERRAS
A2: ENTIDAD | C2: =+RESUMEN!B4 -> GERENCIA TERRITORIAL BAJO MAYO - TARAPOTO
A3: PROYECTO | C3: =+RESUMEN!B5 -> “CREACIÓN DEL SERVICIO DE PROTECCIÓN A MUJERES VÍCTIMAS DE VIOLENCIA EN SITUACIÓN DE RIESGO DE FEMINICIDIO O PELIGRE SU INTEGRIDAD Y/O SALUD FÍSICA Y/O MENTAL EN HOGAR DE REFUGIO TEMPORAL DISTRITO DE MORALES DE LA PROVINCIA DE SAN MARTÍN DEL DEPARTAMENTO DE SAN MARTÍN”, con CUI N.° 2675514
A4: UBICACIÓN | C4: =+RESUMEN!B6 -> SAN MARTIN - SAN MARTIN - MORALES
A5: FECHA | C5: =+RESUMEN!B7 -> 46266
A7: Criterio (lamina DA-01): LIMPIEZA Y TRAZO = ancho de zanja x L. EXCAVACION = ancho de zanja x Hz x L, con Hz = terreno existente (topografia) - fondo del solado. REFINE = (ancho exterior + 0.10) x L (fondo del solado). RELLENO LATERAL = 2 x sobreancho x Hz x L. RELLENO FRANJA = 1.00 x (NPT - terreno) x L (nivelacion del retiro lado via). h y Hz son valores medios ponderados del tramo (perfil DP-02 y topografia); el detalle cada 2.00 m esta en la memoria de calculo.
A9: N° | B9: TRAMO | C9: ZONA | D9: PROG. INICIO | E9: PROG. FIN | F9: LONGITUD (m) | G9: ALTURA INTERIOR h (m) | H9: e LOSA SUP. (m) | I9: ANCHO EXT. b + 2e (m) | J9: ANCHO DE ZANJA (m) | K9: Hz: TERRENO - FONDO DE SOLADO (m) | L9: NPT - TERRENO (m) | M9: LIMPIEZA Y TRAZO (m2) | N9: EXCAVACION (m3) | O9: REFINE Y NIVELACION (m2) | P9: RELLENO LATERAL DE ZANJA (m3) | Q9: RELLENO FRANJA DE NIVELACION (m3) | R9: SUSTENTO
A10: 1 | B10: tramo normal | C10: NORMAL | D10: 0+000.00 | E10: 0+026.32 | F10: 26.32 | G10: 1.439 | H10: 0.1 | I10: ='COLECTOR PARAMETROS'!$C$10+2*'COLECTOR PARAMETROS'!$C$11 -> 1.1 | J10: =I10+2*'COLECTOR PARAMETROS'!$C$17 -> 1.6 | K10: 1.395 | L10: 0.345 | M10: =J10*F10 -> 42.112 | N10: =J10*K10*F10 -> 58.74624 | O10: =(I10+0.1)*F10 -> 31.584 | P10: =2*'COLECTOR PARAMETROS'!$C$17*K10*F10 -> 18.3582 | Q10: ='COLECTOR PARAMETROS'!$C$18*L10*F10 -> 9.0804 | R10: DP-01 (planta), DP-02 (perfil: fondo y terreno), DP-04 (seccion), DA-01 (criterio)
A11: 2 | B11: cruce de camiones | C11: CAMION | D11: 0+026.32 | E11: 0+031.33 | F11: 5.01 | G11: 1.336 | H11: 0.25 | I11: ='COLECTOR PARAMETROS'!$C$10+2*'COLECTOR PARAMETROS'!$C$11 -> 1.1 | J11: =I11+2*'COLECTOR PARAMETROS'!$C$17 -> 1.6 | K11: 1.274 | L11: 0.513 | M11: =J11*F11 -> 8.016 | N11: =J11*K11*F11 -> 10.212384 | O11: =(I11+0.1)*F11 -> 6.012 | P11: =2*'COLECTOR PARAMETROS'!$C$17*K11*F11 -> 3.19137 | Q11: ='COLECTOR PARAMETROS'!$C$18*L11*F11 -> 2.57013 | R11: DP-01 (planta), DP-02 (perfil: fondo y terreno), DP-04 (seccion), DA-01 (criterio)
A12: 3 | B12: tramo normal | C12: NORMAL | D12: 0+031.33 | E12: 0+039.04 | F12: 7.71 | G12: 1.506 | H12: 0.1 | I12: ='COLECTOR PARAMETROS'!$C$10+2*'COLECTOR PARAMETROS'!$C$11 -> 1.1 | J12: =I12+2*'COLECTOR PARAMETROS'!$C$17 -> 1.6 | K12: 1.368 | L12: 0.437 | M12: =J12*F12 -> 12.336 | N12: =J12*K12*F12 -> 16.875648 | O12: =(I12+0.1)*F12 -> 9.252 | P12: =2*'COLECTOR PARAMETROS'!$C$17*K12*F12 -> 5.27364 | Q12: ='COLECTOR PARAMETROS'!$C$18*L12*F12 -> 3.36927 | R12: DP-01 (planta), DP-02 (perfil: fondo y terreno), DP-04 (seccion), DA-01 (criterio)
A13: 4 | B13: cruce de motos | C13: MOTOS | D13: 0+039.04 | E13: 0+041.04 | F13: 2 | G13: 1.52 | H13: 0.1 | I13: ='COLECTOR PARAMETROS'!$C$10+2*'COLECTOR PARAMETROS'!$C$11 -> 1.1 | J13: =I13+2*'COLECTOR PARAMETROS'!$C$17 -> 1.6 | K13: 1.605 | L13: 0.215 | M13: =J13*F13 -> 3.2 | N13: =J13*K13*F13 -> 5.136 | O13: =(I13+0.1)*F13 -> 2.4 | P13: =2*'COLECTOR PARAMETROS'!$C$17*K13*F13 -> 1.605 | Q13: ='COLECTOR PARAMETROS'!$C$18*L13*F13 -> 0.43 | R13: DP-01 (planta), DP-02 (perfil: fondo y terreno), DP-04 (seccion), DA-01 (criterio)
A14: 5 | B14: tramo normal | C14: NORMAL | D14: 0+041.04 | E14: 0+058.81 | F14: 17.77 | G14: 1.55 | H14: 0.1 | I14: ='COLECTOR PARAMETROS'!$C$10+2*'COLECTOR PARAMETROS'!$C$11 -> 1.1 | J14: =I14+2*'COLECTOR PARAMETROS'!$C$17 -> 1.6 | K14: 1.155 | L14: 0.695 | M14: =J14*F14 -> 28.432 | N14: =J14*K14*F14 -> 32.83896 | O14: =(I14+0.1)*F14 -> 21.324 | P14: =2*'COLECTOR PARAMETROS'!$C$17*K14*F14 -> 10.262175 | Q14: ='COLECTOR PARAMETROS'!$C$18*L14*F14 -> 12.35015 | R14: DP-01 (planta), DP-02 (perfil: fondo y terreno), DP-04 (seccion), DA-01 (criterio)
A15: 6 | B15: tramo diagonal (quiebres) | C15: NORMAL | D15: 0+058.81 | E15: 0+066.89 | F15: 8.08 | G15: 1.589 | H15: 0.1 | I15: ='COLECTOR PARAMETROS'!$C$10+2*'COLECTOR PARAMETROS'!$C$11 -> 1.1 | J15: =I15+2*'COLECTOR PARAMETROS'!$C$17 -> 1.6 | K15: 1.033 | L15: 0.855 | M15: =J15*F15 -> 12.928 | N15: =J15*K15*F15 -> 13.354624 | O15: =(I15+0.1)*F15 -> 9.696 | P15: =2*'COLECTOR PARAMETROS'!$C$17*K15*F15 -> 4.17332 | Q15: ='COLECTOR PARAMETROS'!$C$18*L15*F15 -> 6.9084 | R15: DP-01 (planta), DP-02 (perfil: fondo y terreno), DP-04 (seccion), DA-01 (criterio)
A16: 7 | B16: tramo recto final | C16: NORMAL | D16: 0+066.89 | E16: 0+069.89 | F16: 3 | G16: 1.605 | H16: 0.1 | I16: ='COLECTOR PARAMETROS'!$C$10+2*'COLECTOR PARAMETROS'!$C$11 -> 1.1 | J16: =I16+2*'COLECTOR PARAMETROS'!$C$17 -> 1.6 | K16: 1.062 | L16: 0.843 | M16: =J16*F16 -> 4.8 | N16: =J16*K16*F16 -> 5.0976 | O16: =(I16+0.1)*F16 -> 3.6 | P16: =2*'COLECTOR PARAMETROS'!$C$17*K16*F16 -> 1.593 | Q16: ='COLECTOR PARAMETROS'!$C$18*L16*F16 -> 2.529 | R16: DP-01 (planta), DP-02 (perfil: fondo y terreno), DP-04 (seccion), DA-01 (criterio)
A17: TOTAL COLECTOR (tramos) | F17: =SUM(F10:F16) -> 69.89 | M17: =SUM(M10:M16) -> 111.824 | N17: =SUM(N10:N16) -> 142.26146 | O17: =SUM(O10:O16) -> 83.868 | P17: =SUM(P10:P16) -> 44.456705 | Q17: =SUM(Q10:Q16) -> 37.23735
A19: CAJAS DE LLEGADA (CL) Y DE CAIDA (CC) - lamina DP-07. Excavacion en planta = (largo int. + 2e + 2 x sobreancho) x (ancho int. + 2e + 2 x sobreancho); Hz = terreno - fondo del solado. Relleno = excavacion - volumen exterior de la caja (hasta el terreno).
A20: N° | B20: CAJA | C20: PROG. | D20: LARGO INT. (m) | E20: ANCHO INT. (m) | F20: ALTURA INT. H (m) | G20: COTA DE PISO (msnm) | H20: TERRENO (msnm) | I20: LARGO EXC. (m) | J20: ANCHO EXC. (m) | K20: Hz (m) | L20: VOL. EXTERIOR CAJA (m3) | M20: LIMPIEZA Y TRAZO (m2) | N20: EXCAVACION (m3) | O20: REFINE Y NIVELACION (m2) | P20: RELLENO LATERAL (m3) | Q20: RELLENO FRANJA (m3) | R20: SUSTENTO
A21: 1 | B21: Caja de llegada CL | C21: 0+000.00 | D21: ='COLECTOR PARAMETROS'!$C$44 -> 1.5 | E21: ='COLECTOR PARAMETROS'!$C$45 -> 1 | F21: ='COLECTOR PARAMETROS'!$C$50-'COLECTOR PARAMETROS'!$C$13-G21 -> 2.25 | G21: ='COLECTOR PARAMETROS'!$C$47-'COLECTOR PARAMETROS'!$C$46 -> 258.8 | H21: 260.302 | I21: =D21+2*'COLECTOR PARAMETROS'!$C$11+2*'COLECTOR PARAMETROS'!$C$17 -> 2.3 | J21: =E21+2*'COLECTOR PARAMETROS'!$C$11+2*'COLECTOR PARAMETROS'!$C$17 -> 1.8 | K21: =H21-(G21-'COLECTOR PARAMETROS'!$C$12-'COLECTOR PARAMETROS'!$C$15) -> 1.702 | L21: =(D21+2*'COLECTOR PARAMETROS'!$C$11)*(E21+2*'COLECTOR PARAMETROS'!$C$11)*(F21+'COLECTOR PARAMETROS'!$C$13+'COLECTOR PARAMETROS'!$C$12+'COLECTOR PARAMETROS'!$C$15) -> 5.967 | M21: =I21*J21 -> 4.14 | N21: =I21*J21*K21 -> 7.04628 | O21: =(D21+2*'COLECTOR PARAMETROS'!$C$11+0.1)*(E21+2*'COLECTOR PARAMETROS'!$C$11+0.1) -> 2.66 | P21: =MAX(0,N21-L21) -> 1.07928 | Q21: 0 | R21: DP-07 (planta y cortes de la caja), DP-02 (cotas), DA-01
A22: 2 | B22: Caja de caida CC | C22: 0+069.89 | D22: ='COLECTOR PARAMETROS'!$C$53 -> 3.5 | E22: ='COLECTOR PARAMETROS'!$C$54 -> 1.5 | F22: ='COLECTOR PARAMETROS'!$C$16-'COLECTOR PARAMETROS'!$C$13-G22 -> 2.18 | G22: ='COLECTOR PARAMETROS'!$C$56-'COLECTOR PARAMETROS'!$C$55 -> 258.32 | H22: 259.696 | I22: =D22+2*'COLECTOR PARAMETROS'!$C$11+2*'COLECTOR PARAMETROS'!$C$17 -> 4.3 | J22: =E22+2*'COLECTOR PARAMETROS'!$C$11+2*'COLECTOR PARAMETROS'!$C$17 -> 2.3 | K22: =H22-(G22-'COLECTOR PARAMETROS'!$C$12-'COLECTOR PARAMETROS'!$C$15) -> 1.576 | L22: =(D22+2*'COLECTOR PARAMETROS'!$C$11)*(E22+2*'COLECTOR PARAMETROS'!$C$11)*(F22+'COLECTOR PARAMETROS'!$C$13+'COLECTOR PARAMETROS'!$C$12+'COLECTOR PARAMETROS'!$C$15) -> 16.9632 | M22: =I22*J22 -> 9.89 | N22: =I22*J22*K22 -> 15.58664 | O22: =(D22+2*'COLECTOR PARAMETROS'!$C$11+0.1)*(E22+2*'COLECTOR PARAMETROS'!$C$11+0.1) -> 7.41 | P22: =MAX(0,N22-L22) -> 0 | Q22: 0 | R22: DP-07 (planta y cortes de la caja), DP-02 (cotas), DA-01
A23: TOTAL CAJAS | M23: =SUM(M21:M22) -> 14.03 | N23: =SUM(N21:N22) -> 22.63292 | O23: =SUM(O21:O22) -> 10.07 | P23: =SUM(P21:P22) -> 1.07928 | Q23: =SUM(Q21:Q22) -> 0
A25: RESUMEN PARA LA PLANILLA GENERAL (partidas 01.04.04.01 y 01.04.04.02)
A26: 1 | B26: LIMPIEZA MANUAL DE TERRENO / TRAZO Y REPLANTEO | F26: m2 | G26: =M17 -> 111.824 | H26: =M23 -> 14.03 | I26: =G26+H26 -> 125.854
A27: 2 | B27: EXCAVACION MANUAL DE ZANJAS | F27: m3 | G27: =N17 -> 142.26146 | H27: =N23 -> 22.63292 | I27: =G27+H27 -> 164.89438
A28: 3 | B28: REFINE, NIVELACION Y COMPACTACION | F28: m2 | G28: =O17 -> 83.868 | H28: =O23 -> 10.07 | I28: =G28+H28 -> 93.938
A29: 4 | B29: RELLENO COMPACTADO (lateral + franja + cajas) | F29: m3 | G29: =P17+Q17 -> 81.694055 | H29: =P23+Q23 -> 1.07928 | I29: =G29+H29 -> 82.773335
A30: 5 | B30: ELIMINACION DE MATERIAL EXCEDENTE = (excavacion - relleno) x esponjamiento | F30: m3 | G30: =(I27-I29) -> 82.121041 | H30: ='COLECTOR PARAMETROS'!$C$25 -> 1.2 | I30: =G30*H30 -> 98.545249
A32: Nota: las prolongaciones de las cunetas de los Ejes 11 y 12 (1.88 y 5.39 m hasta el muro del colector) no forman parte de esta partida; se metran dentro de las partidas de cunetas del proyecto.

Sheet COLECTOR CONCRETO
A1: COLECTOR PLUVIAL FRONTAL - METRADO DE CONCRETO SIMPLE Y ARMADO
A2: ENTIDAD | C2: =+RESUMEN!B4 -> GERENCIA TERRITORIAL BAJO MAYO - TARAPOTO
A3: PROYECTO | C3: =+RESUMEN!B5 -> “CREACIÓN DEL SERVICIO DE PROTECCIÓN A MUJERES VÍCTIMAS DE VIOLENCIA EN SITUACIÓN DE RIESGO DE FEMINICIDIO O PELIGRE SU INTEGRIDAD Y/O SALUD FÍSICA Y/O MENTAL EN HOGAR DE REFUGIO TEMPORAL DISTRITO DE MORALES DE LA PROVINCIA DE SAN MARTÍN DEL DEPARTAMENTO DE SAN MARTÍN”, con CUI N.° 2675514
A4: UBICACIÓN | C4: =+RESUMEN!B6 -> SAN MARTIN - SAN MARTIN - MORALES
A5: FECHA | C5: =+RESUMEN!B7 -> 46266
A7: Criterio (lamina DA-02): SOLADO = (ancho exterior + 0.10) x L. LOSA DE FONDO = ancho exterior x e fondo x L. MUROS = 2 x e muro x h x L. LOSA SUPERIOR = ancho exterior x e losa x L. ACABADO = ancho exterior x L (losa superior frotachada y brunada). CURADO = 2 caras interiores de muros (2 x h x L) + fondo interior (b x L) + losa superior (ancho exterior x L), igual al criterio de la hoja METRADO DE CURADO.
A9: N° | B9: TRAMO | C9: ZONA | D9: LONGITUD (m) | E9: ALTURA INTERIOR h (m) | F9: e LOSA SUP. (m) | G9: ANCHO EXT. (m) | H9: SOLADO f'c=100 (m2) | I9: LOSA DE FONDO (m3) | J9: MUROS (m3) | K9: LOSA SUPERIOR (m3) | L9: ACABADO DE LOSA SUP. (m2) | M9: CURADO (m2) | N9: SUSTENTO
A10: 1 | B10: tramo normal | C10: NORMAL | D10: ='COLECTOR MOV. TIERRAS'!F10 -> 26.32 | E10: ='COLECTOR MOV. TIERRAS'!G10 -> 1.439 | F10: ='COLECTOR MOV. TIERRAS'!H10 -> 0.1 | G10: ='COLECTOR MOV. TIERRAS'!I10 -> 1.1 | H10: =(G10+0.1)*D10 -> 31.584 | I10: =G10*'COLECTOR PARAMETROS'!$C$12*D10 -> 4.3428 | J10: =2*'COLECTOR PARAMETROS'!$C$11*E10*D10 -> 11.362344 | K10: =G10*F10*D10 -> 2.8952 | L10: =G10*D10 -> 28.952 | M10: =(2*E10+'COLECTOR PARAMETROS'!$C$10+G10)*D10 -> 125.75696 | N10: DP-04 (secciones A, B, C), DP-02 (h por tramo), DA-02 (areas por metro)
A11: 2 | B11: cruce de camiones | C11: CAMION | D11: ='COLECTOR MOV. TIERRAS'!F11 -> 5.01 | E11: ='COLECTOR MOV. TIERRAS'!G11 -> 1.336 | F11: ='COLECTOR MOV. TIERRAS'!H11 -> 0.25 | G11: ='COLECTOR MOV. TIERRAS'!I11 -> 1.1 | H11: =(G11+0.1)*D11 -> 6.012 | I11: =G11*'COLECTOR PARAMETROS'!$C$12*D11 -> 0.82665 | J11: =2*'COLECTOR PARAMETROS'!$C$11*E11*D11 -> 2.008008 | K11: =G11*F11*D11 -> 1.37775 | L11: =G11*D11 -> 5.511 | M11: =(2*E11+'COLECTOR PARAMETROS'!$C$10+G11)*D11 -> 22.90572 | N11: DP-04 (secciones A, B, C), DP-02 (h por tramo), DA-02 (areas por metro)
A12: 3 | B12: tramo normal | C12: NORMAL | D12: ='COLECTOR MOV. TIERRAS'!F12 -> 7.71 | E12: ='COLECTOR MOV. TIERRAS'!G12 -> 1.506 | F12: ='COLECTOR MOV. TIERRAS'!H12 -> 0.1 | G12: ='COLECTOR MOV. TIERRAS'!I12 -> 1.1 | H12: =(G12+0.1)*D12 -> 9.252 | I12: =G12*'COLECTOR PARAMETROS'!$C$12*D12 -> 1.27215 | J12: =2*'COLECTOR PARAMETROS'!$C$11*E12*D12 -> 3.483378 | K12: =G12*F12*D12 -> 0.8481 | L12: =G12*D12 -> 8.481 | M12: =(2*E12+'COLECTOR PARAMETROS'!$C$10+G12)*D12 -> 37.87152 | N12: DP-04 (secciones A, B, C), DP-02 (h por tramo), DA-02 (areas por metro)
A13: 4 | B13: cruce de motos | C13: MOTOS | D13: ='COLECTOR MOV. TIERRAS'!F13 -> 2 | E13: ='COLECTOR MOV. TIERRAS'!G13 -> 1.52 | F13: ='COLECTOR MOV. TIERRAS'!H13 -> 0.1 | G13: ='COLECTOR MOV. TIERRAS'!I13 -> 1.1 | H13: =(G13+0.1)*D13 -> 2.4 | I13: =G13*'COLECTOR PARAMETROS'!$C$12*D13 -> 0.33 | J13: =2*'COLECTOR PARAMETROS'!$C$11*E13*D13 -> 0.912 | K13: =G13*F13*D13 -> 0.22 | L13: =G13*D13 -> 2.2 | M13: =(2*E13+'COLECTOR PARAMETROS'!$C$10+G13)*D13 -> 9.88 | N13: DP-04 (secciones A, B, C), DP-02 (h por tramo), DA-02 (areas por metro)
A14: 5 | B14: tramo normal | C14: NORMAL | D14: ='COLECTOR MOV. TIERRAS'!F14 -> 17.77 | E14: ='COLECTOR MOV. TIERRAS'!G14 -> 1.55 | F14: ='COLECTOR MOV. TIERRAS'!H14 -> 0.1 | G14: ='COLECTOR MOV. TIERRAS'!I14 -> 1.1 | H14: =(G14+0.1)*D14 -> 21.324 | I14: =G14*'COLECTOR PARAMETROS'!$C$12*D14 -> 2.93205 | J14: =2*'COLECTOR PARAMETROS'!$C$11*E14*D14 -> 8.26305 | K14: =G14*F14*D14 -> 1.9547 | L14: =G14*D14 -> 19.547 | M14: =(2*E14+'COLECTOR PARAMETROS'!$C$10+G14)*D14 -> 88.85 | N14: DP-04 (secciones A, B, C), DP-02 (h por tramo), DA-02 (areas por metro)
A15: 6 | B15: tramo diagonal (quiebres) | C15: NORMAL | D15: ='COLECTOR MOV. TIERRAS'!F15 -> 8.08 | E15: ='COLECTOR MOV. TIERRAS'!G15 -> 1.589 | F15: ='COLECTOR MOV. TIERRAS'!H15 -> 0.1 | G15: ='COLECTOR MOV. TIERRAS'!I15 -> 1.1 | H15: =(G15+0.1)*D15 -> 9.696 | I15: =G15*'COLECTOR PARAMETROS'!$C$12*D15 -> 1.3332 | J15: =2*'COLECTOR PARAMETROS'!$C$11*E15*D15 -> 3.851736 | K15: =G15*F15*D15 -> 0.8888 | L15: =G15*D15 -> 8.888 | M15: =(2*E15+'COLECTOR PARAMETROS'!$C$10+G15)*D15 -> 41.03024 | N15: DP-04 (secciones A, B, C), DP-02 (h por tramo), DA-02 (areas por metro)
A16: 7 | B16: tramo recto final | C16: NORMAL | D16: ='COLECTOR MOV. TIERRAS'!F16 -> 3 | E16: ='COLECTOR MOV. TIERRAS'!G16 -> 1.605 | F16: ='COLECTOR MOV. TIERRAS'!H16 -> 0.1 | G16: ='COLECTOR MOV. TIERRAS'!I16 -> 1.1 | H16: =(G16+0.1)*D16 -> 3.6 | I16: =G16*'COLECTOR PARAMETROS'!$C$12*D16 -> 0.495 | J16: =2*'COLECTOR PARAMETROS'!$C$11*E16*D16 -> 1.4445 | K16: =G16*F16*D16 -> 0.33 | L16: =G16*D16 -> 3.3 | M16: =(2*E16+'COLECTOR PARAMETROS'!$C$10+G16)*D16 -> 15.33 | N16: DP-04 (secciones A, B, C), DP-02 (h por tramo), DA-02 (areas por metro)
A17: TOTAL COLECTOR (tramos) | D17: =SUM(D10:D16) -> 69.89 | H17: =SUM(H10:H16) -> 83.868 | I17: =SUM(I10:I16) -> 11.53185 | J17: =SUM(J10:J16) -> 31.325016 | K17: =SUM(K10:K16) -> 8.51455 | L17: =SUM(L10:L16) -> 76.879 | M17: =SUM(M10:M16) -> 341.62444
A19: CAJAS CL Y CC POR ELEMENTO - lamina DP-07 (dimensiones interiores de la hoja COLECTOR MOV. TIERRAS; e muro = e fondo = 0.15; losa superior e = 0.10)
A20: N° | B20: CAJA / ELEMENTO | C20: DETALLE | D20: LARGO (m) | E20: ANCHO (m) | F20: ALTO / ESPESOR (m) | G20: VECES | H20: SOLADO (m2) | I20: LOSA DE FONDO (m3) | J20: MUROS (m3) | K20: LOSA SUPERIOR (m3) | L20: ACABADO (m2) | M20: CURADO (m2) | N20: SUSTENTO
B21: Caja de llegada CL: solado | C21: fondo + 0.05/lado | D21: ='COLECTOR MOV. TIERRAS'!D21+2*'COLECTOR PARAMETROS'!$C$11+0.1 -> 1.9 | E21: ='COLECTOR MOV. TIERRAS'!E21+2*'COLECTOR PARAMETROS'!$C$11+0.1 -> 1.4 | F21: 1 | G21: 1 | H21: =D21*E21 -> 2.66 | N21: DP-07: solado f'c=100 e=0.05 bajo la losa de fondo
B22: Caja de llegada CL: losa de fondo | C22: exterior x e | D22: ='COLECTOR MOV. TIERRAS'!D21+2*'COLECTOR PARAMETROS'!$C$11 -> 1.8 | E22: ='COLECTOR MOV. TIERRAS'!E21+2*'COLECTOR PARAMETROS'!$C$11 -> 1.3 | F22: ='COLECTOR PARAMETROS'!$C$12 -> 0.15 | G22: 1 | I22: =D22*E22*F22*G22 -> 0.351 | N22: DP-07: losa de fondo e=0.15 (ancho exterior)
B23: Caja de llegada CL: muros largos | C23: exterior x e x H | D23: ='COLECTOR MOV. TIERRAS'!D21+2*'COLECTOR PARAMETROS'!$C$11 -> 1.8 | E23: ='COLECTOR PARAMETROS'!$C$11 -> 0.15 | F23: ='COLECTOR MOV. TIERRAS'!F21 -> 2.25 | G23: 2 | J23: =D23*E23*F23*G23 -> 1.215 | N23: DP-07: dos muros largos de e=0.15, altura interior H
B24: Caja de llegada CL: muros cortos | C24: interior x e x H | D24: ='COLECTOR MOV. TIERRAS'!E21 -> 1 | E24: ='COLECTOR PARAMETROS'!$C$11 -> 0.15 | F24: ='COLECTOR MOV. TIERRAS'!F21 -> 2.25 | G24: 2 | J24: =D24*E24*F24*G24 -> 0.675 | N24: DP-07: dos muros de cierre de e=0.15
B25: Caja de llegada CL: descuento ventana de salida al colector | C25: ancho x alto x e | D25: ='COLECTOR PARAMETROS'!$C$10 -> 0.8 | E25: ='COLECTOR PARAMETROS'!$C$11 -> 0.15 | F25: ='COLECTOR PARAMETROS'!$C$16-'COLECTOR PARAMETROS'!$C$13-'COLECTOR PARAMETROS'!$C$47 -> 1.4 | G25: -1 | J25: =D25*E25*F25*G25 -> -0.168 | N25: DP-07 (corte): salida al colector (muro oeste), 0.80 x 1.40 hasta la losa del colector
B26: Caja de llegada CL: descuento ventana de llegada del CAR Varones | C26: ancho x alto x e | D26: ='COLECTOR PARAMETROS'!$C$48 -> 0.6 | E26: ='COLECTOR PARAMETROS'!$C$11 -> 0.15 | F26: ='COLECTOR PARAMETROS'!$C$50-'COLECTOR PARAMETROS'!$C$13-'COLECTOR PARAMETROS'!$C$49 -> 1.166 | G26: -1 | J26: =D26*E26*F26*G26 -> -0.10494 | N26: DP-07 (corte): ventana del colector del CAR Varones en el muro este, 0.60 x 1.17 hasta el techo de la CL
B27: Caja de llegada CL: descuento ventana cuneta Eje 01 (CAR Varones) | C27: ancho x alto x e | D27: ='COLECTOR PARAMETROS'!$C$51 -> 0.4 | E27: ='COLECTOR PARAMETROS'!$C$11 -> 0.15 | F27: ='COLECTOR PARAMETROS'!$C$50-'COLECTOR PARAMETROS'!$C$13-'COLECTOR PARAMETROS'!$C$52 -> 0.656 | G27: -1 | J27: =D27*E27*F27*G27 -> -0.03936 | N27: DP-07 (planta y corte): ventana 0.40 x 0.66 en el muro norte
B28: Caja de llegada CL: murete del escalon de la poza | C28: ancho x e x desnivel | D28: ='COLECTOR MOV. TIERRAS'!E21 -> 1 | E28: ='COLECTOR PARAMETROS'!$C$11 -> 0.15 | F28: ='COLECTOR PARAMETROS'!$C$46 -> 0.3 | G28: 1 | J28: =D28*E28*F28*G28 -> 0.045 | N28: DP-07 (corte): murete e=0.15 entre el fondo del colector y el piso de la poza
B29: Caja de llegada CL: losa superior | C29: exterior x e | D29: ='COLECTOR MOV. TIERRAS'!D21+2*'COLECTOR PARAMETROS'!$C$11 -> 1.8 | E29: ='COLECTOR MOV. TIERRAS'!E21+2*'COLECTOR PARAMETROS'!$C$11 -> 1.3 | F29: ='COLECTOR PARAMETROS'!$C$13 -> 0.1 | G29: 1 | K29: =D29*E29*F29*G29 -> 0.234 | N29: DP-07: losa superior e=0.10 a nivel del piso terminado (CL en +261.15, CC en +260.60)
B30: Caja de llegada CL: descuento aberturas de registro | C30: 0.70 x 0.70 x e | D30: ='COLECTOR PARAMETROS'!$C$35 -> 0.7 | E30: ='COLECTOR PARAMETROS'!$C$35 -> 0.7 | F30: ='COLECTOR PARAMETROS'!$C$13 -> 0.1 | G30: -1 | K30: =D30*E30*F30*G30 -> -0.049 | N30: DP-06B: 1 abertura(s) de registro en la losa
B31: Caja de llegada CL: acabado de losa superior | C31: exterior | D31: ='COLECTOR MOV. TIERRAS'!D21+2*'COLECTOR PARAMETROS'!$C$11 -> 1.8 | E31: ='COLECTOR MOV. TIERRAS'!E21+2*'COLECTOR PARAMETROS'!$C$11 -> 1.3 | F31: 1 | G31: 1 | L31: =D31*E31 -> 2.34 | N31: DP-07: losa superior frotachada y brunada
B32: Caja de llegada CL: curado | C32: caras int. + fondo + losa | D32: =2*('COLECTOR MOV. TIERRAS'!D21+'COLECTOR MOV. TIERRAS'!E21) -> 5 | E32: ='COLECTOR MOV. TIERRAS'!F21 -> 2.25 | F32: 1 | G32: 1 | M32: =D32*E32+'COLECTOR MOV. TIERRAS'!D21*'COLECTOR MOV. TIERRAS'!E21+('COLECTOR MOV. TIERRAS'!D21+2*'COLECTOR PARAMETROS'!$C$11)*('COLECTOR MOV. TIERRAS'!E21+2*'COLECTOR PARAMETROS'!$C$11) -> 15.09 | N32: Caras interiores de muros (perimetro x H) + fondo interior + losa superior
B33: Caja de caida CC: solado | C33: fondo + 0.05/lado | D33: ='COLECTOR MOV. TIERRAS'!D22+2*'COLECTOR PARAMETROS'!$C$11+0.1 -> 3.9 | E33: ='COLECTOR MOV. TIERRAS'!E22+2*'COLECTOR PARAMETROS'!$C$11+0.1 -> 1.9 | F33: 1 | G33: 1 | H33: =D33*E33 -> 7.41 | N33: DP-07: solado f'c=100 e=0.05 bajo la losa de fondo
B34: Caja de caida CC: losa de fondo | C34: exterior x e | D34: ='COLECTOR MOV. TIERRAS'!D22+2*'COLECTOR PARAMETROS'!$C$11 -> 3.8 | E34: ='COLECTOR MOV. TIERRAS'!E22+2*'COLECTOR PARAMETROS'!$C$11 -> 1.8 | F34: ='COLECTOR PARAMETROS'!$C$12 -> 0.15 | G34: 1 | I34: =D34*E34*F34*G34 -> 1.026 | N34: DP-07: losa de fondo e=0.15 (ancho exterior)
B35: Caja de caida CC: umbral de la poza | C35: 0.25 x 0.40 | D35: ='COLECTOR MOV. TIERRAS'!E22 -> 1.5 | E35: ='COLECTOR PARAMETROS'!$C$60 -> 0.25 | F35: ='COLECTOR PARAMETROS'!$C$61 -> 0.4 | G35: 1 | I35: =D35*E35*F35*G35 -> 0.15 | N35: DP-07: umbral 0.25 x 0.40 en el fondo, borde de la poza
B36: Caja de caida CC: muros largos | C36: exterior x e x H | D36: ='COLECTOR MOV. TIERRAS'!D22+2*'COLECTOR PARAMETROS'!$C$11 -> 3.8 | E36: ='COLECTOR PARAMETROS'!$C$11 -> 0.15 | F36: ='COLECTOR MOV. TIERRAS'!F22 -> 2.18 | G36: 2 | J36: =D36*E36*F36*G36 -> 2.4852 | N36: DP-07: dos muros largos de e=0.15, altura interior H
B37: Caja de caida CC: muros cortos | C37: interior x e x H | D37: ='COLECTOR MOV. TIERRAS'!E22 -> 1.5 | E37: ='COLECTOR PARAMETROS'!$C$11 -> 0.15 | F37: ='COLECTOR MOV. TIERRAS'!F22 -> 2.18 | G37: 1 | J37: =D37*E37*F37*G37 -> 0.4905 | N37: DP-07: muro(s) de cierre; en CC el lado de llegada lo cierra el colector
B38: Caja de caida CC: descuento ventana de salida | C38: ancho x alto x e | D38: ='COLECTOR PARAMETROS'!$C$59 -> 1.5 | E38: ='COLECTOR PARAMETROS'!$C$11 -> 0.15 | F38: ='COLECTOR PARAMETROS'!$C$57+0.5-'COLECTOR PARAMETROS'!$C$56 -> 0.842 | G38: -1 | J38: =D38*E38*F38*G38 -> -0.18945 | N38: DP-07 (corte): ventana de salida al receptor R-01 (0.50 m sobre el nivel de agua)
B39: Caja de caida CC: murete del escalon de la poza | C39: ancho x e x desnivel | D39: ='COLECTOR MOV. TIERRAS'!E22 -> 1.5 | E39: ='COLECTOR PARAMETROS'!$C$11 -> 0.15 | F39: ='COLECTOR PARAMETROS'!$C$58-('COLECTOR PARAMETROS'!$C$56-'COLECTOR PARAMETROS'!$C$55) -> 0.57 | G39: 1 | J39: =D39*E39*F39*G39 -> 0.12825 | N39: DP-07 (corte): murete e=0.15 entre el fondo del colector y el piso de la poza
B40: Caja de caida CC: losa superior | C40: exterior x e | D40: ='COLECTOR MOV. TIERRAS'!D22+2*'COLECTOR PARAMETROS'!$C$11 -> 3.8 | E40: ='COLECTOR MOV. TIERRAS'!E22+2*'COLECTOR PARAMETROS'!$C$11 -> 1.8 | F40: ='COLECTOR PARAMETROS'!$C$13 -> 0.1 | G40: 1 | K40: =D40*E40*F40*G40 -> 0.684 | N40: DP-07: losa superior e=0.10 a nivel del piso terminado (CL en +261.15, CC en +260.60)
B41: Caja de caida CC: descuento aberturas de registro | C41: 0.70 x 0.70 x e | D41: ='COLECTOR PARAMETROS'!$C$35 -> 0.7 | E41: ='COLECTOR PARAMETROS'!$C$35 -> 0.7 | F41: ='COLECTOR PARAMETROS'!$C$13 -> 0.1 | G41: -2 | K41: =D41*E41*F41*G41 -> -0.098 | N41: DP-06B: 2 abertura(s) de registro en la losa
B42: Caja de caida CC: acabado de losa superior | C42: exterior | D42: ='COLECTOR MOV. TIERRAS'!D22+2*'COLECTOR PARAMETROS'!$C$11 -> 3.8 | E42: ='COLECTOR MOV. TIERRAS'!E22+2*'COLECTOR PARAMETROS'!$C$11 -> 1.8 | F42: 1 | G42: 1 | L42: =D42*E42 -> 6.84 | N42: DP-07: losa superior frotachada y brunada
B43: Caja de caida CC: curado | C43: caras int. + fondo + losa | D43: =2*('COLECTOR MOV. TIERRAS'!D22+'COLECTOR MOV. TIERRAS'!E22) -> 10 | E43: ='COLECTOR MOV. TIERRAS'!F22 -> 2.18 | F43: 1 | G43: 1 | M43: =D43*E43+'COLECTOR MOV. TIERRAS'!D22*'COLECTOR MOV. TIERRAS'!E22+('COLECTOR MOV. TIERRAS'!D22+2*'COLECTOR PARAMETROS'!$C$11)*('COLECTOR MOV. TIERRAS'!E22+2*'COLECTOR PARAMETROS'!$C$11) -> 33.89 | N43: Caras interiores de muros (perimetro x H) + fondo interior + losa superior
A44: REGISTROS DE LIMPIEZA EN LA LOSA DEL COLECTOR - lamina DP-06B (borde engrosado 0.15 x 0.10 alrededor de la abertura; descuento de la abertura 0.70 x 0.70 en la losa superior)
B45: Registros: borde engrosado de la abertura | C45: perimetro x seccion | D45: ='COLECTOR PARAMETROS'!$C$42 -> 3 | E45: ='COLECTOR PARAMETROS'!$C$43 -> 0.015 | F45: 1 | G45: ='COLECTOR PARAMETROS'!$C$32 -> 10 | K45: =D45*E45*F45*G45 -> 0.45 | N45: DP-06B: borde engrosado en los 10 registros (7 en la losa del colector, 1 en CL y 2 en CC)
B46: Registros RS-01 a RS-07: descuento de la abertura en la losa superior | C46: 0.70 x 0.70 x e | D46: ='COLECTOR PARAMETROS'!$C$35 -> 0.7 | E46: ='COLECTOR PARAMETROS'!$C$35 -> 0.7 | F46: ='COLECTOR PARAMETROS'!$C$13 -> 0.1 | G46: =-('COLECTOR PARAMETROS'!$C$32-3) -> -7 | K46: =D46*E46*F46*G46 -> -0.343 | N46: DP-06B
A47: TOTAL CAJAS Y REGISTROS | H47: =SUM(H21:H46) -> 10.07 | I47: =SUM(I21:I46) -> 1.527 | J47: =SUM(J21:J46) -> 4.5372 | K47: =SUM(K21:K46) -> 0.878 | L47: =SUM(L21:L46) -> 9.18 | M47: =SUM(M21:M46) -> 48.98
A49: RESUMEN PARA LA PLANILLA GENERAL (partidas 01.04.04.03 y 01.04.04.04)
A50: 1 | B50: CONCRETO f'c=100 PARA SOLADO e=0.05 | F50: m2 | G50: =H17 -> 83.868 | H50: =H47 -> 10.07 | I50: =G50+H50 -> 93.938
A51: 2 | B51: CONCRETO f'c=210 EN LOSA DE FONDO | F51: m3 | G51: =I17 -> 11.53185 | H51: =I47 -> 1.527 | I51: =G51+H51 -> 13.05885
A52: 3 | B52: CONCRETO f'c=210 EN MUROS | F52: m3 | G52: =J17 -> 31.325016 | H52: =J47 -> 4.5372 | I52: =G52+H52 -> 35.862216
A53: 4 | B53: CONCRETO f'c=210 EN LOSA SUPERIOR | F53: m3 | G53: =K17 -> 8.51455 | H53: =K47 -> 0.878 | I53: =G53+H53 -> 9.39255
A54: 5 | B54: ACABADO FROTACHADO DE LOSA SUPERIOR (VEREDA) | F54: m2 | G54: =L17 -> 76.879 | H54: =L47 -> 9.18 | I54: =G54+H54 -> 86.059
A55: 6 | B55: CURADO DE CONCRETO | F55: m2 | G55: =M17 -> 341.62444 | H55: =M47 -> 48.98 | I55: =G55+H55 -> 390.60444

Sheet COLECTOR ENCOFRADO
A1: COLECTOR PLUVIAL FRONTAL - METRADO DE ENCOFRADO Y DESENCOFRADO
A2: ENTIDAD | C2: =+RESUMEN!B4 -> GERENCIA TERRITORIAL BAJO MAYO - TARAPOTO
A3: PROYECTO | C3: =+RESUMEN!B5 -> “CREACIÓN DEL SERVICIO DE PROTECCIÓN A MUJERES VÍCTIMAS DE VIOLENCIA EN SITUACIÓN DE RIESGO DE FEMINICIDIO O PELIGRE SU INTEGRIDAD Y/O SALUD FÍSICA Y/O MENTAL EN HOGAR DE REFUGIO TEMPORAL DISTRITO DE MORALES DE LA PROVINCIA DE SAN MARTÍN DEL DEPARTAMENTO DE SAN MARTÍN”, con CUI N.° 2675514
A4: UBICACIÓN | C4: =+RESUMEN!B6 -> SAN MARTIN - SAN MARTIN - MORALES
A5: FECHA | C5: =+RESUMEN!B7 -> 46266
A7: Criterio (lamina DA-02): se encofran las dos caras interiores de los muros, las dos caras exteriores en toda la altura del cajon (losa de fondo + muro + losa superior) y el fondo de la losa superior (ancho interior b). La losa de fondo se vacia sobre el solado y la cara superior de la losa queda libre (acabado).
A9: N° | B9: TRAMO | C9: ZONA | D9: LONGITUD (m) | E9: ALTURA INTERIOR h (m) | F9: e LOSA SUP. (m) | G9: ANCHO INT. b (m) | H9: CARAS INTERIORES DE MUROS 2 x h x L (m2) | I9: CARAS EXTERIORES 2 x (e fondo + h + e losa) x L (m2) | J9: FONDO DE LOSA SUPERIOR b x L (m2) | K9: TOTAL ENCOFRADO (m2) | L9: SUSTENTO
A10: 1 | B10: tramo normal | C10: NORMAL | D10: ='COLECTOR MOV. TIERRAS'!F10 -> 26.32 | E10: ='COLECTOR MOV. TIERRAS'!G10 -> 1.439 | F10: ='COLECTOR MOV. TIERRAS'!H10 -> 0.1 | G10: ='COLECTOR PARAMETROS'!$C$10 -> 0.8 | H10: =2*E10*D10 -> 75.74896 | I10: =2*('COLECTOR PARAMETROS'!$C$12+E10+F10)*D10 -> 88.90896 | J10: =G10*D10 -> 21.056 | K10: =SUM(H10:J10) -> 185.71392 | L10: DP-04 (secciones), DA-02 (areas por metro)
A11: 2 | B11: cruce de camiones | C11: CAMION | D11: ='COLECTOR MOV. TIERRAS'!F11 -> 5.01 | E11: ='COLECTOR MOV. TIERRAS'!G11 -> 1.336 | F11: ='COLECTOR MOV. TIERRAS'!H11 -> 0.25 | G11: ='COLECTOR PARAMETROS'!$C$10 -> 0.8 | H11: =2*E11*D11 -> 13.38672 | I11: =2*('COLECTOR PARAMETROS'!$C$12+E11+F11)*D11 -> 17.39472 | J11: =G11*D11 -> 4.008 | K11: =SUM(H11:J11) -> 34.78944 | L11: DP-04 (secciones), DA-02 (areas por metro)
A12: 3 | B12: tramo normal | C12: NORMAL | D12: ='COLECTOR MOV. TIERRAS'!F12 -> 7.71 | E12: ='COLECTOR MOV. TIERRAS'!G12 -> 1.506 | F12: ='COLECTOR MOV. TIERRAS'!H12 -> 0.1 | G12: ='COLECTOR PARAMETROS'!$C$10 -> 0.8 | H12: =2*E12*D12 -> 23.22252 | I12: =2*('COLECTOR PARAMETROS'!$C$12+E12+F12)*D12 -> 27.07752 | J12: =G12*D12 -> 6.168 | K12: =SUM(H12:J12) -> 56.46804 | L12: DP-04 (secciones), DA-02 (areas por metro)
A13: 4 | B13: cruce de motos | C13: MOTOS | D13: ='COLECTOR MOV. TIERRAS'!F13 -> 2 | E13: ='COLECTOR MOV. TIERRAS'!G13 -> 1.52 | F13: ='COLECTOR MOV. TIERRAS'!H13 -> 0.1 | G13: ='COLECTOR PARAMETROS'!$C$10 -> 0.8 | H13: =2*E13*D13 -> 6.08 | I13: =2*('COLECTOR PARAMETROS'!$C$12+E13+F13)*D13 -> 7.08 | J13: =G13*D13 -> 1.6 | K13: =SUM(H13:J13) -> 14.76 | L13: DP-04 (secciones), DA-02 (areas por metro)
A14: 5 | B14: tramo normal | C14: NORMAL | D14: ='COLECTOR MOV. TIERRAS'!F14 -> 17.77 | E14: ='COLECTOR MOV. TIERRAS'!G14 -> 1.55 | F14: ='COLECTOR MOV. TIERRAS'!H14 -> 0.1 | G14: ='COLECTOR PARAMETROS'!$C$10 -> 0.8 | H14: =2*E14*D14 -> 55.087 | I14: =2*('COLECTOR PARAMETROS'!$C$12+E14+F14)*D14 -> 63.972 | J14: =G14*D14 -> 14.216 | K14: =SUM(H14:J14) -> 133.275 | L14: DP-04 (secciones), DA-02 (areas por metro)
A15: 6 | B15: tramo diagonal (quiebres) | C15: NORMAL | D15: ='COLECTOR MOV. TIERRAS'!F15 -> 8.08 | E15: ='COLECTOR MOV. TIERRAS'!G15 -> 1.589 | F15: ='COLECTOR MOV. TIERRAS'!H15 -> 0.1 | G15: ='COLECTOR PARAMETROS'!$C$10 -> 0.8 | H15: =2*E15*D15 -> 25.67824 | I15: =2*('COLECTOR PARAMETROS'!$C$12+E15+F15)*D15 -> 29.71824 | J15: =G15*D15 -> 6.464 | K15: =SUM(H15:J15) -> 61.86048 | L15: DP-04 (secciones), DA-02 (areas por metro)
A16: 7 | B16: tramo recto final | C16: NORMAL | D16: ='COLECTOR MOV. TIERRAS'!F16 -> 3 | E16: ='COLECTOR MOV. TIERRAS'!G16 -> 1.605 | F16: ='COLECTOR MOV. TIERRAS'!H16 -> 0.1 | G16: ='COLECTOR PARAMETROS'!$C$10 -> 0.8 | H16: =2*E16*D16 -> 9.63 | I16: =2*('COLECTOR PARAMETROS'!$C$12+E16+F16)*D16 -> 11.13 | J16: =G16*D16 -> 2.4 | K16: =SUM(H16:J16) -> 23.16 | L16: DP-04 (secciones), DA-02 (areas por metro)
A17: TOTAL COLECTOR (tramos) | D17: =SUM(D10:D16) -> 69.89 | H17: =SUM(H10:H16) -> 208.83344 | I17: =SUM(I10:I16) -> 245.28144 | J17: =SUM(J10:J16) -> 55.912 | K17: =SUM(K10:K16) -> 510.02688
A19: CAJAS CL Y CC - lamina DP-07: caras interiores y exteriores de muros (perimetro x H, dos caras), fondo de la losa superior (interior) y, en CC, caras del umbral y del murete de la poza
A20: N° | B20: CAJA / ELEMENTO | C20: DETALLE | D20: LARGO (m) | E20: ALTO (m) | F20: CARAS | K20: AREA (m2) | L20: SUSTENTO
B21: Caja de llegada CL: muros, cara interior y exterior | C21: perimetro int. x H | D21: =2*('COLECTOR MOV. TIERRAS'!D21+'COLECTOR MOV. TIERRAS'!E21) -> 5 | E21: ='COLECTOR MOV. TIERRAS'!F21 -> 2.25 | F21: 2 | K21: =D21*E21*F21 -> 22.5 | L21: DP-07: muros e=0.15 encofrados por ambas caras
B22: Caja de llegada CL: fondo de la losa superior | C22: interior | D22: ='COLECTOR MOV. TIERRAS'!D21 -> 1.5 | E22: ='COLECTOR MOV. TIERRAS'!E21 -> 1 | F22: 1 | K22: =D22*E22*F22 -> 1.5 | L22: DP-07: losa superior e=0.10 encofrada por debajo
B23: Caja de llegada CL: cara del murete de la poza | C23: ancho x desnivel | D23: ='COLECTOR MOV. TIERRAS'!E21 -> 1 | E23: ='COLECTOR PARAMETROS'!$C$46 -> 0.3 | F23: 1 | K23: =D23*E23*F23 -> 0.3 | L23: DP-07 (corte): murete entre el fondo del colector y el piso de la poza
B24: Caja de caida CC: muros, cara interior y exterior | C24: perimetro int. x H | D24: =2*('COLECTOR MOV. TIERRAS'!D22+'COLECTOR MOV. TIERRAS'!E22) -> 10 | E24: ='COLECTOR MOV. TIERRAS'!F22 -> 2.18 | F24: 2 | K24: =D24*E24*F24 -> 43.6 | L24: DP-07: muros e=0.15 encofrados por ambas caras
B25: Caja de caida CC: fondo de la losa superior | C25: interior | D25: ='COLECTOR MOV. TIERRAS'!D22 -> 3.5 | E25: ='COLECTOR MOV. TIERRAS'!E22 -> 1.5 | F25: 1 | K25: =D25*E25*F25 -> 5.25 | L25: DP-07: losa superior e=0.10 encofrada por debajo
B26: Caja de caida CC: caras del umbral de la poza | C26: 2 caras x ancho | D26: ='COLECTOR MOV. TIERRAS'!E22 -> 1.5 | E26: ='COLECTOR PARAMETROS'!$C$61 -> 0.4 | F26: 2 | K26: =D26*E26*F26 -> 1.2 | L26: DP-07: umbral 0.25 x 0.40
B27: Caja de caida CC: cara del murete de la poza | C27: ancho x desnivel | D27: ='COLECTOR MOV. TIERRAS'!E22 -> 1.5 | E27: ='COLECTOR PARAMETROS'!$C$58-('COLECTOR PARAMETROS'!$C$56-'COLECTOR PARAMETROS'!$C$55) -> 0.57 | F27: 1 | K27: =D27*E27*F27 -> 0.855 | L27: DP-07 (corte): murete entre el fondo del colector y el piso de la poza
A28: TOTAL CAJAS | K28: =SUM(K21:K27) -> 75.205
A30: RESUMEN PARA LA PLANILLA GENERAL (partida 01.04.04.04.04)
A31: 1 | B31: ENCOFRADO Y DESENCOFRADO DE COLECTOR | F31: m2 | G31: =K17 -> 510.02688 | H31: =K28 -> 75.205 | I31: =G31+H31 -> 585.23188

Sheet COLECTOR ACERO
A1: COLECTOR PLUVIAL FRONTAL - METRADO DE ACERO DE REFUERZO fy=4200 kg/cm2
A2: ENTIDAD | C2: =+RESUMEN!B4 -> GERENCIA TERRITORIAL BAJO MAYO - TARAPOTO
A3: PROYECTO | C3: =+RESUMEN!B5 -> “CREACIÓN DEL SERVICIO DE PROTECCIÓN A MUJERES VÍCTIMAS DE VIOLENCIA EN SITUACIÓN DE RIESGO DE FEMINICIDIO O PELIGRE SU INTEGRIDAD Y/O SALUD FÍSICA Y/O MENTAL EN HOGAR DE REFUGIO TEMPORAL DISTRITO DE MORALES DE LA PROVINCIA DE SAN MARTÍN DEL DEPARTAMENTO DE SAN MARTÍN”, con CUI N.° 2675514
A4: UBICACIÓN | C4: =+RESUMEN!B6 -> SAN MARTIN - SAN MARTIN - MORALES
A5: FECHA | C5: =+RESUMEN!B7 -> 46266
A7: Criterio (laminas DP-04 y DP-08, norma E.060 14.3.4): tramo normal y cruce de motos llevan un solo marco cerrado en el eje de muros y losas (perimetro = 2 x (ancho ext. - e) + 2 x (e fondo/2 + h + e losa/2) + ganchos); el cruce de camiones lleva marco exterior + marco interior de 1/2" (perimetros con recubrimiento 0.04). Barras longitudinales 3/8" en cada marco, con traslape de 0.40 cada 9.00 m. Peso: 3/8" = 0.56 kg/m, 1/2" = 0.994 kg/m.
A9: N° | B9: TRAMO | C9: ZONA | D9: LONGITUD (m) | E9: ALTURA INTERIOR h (m) | F9: e LOSA SUP. (m) | G9: ANCHO EXT. (m) | H9: ESPAC. MARCOS s (m) | I9: CAPAS (1 = marco unico; 2 = ext. + int.) | J9: DIAM. MARCOS | K9: N° DE JUEGOS (L / s, redondeado arriba) | L9: PERIMETRO MARCO 1 (m) | M9: PERIMETRO MARCO 2 (m) | N9: LONGITUD DE MARCOS (m) | O9: PESO (kg/m) | P9: ACERO EN MARCOS (kg) | Q9: ESPAC. LONGIT. (m) | R9: N° BARRAS LONGIT. (perimetro / espac.) | S9: LONGITUD LONGIT. CON TRASLAPE (m) | T9: ACERO LONGIT. 3/8" (kg) | U9: TOTAL (kg) | V9: SUSTENTO
A10: 1 | B10: tramo normal | C10: NORMAL | D10: ='COLECTOR MOV. TIERRAS'!F10 -> 26.32 | E10: ='COLECTOR MOV. TIERRAS'!G10 -> 1.439 | F10: ='COLECTOR MOV. TIERRAS'!H10 -> 0.1 | G10: ='COLECTOR MOV. TIERRAS'!I10 -> 1.1 | H10: ='COLECTOR PARAMETROS'!$C$26 -> 0.2 | I10: 1 | J10: 3/8" | K10: =ROUNDUP(D10/H10,0) -> 132 | L10: =IF(I10=2,2*(G10-2*'COLECTOR PARAMETROS'!$C$19)+2*('COLECTOR PARAMETROS'!$C$12+E10+F10-2*'COLECTOR PARAMETROS'!$C$19)+'COLECTOR PARAMETROS'!$C$24,2*(G10-'COLECTOR PARAMETROS'!$C$11)+2*('COLECTOR PARAMETROS'!$C$12/2+E10+F10/2)+'COLECTOR PARAMETROS'!$C$24) -> 5.328 | M10: =IF(I10=2,2*('COLECTOR PARAMETROS'!$C$10+2*('COLECTOR PARAMETROS'!$C$11-'COLECTOR PARAMETROS'!$C$19))+2*(E10+2*('COLECTOR PARAMETROS'!$C$11-'COLECTOR PARAMETROS'!$C$19))+'COLECTOR PARAMETROS'!$C$24,0) -> 0 | N10: =K10*(L10+M10) -> 703.296 | O10: =IF(J10="1/2""",'COLECTOR PARAMETROS'!$C$21,'COLECTOR PARAMETROS'!$C$20) -> 0.56 | P10: =N10*O10 -> 393.84576 | Q10: ='COLECTOR PARAMETROS'!$C$28 -> 0.25 | R10: =ROUND(L10/Q10,0)+IF(M10>0,ROUND(M10/Q10,0),0) -> 21 | S10: =R10*D10*(1+'COLECTOR PARAMETROS'!$C$22/'COLECTOR PARAMETROS'!$C$23) -> 577.28533 | T10: =S10*'COLECTOR PARAMETROS'!$C$20 -> 323.27979 | U10: =P10+T10 -> 717.12555 | V10: DP-04 (seccion A), DP-08 (cuadro de doblado), DA-03
A11: 2 | B11: cruce de camiones | C11: CAMION | D11: ='COLECTOR MOV. TIERRAS'!F11 -> 5.01 | E11: ='COLECTOR MOV. TIERRAS'!G11 -> 1.336 | F11: ='COLECTOR MOV. TIERRAS'!H11 -> 0.25 | G11: ='COLECTOR MOV. TIERRAS'!I11 -> 1.1 | H11: ='COLECTOR PARAMETROS'!$C$27 -> 0.15 | I11: 2 | J11: 1/2" | K11: =ROUNDUP(D11/H11,0) -> 34 | L11: =IF(I11=2,2*(G11-2*'COLECTOR PARAMETROS'!$C$19)+2*('COLECTOR PARAMETROS'!$C$12+E11+F11-2*'COLECTOR PARAMETROS'!$C$19)+'COLECTOR PARAMETROS'!$C$24,2*(G11-'COLECTOR PARAMETROS'!$C$11)+2*('COLECTOR PARAMETROS'!$C$12/2+E11+F11/2)+'COLECTOR PARAMETROS'!$C$24) -> 5.652 | M11: =IF(I11=2,2*('COLECTOR PARAMETROS'!$C$10+2*('COLECTOR PARAMETROS'!$C$11-'COLECTOR PARAMETROS'!$C$19))+2*(E11+2*('COLECTOR PARAMETROS'!$C$11-'COLECTOR PARAMETROS'!$C$19))+'COLECTOR PARAMETROS'!$C$24,0) -> 5.452 | N11: =K11*(L11+M11) -> 377.536 | O11: =IF(J11="1/2""",'COLECTOR PARAMETROS'!$C$21,'COLECTOR PARAMETROS'!$C$20) -> 0.994 | P11: =N11*O11 -> 375.27078 | Q11: ='COLECTOR PARAMETROS'!$C$29 -> 0.2 | R11: =ROUND(L11/Q11,0)+IF(M11>0,ROUND(M11/Q11,0),0) -> 55 | S11: =R11*D11*(1+'COLECTOR PARAMETROS'!$C$22/'COLECTOR PARAMETROS'!$C$23) -> 287.79667 | T11: =S11*'COLECTOR PARAMETROS'!$C$20 -> 161.16613 | U11: =P11+T11 -> 536.43692 | V11: DP-04 (seccion C), DP-08 (cuadro de doblado), DA-03
A12: 3 | B12: tramo normal | C12: NORMAL | D12: ='COLECTOR MOV. TIERRAS'!F12 -> 7.71 | E12: ='COLECTOR MOV. TIERRAS'!G12 -> 1.506 | F12: ='COLECTOR MOV. TIERRAS'!H12 -> 0.1 | G12: ='COLECTOR MOV. TIERRAS'!I12 -> 1.1 | H12: ='COLECTOR PARAMETROS'!$C$26 -> 0.2 | I12: 1 | J12: 3/8" | K12: =ROUNDUP(D12/H12,0) -> 39 | L12: =IF(I12=2,2*(G12-2*'COLECTOR PARAMETROS'!$C$19)+2*('COLECTOR PARAMETROS'!$C$12+E12+F12-2*'COLECTOR PARAMETROS'!$C$19)+'COLECTOR PARAMETROS'!$C$24,2*(G12-'COLECTOR PARAMETROS'!$C$11)+2*('COLECTOR PARAMETROS'!$C$12/2+E12+F12/2)+'COLECTOR PARAMETROS'!$C$24) -> 5.462 | M12: =IF(I12=2,2*('COLECTOR PARAMETROS'!$C$10+2*('COLECTOR PARAMETROS'!$C$11-'COLECTOR PARAMETROS'!$C$19))+2*(E12+2*('COLECTOR PARAMETROS'!$C$11-'COLECTOR PARAMETROS'!$C$19))+'COLECTOR PARAMETROS'!$C$24,0) -> 0 | N12: =K12*(L12+M12) -> 213.018 | O12: =IF(J12="1/2""",'COLECTOR PARAMETROS'!$C$21,'COLECTOR PARAMETROS'!$C$20) -> 0.56 | P12: =N12*O12 -> 119.29008 | Q12: ='COLECTOR PARAMETROS'!$C$28 -> 0.25 | R12: =ROUND(L12/Q12,0)+IF(M12>0,ROUND(M12/Q12,0),0) -> 22 | S12: =R12*D12*(1+'COLECTOR PARAMETROS'!$C$22/'COLECTOR PARAMETROS'!$C$23) -> 177.15867 | T12: =S12*'COLECTOR PARAMETROS'!$C$20 -> 99.208853 | U12: =P12+T12 -> 218.49893 | V12: DP-04 (seccion A), DP-08 (cuadro de doblado), DA-03
A13: 4 | B13: cruce de motos | C13: MOTOS | D13: ='COLECTOR MOV. TIERRAS'!F13 -> 2 | E13: ='COLECTOR MOV. TIERRAS'!G13 -> 1.52 | F13: ='COLECTOR MOV. TIERRAS'!H13 -> 0.1 | G13: ='COLECTOR MOV. TIERRAS'!I13 -> 1.1 | H13: ='COLECTOR PARAMETROS'!$C$27 -> 0.15 | I13: 1 | J13: 3/8" | K13: =ROUNDUP(D13/H13,0) -> 14 | L13: =IF(I13=2,2*(G13-2*'COLECTOR PARAMETROS'!$C$19)+2*('COLECTOR PARAMETROS'!$C$12+E13+F13-2*'COLECTOR PARAMETROS'!$C$19)+'COLECTOR PARAMETROS'!$C$24,2*(G13-'COLECTOR PARAMETROS'!$C$11)+2*('COLECTOR PARAMETROS'!$C$12/2+E13+F13/2)+'COLECTOR PARAMETROS'!$C$24) -> 5.49 | M13: =IF(I13=2,2*('COLECTOR PARAMETROS'!$C$10+2*('COLECTOR PARAMETROS'!$C$11-'COLECTOR PARAMETROS'!$C$19))+2*(E13+2*('COLECTOR PARAMETROS'!$C$11-'COLECTOR PARAMETROS'!$C$19))+'COLECTOR PARAMETROS'!$C$24,0) -> 0 | N13: =K13*(L13+M13) -> 76.86 | O13: =IF(J13="1/2""",'COLECTOR PARAMETROS'!$C$21,'COLECTOR PARAMETROS'!$C$20) -> 0.56 | P13: =N13*O13 -> 43.0416 | Q13: ='COLECTOR PARAMETROS'!$C$28 -> 0.25 | R13: =ROUND(L13/Q13,0)+IF(M13>0,ROUND(M13/Q13,0),0) -> 22 | S13: =R13*D13*(1+'COLECTOR PARAMETROS'!$C$22/'COLECTOR PARAMETROS'!$C$23) -> 45.955556 | T13: =S13*'COLECTOR PARAMETROS'!$C$20 -> 25.735111 | U13: =P13+T13 -> 68.776711 | V13: DP-04 (seccion B), DP-08 (cuadro de doblado), DA-03
A14: 5 | B14: tramo normal | C14: NORMAL | D14: ='COLECTOR MOV. TIERRAS'!F14 -> 17.77 | E14: ='COLECTOR MOV. TIERRAS'!G14 -> 1.55 | F14: ='COLECTOR MOV. TIERRAS'!H14 -> 0.1 | G14: ='COLECTOR MOV. TIERRAS'!I14 -> 1.1 | H14: ='COLECTOR PARAMETROS'!$C$26 -> 0.2 | I14: 1 | J14: 3/8" | K14: =ROUNDUP(D14/H14,0) -> 89 | L14: =IF(I14=2,2*(G14-2*'COLECTOR PARAMETROS'!$C$19)+2*('COLECTOR PARAMETROS'!$C$12+E14+F14-2*'COLECTOR PARAMETROS'!$C$19)+'COLECTOR PARAMETROS'!$C$24,2*(G14-'COLECTOR PARAMETROS'!$C$11)+2*('COLECTOR PARAMETROS'!$C$12/2+E14+F14/2)+'COLECTOR PARAMETROS'!$C$24) -> 5.55 | M14: =IF(I14=2,2*('COLECTOR PARAMETROS'!$C$10+2*('COLECTOR PARAMETROS'!$C$11-'COLECTOR PARAMETROS'!$C$19))+2*(E14+2*('COLECTOR PARAMETROS'!$C$11-'COLECTOR PARAMETROS'!$C$19))+'COLECTOR PARAMETROS'!$C$24,0) -> 0 | N14: =K14*(L14+M14) -> 493.95 | O14: =IF(J14="1/2""",'COLECTOR PARAMETROS'!$C$21,'COLECTOR PARAMETROS'!$C$20) -> 0.56 | P14: =N14*O14 -> 276.612 | Q14: ='COLECTOR PARAMETROS'!$C$28 -> 0.25 | R14: =ROUND(L14/Q14,0)+IF(M14>0,ROUND(M14/Q14,0),0) -> 22 | S14: =R14*D14*(1+'COLECTOR PARAMETROS'!$C$22/'COLECTOR PARAMETROS'!$C$23) -> 408.31511 | T14: =S14*'COLECTOR PARAMETROS'!$C$20 -> 228.65646 | U14: =P14+T14 -> 505.26846 | V14: DP-04 (seccion A), DP-08 (cuadro de doblado), DA-03
A15: 6 | B15: tramo diagonal (quiebres) | C15: NORMAL | D15: ='COLECTOR MOV. TIERRAS'!F15 -> 8.08 | E15: ='COLECTOR MOV. TIERRAS'!G15 -> 1.589 | F15: ='COLECTOR MOV. TIERRAS'!H15 -> 0.1 | G15: ='COLECTOR MOV. TIERRAS'!I15 -> 1.1 | H15: ='COLECTOR PARAMETROS'!$C$26 -> 0.2 | I15: 1 | J15: 3/8" | K15: =ROUNDUP(D15/H15,0) -> 41 | L15: =IF(I15=2,2*(G15-2*'COLECTOR PARAMETROS'!$C$19)+2*('COLECTOR PARAMETROS'!$C$12+E15+F15-2*'COLECTOR PARAMETROS'!$C$19)+'COLECTOR PARAMETROS'!$C$24,2*(G15-'COLECTOR PARAMETROS'!$C$11)+2*('COLECTOR PARAMETROS'!$C$12/2+E15+F15/2)+'COLECTOR PARAMETROS'!$C$24) -> 5.628 | M15: =IF(I15=2,2*('COLECTOR PARAMETROS'!$C$10+2*('COLECTOR PARAMETROS'!$C$11-'COLECTOR PARAMETROS'!$C$19))+2*(E15+2*('COLECTOR PARAMETROS'!$C$11-'COLECTOR PARAMETROS'!$C$19))+'COLECTOR PARAMETROS'!$C$24,0) -> 0 | N15: =K15*(L15+M15) -> 230.748 | O15: =IF(J15="1/2""",'COLECTOR PARAMETROS'!$C$21,'COLECTOR PARAMETROS'!$C$20) -> 0.56 | P15: =N15*O15 -> 129.21888 | Q15: ='COLECTOR PARAMETROS'!$C$28 -> 0.25 | R15: =ROUND(L15/Q15,0)+IF(M15>0,ROUND(M15/Q15,0),0) -> 23 | S15: =R15*D15*(1+'COLECTOR PARAMETROS'!$C$22/'COLECTOR PARAMETROS'!$C$23) -> 194.09956 | T15: =S15*'COLECTOR PARAMETROS'!$C$20 -> 108.69575 | U15: =P15+T15 -> 237.91463 | V15: DP-04 (seccion A), DP-08 (cuadro de doblado), DA-03
A16: 7 | B16: tramo recto final | C16: NORMAL | D16: ='COLECTOR MOV. TIERRAS'!F16 -> 3 | E16: ='COLECTOR MOV. TIERRAS'!G16 -> 1.605 | F16: ='COLECTOR MOV. TIERRAS'!H16 -> 0.1 | G16: ='COLECTOR MOV. TIERRAS'!I16 -> 1.1 | H16: ='COLECTOR PARAMETROS'!$C$26 -> 0.2 | I16: 1 | J16: 3/8" | K16: =ROUNDUP(D16/H16,0) -> 15 | L16: =IF(I16=2,2*(G16-2*'COLECTOR PARAMETROS'!$C$19)+2*('COLECTOR PARAMETROS'!$C$12+E16+F16-2*'COLECTOR PARAMETROS'!$C$19)+'COLECTOR PARAMETROS'!$C$24,2*(G16-'COLECTOR PARAMETROS'!$C$11)+2*('COLECTOR PARAMETROS'!$C$12/2+E16+F16/2)+'COLECTOR PARAMETROS'!$C$24) -> 5.66 | M16: =IF(I16=2,2*('COLECTOR PARAMETROS'!$C$10+2*('COLECTOR PARAMETROS'!$C$11-'COLECTOR PARAMETROS'!$C$19))+2*(E16+2*('COLECTOR PARAMETROS'!$C$11-'COLECTOR PARAMETROS'!$C$19))+'COLECTOR PARAMETROS'!$C$24,0) -> 0 | N16: =K16*(L16+M16) -> 84.9 | O16: =IF(J16="1/2""",'COLECTOR PARAMETROS'!$C$21,'COLECTOR PARAMETROS'!$C$20) -> 0.56 | P16: =N16*O16 -> 47.544 | Q16: ='COLECTOR PARAMETROS'!$C$28 -> 0.25 | R16: =ROUND(L16/Q16,0)+IF(M16>0,ROUND(M16/Q16,0),0) -> 23 | S16: =R16*D16*(1+'COLECTOR PARAMETROS'!$C$22/'COLECTOR PARAMETROS'!$C$23) -> 72.066667 | T16: =S16*'COLECTOR PARAMETROS'!$C$20 -> 40.357333 | U16: =P16+T16 -> 87.901333 | V16: DP-04 (seccion A), DP-08 (cuadro de doblado), DA-03
A17: TOTAL COLECTOR (tramos) | D17: =SUM(D10:D16) -> 69.89 | N17: =SUM(N10:N16) -> 2180.308 | P17: =SUM(P10:P16) -> 1384.8231 | S17: =SUM(S10:S16) -> 1762.6776 | T17: =SUM(T10:T16) -> 987.09943 | U17: =SUM(U10:U16) -> 2371.9225
A19: CAJAS CL Y CC - lamina DP-07: malla 3/8" @0.20 en ambas caras de losas y muros. Por paño: barras = (L1 / s + 1) x L2 + (L2 / s + 1) x L1, por el numero de caras y el factor de traslapes y ganchos
A20: N° | B20: CAJA / PAÑO | C20: DETALLE | D20: L1 (m) | E20: L2 (m) | F20: ESPAC. s (m) | G20: CARAS | H20: PAÑOS IGUALES | I20: BARRAS (m) | J20: FACTOR TRASLAPE | K20: PESO (kg/m) | U20: ACERO (kg) | V20: SUSTENTO
B21: Caja de llegada CL: losa de fondo | C21: exterior | D21: ='COLECTOR MOV. TIERRAS'!D21+2*'COLECTOR PARAMETROS'!$C$11 -> 1.8 | E21: ='COLECTOR MOV. TIERRAS'!E21+2*'COLECTOR PARAMETROS'!$C$11 -> 1.3 | F21: ='COLECTOR PARAMETROS'!$C$30 -> 0.2 | G21: 2 | H21: 1 | I21: =((D21/F21+1)*E21+(E21/F21+1)*D21)*G21*H21 -> 53 | J21: ='COLECTOR PARAMETROS'!$C$31 -> 1.1 | K21: ='COLECTOR PARAMETROS'!$C$20 -> 0.56 | U21: =I21*J21*K21 -> 32.648 | V21: DP-07: malla 3/8" @0.20 ambas caras
B22: Caja de llegada CL: losa superior | C22: exterior | D22: ='COLECTOR MOV. TIERRAS'!D21+2*'COLECTOR PARAMETROS'!$C$11 -> 1.8 | E22: ='COLECTOR MOV. TIERRAS'!E21+2*'COLECTOR PARAMETROS'!$C$11 -> 1.3 | F22: ='COLECTOR PARAMETROS'!$C$30 -> 0.2 | G22: 2 | H22: 1 | I22: =((D22/F22+1)*E22+(E22/F22+1)*D22)*G22*H22 -> 53 | J22: ='COLECTOR PARAMETROS'!$C$31 -> 1.1 | K22: ='COLECTOR PARAMETROS'!$C$20 -> 0.56 | U22: =I22*J22*K22 -> 32.648 | V22: DP-07: malla 3/8" @0.20 ambas caras
B23: Caja de llegada CL: muros largos | C23: exterior x H | D23: ='COLECTOR MOV. TIERRAS'!D21+2*'COLECTOR PARAMETROS'!$C$11 -> 1.8 | E23: ='COLECTOR MOV. TIERRAS'!F21 -> 2.25 | F23: ='COLECTOR PARAMETROS'!$C$30 -> 0.2 | G23: 2 | H23: 2 | I23: =((D23/F23+1)*E23+(E23/F23+1)*D23)*G23*H23 -> 178.2 | J23: ='COLECTOR PARAMETROS'!$C$31 -> 1.1 | K23: ='COLECTOR PARAMETROS'!$C$20 -> 0.56 | U23: =I23*J23*K23 -> 109.7712 | V23: DP-07: dos muros largos, malla ambas caras
B24: Caja de llegada CL: muros cortos | C24: interior x H | D24: ='COLECTOR MOV. TIERRAS'!E21 -> 1 | E24: ='COLECTOR MOV. TIERRAS'!F21 -> 2.25 | F24: ='COLECTOR PARAMETROS'!$C$30 -> 0.2 | G24: 2 | H24: 2 | I24: =((D24/F24+1)*E24+(E24/F24+1)*D24)*G24*H24 -> 103 | J24: ='COLECTOR PARAMETROS'!$C$31 -> 1.1 | K24: ='COLECTOR PARAMETROS'!$C$20 -> 0.56 | U24: =I24*J24*K24 -> 63.448 | V24: DP-07: muro(s) de cierre, malla ambas caras
B25: Caja de caida CC: losa de fondo | C25: exterior | D25: ='COLECTOR MOV. TIERRAS'!D22+2*'COLECTOR PARAMETROS'!$C$11 -> 3.8 | E25: ='COLECTOR MOV. TIERRAS'!E22+2*'COLECTOR PARAMETROS'!$C$11 -> 1.8 | F25: ='COLECTOR PARAMETROS'!$C$30 -> 0.2 | G25: 2 | H25: 1 | I25: =((D25/F25+1)*E25+(E25/F25+1)*D25)*G25*H25 -> 148 | J25: ='COLECTOR PARAMETROS'!$C$31 -> 1.1 | K25: ='COLECTOR PARAMETROS'!$C$20 -> 0.56 | U25: =I25*J25*K25 -> 91.168 | V25: DP-07: malla 3/8" @0.20 ambas caras
B26: Caja de caida CC: losa superior | C26: exterior | D26: ='COLECTOR MOV. TIERRAS'!D22+2*'COLECTOR PARAMETROS'!$C$11 -> 3.8 | E26: ='COLECTOR MOV. TIERRAS'!E22+2*'COLECTOR PARAMETROS'!$C$11 -> 1.8 | F26: ='COLECTOR PARAMETROS'!$C$30 -> 0.2 | G26: 2 | H26: 1 | I26: =((D26/F26+1)*E26+(E26/F26+1)*D26)*G26*H26 -> 148 | J26: ='COLECTOR PARAMETROS'!$C$31 -> 1.1 | K26: ='COLECTOR PARAMETROS'!$C$20 -> 0.56 | U26: =I26*J26*K26 -> 91.168 | V26: DP-07: malla 3/8" @0.20 ambas caras
B27: Caja de caida CC: muros largos | C27: exterior x H | D27: ='COLECTOR MOV. TIERRAS'!D22+2*'COLECTOR PARAMETROS'!$C$11 -> 3.8 | E27: ='COLECTOR MOV. TIERRAS'!F22 -> 2.18 | F27: ='COLECTOR PARAMETROS'!$C$30 -> 0.2 | G27: 2 | H27: 2 | I27: =((D27/F27+1)*E27+(E27/F27+1)*D27)*G27*H27 -> 355.28 | J27: ='COLECTOR PARAMETROS'!$C$31 -> 1.1 | K27: ='COLECTOR PARAMETROS'!$C$20 -> 0.56 | U27: =I27*J27*K27 -> 218.85248 | V27: DP-07: dos muros largos, malla ambas caras
B28: Caja de caida CC: muros cortos | C28: interior x H | D28: ='COLECTOR MOV. TIERRAS'!E22 -> 1.5 | E28: ='COLECTOR MOV. TIERRAS'!F22 -> 2.18 | F28: ='COLECTOR PARAMETROS'!$C$30 -> 0.2 | G28: 2 | H28: 1 | I28: =((D28/F28+1)*E28+(E28/F28+1)*D28)*G28*H28 -> 72.76 | J28: ='COLECTOR PARAMETROS'!$C$31 -> 1.1 | K28: ='COLECTOR PARAMETROS'!$C$20 -> 0.56 | U28: =I28*J28*K28 -> 44.82016 | V28: DP-07: muro(s) de cierre, malla ambas caras
A29: TOTAL CAJAS | U29: =SUM(U21:U28) -> 684.52384
A31: REGISTROS DE LIMPIEZA Y TAPAS - lamina DP-06B: refuerzo de borde de la abertura, parrilla de la tapa, asas y anclajes del contramarco (cantidad de registros de la hoja COLECTOR REGISTROS Y TAPAS)
A32: N° | B32: ELEMENTO | C32: DIAM. | D32: FORMA | E32: PIEZAS POR REGISTRO | F32: REGISTROS | G32: LONG. POR PIEZA (m) | H32: LONG. TOTAL (m) | I32: PESO (kg/m) | U32: ACERO (kg) | V32: SUSTENTO
A33: 1 | B33: Refuerzo de borde de la abertura | C33: 1/2" | D33: recta | E33: 8 | F33: ='COLECTOR PARAMETROS'!$C$32 -> 10 | G33: 1.4 | H33: =E33*F33*G33 -> 112 | I33: ='COLECTOR PARAMETROS'!$C$21 -> 0.994 | U33: =H33*I33 -> 111.328 | V33: DP-06B: 2 barras de 1/2" por lado, L = 1.40
A34: 2 | B34: Parrilla de la tapa de concreto | C34: 3/8" | D34: recta | E34: 14 | F34: ='COLECTOR PARAMETROS'!$C$32 -> 10 | G34: 0.62 | H34: =E34*F34*G34 -> 86.8 | I34: ='COLECTOR PARAMETROS'!$C$20 -> 0.56 | U34: =H34*I34 -> 48.608 | V34: DP-06B: 7 + 7 barras 3/8" @0.10
A35: 3 | B35: Asas de la tapa | C35: 3/8" liso | D35: U | E35: 2 | F35: ='COLECTOR PARAMETROS'!$C$32 -> 10 | G35: 0.4 | H35: =E35*F35*G35 -> 8 | I35: ='COLECTOR PARAMETROS'!$C$20 -> 0.56 | U35: =H35*I35 -> 4.48 | V35: DP-06B: 2 asas de 0.40 desarrollado
A36: 4 | B36: Anclajes del contramarco | C36: 3/8" | D36: L | E36: 8 | F36: ='COLECTOR PARAMETROS'!$C$32 -> 10 | G36: 0.2 | H36: =E36*F36*G36 -> 16 | I36: ='COLECTOR PARAMETROS'!$C$20 -> 0.56 | U36: =H36*I36 -> 8.96 | V36: DP-06B: 8 anclajes de 0.20 soldados al angulo
A37: TOTAL REGISTROS Y TAPAS | U37: =SUM(U33:U36) -> 173.376
A39: RESUMEN PARA LA PLANILLA GENERAL (partidas 01.04.04.04.05 y 01.04.04.05.06)
A40: 1 | B40: ACERO DE REFUERZO EN COLECTOR Y CAJAS | F40: kg | G40: =SUMIF(J10:J16,"3/8""",P10:P16)+T17+U29 -> 2681.1756 | H40: =SUMIF(J10:J16,"1/2""",P10:P16) -> 375.27078 | I40: =U17+U29 -> 3056.4464
A41: 2 | B41: ACERO DE REFUERZO EN TAPAS, BORDES Y ANCLAJES | F41: kg | G41: =SUMIF(C33:C36,"3/8*",U33:U36) -> 62.048 | H41: =SUMIF(C33:C36,"1/2*",U33:U36) -> 111.328 | I41: =U37 -> 173.376

Sheet COLECTOR REGISTROS Y TAPAS
A1: COLECTOR PLUVIAL FRONTAL - REGISTROS DE LIMPIEZA Y TAPAS
A2: ENTIDAD | C2: =+RESUMEN!B4 -> GERENCIA TERRITORIAL BAJO MAYO - TARAPOTO
A3: PROYECTO | C3: =+RESUMEN!B5 -> “CREACIÓN DEL SERVICIO DE PROTECCIÓN A MUJERES VÍCTIMAS DE VIOLENCIA EN SITUACIÓN DE RIESGO DE FEMINICIDIO O PELIGRE SU INTEGRIDAD Y/O SALUD FÍSICA Y/O MENTAL EN HOGAR DE REFUGIO TEMPORAL DISTRITO DE MORALES DE LA PROVINCIA DE SAN MARTÍN DEL DEPARTAMENTO DE SAN MARTÍN”, con CUI N.° 2675514
A4: UBICACIÓN | C4: =+RESUMEN!B6 -> SAN MARTIN - SAN MARTIN - MORALES
A5: FECHA | C5: =+RESUMEN!B7 -> 46266
A7: Lamina DP-01 (ubicacion) y DP-06B (detalle): contramarco L 1 1/2"x1 1/2"x1/8" anclado a la losa, marco L 1 1/2"x1 1/2"x1/8" soldado a la tapa, tapa de concreto armado 0.68 x 0.68 x 0.08 con parrilla 3/8" @0.10 y asas; borde engrosado 0.15 x 0.10 alrededor de la abertura de 0.70 x 0.70.
A9: N° | B9: REGISTRO | C9: PROGRESIVA | D9: UBICACION | E9: TAPA 0.68 x 0.68 (und) | F9: SUSTENTO
A10: 1 | B10: CL | C10: 0+000.00 | D10: Caja de llegada (empalme con CAR Varones y cuneta Eje 01) | E10: 1 | F10: DP-07
A11: 2 | B11: RS-01 | C11: 0+011.27 | D11: Registro en la losa del colector; empalme cuneta | E11: 1 | F11: DP-01, DP-06B
A12: 3 | B12: RS-02 | C12: 0+022.00 | D12: Registro en la losa del colector; limpieza / quiebre | E12: 1 | F12: DP-01, DP-06B
A13: 4 | B13: RS-03 | C13: 0+032.50 | D13: Registro en la losa del colector; empalme cuneta | E13: 1 | F13: DP-01, DP-06B
A14: 5 | B14: RS-04 | C14: 0+042.68 | D14: Registro en la losa del colector; empalme cuneta | E14: 1 | F14: DP-01, DP-06B
A15: 6 | B15: RS-05 | C15: 0+052.00 | D15: Registro en la losa del colector; limpieza / quiebre | E15: 1 | F15: DP-01, DP-06B
A16: 7 | B16: RS-06 | C16: 0+058.81 | D16: Registro en la losa del colector; limpieza / quiebre | E16: 1 | F16: DP-01, DP-06B
A17: 8 | B17: RS-07 | C17: 0+066.89 | D17: Registro en la losa del colector; limpieza / quiebre | E17: 1 | F17: DP-01, DP-06B
A18: 9 | B18: CC (2) | C18: 0+069.89 | D18: Caja de caida: dos registros sobre la poza | E18: 2 | F18: DP-07
A19: TOTAL DE REGISTROS CON TAPA | E19: =SUM(E10:E18) -> 10
A21: METRADO DE LAS PARTIDAS DE REGISTROS (cantidad = total de registros; dimensiones de la hoja COLECTOR PARAMETROS)
A22: N° | B22: PARTIDA | C22: UND | D22: CALCULO | E22: TOTAL | F22: SUSTENTO
A23: 1 | B23: CONTRAMARCO METALICO L 1 1/2"x1 1/2"x1/8" CON ANCLAJES | C23: und | D23: 1 por registro | E23: =E19 -> 10 | F23: DP-06B
A24: 2 | B24: MARCO METALICO DE TAPA L 1 1/2"x1 1/2"x1/8" | C24: und | D24: 1 por tapa | E24: =E19 -> 10 | F24: DP-06B
A25: 3 | B25: ANGULOS METALICOS P/MARCO Y CONTRAMARCO | C25: kg | D25: registros x (2.80 x 1.83 + 2.72 x 1.83) | E25: =E19*('COLECTOR PARAMETROS'!$C$36*'COLECTOR PARAMETROS'!$C$38+'COLECTOR PARAMETROS'!$C$37*'COLECTOR PARAMETROS'!$C$39) -> 101.016 | F25: DP-06B; pesos de catalogo
A26: 4 | B26: TAPA DE CONCRETO ARMADO 0.68 x 0.68 x 0.08 | C26: und | D26: 1 por registro | E26: =E19 -> 10 | F26: DP-06B
A27: 5 | B27: CONCRETO f'c=210 EN TAPAS | C27: m3 | D27: registros x 0.68 x 0.68 x 0.08 | E27: =E19*'COLECTOR PARAMETROS'!$C$33*'COLECTOR PARAMETROS'!$C$33*'COLECTOR PARAMETROS'!$C$34 -> 0.36992 | F27: DP-06B
A28: 6 | B28: PINTURA ANTICORROSIVA Y ESMALTE EN ANGULOS | C28: m2 | D28: registros x (2.80 x 0.152 + 2.72 x 0.152) | E28: =E19*('COLECTOR PARAMETROS'!$C$36*'COLECTOR PARAMETROS'!$C$40+'COLECTOR PARAMETROS'!$C$37*'COLECTOR PARAMETROS'!$C$41) -> 8.3904 | F28: 4 caras de cada angulo

Sheet COLECTOR JUNTAS Y EMPALMES
A1: COLECTOR PLUVIAL FRONTAL - JUNTAS Y EMPALMES DE CUNETAS
A2: ENTIDAD | C2: =+RESUMEN!B4 -> GERENCIA TERRITORIAL BAJO MAYO - TARAPOTO
A3: PROYECTO | C3: =+RESUMEN!B5 -> “CREACIÓN DEL SERVICIO DE PROTECCIÓN A MUJERES VÍCTIMAS DE VIOLENCIA EN SITUACIÓN DE RIESGO DE FEMINICIDIO O PELIGRE SU INTEGRIDAD Y/O SALUD FÍSICA Y/O MENTAL EN HOGAR DE REFUGIO TEMPORAL DISTRITO DE MORALES DE LA PROVINCIA DE SAN MARTÍN DEL DEPARTAMENTO DE SAN MARTÍN”, con CUI N.° 2675514
A4: UBICACIÓN | C4: =+RESUMEN!B6 -> SAN MARTIN - SAN MARTIN - MORALES
A5: FECHA | C5: =+RESUMEN!B7 -> 46266
A7: Lamina DP-01 (nota 5), DP-03 y DP-06C. Junta de dilatacion de 1" cada 4.00 m en todo el perimetro de la seccion (tecnopor de 1" en todo el perimetro + sellador asfaltico RC-250 con arena de 1" x 2" en la cara expuesta, EG-2013 secc. 510.02 c y 438.02 e 3). Junta de tecnopor de 1" entre el colector y el cimiento del cerco, y entre el borde de la losa y el piso adyacente. Empalme de cada cuneta por ventana en el muro lado predio con caida libre al fondo (sin dintel adicional).
A9: N° | B9: ELEMENTO | C9: PROGRESIVA / DETALLE | D9: VECES | E9: LONGITUD (m) | F9: PARCIAL (m) | G9: SUSTENTO
A10: JUNTA DE DILATACION e=1" CON TECNOPOR Y SELLADOR ASFALTICO EN COLECTOR (perimetro = 2 x ancho exterior + 2 x (e fondo + h max + e losa))
A11: 1 | B11: Juntas de dilatacion cada 4.00 m entre 0+004.00 y 0+068.00 | C11: ="n = ENTERO("&TEXT('COLECTOR PARAMETROS'!$C$64,"0.00")&" / 4.00)" -> n = ENTERO(69.89 / 4.00) | D11: =INT('COLECTOR PARAMETROS'!$C$64/'COLECTOR PARAMETROS'!$C$62) -> 17 | E11: =2*('COLECTOR PARAMETROS'!$C$10+2*'COLECTOR PARAMETROS'!$C$11)+2*('COLECTOR PARAMETROS'!$C$12+'COLECTOR PARAMETROS'!$C$63+'COLECTOR PARAMETROS'!$C$13) -> 5.92 | F11: =D11*E11 -> 100.64 | G11: DP-01 nota 5; DP-03 (juntas en el perfil); perimetro de la seccion
A12: TOTAL JUNTA DE DILATACION (m) | F12: =SUM(F11:F11) -> 100.64
A14: JUNTA e=1" CON TECNOPOR Y SELLADOR ASFALTICO ENTRE COLECTOR Y CERCO PERIMETRICO
A15: 1 | B15: Contra el cimiento del cerco (tramo pegado al cerco, 0+000 a primer quiebre) | C15: ="0+000.00 a 0+"&TEXT('COLECTOR PARAMETROS'!$C$65,"000.00") -> 0+000.00 a 0+058.81 | D15: 1 | E15: ='COLECTOR PARAMETROS'!$C$65 -> 58.805 | F15: =D15*E15 -> 58.805 | G15: DP-01, DP-04 (junta entre muro y cimiento del cerco)
A16: 2 | B16: Borde de la losa con el piso adyacente: colector (ambos lados) | C16: ="2 x 0+"&TEXT('COLECTOR PARAMETROS'!$C$64,"000.00") -> 2 x 0+069.89 | D16: 2 | E16: ='COLECTOR PARAMETROS'!$C$64 -> 69.887 | F16: =D16*E16 -> 139.774 | G16: DP-04: junta de tecnopor en el borde de la losa superior
A17: 3 | B17: Borde de la losa con el piso adyacente: caja CL (ambos lados) | C17: 2 x (largo exterior + 0.30) | D17: 2 | E17: ='COLECTOR MOV. TIERRAS'!D21+2*'COLECTOR PARAMETROS'!$C$11+0.3 -> 2.1 | F17: =D17*E17 -> 4.2 | G17: DP-07
A18: 4 | B18: Borde de la losa con el piso adyacente: caja CC (ambos lados) | C18: 2 x (largo exterior + 0.30) | D18: 2 | E18: ='COLECTOR MOV. TIERRAS'!D22+2*'COLECTOR PARAMETROS'!$C$11+0.3 -> 4.1 | F18: =D18*E18 -> 8.2 | G18: DP-07
A19: TOTAL JUNTA DE TECNOPOR (m) | F19: =SUM(F15:F18) -> 210.979
A21: EMPALME DE CUNETA AL COLECTOR (ventana 0.40 x H en el muro lado predio, caida libre y registro encima) - lamina DP-06C
A22: 1 | B22: Cuneta Eje 01 (perimetral este), perfil 01 | C22: 0+001.07 | D22: 1 | F22: =D22 -> 1 | G22: DP-06C (cuadro de empalmes); DP-01
A23: 2 | B23: Cuneta Eje 02 (estacionamiento), perfil 02 | C23: 0+011.27 | D23: 1 | F23: =D23 -> 1 | G23: DP-06C (cuadro de empalmes); DP-01
A24: 3 | B24: Cuneta Eje 06 (ingreso vehicular), perfil 06 | C24: 0+032.50 | D24: 1 | F24: =D24 -> 1 | G24: DP-06C (cuadro de empalmes); DP-01
A25: 4 | B25: Cuneta Eje 07, perfil 07 | C25: 0+042.68 | D25: 1 | F25: =D25 -> 1 | G25: DP-06C (cuadro de empalmes); DP-01
A26: 5 | B26: Cuneta Eje 11, perfil 11 | C26: 0+060.89 | D26: 1 | F26: =D26 -> 1 | G26: DP-06C (cuadro de empalmes); DP-01
A27: 6 | B27: Cuneta Eje 12 (perimetral oeste), perfil 12 | C27: 0+069.56 | D27: 1 | F27: =D27 -> 1 | G27: DP-06C (cuadro de empalmes); DP-01
A28: TOTAL EMPALMES (und) | F28: =SUM(F22:F27) -> 6
A30: Nota: las cunetas de los Ejes 11 y 12 terminan antes del cerco y se prolongan 1.88 y 5.39 m hasta el muro del colector con su misma seccion (DP-06C). Esa prolongacion se metra en las partidas de cunetas del proyecto; aqui solo se cuenta la ventana de empalme.

Sheet COLECTOR INSUMOS
A1: COLECTOR PLUVIAL FRONTAL - DESGLOSE DE INSUMOS POR PARTIDA
A2: ENTIDAD | C2: =+RESUMEN!B4 -> GERENCIA TERRITORIAL BAJO MAYO - TARAPOTO
A3: PROYECTO | C3: =+RESUMEN!B5 -> “CREACIÓN DEL SERVICIO DE PROTECCIÓN A MUJERES VÍCTIMAS DE VIOLENCIA EN SITUACIÓN DE RIESGO DE FEMINICIDIO O PELIGRE SU INTEGRIDAD Y/O SALUD FÍSICA Y/O MENTAL EN HOGAR DE REFUGIO TEMPORAL DISTRITO DE MORALES DE LA PROVINCIA DE SAN MARTÍN DEL DEPARTAMENTO DE SAN MARTÍN”, con CUI N.° 2675514
A4: UBICACIÓN | C4: =+RESUMEN!B6 -> SAN MARTIN - SAN MARTIN - MORALES
A5: FECHA | C5: =+RESUMEN!B7 -> 46266
A7: Rendimientos unitarios referenciales (celdas amarillas, editar segun el analisis de costos unitarios adoptado). El metrado se toma de la PLANILLA GENERAL DE METRADOS.
A9: N° | B9: PARTIDA | C9: UND | D9: METRADO | E9: INSUMO | F9: UND INSUMO | G9: CANTIDAD POR UND DE PARTIDA | H9: CANTIDAD TOTAL
A10: 1 | B10: 01.04.04.04.01 CONCRETO f'c=210 PARA COLECTOR - losa de fondo | C10: m3 | D10: =SUM('PLANILLA GENERAL DE METRADOS'!J241:J249) -> 13.05885 | E10: Cemento Portland tipo I | F10: bol | G10: 9.73 | H10: =G10*$D$10 -> 127.06261
E11: Arena gruesa | F11: m3 | G11: 0.52 | H11: =G11*$D$10 -> 6.790602
E12: Piedra chancada 1/2" | F12: m3 | G12: 0.53 | H12: =G12*$D$10 -> 6.9211905
E13: Agua | F13: m3 | G13: 0.186 | H13: =G13*$D$10 -> 2.4289461
E14: Mezcladora 9-11 p3 | F14: hm | G14: 0.8 | H14: =G14*$D$10 -> 10.44708
E15: Vibrador de concreto | F15: hm | G15: 0.8 | H15: =G15*$D$10 -> 10.44708
E16: Operario | F16: hh | G16: 0.8 | H16: =G16*$D$10 -> 10.44708
E17: Oficial | F17: hh | G17: 0.8 | H17: =G17*$D$10 -> 10.44708
E18: Peon | F18: hh | G18: 6.4 | H18: =G18*$D$10 -> 83.57664
A19: 2 | B19: 01.04.04.04.01 CONCRETO f'c=210 PARA COLECTOR - muros | C19: m3 | D19: =SUM('PLANILLA GENERAL DE METRADOS'!J251:J259) -> 35.862216 | E19: Cemento Portland tipo I | F19: bol | G19: 9.73 | H19: =G19*$D$19 -> 348.93936
E20: Arena gruesa | F20: m3 | G20: 0.52 | H20: =G20*$D$19 -> 18.648352
E21: Piedra chancada 1/2" | F21: m3 | G21: 0.53 | H21: =G21*$D$19 -> 19.006974
E22: Agua | F22: m3 | G22: 0.186 | H22: =G22*$D$19 -> 6.6703722
E23: Mezcladora 9-11 p3 | F23: hm | G23: 1 | H23: =G23*$D$19 -> 35.862216
E24: Vibrador de concreto | F24: hm | G24: 1 | H24: =G24*$D$19 -> 35.862216
E25: Operario | F25: hh | G25: 1 | H25: =G25*$D$19 -> 35.862216
E26: Oficial | F26: hh | G26: 1 | H26: =G26*$D$19 -> 35.862216
E27: Peon | F27: hh | G27: 8 | H27: =G27*$D$19 -> 286.89773
A28: 3 | B28: 01.04.04.04.01 CONCRETO f'c=210 PARA COLECTOR - losa superior | C28: m3 | D28: =SUM('PLANILLA GENERAL DE METRADOS'!J261:J271) -> 9.39255 | E28: Cemento Portland tipo I | F28: bol | G28: 9.73 | H28: =G28*$D$28 -> 91.389511
E29: Arena gruesa | F29: m3 | G29: 0.52 | H29: =G29*$D$28 -> 4.884126
E30: Piedra chancada 1/2" | F30: m3 | G30: 0.53 | H30: =G30*$D$28 -> 4.9780515
E31: Agua | F31: m3 | G31: 0.186 | H31: =G31*$D$28 -> 1.7470143
E32: Mezcladora 9-11 p3 | F32: hm | G32: 0.8 | H32: =G32*$D$28 -> 7.51404
E33: Vibrador de concreto | F33: hm | G33: 0.8 | H33: =G33*$D$28 -> 7.51404
E34: Operario | F34: hh | G34: 0.8 | H34: =G34*$D$28 -> 7.51404
E35: Oficial | F35: hh | G35: 0.8 | H35: =G35*$D$28 -> 7.51404
E36: Peon | F36: hh | G36: 6.4 | H36: =G36*$D$28 -> 60.11232
A37: 4 | B37: 01.04.04.04.02 ENCOFRADO Y DESENCOFRADO DE COLECTOR | C37: m2 | D37: ='PLANILLA GENERAL DE METRADOS'!K272 -> 585.23188 | E37: Madera tornillo | F37: p2 | G37: 4.24 | H37: =G37*$D$37 -> 2481.3832
E38: Clavos 3" | F38: kg | G38: 0.2 | H38: =G38*$D$37 -> 117.04638
E39: Alambre negro N 8 | F39: kg | G39: 0.2 | H39: =G39*$D$37 -> 117.04638
E40: Operario | F40: hh | G40: 0.8 | H40: =G40*$D$37 -> 468.1855
E41: Oficial | F41: hh | G41: 0.8 | H41: =G41*$D$37 -> 468.1855
A42: 5 | B42: 01.04.04.04.03 ACERO f'y=4200 PARA COLECTOR | C42: kg | D42: ='PLANILLA GENERAL DE METRADOS'!K282 -> 3056.4464 | E42: Acero corrugado fy=4200 (incluye 5 % desperdicio) | F42: kg | G42: 1.05 | H42: =G42*$D$42 -> 3209.2687
E43: Alambre negro N 16 | F43: kg | G43: 0.06 | H43: =G43*$D$42 -> 183.38678
E44: Operario | F44: hh | G44: 0.032 | H44: =G44*$D$42 -> 97.806284
E45: Oficial | F45: hh | G45: 0.032 | H45: =G45*$D$42 -> 97.806284
A46: 6 | B46: 01.04.04.03.01 SOLADO f'c=100 e=0.05 | C46: m2 | D46: ='PLANILLA GENERAL DE METRADOS'!K229 -> 93.938 | E46: Cemento Portland tipo I | F46: bol | G46: 0.3 | H46: =G46*$D$46 -> 28.1814
E47: Hormigon | F47: m3 | G47: 0.064 | H47: =G47*$D$46 -> 6.012032
E48: Agua | F48: m3 | G48: 0.01 | H48: =G48*$D$46 -> 0.93938
E49: Operario | F49: hh | G49: 0.1 | H49: =G49*$D$46 -> 9.3938
E50: Peon | F50: hh | G50: 0.4 | H50: =G50*$D$46 -> 37.5752
A51: 7 | B51: 01.04.04.02.01 EXCAVACION MANUAL DE ZANJAS | C51: m3 | D51: ='PLANILLA GENERAL DE METRADOS'!K188 -> 164.89438 | E51: Peon | F51: hh | G51: 2.67 | H51: =G51*$D$51 -> 440.26798
E52: Herramientas manuales | F52: %mo | G52: 0.03 | H52: =G52*$D$51 -> 4.9468313
A53: 8 | B53: 01.04.04.02.03 RELLENO COMPACTADO CON MATERIAL PROPIO | C53: m3 | D53: ='PLANILLA GENERAL DE METRADOS'!K208 -> 82.773335 | E53: Agua | F53: m3 | G53: 0.05 | H53: =G53*$D$53 -> 4.1386668
E54: Compactador vibratorio tipo plancha | F54: hm | G54: 0.4 | H54: =G54*$D$53 -> 33.109334
E55: Operario | F55: hh | G55: 0.4 | H55: =G55*$D$53 -> 33.109334
E56: Peon | F56: hh | G56: 1.6 | H56: =G56*$D$53 -> 132.43734
A57: 9 | B57: 01.04.04.02.04 ELIMINACION DE MATERIAL EXCEDENTE | C57: m3 | D57: ='PLANILLA GENERAL DE METRADOS'!K225 -> 98.545249 | E57: Volquete 6 m3 | F57: hm | G57: 0.133 | H57: =G57*$D$57 -> 13.106518
E58: Cargador frontal | F58: hm | G58: 0.033 | H58: =G58*$D$57 -> 3.2519932
E59: Peon | F59: hh | G59: 0.133 | H59: =G59*$D$57 -> 13.106518
A60: 10 | B60: 01.04.04.05.01 TAPA DE REGISTRO: angulos (marco y contramarco) | C60: kg | D60: ='COLECTOR REGISTROS Y TAPAS'!E25 -> 101.016 | E60: Angulo L 1 1/2"x1 1/2"x1/8" (incluye corte y soldadura) | F60: kg | G60: 1.05 | H60: =G60*$D$60 -> 106.0668
E61: Soldadura cellocord | F61: kg | G61: 0.03 | H61: =G61*$D$60 -> 3.03048
E62: Operario | F62: hh | G62: 0.1 | H62: =G62*$D$60 -> 10.1016
E63: Oficial | F63: hh | G63: 0.1 | H63: =G63*$D$60 -> 10.1016
A64: 11 | B64: 01.04.04.05.01 TAPA DE REGISTRO: pintura en angulos | C64: m2 | D64: ='COLECTOR REGISTROS Y TAPAS'!E28 -> 8.3904 | E64: Pintura anticorrosiva | F64: gal | G64: 0.08 | H64: =G64*$D$64 -> 0.671232
E65: Esmalte sintetico | F65: gal | G65: 0.08 | H65: =G65*$D$64 -> 0.671232
E66: Lija para fierro N° 80 | F66: und | G66: 0.25 | H66: =G66*$D$64 -> 2.0976
E67: Thinner acrilico | F67: gal | G67: 0.024 | H67: =G67*$D$64 -> 0.2013696
E68: Operario | F68: hh | G68: 0.4 | H68: =G68*$D$64 -> 3.35616
A69: 12 | B69: 01.04.04.06.01 JUNTA DE DILATACION e=1" CON TECNOPOR Y SELLADOR ASFALTICO | C69: m | D69: ='PLANILLA GENERAL DE METRADOS'!K321 -> 100.64 | E69: Tecnopor 1" | F69: m2 | G69: ='ACU JUNTA DILATACION'!$D$14*(1+'ACU JUNTA DILATACION'!$D$15) -> 0.14084459 | H69: =G69*$D$69 -> 14.1746
E70: Sellador asfaltico: asfalto liquido RC-250 + arena gruesa (sello de 1" x 2") | F70: m3 | G70: ='ACU JUNTA DILATACION'!$D$20 -> 0.0011159524 | H70: =G70*$D$69 -> 0.11230945
E71: Operario | F71: hh | G71: 0.2 | H71: =G71*$D$69 -> 20.128
E72: Peon | F72: hh | G72: 0.2 | H72: =G72*$D$69 -> 20.128
A73: 13 | B73: 01.04.04.06.02 JUNTA e=1" CON TECNOPOR Y SELLADOR ASFALTICO ENTRE COLECTOR Y CERCO PERIMETRICO | C73: m | D73: ='PLANILLA GENERAL DE METRADOS'!K322 -> 210.979 | E73: Tecnopor 1" | F73: m2 | G73: ='ACU JUNTA CERCO'!$D$16*(1+'ACU JUNTA CERCO'!$D$17) -> 0.33912852 | H73: =G73*$D$73 -> 71.548995
E74: Peon | F74: hh | G74: 0.1 | H74: =G74*$D$73 -> 21.0979
E75: Sellador asfaltico: asfalto liquido RC-250 + arena gruesa (sello de 1" x 2") | F75: m3 | G75: ='ACU JUNTA CERCO'!$D$20 -> 0.00129032 | H75: =G75*$D$73 -> 0.27223042
E76: Operario | F76: hh | G76: 0.05 | H76: =G76*$D$73 -> 10.54895

Sheet ACU TAPA REGISTRO
A1: ANALISIS DE COSTO UNITARIO - TAPA DE REGISTRO 0.68 x 0.68 C/MARCO Y CONTRAMARCO
A2: ENTIDAD | C2: =+RESUMEN!B4 -> GERENCIA TERRITORIAL BAJO MAYO - TARAPOTO
A3: PROYECTO | C3: =+RESUMEN!B5 -> “CREACIÓN DEL SERVICIO DE PROTECCIÓN A MUJERES VÍCTIMAS DE VIOLENCIA EN SITUACIÓN DE RIESGO DE FEMINICIDIO O PELIGRE SU INTEGRIDAD Y/O SALUD FÍSICA Y/O MENTAL EN HOGAR DE REFUGIO TEMPORAL DISTRITO DE MORALES DE LA PROVINCIA DE SAN MARTÍN DEL DEPARTAMENTO DE SAN MARTÍN”, con CUI N.° 2675514
A4: UBICACIÓN | C4: =+RESUMEN!B6 -> SAN MARTIN - SAN MARTIN - MORALES
A5: FECHA | C5: =+RESUMEN!B7 -> 46266
A7: Analisis de la partida de Delphin 01.04.04.06.05.01 TAPA DE REGISTRO 0.68x0.68 C/MARCO Y CONTRAMARCO, partida 01.04.04.05.01 del metrado; componentes desagregados en la hoja DESAGREGADO TAPA REGISTRO. Cantidad por tapa = metrado del componente / numero de tapas. Ratios de insumos tomados de la hoja COLECTOR INSUMOS. Celda amarilla = dato (ratio o precio); verde = formula. Precios sin IGV obtenidos de precios publicados (octubre 2026), con su fuente en la columna H; los marcados "por cotizar" deben confirmarse en Tarapoto.
A9: 1. CANTIDADES POR TAPA (tomadas de este metrado)
A10: N° | B10: COMPONENTE | C10: UND | D10: METRADO TOTAL | E10: N° DE TAPAS | F10: CANTIDAD POR TAPA | G10: COMPONENTE | H10: SUSTENTO
A11: 1 | B11: Contramarco metalico L 1 1/2"x1 1/2"x1/8" con anclajes | C11: und | D11: =+'COLECTOR REGISTROS Y TAPAS'!E23 -> 10 | E11: =+'COLECTOR REGISTROS Y TAPAS'!E19 -> 10 | F11: =D11/E11 -> 1 | G11: contramarco | H11: DP-06B; 1 por registro
A12: 2 | B12: Marco metalico de tapa L 1 1/2"x1 1/2"x1/8" | C12: und | D12: =+'COLECTOR REGISTROS Y TAPAS'!E24 -> 10 | E12: =+'COLECTOR REGISTROS Y TAPAS'!E19 -> 10 | F12: =D12/E12 -> 1 | G12: marco | H12: DP-06B; 1 por tapa
A13: 3 | B13: Angulos metalicos para marco y contramarco (incluye soldadura) | C13: kg | D13: =+'COLECTOR REGISTROS Y TAPAS'!E25 -> 101.016 | E13: =+'COLECTOR REGISTROS Y TAPAS'!E19 -> 10 | F13: =D13/E13 -> 10.1016 | G13: angulos | H13: 2.80 x 1.83 + 2.72 x 1.83 = 10.10 kg por tapa
A14: 4 | B14: Tapa de concreto armado 0.68 x 0.68 x 0.08 m (incluye acero y asas) | C14: und | D14: =+'COLECTOR REGISTROS Y TAPAS'!E26 -> 10 | E14: =+'COLECTOR REGISTROS Y TAPAS'!E19 -> 10 | F14: =D14/E14 -> 1 | G14: tapa | H14: DP-06B
A15: 5 | B15: Concreto f'c=210 kg/cm2 en tapas | C15: m3 | D15: =+'COLECTOR REGISTROS Y TAPAS'!E27 -> 0.36992 | E15: =+'COLECTOR REGISTROS Y TAPAS'!E19 -> 10 | F15: =D15/E15 -> 0.036992 | G15: concreto | H15: 0.68 x 0.68 x 0.08 = 0.0370 m3 por tapa
A16: 6 | B16: Acero fy=4200 kg/cm2 en tapas, bordes y anclajes | C16: kg | D16: =+'COLECTOR ACERO'!I41 -> 173.376 | E16: =+'COLECTOR REGISTROS Y TAPAS'!E19 -> 10 | F16: =D16/E16 -> 17.3376 | G16: acero | H16: Hoja COLECTOR ACERO, filas 33 a 36
A17: 7 | B17: Pintura anticorrosiva y esmalte en angulos | C17: m2 | D17: =+'COLECTOR REGISTROS Y TAPAS'!E28 -> 8.3904 | E17: =+'COLECTOR REGISTROS Y TAPAS'!E19 -> 10 | F17: =D17/E17 -> 0.83904 | G17: pintura | H17: 2.80 x 0.152 + 2.72 x 0.152 = 0.84 m2 por tapa
A19: 2. DESGLOSE POR COMPONENTE (insumos que aporta cada componente a una tapa)
A20: N° | B20: INSUMO | C20: UND | D20: CANTIDAD DEL COMPONENTE POR TAPA | E20: RATIO POR UND DE COMPONENTE | F20: APORTE POR TAPA | G20: PARCIAL S/ | H20: SUSTENTO DEL RATIO
A21: A | B21: Marco y contramarco metalicos: fabricacion, soldadura de anclajes y colocacion (kg de angulo por tapa)
B22: Angulo L 1 1/2"x1 1/2"x1/8" | C22: kg | D22: ='COLECTOR PARAMETROS'!C36*'COLECTOR PARAMETROS'!C38 -> 5.124 | E22: =+'COLECTOR INSUMOS'!G60 -> 1.05 | F22: =D22*E22 -> 5.3802 | G22: =F22*SUMIF($B$68:$B$93,B22,$F$68:$F$93) -> 16.571016 | H22: Contramarco 4 x 0.70 = 2.80 m x 1.83 kg/m; 5 % de desperdicio (COLECTOR INSUMOS)
B23: Angulo L 1 1/2"x1 1/2"x1/8" | C23: kg | D23: ='COLECTOR PARAMETROS'!C37*'COLECTOR PARAMETROS'!C39 -> 4.9776 | E23: =+'COLECTOR INSUMOS'!G60 -> 1.05 | F23: =D23*E23 -> 5.22648 | G23: =F23*SUMIF($B$68:$B$93,B23,$F$68:$F$93) -> 16.097558 | H23: Marco 4 x 0.68 = 2.72 m x 1.83 kg/m; 5 % de desperdicio
B24: Soldadura cellocord E6011 1/8" | C24: kg | D24: =F13 -> 10.1016 | E24: =+'COLECTOR INSUMOS'!G61 -> 0.03 | F24: =D24*E24 -> 0.303048 | G24: =F24*SUMIF($B$68:$B$93,B24,$F$68:$F$93) -> 5.6457842 | H24: COLECTOR INSUMOS, ratio por kg de angulo
B25: Operario | C25: hh | D25: =F13 -> 10.1016 | E25: =+'COLECTOR INSUMOS'!G62 -> 0.1 | F25: =D25*E25 -> 1.01016 | G25: =F25*SUMIF($B$68:$B$93,B25,$F$68:$F$93) -> 30.729067 | H25: COLECTOR INSUMOS, ratio por kg de angulo
B26: Oficial | C26: hh | D26: =F13 -> 10.1016 | E26: =+'COLECTOR INSUMOS'!G63 -> 0.1 | F26: =D26*E26 -> 1.01016 | G26: =F26*SUMIF($B$68:$B$93,B26,$F$68:$F$93) -> 23.183172 | H26: COLECTOR INSUMOS, ratio por kg de angulo
B27: Maquina de soldar 250 A | C27: hm | D27: =F13 -> 10.1016 | E27: =+'COLECTOR INSUMOS'!G62 -> 0.1 | F27: =D27*E27 -> 1.01016 | G27: =F27*SUMIF($B$68:$B$93,B27,$F$68:$F$93) -> 8.08128 | H27: Mismo tiempo del operario soldador
B28: Subtotal A | G28: =SUM(G22:G27) -> 100.30788
A29: B | B29: Concreto f'c=210 kg/cm2 de la tapa (m3 por tapa)
B30: Cemento Portland tipo I | C30: bol | D30: =F15 -> 0.036992 | E30: =+'COLECTOR INSUMOS'!G28 -> 9.73 | F30: =D30*E30 -> 0.35993216 | G30: =F30*SUMIF($B$68:$B$93,B30,$F$68:$F$93) -> 11.132702 | H30: COLECTOR INSUMOS, concreto f'c=210 (diseno de mezcla)
B31: Arena gruesa | C31: m3 | D31: =F15 -> 0.036992 | E31: =+'COLECTOR INSUMOS'!G29 -> 0.52 | F31: =D31*E31 -> 0.01923584 | G31: =F31*SUMIF($B$68:$B$93,B31,$F$68:$F$93) -> 0.78251397 | H31: COLECTOR INSUMOS
B32: Piedra chancada 1/2" | C32: m3 | D32: =F15 -> 0.036992 | E32: =+'COLECTOR INSUMOS'!G30 -> 0.53 | F32: =D32*E32 -> 0.01960576 | G32: =F32*SUMIF($B$68:$B$93,B32,$F$68:$F$93) -> 1.9937097 | H32: COLECTOR INSUMOS
B33: Agua | C33: m3 | D33: =F15 -> 0.036992 | E33: =+'COLECTOR INSUMOS'!G31 -> 0.186 | F33: =D33*E33 -> 0.006880512 | G33: =F33*SUMIF($B$68:$B$93,B33,$F$68:$F$93) -> 0.057314665 | H33: COLECTOR INSUMOS
B34: Mezcladora 9-11 p3 | C34: hm | D34: =F15 -> 0.036992 | E34: =+'COLECTOR INSUMOS'!G32 -> 0.8 | F34: =D34*E34 -> 0.0295936 | G34: =F34*SUMIF($B$68:$B$93,B34,$F$68:$F$93) -> 0.37613466 | H34: COLECTOR INSUMOS
B35: Vibrador de concreto | C35: hm | D35: =F15 -> 0.036992 | E35: =+'COLECTOR INSUMOS'!G33 -> 0.8 | F35: =D35*E35 -> 0.0295936 | G35: =F35*SUMIF($B$68:$B$93,B35,$F$68:$F$93) -> 0.32612147 | H35: COLECTOR INSUMOS
B36: Operario | C36: hh | D36: =F15 -> 0.036992 | E36: =+'COLECTOR INSUMOS'!G34 -> 0.8 | F36: =D36*E36 -> 0.0295936 | G36: =F36*SUMIF($B$68:$B$93,B36,$F$68:$F$93) -> 0.90023731 | H36: COLECTOR INSUMOS
B37: Oficial | C37: hh | D37: =F15 -> 0.036992 | E37: =+'COLECTOR INSUMOS'!G35 -> 0.8 | F37: =D37*E37 -> 0.0295936 | G37: =F37*SUMIF($B$68:$B$93,B37,$F$68:$F$93) -> 0.67917312 | H37: COLECTOR INSUMOS
B38: Peon | C38: hh | D38: =F15 -> 0.036992 | E38: =+'COLECTOR INSUMOS'!G36 -> 6.4 | F38: =D38*E38 -> 0.2367488 | G38: =F38*SUMIF($B$68:$B$93,B38,$F$68:$F$93) -> 4.9220076 | H38: COLECTOR INSUMOS
B39: Subtotal B | G39: =SUM(G30:G38) -> 21.169914
A40: C | B40: Vaciado de la tapa dentro del marco (und de tapa)
B41: Madera tornillo | C41: p2 | D41: =F14 -> 1 | E41: 1.15 | F41: =D41*E41 -> 1.15 | G41: =F41*SUMIF($B$68:$B$93,B41,$F$68:$F$93) -> 5.0715 | H41: Tablero de vaciado 0.80 x 0.80 x 1" = 6.89 p2, 6 usos; el marco metalico hace de encofrado lateral
B42: Subtotal C | G42: =SUM(G41:G41) -> 5.0715
A43: D | B43: Acero fy=4200 kg/cm2 de tapa, borde de abertura, asas y anclajes (kg por tapa)
B44: Acero corrugado fy=4200 | C44: kg | D44: =F16 -> 17.3376 | E44: =+'COLECTOR INSUMOS'!G42 -> 1.05 | F44: =D44*E44 -> 18.20448 | G44: =F44*SUMIF($B$68:$B$93,B44,$F$68:$F$93) -> 62.623411 | H44: COLECTOR INSUMOS (incluye 5 % de desperdicio)
B45: Alambre negro N 16 | C45: kg | D45: =F16 -> 17.3376 | E45: =+'COLECTOR INSUMOS'!G43 -> 0.06 | F45: =D45*E45 -> 1.040256 | G45: =F45*SUMIF($B$68:$B$93,B45,$F$68:$F$93) -> 5.2845005 | H45: COLECTOR INSUMOS
B46: Operario | C46: hh | D46: =F16 -> 17.3376 | E46: =+'COLECTOR INSUMOS'!G44 -> 0.032 | F46: =D46*E46 -> 0.5548032 | G46: =F46*SUMIF($B$68:$B$93,B46,$F$68:$F$93) -> 16.877113 | H46: COLECTOR INSUMOS
B47: Oficial | C47: hh | D47: =F16 -> 17.3376 | E47: =+'COLECTOR INSUMOS'!G45 -> 0.032 | F47: =D47*E47 -> 0.5548032 | G47: =F47*SUMIF($B$68:$B$93,B47,$F$68:$F$93) -> 12.732733 | H47: COLECTOR INSUMOS
B48: Subtotal D | G48: =SUM(G44:G47) -> 97.517758
A49: E | B49: Pintura anticorrosiva y esmalte en angulos (m2 por tapa)
B50: Pintura anticorrosiva | C50: gal | D50: =F17 -> 0.83904 | E50: =+'COLECTOR INSUMOS'!G64 -> 0.08 | F50: =D50*E50 -> 0.0671232 | G50: =F50*SUMIF($B$68:$B$93,B50,$F$68:$F$93) -> 3.0151741 | H50: COLECTOR INSUMOS
B51: Esmalte sintetico | C51: gal | D51: =F17 -> 0.83904 | E51: =+'COLECTOR INSUMOS'!G65 -> 0.08 | F51: =D51*E51 -> 0.0671232 | G51: =F51*SUMIF($B$68:$B$93,B51,$F$68:$F$93) -> 3.2427218 | H51: COLECTOR INSUMOS
B52: Lija para fierro N° 80 | C52: und | D52: =F17 -> 0.83904 | E52: =+'COLECTOR INSUMOS'!G66 -> 0.25 | F52: =D52*E52 -> 0.20976 | G52: =F52*SUMIF($B$68:$B$93,B52,$F$68:$F$93) -> 0.4446912 | H52: COLECTOR INSUMOS: 1 pliego cada 4 m2
B53: Thinner acrilico | C53: gal | D53: =F17 -> 0.83904 | E53: =+'COLECTOR INSUMOS'!G67 -> 0.024 | F53: =D53*E53 -> 0.02013696 | G53: =F53*SUMIF($B$68:$B$93,B53,$F$68:$F$93) -> 0.71788262 | H53: COLECTOR INSUMOS: 15 % del volumen de pintura (dilucion y limpieza)
B54: Operario | C54: hh | D54: =F17 -> 0.83904 | E54: =+'COLECTOR INSUMOS'!G68 -> 0.4 | F54: =D54*E54 -> 0.335616 | G54: =F54*SUMIF($B$68:$B$93,B54,$F$68:$F$93) -> 10.209439 | H54: COLECTOR INSUMOS
B55: Subtotal E | G55: =SUM(G50:G54) -> 17.629908
A56: F | B56: Colocacion: nivelacion y fijacion del contramarco antes del vaciado de la losa y asentado de la tapa (und de tapa)
B57: Operario | C57: hh | D57: =F14 -> 1 | E57: 1 | F57: =D57*E57 -> 1 | G57: =F57*SUMIF($B$68:$B$93,B57,$F$68:$F$93) -> 30.42 | H57: Criterio de obra: 1 hh por registro
B58: Peon | C58: hh | D58: =F14 -> 1 | E58: 1 | F58: =D58*E58 -> 1 | G58: =F58*SUMIF($B$68:$B$93,B58,$F$68:$F$93) -> 20.79 | H58: Criterio de obra: 1 hh por registro
B59: Subtotal F | G59: =SUM(G57:G58) -> 51.21
B60: Costo de los componentes por tapa (sin herramientas manuales) | G60: =+G28+G39+G42+G48+G55+G59 -> 292.90696
A61: 3. ANALISIS DE COSTO UNITARIO (formato Delphin)
A62: Partida | C62: 01.04.04.06.05.01 TAPA DE REGISTRO 0.68x0.68 C/MARCO Y CONTRAMARCO
A63: Partida del metrado | C63: 01.04.04.05.01 TAPA DE REGISTRO (10 und); componentes en la hoja DESAGREGADO TAPA REGISTRO
A64: Unidad | C64: und
A65: Metrado | C65: =+E11 -> 10
A66: Rendimiento (und/dia, cuadrilla de 1 operario) | C66: =8/E69 -> 2.7302144
A67: N° | B67: RECURSO | C67: UND | D67: CUADRILLA | E67: CANTIDAD POR TAPA | F67: PRECIO S/ | G67: PARCIAL S/ | H67: FUENTE DEL PRECIO
B68: MANO DE OBRA
A69: 1 | B69: Operario | C69: hh | D69: =E69*$C$66/8 -> 1 | E69: =SUMIF($B$21:$B$59,B69,$F$21:$F$59) -> 2.9301728 | F69: 30.42 | G69: =E69*F69 -> 89.135857 | H69: CAPECO: costo hora-hombre 2024-2025 llevado al jornal basico 2025-2026
A70: 2 | B70: Oficial | C70: hh | D70: =E70*$C$66/8 -> 0.54418524 | E70: =SUMIF($B$21:$B$59,B70,$F$21:$F$59) -> 1.5945568 | F70: 22.95 | G70: =E70*F70 -> 36.595079 | H70: CAPECO: costo hora-hombre 2024-2025 llevado al jornal basico 2025-2026
A71: 3 | B71: Peon | C71: hh | D71: =E71*$C$66/8 -> 0.42207367 | E71: =SUMIF($B$21:$B$59,B71,$F$21:$F$59) -> 1.2367488 | F71: 20.79 | G71: =E71*F71 -> 25.712008 | H71: CAPECO: costo hora-hombre 2024-2025 llevado al jornal basico 2025-2026
B72: Subtotal mano de obra | G72: =SUM(G69:G71) -> 151.44294
B73: MATERIALES
A74: 4 | B74: Angulo L 1 1/2"x1 1/2"x1/8" | C74: kg | E74: =SUMIF($B$21:$B$59,B74,$F$21:$F$59) -> 10.60668 | F74: 3.08 | G74: =E74*F74 -> 32.668574 | H74: Sodimac Peru: barra de 6 m (10.98 kg) S/ 39.90 con IGV
A75: 5 | B75: Soldadura cellocord E6011 1/8" | C75: kg | E75: =SUMIF($B$21:$B$59,B75,$F$21:$F$59) -> 0.303048 | F75: 18.63 | G75: =E75*F75 -> 5.6457842 | H75: Sodimac Peru: caja de 5 kg S/ 109.90 con IGV
A76: 6 | B76: Cemento Portland tipo I | C76: bol | E76: =SUMIF($B$21:$B$59,B76,$F$21:$F$59) -> 0.35993216 | F76: 30.93 | G76: =E76*F76 -> 11.132702 | H76: Cemento Pacasmayo tipo I 42.5 kg: S/ 36.50 con IGV
A77: 7 | B77: Arena gruesa | C77: m3 | E77: =SUMIF($B$21:$B$59,B77,$F$21:$F$59) -> 0.01923584 | F77: 40.68 | G77: =E77*F77 -> 0.78251397 | H77: Agregados Tarapoto (Morales): S/ 48.00 el m3
A78: 8 | B78: Piedra chancada 1/2" | C78: m3 | E78: =SUMIF($B$21:$B$59,B78,$F$21:$F$59) -> 0.01960576 | F78: 101.69 | G78: =E78*F78 -> 1.9937097 | H78: Por cotizar en Tarapoto: no hay precio publicado de la piedra de 1/2"
A79: 9 | B79: Agua | C79: m3 | E79: =SUMIF($B$21:$B$59,B79,$F$21:$F$59) -> 0.006880512 | F79: 8.33 | G79: =E79*F79 -> 0.057314665 | H79: EMAPA San Martin: tarifa comercial de 30 m3 a mas, agua 6.80 + alcantarillado 1.53
A80: 10 | B80: Madera tornillo | C80: p2 | E80: =SUMIF($B$21:$B$59,B80,$F$21:$F$59) -> 1.15 | F80: 4.41 | G80: =E80*F80 -> 5.0715 | H80: Maderas del Norte: S/ 5.20 el p2 con IGV
A81: 11 | B81: Acero corrugado fy=4200 | C81: kg | E81: =SUMIF($B$21:$B$59,B81,$F$21:$F$59) -> 18.20448 | F81: 3.44 | G81: =E81*F81 -> 62.623411 | H81: Sodimac Peru, Aceros Arequipa: 1/2" x 9 m S/ 36.50 y 3/8" x 9 m S/ 20.35 con IGV (ponderado)
A82: 12 | B82: Alambre negro N 16 | C82: kg | E82: =SUMIF($B$21:$B$59,B82,$F$21:$F$59) -> 1.040256 | F82: 5.08 | G82: =E82*F82 -> 5.2845005 | H82: Sodimac Peru: rollo de 10 kg S/ 59.90 con IGV
A83: 13 | B83: Pintura anticorrosiva | C83: gal | E83: =SUMIF($B$21:$B$59,B83,$F$21:$F$59) -> 0.0671232 | F83: 44.92 | G83: =E83*F83 -> 3.0151741 | H83: Promart: anticorrosivo Vencedor 1 gl S/ 53.00 con IGV
A84: 14 | B84: Esmalte sintetico | C84: gal | E84: =SUMIF($B$21:$B$59,B84,$F$21:$F$59) -> 0.0671232 | F84: 48.31 | G84: =E84*F84 -> 3.2427218 | H84: Promart: esmalte sintetico CPP 1 gl S/ 57.00 con IGV
A85: 15 | B85: Lija para fierro N° 80 | C85: und | E85: =SUMIF($B$21:$B$59,B85,$F$21:$F$59) -> 0.20976 | F85: 2.12 | G85: =E85*F85 -> 0.4446912 | H85: Sodimac Peru: lija para fierro 3M grano 80 S/ 2.50 con IGV
A86: 16 | B86: Thinner acrilico | C86: gal | E86: =SUMIF($B$21:$B$59,B86,$F$21:$F$59) -> 0.02013696 | F86: 35.65 | G86: =E86*F86 -> 0.71788262 | H86: Sodimac Peru: thinner acrilico TOPEX 3.5 L S/ 38.90 con IGV
B87: Subtotal materiales | G87: =SUM(G74:G86) -> 132.68048
B88: EQUIPOS
A89: 17 | B89: Herramientas manuales | C89: %mo | E89: 0.03 | F89: =+G72 -> 151.44294 | G89: =E89*F89 -> 4.5432883 | H89: 3 % del costo de mano de obra
A90: 18 | B90: Mezcladora 9-11 p3 | C90: hm | D90: =E90*$C$66/8 -> 0.010099609 | E90: =SUMIF($B$21:$B$59,B90,$F$21:$F$59) -> 0.0295936 | F90: 12.71 | G90: =E90*F90 -> 0.37613466 | H90: Konstrutecnia: S/ 15.00 la hora-maquina con IGV
A91: 19 | B91: Vibrador de concreto | C91: hm | D91: =E91*$C$66/8 -> 0.010099609 | E91: =SUMIF($B$21:$B$59,B91,$F$21:$F$59) -> 0.0295936 | F91: 11.02 | G91: =E91*F91 -> 0.32612147 | H91: Konstrutecnia: S/ 13.00 la hora-maquina con IGV
A92: 20 | B92: Maquina de soldar 250 A | C92: hm | D92: =E92*$C$66/8 -> 0.34474417 | E92: =SUMIF($B$21:$B$59,B92,$F$21:$F$59) -> 1.01016 | F92: 8 | G92: =E92*F92 -> 8.08128 | H92: Por cotizar en Tarapoto: no hay tarifa publicada
B93: Subtotal equipos | G93: =SUM(G89:G92) -> 13.326824
A94: COSTO UNITARIO DIRECTO POR TAPA (S/ por und) | G94: =+G72+G87+G93 -> 297.45025
A95: COSTO DIRECTO DE LA PARTIDA (metrado x costo unitario) | G95: =G94*C65 -> 2974.5025
A96: Control: costo de componentes (seccion 2) + herramientas manuales = costo unitario | G96: =IF(ABS(G60+G89-G94)<0.005,"CONFORME","REVISAR") -> CONFORME

Sheet ACU CANALETAS
A1: ANALISIS DE COSTOS UNITARIOS - CANALETAS DE TECHO DE PLANCHA GALVANIZADA
A2: ENTIDAD | C2: =+RESUMEN!B4 -> GERENCIA TERRITORIAL BAJO MAYO - TARAPOTO
A3: PROYECTO | C3: =+RESUMEN!B5 -> “CREACIÓN DEL SERVICIO DE PROTECCIÓN A MUJERES VÍCTIMAS DE VIOLENCIA EN SITUACIÓN DE RIESGO DE FEMINICIDIO O PELIGRE SU INTEGRIDAD Y/O SALUD FÍSICA Y/O MENTAL EN HOGAR DE REFUGIO TEMPORAL DISTRITO DE MORALES DE LA PROVINCIA DE SAN MARTÍN DEL DEPARTAMENTO DE SAN MARTÍN”, con CUI N.° 2675514
A4: UBICACIÓN | C4: =+RESUMEN!B6 -> SAN MARTIN - SAN MARTIN - MORALES
A5: FECHA | C5: =+RESUMEN!B7 -> 46266
A7: Analisis de las partidas 01.04.03.05.01.03 a 01.04.03.05.01.06 (red de recoleccion de techo). Las cantidades de insumos salen de los parametros de la hoja METRADO CANALETAS (seccion 0.25 x 0.20, pestana 0.05, plancha e=0.9 mm, soportes @0.60). Celda amarilla = dato (cuadrilla, rendimiento, aporte o precio); verde = formula. Precios sin IGV, referenciales: al pasar a Delphin rigen los de la base de precios del presupuesto.
A9: DATOS DE CALCULO (de la hoja METRADO CANALETAS y de catalogo)
A10: N° | B10: DATO | C10: UND | D10: VALOR | H10: SUSTENTO
A11: 1 | B11: Fondo interior de la canaleta | C11: m | D11: =+'METRADO CANALETAS'!F45 -> 0.25 | H11: METRADO CANALETAS F45
A12: 2 | B12: Altura interior de la canaleta | C12: m | D12: =+'METRADO CANALETAS'!F46 -> 0.2 | H12: METRADO CANALETAS F46
A13: 3 | B13: Pestana superior (cada lado) | C13: m | D13: =+'METRADO CANALETAS'!F47 -> 0.05 | H13: METRADO CANALETAS F47
A14: 4 | B14: Desarrollo de plancha por metro de canaleta | C14: m2/m | D14: =+'METRADO CANALETAS'!F48 -> 0.75 | H14: fondo + 2 alturas + 2 pestanas
A15: 5 | B15: Espesor de plancha galvanizada | C15: mm | D15: =+'METRADO CANALETAS'!F49 -> 0.9 | H15: METRADO CANALETAS F49
A16: 6 | B16: Separacion de soportes | C16: m | D16: =+'METRADO CANALETAS'!F50 -> 0.6 | H16: METRADO CANALETAS F50
A17: 7 | B17: Peso de la plancha galvanizada | C17: kg/m2 | D17: =D15*7.85+0.3 -> 7.365 | H17: espesor x 7.85 kg/m2 por mm + zinc (0.3 kg/m2)
A18: 8 | B18: Largo de la plancha comercial (1.22 x 2.44) | C18: m | D18: 2.44 | H18: catalogo; la canaleta se fabrica en tramos de 2.44 m
A19: 9 | B19: Traslape entre tramos | C19: m | D19: 0.05 | H19: criterio de obra (remachado y sellado)
A20: 10 | B20: Desarrollo de la platina de un soporte | C20: m | D20: =D11+2*D12+2*0.1 -> 0.85 | H20: abraza la canaleta (fondo + 2 lados) + 2 orejas de fijacion de 0.10
A21: 11 | B21: Peso de la platina 1" x 1/8" | C21: kg/m | D21: 0.633 | H21: 25.4 x 3.18 mm x 7.85 = 0.633 kg/m
A22: 12 | B22: Largo de la platina comercial | C22: m | D22: 6 | H22: catalogo
A25: ACU 1: 01.04.03.05.01.03 CANALETA DE PLANCHA DE ACERO GALVANIZADO e=0.9mm, SECCION 0.25m x 0.20m
A26: Unidad | C26: m
A27: Metrado | C27: =+'PLANILLA GENERAL DE METRADOS'!K149 -> 513.98
A28: Rendimiento (m/dia) | C28: 25 | E28: fabricacion (corte y doblado en obra), remachado, sellado y colocacion sobre los soportes; cuadrilla 1 op + 1 peon
A29: N° | B29: RECURSO | C29: UND | D29: CUADRILLA | E29: CANTIDAD | F29: PRECIO S/ | G29: PARCIAL S/ | H29: SUSTENTO / FUENTE
B30: MANO DE OBRA
A31: 1 | B31: Operario (hojalatero) | C31: hh | D31: 1 | E31: =D31*8/$C$28 -> 0.32 | F31: 30.42 | G31: =E31*F31 -> 9.7344 | H31: CAPECO: costo hora-hombre 2024-2025 llevado al jornal basico 2025-2026
A32: 2 | B32: Peon | C32: hh | D32: 1 | E32: =D32*8/$C$28 -> 0.32 | F32: 20.79 | G32: =E32*F32 -> 6.6528 | H32: CAPECO: costo hora-hombre 2024-2025 llevado al jornal basico 2025-2026
B33: Subtotal mano de obra | G33: =SUM(G31:G32) -> 16.3872
B34: MATERIALES
A35: 3 | B35: Plancha de acero galvanizado e=0.9 mm | C35: m2 | E35: =$D$14*(1+$D$19/$D$18)*1.05 -> 0.8036373 | F35: 26.95 | G35: =E35*F35 -> 21.658025 | H35: desarrollo x (1 + traslape/2.44) x 1.05 desperdicio; Mercado Tarapoto 2026, sin IGV (referencial)
A36: 4 | B36: Remache pop 1/8" | C36: und | E36: =2*($D$11+2*$D$12)/0.05/$D$18 -> 10.655738 | F36: 0.1 | G36: =E36*F36 -> 1.0655738 | H36: 2 filas a @0.05 en cada traslape (cada 2.44 m)
A37: 5 | B37: Sellador de poliuretano (cartucho 300 ml) | C37: und | E37: =($D$11+2*$D$12)/$D$18/8 -> 0.03329918 | F37: 21.19 | G37: =E37*F37 -> 0.70560963 | H37: 1 cartucho = 8 m de cordon de 6 mm; una junta (0.65 m) cada 2.44 m
B38: Subtotal materiales | G38: =SUM(G35:G37) -> 23.429209
B39: EQUIPOS
A40: 6 | B40: Herramientas manuales | C40: %mo | E40: 0.05 | F40: =+G33 -> 16.3872 | G40: =E40*F40 -> 0.81936 | H40: 5 % del costo de mano de obra (hojalateria)
B41: Subtotal equipos | G41: =SUM(G40:G40) -> 0.81936
A42: COSTO UNITARIO DIRECTO (S/ por m) | G42: =+G33+G38+G41 -> 40.635769
A43: COSTO DIRECTO DE LA PARTIDA (metrado x costo unitario) | G43: =G42*C27 -> 20885.972
A45: ACU 2: 01.04.03.05.01.04 SOPORTE DE PLATINA F°G° 1" x 1/8" P/CANALETA
A46: Unidad | C46: und
A47: Metrado | C47: =+'PLANILLA GENERAL DE METRADOS'!K150 -> 884
A48: Rendimiento (und/dia) | C48: 40 | E48: corte, doblado en U con orejas, perforado y fijacion al alero o viga; cuadrilla 1 op + 0.5 peon
A49: N° | B49: RECURSO | C49: UND | D49: CUADRILLA | E49: CANTIDAD | F49: PRECIO S/ | G49: PARCIAL S/ | H49: SUSTENTO / FUENTE
B50: MANO DE OBRA
A51: 1 | B51: Operario | C51: hh | D51: 1 | E51: =D51*8/$C$48 -> 0.2 | F51: 30.42 | G51: =E51*F51 -> 6.084 | H51: CAPECO: costo hora-hombre 2024-2025 llevado al jornal basico 2025-2026
A52: 2 | B52: Peon | C52: hh | D52: 0.5 | E52: =D52*8/$C$48 -> 0.1 | F52: 20.79 | G52: =E52*F52 -> 2.079 | H52: CAPECO: costo hora-hombre 2024-2025 llevado al jornal basico 2025-2026
B53: Subtotal mano de obra | G53: =SUM(G51:G52) -> 8.163
B54: MATERIALES
A55: 3 | B55: Platina de fierro galvanizado 1" x 1/8" | C55: m | E55: =$D$20*1.05 -> 0.8925 | F55: 6.36 | G55: =E55*F55 -> 5.6763 | H55: desarrollo del soporte x 1.05 desperdicio; Mercado Tarapoto 2026, sin IGV (referencial)
A56: 4 | B56: Perno de expansion 1/4" x 2 1/2" con tarugo | C56: und | E56: 2 | F56: 1.02 | G56: =E56*F56 -> 2.04 | H56: 2 por soporte (una oreja a cada lado)
A57: 5 | B57: Tornillo autorroscante 1/4" x 3/4" (soporte a canaleta) | C57: und | E57: 2 | F57: 0.25 | G57: =E57*F57 -> 0.5 | H57: 2 por soporte
B58: Subtotal materiales | G58: =SUM(G55:G57) -> 8.2163
B59: EQUIPOS
A60: 6 | B60: Herramientas manuales | C60: %mo | E60: 0.05 | F60: =+G53 -> 8.163 | G60: =E60*F60 -> 0.40815 | H60: 5 % del costo de mano de obra (hojalateria)
B61: Subtotal equipos | G61: =SUM(G60:G60) -> 0.40815
A62: COSTO UNITARIO DIRECTO (S/ por und) | G62: =+G53+G58+G61 -> 16.78745
A63: COSTO DIRECTO DE LA PARTIDA (metrado x costo unitario) | G63: =G62*C47 -> 14840.106
A65: ACU 3: 01.04.03.05.01.05 TAPA LATERAL DE PLANCHA GALVANIZADA P/CANALETA
A66: Unidad | C66: und
A67: Metrado | C67: =+'PLANILLA GENERAL DE METRADOS'!K151 -> 40
A68: Rendimiento (und/dia) | C68: 30 | E68: trazo, corte, doblez de pestanas, remachado y sellado en el extremo de la canaleta; cuadrilla 1 op + 0.5 peon
A69: N° | B69: RECURSO | C69: UND | D69: CUADRILLA | E69: CANTIDAD | F69: PRECIO S/ | G69: PARCIAL S/ | H69: SUSTENTO / FUENTE
B70: MANO DE OBRA
A71: 1 | B71: Operario (hojalatero) | C71: hh | D71: 1 | E71: =D71*8/$C$68 -> 0.26666667 | F71: 30.42 | G71: =E71*F71 -> 8.112 | H71: CAPECO: costo hora-hombre 2024-2025 llevado al jornal basico 2025-2026
A72: 2 | B72: Peon | C72: hh | D72: 0.5 | E72: =D72*8/$C$68 -> 0.13333333 | F72: 20.79 | G72: =E72*F72 -> 2.772 | H72: CAPECO: costo hora-hombre 2024-2025 llevado al jornal basico 2025-2026
B73: Subtotal mano de obra | G73: =SUM(G71:G72) -> 10.884
B74: MATERIALES
A75: 3 | B75: Plancha de acero galvanizado e=0.9 mm | C75: m2 | E75: =($D$11*$D$12+2*($D$11+$D$12)*0.03)*1.1 -> 0.0847 | F75: 26.95 | G75: =E75*F75 -> 2.282665 | H75: tapa 0.25 x 0.20 + pestana de 0.03 en el contorno, 10 % desperdicio
A76: 4 | B76: Remache pop 1/8" | C76: und | E76: 6 | F76: 0.1 | G76: =E76*F76 -> 0.6 | H76: 6 por tapa
A77: 5 | B77: Sellador de poliuretano (cartucho 300 ml) | C77: und | E77: =($D$11+2*$D$12)/8 -> 0.08125 | F77: 21.19 | G77: =E77*F77 -> 1.7216875 | H77: contorno de la tapa (0.65 m) / 8 m por cartucho
B78: Subtotal materiales | G78: =SUM(G75:G77) -> 4.6043525
B79: EQUIPOS
A80: 6 | B80: Herramientas manuales | C80: %mo | E80: 0.05 | F80: =+G73 -> 10.884 | G80: =E80*F80 -> 0.5442 | H80: 5 % del costo de mano de obra (hojalateria)
B81: Subtotal equipos | G81: =SUM(G80:G80) -> 0.5442
A82: COSTO UNITARIO DIRECTO (S/ por und) | G82: =+G73+G78+G81 -> 16.032553
A83: COSTO DIRECTO DE LA PARTIDA (metrado x costo unitario) | G83: =G82*C67 -> 641.3021
A85: ACU 4: 01.04.03.05.01.06 BOQUILLA DE PLANCHA GALVANIZADA P/CONEXION DE CANALETA A MONTANTE Ø4"
A86: Unidad | C86: und
A87: Metrado | C87: =+'PLANILLA GENERAL DE METRADOS'!K152 -> 52
A88: Rendimiento (und/dia) | C88: 16 | E88: corte de la abertura en el fondo, fabricacion del tubo y la brida, remachado, sellado y embone al montante; cuadrilla 1 op + 0.5 peon
A89: N° | B89: RECURSO | C89: UND | D89: CUADRILLA | E89: CANTIDAD | F89: PRECIO S/ | G89: PARCIAL S/ | H89: SUSTENTO / FUENTE
B90: MANO DE OBRA
A91: 1 | B91: Operario (hojalatero) | C91: hh | D91: 1 | E91: =D91*8/$C$88 -> 0.5 | F91: 30.42 | G91: =E91*F91 -> 15.21 | H91: CAPECO: costo hora-hombre 2024-2025 llevado al jornal basico 2025-2026
A92: 2 | B92: Peon | C92: hh | D92: 0.5 | E92: =D92*8/$C$88 -> 0.25 | F92: 20.79 | G92: =E92*F92 -> 5.1975 | H92: CAPECO: costo hora-hombre 2024-2025 llevado al jornal basico 2025-2026
B93: Subtotal mano de obra | G93: =SUM(G91:G92) -> 20.4075
B94: MATERIALES
A95: 3 | B95: Plancha de acero galvanizado e=0.9 mm | C95: m2 | E95: =(PI()*0.1016*0.15+0.2*0.2)*1.15 -> 0.10105955 | F95: 26.95 | G95: =E95*F95 -> 2.7235549 | H95: tubo de 4" x 0.15 m (embone en el montante) + brida 0.20 x 0.20 en el fondo de la canaleta; 15 % desperdicio
A96: 4 | B96: Remache pop 1/8" | C96: und | E96: 8 | F96: 0.1 | G96: =E96*F96 -> 0.8 | H96: 8 por boquilla (brida al fondo de la canaleta)
A97: 5 | B97: Sellador de poliuretano (cartucho 300 ml) | C97: und | E97: =(4*0.2+PI()*0.1016)/8 -> 0.13989823 | F97: 21.19 | G97: =E97*F97 -> 2.9644434 | H97: contorno de la brida + embone (1.12 m) / 8 m por cartucho
B98: Subtotal materiales | G98: =SUM(G95:G97) -> 6.4879984
B99: EQUIPOS
A100: 6 | B100: Herramientas manuales | C100: %mo | E100: 0.05 | F100: =+G93 -> 20.4075 | G100: =E100*F100 -> 1.020375 | H100: 5 % del costo de mano de obra (hojalateria)
B101: Subtotal equipos | G101: =SUM(G100:G100) -> 1.020375
A102: COSTO UNITARIO DIRECTO (S/ por und) | G102: =+G93+G98+G101 -> 27.915873
A103: COSTO DIRECTO DE LA PARTIDA (metrado x costo unitario) | G103: =G102*C87 -> 1451.6254
A105: RESUMEN DE COSTOS DIRECTOS (referencial)
B106: PARTIDA | C106: UND | D106: METRADO | E106: C.U. S/ | F106: PARCIAL S/
A107: 01.04.03.05.01.03 | B107: CANALETA DE PLANCHA DE ACERO GALVANIZADO e=0.9mm, SECCION 0.25m x 0.20m | C107: m | D107: =+C27 -> 513.98 | E107: =+G42 -> 40.635769 | F107: =+G43 -> 20885.972
A108: 01.04.03.05.01.04 | B108: SOPORTE DE PLATINA F°G° 1" x 1/8" P/CANALETA | C108: und | D108: =+C47 -> 884 | E108: =+G62 -> 16.78745 | F108: =+G63 -> 14840.106
...

Sheet DESAGREGADO TAPA REGISTRO
A1: DESAGREGADO DE LA PARTIDA 01.04.04.05.01 - TAPA DE REGISTRO 0.68x0.68 C/MARCO Y CONTRAMARCO
A2: ENTIDAD | C2: =+RESUMEN!B4 -> GERENCIA TERRITORIAL BAJO MAYO - TARAPOTO
A3: PROYECTO | C3: =+RESUMEN!B5 -> “CREACIÓN DEL SERVICIO DE PROTECCIÓN A MUJERES VÍCTIMAS DE VIOLENCIA EN SITUACIÓN DE RIESGO DE FEMINICIDIO O PELIGRE SU INTEGRIDAD Y/O SALUD FÍSICA Y/O MENTAL EN HOGAR DE REFUGIO TEMPORAL DISTRITO DE MORALES DE LA PROVINCIA DE SAN MARTÍN DEL DEPARTAMENTO DE SAN MARTÍN”, con CUI N.° 2675514
A4: UBICACIÓN | C4: =+RESUMEN!B6 -> SAN MARTIN - SAN MARTIN - MORALES
A5: FECHA | C5: =+RESUMEN!B7 -> 46266
A7: La partida se mide por unidad de registro (tapa con marco y contramarco). Esta hoja muestra donde va cada registro y lo que lleva cada uno; las cantidades salen de las hojas COLECTOR PARAMETROS, COLECTOR REGISTROS Y TAPAS y COLECTOR ACERO (lamina DP-06B).
A9: A. UBICACION DE LOS REGISTROS
A10: N° | B10: REGISTRO | C10: PROGRESIVA | D10: UBICACION | F10: CANT. (und) | G10: SUSTENTO
A11: 1 | B11: =+'COLECTOR REGISTROS Y TAPAS'!B10 -> CL | C11: =+'COLECTOR REGISTROS Y TAPAS'!C10 -> 0+000.00 | D11: =+'COLECTOR REGISTROS Y TAPAS'!D10 -> Caja de llegada (empalme con CAR Varones y cuneta Eje 01) | F11: =+'COLECTOR REGISTROS Y TAPAS'!E10 -> 1 | G11: =+'COLECTOR REGISTROS Y TAPAS'!F10 -> DP-07
A12: 2 | B12: =+'COLECTOR REGISTROS Y TAPAS'!B11 -> RS-01 | C12: =+'COLECTOR REGISTROS Y TAPAS'!C11 -> 0+011.27 | D12: =+'COLECTOR REGISTROS Y TAPAS'!D11 -> Registro en la losa del colector; empalme cuneta | F12: =+'COLECTOR REGISTROS Y TAPAS'!E11 -> 1 | G12: =+'COLECTOR REGISTROS Y TAPAS'!F11 -> DP-01, DP-06B
A13: 3 | B13: =+'COLECTOR REGISTROS Y TAPAS'!B12 -> RS-02 | C13: =+'COLECTOR REGISTROS Y TAPAS'!C12 -> 0+022.00 | D13: =+'COLECTOR REGISTROS Y TAPAS'!D12 -> Registro en la losa del colector; limpieza / quiebre | F13: =+'COLECTOR REGISTROS Y TAPAS'!E12 -> 1 | G13: =+'COLECTOR REGISTROS Y TAPAS'!F12 -> DP-01, DP-06B
A14: 4 | B14: =+'COLECTOR REGISTROS Y TAPAS'!B13 -> RS-03 | C14: =+'COLECTOR REGISTROS Y TAPAS'!C13 -> 0+032.50 | D14: =+'COLECTOR REGISTROS Y TAPAS'!D13 -> Registro en la losa del colector; empalme cuneta | F14: =+'COLECTOR REGISTROS Y TAPAS'!E13 -> 1 | G14: =+'COLECTOR REGISTROS Y TAPAS'!F13 -> DP-01, DP-06B
A15: 5 | B15: =+'COLECTOR REGISTROS Y TAPAS'!B14 -> RS-04 | C15: =+'COLECTOR REGISTROS Y TAPAS'!C14 -> 0+042.68 | D15: =+'COLECTOR REGISTROS Y TAPAS'!D14 -> Registro en la losa del colector; empalme cuneta | F15: =+'COLECTOR REGISTROS Y TAPAS'!E14 -> 1 | G15: =+'COLECTOR REGISTROS Y TAPAS'!F14 -> DP-01, DP-06B
A16: 6 | B16: =+'COLECTOR REGISTROS Y TAPAS'!B15 -> RS-05 | C16: =+'COLECTOR REGISTROS Y TAPAS'!C15 -> 0+052.00 | D16: =+'COLECTOR REGISTROS Y TAPAS'!D15 -> Registro en la losa del colector; limpieza / quiebre | F16: =+'COLECTOR REGISTROS Y TAPAS'!E15 -> 1 | G16: =+'COLECTOR REGISTROS Y TAPAS'!F15 -> DP-01, DP-06B
A17: 7 | B17: =+'COLECTOR REGISTROS Y TAPAS'!B16 -> RS-06 | C17: =+'COLECTOR REGISTROS Y TAPAS'!C16 -> 0+058.81 | D17: =+'COLECTOR REGISTROS Y TAPAS'!D16 -> Registro en la losa del colector; limpieza / quiebre | F17: =+'COLECTOR REGISTROS Y TAPAS'!E16 -> 1 | G17: =+'COLECTOR REGISTROS Y TAPAS'!F16 -> DP-01, DP-06B
A18: 8 | B18: =+'COLECTOR REGISTROS Y TAPAS'!B17 -> RS-07 | C18: =+'COLECTOR REGISTROS Y TAPAS'!C17 -> 0+066.89 | D18: =+'COLECTOR REGISTROS Y TAPAS'!D17 -> Registro en la losa del colector; limpieza / quiebre | F18: =+'COLECTOR REGISTROS Y TAPAS'!E17 -> 1 | G18: =+'COLECTOR REGISTROS Y TAPAS'!F17 -> DP-01, DP-06B
A19: 9 | B19: =+'COLECTOR REGISTROS Y TAPAS'!B18 -> CC (2) | C19: =+'COLECTOR REGISTROS Y TAPAS'!C18 -> 0+069.89 | D19: =+'COLECTOR REGISTROS Y TAPAS'!D18 -> Caja de caida: dos registros sobre la poza | F19: =+'COLECTOR REGISTROS Y TAPAS'!E18 -> 2 | G19: =+'COLECTOR REGISTROS Y TAPAS'!F18 -> DP-07
B20: TOTAL DE REGISTROS (und de la partida) | F20: =SUM(F11:F19) -> 10
A22: B. COMPONENTES DE UNA TAPA DE REGISTRO Y TOTAL DE LA PARTIDA
A23: N° | B23: COMPONENTE | C23: UND | D23: POR REGISTRO | E23: N° REGISTROS | F23: TOTAL | G23: SUSTENTO
B24: ANGULOS METALICOS
A25: 1 | B25: Contramarco: angulo L 1 1/2"x1 1/2"x1/8", 4 x 0.70 = 2.80 m x 1.83 kg/m | C25: kg | D25: ='COLECTOR PARAMETROS'!C36*'COLECTOR PARAMETROS'!C38 -> 5.124 | E25: =+$F$20 -> 10 | F25: =D25*E25 -> 51.24 | G25: lamina DP-06B; esquinas a 45 grados soldadas
A26: 2 | B26: Marco de tapa: angulo L 1 1/2"x1 1/2"x1/8", 4 x 0.68 = 2.72 m x 1.83 kg/m | C26: kg | D26: ='COLECTOR PARAMETROS'!C37*'COLECTOR PARAMETROS'!C39 -> 4.9776 | E26: =+$F$20 -> 10 | F26: =D26*E26 -> 49.776 | G26: lamina DP-06B; sirve de encofrado de la tapa
B27: Subtotal angulos | C27: kg | D27: =SUM(D25:D26) -> 10.1016 | F27: =SUM(F25:F26) -> 101.016
B28: CONCRETO
A29: 3 | B29: Tapa de concreto f'c=210: 0.68 x 0.68 x 0.08 | C29: m3 | D29: ='COLECTOR PARAMETROS'!C33*'COLECTOR PARAMETROS'!C33*'COLECTOR PARAMETROS'!C34 -> 0.036992 | E29: =+$F$20 -> 10 | F29: =D29*E29 -> 0.36992 | G29: lamina DP-06B
B30: Subtotal concreto | C30: m3 | D30: =SUM(D29:D29) -> 0.036992 | F30: =SUM(F29:F29) -> 0.36992
B31: ACERO DE REFUERZO fy=4200
A32: 4 | B32: Parrilla de la tapa: 7 + 7 barras 3/8" @0.10, L = 0.62 | C32: kg | D32: ='COLECTOR ACERO'!U34/'COLECTOR ACERO'!F34 -> 4.8608 | E32: =+$F$20 -> 10 | F32: =D32*E32 -> 48.608 | G32: COLECTOR ACERO fila 34
A33: 5 | B33: Asas de la tapa: 2 barras 3/8" liso, desarrollo 0.40 | C33: kg | D33: ='COLECTOR ACERO'!U35/'COLECTOR ACERO'!F35 -> 0.448 | E33: =+$F$20 -> 10 | F33: =D33*E33 -> 4.48 | G33: COLECTOR ACERO fila 35
A34: 6 | B34: Anclajes del contramarco: 8 barras 3/8", L = 0.20 | C34: kg | D34: ='COLECTOR ACERO'!U36/'COLECTOR ACERO'!F36 -> 0.896 | E34: =+$F$20 -> 10 | F34: =D34*E34 -> 8.96 | G34: COLECTOR ACERO fila 36
A35: 7 | B35: Refuerzo de borde de la abertura: 8 barras 1/2", L = 1.40 | C35: kg | D35: ='COLECTOR ACERO'!U33/'COLECTOR ACERO'!F33 -> 11.1328 | E35: =+$F$20 -> 10 | F35: =D35*E35 -> 111.328 | G35: COLECTOR ACERO fila 33
B36: Subtotal acero | C36: kg | D36: =SUM(D32:D35) -> 17.3376 | F36: =SUM(F32:F35) -> 173.376
B37: PINTURA
A38: 8 | B38: Anticorrosivo y esmalte en angulos: 2.80 x 0.152 + 2.72 x 0.152 | C38: m2 | D38: ='COLECTOR PARAMETROS'!C36*'COLECTOR PARAMETROS'!C40+'COLECTOR PARAMETROS'!C37*'COLECTOR PARAMETROS'!C41 -> 0.83904 | E38: =+$F$20 -> 10 | F38: =D38*E38 -> 8.3904 | G38: 4 caras de cada angulo
B39: Subtotal pintura | C39: m2 | D39: =SUM(D38:D38) -> 0.83904 | F39: =SUM(F38:F38) -> 8.3904
A41: C. CONTROL CON EL METRADO DE LOS COMPONENTES (hojas del colector)
B42: COMPONENTE | C42: UND | E42: ESTA HOJA | F42: HOJA DEL COLECTOR | G42: CONTROL
B43: Angulos (marco y contramarco) | C43: kg | E43: =+F27 -> 101.016 | F43: =+'COLECTOR REGISTROS Y TAPAS'!E25 -> 101.016 | G43: =IF(ABS(E43-F43)<0.001,"CONFORME","REVISAR") -> CONFORME
B44: Concreto en tapas | C44: m3 | E44: =+F30 -> 0.36992 | F44: =+'COLECTOR REGISTROS Y TAPAS'!E27 -> 0.36992 | G44: =IF(ABS(E44-F44)<0.001,"CONFORME","REVISAR") -> CONFORME
B45: Acero en tapas, bordes y anclajes | C45: kg | E45: =+F36 -> 173.376 | F45: =+'COLECTOR ACERO'!I41 -> 173.376 | G45: =IF(ABS(E45-F45)<0.001,"CONFORME","REVISAR") -> CONFORME
B46: Pintura en angulos | C46: m2 | E46: =+F39 -> 8.3904 | F46: =+'COLECTOR REGISTROS Y TAPAS'!E28 -> 8.3904 | G46: =IF(ABS(E46-F46)<0.001,"CONFORME","REVISAR") -> CONFORME

Sheet ACU JUNTA DILATACION
A1: ANALISIS DE COSTO UNITARIO - JUNTA DE DILATACION E=1" CON TECNOPOR Y SELLADOR ASFALTICO EN COLECTOR
A2: ENTIDAD | C2: =+RESUMEN!B4 -> GERENCIA TERRITORIAL BAJO MAYO - TARAPOTO
A3: PROYECTO | C3: =+RESUMEN!B5 -> “CREACIÓN DEL SERVICIO DE PROTECCIÓN A MUJERES VÍCTIMAS DE VIOLENCIA EN SITUACIÓN DE RIESGO DE FEMINICIDIO O PELIGRE SU INTEGRIDAD Y/O SALUD FÍSICA Y/O MENTAL EN HOGAR DE REFUGIO TEMPORAL DISTRITO DE MORALES DE LA PROVINCIA DE SAN MARTÍN DEL DEPARTAMENTO DE SAN MARTÍN”, con CUI N.° 2675514
A4: UBICACIÓN | C4: =+RESUMEN!B6 -> SAN MARTIN - SAN MARTIN - MORALES
A5: FECHA | C5: =+RESUMEN!B7 -> 46266
A7: Partida de Delphin 01.04.04.06.01 JUNTA DE DILATACION E=1" CON TECNOPOR Y SELLADOR ASFALTICO EN COLECTOR (metrado 01.04.04.06.01, hoja COLECTOR JUNTAS Y EMPALMES). Se mide por metro de junta a lo largo del perimetro de la seccion. Cantidades de la lamina DD-03: plancha de tecnopor de 1" en toda la seccion y sellador asfaltico 1" x 2" (asfalto liquido RC-250 + arena gruesa) en las caras interiores y en la cara superior (EG-2013 MTC, 510). Celda amarilla = dato; verde = formula. Precios sin IGV.
A9: 1. CANTIDADES POR METRO DE JUNTA (lamina DD-03 y hoja COLECTOR JUNTAS Y EMPALMES)
A10: N° | B10: CONCEPTO | C10: UND | D10: VALOR | H10: SUSTENTO
A11: 1 | B11: Perimetro de la seccion en cada junta: 2 x 1.10 + 2 x (0.15 + 1.61 + 0.10) | C11: m | D11: ='COLECTOR JUNTAS Y EMPALMES'!E11 -> 5.92 | H11: COLECTOR JUNTAS Y EMPALMES fila 11; DD-03 A
A12: 2 | B12: Numero de juntas de dilatacion (cada 4.00 m) | C12: und | D12: ='COLECTOR JUNTAS Y EMPALMES'!D11 -> 17 | H12: COLECTOR JUNTAS Y EMPALMES fila 11; DD-03 E
A13: 3 | B13: Area de tecnopor por junta: seccion 1.10 x 1.86 menos el hueco 0.80 x 1.61 | C13: m2 | D13: =1.10*(0.15+1.61+0.10)-0.80*1.61 -> 0.758 | H13: DD-03, cuadro de componentes
A14: 4 | B14: Tecnopor por metro de junta (area neta) | C14: m2/m | D14: =D13/D11 -> 0.12804054 | H14: formula
