Workbook

Sheet RESUMEN
A2: RESUMEN METRADOS DE DRENAJE PLUVIAL
A4: ENTIDAD | B4: GERENCIA TERRITORIAL BAJO MAYO - TARAPOTO
A5: PROYECTO | B5: “CREACIÓN DEL SERVICIO DE PROTECCIÓN A MUJERES VÍCTIMAS DE VIOLENCIA EN SITUACIÓN DE RIESGO DE FEMINICIDIO O PELIGRE SU INTEGRIDAD Y/O SALUD FÍSICA Y/O MENTAL EN HOGAR DE REFUGIO TEMPORAL DISTRITO DE MORALES DE LA PROVINCIA DE SAN MARTÍN DEL DEPARTAMENTO DE SAN MARTÍN”, con CUI N.° 2675514
A6: UBICACIÓN | B6: SAN MARTIN - SAN MARTIN - MORALES
A7: FECHA | B7: 46266
A8: Item | B8: Descripción | C8: Unid. | D8: Total.
A9: 01.04.03 | B9: SISTEMA DE DRENAJE PLUVIAL
A10: 01.04.03.01 | B10: TRABAJOS PRELIMINARES
A11: 01.04.03.01.01 | B11: LIMPIEZA MANUAL DE TERRENO | C11: m² | D11: =+'PLANILLA GENERAL DE METRADOS'!K11
A12: 01.04.03.01.02 | B12: TRAZO, NIVELES Y REPLANTEO PRELIMINAR | C12: m² | D12: =+'PLANILLA GENERAL DE METRADOS'!K24
A13: 01.04.03.02 | B13: MOVIMIENTO DE TIERRAS
A14: 01.04.03.02.01 | B14: EXCAVACIÓN MANUAL DE ZANJAS P/CUNETAS | C14: m³ | D14: =+'PLANILLA GENERAL DE METRADOS'!K38
A15: 01.04.03.02.02 | B15: EXCAVACIÓN MANUAL DE ZANJAS P/DADOS DE CONCRETO | C15: m³ | D15: =+'PLANILLA GENERAL DE METRADOS'!K51
A16: 01.04.03.02.03 | B16: REFINE, NIVELACIÓN Y COMPACTACIÓN EN TERRENO NORMAL | C16: m² | D16: =+'PLANILLA GENERAL DE METRADOS'!K54
A17: 01.04.03.02.04 | B17: RELLENO COMPACTADO CON MATERIAL PROPIO SELECCIONADO | C17: m³ | D17: =+'PLANILLA GENERAL DE METRADOS'!K67
A18: 01.04.03.02.05 | B18: ELIMINACIÓN DE MATERIAL EXCEDENTE | C18: m³ | D18: =+'PLANILLA GENERAL DE METRADOS'!K80
A19: 01.04.03.03 | B19: OBRAS DE CONCRETO SIMPLE
A20: 01.04.03.03.01 | B20: CONCRETO f'c=100 kg/cm2 PARA SOLADO E=4'' | C20: m² | D20: =+'PLANILLA GENERAL DE METRADOS'!K84
A21: 01.04.03.03.02 | B21: CONCRETO f'c=140 Kg/cm2 PARA DADOS DE CONCRETO | C21: m³ | D21: =+'PLANILLA GENERAL DE METRADOS'!K97
A22: 01.04.03.04 | B22: OBRAS DE CONCRETO ARMADO
A23: 01.04.03.04.02 | B23: CUNETAS
A24: 01.04.03.04.02.01 | B24: CONCRETO P/CUNETAS f'c=175 kg/cm2 | C24: m³ | D24: =+'PLANILLA GENERAL DE METRADOS'!K101
A25: 01.04.03.04.02.02 | B25: ENCOFRADO Y DESENCOFRADO DE CUNETA | C25: m² | D25: =+'PLANILLA GENERAL DE METRADOS'!K114
A26: 01.04.03.04.02.03 | B26: ACERO f'y=4200 kg/cm2 PARA CUNETA | C26: kg | D26: =+'PLANILLA GENERAL DE METRADOS'!K127
A27: 01.04.03.04.02.04 | B27: CURADO DE CONCRETO EN CUNETA | C27: m² | D27: =+'METRADO DE CURADO'!M38
A28: 01.04.03.04.03 | B28: VARIOS
A29: 01.04.03.04.03.01 | B29: REJILLA METALICA P/CUNETA C/PL 1''x 3/16'' Y ANGULO 1'' x 1'' x 3/16'' | C29: ml | D29: =+'PLANILLA GENERAL DE METRADOS'!K132
A30: 01.04.03.04.03.02 | B30: TAPA DE INSPECCION 0.60m x 0.60m | C30: und | D30: =+'PLANILLA GENERAL DE METRADOS'!K133
A31: 01.04.03.04.03.03 | B31: JUNTA DE DILATACION E=1" CON SELLADOR ASFALTO | C31: ml | D31: =+'PLANILLA GENERAL DE METRADOS'!K134
A32: 01.04.03.05 | B32: RED DE COLECCIÓN
A33: 01.04.03.05.01 | B33: RED DE RECOLECCION TECHO
A34: 01.04.03.05.01.01 | B34: MONTANTE TUBERÍA PVC DE 4" | C34: m | D34: =+'PLANILLA GENERAL DE METRADOS'!K138
A35: 01.04.03.05.01.02 | B35: FALSA COLUMNA P/MONTANTE DE 0.20m x 0.15m x 1.30m | C35: und | D35: =+'PLANILLA GENERAL DE METRADOS'!K139
A36: 01.04.03.05.01.04,01 | B36: CONCRETO F´C=175 KG/CM2 EN FALSA COLUMNA | C36: m³ | D36: =+'PLANILLA GENERAL DE METRADOS'!K140
A37: 01.04.03.05.01.04,02 | B37: ENCOFRADO Y DESENCOFRADO EN FALSA COLUMNA - MONTANTE PLUVIAL | C37: m² | D37: =+'PLANILLA GENERAL DE METRADOS'!K142
A38: 01.04.03.05.01.04,03 | B38: ACERO FY=4200 KG/CM2 EN FALSA COLUMNA (MONTANTE PLUVIAL) | C38: kg | D38: =+'PLANILLA GENERAL DE METRADOS'!K145
A39: 01.04.03.05.02 | B39: RED DE RECOLECCION PISO
A40: 01.04.03.05.02.01 | B40: TUBERIA DESAGÜE PVC-CP Ø4" x 3m | C40: m | D40: =+'PLANILLA GENERAL DE METRADOS'!K150
A41: 01.04.03.05.02.02 | B41: SUMIDERO METALICO C/PLATINA 1" X 3/16" | C41: und | D41: =+'PLANILLA GENERAL DE METRADOS'!K151
A42: 01.04.03.05.02.03 | B42: CODO 90° x 4" | C42: und | D42: =+'PLANILLA GENERAL DE METRADOS'!K152
A43: 01.04.03.05.02.04 | B43: TEE° x 4" | C43: und | D43: =+'PLANILLA GENERAL DE METRADOS'!K153
A44: 01.04.03.05.03 | B44: ACCESORIOS
A45: 01.04.03.05.03.01 | B45: CODO DESAGÜE PVC Ø4" x 45° | C45: und | D45: =+'PLANILLA GENERAL DE METRADOS'!K156
A46: 01.04.03.05.03.02 | B46: CODO DESAGÜE PVC Ø4" x 90° | C46: und | D46: =+'PLANILLA GENERAL DE METRADOS'!K157
A47: 01.04.03.05.03.03 | B47: TEE DESAGÜE PVC Ø4" | C47: und | D47: =+'PLANILLA GENERAL DE METRADOS'!K158
A48: 01.04.03.05.03.04 | B48: COLGADOR F°G° P/TUBERIA PVC Ø4" | C48: und | D48: =+'PLANILLA GENERAL DE METRADOS'!K159
A49: 01.04.03.05.03.05 | B49: ABRAZADERA DE F°G° P/TUBERIA PVC Ø4" | C49: und | D49: =+'PLANILLA GENERAL DE METRADOS'!K160
A51: 01.04.04 | B51: COLECTOR PLUVIAL FRONTAL (TRAMO HOGAR DE REFUGIO - EMPALME CON CAR MUJERES)
A52: 01.04.04.01 | B52: TRABAJOS PRELIMINARES
A53: 01.04.04.01.01 | B53: LIMPIEZA MANUAL DE TERRENO | C53: m² | D53: =+'PLANILLA GENERAL DE METRADOS'!K164
A54: 01.04.04.01.02 | B54: TRAZO, NIVELES Y REPLANTEO PRELIMINAR | C54: m² | D54: =+'PLANILLA GENERAL DE METRADOS'!K174
A55: 01.04.04.02 | B55: MOVIMIENTO DE TIERRAS
A56: 01.04.04.02.01 | B56: EXCAVACIÓN MANUAL DE ZANJAS P/COLECTOR (ancho 1.60 m) | C56: m³ | D56: =+'PLANILLA GENERAL DE METRADOS'!K185
A57: 01.04.04.02.02 | B57: REFINE, NIVELACIÓN Y COMPACTACIÓN EN TERRENO NORMAL | C57: m² | D57: =+'PLANILLA GENERAL DE METRADOS'!K195
A58: 01.04.04.02.03 | B58: RELLENO COMPACTADO CON MATERIAL PROPIO SELECCIONADO (incluye nivelacion del retiro y base de cajas) | C58: m³ | D58: =+'PLANILLA GENERAL DE METRADOS'!K205
A59: 01.04.04.02.04 | B59: ELIMINACIÓN DE MATERIAL EXCEDENTE | C59: m³ | D59: =+'PLANILLA GENERAL DE METRADOS'!K222
A60: 01.04.04.03 | B60: OBRAS DE CONCRETO SIMPLE
A61: 01.04.04.03.01 | B61: CONCRETO f'c=100 kg/cm2 PARA SOLADO E=2" (0.05 m) | C61: m² | D61: =+'PLANILLA GENERAL DE METRADOS'!K226
A62: 01.04.04.04 | B62: OBRAS DE CONCRETO ARMADO - COLECTOR Y CAJAS
A63: 01.04.04.04.01 | B63: CONCRETO f'c=210 kg/cm2 EN LOSA DE FONDO | C63: m³ | D63: =+'PLANILLA GENERAL DE METRADOS'!K237
A64: 01.04.04.04.02 | B64: CONCRETO f'c=210 kg/cm2 EN MUROS | C64: m³ | D64: =+'PLANILLA GENERAL DE METRADOS'!K247
A65: 01.04.04.04.03 | B65: CONCRETO f'c=210 kg/cm2 EN LOSA SUPERIOR (incluye bordes de registro) | C65: m³ | D65: =+'PLANILLA GENERAL DE METRADOS'!K257
A66: 01.04.04.04.04 | B66: ENCOFRADO Y DESENCOFRADO NORMAL EN COLECTOR Y CAJAS | C66: m² | D66: =+'PLANILLA GENERAL DE METRADOS'!K269
A67: 01.04.04.04.05 | B67: ACERO DE REFUERZO fy=4200 kg/cm2 EN COLECTOR Y CAJAS | C67: kg | D67: =+'PLANILLA GENERAL DE METRADOS'!K279
A68: 01.04.04.04.06 | B68: ACABADO FROTACHADO Y BRUÑADO DE LOSA SUPERIOR | C68: m² | D68: =+'PLANILLA GENERAL DE METRADOS'!K289
A69: 01.04.04.04.07 | B69: CURADO DE CONCRETO EN COLECTOR Y CAJAS | C69: m² | D69: =+'PLANILLA GENERAL DE METRADOS'!K299
A70: 01.04.04.05 | B70: REGISTROS DE LIMPIEZA Y TAPAS
A71: 01.04.04.05.01 | B71: CONTRAMARCO METALICO L 2"x2"x3/16" CON ANCLAJES | C71: und | D71: =+'PLANILLA GENERAL DE METRADOS'!K310
A72: 01.04.04.05.02 | B72: MARCO METALICO DE TAPA L 1 1/2"x1 1/2"x1/8" | C72: und | D72: =+'PLANILLA GENERAL DE METRADOS'!K311
A73: 01.04.04.05.03 | B73: ANGULOS METALICOS P/MARCO Y CONTRAMARCO (incluye soldadura) | C73: kg | D73: =+'PLANILLA GENERAL DE METRADOS'!K312
A74: 01.04.04.05.04 | B74: TAPA DE CONCRETO ARMADO 0.68 x 0.68 x 0.08 m (incluye acero y asas) | C74: und | D74: =+'PLANILLA GENERAL DE METRADOS'!K313
A75: 01.04.04.05.05 | B75: CONCRETO f'c=210 kg/cm2 EN TAPAS | C75: m³ | D75: =+'PLANILLA GENERAL DE METRADOS'!K314
A76: 01.04.04.05.06 | B76: ACERO DE REFUERZO fy=4200 kg/cm2 EN TAPAS, BORDES Y ANCLAJES | C76: kg | D76: =+'PLANILLA GENERAL DE METRADOS'!K315
A77: 01.04.04.05.07 | B77: PINTURA ANTICORROSIVA Y ESMALTE EN ANGULOS | C77: m² | D77: =+'PLANILLA GENERAL DE METRADOS'!K316
A78: 01.04.04.06 | B78: JUNTAS Y EMPALMES
A79: 01.04.04.06.01 | B79: JUNTA DE DILATACION E=1" CON TECNOPOR Y SELLADOR ELASTOMERICO | C79: m | D79: =+'PLANILLA GENERAL DE METRADOS'!K318
A80: 01.04.04.06.02 | B80: JUNTA DE TECNOPOR E=1" ENTRE COLECTOR, CERCO Y PISO ADYACENTE | C80: m | D80: =+'PLANILLA GENERAL DE METRADOS'!K319
A81: 01.04.04.06.03 | B81: EMPALME DE CUNETA AL COLECTOR (ventana en muro y caida) | C81: und | D81: =+'PLANILLA GENERAL DE METRADOS'!K320

Sheet PLANILLA GENERAL DE METRADOS
A2: RESUMEN METRADOS DE DRENAJE PLUVIAL
A3: ENTIDAD | B3: =+RESUMEN!B4
A4: PROYECTO | B4: =+RESUMEN!B5
A5: UBICACIÓN | B5: =+RESUMEN!B6
A6: FECHA | B6: =+RESUMEN!B7
A8: ITEM | B8: DESCRIPCION | C8: Nº DE VECES | D8: LARGO | E8: ANCHO | F8: ALTURA | G8: FACT. | H8: AREA | I8: VOLUMEN | J8: PARCIAL | K8: TOTAL | L8: UND
A9: 01.04.03 | B9: SISTEMA DE DRENAJE PLUVIAL
A10: 01.04.03.01 | B10: TRABAJOS PRELIMINARES
A11: 01.04.03.01.01 | B11: LIMPIEZA MANUAL DE TERRENO | K11: =SUM(J12:J23) | L11: m²
B12: EJE 1 | C12: 1 | D12: 37.14 | E12: 1.4 | J12: =C12*D12*E12
B13: EJE 2 | C13: 1 | D13: 130.85 | E13: 1.4 | J13: =C13*D13*E13
B14: EJE 3 | C14: 1 | D14: 5.82 | E14: 1.4 | J14: =C14*D14*E14
B15: EJE 4 | C15: 1 | D15: 8.6 | E15: 1.4 | J15: =C15*D15*E15
B16: EJE 5 | C16: 1 | D16: 43.23 | E16: 1.4 | J16: =C16*D16*E16
B17: EJE 6 | C17: 1 | D17: 120.36 | E17: 1.4 | J17: =C17*D17*E17
B18: EJE 7 | C18: 1 | D18: 125.7 | E18: 1.4 | J18: =C18*D18*E18
B19: EJE 8 | C19: 1 | D19: 8.2 | E19: 1.4 | J19: =C19*D19*E19
B20: EJE 9 | C20: 1 | D20: 7 | E20: 1.4 | J20: =C20*D20*E20
B21: EJE 10 | C21: 1 | D21: 16 | E21: 1.4 | J21: =C21*D21*E21
B22: EJE 11 | C22: 1 | D22: 71.46 | E22: 1.4 | J22: =C22*D22*E22
B23: EJE 12 | C23: 1 | D23: 109.12 | E23: 1.4 | J23: =C23*D23*E23
A24: 01.04.03.01.02 | B24: TRAZO, NIVELES Y REPLANTEO PRELIMINAR | K24: =SUM(J25:J36) | L24: m²
B25: EJE 1 | C25: 1 | D25: 37.14 | E25: 1.4 | J25: =C25*D25*E25
B26: EJE 2 | C26: 1 | D26: 130.85 | E26: 1.4 | J26: =C26*D26*E26
B27: EJE 3 | C27: 1 | D27: 5.82 | E27: 1.4 | J27: =C27*D27*E27
B28: EJE 4 | C28: 1 | D28: 8.6 | E28: 1.4 | J28: =C28*D28*E28
B29: EJE 5 | C29: 1 | D29: 43.23 | E29: 1.4 | J29: =C29*D29*E29
B30: EJE 6 | C30: 1 | D30: 120.36 | E30: 1.4 | J30: =C30*D30*E30
B31: EJE 7 | C31: 1 | D31: 125.7 | E31: 1.4 | J31: =C31*D31*E31
B32: EJE 8 | C32: 1 | D32: 8.2 | E32: 1.4 | J32: =C32*D32*E32
B33: EJE 9 | C33: 1 | D33: 7 | E33: 1.4 | J33: =C33*D33*E33
B34: EJE 10 | C34: 1 | D34: 16 | E34: 1.4 | J34: =C34*D34*E34
B35: EJE 11 | C35: 1 | D35: 71.46 | E35: 1.4 | J35: =C35*D35*E35
B36: EJE 12 | C36: 1 | D36: 109.12 | E36: 1.4 | J36: =C36*D36*E36
A37: 01.04.03.02 | B37: MOVIMIENTO DE TIERRAS
A38: 01.04.03.02.01 | B38: EXCAVACIÓN MANUAL DE ZANJAS P/CUNETAS | K38: =SUM(J39:J50) | L38: m³
B39: EJE 1 | C39: 1 | D39: 37.14 | E39: 1.4 | F39: 0.4 | J39: =C39*D39*E39*(F39+PARAMETROS!$B$15)
B40: EJE 2 | C40: 1 | D40: 130.85 | E40: 1.4 | F40: 0.62 | J40: =C40*D40*E40*(F40+PARAMETROS!$B$15)
B41: EJE 3 | C41: 1 | D41: 5.82 | E41: 1.4 | F41: 0.3 | J41: =C41*D41*E41*(F41+PARAMETROS!$B$15)
B42: EJE 4 | C42: 1 | D42: 8.6 | E42: 1.4 | F42: 0.32 | J42: =C42*D42*E42*(F42+PARAMETROS!$B$15)
B43: EJE 5 | C43: 1 | D43: 43.23 | E43: 1.4 | F43: 0.4 | J43: =C43*D43*E43*(F43+PARAMETROS!$B$15)
B44: EJE 6 | C44: 1 | D44: 120.36 | E44: 1.4 | F44: 0.6 | J44: =C44*D44*E44*(F44+PARAMETROS!$B$15)
B45: EJE 7 | C45: 1 | D45: 125.7 | E45: 1.4 | F45: 0.61 | J45: =C45*D45*E45*(F45+PARAMETROS!$B$15)
B46: EJE 8 | C46: 1 | D46: 8.2 | E46: 1.4 | F46: 0.42 | J46: =C46*D46*E46*(F46+PARAMETROS!$B$15)
B47: EJE 9 | C47: 1 | D47: 7 | E47: 1.4 | F47: 0.41 | J47: =C47*D47*E47*(F47+PARAMETROS!$B$15)
B48: EJE 10 | C48: 1 | D48: 16 | E48: 1.4 | F48: 0.35 | J48: =C48*D48*E48*(F48+PARAMETROS!$B$15)
B49: EJE 11 | C49: 1 | D49: 71.46 | E49: 1.4 | F49: 0.47 | J49: =C49*D49*E49*(F49+PARAMETROS!$B$15)
B50: EJE 12 | C50: 1 | D50: 109.12 | E50: 1.4 | F50: 0.57 | J50: =C50*D50*E50*(F50+PARAMETROS!$B$15)
A51: 01.04.03.02.02 | B51: EXCAVACIÓN MANUAL DE ZANJAS P/DADOS DE CONCRETO | C51: 62 | K51: =J52*C51 | L51: m³
B52: DADO 0.40 X 0.40 | D52: 0.4 | E52: 0.35 | F52: 0.4 | J52: =D52*E52*F52
A54: 01.04.03.02.03 | B54: REFINE, NIVELACIÓN Y COMPACTACIÓN EN TERRENO NORMAL | K54: =SUM(J55:J66) | L54: m²
B55: EJE 1 | C55: 1 | D55: 37.14 | E55: 0.6 | J55: =C55*D55*E55
B56: EJE 2 | C56: 1 | D56: 130.85 | E56: 0.6 | J56: =C56*D56*E56
B57: EJE 3 | C57: 1 | D57: 5.82 | E57: 0.6 | J57: =C57*D57*E57
B58: EJE 4 | C58: 1 | D58: 8.6 | E58: 0.6 | J58: =C58*D58*E58
B59: EJE 5 | C59: 1 | D59: 43.23 | E59: 0.6 | J59: =C59*D59*E59
B60: EJE 6 | C60: 1 | D60: 120.36 | E60: 0.6 | J60: =C60*D60*E60
B61: EJE 7 | C61: 1 | D61: 125.7 | E61: 0.6 | J61: =C61*D61*E61
B62: EJE 8 | C62: 1 | D62: 8.2 | E62: 0.6 | J62: =C62*D62*E62
B63: EJE 9 | C63: 1 | D63: 7 | E63: 0.6 | J63: =C63*D63*E63
B64: EJE 10 | C64: 1 | D64: 16 | E64: 0.6 | J64: =C64*D64*E64
B65: EJE 11 | C65: 1 | D65: 71.46 | E65: 0.6 | J65: =C65*D65*E65
B66: EJE 12 | C66: 1 | D66: 109.12 | E66: 0.6 | J66: =C66*D66*E66
A67: 01.04.03.02.04 | B67: RELLENO COMPACTADO CON MATERIAL PROPIO SELECCIONADO | K67: =SUM(J68:J79) | L67: m³
B68: EJE 1 | C68: 1 | D68: 37.14 | E68: 0.8 | F68: 0.41 | J68: =C68*D68*E68*(F68+PARAMETROS!$B$15)
B69: EJE 2 | C69: 1 | D69: 130.85 | E69: 0.8 | F69: 0.65 | J69: =C69*D69*E69*(F69+PARAMETROS!$B$15)
B70: EJE 3 | C70: 1 | D70: 5.82 | E70: 0.8 | F70: 0.37 | J70: =C70*D70*E70*(F70+PARAMETROS!$B$15)
B71: EJE 4 | C71: 1 | D71: 8.6 | E71: 0.8 | F71: 0.33 | J71: =C71*D71*E71*(F71+PARAMETROS!$B$15)
B72: EJE 5 | C72: 1 | D72: 43.23 | E72: 0.8 | F72: 0.37 | J72: =C72*D72*E72*(F72+PARAMETROS!$B$15)
B73: EJE 6 | C73: 1 | D73: 120.36 | E73: 0.8 | F73: 0.56 | J73: =C73*D73*E73*(F73+PARAMETROS!$B$15)
B74: EJE 7 | C74: 1 | D74: 125.7 | E74: 0.8 | F74: 0.62 | J74: =C74*D74*E74*(F74+PARAMETROS!$B$15)
B75: EJE 8 | C75: 1 | D75: 8.2 | E75: 0.8 | F75: 0.35 | J75: =C75*D75*E75*(F75+PARAMETROS!$B$15)
B76: EJE 9 | C76: 1 | D76: 7 | E76: 0.8 | F76: 0.45 | J76: =C76*D76*E76*(F76+PARAMETROS!$B$15)
B77: EJE 10 | C77: 1 | D77: 16 | E77: 0.8 | F77: 0.55 | J77: =C77*D77*E77*(F77+PARAMETROS!$B$15)
B78: EJE 11 | C78: 1 | D78: 71.46 | E78: 0.8 | F78: 0.34 | J78: =C78*D78*E78*(F78+PARAMETROS!$B$15)
B79: EJE 12 | C79: 1 | D79: 109.12 | E79: 0.8 | F79: 0.51 | J79: =C79*D79*E79*(F79+PARAMETROS!$B$15)
A80: 01.04.03.02.05 | B80: ELIMINACIÓN DE MATERIAL EXCEDENTE | G80: =PARAMETROS!$B$16 | K80: =(J81+J82)*G80 | L80: m³
B81: EXCAVACIÓN MANUAL DE ZANJA PARA CUNETA | G81: 1 | I81: =+K38 | J81: =G81*I81
B82: RELLENO COMPACTADO CON MATERIAL PROPIO | G82: -1 | I82: =+K67 | J82: =G82*I82
A83: 01.04.03.03 | B83: OBRAS DE CONCRETO SIMPLE
A84: 01.04.03.03.01 | B84: CONCRETO f'c=100 kg/cm2 PARA SOLADO E=4'' | K84: =SUM(J85:J96) | L84: m²
B85: EJE 1 | C85: 1 | D85: 37.14 | E85: 0.6 | J85: =C85*D85*E85
B86: EJE 2 | C86: 1 | D86: 130.85 | E86: 0.6 | J86: =C86*D86*E86
B87: EJE 3 | C87: 1 | D87: 5.82 | E87: 0.6 | J87: =C87*D87*E87
B88: EJE 4 | C88: 1 | D88: 8.6 | E88: 0.6 | J88: =C88*D88*E88
B89: EJE 5 | C89: 1 | D89: 43.23 | E89: 0.6 | J89: =C89*D89*E89
B90: EJE 6 | C90: 1 | D90: 120.36 | E90: 0.6 | J90: =C90*D90*E90
B91: EJE 7 | C91: 1 | D91: 125.7 | E91: 0.6 | J91: =C91*D91*E91
B92: EJE 8 | C92: 1 | D92: 8.2 | E92: 0.6 | J92: =C92*D92*E92
B93: EJE 9 | C93: 1 | D93: 7 | E93: 0.6 | J93: =C93*D93*E93
B94: EJE 10 | C94: 1 | D94: 16 | E94: 0.6 | J94: =C94*D94*E94
B95: EJE 11 | C95: 1 | D95: 71.46 | E95: 0.6 | J95: =C95*D95*E95
B96: EJE 12 | C96: 1 | D96: 109.12 | E96: 0.6 | J96: =C96*D96*E96
A97: 01.04.03.03.02 | B97: CONCRETO f'c=140 Kg/cm2 PARA DADOS DE CONCRETO | C97: 62 | K97: =J98*C97 | L97: m³
B98: DADO 0.40 X 0.40 | D98: 0.4 | E98: 0.35 | F98: 0.4 | J98: =D98*E98*F98
A99: 01.04.03.04 | B99: OBRAS DE CONCRETO ARMADO
A100: 01.04.03.04.02 | B100: CUNETAS
A101: 01.04.03.04.02.01 | B101: CONCRETO P/CUNETAS f'c=175 kg/cm2 | K101: =SUM(J102:J113) | L101: m³
B102: EJE 1 | C102: 1 | J102: =+'CONCRETO EN CUNETAS'!G10
B103: EJE 2 | C103: 1 | J103: =+'CONCRETO EN CUNETAS'!G22
...

Sheet CONCRETO EN CUNETAS
B2: CONCRETO F´C=175 KG/CM2 PARA CUNETAS - DRENAJE PLUVIAL
B3: ENTIDAD | C3: =+RESUMEN!B4
B4: PROYECTO | C4: =+RESUMEN!B5
B5: UBICACIÓN | C5: =+RESUMEN!B6
B6: FECHA | C6: =+RESUMEN!B7
B7: OBRAS DE CONCRETO ARMADO
B9: LONGITUDES Y AREAS | E9: m3 | F9: Sub.TOTAL | G9: TOTAL (m3) | J9: LONGITUDES Y AREAS | M9: m3 | N9: Sub.TOTAL | O9: TOTAL (m3)
B10: CUNETA EJE 01 | C10: MUROS | D10: AREA | E10: 14.07 | F10: =E10*E11*E12 | G10: =SUM(F10:F18) | J10: CUNETA EJE 07 | K10: MUROS | L10: AREA | M10: 74.5 | N10: =M10*M11*M12 | O10: =SUM(N10:N18)
D11: ESPESOR | E11: 0.1 | L11: ESPESOR | M11: 0.1
D12: CANT. | E12: 2 | L12: CANT. | M12: 2
C13: LOSA | D13: ESPESOR | E13: 0.1 | F13: =E13*E14*E15 | K13: LOSA | L13: ESPESOR | M13: 0.1 | N13: =M13*M14*M15
D14: LONGITUD | E14: 37.14 | L14: LONGITUD | M14: 125.7
D15: ANCHO | E15: 0.6 | L15: ANCHO | M15: 0.6
C16: TAPA | D16: LONGITUD | E16: 5.14 | F16: =E16*E17*E18 | K16: TAPA | L16: LONGITUD | M16: 24.41 | N16: =M16*M17*M18
D17: ESPESOR | E17: 0.1 | L17: ESPESOR | M17: 0.1
D18: ANCHO | E18: 0.6 | L18: ANCHO | M18: 0.6
B21: LONGITUDES Y AREAS | E21: m3 | F21: Sub.TOTAL | G21: TOTAL (m3) | J21: LONGITUDES Y AREAS | M21: m3 | N21: Sub.TOTAL | O21: TOTAL (m3)
B22: CUNETA EJE 02 | C22: MUROS | D22: AREA | E22: 78.32 | F22: =E22*E23*E24 | G22: =SUM(F22:F30) | J22: CUNETA EJE 08 | K22: MUROS | L22: AREA | M22: 2.62 | N22: =M22*M23*M24 | O22: =SUM(N22:N30)
D23: ESPESOR | E23: 0.1 | L23: ESPESOR | M23: 0.1
D24: CANT. | E24: 2 | L24: CANT. | M24: 2
C25: LOSA | D25: ESPESOR | E25: 0.1 | F25: =E25*E26*E27 | K25: LOSA | L25: ESPESOR | M25: 0.1 | N25: =M25*M26*M27
D26: LONGITUD | E26: 130.85 | L26: LONGITUD | M26: 8.2
D27: ANCHO | E27: 0.6 | L27: ANCHO | M27: 0.6
C28: TAPA | D28: LONGITUD | E28: 31.66 | F28: =E28*E29*E30 | K28: TAPA | L28: LONGITUD | M28: 8.2 | N28: =M28*M29*M30
D29: ESPESOR | E29: 0.1 | L29: ESPESOR | M29: 0.1
D30: ANCHO | E30: 0.6 | L30: ANCHO | M30: 0.6
B33: LONGITUDES Y AREAS | E33: m3 | F33: Sub.TOTAL | G33: TOTAL (m3) | J33: LONGITUDES Y AREAS | M33: m3 | N33: Sub.TOTAL | O33: TOTAL (m3)
B34: CUNETA EJE 03 | C34: MUROS | D34: AREA | E34: 1.83 | F34: =E34*E35*E36 | G34: =SUM(F34:F42) | J34: CUNETA EJE 09 | K34: MUROS | L34: AREA | M34: 2.22 | N34: =M34*M35*M36 | O34: =SUM(N34:N42)
D35: ESPESOR | E35: 0.1 | L35: ESPESOR | M35: 0.1
D36: CANT. | E36: 2 | L36: CANT. | M36: 2
C37: LOSA | D37: ESPESOR | E37: 0.1 | F37: =E37*E38*E39 | K37: LOSA | L37: ESPESOR | M37: 0.1 | N37: =M37*M38*M39
D38: LONGITUD | E38: 5.82 | L38: LONGITUD | M38: 7
D39: ANCHO | E39: 0.6 | L39: ANCHO | M39: 0.6
C40: TAPA | D40: LONGITUD | E40: 0 | F40: =E40*E41*E42 | K40: TAPA | L40: LONGITUD | M40: 7 | N40: =M40*M41*M42
D41: ESPESOR | E41: 0.1 | L41: ESPESOR | M41: 0.1
D42: ANCHO | E42: 0.6 | L42: ANCHO | M42: 0.6
B45: LONGITUDES Y AREAS | E45: m3 | F45: Sub.TOTAL | G45: TOTAL (m3) | J45: LONGITUDES Y AREAS | M45: m3 | N45: Sub.TOTAL | O45: TOTAL (m3)
B46: CUNETA EJE 04 | C46: MUROS | D46: AREA | E46: 2.76 | F46: =E46*E47*E48 | G46: =SUM(F46:F54) | J46: CUNETA EJE 10 | K46: MUROS | L46: AREA | M46: 5.44 | N46: =M46*M47*M48 | O46: =SUM(N46:N54)
D47: ESPESOR | E47: 0.1 | L47: ESPESOR | M47: 0.1
D48: CANT. | E48: 2 | L48: CANT. | M48: 2
C49: LOSA | D49: ESPESOR | E49: 0.1 | F49: =E49*E50*E51 | K49: LOSA | L49: ESPESOR | M49: 0.1 | N49: =M49*M50*M51
D50: LONGITUD | E50: 8.6 | L50: LONGITUD | M50: 16
D51: ANCHO | E51: 0.6 | L51: ANCHO | M51: 0.6
C52: TAPA | D52: LONGITUD | E52: 0 | F52: =E52*E53*E54 | K52: TAPA | L52: LONGITUD | M52: 0 | N52: =M52*M53*M54
D53: ESPESOR | E53: 0.1 | L53: ESPESOR | M53: 0.1
D54: ANCHO | E54: 0.6 | L54: ANCHO | M54: 0.6
B57: LONGITUDES Y AREAS | E57: m3 | F57: Sub.TOTAL | G57: TOTAL (m3) | J57: LONGITUDES Y AREAS | M57: m3 | N57: Sub.TOTAL | O57: TOTAL (m3)
B58: CUNETA EJE 05 | C58: MUROS | D58: AREA | E58: 17.7 | F58: =E58*E59*E60 | G58: =SUM(F58:F66) | J58: CUNETA EJE 11 | K58: MUROS | L58: AREA | M58: 33 | N58: =M58*M59*M60 | O58: =SUM(N58:N66)
D59: ESPESOR | E59: 0.1 | L59: ESPESOR | M59: 0.1
D60: CANT. | E60: 2 | L60: CANT. | M60: 2
C61: LOSA | D61: ESPESOR | E61: 0.1 | F61: =E61*E62*E63 | K61: LOSA | L61: ESPESOR | M61: 0.1 | N61: =M61*M62*M63
D62: LONGITUD | E62: 43.23 | L62: LONGITUD | M62: 71.46
D63: ANCHO | E63: 0.6 | L63: ANCHO | M63: 0.6
C64: TAPA | D64: LONGITUD | E64: 5.7 | F64: =E64*E65*E66 | K64: TAPA | L64: LONGITUD | M64: 8.7 | N64: =M64*M65*M66
D65: ESPESOR | E65: 0.1 | L65: ESPESOR | M65: 0.1
D66: ANCHO | E66: 0.6 | L66: ANCHO | M66: 0.6
B69: LONGITUDES Y AREAS | E69: m3 | F69: Sub.TOTAL | G69: TOTAL (m3) | J69: LONGITUDES Y AREAS | M69: m3 | N69: Sub.TOTAL | O69: TOTAL (m3)
B70: CUNETA EJE 06 | C70: MUROS | D70: AREA | E70: 69.72 | F70: =E70*E71*E72 | G70: =SUM(F70:F78) | J70: CUNETA EJE 12 | K70: MUROS | L70: AREA | M70: 54 | N70: =M70*M71*M72 | O70: =SUM(N70:N78)
D71: ESPESOR | E71: 0.1 | L71: ESPESOR | M71: 0.1
D72: CANT. | E72: 2 | L72: CANT. | M72: 2
C73: LOSA | D73: ESPESOR | E73: 0.1 | F73: =E73*E74*E75 | K73: LOSA | L73: ESPESOR | M73: 0.1 | N73: =M73*M74*M75
D74: LONGITUD | E74: 120.36 | L74: LONGITUD | M74: 109.12
D75: ANCHO | E75: 0.6 | L75: ANCHO | M75: 0.6
C76: TAPA | D76: LONGITUD | E76: 25.9 | F76: =E76*E77*E78 | K76: TAPA | L76: LONGITUD | M76: 56.64 | N76: =M76*M77*M78
D77: ESPESOR | E77: 0.1 | L77: ESPESOR | M77: 0.1
D78: ANCHO | E78: 0.6 | L78: ANCHO | M78: 0.6

Sheet ENCOFRADO Y DESENCOFRADO
B2: ENCOFRADO Y DESENCOFRADO CUNETAS - DRENAJE PLUVIAL
B3: ENTIDAD | C3: =+RESUMEN!B4
B4: PROYECTO | C4: =+RESUMEN!B5
B5: UBICACIÓN | C5: =+RESUMEN!B6
B6: FECHA | C6: =+RESUMEN!B7
B8: OBRAS DE CONCRETO ARMADO - ENCOFRADO Y DESENCOFRADO CUNETAS
B11: LONGITUDES Y AREAS | G11: Sub.TOTAL | H11: TOTAL (m2) | J11: LONGITUDES Y AREAS | O11: Sub.TOTAL | P11: TOTAL (m2)
B12: EJE1 | C12: ABIERTA | D12: MUROS EXTERNO | E12: AREA | F12: 15.36 | G12: =F12*F13 | H12: =SUM(G12:G20) | J12: EJE 2 | K12: NORMAL | L12: MUROS EXTERNO | M12: AREA | N12: 68.67 | O12: =N12*N13 | P12: =SUM(O12:O20)
E13: CANT. | F13: 2 | M13: CANT. | N13: 2
D14: MURO INTERNO | E14: AREA | F14: 12.16 | G14: =F14*F15 | L14: MURO INTERNO | M14: AREA | N14: 58.75 | O14: =N14*N15
E15: CANTIDAD | F15: 2 | M15: CANTIDAD | N15: 2
C16: TAPADO | D16: MURO EXTERNO | E16: AREA | F16: 2.94 | G16: =F16*F17 | K16: TAPADO | L16: MURO EXTERNO | M16: AREA | N16: 25.9 | O16: =N16*N17
E17: CANT. | F17: 2 | M17: CANT. | N17: 2
D18: MURO INTERNO | E18: AREA | F18: 1.91 | G18: =(F18*F19)+F20 | L18: MURO INTERNO | M18: AREA | N18: 19.57 | O18: =N18*N19+N20
E19: CANTIDAD | F19: 2 | M19: CANTIDAD | N19: 2
E20: TAPA | F20: =5.14*0.4 | M20: TAPA | N20: =31.66*0.4
B22: LONGITUDES Y AREAS | G22: Sub.TOTAL | H22: TOTAL (m2) | J22: LONGITUDES Y AREAS | O22: Sub.TOTAL | P22: TOTAL (m2)
B23: EJE 3 | C23: ABIERTA | D23: MUROS EXTERNO | E23: AREA | F23: 2.41 | G23: =F23*F24 | H23: =SUM(G23:G31) | J23: EJE 4 | K23: NORMAL | L23: MUROS EXTERNO | M23: AREA | N23: 3.62 | O23: =N23*N24 | P23: =SUM(O23:O31)
E24: CANT. | F24: 2 | M24: CANT. | N24: 2
D25: MURO INTERNO | E25: AREA | F25: 1.83 | G25: =F25*F26 | L25: MURO INTERNO | M25: AREA | N25: 2.76 | O25: =N25*N26
E26: CANTIDAD | F26: 2 | M26: CANTIDAD | N26: 2
C27: TAPADO | D27: MURO EXTERNO | E27: AREA | F27: 0 | G27: =F27*F28 | K27: TAPADO | L27: MURO EXTERNO | M27: AREA | N27: 0 | O27: =N27*N28
E28: CANT. | F28: 2 | M28: CANT. | N28: 2
D29: MURO INTERNO | E29: AREA | F29: 0 | G29: =F29*F30+F31 | L29: MURO INTERNO | M29: AREA | N29: 0 | O29: =N29*N30+N31
E30: CANTIDAD | F30: 2 | M30: CANTIDAD | N30: 2
E31: TAPA | F31: 0 | M31: TAPA | N31: 0
B33: LONGITUDES Y AREAS | G33: Sub.TOTAL | H33: TOTAL (m2) | J33: LONGITUDES Y AREAS | O33: Sub.TOTAL | P33: TOTAL (m2)
B34: EJE 5 | C34: NORMAL | D34: MUROS EXTERNO | E34: AREA | F34: 18.53 | G34: =F34*F35 | H34: =SUM(G34:G42) | J34: EJE 6 | K34: NORMAL | L34: MUROS EXTERNO | M34: AREA | N34: 63.19 | O34: =N34*N35 | P34: =SUM(O34:O42)
E35: CANT. | F35: 2 | M35: CANT. | N35: 2
D36: MURO INTERNO | E36: AREA | F36: 14.78 | G36: =F36*F37 | L36: MURO INTERNO | M36: AREA | N36: 53.74 | O36: =N36*N37
E37: CANTIDAD | F37: 2 | M37: CANTIDAD | N37: 2
C38: TAPADO | D38: MURO EXTERNO | E38: AREA | F38: 3.43 | G38: =F38*F39 | K38: TAPADO | L38: MURO EXTERNO | M38: AREA | N38: 21.16 | O38: =N38*N39
E39: CANT. | F39: 2 | M39: CANT. | N39: 2
D40: MURO INTERNO | E40: AREA | F40: 2.3 | G40: =F40*F41+F42 | L40: MURO INTERNO | M40: AREA | N40: 16 | O40: =N40*N41+N42
E41: CANTIDAD | F41: 2 | M41: CANTIDAD | N41: 2
E42: TAPA | F42: =5.7*0.4 | M42: TAPA | N42: =25.9*0.4
B44: LONGITUDES Y AREAS | G44: Sub.TOTAL | H44: TOTAL (m2) | J44: LONGITUDES Y AREAS | O44: Sub.TOTAL | P44: TOTAL (m2)
B45: EJE 7 | C45: NORMAL | D45: MUROS EXTERNO | E45: AREA | F45: 68.6 | G45: =F45*F46 | H45: =SUM(G45:G53) | J45: EJE 8 | K45: NORMAL | L45: MUROS EXTERNO | M45: AREA | N45: 0 | O45: =N45*N46 | P45: =SUM(O45:O53)
E46: CANT. | F46: 2 | M46: CANT. | N46: 2
D47: MURO INTERNO | E47: AREA | F47: 58.46 | G47: =F47*F48 | L47: MURO INTERNO | M47: AREA | N47: 0 | O47: =N47*N48
E48: CANTIDAD | F48: 2 | M48: CANTIDAD | N48: 2
C49: TAPADO | D49: MURO EXTERNO | E49: AREA | F49: 20.91 | G49: =F49*F50 | K49: TAPADO | L49: MURO EXTERNO | M49: AREA | N49: 4.26 | O49: =N49*N50
E50: CANT. | F50: 2 | M50: CANT. | N50: 2
D51: MURO INTERNO | E51: AREA | F51: 16 | G51: =F51*F52+F53 | L51: MURO INTERNO | M51: AREA | N51: 2.62 | O51: =N51*N52+N53
E52: CANTIDAD | F52: 2 | M52: CANTIDAD | N52: 2
E53: TAPA | F53: =24.4*0.4 | M53: TAPA | N53: =8.2*0.4
B56: LONGITUDES Y AREAS | G56: Sub.TOTAL | H56: TOTAL (m2) | J56: LONGITUDES Y AREAS | O56: Sub.TOTAL | P56: TOTAL (m2)
B57: EJE 9 | C57: NORMAL | D57: MUROS EXTERNO | E57: AREA | F57: 0 | G57: =F57*F58 | H57: =SUM(G57:G65) | J57: EJE 10 | K57: NORMAL | L57: MUROS EXTERNO | M57: AREA | N57: 7.04 | O57: =N57*N58 | P57: =SUM(O57:O65)
E58: CANT. | F58: 2 | M58: CANT. | N58: 2
D59: MURO INTERNO | E59: AREA | F59: 0 | G59: =F59*F60 | L59: MURO INTERNO | M59: AREA | N59: 5.44 | O59: =N59*N60
E60: CANTIDAD | F60: 2 | M60: CANTIDAD | N60: 2
C61: TAPADO | D61: MURO EXTERNO | E61: AREA | F61: 3.62 | G61: =F61*F62 | K61: TAPADO | L61: MURO EXTERNO | M61: AREA | N61: 0 | O61: =N61*N62
E62: CANT. | F62: 2 | M62: CANT. | N62: 2
D63: MURO INTERNO | E63: AREA | F63: 2.22 | G63: =F63*F64+F65 | L63: MURO INTERNO | M63: AREA | N63: 0 | O63: =N63*N64+N65
E64: CANTIDAD | F64: 2 | M64: CANTIDAD | N64: 2
E65: TAPA | F65: =7*0.4 | M65: TAPA | N65: 0
B68: LONGITUDES Y AREAS | G68: Sub.TOTAL | H68: TOTAL (m2) | J68: LONGITUDES Y AREAS | O68: Sub.TOTAL | P68: TOTAL (m2)
B69: EJE 11 | C69: NORMAL | D69: MUROS EXTERNO | E69: AREA | F69: 34.95 | G69: =F69*F70 | H69: =SUM(G69:G77) | J69: EJE 12 | K69: NORMAL | L69: MUROS EXTERNO | M69: AREA | N69: 27.87 | O69: =N69*N70 | P69: =SUM(O69:O77)
E70: CANT. | F70: 2 | M70: CANT. | N70: 2
D71: MURO INTERNO | E71: AREA | F71: 28.67 | G71: =F71*F72 | L71: MURO INTERNO | M71: AREA | N71: 22.62 | O71: =N71*N72
E72: CANTIDAD | F72: 2 | M72: CANTIDAD | N72: 2
C73: TAPADO | D73: MURO EXTERNO | E73: AREA | F73: 6.07 | G73: =F73*F74 | K73: TAPADO | L73: MURO EXTERNO | M73: AREA | N73: 42.7 | O73: =N73*N74
E74: CANT. | F74: 2 | M74: CANT. | N74: 2
D75: MURO INTERNO | E75: AREA | F75: 4.33 | G75: =F75*F76+F77 | L75: MURO INTERNO | M75: AREA | N75: 31.37 | O75: =N75*N76+N77
E76: CANTIDAD | F76: 2 | M76: CANTIDAD | N76: 2
E77: TAPA | F77: =6.46*0.4 | M77: TAPA | N77: =56.64*0.4

Sheet METRADO MONTANTES
B2: CALCULO DE MONTANTES POR EDIFICACION - DRENAJE PLUVIAL
B3: ENTIDAD | C3: =+RESUMEN!B4
B4: PROYECTO | C4: =+RESUMEN!B5
B5: UBICACIÓN | C5: =+RESUMEN!B6
B6: FECHA | C6: =+RESUMEN!B7
C9: MONTANTES | D9: LONG. TUBERIA PVC 4" | G9: CODO PVC 90° 4" | J9: ABRAZADERA 4" | M9: COLGADOR 4" | P9: CODO PVC 45° 4"
D10: VECES | E10: LONGITUD | F10: TOTAL (m) | G10: CANTIDAD | H10: VECES | I10: TOTAL (und) | J10: CANTIDAD | K10: VECES | L10: TOTAL (und) | M10: CANTIDAD | N10: VECES | O10: TOTAL (und) | P10: CANTIDAD | Q10: VECES | R10: TOTAL (und)
B11: EDIFICACION 01
B12: Lado A | F12: =E12*D12 | I12: =H12*G12 | L12: =K12*J12 | O12: =N12*M12 | R12: =Q12*P12
B13: Lado B | F13: =E13*D13 | I13: =H13*G13 | L13: =K13*J13 | O13: =N13*M13 | R13: =Q13*P13
B14: EDIFICACION 02
B15: Lado A | F15: =E15*D15 | I15: =H15*G15 | L15: =K15*J15 | O15: =N15*M15 | R15: =Q15*P15
B16: Lado B | F16: =E16*D16 | I16: =H16*G16 | L16: =K16*J16 | O16: =N16*M16 | R16: =Q16*P16
B17: EDIFICACION 03
B18: Lado A | F18: =E18*D18 | I18: =H18*G18 | L18: =K18*J18 | O18: =N18*M18 | R18: =Q18*P18
B19: Lado B | F19: =E19*D19 | I19: =H19*G19 | L19: =K19*J19 | O19: =N19*M19 | R19: =Q19*P19
B20: EDIFICACION 04
B21: Lado A | F21: =E21*D21 | I21: =H21*G21 | L21: =K21*J21 | O21: =N21*M21 | R21: =Q21*P21
B22: Lado B | F22: =E22*D22 | I22: =H22*G22 | L22: =K22*J22 | O22: =N22*M22 | R22: =Q22*P22
B23: EDIFICACION 05
B24: Lado A | F24: =E24*D24 | I24: =H24*G24 | L24: =K24*J24 | O24: =N24*M24 | R24: =Q24*P24
B25: Lado B | F25: =E25*D25 | I25: =H25*G25 | L25: =K25*J25 | O25: =N25*M25 | R25: =Q25*P25
B26: EDIFICACION 06
B27: Lado A | F27: =E27*D27 | I27: =H27*G27 | L27: =K27*J27 | O27: =N27*M27 | R27: =Q27*P27
B28: Lado B | F28: =E28*D28 | I28: =H28*G28 | L28: =K28*J28 | O28: =N28*M28 | R28: =Q28*P28
B29: EDIFICACION 07
B30: Lado A | F30: =E30*D30 | I30: =H30*G30 | L30: =K30*J30 | O30: =N30*M30 | R30: =Q30*P30
B31: Lado B | F31: =E31*D31 | I31: =H31*G31 | L31: =K31*J31 | O31: =N31*M31 | R31: =Q31*P31
B32: EDIFICACION 08
B33: Lado A | F33: =E33*D33 | I33: =H33*G33 | L33: =K33*J33 | O33: =N33*M33 | R33: =Q33*P33
B34: Lado B | F34: =E34*D34 | I34: =H34*G34 | L34: =K34*J34 | O34: =N34*M34 | R34: =Q34*P34
B35: EDIFICACION 09
B36: Lado A | F36: =E36*D36 | I36: =H36*G36 | L36: =K36*J36 | O36: =N36*M36 | R36: =Q36*P36
B37: Lado B | F37: =E37*D37 | I37: =H37*G37 | L37: =K37*J37 | O37: =N37*M37 | R37: =Q37*P37
B38: EDIFICACION 10
B39: Lado A | F39: =E39*D39 | I39: =H39*G39 | L39: =K39*J39 | O39: =N39*M39 | R39: =Q39*P39
B40: Lado B | F40: =E40*D40 | I40: =H40*G40 | L40: =K40*J40 | O40: =N40*M40 | R40: =Q40*P40
B41: EDIFICACION 11
B42: Lado A | F42: =E42*D42 | I42: =H42*G42 | L42: =K42*J42 | O42: =N42*M42 | R42: =Q42*P42
B43: Lado B | F43: =E43*D43 | I43: =H43*G43 | L43: =K43*J43 | O43: =N43*M43 | R43: =Q43*P43
B44: EDIFICACION 12
B45: Lado A | F45: =E45*D45 | I45: =H45*G45 | L45: =K45*J45 | O45: =N45*M45 | R45: =Q45*P45
B46: Lado B | F46: =E46*D46 | I46: =H46*G46 | L46: =K46*J46 | O46: =N46*M46 | R46: =Q46*P46
B47: EDIFICACION 13
B48: Lado A | F48: =E48*D48 | I48: =H48*G48 | L48: =K48*J48 | O48: =N48*M48 | R48: =Q48*P48
B49: Lado B | F49: =E49*D49 | I49: =H49*G49 | L49: =K49*J49 | O49: =N49*M49 | R49: =Q49*P49
B50: EDIFICACION 14
B51: Lado A | F51: =E51*D51 | I51: =H51*G51 | L51: =K51*J51 | O51: =N51*M51 | R51: =Q51*P51
B52: Lado B | F52: =E52*D52 | I52: =H52*G52 | L52: =K52*J52 | O52: =N52*M52 | R52: =Q52*P52
B53: OBRA EXTERIOR 01 | F53: =E53*D53 | I53: =H53*G53 | L53: =K53*J53 | O53: =N53*M53 | R53: =Q53*P53
B54: OBRA EXTERIOR03 | F54: =E54*D54 | I54: =H54*G54 | L54: =K54*J54 | O54: =N54*M54 | R54: =Q54*P54
B55: OBRA EXTERIOR 05 | F55: =E55*D55 | I55: =H55*G55 | L55: =K55*J55 | O55: =N55*M55 | R55: =Q55*P55
B56: OBRA EXTERIOR 06 | F56: =E56*D56 | I56: =H56*G56 | L56: =K56*J56 | O56: =N56*M56 | R56: =Q56*P56
C57: =SUM(C11:C56) | F57: =SUM(F11:F56) | I57: =SUM(I11:I56) | L57: =SUM(L11:L56) | O57: =SUM(O11:O56) | R57: =SUM(R11:R56)

Sheet METRADO  EN PISO (SUMIDERO)
A1: PLANILLA DE METRADOS - RED DE DRENAJE EN PISO Y SUMIDEROS
A2: ENTIDAD | B2: =+RESUMEN!B4
A3: PROYECTO | B3: =+RESUMEN!B5
A4: UBICACIÓN | B4: =+RESUMEN!B6
A5: FECHA | B5: =+RESUMEN!B7
A7: SECTOR | B7: TUBERÍA 4" PVC-U Desagüe Clase Pesada (m) | C7: SUMIDERO DE 4" (und) | D7: CODO 90° x 4" (und) | E7: CODO 45° x 4" (und) | F7: TEE° x 4" (und) | G7: OBSERVACIÓN
A8: SECTOR 01 | B8: 26.52 | C8: 6 | D8: 4 | E8: 0 | F8: 2 | G8: Según sector
A9: SECTOR 02 | B9: 27.18 | C9: 8 | D9: 4 | E9: 0 | F9: 2 | G9: Según sector
A10: SECTOR 03 | B10: 32 | C10: 6 | D10: 6 | E10: 0 | F10: 0 | G10: Según sector
A11: SECTOR 04 | B11: 26.56 | C11: 10 | D11: 10 | E11: 0 | F11: 0 | G11: Según sector
A12: TOTAL | B12: =SUM(B8:B11) | C12: =SUM(C8:C11) | D12: =SUM(D8:D11) | E12: =SUM(E8:E11) | F12: =SUM(F8:F11)

Sheet METRADO ACERO
A2: METRADO DE ACERO EN CUNETAS - DRENAJE PLUVIAL
A3: ENTIDAD | B3: =+RESUMEN!B4
A4: PROYECTO | B4: =+RESUMEN!B5
A5: UBICACIÓN | B5: =+RESUMEN!B6
A6: FECHA | B6: =+RESUMEN!B7
A8: METRADO DETALLADO POR EJE Y POR TRAMO
A9: IDENTIFICACIÓN Y GEOMETRÍA | H9: ACERO LONGITUDINAL DEL CUERPO U | P9: ACERO TRANSVERSAL DEL CUERPO U | X9: ACERO TRANSVERSAL DE LA TAPA (SOLO CUNETA TAPADA) | AG9: RESULTADO
A10: N° | B10: EJE | C10: TRAMO | D10: TIPO DE CUNETA | E10: SEC. INI | F10: SEC. FIN | G10: LONGITUD TRAMO (m) | H10: Ø CUERPO | I10: FACTOR CUERPO (kg/m) | J10: SEP. LONG. (m) | K10: BARRAS LONG. INI | L10: BARRAS LONG. FIN | M10: BARRAS PROM. | N10: LONG. ACERO LONG. (m) | O10: KG LONG. | P10: SEP. TRANSV. U (m) | Q10: DES. TRANSV. U INI (m) | R10: DES. TRANSV. U FIN (m) | S10: DES. PROM. U (m) | T10: CANT. TRANSV. U | U10: LONG. ACERO TRANSV. U (m) | V10: KG TRANSV. U | W10: TOTAL KG CUERPO U | X10: Ø TAPA | Y10: FACTOR TAPA (kg/m) | Z10: SEP. TRANSV. TAPA (m) | AA10: LONG. BARRA TAPA INI (m) | AB10: LONG. BARRA TAPA FIN (m) | AC10: LONG. PROM. TAPA (m) | AD10: CANT. BARRAS TAPA | AE10: LONG. ACERO TAPA (m) | AF10: KG ACERO TAPA | AG10: TOTAL KG TRAMO
A11: 1 | B11: EJE 01 | C11: TRAMO 01 | D11: ABIERTA | E11: SEC 02 | F11: SEC 03 | G11: 12 | H11: 3/8" | I11: =IF(H11="","",IFERROR(VLOOKUP(H11,Listas!$A$4:$B$11,2,FALSE),"")) | J11: 0.21 | K11: 7 | L11: 7 | M11: =IF(B11="","",(K11+L11)/2) | N11: =IF(B11="","",G11*M11) | O11: =IF(B11="","",N11*I11) | P11: 0.25 | Q11: 1.42 | R11: 1.5 | S11: =IF(B11="","",(Q11+R11)/2) | T11: =IF(B11="","",IFERROR(IF($X$1="ENTERO (redondeo arriba)",ROUNDUP(G11/P11,0)+1,G11/P11+1),0)) | U11: =IF(B11="","",S11*T11) | V11: =IF(B11="","",U11*I11) | W11: =IF(B11="","",O11+V11) | AC11: =IF(B11="","",IF(D11="TAPADA",(AA11+AB11)/2,0)) | AD11: =IF(B11="","",IF(D11="TAPADA",IFERROR(IF($X$1="ENTERO (redondeo arriba)",ROUNDUP(G11/Z11,0)+1,G11/Z11+1),0),0)) | AE11: =IF(B11="","",IF(D11="TAPADA",AC11*AD11,0)) | AF11: =IF(B11="","",IF(D11="TAPADA",AE11*Y11,0)) | AG11: =IF(B11="","",W11+AF11)
A12: 2 | B12: EJE 01 | C12: TRAMO 02 | D12: TAPADA | E12: SEC 03 | F12: SEC 04 | G12: 5.14 | H12: 3/8" | I12: =IF(H12="","",IFERROR(VLOOKUP(H12,Listas!$A$4:$B$11,2,FALSE),"")) | J12: 0.23 | K12: 8 | L12: 8 | M12: =IF(B12="","",(K12+L12)/2) | N12: =IF(B12="","",G12*M12) | O12: =IF(B12="","",N12*I12) | P12: 0.25 | Q12: 1.5 | R12: 1.58 | S12: =IF(B12="","",(Q12+R12)/2) | T12: =IF(B12="","",IFERROR(IF($X$1="ENTERO (redondeo arriba)",ROUNDUP(G12/P12,0)+1,G12/P12+1),0)) | U12: =IF(B12="","",S12*T12) | V12: =IF(B12="","",U12*I12) | W12: =IF(B12="","",O12+V12) | X12: 3/8" | Y12: 0.56 | Z12: 0.25 | AA12: 0.56 | AB12: 0.56 | AC12: =IF(B12="","",IF(D12="TAPADA",(AA12+AB12)/2,0)) | AD12: =IF(B12="","",IF(D12="TAPADA",IFERROR(IF($X$1="ENTERO (redondeo arriba)",ROUNDUP(G12/Z12,0)+1,G12/Z12+1),0),0)) | AE12: =IF(B12="","",IF(D12="TAPADA",AC12*AD12,0)) | AF12: =IF(B12="","",IF(D12="TAPADA",AE12*Y12,0)) | AG12: =IF(B12="","",W12+AF12)
A13: 3 | B13: EJE 02 | C13: TRAMO 01 | D13: ABIERTA | E13: SEC 06 | F13: SEC 07 | G13: 17.5 | H13: 3/8" | I13: =IF(H13="","",IFERROR(VLOOKUP(H13,Listas!$A$4:$B$11,2,FALSE),"")) | J13: 0.23 | K13: 7 | L13: 7 | M13: =IF(B13="","",(K13+L13)/2) | N13: =IF(B13="","",G13*M13) | O13: =IF(B13="","",N13*I13) | P13: 0.25 | Q13: 1.42 | R13: 1.58 | S13: =IF(B13="","",(Q13+R13)/2) | T13: =IF(B13="","",IFERROR(IF($X$1="ENTERO (redondeo arriba)",ROUNDUP(G13/P13,0)+1,G13/P13+1),0)) | U13: =IF(B13="","",S13*T13) | V13: =IF(B13="","",U13*I13) | W13: =IF(B13="","",O13+V13) | AC13: =IF(B13="","",IF(D13="TAPADA",(AA13+AB13)/2,0)) | AD13: =IF(B13="","",IF(D13="TAPADA",IFERROR(IF($X$1="ENTERO (redondeo arriba)",ROUNDUP(G13/Z13,0)+1,G13/Z13+1),0),0)) | AE13: =IF(B13="","",IF(D13="TAPADA",AC13*AD13,0)) | AF13: =IF(B13="","",IF(D13="TAPADA",AE13*Y13,0)) | AG13: =IF(B13="","",W13+AF13)
A14: 4 | B14: EJE 02 | C14: TRAMO 02 | D14: TAPADA | E14: SEC 07 | F14: SEC 08 | G14: 10.2 | H14: 3/8" | I14: =IF(H14="","",IFERROR(VLOOKUP(H14,Listas!$A$4:$B$11,2,FALSE),"")) | J14: 0.22 | K14: 8 | L14: 10 | M14: =IF(B14="","",(K14+L14)/2) | N14: =IF(B14="","",G14*M14) | O14: =IF(B14="","",N14*I14) | P14: 0.25 | Q14: 1.58 | R14: 1.66 | S14: =IF(B14="","",(Q14+R14)/2) | T14: =IF(B14="","",IFERROR(IF($X$1="ENTERO (redondeo arriba)",ROUNDUP(G14/P14,0)+1,G14/P14+1),0)) | U14: =IF(B14="","",S14*T14) | V14: =IF(B14="","",U14*I14) | W14: =IF(B14="","",O14+V14) | X14: 3/8" | Y14: 0.56 | Z14: 0.25 | AA14: 0.56 | AB14: 0.56 | AC14: =IF(B14="","",IF(D14="TAPADA",(AA14+AB14)/2,0)) | AD14: =IF(B14="","",IF(D14="TAPADA",IFERROR(IF($X$1="ENTERO (redondeo arriba)",ROUNDUP(G14/Z14,0)+1,G14/Z14+1),0),0)) | AE14: =IF(B14="","",IF(D14="TAPADA",AC14*AD14,0)) | AF14: =IF(B14="","",IF(D14="TAPADA",AE14*Y14,0)) | AG14: =IF(B14="","",W14+AF14)
A15: 5 | B15: EJE 02 | C15: TRAMO 03 | D15: ABIERTA | E15: SEC 08 | F15: SEC 09 | G15: 31.33 | H15: 3/8" | I15: =IF(H15="","",IFERROR(VLOOKUP(H15,Listas!$A$4:$B$11,2,FALSE),"")) | J15: 0.2 | K15: 9 | L15: 9 | M15: =IF(B15="","",(K15+L15)/2) | N15: =IF(B15="","",G15*M15) | O15: =IF(B15="","",N15*I15) | P15: 0.25 | Q15: 1.66 | R15: 2.02 | S15: =IF(B15="","",(Q15+R15)/2) | T15: =IF(B15="","",IFERROR(IF($X$1="ENTERO (redondeo arriba)",ROUNDUP(G15/P15,0)+1,G15/P15+1),0)) | U15: =IF(B15="","",S15*T15) | V15: =IF(B15="","",U15*I15) | W15: =IF(B15="","",O15+V15) | AC15: =IF(B15="","",IF(D15="TAPADA",(AA15+AB15)/2,0)) | AD15: =IF(B15="","",IF(D15="TAPADA",IFERROR(IF($X$1="ENTERO (redondeo arriba)",ROUNDUP(G15/Z15,0)+1,G15/Z15+1),0),0)) | AE15: =IF(B15="","",IF(D15="TAPADA",AC15*AD15,0)) | AF15: =IF(B15="","",IF(D15="TAPADA",AE15*Y15,0)) | AG15: =IF(B15="","",W15+AF15)
A16: 6 | B16: EJE 02 | C16: TRAMO 04 | D16: TAPADA | E16: SEC 09 | F16: SEC 10 | G16: 8.36 | H16: 3/8" | I16: =IF(H16="","",IFERROR(VLOOKUP(H16,Listas!$A$4:$B$11,2,FALSE),"")) | J16: 0.23 | K16: 10 | L16: 10 | M16: =IF(B16="","",(K16+L16)/2) | N16: =IF(B16="","",G16*M16) | O16: =IF(B16="","",N16*I16) | P16: 0.25 | Q16: 2.02 | R16: 2.08 | S16: =IF(B16="","",(Q16+R16)/2) | T16: =IF(B16="","",IFERROR(IF($X$1="ENTERO (redondeo arriba)",ROUNDUP(G16/P16,0)+1,G16/P16+1),0)) | U16: =IF(B16="","",S16*T16) | V16: =IF(B16="","",U16*I16) | W16: =IF(B16="","",O16+V16) | X16: 3/8" | Y16: 0.56 | Z16: 0.25 | AA16: 0.56 | AB16: 0.56 | AC16: =IF(B16="","",IF(D16="TAPADA",(AA16+AB16)/2,0)) | AD16: =IF(B16="","",IF(D16="TAPADA",IFERROR(IF($X$1="ENTERO (redondeo arriba)",ROUNDUP(G16/Z16,0)+1,G16/Z16+1),0),0)) | AE16: =IF(B16="","",IF(D16="TAPADA",AC16*AD16,0)) | AF16: =IF(B16="","",IF(D16="TAPADA",AE16*Y16,0)) | AG16: =IF(B16="","",W16+AF16)
A17: 7 | B17: EJE 02 | C17: TRAMO 05 | D17: ABIERTA | E17: SEC 10 | F17: SEC 11 | G17: 30.36 | H17: 3/8" | I17: =IF(H17="","",IFERROR(VLOOKUP(H17,Listas!$A$4:$B$11,2,FALSE),"")) | J17: 0.22 | K17: 9 | L17: 11 | M17: =IF(B17="","",(K17+L17)/2) | N17: =IF(B17="","",G17*M17) | O17: =IF(B17="","",N17*I17) | P17: 0.25 | Q17: 2.08 | R17: 2.36 | S17: =IF(B17="","",(Q17+R17)/2) | T17: =IF(B17="","",IFERROR(IF($X$1="ENTERO (redondeo arriba)",ROUNDUP(G17/P17,0)+1,G17/P17+1),0)) | U17: =IF(B17="","",S17*T17) | V17: =IF(B17="","",U17*I17) | W17: =IF(B17="","",O17+V17) | AC17: =IF(B17="","",IF(D17="TAPADA",(AA17+AB17)/2,0)) | AD17: =IF(B17="","",IF(D17="TAPADA",IFERROR(IF($X$1="ENTERO (redondeo arriba)",ROUNDUP(G17/Z17,0)+1,G17/Z17+1),0),0)) | AE17: =IF(B17="","",IF(D17="TAPADA",AC17*AD17,0)) | AF17: =IF(B17="","",IF(D17="TAPADA",AE17*Y17,0)) | AG17: =IF(B17="","",W17+AF17)
A18: 8 | B18: EJE 02 | C18: TRAMO 06 | D18: TAPADA | E18: SEC 11 | F18: SEC 12 | G18: 2.25 | H18: 3/8" | I18: =IF(H18="","",IFERROR(VLOOKUP(H18,Listas!$A$4:$B$11,2,FALSE),"")) | J18: 0.22 | K18: 12 | L18: 12 | M18: =IF(B18="","",(K18+L18)/2) | N18: =IF(B18="","",G18*M18) | O18: =IF(B18="","",N18*I18) | P18: 0.25 | Q18: 2.36 | R18: 2.42 | S18: =IF(B18="","",(Q18+R18)/2) | T18: =IF(B18="","",IFERROR(IF($X$1="ENTERO (redondeo arriba)",ROUNDUP(G18/P18,0)+1,G18/P18+1),0)) | U18: =IF(B18="","",S18*T18) | V18: =IF(B18="","",U18*I18) | W18: =IF(B18="","",O18+V18) | X18: 3/8" | Y18: 0.56 | Z18: 0.25 | AA18: 0.56 | AB18: 0.56 | AC18: =IF(B18="","",IF(D18="TAPADA",(AA18+AB18)/2,0)) | AD18: =IF(B18="","",IF(D18="TAPADA",IFERROR(IF($X$1="ENTERO (redondeo arriba)",ROUNDUP(G18/Z18,0)+1,G18/Z18+1),0),0)) | AE18: =IF(B18="","",IF(D18="TAPADA",AC18*AD18,0)) | AF18: =IF(B18="","",IF(D18="TAPADA",AE18*Y18,0)) | AG18: =IF(B18="","",W18+AF18)
A19: 9 | B19: EJE 02 | C19: TRAMO 07 | D19: TAPADA | E19: SEC 13 | F19: SEC 14 | G19: 10.85 | H19: 3/8" | I19: =IF(H19="","",IFERROR(VLOOKUP(H19,Listas!$A$4:$B$11,2,FALSE),"")) | J19: 0.21 | K19: 12 | L19: 12 | M19: =IF(B19="","",(K19+L19)/2) | N19: =IF(B19="","",G19*M19) | O19: =IF(B19="","",N19*I19) | P19: 0.25 | Q19: 2.32 | R19: 2.42 | S19: =IF(B19="","",(Q19+R19)/2) | T19: =IF(B19="","",IFERROR(IF($X$1="ENTERO (redondeo arriba)",ROUNDUP(G19/P19,0)+1,G19/P19+1),0)) | U19: =IF(B19="","",S19*T19) | V19: =IF(B19="","",U19*I19) | W19: =IF(B19="","",O19+V19) | X19: 3/8" | Y19: 0.56 | Z19: 0.25 | AA19: 0.56 | AB19: 0.56 | AC19: =IF(B19="","",IF(D19="TAPADA",(AA19+AB19)/2,0)) | AD19: =IF(B19="","",IF(D19="TAPADA",IFERROR(IF($X$1="ENTERO (redondeo arriba)",ROUNDUP(G19/Z19,0)+1,G19/Z19+1),0),0)) | AE19: =IF(B19="","",IF(D19="TAPADA",AC19*AD19,0)) | AF19: =IF(B19="","",IF(D19="TAPADA",AE19*Y19,0)) | AG19: =IF(B19="","",W19+AF19)
A20: 10 | B20: EJE 05 | C20: TRAMO 01 | D20: ABIERTA | E20: SEC 20 | F20: SEC 21 | G20: 17.53 | H20: 3/8" | I20: =IF(H20="","",IFERROR(VLOOKUP(H20,Listas!$A$4:$B$11,2,FALSE),"")) | J20: 0.22 | K20: 7 | L20: 7 | M20: =IF(B20="","",(K20+L20)/2) | N20: =IF(B20="","",G20*M20) | O20: =IF(B20="","",N20*I20) | P20: 0.25 | Q20: 1.42 | R20: 1.58 | S20: =IF(B20="","",(Q20+R20)/2) | T20: =IF(B20="","",IFERROR(IF($X$1="ENTERO (redondeo arriba)",ROUNDUP(G20/P20,0)+1,G20/P20+1),0)) | U20: =IF(B20="","",S20*T20) | V20: =IF(B20="","",U20*I20) | W20: =IF(B20="","",O20+V20) | AC20: =IF(B20="","",IF(D20="TAPADA",(AA20+AB20)/2,0)) | AD20: =IF(B20="","",IF(D20="TAPADA",IFERROR(IF($X$1="ENTERO (redondeo arriba)",ROUNDUP(G20/Z20,0)+1,G20/Z20+1),0),0)) | AE20: =IF(B20="","",IF(D20="TAPADA",AC20*AD20,0)) | AF20: =IF(B20="","",IF(D20="TAPADA",AE20*Y20,0)) | AG20: =IF(B20="","",W20+AF20)
A21: 11 | B21: EJE 05 | C21: TRAMO 02 | D21: TAPADA | E21: SEC 21 | F21: SEC 22 | G21: 5.7 | H21: 3/8" | I21: =IF(H21="","",IFERROR(VLOOKUP(H21,Listas!$A$4:$B$11,2,FALSE),"")) | J21: 0.21 | K21: 8 | L21: 10 | M21: =IF(B21="","",(K21+L21)/2) | N21: =IF(B21="","",G21*M21) | O21: =IF(B21="","",N21*I21) | P21: 0.25 | Q21: 1.58 | R21: 1.62 | S21: =IF(B21="","",(Q21+R21)/2) | T21: =IF(B21="","",IFERROR(IF($X$1="ENTERO (redondeo arriba)",ROUNDUP(G21/P21,0)+1,G21/P21+1),0)) | U21: =IF(B21="","",S21*T21) | V21: =IF(B21="","",U21*I21) | W21: =IF(B21="","",O21+V21) | X21: 3/8" | Y21: 0.56 | Z21: 0.25 | AA21: 0.56 | AB21: 0.56 | AC21: =IF(B21="","",IF(D21="TAPADA",(AA21+AB21)/2,0)) | AD21: =IF(B21="","",IF(D21="TAPADA",IFERROR(IF($X$1="ENTERO (redondeo arriba)",ROUNDUP(G21/Z21,0)+1,G21/Z21+1),0),0)) | AE21: =IF(B21="","",IF(D21="TAPADA",AC21*AD21,0)) | AF21: =IF(B21="","",IF(D21="TAPADA",AE21*Y21,0)) | AG21: =IF(B21="","",W21+AF21)
A22: 12 | B22: EJE 06 | C22: TRAMO 01 | D22: ABIERTA | E22: SEC 24 | F22: SEC 25 | G22: 17.53 | H22: 3/8" | I22: =IF(H22="","",IFERROR(VLOOKUP(H22,Listas!$A$4:$B$11,2,FALSE),"")) | J22: 0.22 | K22: 7 | L22: 7 | M22: =IF(B22="","",(K22+L22)/2) | N22: =IF(B22="","",G22*M22) | O22: =IF(B22="","",N22*I22) | P22: 0.25 | Q22: 1.42 | R22: 1.58 | S22: =IF(B22="","",(Q22+R22)/2) | T22: =IF(B22="","",IFERROR(IF($X$1="ENTERO (redondeo arriba)",ROUNDUP(G22/P22,0)+1,G22/P22+1),0)) | U22: =IF(B22="","",S22*T22) | V22: =IF(B22="","",U22*I22) | W22: =IF(B22="","",O22+V22) | AC22: =IF(B22="","",IF(D22="TAPADA",(AA22+AB22)/2,0)) | AD22: =IF(B22="","",IF(D22="TAPADA",IFERROR(IF($X$1="ENTERO (redondeo arriba)",ROUNDUP(G22/Z22,0)+1,G22/Z22+1),0),0)) | AE22: =IF(B22="","",IF(D22="TAPADA",AC22*AD22,0)) | AF22: =IF(B22="","",IF(D22="TAPADA",AE22*Y22,0)) | AG22: =IF(B22="","",W22+AF22)
A23: 13 | B23: EJE 06 | C23: TRAMO 02 | D23: TAPADA | E23: SEC 25 | F23: SEC 26 | G23: 10.9 | H23: 3/8" | I23: =IF(H23="","",IFERROR(VLOOKUP(H23,Listas!$A$4:$B$11,2,FALSE),"")) | J23: 0.22 | K23: 8 | L23: 10 | M23: =IF(B23="","",(K23+L23)/2) | N23: =IF(B23="","",G23*M23) | O23: =IF(B23="","",N23*I23) | P23: 0.25 | Q23: 1.58 | R23: 1.7 | S23: =IF(B23="","",(Q23+R23)/2) | T23: =IF(B23="","",IFERROR(IF($X$1="ENTERO (redondeo arriba)",ROUNDUP(G23/P23,0)+1,G23/P23+1),0)) | U23: =IF(B23="","",S23*T23) | V23: =IF(B23="","",U23*I23) | W23: =IF(B23="","",O23+V23) | X23: 3/8" | Y23: 0.56 | Z23: 0.25 | AA23: 0.56 | AB23: 0.56 | AC23: =IF(B23="","",IF(D23="TAPADA",(AA23+AB23)/2,0)) | AD23: =IF(B23="","",IF(D23="TAPADA",IFERROR(IF($X$1="ENTERO (redondeo arriba)",ROUNDUP(G23/Z23,0)+1,G23/Z23+1),0),0)) | AE23: =IF(B23="","",IF(D23="TAPADA",AC23*AD23,0)) | AF23: =IF(B23="","",IF(D23="TAPADA",AE23*Y23,0)) | AG23: =IF(B23="","",W23+AF23)
A24: 14 | B24: EJE 06 | C24: TRAMO 03 | D24: ABIERTA | E24: SEC 26 | F24: SEC 27 | G24: 56.93 | H24: 3/8" | I24: =IF(H24="","",IFERROR(VLOOKUP(H24,Listas!$A$4:$B$11,2,FALSE),"")) | J24: 0.2 | K24: 9 | L24: 11 | M24: =IF(B24="","",(K24+L24)/2) | N24: =IF(B24="","",G24*M24) | O24: =IF(B24="","",N24*I24) | P24: 0.25 | Q24: 1.7 | R24: 2.26 | S24: =IF(B24="","",(Q24+R24)/2) | T24: =IF(B24="","",IFERROR(IF($X$1="ENTERO (redondeo arriba)",ROUNDUP(G24/P24,0)+1,G24/P24+1),0)) | U24: =IF(B24="","",S24*T24) | V24: =IF(B24="","",U24*I24) | W24: =IF(B24="","",O24+V24) | AC24: =IF(B24="","",IF(D24="TAPADA",(AA24+AB24)/2,0)) | AD24: =IF(B24="","",IF(D24="TAPADA",IFERROR(IF($X$1="ENTERO (redondeo arriba)",ROUNDUP(G24/Z24,0)+1,G24/Z24+1),0),0)) | AE24: =IF(B24="","",IF(D24="TAPADA",AC24*AD24,0)) | AF24: =IF(B24="","",IF(D24="TAPADA",AE24*Y24,0)) | AG24: =IF(B24="","",W24+AF24)
A25: 15 | B25: EJE 06 | C25: TRAMO 04 | D25: TAPADA | E25: SEC 27 | F25: SEC 28 | G25: 15 | H25: 3/8" | I25: =IF(H25="","",IFERROR(VLOOKUP(H25,Listas!$A$4:$B$11,2,FALSE),"")) | J25: 0.21 | K25: 12 | L25: 12 | M25: =IF(B25="","",(K25+L25)/2) | N25: =IF(B25="","",G25*M25) | O25: =IF(B25="","",N25*I25) | P25: 0.25 | Q25: 2.26 | R25: 2.42 | S25: =IF(B25="","",(Q25+R25)/2) | T25: =IF(B25="","",IFERROR(IF($X$1="ENTERO (redondeo arriba)",ROUNDUP(G25/P25,0)+1,G25/P25+1),0)) | U25: =IF(B25="","",S25*T25) | V25: =IF(B25="","",U25*I25) | W25: =IF(B25="","",O25+V25) | X25: 3/8" | Y25: 0.56 | Z25: 0.25 | AA25: 0.56 | AB25: 0.56 | AC25: =IF(B25="","",IF(D25="TAPADA",(AA25+AB25)/2,0)) | AD25: =IF(B25="","",IF(D25="TAPADA",IFERROR(IF($X$1="ENTERO (redondeo arriba)",ROUNDUP(G25/Z25,0)+1,G25/Z25+1),0),0)) | AE25: =IF(B25="","",IF(D25="TAPADA",AC25*AD25,0)) | AF25: =IF(B25="","",IF(D25="TAPADA",AE25*Y25,0)) | AG25: =IF(B25="","",W25+AF25)
A26: 16 | B26: EJE 07 | C26: TRAMO 01 | D26: ABIERTA | E26: SEC 30 | F26: SEC 31 | G26: 17.53 | H26: 3/8" | I26: =IF(H26="","",IFERROR(VLOOKUP(H26,Listas!$A$4:$B$11,2,FALSE),"")) | J26: 0.22 | K26: 7 | L26: 7 | M26: =IF(B26="","",(K26+L26)/2) | N26: =IF(B26="","",G26*M26) | O26: =IF(B26="","",N26*I26) | P26: 0.25 | Q26: 1.42 | R26: 1.58 | S26: =IF(B26="","",(Q26+R26)/2) | T26: =IF(B26="","",IFERROR(IF($X$1="ENTERO (redondeo arriba)",ROUNDUP(G26/P26,0)+1,G26/P26+1),0)) | U26: =IF(B26="","",S26*T26) | V26: =IF(B26="","",U26*I26) | W26: =IF(B26="","",O26+V26) | AC26: =IF(B26="","",IF(D26="TAPADA",(AA26+AB26)/2,0)) | AD26: =IF(B26="","",IF(D26="TAPADA",IFERROR(IF($X$1="ENTERO (redondeo arriba)",ROUNDUP(G26/Z26,0)+1,G26/Z26+1),0),0)) | AE26: =IF(B26="","",IF(D26="TAPADA",AC26*AD26,0)) | AF26: =IF(B26="","",IF(D26="TAPADA",AE26*Y26,0)) | AG26: =IF(B26="","",W26+AF26)
A27: 17 | B27: EJE 07 | C27: TRAMO 02 | D27: TAPADA | E27: SEC 31 | F27: SEC 32 | G27: 7.66 | H27: 3/8" | I27: =IF(H27="","",IFERROR(VLOOKUP(H27,Listas!$A$4:$B$11,2,FALSE),"")) | J27: 0.22 | K27: 8 | L27: 10 | M27: =IF(B27="","",(K27+L27)/2) | N27: =IF(B27="","",G27*M27) | O27: =IF(B27="","",N27*I27) | P27: 0.25 | Q27: 1.58 | R27: 1.66 | S27: =IF(B27="","",(Q27+R27)/2) | T27: =IF(B27="","",IFERROR(IF($X$1="ENTERO (redondeo arriba)",ROUNDUP(G27/P27,0)+1,G27/P27+1),0)) | U27: =IF(B27="","",S27*T27) | V27: =IF(B27="","",U27*I27) | W27: =IF(B27="","",O27+V27) | X27: 3/8" | Y27: 0.56 | Z27: 0.25 | AA27: 0.56 | AB27: 0.56 | AC27: =IF(B27="","",IF(D27="TAPADA",(AA27+AB27)/2,0)) | AD27: =IF(B27="","",IF(D27="TAPADA",IFERROR(IF($X$1="ENTERO (redondeo arriba)",ROUNDUP(G27/Z27,0)+1,G27/Z27+1),0),0)) | AE27: =IF(B27="","",IF(D27="TAPADA",AC27*AD27,0)) | AF27: =IF(B27="","",IF(D27="TAPADA",AE27*Y27,0)) | AG27: =IF(B27="","",W27+AF27)
A28: 18 | B28: EJE 07 | C28: TRAMO 03 | D28: ABIERTA | E28: SEC 32 | F28: SEC 33 | G28: 63.75 | H28: 3/8" | I28: =IF(H28="","",IFERROR(VLOOKUP(H28,Listas!$A$4:$B$11,2,FALSE),"")) | J28: 0.19 | K28: 9 | L28: 11 | M28: =IF(B28="","",(K28+L28)/2) | N28: =IF(B28="","",G28*M28) | O28: =IF(B28="","",N28*I28) | P28: 0.25 | Q28: 1.66 | R28: 2.32 | S28: =IF(B28="","",(Q28+R28)/2) | T28: =IF(B28="","",IFERROR(IF($X$1="ENTERO (redondeo arriba)",ROUNDUP(G28/P28,0)+1,G28/P28+1),0)) | U28: =IF(B28="","",S28*T28) | V28: =IF(B28="","",U28*I28) | W28: =IF(B28="","",O28+V28) | AC28: =IF(B28="","",IF(D28="TAPADA",(AA28+AB28)/2,0)) | AD28: =IF(B28="","",IF(D28="TAPADA",IFERROR(IF($X$1="ENTERO (redondeo arriba)",ROUNDUP(G28/Z28,0)+1,G28/Z28+1),0),0)) | AE28: =IF(B28="","",IF(D28="TAPADA",AC28*AD28,0)) | AF28: =IF(B28="","",IF(D28="TAPADA",AE28*Y28,0)) | AG28: =IF(B28="","",W28+AF28)
A29: 19 | B29: EJE 07 | C29: TRAMO 04 | D29: TAPADA | E29: SEC 33 | F29: SEC 34 | G29: 11.47 | H29: 3/8" | I29: =IF(H29="","",IFERROR(VLOOKUP(H29,Listas!$A$4:$B$11,2,FALSE),"")) | J29: 0.21 | K29: 12 | L29: 12 | M29: =IF(B29="","",(K29+L29)/2) | N29: =IF(B29="","",G29*M29) | O29: =IF(B29="","",N29*I29) | P29: 0.25 | Q29: 2.32 | R29: 2.42 | S29: =IF(B29="","",(Q29+R29)/2) | T29: =IF(B29="","",IFERROR(IF($X$1="ENTERO (redondeo arriba)",ROUNDUP(G29/P29,0)+1,G29/P29+1),0)) | U29: =IF(B29="","",S29*T29) | V29: =IF(B29="","",U29*I29) | W29: =IF(B29="","",O29+V29) | X29: 3/8" | Y29: 0.56 | Z29: 0.25 | AA29: 0.56 | AB29: 0.56 | AC29: =IF(B29="","",IF(D29="TAPADA",(AA29+AB29)/2,0)) | AD29: =IF(B29="","",IF(D29="TAPADA",IFERROR(IF($X$1="ENTERO (redondeo arriba)",ROUNDUP(G29/Z29,0)+1,G29/Z29+1),0),0)) | AE29: =IF(B29="","",IF(D29="TAPADA",AC29*AD29,0)) | AF29: =IF(B29="","",IF(D29="TAPADA",AE29*Y29,0)) | AG29: =IF(B29="","",W29+AF29)
A30: 20 | B30: EJE 07 | C30: TRAMO 05 | D30: TAPADA | E30: SEC 35 | F30: SEC 36 | G30: 5.17 | H30: 3/8" | I30: =IF(H30="","",IFERROR(VLOOKUP(H30,Listas!$A$4:$B$11,2,FALSE),"")) | J30: 0.21 | K30: 12 | L30: 12 | M30: =IF(B30="","",(K30+L30)/2) | N30: =IF(B30="","",G30*M30) | O30: =IF(B30="","",N30*I30) | P30: 0.25 | Q30: 2.32 | R30: 2.36 | S30: =IF(B30="","",(Q30+R30)/2) | T30: =IF(B30="","",IFERROR(IF($X$1="ENTERO (redondeo arriba)",ROUNDUP(G30/P30,0)+1,G30/P30+1),0)) | U30: =IF(B30="","",S30*T30) | V30: =IF(B30="","",U30*I30) | W30: =IF(B30="","",O30+V30) | X30: 3/8" | Y30: 0.56 | Z30: 0.25 | AA30: 0.56 | AB30: 0.56 | AC30: =IF(B30="","",IF(D30="TAPADA",(AA30+AB30)/2,0)) | AD30: =IF(B30="","",IF(D30="TAPADA",IFERROR(IF($X$1="ENTERO (redondeo arriba)",ROUNDUP(G30/Z30,0)+1,G30/Z30+1),0),0)) | AE30: =IF(B30="","",IF(D30="TAPADA",AC30*AD30,0)) | AF30: =IF(B30="","",IF(D30="TAPADA",AE30*Y30,0)) | AG30: =IF(B30="","",W30+AF30)
A31: 21 | B31: EJE 08 | C31: TRAMO 01 | D31: TAPADA | E31: SEC 37 | F31: SEC 38 | G31: 8.2 | H31: 3/8" | I31: =IF(H31="","",IFERROR(VLOOKUP(H31,Listas!$A$4:$B$11,2,FALSE),"")) | J31: 0.21 | K31: 8 | L31: 8 | M31: =IF(B31="","",(K31+L31)/2) | N31: =IF(B31="","",G31*M31) | O31: =IF(B31="","",N31*I31) | P31: 0.25 | Q31: 1.42 | R31: 1.48 | S31: =IF(B31="","",(Q31+R31)/2) | T31: =IF(B31="","",IFERROR(IF($X$1="ENTERO (redondeo arriba)",ROUNDUP(G31/P31,0)+1,G31/P31+1),0)) | U31: =IF(B31="","",S31*T31) | V31: =IF(B31="","",U31*I31) | W31: =IF(B31="","",O31+V31) | X31: 3/8" | Y31: 0.56 | Z31: 0.25 | AA31: 0.56 | AB31: 0.56 | AC31: =IF(B31="","",IF(D31="TAPADA",(AA31+AB31)/2,0)) | AD31: =IF(B31="","",IF(D31="TAPADA",IFERROR(IF($X$1="ENTERO (redondeo arriba)",ROUNDUP(G31/Z31,0)+1,G31/Z31+1),0),0)) | AE31: =IF(B31="","",IF(D31="TAPADA",AC31*AD31,0)) | AF31: =IF(B31="","",IF(D31="TAPADA",AE31*Y31,0)) | AG31: =IF(B31="","",W31+AF31)
A32: 22 | B32: EJE 09 | C32: TRAMO 01 | D32: TAPADA | E32: SEC 39 | F32: SEC 40 | G32: 7 | H32: 3/8" | I32: =IF(H32="","",IFERROR(VLOOKUP(H32,Listas!$A$4:$B$11,2,FALSE),"")) | J32: 0.21 | K32: 8 | L32: 8 | M32: =IF(B32="","",(K32+L32)/2) | N32: =IF(B32="","",G32*M32) | O32: =IF(B32="","",N32*I32) | P32: 0.25 | Q32: 1.42 | R32: 1.48 | S32: =IF(B32="","",(Q32+R32)/2) | T32: =IF(B32="","",IFERROR(IF($X$1="ENTERO (redondeo arriba)",ROUNDUP(G32/P32,0)+1,G32/P32+1),0)) | U32: =IF(B32="","",S32*T32) | V32: =IF(B32="","",U32*I32) | W32: =IF(B32="","",O32+V32) | X32: 3/8" | Y32: 0.56 | Z32: 0.25 | AA32: 0.56 | AB32: 0.56 | AC32: =IF(B32="","",IF(D32="TAPADA",(AA32+AB32)/2,0)) | AD32: =IF(B32="","",IF(D32="TAPADA",IFERROR(IF($X$1="ENTERO (redondeo arriba)",ROUNDUP(G32/Z32,0)+1,G32/Z32+1),0),0)) | AE32: =IF(B32="","",IF(D32="TAPADA",AC32*AD32,0)) | AF32: =IF(B32="","",IF(D32="TAPADA",AE32*Y32,0)) | AG32: =IF(B32="","",W32+AF32)
A33: 23 | B33: EJE 11 | C33: TRAMO 01 | D33: ABIERTA | E33: SEC 44 | F33: SEC 45 | G33: 42.76 | H33: 3/8" | I33: =IF(H33="","",IFERROR(VLOOKUP(H33,Listas!$A$4:$B$11,2,FALSE),"")) | J33: 0.2 | K33: 7 | L33: 9 | M33: =IF(B33="","",(K33+L33)/2) | N33: =IF(B33="","",G33*M33) | O33: =IF(B33="","",N33*I33) | P33: 0.25 | Q33: 1.42 | R33: 1.82 | S33: =IF(B33="","",(Q33+R33)/2) | T33: =IF(B33="","",IFERROR(IF($X$1="ENTERO (redondeo arriba)",ROUNDUP(G33/P33,0)+1,G33/P33+1),0)) | U33: =IF(B33="","",S33*T33) | V33: =IF(B33="","",U33*I33) | W33: =IF(B33="","",O33+V33) | AC33: =IF(B33="","",IF(D33="TAPADA",(AA33+AB33)/2,0)) | AD33: =IF(B33="","",IF(D33="TAPADA",IFERROR(IF($X$1="ENTERO (redondeo arriba)",ROUNDUP(G33/Z33,0)+1,G33/Z33+1),0),0)) | AE33: =IF(B33="","",IF(D33="TAPADA",AC33*AD33,0)) | AF33: =IF(B33="","",IF(D33="TAPADA",AE33*Y33,0)) | AG33: =IF(B33="","",W33+AF33)
A34: 24 | B34: EJE 11 | C34: TRAMO 02 | D34: TAPADA | E34: SEC 45 | F34: SEC 46 | G34: 2.2 | H34: 3/8" | I34: =IF(H34="","",IFERROR(VLOOKUP(H34,Listas!$A$4:$B$11,2,FALSE),"")) | J34: 0.2 | K34: 10 | L34: 10 | M34: =IF(B34="","",(K34+L34)/2) | N34: =IF(B34="","",G34*M34) | O34: =IF(B34="","",N34*I34) | P34: 0.25 | Q34: 1.82 | R34: 1.84 | S34: =IF(B34="","",(Q34+R34)/2) | T34: =IF(B34="","",IFERROR(IF($X$1="ENTERO (redondeo arriba)",ROUNDUP(G34/P34,0)+1,G34/P34+1),0)) | U34: =IF(B34="","",S34*T34) | V34: =IF(B34="","",U34*I34) | W34: =IF(B34="","",O34+V34) | X34: 3/8" | Y34: 0.56 | Z34: 0.25 | AA34: 0.56 | AB34: 0.56 | AC34: =IF(B34="","",IF(D34="TAPADA",(AA34+AB34)/2,0)) | AD34: =IF(B34="","",IF(D34="TAPADA",IFERROR(IF($X$1="ENTERO (redondeo arriba)",ROUNDUP(G34/Z34,0)+1,G34/Z34+1),0),0)) | AE34: =IF(B34="","",IF(D34="TAPADA",AC34*AD34,0)) | AF34: =IF(B34="","",IF(D34="TAPADA",AE34*Y34,0)) | AG34: =IF(B34="","",W34+AF34)
A35: 25 | B35: EJE 11 | C35: TRAMO 03 | D35: TAPADA | E35: SEC 47 | F35: SEC 48 | G35: 6.5 | H35: 3/8" | I35: =IF(H35="","",IFERROR(VLOOKUP(H35,Listas!$A$4:$B$11,2,FALSE),"")) | J35: 0.21 | K35: 10 | L35: 10 | M35: =IF(B35="","",(K35+L35)/2) | N35: =IF(B35="","",G35*M35) | O35: =IF(B35="","",N35*I35) | P35: 0.25 | Q35: 1.76 | R35: 1.82 | S35: =IF(B35="","",(Q35+R35)/2) | T35: =IF(B35="","",IFERROR(IF($X$1="ENTERO (redondeo arriba)",ROUNDUP(G35/P35,0)+1,G35/P35+1),0)) | U35: =IF(B35="","",S35*T35) | V35: =IF(B35="","",U35*I35) | W35: =IF(B35="","",O35+V35) | X35: 3/8" | Y35: 0.56 | Z35: 0.25 | AA35: 0.56 | AB35: 0.56 | AC35: =IF(B35="","",IF(D35="TAPADA",(AA35+AB35)/2,0)) | AD35: =IF(B35="","",IF(D35="TAPADA",IFERROR(IF($X$1="ENTERO (redondeo arriba)",ROUNDUP(G35/Z35,0)+1,G35/Z35+1),0),0)) | AE35: =IF(B35="","",IF(D35="TAPADA",AC35*AD35,0)) | AF35: =IF(B35="","",IF(D35="TAPADA",AE35*Y35,0)) | AG35: =IF(B35="","",W35+AF35)
A36: 26 | B36: EJE 12 | C36: TRAMO 01 | D36: ABIERTA | E36: SEC 50 | F36: SEC 51 | G36: 32.48 | H36: 3/8" | I36: =IF(H36="","",IFERROR(VLOOKUP(H36,Listas!$A$4:$B$11,2,FALSE),"")) | J36: 0.2 | K36: 7 | L36: 1.76 | M36: =IF(B36="","",(K36+L36)/2) | N36: =IF(B36="","",G36*M36) | O36: =IF(B36="","",N36*I36) | P36: 0.25 | Q36: 1.42 | R36: 1.76 | S36: =IF(B36="","",(Q36+R36)/2) | T36: =IF(B36="","",IFERROR(IF($X$1="ENTERO (redondeo arriba)",ROUNDUP(G36/P36,0)+1,G36/P36+1),0)) | U36: =IF(B36="","",S36*T36) | V36: =IF(B36="","",U36*I36) | W36: =IF(B36="","",O36+V36) | AC36: =IF(B36="","",IF(D36="TAPADA",(AA36+AB36)/2,0)) | AD36: =IF(B36="","",IF(D36="TAPADA",IFERROR(IF($X$1="ENTERO (redondeo arriba)",ROUNDUP(G36/Z36,0)+1,G36/Z36+1),0),0)) | AE36: =IF(B36="","",IF(D36="TAPADA",AC36*AD36,0)) | AF36: =IF(B36="","",IF(D36="TAPADA",AE36*Y36,0)) | AG36: =IF(B36="","",W36+AF36)
A37: 27 | B37: EJE 12 | C37: TRAMO 02 | D37: TAPADA | E37: SEC 52 | F37: SEC 53 | G37: 56.64 | H37: 3/8" | I37: =IF(H37="","",IFERROR(VLOOKUP(H37,Listas!$A$4:$B$11,2,FALSE),"")) | J37: 0.21 | K37: 10 | L37: 12 | M37: =IF(B37="","",(K37+L37)/2) | N37: =IF(B37="","",G37*M37) | O37: =IF(B37="","",N37*I37) | P37: 0.25 | Q37: 1.66 | R37: 2.22 | S37: =IF(B37="","",(Q37+R37)/2) | T37: =IF(B37="","",IFERROR(IF($X$1="ENTERO (redondeo arriba)",ROUNDUP(G37/P37,0)+1,G37/P37+1),0)) | U37: =IF(B37="","",S37*T37) | V37: =IF(B37="","",U37*I37) | W37: =IF(B37="","",O37+V37) | X37: 3/8" | Y37: 0.56 | Z37: 0.25 | AA37: 0.56 | AB37: 0.56 | AC37: =IF(B37="","",IF(D37="TAPADA",(AA37+AB37)/2,0)) | AD37: =IF(B37="","",IF(D37="TAPADA",IFERROR(IF($X$1="ENTERO (redondeo arriba)",ROUNDUP(G37/Z37,0)+1,G37/Z37+1),0),0)) | AE37: =IF(B37="","",IF(D37="TAPADA",AC37*AD37,0)) | AF37: =IF(B37="","",IF(D37="TAPADA",AE37*Y37,0)) | AG37: =IF(B37="","",W37+AF37)
A38: TOTALES DE LA PLANILLA | G38: =SUM(G11:G37) | N38: =SUM(N11:N37) | O38: =SUM(O11:O37) | U38: =SUM(U11:U37) | V38: =SUM(V11:V37) | W38: =SUM(W11:W37) | AE38: =SUM(AE11:AE37) | AF38: =SUM(AF11:AF37) | AG38: =SUM(AG11:AG37)

Sheet METRADO DE CURADO
A1: METRADO DE CURADO DE CONCRETO EN CUNETAS
A2: ENTIDAD | C2: GERENCIA TERRITORIAL BAJO MAYO - TARAPOTO
A3: PROYECTO | C3: =+RESUMEN!B5
A4: UBICACIÓN | C4: =+RESUMEN!B6 | K4: FECHA | L4: =+RESUMEN!B7
A6: N° | B6: EJE | C6: TRAMO | D6: TIPO DE CUNETA | E6: LONGITUD (m) | F6: ANCHO INTERIOR (m) | G6: ALTURA INT. INI (m) | H6: ALTURA INT. FIN (m) | I6: ALTURA PROM. (m) | J6: ÁREA 2 MUROS (m²) | K6: ÁREA FONDO (m²) | L6: ÁREA TAPA / TECHO (m²) | M6: TOTAL CURADO (m²) | N6: N° CARAS | O6: UND.
A7: 1 | B7: EJE 01 | C7: TRAMO 01 | D7: ABIERTA | E7: 32 | F7: 0.4 | G7: 0.3 | H7: 0.46 | I7: =IF(B7="","",(G7+H7)/2) | J7: =IF(B7="","",2*E7*I7) | K7: =IF(B7="","",E7*F7) | L7: =IF(B7="","",IF(D7="TAPADA",E7*F7,0)) | M7: =SUM(J7:L7) | N7: =IF(B7="","",IF(D7="TAPADA",4,3)) | O7: m²
A8: 2 | B8: EJE 01 | C8: TRAMO 02 | D8: TAPADA | E8: 5.14 | F8: 0.4 | G8: 0.46 | H8: 0.48 | I8: =IF(B8="","",(G8+H8)/2) | J8: =IF(B8="","",2*E8*I8) | K8: =IF(B8="","",E8*F8) | L8: =IF(B8="","",IF(D8="TAPADA",E8*F8,0)) | M8: =SUM(J8:L8) | N8: =IF(B8="","",IF(D8="TAPADA",4,3)) | O8: m²
A9: 3 | B9: EJE 02 | C9: TRAMO 01 | D9: ABIERTA | E9: 37.5 | F9: 0.4 | G9: 0.3 | H9: 0.48 | I9: =IF(B9="","",(G9+H9)/2) | J9: =IF(B9="","",2*E9*I9) | K9: =IF(B9="","",E9*F9) | L9: =IF(B9="","",IF(D9="TAPADA",E9*F9,0)) | M9: =SUM(J9:L9) | N9: =IF(B9="","",IF(D9="TAPADA",4,3)) | O9: m²
A10: 4 | B10: EJE 02 | C10: TRAMO 02 | D10: TAPADA | E10: 10.2 | F10: 0.4 | G10: 0.48 | H10: 0.53 | I10: =IF(B10="","",(G10+H10)/2) | J10: =IF(B10="","",2*E10*I10) | K10: =IF(B10="","",E10*F10) | L10: =IF(B10="","",IF(D10="TAPADA",E10*F10,0)) | M10: =SUM(J10:L10) | N10: =IF(B10="","",IF(D10="TAPADA",4,3)) | O10: m²
A11: 5 | B11: EJE 02 | C11: TRAMO 03 | D11: ABIERTA | E11: 31.33 | F11: 0.4 | G11: 0.53 | H11: 0.7 | I11: =IF(B11="","",(G11+H11)/2) | J11: =IF(B11="","",2*E11*I11) | K11: =IF(B11="","",E11*F11) | L11: =IF(B11="","",IF(D11="TAPADA",E11*F11,0)) | M11: =SUM(J11:L11) | N11: =IF(B11="","",IF(D11="TAPADA",4,3)) | O11: m²
A12: 6 | B12: EJE 02 | C12: TRAMO 04 | D12: TAPADA | E12: 8.36 | F12: 0.4 | G12: 0.7 | H12: 0.73 | I12: =IF(B12="","",(G12+H12)/2) | J12: =IF(B12="","",2*E12*I12) | K12: =IF(B12="","",E12*F12) | L12: =IF(B12="","",IF(D12="TAPADA",E12*F12,0)) | M12: =SUM(J12:L12) | N12: =IF(B12="","",IF(D12="TAPADA",4,3)) | O12: m²
A13: 7 | B13: EJE 02 | C13: TRAMO 05 | D13: ABIERTA | E13: 30.36 | F13: 0.4 | G13: 0.73 | H13: 0.88 | I13: =IF(B13="","",(G13+H13)/2) | J13: =IF(B13="","",2*E13*I13) | K13: =IF(B13="","",E13*F13) | L13: =IF(B13="","",IF(D13="TAPADA",E13*F13,0)) | M13: =SUM(J13:L13) | N13: =IF(B13="","",IF(D13="TAPADA",4,3)) | O13: m²
A14: 8 | B14: EJE 02 | C14: TRAMO 06 | D14: TAPADA | E14: 2.25 | F14: 0.4 | G14: 0.88 | H14: 0.9 | I14: =IF(B14="","",(G14+H14)/2) | J14: =IF(B14="","",2*E14*I14) | K14: =IF(B14="","",E14*F14) | L14: =IF(B14="","",IF(D14="TAPADA",E14*F14,0)) | M14: =SUM(J14:L14) | N14: =IF(B14="","",IF(D14="TAPADA",4,3)) | O14: m²
A15: 9 | B15: EJE 02 | C15: TRAMO 07 | D15: TAPADA | E15: 10.85 | F15: 0.4 | G15: 0.85 | H15: 0.9 | I15: =IF(B15="","",(G15+H15)/2) | J15: =IF(B15="","",2*E15*I15) | K15: =IF(B15="","",E15*F15) | L15: =IF(B15="","",IF(D15="TAPADA",E15*F15,0)) | M15: =SUM(J15:L15) | N15: =IF(B15="","",IF(D15="TAPADA",4,3)) | O15: m²
A16: 10 | B16: EJE 03 | C16: TRAMO 01 | D16: ABIERTA | E16: 5.82 | F16: 0.4 | G16: 0.3 | H16: 0.32 | I16: =IF(B16="","",(G16+H16)/2) | J16: =IF(B16="","",2*E16*I16) | K16: =IF(B16="","",E16*F16) | L16: =IF(B16="","",IF(D16="TAPADA",E16*F16,0)) | M16: =SUM(J16:L16) | N16: =IF(B16="","",IF(D16="TAPADA",4,3)) | O16: m²
A17: 11 | B17: EJE 04 | C17: TRAMO 01 | D17: ABIERTA | E17: 8.6 | F17: 0.4 | G17: 0.3 | H17: 0.34 | I17: =IF(B17="","",(G17+H17)/2) | J17: =IF(B17="","",2*E17*I17) | K17: =IF(B17="","",E17*F17) | L17: =IF(B17="","",IF(D17="TAPADA",E17*F17,0)) | M17: =SUM(J17:L17) | N17: =IF(B17="","",IF(D17="TAPADA",4,3)) | O17: m²
A18: 12 | B18: EJE 05 | C18: TRAMO 01 | D18: ABIERTA | E18: 37.53 | F18: 0.4 | G18: 0.3 | H18: 0.48 | I18: =IF(B18="","",(G18+H18)/2) | J18: =IF(B18="","",2*E18*I18) | K18: =IF(B18="","",E18*F18) | L18: =IF(B18="","",IF(D18="TAPADA",E18*F18,0)) | M18: =SUM(J18:L18) | N18: =IF(B18="","",IF(D18="TAPADA",4,3)) | O18: m²
... A36: 30 | B36: EJE 12 | C36: TRAMO 02 | D36: TAPADA | E36: 56.64 | F36: 0.4 | G36: 0.51 | H36: 0.8 | I36: =IF(B36="","",(G36+H36)/2) | J36: =IF(B36="","",2*E36*I36) | K36: =IF(B36="","",E36*F36) | L36: =IF(B36="","",IF(D36="TAPADA",E36*F36,0)) | M36: =SUM(J36:L36) | N36: =IF(B36="","",IF(D36="TAPADA",4,3)) | O36: m²
A38: TOTAL DE CURADO DE CONCRETO EN CUNETAS | M38: =SUM(M7:M36) | O38: m²

Sheet METRADO DE REJILLAS
A1: METRADO DE REJILLAS PARA CUNETAS
A2: ENTIDAD | C2: GERENCIA TERRITORIAL BAJO MAYO - TARAPOTO
A3: PROYECTO | C3: =+RESUMEN!B5
A4: UBICACIÓN | C4: =+RESUMEN!B6 | G4: FECHA | H4: =+RESUMEN!B7
A6: N° | B6: EJE | C6: TRAMO | D6: TIPO DE CUNETA | E6: LONGITUD DEL TRAMO (m) | F6: DESCUENTO SIN REJILLA (m) | G6: LONGITUD CON REJILLA (m) | H6: UND.
A7: 1 | B7: EJE 01 | C7: TRAMO 01 | D7: ABIERTA | E7: 32 | F7: 0 | G7: =IF(B7="","",IF(D7="ABIERTA",IF(E7-F7<0,0,E7-F7),0)) | H7: m
A8: 2 | B8: EJE 01 | C8: TRAMO 02 | D8: TAPADA | E8: 5.14 | F8: 0 | G8: =IF(B8="","",IF(D8="ABIERTA",IF(E8-F8<0,0,E8-F8),0)) | H8: m
A9: 3 | B9: EJE 02 | C9: TRAMO 01 | D9: ABIERTA | E9: 37.5 | F9: 0 | G9: =IF(B9="","",IF(D9="ABIERTA",IF(E9-F9<0,0,E9-F9),0)) | H9: m
A10: 4 | B10: EJE 02 | C10: TRAMO 02 | D10: TAPADA | E10: 10.2 | F10: 0 | G10: =IF(B10="","",IF(D10="ABIERTA",IF(E10-F10<0,0,E10-F10),0)) | H10: m
A11: 5 | B11: EJE 02 | C11: TRAMO 03 | D11: ABIERTA | E11: 31.33 | F11: 0 | G11: =IF(B11="","",IF(D11="ABIERTA",IF(E11-F11<0,0,E11-F11),0)) | H11: m
A12: 6 | B12: EJE 02 | C12: TRAMO 04 | D12: TAPADA | E12: 8.36 | F12: 0 | G12: =IF(B12="","",IF(D12="ABIERTA",IF(E12-F12<0,0,E12-F12),0)) | H12: m
A13: 7 | B13: EJE 02 | C13: TRAMO 05 | D13: ABIERTA | E13: 30.36 | F13: 0 | G13: =IF(B13="","",IF(D13="ABIERTA",IF(E13-F13<0,0,E13-F13),0)) | H13: m
A14: 8 | B14: EJE 02 | C14: TRAMO 06 | D14: TAPADA | E14: 2.25 | F14: 0 | G14: =IF(B14="","",IF(D14="ABIERTA",IF(E14-F14<0,0,E14-F14),0)) | H14: m
A15: 9 | B15: EJE 02 | C15: TRAMO 07 | D15: TAPADA | E15: 10.85 | F15: 0 | G15: =IF(B15="","",IF(D15="ABIERTA",IF(E15-F15<0,0,E15-F15),0)) | H15: m
A16: 10 | B16: EJE 03 | C16: TRAMO 01 | D16: ABIERTA | E16: 5.82 | F16: 0 | G16: =IF(B16="","",IF(D16="ABIERTA",IF(E16-F16<0,0,E16-F16),0)) | H16: m
A17: 11 | B17: EJE 04 | C17: TRAMO 01 | D17: ABIERTA | E17: 8.6 | F17: 0 | G17: =IF(B17="","",IF(D17="ABIERTA",IF(E17-F17<0,0,E17-F17),0)) | H17: m
A18: 12 | B18: EJE 05 | C18: TRAMO 01 | D18: ABIERTA | E18: 37.53 | F18: 0 | G18: =IF(B18="","",IF(D18="ABIERTA",IF(E18-F18<0,0,E18-F18),0)) | H18: m
... A36: 30 | B36: EJE 12 | C36: TRAMO 02 | D36: TAPADA | E36: 56.64 | F36: 0 | G36: =IF(B36="","",IF(D36="ABIERTA",IF(E36-F36<0,0,E36-F36),0)) | H36: m
A38: TOTAL CALCULADO DE REJILLA EN CUNETAS ABIERTAS | G38: =SUM(G7:G36) | H38: m

Sheet METRADO JUNTA DE DILATACION
A1: PLANILLA DE METRADOS - JUNTA DE DILATACIÓN E=1" CON SELLADOR ASFÁLTICO EN MUROS DE CUNETAS
A2: ENTIDAD | B2: GERENCIA TERRITORIAL BAJO MAYO - TARAPOTO
A3: PROYECTO | B3: =+RESUMEN!B5
A4: UBICACIÓN | B4: =+RESUMEN!B6
A5: FECHA | B5: =+RESUMEN!B7
A7: PARÁMETROS
A8: Espaciamiento entre juntas (m) | B8: 3
A9: N° de muros con junta por cuneta | B9: 2
A10: Espesor de junta (referencial, no interviene en el metrado lineal) | B10: 1" = 0.0254 m
A11: ITEM | B11: EJE / DESCRIPCIÓN | C11: UND. | D11: LONGITUD EJE (m) | E11: ÁREA MURO (m²) | F11: ALTURA MURO (m) | G11: ESPACIAMIENTO (m) | H11: N° DE JUNTAS | I11: N° MUROS x JUNTA | J11: PARCIAL (ml)
A12: Descripccion | B12: JUNTA DE DILATACION E=1" CON SELLADOR ASFALTO | C12: ml | J12: =SUM(J13:J24)
A13: 1 | B13: EJE 01 | D13: 37.14 | E13: =+'CONCRETO EN CUNETAS'!E10 | F13: =E13/D13 | G13: =B8 | H13: =ROUNDUP(D13/G13,0) | I13: =B9 | J13: =H13*I13*F13
A14: 2 | B14: EJE 02 | D14: 130.85 | E14: =+'CONCRETO EN CUNETAS'!E22 | F14: =E14/D14 | G14: =B8 | H14: =ROUNDUP(D14/G14,0) | I14: =B9 | J14: =H14*I14*F14
A15: 3 | B15: EJE 03 | D15: 5.82 | E15: =+'CONCRETO EN CUNETAS'!E34 | F15: =E15/D15 | G15: =B8 | H15: =ROUNDUP(D15/G15,0) | I15: =B9 | J15: =H15*I15*F15
A16: 4 | B16: EJE 04 | D16: 8.6 | E16: =+'CONCRETO EN CUNETAS'!E46 | F16: =E16/D16 | G16: =B8 | H16: =ROUNDUP(D16/G16,0) | I16: =B9 | J16: =H16*I16*F16
A17: 5 | B17: EJE 05 | D17: 43.23 | E17: =+'CONCRETO EN CUNETAS'!E58 | F17: =E17/D17 | G17: =B8 | H17: =ROUNDUP(D17/G17,0) | I17: =B9 | J17: =H17*I17*F17
A18: 6 | B18: EJE 06 | D18: 120.36 | E18: =+'CONCRETO EN CUNETAS'!E70 | F18: =E18/D18 | G18: =B8 | H18: =ROUNDUP(D18/G18,0) | I18: =B9 | J18: =H18*I18*F18
A19: 7 | B19: EJE 07 | D19: 125.7 | E19: =+'CONCRETO EN CUNETAS'!M10 | F19: =E19/D19 | G19: =B8 | H19: =ROUNDUP(D19/G19,0) | I19: =B9 | J19: =H19*I19*F19
A20: 8 | B20: EJE 08 | D20: 8.2 | E20: =+'CONCRETO EN CUNETAS'!M22 | F20: =E20/D20 | G20: =B8 | H20: =ROUNDUP(D20/G20,0) | I20: =B9 | J20: =H20*I20*F20
A21: 9 | B21: EJE 09 | D21: 7 | E21: =+'CONCRETO EN CUNETAS'!M34 | F21: =E21/D21 | G21: =B8 | H21: =ROUNDUP(D21/G21,0) | I21: =B9 | J21: =H21*I21*F21
A22: 10 | B22: EJE 10 | D22: 16 | E22: =+'CONCRETO EN CUNETAS'!M46 | F22: =E22/D22 | G22: =B8 | H22: =ROUNDUP(D22/G22,0) | I22: =B9 | J22: =H22*I22*F22
A23: 11 | B23: EJE 11 | D23: 71.46 | E23: =+'CONCRETO EN CUNETAS'!M58 | F23: =E23/D23 | G23: =B8 | H23: =ROUNDUP(D23/G23,0) | I23: =B9 | J23: =H23*I23*F23
A24: 12 | B24: EJE 12 | D24: 109.12 | E24: =+'CONCRETO EN CUNETAS'!M70 | F24: =E24/D24 | G24: =B8 | H24: =ROUNDUP(D24/G24,0) | I24: =B9 | J24: =H24*I24*F24

Sheet PLANILLA TAPAS REGISTRO INTERNO
A1: METRADO DE TAPAS DE REGISTRO EN CUNETAS TAPADAS
A2: ENTIDAD | B2: GERENCIA TERRITORIAL BAJO MAYO - TARAPOTO
A3: PROYECTO | B3: =+RESUMEN!B5
A4: UBICACIÓN | B4: =+RESUMEN!B6
A5: FECHA | B5: =+RESUMEN!B7
A7: ITEM | B7: DESCRIPCIÓN | C7: Nº DE VECES | D7: DIMENSIONES | I7: PARCIAL | J7: TOTAL | K7: UND
D8: LARGO | E8: ANCHO | F8: ALTURA | G8: FACT. | H8: AREA | I8: VOLUMEN / PARCIAL
A9: 01.04.03.04.03.02 | B9: TAPA DE REGISTRO (DE CONCRETO) | J9: =+PARAMETROS!B4 | K9: und
B11: CONCRETO F´C=210 KG/CM2 EN TAPA DE REGISTRO | I11: TOTAL
B12: TAPA 0.60 x 0.60 x 0.10 m | C12: =PARAMETROS!B4 | D12: =PARAMETROS!B5 | E12: =PARAMETROS!B6 | F12: =PARAMETROS!B7 | I12: =C12*D12*E12*F12 | J12: =I12 | K12: m3
B14: ENCOFRADO Y DESENCOFRADO EN TAPA DE REGISTRO | I14: TOTAL
B15: LATERALES DE TAPA | C15: =PARAMETROS!B4 | D15: =2*(PARAMETROS!B5+PARAMETROS!B6) | F15: =PARAMETROS!B7 | H15: =D15*F15 | I15: =C15*H15 | J15: =I15 | K15: m2
B16: FONDO DE MOLDE / BASE DE PREFABRICADO | C16: =PARAMETROS!B4 | D16: =PARAMETROS!B5 | E16: =PARAMETROS!B6 | H16: =D16*E16 | I16: =C16*H16 | J16: =I16 | K16: m2
B17: TOTAL ENCOFRADO FONDO + LATERALES | J17: =J15+J16 | K17: m2
B19: ACERO FY=4200 KG/CM2 EN TAPA DE REGISTRO - VARILLA 3/8 | D19: LONGITUD DE CADA BARRA | E19: CANTIDAD DE BARRAS POR TAPA | I19: TOTAL
B20: Acero longitudinal 3/8 - parrilla simple | C20: =PARAMETROS!B4 | D20: =PARAMETROS!B5-2*PARAMETROS!B8 | E20: =ROUND((PARAMETROS!B6-2*PARAMETROS!B8)/PARAMETROS!B9,0)+1 | G20: =PARAMETROS!B10 | I20: =C20*D20*E20*G20 | J20: =I20 | K20: kg
B21: Acero transversal 3/8 - parrilla simple | C21: =PARAMETROS!B4 | D21: =PARAMETROS!B6-2*PARAMETROS!B8 | E21: =ROUND((PARAMETROS!B5-2*PARAMETROS!B8)/PARAMETROS!B9,0)+1 | G21: =PARAMETROS!B10 | I21: =C21*D21*E21*G21 | J21: =I21 | K21: kg
B22: TOTAL ACERO 3/8 | J22: =J20+J21 | K22: kg

Sheet PARAMETROS
A1: PARÁMETROS - TAPA DE REGISTRO DE CONCRETO
A3: Descripción | B3: Valor | C3: Unidad | D3: Criterio
A4: Cantidad de tapas | B4: 17 | C4: und | D4: Según resumen: 10 tapas
A5: Largo de tapa | B5: 0.6 | C5: m | D5: Según detalle
A6: Ancho de tapa | B6: 0.6 | C6: m | D6: Según detalle
A7: Espesor de tapa | B7: 0.1 | C7: m | D7: Según detalle
A8: Recubrimiento considerado | B8: 0.025 | C8: m | D8: Editable según plano estructural
A9: Separación de varillas 3/8 | B9: 0.15 | C9: m | D9: Parrilla simple en ambos sentidos
A10: Peso varilla 3/8 | B10: 0.56 | C10: kg/m | D10: Peso unitario usado para metrado
A11: Longitud varilla comercial | B11: 9 | C11: m | D11: Solo equivalente de longitud, sin redondeo
A13: PARÁMETROS - MOVIMIENTO DE TIERRAS
A14: Descripción | B14: Valor | C14: Unidad | D14: Criterio
A15: Espesor de solado sumado a excavación y relleno | B15: 0.1 | C15: m | D15: Solado e=4" bajo la losa. Poner 0 si la altura ya lo incluye
A16: Factor de esponjamiento | B16: 1.2 | C16: - | D16: Eliminación = (excavación − relleno) × factor

Sheet Listas
A1: LISTAS, FACTORES Y PARÁMETROS EDITABLES
A3: DIÁMETRO | B3: FACTOR kg/m | D3: TIPO DE CUNETA | F3: CRITERIO DE CONTEO
A4: 6 mm | B4: 0.222 | D4: ABIERTA | F4: TEÓRICO (L/s+1)
A5: 8 mm | B5: 0.395 | D5: TAPADA | F5: ENTERO (redondeo arriba)
A6: 3/8" | B6: 0.56
A7: 12 mm | B7: 0.888
A8: 1/2" | B8: 0.994
A9: 5/8" | B9: 1.552
A10: 3/4" | B10: 2.235
A11: 1" | B11: 3.973
A13: NOTA
A14: Los factores kg/m son editables. Si el proyecto usa otro factor, cámbialo aquí.
A15: La opción TEÓRICO mantiene cantidades decimales: Longitud / separación + 1.
A16: La opción ENTERO redondea hacia arriba antes de sumar la barra final.

Sheet COLECTOR PARAMETROS
A1: COLECTOR PLUVIAL FRONTAL - PARAMETROS DE METRADO
A2: ENTIDAD | C2: =+RESUMEN!B4
A3: PROYECTO | C3: =+RESUMEN!B5
A4: UBICACIÓN | C4: =+RESUMEN!B6
A5: FECHA | C5: =+RESUMEN!B7
A7: Tramo Hogar de Refugio Temporal (CUI 2675514), empalme con el colector de CAR Mujeres (CUI 2717013). Valores tomados de los planos DP-01 a DP-10 y DA-01 a DA-03 y de la memoria de calculo del colector. Celda amarilla = dato; verde = formula.
A9: N° | B9: PARAMETRO | C9: VALOR | D9: UND | E9: SUSTENTO (lamina / norma / criterio)
A10: 1 | B10: Ancho interior del colector b | C10: 0.8 | D10: m | E10: Lamina DP-04 (secciones); memoria de calculo, hoja DATOS
A11: 2 | B11: Espesor de muros | C11: 0.15 | D11: m | E11: Lamina DP-04; memoria, hoja ESTRUCTURAL
A12: 3 | B12: Espesor de losa de fondo | C12: 0.15 | D12: m | E12: Lamina DP-04
A13: 4 | B13: Espesor de losa superior (tramo normal y cruce de motos) | C13: 0.1 | D13: m | E13: Lamina DP-04 (secciones A y B)
A14: 5 | B14: Espesor de losa superior (cruce de camiones) | C14: 0.25 | D14: m | E14: Lamina DP-04 (seccion C); memoria, hoja ESTRUCTURAL (carga HL-93)
A15: 6 | B15: Espesor de solado | C15: 0.05 | D15: m | E15: Lamina DP-04 y DA-02
A16: 7 | B16: Nivel de piso terminado del frente (cara superior de la losa) | C16: 260.6 | D16: msnm | E16: Lamina DP-02 (perfil) y plano de arquitectura
A17: 8 | B17: Sobreancho de excavacion a cada lado del colector | C17: 0.25 | D17: m | E17: Lamina DA-01: zanja de 1.60 m (1.10 + 2 x 0.25)
A18: 9 | B18: Franja de relleno de nivelacion del retiro, lado via | C18: 1 | D18: m | E18: Lamina DA-01, nota 2
A19: 10 | B19: Recubrimiento del acero | C19: 0.04 | D19: m | E19: Norma E.060, tabla 7.7.1 (concreto en contacto con el suelo)
A20: 11 | B20: Peso de la barra de 3/8" | C20: 0.56 | D20: kg/m | E20: Igual a PARAMETROS!B10 de esta planilla
A21: 12 | B21: Peso de la barra de 1/2" | C21: 0.994 | D21: kg/m | E21: Catalogo del fabricante (0.994 kg/m)
... A24: 15 | B24: Ganchos de cierre del marco (2 x 0.15) | C24: 0.3 | D24: m | E24: Lamina DP-08, cuadro de doblado
A25: 16 | B25: Factor de esponjamiento | C25: =PARAMETROS!$B$16 | D25: - | E25: Igual a PARAMETROS!B16 de esta planilla
A26: 17 | B26: Espaciamiento de marcos en tramo normal | C26: 0.2 | D26: m | E26: Lamina DP-04 (seccion A) y DP-08
A27: 18 | B27: Espaciamiento de marcos en cruces (motos y camiones) | C27: 0.15 | D27: m | E27: Lamina DP-04 (secciones B y C) y DP-08
A28: 19 | B28: Espaciamiento de barras longitudinales (normal y motos) | C28: 0.25 | D28: m | E28: Lamina DP-04 y DP-08
A29: 20 | B29: Espaciamiento de barras longitudinales (camiones) | C29: 0.2 | D29: m | E29: Lamina DP-04 (seccion C) y DP-08
A30: 21 | B30: Malla de las cajas: espaciamiento 3/8" ambas caras | C30: 0.2 | D30: m | E30: Lamina DP-07
A31: 22 | B31: Factor por traslapes y ganchos de la malla | C31: 1.1 | D31: - | E31: 10 % (traslape 0.40 cada 9.00 m y ganchos de esquina 0.40)
A32: 23 | B32: Numero de registros de limpieza con tapa | C32: 10 | D32: und | E32: Lamina DP-01 (RS-01 a RS-07) + 1 en CL + 2 en CC = 10; hoja COLECTOR REGISTROS Y TAPAS
A33: 24 | B33: Lado de la tapa de concreto | C33: 0.68 | D33: m | E33: Lamina DP-06B
A34: 25 | B34: Espesor de la tapa | C34: 0.08 | D34: m | E34: Lamina DP-06B
A35: 26 | B35: Lado de la abertura en la losa (luz del contramarco) | C35: 0.7 | D35: m | E35: Lamina DP-06B
A36: 27 | B36: Perimetro del contramarco L 2"x2"x3/16" (4 x 0.70) | C36: 2.8 | D36: m | E36: Lamina DP-06B
A37: 28 | B37: Perimetro del marco de tapa L 1 1/2"x1 1/2"x1/8" (4 x 0.68) | C37: 2.72 | D37: m | E37: Lamina DP-06B
... A61: 52 | B61: Progresiva del primer quiebre (fin del tramo pegado al cerco) | C61: 58.805 | D61: m | E61: Lamina DP-01

Sheet COLECTOR MOV. TIERRAS
A1: COLECTOR PLUVIAL FRONTAL - METRADO DE MOVIMIENTO DE TIERRAS
A2: ENTIDAD | C2: =+RESUMEN!B4
A3: PROYECTO | C3: =+RESUMEN!B5
A4: UBICACIÓN | C4: =+RESUMEN!B6
A5: FECHA | C5: =+RESUMEN!B7
A7: Criterio (lamina DA-01): LIMPIEZA Y TRAZO = ancho de zanja x L. EXCAVACION = ancho de zanja x Hz x L, con Hz = terreno existente (topografia) - fondo del solado. REFINE = (ancho exterior + 0.10) x L (fondo del solado). RELLENO LATERAL = 2 x sobreancho x Hz x L. RELLENO FRANJA = 1.00 x (NPT - terreno) x L (nivelacion del retiro lado via). h y Hz son valores medios ponderados del tramo (perfil DP-02 y topografia); el detalle cada 2.00 m esta en la memoria de calculo.
A9: N° | B9: TRAMO | C9: ZONA | D9: PROG. INICIO | E9: PROG. FIN | F9: LONGITUD (m) | G9: ALTURA INTERIOR h (m) | H9: e LOSA SUP. (m) | I9: ANCHO EXT. b + 2e (m) | J9: ANCHO DE ZANJA (m) | K9: Hz: TERRENO - FONDO DE SOLADO (m) | L9: NPT - TERRENO (m) | M9: LIMPIEZA Y TRAZO (m2) | N9: EXCAVACION (m3) | O9: REFINE Y NIVELACION (m2) | P9: RELLENO LATERAL DE ZANJA (m3) | Q9: RELLENO FRANJA DE NIVELACION (m3) | R9: SUSTENTO
A10: 1 | B10: tramo normal | C10: NORMAL | D10: 0+000.00 | E10: 0+026.32 | F10: 26.32 | G10: 1.439 | H10: 0.1 | I10: ='COLECTOR PARAMETROS'!$C$10+2*'COLECTOR PARAMETROS'!$C$11 | J10: =I10+2*'COLECTOR PARAMETROS'!$C$17 | K10: 1.395 | L10: 0.345 | M10: =J10*F10 | N10: =J10*K10*F10 | O10: =(I10+0.10)*F10 | P10: =2*'COLECTOR PARAMETROS'!$C$17*K10*F10 | Q10: ='COLECTOR PARAMETROS'!$C$18*L10*F10 | R10: DP-01 (planta), DP-02 (perfil: fondo y terreno), DP-04 (seccion), DA-01 (criterio)
A11: 2 | B11: cruce de camiones | C11: CAMION | D11: 0+026.32 | E11: 0+031.33 | F11: 5.01 | G11: 1.336 | H11: 0.25 | I11: ='COLECTOR PARAMETROS'!$C$10+2*'COLECTOR PARAMETROS'!$C$11 | J11: =I11+2*'COLECTOR PARAMETROS'!$C$17 | K11: 1.274 | L11: 0.513 | M11: =J11*F11 | N11: =J11*K11*F11 | O11: =(I11+0.10)*F11 | P11: =2*'COLECTOR PARAMETROS'!$C$17*K11*F11 | Q11: ='COLECTOR PARAMETROS'!$C$18*L11*F11 | R11: DP-01 (planta), DP-02 (perfil: fondo y terreno), DP-04 (seccion), DA-01 (criterio)
A12: 3 | B12: tramo normal | C12: NORMAL | D12: 0+031.33 | E12: 0+039.04 | F12: 7.71 | G12: 1.506 | H12: 0.1 | I12: ='COLECTOR PARAMETROS'!$C$10+2*'COLECTOR PARAMETROS'!$C$11 | J12: =I12+2*'COLECTOR PARAMETROS'!$C$17 | K12: 1.368 | L12: 0.437 | M12: =J12*F12 | N12: =J12*K12*F12 | O12: =(I12+0.10)*F12 | P12: =2*'COLECTOR PARAMETROS'!$C$17*K12*F12 | Q12: ='COLECTOR PARAMETROS'!$C$18*L12*F12 | R12: DP-01 (planta), DP-02 (perfil: fondo y terreno), DP-04 (seccion), DA-01 (criterio)
A13: 4 | B13: cruce de motos | C13: MOTOS | D13: 0+039.04 | E13: 0+041.04 | F13: 2 | G13: 1.52 | H13: 0.1 | I13: ='COLECTOR PARAMETROS'!$C$10+2*'COLECTOR PARAMETROS'!$C$11 | J13: =I13+2*'COLECTOR PARAMETROS'!$C$17 | K13: 1.605 | L13: 0.215 | M13: =J13*F13 | N13: =J13*K13*F13 | O13: =(I13+0.10)*F13 | P13: =2*'COLECTOR PARAMETROS'!$C$17*K13*F13 | Q13: ='COLECTOR PARAMETROS'!$C$18*L13*F13 | R13: DP-01 (planta), DP-02 (perfil: fondo y terreno), DP-04 (seccion), DA-01 (criterio)
A14: 5 | B14: tramo normal | C14: NORMAL | D14: 0+041.04 | E14: 0+058.81 | F14: 17.77 | G14: 1.55 | H14: 0.1 | I14: ='COLECTOR PARAMETROS'!$C$10+2*'COLECTOR PARAMETROS'!$C$11 | J14: =I14+2*'COLECTOR PARAMETROS'!$C$17 | K14: 1.155 | L14: 0.695 | M14: =J14*F14 | N14: =J14*K14*F14 | O14: =(I14+0.10)*F14 | P14: =2*'COLECTOR PARAMETROS'!$C$17*K14*F14 | Q14: ='COLECTOR PARAMETROS'!$C$18*L14*F14 | R14: DP-01 (planta), DP-02 (perfil: fondo y terreno), DP-04 (seccion), DA-01 (criterio)
A15: 6 | B15: tramo diagonal (quiebres) | C15: NORMAL | D15: 0+058.81 | E15: 0+066.89 | F15: 8.08 | G15: 1.589 | H15: 0.1 | I15: ='COLECTOR PARAMETROS'!$C$10+2*'COLECTOR PARAMETROS'!$C$11 | J15: =I15+2*'COLECTOR PARAMETROS'!$C$17 | K15: 1.033 | L15: 0.855 | M15: =J15*F15 | N15: =J15*K15*F15 | O15: =(I15+0.10)*F15 | P15: =2*'COLECTOR PARAMETROS'!$C$17*K15*F15 | Q15: ='COLECTOR PARAMETROS'!$C$18*L15*F15 | R15: DP-01 (planta), DP-02 (perfil: fondo y terreno), DP-04 (seccion), DA-01 (criterio)
A16: 7 | B16: tramo recto final | C16: NORMAL | D16: 0+066.89 | E16: 0+069.89 | F16: 3 | G16: 1.605 | H16: 0.1 | I16: ='COLECTOR PARAMETROS'!$C$10+2*'COLECTOR PARAMETROS'!$C$11 | J16: =I16+2*'COLECTOR PARAMETROS'!$C$17 | K16: 1.062 | L16: 0.843 | M16: =J16*F16 | N16: =J16*K16*F16 | O16: =(I16+0.10)*F16 | P16: =2*'COLECTOR PARAMETROS'!$C$17*K16*F16 | Q16: ='COLECTOR PARAMETROS'!$C$18*L16*F16 | R16: DP-01 (planta), DP-02 (perfil: fondo y terreno), DP-04 (seccion), DA-01 (criterio)
A17: TOTAL COLECTOR (tramos) | F17: =SUM(F10:F16) | M17: =SUM(M10:M16) | N17: =SUM(N10:N16) | O17: =SUM(O10:O16) | P17: =SUM(P10:P16) | Q17: =SUM(Q10:Q16)
A19: CAJAS DE LLEGADA (CL) Y DE CAIDA (CC) - lamina DP-07. Excavacion en planta = (largo int. + 2e + 2 x sobreancho) x (ancho int. + 2e + 2 x sobreancho); Hz = terreno - fondo del solado. Relleno = excavacion - volumen exterior de la caja (hasta el terreno).
A20: N° | B20: CAJA | C20: PROG. | D20: LARGO INT. (m) | E20: ANCHO INT. (m) | F20: ALTURA INT. H (m) | G20: COTA DE PISO (msnm) | H20: TERRENO (msnm) | I20: LARGO EXC. (m) | J20: ANCHO EXC. (m) | K20: Hz (m) | L20: VOL. EXTERIOR CAJA (m3) | M20: LIMPIEZA Y TRAZO (m2) | N20: EXCAVACION (m3) | O20: REFINE Y NIVELACION (m2) | P20: RELLENO LATERAL (m3) | Q20: RELLENO FRANJA (m3) | R20: SUSTENTO
A21: 1 | B21: Caja de llegada CL | C21: 0+000.00 | D21: ='COLECTOR PARAMETROS'!$C$44 | E21: ='COLECTOR PARAMETROS'!$C$45 | F21: ='COLECTOR PARAMETROS'!$C$16-'COLECTOR PARAMETROS'!$C$13-G21 | G21: ='COLECTOR PARAMETROS'!$C$47-'COLECTOR PARAMETROS'!$C$46 | H21: 260.302 | I21: =D21+2*'COLECTOR PARAMETROS'!$C$11+2*'COLECTOR PARAMETROS'!$C$17 | J21: =E21+2*'COLECTOR PARAMETROS'!$C$11+2*'COLECTOR PARAMETROS'!$C$17 | K21: =H21-(G21-'COLECTOR PARAMETROS'!$C$12-'COLECTOR PARAMETROS'!$C$15) | L21: =(D21+2*'COLECTOR PARAMETROS'!$C$11)*(E21+2*'COLECTOR PARAMETROS'!$C$11)*(F21+'COLECTOR PARAMETROS'!$C$13+'COLECTOR PARAMETROS'!$C$12+'COLECTOR PARAMETROS'!$C$15) | M21: =I21*J21 | N21: =I21*J21*K21 | O21: =(D21+2*'COLECTOR PARAMETROS'!$C$11+0.10)*(E21+2*'COLECTOR PARAMETROS'!$C$11+0.10) | P21: =MAX(0,N21-L21) | Q21: 0 | R21: DP-07 (planta y cortes de la caja), DP-02 (cotas), DA-01
A22: 2 | B22: Caja de caida CC | C22: 0+069.89 | D22: ='COLECTOR PARAMETROS'!$C$49 | E22: ='COLECTOR PARAMETROS'!$C$50 | F22: ='COLECTOR PARAMETROS'!$C$16-'COLECTOR PARAMETROS'!$C$13-G22 | G22: ='COLECTOR PARAMETROS'!$C$52-'COLECTOR PARAMETROS'!$C$51 | H22: 259.696 | I22: =D22+2*'COLECTOR PARAMETROS'!$C$11+2*'COLECTOR PARAMETROS'!$C$17 | J22: =E22+2*'COLECTOR PARAMETROS'!$C$11+2*'COLECTOR PARAMETROS'!$C$17 | K22: =H22-(G22-'COLECTOR PARAMETROS'!$C$12-'COLECTOR PARAMETROS'!$C$15) | L22: =(D22+2*'COLECTOR PARAMETROS'!$C$11)*(E22+2*'COLECTOR PARAMETROS'!$C$11)*(F22+'COLECTOR PARAMETROS'!$C$13+'COLECTOR PARAMETROS'!$C$12+'COLECTOR PARAMETROS'!$C$15) | M22: =I22*J22 | N22: =I22*J22*K22 | O22: =(D22+2*'COLECTOR PARAMETROS'!$C$11+0.10)*(E22+2*'COLECTOR PARAMETROS'!$C$11+0.10) | P22: =MAX(0,N22-L22) | Q22: 0 | R22: DP-07 (planta y cortes de la caja), DP-02 (cotas), DA-01
A23: TOTAL CAJAS | M23: =SUM(M21:M22) | N23: =SUM(N21:N22) | O23: =SUM(O21:O22) | P23: =SUM(P21:P22) | Q23: =SUM(Q21:Q22)
A25: RESUMEN PARA LA PLANILLA GENERAL (partidas 01.04.04.01 y 01.04.04.02)
A26: 1 | B26: LIMPIEZA MANUAL DE TERRENO / TRAZO Y REPLANTEO | F26: m2 | G26: =M17 | H26: =M23 | I26: =G26+H26
A27: 2 | B27: EXCAVACION MANUAL DE ZANJAS | F27: m3 | G27: =N17 | H27: =N23 | I27: =G27+H27
A28: 3 | B28: REFINE, NIVELACION Y COMPACTACION | F28: m2 | G28: =O17 | H28: =O23 | I28: =G28+H28
A29: 4 | B29: RELLENO COMPACTADO (lateral + franja + cajas) | F29: m3 | G29: =P17+Q17 | H29: =P23+Q23 | I29: =G29+H29
A30: 5 | B30: ELIMINACION DE MATERIAL EXCEDENTE = (excavacion - relleno) x esponjamiento | F30: m3 | G30: =(I27-I29) | H30: ='COLECTOR PARAMETROS'!$C$25 | I30: =G30*H30
A32: Nota: las prolongaciones de las cunetas de los Ejes 11 y 12 (1.88 y 5.39 m hasta el muro del colector) no forman parte de esta partida; se metran dentro de las partidas de cunetas del proyecto.

Sheet COLECTOR CONCRETO
A1: COLECTOR PLUVIAL FRONTAL - METRADO DE CONCRETO SIMPLE Y ARMADO
A2: ENTIDAD | C2: =+RESUMEN!B4
A3: PROYECTO | C3: =+RESUMEN!B5
A4: UBICACIÓN | C4: =+RESUMEN!B6
A5: FECHA | C5: =+RESUMEN!B7
A7: Criterio (lamina DA-02): SOLADO = (ancho exterior + 0.10) x L. LOSA DE FONDO = ancho exterior x e fondo x L. MUROS = 2 x e muro x h x L. LOSA SUPERIOR = ancho exterior x e losa x L. ACABADO = ancho exterior x L (losa superior frotachada y brunada). CURADO = 2 caras interiores de muros (2 x h x L) + fondo interior (b x L) + losa superior (ancho exterior x L), igual al criterio de la hoja METRADO DE CURADO.
A9: N° | B9: TRAMO | C9: ZONA | D9: LONGITUD (m) | E9: ALTURA INTERIOR h (m) | F9: e LOSA SUP. (m) | G9: ANCHO EXT. (m) | H9: SOLADO f'c=100 (m2) | I9: LOSA DE FONDO (m3) | J9: MUROS (m3) | K9: LOSA SUPERIOR (m3) | L9: ACABADO DE LOSA SUP. (m2) | M9: CURADO (m2) | N9: SUSTENTO
A10: 1 | B10: tramo normal | C10: NORMAL | D10: ='COLECTOR MOV. TIERRAS'!F10 | E10: ='COLECTOR MOV. TIERRAS'!G10 | F10: ='COLECTOR MOV. TIERRAS'!H10 | G10: ='COLECTOR MOV. TIERRAS'!I10 | H10: =(G10+0.10)*D10 | I10: =G10*'COLECTOR PARAMETROS'!$C$12*D10 | J10: =2*'COLECTOR PARAMETROS'!$C$11*E10*D10 | K10: =G10*F10*D10 | L10: =G10*D10 | M10: =(2*E10+'COLECTOR PARAMETROS'!$C$10+G10)*D10 | N10: DP-04 (secciones A, B, C), DP-02 (h por tramo), DA-02 (areas por metro)
A11: 2 | B11: cruce de camiones | C11: CAMION | D11: ='COLECTOR MOV. TIERRAS'!F11 | E11: ='COLECTOR MOV. TIERRAS'!G11 | F11: ='COLECTOR MOV. TIERRAS'!H11 | G11: ='COLECTOR MOV. TIERRAS'!I11 | H11: =(G11+0.10)*D11 | I11: =G11*'COLECTOR PARAMETROS'!$C$12*D11 | J11: =2*'COLECTOR PARAMETROS'!$C$11*E11*D11 | K11: =G11*F11*D11 | L11: =G11*D11 | M11: =(2*E11+'COLECTOR PARAMETROS'!$C$10+G11)*D11 | N11: DP-04 (secciones A, B, C), DP-02 (h por tramo), DA-02 (areas por metro)
A12: 3 | B12: tramo normal | C12: NORMAL | D12: ='COLECTOR MOV. TIERRAS'!F12 | E12: ='COLECTOR MOV. TIERRAS'!G12 | F12: ='COLECTOR MOV. TIERRAS'!H12 | G12: ='COLECTOR MOV. TIERRAS'!I12 | H12: =(G12+0.10)*D12 | I12: =G12*'COLECTOR PARAMETROS'!$C$12*D12 | J12: =2*'COLECTOR PARAMETROS'!$C$11*E12*D12 | K12: =G12*F12*D12 | L12: =G12*D12 | M12: =(2*E12+'COLECTOR PARAMETROS'!$C$10+G12)*D12 | N12: DP-04 (secciones A, B, C), DP-02 (h por tramo), DA-02 (areas por metro)
A13: 4 | B13: cruce de motos | C13: MOTOS | D13: ='COLECTOR MOV. TIERRAS'!F13 | E13: ='COLECTOR MOV. TIERRAS'!G13 | F13: ='COLECTOR MOV. TIERRAS'!H13 | G13: ='COLECTOR MOV. TIERRAS'!I13 | H13: =(G13+0.10)*D13 | I13: =G13*'COLECTOR PARAMETROS'!$C$12*D13 | J13: =2*'COLECTOR PARAMETROS'!$C$11*E13*D13 | K13: =G13*F13*D13 | L13: =G13*D13 | M13: =(2*E13+'COLECTOR PARAMETROS'!$C$10+G13)*D13 | N13: DP-04 (secciones A, B, C), DP-02 (h por tramo), DA-02 (areas por metro)
A14: 5 | B14: tramo normal | C14: NORMAL | D14: ='COLECTOR MOV. TIERRAS'!F14 | E14: ='COLECTOR MOV. TIERRAS'!G14 | F14: ='COLECTOR MOV. TIERRAS'!H14 | G14: ='COLECTOR MOV. TIERRAS'!I14 | H14: =(G14+0.10)*D14 | I14: =G14*'COLECTOR PARAMETROS'!$C$12*D14 | J14: =2*'COLECTOR PARAMETROS'!$C$11*E14*D14 | K14: =G14*F14*D14 | L14: =G14*D14 | M14: =(2*E14+'COLECTOR PARAMETROS'!$C$10+G14)*D14 | N14: DP-04 (secciones A, B, C), DP-02 (h por tramo), DA-02 (areas por metro)
A15: 6 | B15: tramo diagonal (quiebres) | C15: NORMAL | D15: ='COLECTOR MOV. TIERRAS'!F15 | E15: ='COLECTOR MOV. TIERRAS'!G15 | F15: ='COLECTOR MOV. TIERRAS'!H15 | G15: ='COLECTOR MOV. TIERRAS'!I15 | H15: =(G15+0.10)*D15 | I15: =G15*'COLECTOR PARAMETROS'!$C$12*D15 | J15: =2*'COLECTOR PARAMETROS'!$C$11*E15*D15 | K15: =G15*F15*D15 | L15: =G15*D15 | M15: =(2*E15+'COLECTOR PARAMETROS'!$C$10+G15)*D15 | N15: DP-04 (secciones A, B, C), DP-02 (h por tramo), DA-02 (areas por metro)
A16: 7 | B16: tramo recto final | C16: NORMAL | D16: ='COLECTOR MOV. TIERRAS'!F16 | E16: ='COLECTOR MOV. TIERRAS'!G16 | F16: ='COLECTOR MOV. TIERRAS'!H16 | G16: ='COLECTOR MOV. TIERRAS'!I16 | H16: =(G16+0.10)*D16 | I16: =G16*'COLECTOR PARAMETROS'!$C$12*D16 | J16: =2*'COLECTOR PARAMETROS'!$C$11*E16*D16 | K16: =G16*F16*D16 | L16: =G16*D16 | M16: =(2*E16+'COLECTOR PARAMETROS'!$C$10+G16)*D16 | N16: DP-04 (secciones A, B, C), DP-02 (h por tramo), DA-02 (areas por metro)
A17: TOTAL COLECTOR (tramos) | D17: =SUM(D10:D16) | H17: =SUM(H10:H16) | I17: =SUM(I10:I16) | J17: =SUM(J10:J16) | K17: =SUM(K10:K16) | L17: =SUM(L10:L16) | M17: =SUM(M10:M16)
A19: CAJAS CL Y CC POR ELEMENTO - lamina DP-07 (dimensiones interiores de la hoja COLECTOR MOV. TIERRAS; e muro = e fondo = 0.15; losa superior e = 0.10)
A20: N° | B20: CAJA / ELEMENTO | C20: DETALLE | D20: LARGO (m) | E20: ANCHO (m) | F20: ALTO / ESPESOR (m) | G20: VECES | H20: SOLADO (m2) | I20: LOSA DE FONDO (m3) | J20: MUROS (m3) | K20: LOSA SUPERIOR (m3) | L20: ACABADO (m2) | M20: CURADO (m2) | N20: SUSTENTO
B21: Caja de llegada CL: solado | C21: fondo + 0.05/lado | D21: ='COLECTOR MOV. TIERRAS'!D21+2*'COLECTOR PARAMETROS'!$C$11+0.10 | E21: ='COLECTOR MOV. TIERRAS'!E21+2*'COLECTOR PARAMETROS'!$C$11+0.10 | F21: 1 | G21: 1 | H21: =D21*E21 | N21: DP-07: solado f'c=100 e=0.05 bajo la losa de fondo
B22: Caja de llegada CL: losa de fondo | C22: exterior x e | D22: ='COLECTOR MOV. TIERRAS'!D21+2*'COLECTOR PARAMETROS'!$C$11 | E22: ='COLECTOR MOV. TIERRAS'!E21+2*'COLECTOR PARAMETROS'!$C$11 | F22: ='COLECTOR PARAMETROS'!$C$12 | G22: 1 | I22: =D22*E22*F22*G22 | N22: DP-07: losa de fondo e=0.15 (ancho exterior)
B23: Caja de llegada CL: muros largos | C23: exterior x e x H | D23: ='COLECTOR MOV. TIERRAS'!D21+2*'COLECTOR PARAMETROS'!$C$11 | E23: ='COLECTOR PARAMETROS'!$C$11 | F23: ='COLECTOR MOV. TIERRAS'!F21 | G23: 2 | J23: =D23*E23*F23*G23 | N23: DP-07: dos muros largos de e=0.15, altura interior H
B24: Caja de llegada CL: muros cortos | C24: interior x e x H | D24: ='COLECTOR MOV. TIERRAS'!E21 | E24: ='COLECTOR PARAMETROS'!$C$11 | F24: ='COLECTOR MOV. TIERRAS'!F21 | G24: 2 | J24: =D24*E24*F24*G24 | N24: DP-07: dos muros de cierre de e=0.15
B25: Caja de llegada CL: descuento ventana de llegada | C25: ancho x alto x e | D25: ='COLECTOR PARAMETROS'!$C$48 | E25: ='COLECTOR PARAMETROS'!$C$11 | F25: ='COLECTOR PARAMETROS'!$C$16-'COLECTOR PARAMETROS'!$C$13-'COLECTOR PARAMETROS'!$C$47 | G25: -1 | J25: =D25*E25*F25*G25 | N25: DP-07 (corte): ventana del colector de CAR Varones hasta la losa
B26: Caja de llegada CL: murete del escalon de la poza | C26: ancho x e x desnivel | D26: ='COLECTOR MOV. TIERRAS'!E21 | E26: ='COLECTOR PARAMETROS'!$C$11 | F26: ='COLECTOR PARAMETROS'!$C$46 | G26: 1 | J26: =D26*E26*F26*G26 | N26: DP-07 (corte): murete e=0.15 entre el fondo del colector y el piso de la poza
B27: Caja de llegada CL: losa superior | C27: exterior x e | D27: ='COLECTOR MOV. TIERRAS'!D21+2*'COLECTOR PARAMETROS'!$C$11 | E27: ='COLECTOR MOV. TIERRAS'!E21+2*'COLECTOR PARAMETROS'!$C$11 | F27: ='COLECTOR PARAMETROS'!$C$13 | G27: 1 | K27: =D27*E27*F27*G27 | N27: DP-07: losa superior e=0.10 a nivel del piso terminado
B28: Caja de llegada CL: descuento aberturas de registro | C28: 0.70 x 0.70 x e | D28: ='COLECTOR PARAMETROS'!$C$35 | E28: ='COLECTOR PARAMETROS'!$C$35 | F28: ='COLECTOR PARAMETROS'!$C$13 | G28: -1 | K28: =D28*E28*F28*G28 | N28: DP-06B: 1 abertura(s) de registro en la losa
B29: Caja de llegada CL: acabado de losa superior | C29: exterior | D29: ='COLECTOR MOV. TIERRAS'!D21+2*'COLECTOR PARAMETROS'!$C$11 | E29: ='COLECTOR MOV. TIERRAS'!E21+2*'COLECTOR PARAMETROS'!$C$11 | F29: 1 | G29: 1 | L29: =D29*E29 | N29: DP-07: losa superior frotachada y brunada
B30: Caja de llegada CL: curado | C30: caras int. + fondo + losa | D30: =2*('COLECTOR MOV. TIERRAS'!D21+'COLECTOR MOV. TIERRAS'!E21) | E30: ='COLECTOR MOV. TIERRAS'!F21 | F30: 1 | G30: 1 | M30: =D30*E30+'COLECTOR MOV. TIERRAS'!D21*'COLECTOR MOV. TIERRAS'!E21+('COLECTOR MOV. TIERRAS'!D21+2*'COLECTOR PARAMETROS'!$C$11)*('COLECTOR MOV. TIERRAS'!E21+2*'COLECTOR PARAMETROS'!$C$11) | N30: Caras interiores de muros (perimetro x H) + fondo interior + losa superior
B31: Caja de caida CC: solado | C31: fondo + 0.05/lado | D31: ='COLECTOR MOV. TIERRAS'!D22+2*'COLECTOR PARAMETROS'!$C$11+0.10 | E31: ='COLECTOR MOV. TIERRAS'!E22+2*'COLECTOR PARAMETROS'!$C$11+0.10 | F31: 1 | G31: 1 | H31: =D31*E31 | N31: DP-07: solado f'c=100 e=0.05 bajo la losa de fondo
B32: Caja de caida CC: losa de fondo | C32: exterior x e | D32: ='COLECTOR MOV. TIERRAS'!D22+2*'COLECTOR PARAMETROS'!$C$11 | E32: ='COLECTOR MOV. TIERRAS'!E22+2*'COLECTOR PARAMETROS'!$C$11 | F32: ='COLECTOR PARAMETROS'!$C$12 | G32: 1 | I32: =D32*E32*F32*G32 | N32: DP-07: losa de fondo e=0.15 (ancho exterior)
B33: Caja de caida CC: umbral de la poza | C33: 0.25 x 0.40 | D33: ='COLECTOR MOV. TIERRAS'!E22 | E33: ='COLECTOR PARAMETROS'!$C$56 | F33: ='COLECTOR PARAMETROS'!$C$57 | G33: 1 | I33: =D33*E33*F33*G33 | N33: DP-07: umbral 0.25 x 0.40 en el fondo, borde de la poza
B34: Caja de caida CC: muros largos | C34: exterior x e x H | D34: ='COLECTOR MOV. TIERRAS'!D22+2*'COLECTOR PARAMETROS'!$C$11 | E34: ='COLECTOR PARAMETROS'!$C$11 | F34: ='COLECTOR MOV. TIERRAS'!F22 | G34: 2 | J34: =D34*E34*F34*G34 | N34: DP-07: dos muros largos de e=0.15, altura interior H
B35: Caja de caida CC: muros cortos | C35: interior x e x H | D35: ='COLECTOR MOV. TIERRAS'!E22 | E35: ='COLECTOR PARAMETROS'!$C$11 | F35: ='COLECTOR MOV. TIERRAS'!F22 | G35: 1 | J35: =D35*E35*F35*G35 | N35: DP-07: muro(s) de cierre; en CC el lado de llegada lo cierra el colector
B36: Caja de caida CC: descuento ventana de salida | C36: ancho x alto x e | D36: ='COLECTOR PARAMETROS'!$C$55 | E36: ='COLECTOR PARAMETROS'!$C$11 | F36: ='COLECTOR PARAMETROS'!$C$53+0.50-'COLECTOR PARAMETROS'!$C$52 | G36: -1 | J36: =D36*E36*F36*G36 | N36: DP-07 (corte): ventana de salida al receptor R-01 (0.50 m sobre el nivel de agua)
B37: Caja de caida CC: murete del escalon de la poza | C37: ancho x e x desnivel | D37: ='COLECTOR MOV. TIERRAS'!E22 | E37: ='COLECTOR PARAMETROS'!$C$11 | F37: ='COLECTOR PARAMETROS'!$C$54-('COLECTOR PARAMETROS'!$C$52-'COLECTOR PARAMETROS'!$C$51) | G37: 1 | J37: =D37*E37*F37*G37 | N37: DP-07 (corte): murete e=0.15 entre el fondo del colector y el piso de la poza
B38: Caja de caida CC: losa superior | C38: exterior x e | D38: ='COLECTOR MOV. TIERRAS'!D22+2*'COLECTOR PARAMETROS'!$C$11 | E38: ='COLECTOR MOV. TIERRAS'!E22+2*'COLECTOR PARAMETROS'!$C$11 | F38: ='COLECTOR PARAMETROS'!$C$13 | G38: 1 | K38: =D38*E38*F38*G38 | N38: DP-07: losa superior e=0.10 a nivel del piso terminado
B39: Caja de caida CC: descuento aberturas de registro | C39: 0.70 x 0.70 x e | D39: ='COLECTOR PARAMETROS'!$C$35 | E39: ='COLECTOR PARAMETROS'!$C$35 | F39: ='COLECTOR PARAMETROS'!$C$13 | G39: -2 | K39: =D39*E39*F39*G39 | N39: DP-06B: 2 abertura(s) de registro en la losa
B40: Caja de caida CC: acabado de losa superior | C40: exterior | D40: ='COLECTOR MOV. TIERRAS'!D22+2*'COLECTOR PARAMETROS'!$C$11 | E40: ='COLECTOR MOV. TIERRAS'!E22+2*'COLECTOR PARAMETROS'!$C$11 | F40: 1 | G40: 1 | L40: =D40*E40 | N40: DP-07: losa superior frotachada y brunada
B41: Caja de caida CC: curado | C41: caras int. + fondo + losa | D41: =2*('COLECTOR MOV. TIERRAS'!D22+'COLECTOR MOV. TIERRAS'!E22) | E41: ='COLECTOR MOV. TIERRAS'!F22 | F41: 1 | G41: 1 | M41: =D41*E41+'COLECTOR MOV. TIERRAS'!D22*'COLECTOR MOV. TIERRAS'!E22+('COLECTOR MOV. TIERRAS'!D22+2*'COLECTOR PARAMETROS'!$C$11)*('COLECTOR MOV. TIERRAS'!E22+2*'COLECTOR PARAMETROS'!$C$11) | N41: Caras interiores de muros (perimetro x H) + fondo interior + losa superior
A42: REGISTROS DE LIMPIEZA EN LA LOSA DEL COLECTOR - lamina DP-06B (borde engrosado 0.15 x 0.10 alrededor de la abertura; descuento de la abertura 0.70 x 0.70 en la losa superior)
B43: Registros: borde engrosado de la abertura | C43: perimetro x seccion | D43: ='COLECTOR PARAMETROS'!$C$42 | E43: ='COLECTOR PARAMETROS'!$C$43 | F43: 1 | G43: ='COLECTOR PARAMETROS'!$C$32 | K43: =D43*E43*F43*G43 | N43: DP-06B: borde engrosado en los 10 registros (7 en la losa del colector, 1 en CL y 2 en CC)
B44: Registros RS-01 a RS-07: descuento de la abertura en la losa superior | C44: 0.70 x 0.70 x e | D44: ='COLECTOR PARAMETROS'!$C$35 | E44: ='COLECTOR PARAMETROS'!$C$35 | F44: ='COLECTOR PARAMETROS'!$C$13 | G44: =-('COLECTOR PARAMETROS'!$C$32-3) | K44: =D44*E44*F44*G44 | N44: DP-06B
A45: TOTAL CAJAS Y REGISTROS | H45: =SUM(H21:H44) | I45: =SUM(I21:I44) | J45: =SUM(J21:J44) | K45: =SUM(K21:K44) | L45: =SUM(L21:L44) | M45: =SUM(M21:M44)
A47: RESUMEN PARA LA PLANILLA GENERAL (partidas 01.04.04.03 y 01.04.04.04)
A48: 1 | B48: CONCRETO f'c=100 PARA SOLADO e=0.05 | F48: m2 | G48: =H17 | H48: =H45 | I48: =G48+H48
A49: 2 | B49: CONCRETO f'c=210 EN LOSA DE FONDO | F49: m3 | G49: =I17 | H49: =I45 | I49: =G49+H49
A50: 3 | B50: CONCRETO f'c=210 EN MUROS | F50: m3 | G50: =J17 | H50: =J45 | I50: =G50+H50
A51: 4 | B51: CONCRETO f'c=210 EN LOSA SUPERIOR | F51: m3 | G51: =K17 | H51: =K45 | I51: =G51+H51
A52: 5 | B52: ACABADO FROTACHADO Y BRUÑADO DE LOSA SUPERIOR | F52: m2 | G52: =L17 | H52: =L45 | I52: =G52+H52
A53: 6 | B53: CURADO DE CONCRETO | F53: m2 | G53: =M17 | H53: =M45 | I53: =G53+H53

Sheet COLECTOR ENCOFRADO
A1: COLECTOR PLUVIAL FRONTAL - METRADO DE ENCOFRADO Y DESENCOFRADO
A2: ENTIDAD | C2: =+RESUMEN!B4
A3: PROYECTO | C3: =+RESUMEN!B5
A4: UBICACIÓN | C4: =+RESUMEN!B6
A5: FECHA | C5: =+RESUMEN!B7
A7: Criterio (lamina DA-02): se encofran las dos caras interiores de los muros, las dos caras exteriores en toda la altura del cajon (losa de fondo + muro + losa superior) y el fondo de la losa superior (ancho interior b). La losa de fondo se vacia sobre el solado y la cara superior de la losa queda libre (acabado).
A9: N° | B9: TRAMO | C9: ZONA | D9: LONGITUD (m) | E9: ALTURA INTERIOR h (m) | F9: e LOSA SUP. (m) | G9: ANCHO INT. b (m) | H9: CARAS INTERIORES DE MUROS 2 x h x L (m2) | I9: CARAS EXTERIORES 2 x (e fondo + h + e losa) x L (m2) | J9: FONDO DE LOSA SUPERIOR b x L (m2) | K9: TOTAL ENCOFRADO (m2) | L9: SUSTENTO
A10: 1 | B10: tramo normal | C10: NORMAL | D10: ='COLECTOR MOV. TIERRAS'!F10 | E10: ='COLECTOR MOV. TIERRAS'!G10 | F10: ='COLECTOR MOV. TIERRAS'!H10 | G10: ='COLECTOR PARAMETROS'!$C$10 | H10: =2*E10*D10 | I10: =2*('COLECTOR PARAMETROS'!$C$12+E10+F10)*D10 | J10: =G10*D10 | K10: =SUM(H10:J10) | L10: DP-04 (secciones), DA-02 (areas por metro)
A11: 2 | B11: cruce de camiones | C11: CAMION | D11: ='COLECTOR MOV. TIERRAS'!F11 | E11: ='COLECTOR MOV. TIERRAS'!G11 | F11: ='COLECTOR MOV. TIERRAS'!H11 | G11: ='COLECTOR PARAMETROS'!$C$10 | H11: =2*E11*D11 | I11: =2*('COLECTOR PARAMETROS'!$C$12+E11+F11)*D11 | J11: =G11*D11 | K11: =SUM(H11:J11) | L11: DP-04 (secciones), DA-02 (areas por metro)
A12: 3 | B12: tramo normal | C12: NORMAL | D12: ='COLECTOR MOV. TIERRAS'!F12 | E12: ='COLECTOR MOV. TIERRAS'!G12 | F12: ='COLECTOR MOV. TIERRAS'!H12 | G12: ='COLECTOR PARAMETROS'!$C$10 | H12: =2*E12*D12 | I12: =2*('COLECTOR PARAMETROS'!$C$12+E12+F12)*D12 | J12: =G12*D12 | K12: =SUM(H12:J12) | L12: DP-04 (secciones), DA-02 (areas por metro)
A13: 4 | B13: cruce de motos | C13: MOTOS | D13: ='COLECTOR MOV. TIERRAS'!F13 | E13: ='COLECTOR MOV. TIERRAS'!G13 | F13: ='COLECTOR MOV. TIERRAS'!H13 | G13: ='COLECTOR PARAMETROS'!$C$10 | H13: =2*E13*D13 | I13: =2*('COLECTOR PARAMETROS'!$C$12+E13+F13)*D13 | J13: =G13*D13 | K13: =SUM(H13:J13) | L13: DP-04 (secciones), DA-02 (areas por metro)
A14: 5 | B14: tramo normal | C14: NORMAL | D14: ='COLECTOR MOV. TIERRAS'!F14 | E14: ='COLECTOR MOV. TIERRAS'!G14 | F14: ='COLECTOR MOV. TIERRAS'!H14 | G14: ='COLECTOR PARAMETROS'!$C$10 | H14: =2*E14*D14 | I14: =2*('COLECTOR PARAMETROS'!$C$12+E14+F14)*D14 | J14: =G14*D14 | K14: =SUM(H14:J14) | L14: DP-04 (secciones), DA-02 (areas por metro)
A15: 6 | B15: tramo diagonal (quiebres) | C15: NORMAL | D15: ='COLECTOR MOV. TIERRAS'!F15 | E15: ='COLECTOR MOV. TIERRAS'!G15 | F15: ='COLECTOR MOV. TIERRAS'!H15 | G15: ='COLECTOR PARAMETROS'!$C$10 | H15: =2*E15*D15 | I15: =2*('COLECTOR PARAMETROS'!$C$12+E15+F15)*D15 | J15: =G15*D15 | K15: =SUM(H15:J15) | L15: DP-04 (secciones), DA-02 (areas por metro)
A16: 7 | B16: tramo recto final | C16: NORMAL | D16: ='COLECTOR MOV. TIERRAS'!F16 | E16: ='COLECTOR MOV. TIERRAS'!G16 | F16: ='COLECTOR MOV. TIERRAS'!H16 | G16: ='COLECTOR PARAMETROS'!$C$10 | H16: =2*E16*D16 | I16: =2*('COLECTOR PARAMETROS'!$C$12+E16+F16)*D16 | J16: =G16*D16 | K16: =SUM(H16:J16) | L16: DP-04 (secciones), DA-02 (areas por metro)
A17: TOTAL COLECTOR (tramos) | D17: =SUM(D10:D16) | H17: =SUM(H10:H16) | I17: =SUM(I10:I16) | J17: =SUM(J10:J16) | K17: =SUM(K10:K16)
A19: CAJAS CL Y CC - lamina DP-07: caras interiores y exteriores de muros (perimetro x H, dos caras), fondo de la losa superior (interior) y, en CC, caras del umbral y del murete de la poza
A20: N° | B20: CAJA / ELEMENTO | C20: DETALLE | D20: LARGO (m) | E20: ALTO (m) | F20: CARAS | K20: AREA (m2) | L20: SUSTENTO
B21: Caja de llegada CL: muros, cara interior y exterior | C21: perimetro int. x H | D21: =2*('COLECTOR MOV. TIERRAS'!D21+'COLECTOR MOV. TIERRAS'!E21) | E21: ='COLECTOR MOV. TIERRAS'!F21 | F21: 2 | K21: =D21*E21*F21 | L21: DP-07: muros e=0.15 encofrados por ambas caras
B22: Caja de llegada CL: fondo de la losa superior | C22: interior | D22: ='COLECTOR MOV. TIERRAS'!D21 | E22: ='COLECTOR MOV. TIERRAS'!E21 | F22: 1 | K22: =D22*E22*F22 | L22: DP-07: losa superior e=0.10 encofrada por debajo
B23: Caja de llegada CL: cara del murete de la poza | C23: ancho x desnivel | D23: ='COLECTOR MOV. TIERRAS'!E21 | E23: ='COLECTOR PARAMETROS'!$C$46 | F23: 1 | K23: =D23*E23*F23 | L23: DP-07 (corte): murete entre el fondo del colector y el piso de la poza
B24: Caja de caida CC: muros, cara interior y exterior | C24: perimetro int. x H | D24: =2*('COLECTOR MOV. TIERRAS'!D22+'COLECTOR MOV. TIERRAS'!E22) | E24: ='COLECTOR MOV. TIERRAS'!F22 | F24: 2 | K24: =D24*E24*F24 | L24: DP-07: muros e=0.15 encofrados por ambas caras
B25: Caja de caida CC: fondo de la losa superior | C25: interior | D25: ='COLECTOR MOV. TIERRAS'!D22 | E25: ='COLECTOR MOV. TIERRAS'!E22 | F25: 1 | K25: =D25*E25*F25 | L25: DP-07: losa superior e=0.10 encofrada por debajo
B26: Caja de caida CC: caras del umbral de la poza | C26: 2 caras x ancho | D26: ='COLECTOR MOV. TIERRAS'!E22 | E26: ='COLECTOR PARAMETROS'!$C$57 | F26: 2 | K26: =D26*E26*F26 | L26: DP-07: umbral 0.25 x 0.40
B27: Caja de caida CC: cara del murete de la poza | C27: ancho x desnivel | D27: ='COLECTOR MOV. TIERRAS'!E22 | E27: ='COLECTOR PARAMETROS'!$C$54-('COLECTOR PARAMETROS'!$C$52-'COLECTOR PARAMETROS'!$C$51) | F27: 1 | K27: =D27*E27*F27 | L27: DP-07 (corte): murete entre el fondo del colector y el piso de la poza
A28: TOTAL CAJAS | K28: =SUM(K21:K27)
A30: RESUMEN PARA LA PLANILLA GENERAL (partida 01.04.04.04.04)
A31: 1 | B31: ENCOFRADO Y DESENCOFRADO NORMAL EN COLECTOR Y CAJAS | F31: m2 | G31: =K17 | H31: =K28 | I31: =G31+H31

Sheet COLECTOR ACERO
A1: COLECTOR PLUVIAL FRONTAL - METRADO DE ACERO DE REFUERZO fy=4200 kg/cm2
A2: ENTIDAD | C2: =+RESUMEN!B4
A3: PROYECTO | C3: =+RESUMEN!B5
A4: UBICACIÓN | C4: =+RESUMEN!B6
A5: FECHA | C5: =+RESUMEN!B7
A7: Criterio (laminas DP-04 y DP-08, norma E.060 14.3.4): tramo normal y cruce de motos llevan un solo marco cerrado en el eje de muros y losas (perimetro = 2 x (ancho ext. - e) + 2 x (e fondo/2 + h + e losa/2) + ganchos); el cruce de camiones lleva marco exterior + marco interior de 1/2" (perimetros con recubrimiento 0.04). Barras longitudinales 3/8" en cada marco, con traslape de 0.40 cada 9.00 m. Peso: 3/8" = 0.56 kg/m, 1/2" = 0.994 kg/m.
A9: N° | B9: TRAMO | C9: ZONA | D9: LONGITUD (m) | E9: ALTURA INTERIOR h (m) | F9: e LOSA SUP. (m) | G9: ANCHO EXT. (m) | H9: ESPAC. MARCOS s (m) | I9: CAPAS (1 = marco unico; 2 = ext. + int.) | J9: DIAM. MARCOS | K9: N° DE JUEGOS (L / s, redondeado arriba) | L9: PERIMETRO MARCO 1 (m) | M9: PERIMETRO MARCO 2 (m) | N9: LONGITUD DE MARCOS (m) | O9: PESO (kg/m) | P9: ACERO EN MARCOS (kg) | Q9: ESPAC. LONGIT. (m) | R9: N° BARRAS LONGIT. (perimetro / espac.) | S9: LONGITUD LONGIT. CON TRASLAPE (m) | T9: ACERO LONGIT. 3/8" (kg) | U9: TOTAL (kg) | V9: SUSTENTO
A10: 1 | B10: tramo normal | C10: NORMAL | D10: ='COLECTOR MOV. TIERRAS'!F10 | E10: ='COLECTOR MOV. TIERRAS'!G10 | F10: ='COLECTOR MOV. TIERRAS'!H10 | G10: ='COLECTOR MOV. TIERRAS'!I10 | H10: ='COLECTOR PARAMETROS'!$C$26 | I10: 1 | J10: 3/8" | K10: =ROUNDUP(D10/H10,0) | L10: =IF(I10=2,2*(G10-2*'COLECTOR PARAMETROS'!$C$19)+2*('COLECTOR PARAMETROS'!$C$12+E10+F10-2*'COLECTOR PARAMETROS'!$C$19)+'COLECTOR PARAMETROS'!$C$24,2*(G10-'COLECTOR PARAMETROS'!$C$11)+2*('COLECTOR PARAMETROS'!$C$12/2+E10+F10/2)+'COLECTOR PARAMETROS'!$C$24) | M10: =IF(I10=2,2*('COLECTOR PARAMETROS'!$C$10+2*('COLECTOR PARAMETROS'!$C$11-'COLECTOR PARAMETROS'!$C$19))+2*(E10+2*('COLECTOR PARAMETROS'!$C$11-'COLECTOR PARAMETROS'!$C$19))+'COLECTOR PARAMETROS'!$C$24,0) | N10: =K10*(L10+M10) | O10: =IF(J10="1/2""",'COLECTOR PARAMETROS'!$C$21,'COLECTOR PARAMETROS'!$C$20) | P10: =N10*O10 | Q10: ='COLECTOR PARAMETROS'!$C$28 | R10: =ROUND(L10/Q10,0)+IF(M10>0,ROUND(M10/Q10,0),0) | S10: =R10*D10*(1+'COLECTOR PARAMETROS'!$C$22/'COLECTOR PARAMETROS'!$C$23) | T10: =S10*'COLECTOR PARAMETROS'!$C$20 | U10: =P10+T10 | V10: DP-04 (seccion A), DP-08 (cuadro de doblado), DA-03
A11: 2 | B11: cruce de camiones | C11: CAMION | D11: ='COLECTOR MOV. TIERRAS'!F11 | E11: ='COLECTOR MOV. TIERRAS'!G11 | F11: ='COLECTOR MOV. TIERRAS'!H11 | G11: ='COLECTOR MOV. TIERRAS'!I11 | H11: ='COLECTOR PARAMETROS'!$C$27 | I11: 2 | J11: 1/2" | K11: =ROUNDUP(D11/H11,0) | L11: =IF(I11=2,2*(G11-2*'COLECTOR PARAMETROS'!$C$19)+2*('COLECTOR PARAMETROS'!$C$12+E11+F11-2*'COLECTOR PARAMETROS'!$C$19)+'COLECTOR PARAMETROS'!$C$24,2*(G11-'COLECTOR PARAMETROS'!$C$11)+2*('COLECTOR PARAMETROS'!$C$12/2+E11+F11/2)+'COLECTOR PARAMETROS'!$C$24) | M11: =IF(I11=2,2*('COLECTOR PARAMETROS'!$C$10+2*('COLECTOR PARAMETROS'!$C$11-'COLECTOR PARAMETROS'!$C$19))+2*(E11+2*('COLECTOR PARAMETROS'!$C$11-'COLECTOR PARAMETROS'!$C$19))+'COLECTOR PARAMETROS'!$C$24,0) | N11: =K11*(L11+M11) | O11: =IF(J11="1/2""",'COLECTOR PARAMETROS'!$C$21,'COLECTOR PARAMETROS'!$C$20) | P11: =N11*O11 | Q11: ='COLECTOR PARAMETROS'!$C$29 | R11: =ROUND(L11/Q11,0)+IF(M11>0,ROUND(M11/Q11,0),0) | S11: =R11*D11*(1+'COLECTOR PARAMETROS'!$C$22/'COLECTOR PARAMETROS'!$C$23) | T11: =S11*'COLECTOR PARAMETROS'!$C$20 | U11: =P11+T11 | V11: DP-04 (seccion C), DP-08 (cuadro de doblado), DA-03
A12: 3 | B12: tramo normal | C12: NORMAL | D12: ='COLECTOR MOV. TIERRAS'!F12 | E12: ='COLECTOR MOV. TIERRAS'!G12 | F12: ='COLECTOR MOV. TIERRAS'!H12 | G12: ='COLECTOR MOV. TIERRAS'!I12 | H12: ='COLECTOR PARAMETROS'!$C$26 | I12: 1 | J12: 3/8" | K12: =ROUNDUP(D12/H12,0) | L12: =IF(I12=2,2*(G12-2*'COLECTOR PARAMETROS'!$C$19)+2*('COLECTOR PARAMETROS'!$C$12+E12+F12-2*'COLECTOR PARAMETROS'!$C$19)+'COLECTOR PARAMETROS'!$C$24,2*(G12-'COLECTOR PARAMETROS'!$C$11)+2*('COLECTOR PARAMETROS'!$C$12/2+E12+F12/2)+'COLECTOR PARAMETROS'!$C$24) | M12: =IF(I12=2,2*('COLECTOR PARAMETROS'!$C$10+2*('COLECTOR PARAMETROS'!$C$11-'COLECTOR PARAMETROS'!$C$19))+2*(E12+2*('COLECTOR PARAMETROS'!$C$11-'COLECTOR PARAMETROS'!$C$19))+'COLECTOR PARAMETROS'!$C$24,0) | N12: =K12*(L12+M12) | O12: =IF(J12="1/2""",'COLECTOR PARAMETROS'!$C$21,'COLECTOR PARAMETROS'!$C$20) | P12: =N12*O12 | Q12: ='COLECTOR PARAMETROS'!$C$28 | R12: =ROUND(L12/Q12,0)+IF(M12>0,ROUND(M12/Q12,0),0) | S12: =R12*D12*(1+'COLECTOR PARAMETROS'!$C$22/'COLECTOR PARAMETROS'!$C$23) | T12: =S12*'COLECTOR PARAMETROS'!$C$20 | U12: =P12+T12 | V12: DP-04 (seccion A), DP-08 (cuadro de doblado), DA-03
A13: 4 | B13: cruce de motos | C13: MOTOS | D13: ='COLECTOR MOV. TIERRAS'!F13 | E13: ='COLECTOR MOV. TIERRAS'!G13 | F13: ='COLECTOR MOV. TIERRAS'!H13 | G13: ='COLECTOR MOV. TIERRAS'!I13 | H13: ='COLECTOR PARAMETROS'!$C$27 | I13: 1 | J13: 3/8" | K13: =ROUNDUP(D13/H13,0) | L13: =IF(I13=2,2*(G13-2*'COLECTOR PARAMETROS'!$C$19)+2*('COLECTOR PARAMETROS'!$C$12+E13+F13-2*'COLECTOR PARAMETROS'!$C$19)+'COLECTOR PARAMETROS'!$C$24,2*(G13-'COLECTOR PARAMETROS'!$C$11)+2*('COLECTOR PARAMETROS'!$C$12/2+E13+F13/2)+'COLECTOR PARAMETROS'!$C$24) | M13: =IF(I13=2,2*('COLECTOR PARAMETROS'!$C$10+2*('COLECTOR PARAMETROS'!$C$11-'COLECTOR PARAMETROS'!$C$19))+2*(E13+2*('COLECTOR PARAMETROS'!$C$11-'COLECTOR PARAMETROS'!$C$19))+'COLECTOR PARAMETROS'!$C$24,0) | N13: =K13*(L13+M13) | O13: =IF(J13="1/2""",'COLECTOR PARAMETROS'!$C$21,'COLECTOR PARAMETROS'!$C$20) | P13: =N13*O13 | Q13: ='COLECTOR PARAMETROS'!$C$28 | R13: =ROUND(L13/Q13,0)+IF(M13>0,ROUND(M13/Q13,0),0) | S13: =R13*D13*(1+'COLECTOR PARAMETROS'!$C$22/'COLECTOR PARAMETROS'!$C$23) | T13: =S13*'COLECTOR PARAMETROS'!$C$20 | U13: =P13+T13 | V13: DP-04 (seccion B), DP-08 (cuadro de doblado), DA-03
A14: 5 | B14: tramo normal | C14: NORMAL | D14: ='COLECTOR MOV. TIERRAS'!F14 | E14: ='COLECTOR MOV. TIERRAS'!G14 | F14: ='COLECTOR MOV. TIERRAS'!H14 | G14: ='COLECTOR MOV. TIERRAS'!I14 | H14: ='COLECTOR PARAMETROS'!$C$26 | I14: 1 | J14: 3/8" | K14: =ROUNDUP(D14/H14,0) | L14: =IF(I14=2,2*(G14-2*'COLECTOR PARAMETROS'!$C$19)+2*('COLECTOR PARAMETROS'!$C$12+E14+F14-2*'COLECTOR PARAMETROS'!$C$19)+'COLECTOR PARAMETROS'!$C$24,2*(G14-'COLECTOR PARAMETROS'!$C$11)+2*('COLECTOR PARAMETROS'!$C$12/2+E14+F14/2)+'COLECTOR PARAMETROS'!$C$24) | M14: =IF(I14=2,2*('COLECTOR PARAMETROS'!$C$10+2*('COLECTOR PARAMETROS'!$C$11-'COLECTOR PARAMETROS'!$C$19))+2*(E14+2*('COLECTOR PARAMETROS'!$C$11-'COLECTOR PARAMETROS'!$C$19))+'COLECTOR PARAMETROS'!$C$24,0) | N14: =K14*(L14+M14) | O14: =IF(J14="1/2""",'COLECTOR PARAMETROS'!$C$21,'COLECTOR PARAMETROS'!$C$20) | P14: =N14*O14 | Q14: ='COLECTOR PARAMETROS'!$C$28 | R14: =ROUND(L14/Q14,0)+IF(M14>0,ROUND(M14/Q14,0),0) | S14: =R14*D14*(1+'COLECTOR PARAMETROS'!$C$22/'COLECTOR PARAMETROS'!$C$23) | T14: =S14*'COLECTOR PARAMETROS'!$C$20 | U14: =P14+T14 | V14: DP-04 (seccion A), DP-08 (cuadro de doblado), DA-03
A15: 6 | B15: tramo diagonal (quiebres) | C15: NORMAL | D15: ='COLECTOR MOV. TIERRAS'!F15 | E15: ='COLECTOR MOV. TIERRAS'!G15 | F15: ='COLECTOR MOV. TIERRAS'!H15 | G15: ='COLECTOR MOV. TIERRAS'!I15 | H15: ='COLECTOR PARAMETROS'!$C$26 | I15: 1 | J15: 3/8" | K15: =ROUNDUP(D15/H15,0) | L15: =IF(I15=2,2*(G15-2*'COLECTOR PARAMETROS'!$C$19)+2*('COLECTOR PARAMETROS'!$C$12+E15+F15-2*'COLECTOR PARAMETROS'!$C$19)+'COLECTOR PARAMETROS'!$C$24,2*(G15-'COLECTOR PARAMETROS'!$C$11)+2*('COLECTOR PARAMETROS'!$C$12/2+E15+F15/2)+'COLECTOR PARAMETROS'!$C$24) | M15: =IF(I15=2,2*('COLECTOR PARAMETROS'!$C$10+2*('COLECTOR PARAMETROS'!$C$11-'COLECTOR PARAMETROS'!$C$19))+2*(E15+2*('COLECTOR PARAMETROS'!$C$11-'COLECTOR PARAMETROS'!$C$19))+'COLECTOR PARAMETROS'!$C$24,0) | N15: =K15*(L15+M15) | O15: =IF(J15="1/2""",'COLECTOR PARAMETROS'!$C$21,'COLECTOR PARAMETROS'!$C$20) | P15: =N15*O15 | Q15: ='COLECTOR PARAMETROS'!$C$28 | R15: =ROUND(L15/Q15,0)+IF(M15>0,ROUND(M15/Q15,0),0) | S15: =R15*D15*(1+'COLECTOR PARAMETROS'!$C$22/'COLECTOR PARAMETROS'!$C$23) | T15: =S15*'COLECTOR PARAMETROS'!$C$20 | U15: =P15+T15 | V15: DP-04 (seccion A), DP-08 (cuadro de doblado), DA-03
A16: 7 | B16: tramo recto final | C16: NORMAL | D16: ='COLECTOR MOV. TIERRAS'!F16 | E16: ='COLECTOR MOV. TIERRAS'!G16 | F16: ='COLECTOR MOV. TIERRAS'!H16 | G16: ='COLECTOR MOV. TIERRAS'!I16 | H16: ='COLECTOR PARAMETROS'!$C$26 | I16: 1 | J16: 3/8" | K16: =ROUNDUP(D16/H16,0) | L16: =IF(I16=2,2*(G16-2*'COLECTOR PARAMETROS'!$C$19)+2*('COLECTOR PARAMETROS'!$C$12+E16+F16-2*'COLECTOR PARAMETROS'!$C$19)+'COLECTOR PARAMETROS'!$C$24,2*(G16-'COLECTOR PARAMETROS'!$C$11)+2*('COLECTOR PARAMETROS'!$C$12/2+E16+F16/2)+'COLECTOR PARAMETROS'!$C$24) | M16: =IF(I16=2,2*('COLECTOR PARAMETROS'!$C$10+2*('COLECTOR PARAMETROS'!$C$11-'COLECTOR PARAMETROS'!$C$19))+2*(E16+2*('COLECTOR PARAMETROS'!$C$11-'COLECTOR PARAMETROS'!$C$19))+'COLECTOR PARAMETROS'!$C$24,0) | N16: =K16*(L16+M16) | O16: =IF(J16="1/2""",'COLECTOR PARAMETROS'!$C$21,'COLECTOR PARAMETROS'!$C$20) | P16: =N16*O16 | Q16: ='COLECTOR PARAMETROS'!$C$28 | R16: =ROUND(L16/Q16,0)+IF(M16>0,ROUND(M16/Q16,0),0) | S16: =R16*D16*(1+'COLECTOR PARAMETROS'!$C$22/'COLECTOR PARAMETROS'!$C$23) | T16: =S16*'COLECTOR PARAMETROS'!$C$20 | U16: =P16+T16 | V16: DP-04 (seccion A), DP-08 (cuadro de doblado), DA-03
A17: TOTAL COLECTOR (tramos) | D17: =SUM(D10:D16) | N17: =SUM(N10:N16) | P17: =SUM(P10:P16) | S17: =SUM(S10:S16) | T17: =SUM(T10:T16) | U17: =SUM(U10:U16)
A19: CAJAS CL Y CC - lamina DP-07: malla 3/8" @0.20 en ambas caras de losas y muros. Por paño: barras = (L1 / s + 1) x L2 + (L2 / s + 1) x L1, por el numero de caras y el factor de traslapes y ganchos
A20: N° | B20: CAJA / PAÑO | C20: DETALLE | D20: L1 (m) | E20: L2 (m) | F20: ESPAC. s (m) | G20: CARAS | H20: PAÑOS IGUALES | I20: BARRAS (m) | J20: FACTOR TRASLAPE | K20: PESO (kg/m) | U20: ACERO (kg) | V20: SUSTENTO
B21: Caja de llegada CL: losa de fondo | C21: exterior | D21: ='COLECTOR MOV. TIERRAS'!D21+2*'COLECTOR PARAMETROS'!$C$11 | E21: ='COLECTOR MOV. TIERRAS'!E21+2*'COLECTOR PARAMETROS'!$C$11 | F21: ='COLECTOR PARAMETROS'!$C$30 | G21: 2 | H21: 1 | I21: =((D21/F21+1)*E21+(E21/F21+1)*D21)*G21*H21 | J21: ='COLECTOR PARAMETROS'!$C$31 | K21: ='COLECTOR PARAMETROS'!$C$20 | U21: =I21*J21*K21 | V21: DP-07: malla 3/8" @0.20 ambas caras
B22: Caja de llegada CL: losa superior | C22: exterior | D22: ='COLECTOR MOV. TIERRAS'!D21+2*'COLECTOR PARAMETROS'!$C$11 | E22: ='COLECTOR MOV. TIERRAS'!E21+2*'COLECTOR PARAMETROS'!$C$11 | F22: ='COLECTOR PARAMETROS'!$C$30 | G22: 2 | H22: 1 | I22: =((D22/F22+1)*E22+(E22/F22+1)*D22)*G22*H22 | J22: ='COLECTOR PARAMETROS'!$C$31 | K22: ='COLECTOR PARAMETROS'!$C$20 | U22: =I22*J22*K22 | V22: DP-07: malla 3/8" @0.20 ambas caras
B23: Caja de llegada CL: muros largos | C23: exterior x H | D23: ='COLECTOR MOV. TIERRAS'!D21+2*'COLECTOR PARAMETROS'!$C$11 | E23: ='COLECTOR MOV. TIERRAS'!F21 | F23: ='COLECTOR PARAMETROS'!$C$30 | G23: 2 | H23: 2 | I23: =((D23/F23+1)*E23+(E23/F23+1)*D23)*G23*H23 | J23: ='COLECTOR PARAMETROS'!$C$31 | K23: ='COLECTOR PARAMETROS'!$C$20 | U23: =I23*J23*K23 | V23: DP-07: dos muros largos, malla ambas caras
B24: Caja de llegada CL: muros cortos | C24: interior x H | D24: ='COLECTOR MOV. TIERRAS'!E21 | E24: ='COLECTOR MOV. TIERRAS'!F21 | F24: ='COLECTOR PARAMETROS'!$C$30 | G24: 2 | H24: 2 | I24: =((D24/F24+1)*E24+(E24/F24+1)*D24)*G24*H24 | J24: ='COLECTOR PARAMETROS'!$C$31 | K24: ='COLECTOR PARAMETROS'!$C$20 | U24: =I24*J24*K24 | V24: DP-07: muro(s) de cierre, malla ambas caras
B25: Caja de caida CC: losa de fondo | C25: exterior | D25: ='COLECTOR MOV. TIERRAS'!D22+2*'COLECTOR PARAMETROS'!$C$11 | E25: ='COLECTOR MOV. TIERRAS'!E22+2*'COLECTOR PARAMETROS'!$C$11 | F25: ='COLECTOR PARAMETROS'!$C$30 | G25: 2 | H25: 1 | I25: =((D25/F25+1)*E25+(E25/F25+1)*D25)*G25*H25 | J25: ='COLECTOR PARAMETROS'!$C$31 | K25: ='COLECTOR PARAMETROS'!$C$20 | U25: =I25*J25*K25 | V25: DP-07: malla 3/8" @0.20 ambas caras
B26: Caja de caida CC: losa superior | C26: exterior | D26: ='COLECTOR MOV. TIERRAS'!D22+2*'COLECTOR PARAMETROS'!$C$11 | E26: ='COLECTOR MOV. TIERRAS'!E22+2*'COLECTOR PARAMETROS'!$C$11 | F26: ='COLECTOR PARAMETROS'!$C$30 | G26: 2 | H26: 1 | I26: =((D26/F26+1)*E26+(E26/F26+1)*D26)*G26*H26 | J26: ='COLECTOR PARAMETROS'!$C$31 | K26: ='COLECTOR PARAMETROS'!$C$20 | U26: =I26*J26*K26 | V26: DP-07: malla 3/8" @0.20 ambas caras
B27: Caja de caida CC: muros largos | C27: exterior x H | D27: ='COLECTOR MOV. TIERRAS'!D22+2*'COLECTOR PARAMETROS'!$C$11 | E27: ='COLECTOR MOV. TIERRAS'!F22 | F27: ='COLECTOR PARAMETROS'!$C$30 | G27: 2 | H27: 2 | I27: =((D27/F27+1)*E27+(E27/F27+1)*D27)*G27*H27 | J27: ='COLECTOR PARAMETROS'!$C$31 | K27: ='COLECTOR PARAMETROS'!$C$20 | U27: =I27*J27*K27 | V27: DP-07: dos muros largos, malla ambas caras
B28: Caja de caida CC: muros cortos | C28: interior x H | D28: ='COLECTOR MOV. TIERRAS'!E22 | E28: ='COLECTOR MOV. TIERRAS'!F22 | F28: ='COLECTOR PARAMETROS'!$C$30 | G28: 2 | H28: 1 | I28: =((D28/F28+1)*E28+(E28/F28+1)*D28)*G28*H28 | J28: ='COLECTOR PARAMETROS'!$C$31 | K28: ='COLECTOR PARAMETROS'!$C$20 | U28: =I28*J28*K28 | V28: DP-07: muro(s) de cierre, malla ambas caras
A29: TOTAL CAJAS | U29: =SUM(U21:U28)
A31: REGISTROS DE LIMPIEZA Y TAPAS - lamina DP-06B: refuerzo de borde de la abertura, parrilla de la tapa, asas y anclajes del contramarco (cantidad de registros de la hoja COLECTOR REGISTROS Y TAPAS)
A32: N° | B32: ELEMENTO | C32: DIAM. | D32: FORMA | E32: PIEZAS POR REGISTRO | F32: REGISTROS | G32: LONG. POR PIEZA (m) | H32: LONG. TOTAL (m) | I32: PESO (kg/m) | U32: ACERO (kg) | V32: SUSTENTO
A33: 1 | B33: Refuerzo de borde de la abertura | C33: 1/2" | D33: recta | E33: 8 | F33: ='COLECTOR PARAMETROS'!$C$32 | G33: 1.4 | H33: =E33*F33*G33 | I33: ='COLECTOR PARAMETROS'!$C$21 | U33: =H33*I33 | V33: DP-06B: 2 barras de 1/2" por lado, L = 1.40
A34: 2 | B34: Parrilla de la tapa de concreto | C34: 3/8" | D34: recta | E34: 14 | F34: ='COLECTOR PARAMETROS'!$C$32 | G34: 0.62 | H34: =E34*F34*G34 | I34: ='COLECTOR PARAMETROS'!$C$20 | U34: =H34*I34 | V34: DP-06B: 7 + 7 barras 3/8" @0.10
A35: 3 | B35: Asas de la tapa | C35: 3/8" liso | D35: U | E35: 2 | F35: ='COLECTOR PARAMETROS'!$C$32 | G35: 0.4 | H35: =E35*F35*G35 | I35: ='COLECTOR PARAMETROS'!$C$20 | U35: =H35*I35 | V35: DP-06B: 2 asas de 0.40 desarrollado
A36: 4 | B36: Anclajes del contramarco | C36: 3/8" | D36: L | E36: 8 | F36: ='COLECTOR PARAMETROS'!$C$32 | G36: 0.2 | H36: =E36*F36*G36 | I36: ='COLECTOR PARAMETROS'!$C$20 | U36: =H36*I36 | V36: DP-06B: 8 anclajes de 0.20 soldados al angulo
A37: TOTAL REGISTROS Y TAPAS | U37: =SUM(U33:U36)
A39: RESUMEN PARA LA PLANILLA GENERAL (partidas 01.04.04.04.05 y 01.04.04.05.06)
A40: 1 | B40: ACERO DE REFUERZO EN COLECTOR Y CAJAS | F40: kg | G40: =SUMIF(J10:J16,"3/8""",P10:P16)+T17+U29 | H40: =SUMIF(J10:J16,"1/2""",P10:P16) | I40: =U17+U29
A41: 2 | B41: ACERO DE REFUERZO EN TAPAS, BORDES Y ANCLAJES | F41: kg | G41: =SUMIF(C33:C36,"3/8*",U33:U36) | H41: =SUMIF(C33:C36,"1/2*",U33:U36) | I41: =U37

Sheet COLECTOR REGISTROS Y TAPAS
A1: COLECTOR PLUVIAL FRONTAL - REGISTROS DE LIMPIEZA Y TAPAS
A2: ENTIDAD | C2: =+RESUMEN!B4
A3: PROYECTO | C3: =+RESUMEN!B5
A4: UBICACIÓN | C4: =+RESUMEN!B6
A5: FECHA | C5: =+RESUMEN!B7
A7: Lamina DP-01 (ubicacion) y DP-06B (detalle): contramarco L 2"x2"x3/16" anclado a la losa, marco L 1 1/2"x1 1/2"x1/8" soldado a la tapa, tapa de concreto armado 0.68 x 0.68 x 0.08 con parrilla 3/8" @0.10 y asas; borde engrosado 0.15 x 0.10 alrededor de la abertura de 0.70 x 0.70.
A9: N° | B9: REGISTRO | C9: PROGRESIVA | D9: UBICACION | E9: TAPA 0.68 x 0.68 (und) | F9: SUSTENTO
A10: 1 | B10: CL | C10: 0+000.00 | D10: Caja de llegada (empalme con CAR Varones y cuneta Eje 01) | E10: 1 | F10: DP-07
A11: 2 | B11: RS-01 | C11: 0+011.27 | D11: Registro en la losa del colector; empalme cuneta | E11: 1 | F11: DP-01, DP-06B
A12: 3 | B12: RS-02 | C12: 0+022.00 | D12: Registro en la losa del colector; limpieza / quiebre | E12: 1 | F12: DP-01, DP-06B
A13: 4 | B13: RS-03 | C13: 0+032.50 | D13: Registro en la losa del colector; empalme cuneta | E13: 1 | F13: DP-01, DP-06B
A14: 5 | B14: RS-04 | C14: 0+042.68 | D14: Registro en la losa del colector; empalme cuneta | E14: 1 | F14: DP-01, DP-06B
A15: 6 | B15: RS-05 | C15: 0+052.00 | D15: Registro en la losa del colector; limpieza / quiebre | E15: 1 | F15: DP-01, DP-06B
A16: 7 | B16: RS-06 | C16: 0+058.81 | D16: Registro en la losa del colector; limpieza / quiebre | E16: 1 | F16: DP-01, DP-06B
A17: 8 | B17: RS-07 | C17: 0+066.89 | D17: Registro en la losa del colector; limpieza / quiebre | E17: 1 | F17: DP-01, DP-06B
A18: 9 | B18: CC (2) | C18: 0+069.89 | D18: Caja de caida: dos registros sobre la poza | E18: 2 | F18: DP-07
A19: TOTAL DE REGISTROS CON TAPA | E19: =SUM(E10:E18)
A21: METRADO DE LAS PARTIDAS DE REGISTROS (cantidad = total de registros; dimensiones de la hoja COLECTOR PARAMETROS)
A22: N° | B22: PARTIDA | C22: UND | D22: CALCULO | E22: TOTAL | F22: SUSTENTO
A23: 1 | B23: CONTRAMARCO METALICO L 2"x2"x3/16" CON ANCLAJES | C23: und | D23: 1 por registro | E23: =E19 | F23: DP-06B
A24: 2 | B24: MARCO METALICO DE TAPA L 1 1/2"x1 1/2"x1/8" | C24: und | D24: 1 por tapa | E24: =E19 | F24: DP-06B
A25: 3 | B25: ANGULOS METALICOS P/MARCO Y CONTRAMARCO | C25: kg | D25: registros x (2.80 x 3.63 + 2.72 x 1.83) | E25: =E19*('COLECTOR PARAMETROS'!$C$36*'COLECTOR PARAMETROS'!$C$38+'COLECTOR PARAMETROS'!$C$37*'COLECTOR PARAMETROS'!$C$39) | F25: DP-06B; pesos de catalogo
A26: 4 | B26: TAPA DE CONCRETO ARMADO 0.68 x 0.68 x 0.08 | C26: und | D26: 1 por registro | E26: =E19 | F26: DP-06B
A27: 5 | B27: CONCRETO f'c=210 EN TAPAS | C27: m3 | D27: registros x 0.68 x 0.68 x 0.08 | E27: =E19*'COLECTOR PARAMETROS'!$C$33*'COLECTOR PARAMETROS'!$C$33*'COLECTOR PARAMETROS'!$C$34 | F27: DP-06B
A28: 6 | B28: PINTURA ANTICORROSIVA Y ESMALTE EN ANGULOS | C28: m2 | D28: registros x (2.80 x 0.203 + 2.72 x 0.152) | E28: =E19*('COLECTOR PARAMETROS'!$C$36*'COLECTOR PARAMETROS'!$C$40+'COLECTOR PARAMETROS'!$C$37*'COLECTOR PARAMETROS'!$C$41) | F28: 4 caras de cada angulo

Sheet COLECTOR JUNTAS Y EMPALMES
A1: COLECTOR PLUVIAL FRONTAL - JUNTAS Y EMPALMES DE CUNETAS
A2: ENTIDAD | C2: =+RESUMEN!B4
A3: PROYECTO | C3: =+RESUMEN!B5
A4: UBICACIÓN | C4: =+RESUMEN!B6
A5: FECHA | C5: =+RESUMEN!B7
A7: Lamina DP-01 (nota 5), DP-03 y DP-06C. Junta de dilatacion de 1" cada 4.00 m en todo el perimetro de la seccion (tecnopor + sellador elastomerico). Junta de tecnopor de 1" entre el colector y el cimiento del cerco, y entre el borde de la losa y el piso adyacente. Empalme de cada cuneta por ventana en el muro lado predio con caida libre al fondo (sin dintel adicional).
A9: N° | B9: ELEMENTO | C9: PROGRESIVA / DETALLE | D9: VECES | E9: LONGITUD (m) | F9: PARCIAL (m) | G9: SUSTENTO
A10: JUNTA DE DILATACION e=1" CON TECNOPOR Y SELLADOR ELASTOMERICO (perimetro = 2 x ancho exterior + 2 x (e fondo + h max + e losa))
A11: 1 | B11: Juntas de dilatacion cada 4.00 m entre 0+004.00 y 0+068.00 | C11: ="n = ENTERO("&TEXT('COLECTOR PARAMETROS'!$C$60,"0.00")&" / 4.00)" | D11: =INT('COLECTOR PARAMETROS'!$C$60/'COLECTOR PARAMETROS'!$C$58) | E11: =2*('COLECTOR PARAMETROS'!$C$10+2*'COLECTOR PARAMETROS'!$C$11)+2*('COLECTOR PARAMETROS'!$C$12+'COLECTOR PARAMETROS'!$C$59+'COLECTOR PARAMETROS'!$C$13) | F11: =D11*E11 | G11: DP-01 nota 5; DP-03 (juntas en el perfil); perimetro de la seccion
A12: TOTAL JUNTA DE DILATACION (m) | F12: =SUM(F11:F11)
A14: JUNTA DE TECNOPOR e=1" ENTRE COLECTOR, CERCO Y PISO ADYACENTE
A15: 1 | B15: Contra el cimiento del cerco (tramo pegado al cerco, 0+000 a primer quiebre) | C15: ="0+000.00 a 0+"&TEXT('COLECTOR PARAMETROS'!$C$61,"000.00") | D15: 1 | E15: ='COLECTOR PARAMETROS'!$C$61 | F15: =D15*E15 | G15: DP-01, DP-04 (junta entre muro y cimiento del cerco)
A16: 2 | B16: Borde de la losa con el piso adyacente: colector (ambos lados) | C16: ="2 x 0+"&TEXT('COLECTOR PARAMETROS'!$C$60,"000.00") | D16: 2 | E16: ='COLECTOR PARAMETROS'!$C$60 | F16: =D16*E16 | G16: DP-04: junta de tecnopor en el borde de la losa superior
A17: 3 | B17: Borde de la losa con el piso adyacente: caja CL (ambos lados) | C17: 2 x (largo exterior + 0.30) | D17: 2 | E17: ='COLECTOR MOV. TIERRAS'!D21+2*'COLECTOR PARAMETROS'!$C$11+0.30 | F17: =D17*E17 | G17: DP-07
A18: 4 | B18: Borde de la losa con el piso adyacente: caja CC (ambos lados) | C18: 2 x (largo exterior + 0.30) | D18: 2 | E18: ='COLECTOR MOV. TIERRAS'!D22+2*'COLECTOR PARAMETROS'!$C$11+0.30 | F18: =D18*E18 | G18: DP-07
A19: TOTAL JUNTA DE TECNOPOR (m) | F19: =SUM(F15:F18)
A21: EMPALME DE CUNETA AL COLECTOR (ventana 0.40 x H en el muro lado predio, caida libre y registro encima) - lamina DP-06C
A22: 1 | B22: Cuneta Eje 01 (perimetral este), perfil 01 | C22: 0+001.07 | D22: 1 | F22: =D22 | G22: DP-06C (cuadro de empalmes); DP-01
A23: 2 | B23: Cuneta Eje 02 (estacionamiento), perfil 02 | C23: 0+011.27 | D23: 1 | F23: =D23 | G23: DP-06C (cuadro de empalmes); DP-01
A24: 3 | B24: Cuneta Eje 06 (ingreso vehicular), perfil 06 | C24: 0+032.50 | D24: 1 | F24: =D24 | G24: DP-06C (cuadro de empalmes); DP-01
A25: 4 | B25: Cuneta Eje 07, perfil 07 | C25: 0+042.68 | D25: 1 | F25: =D25 | G25: DP-06C (cuadro de empalmes); DP-01
A26: 5 | B26: Cuneta Eje 11, perfil 11 | C26: 0+060.89 | D26: 1 | F26: =D26 | G26: DP-06C (cuadro de empalmes); DP-01
A27: 6 | B27: Cuneta Eje 12 (perimetral oeste), perfil 12 | C27: 0+069.56 | D27: 1 | F27: =D27 | G27: DP-06C (cuadro de empalmes); DP-01
A28: TOTAL EMPALMES (und) | F28: =SUM(F22:F27)
A30: Nota: las cunetas de los Ejes 11 y 12 terminan antes del cerco y se prolongan 1.88 y 5.39 m hasta el muro del colector con su misma seccion (DP-06C). Esa prolongacion se metra en las partidas de cunetas del proyecto; aqui solo se cuenta la ventana de empalme.

Sheet COLECTOR INSUMOS
A1: COLECTOR PLUVIAL FRONTAL - DESGLOSE DE INSUMOS POR PARTIDA
A2: ENTIDAD | C2: =+RESUMEN!B4
A3: PROYECTO | C3: =+RESUMEN!B5
A4: UBICACIÓN | C4: =+RESUMEN!B6
A5: FECHA | C5: =+RESUMEN!B7
A7: Rendimientos unitarios referenciales (celdas amarillas, editar segun el analisis de costos unitarios adoptado). El metrado se toma de la PLANILLA GENERAL DE METRADOS.
A9: N° | B9: PARTIDA | C9: UND | D9: METRADO | E9: INSUMO | F9: UND INSUMO | G9: CANTIDAD POR UND DE PARTIDA | H9: CANTIDAD TOTAL
A10: 1 | B10: 01.04.04.04.01 CONCRETO f'c=210 - losa de fondo | C10: m3 | D10: ='PLANILLA GENERAL DE METRADOS'!K237 | E10: Cemento Portland tipo I | F10: bol | G10: 9.73 | H10: =G10*$D$10
E11: Arena gruesa | F11: m3 | G11: 0.52 | H11: =G11*$D$10
E12: Piedra chancada 1/2" | F12: m3 | G12: 0.53 | H12: =G12*$D$10
E13: Agua | F13: m3 | G13: 0.186 | H13: =G13*$D$10
E14: Mezcladora 9-11 p3 | F14: hm | G14: 0.8 | H14: =G14*$D$10
E15: Vibrador de concreto | F15: hm | G15: 0.8 | H15: =G15*$D$10
E16: Operario | F16: hh | G16: 0.8 | H16: =G16*$D$10
E17: Oficial | F17: hh | G17: 0.8 | H17: =G17*$D$10
E18: Peon | F18: hh | G18: 6.4 | H18: =G18*$D$10
A19: 2 | B19: 01.04.04.04.02 CONCRETO f'c=210 - muros | C19: m3 | D19: ='PLANILLA GENERAL DE METRADOS'!K247 | E19: Cemento Portland tipo I | F19: bol | G19: 9.73 | H19: =G19*$D$19
E20: Arena gruesa | F20: m3 | G20: 0.52 | H20: =G20*$D$19
E21: Piedra chancada 1/2" | F21: m3 | G21: 0.53 | H21: =G21*$D$19
E22: Agua | F22: m3 | G22: 0.186 | H22: =G22*$D$19
E23: Mezcladora 9-11 p3 | F23: hm | G23: 1 | H23: =G23*$D$19
E24: Vibrador de concreto | F24: hm | G24: 1 | H24: =G24*$D$19
E25: Operario | F25: hh | G25: 1 | H25: =G25*$D$19
E26: Oficial | F26: hh | G26: 1 | H26: =G26*$D$19
E27: Peon | F27: hh | G27: 8 | H27: =G27*$D$19
A28: 3 | B28: 01.04.04.04.03 CONCRETO f'c=210 - losa superior | C28: m3 | D28: ='PLANILLA GENERAL DE METRADOS'!K257 | E28: Cemento Portland tipo I | F28: bol | G28: 9.73 | H28: =G28*$D$28
E29: Arena gruesa | F29: m3 | G29: 0.52 | H29: =G29*$D$28
E30: Piedra chancada 1/2" | F30: m3 | G30: 0.53 | H30: =G30*$D$28
E31: Agua | F31: m3 | G31: 0.186 | H31: =G31*$D$28
E32: Mezcladora 9-11 p3 | F32: hm | G32: 0.8 | H32: =G32*$D$28
E33: Vibrador de concreto | F33: hm | G33: 0.8 | H33: =G33*$D$28
E34: Operario | F34: hh | G34: 0.8 | H34: =G34*$D$28
E35: Oficial | F35: hh | G35: 0.8 | H35: =G35*$D$28
E36: Peon | F36: hh | G36: 6.4 | H36: =G36*$D$28
A37: 4 | B37: 01.04.04.04.04 ENCOFRADO Y DESENCOFRADO | C37: m2 | D37: ='PLANILLA GENERAL DE METRADOS'!K269 | E37: Madera tornillo | F37: p2 | G37: 4.24 | H37: =G37*$D$37
E38: Clavos 3" | F38: kg | G38: 0.2 | H38: =G38*$D$37
E39: Alambre negro N 8 | F39: kg | G39: 0.2 | H39: =G39*$D$37
E40: Operario | F40: hh | G40: 0.8 | H40: =G40*$D$37
E41: Oficial | F41: hh | G41: 0.8 | H41: =G41*$D$37
A42: 5 | B42: 01.04.04.04.05 ACERO DE REFUERZO fy=4200 | C42: kg | D42: ='PLANILLA GENERAL DE METRADOS'!K279 | E42: Acero corrugado fy=4200 (incluye 5 % desperdicio) | F42: kg | G42: 1.05 | H42: =G42*$D$42
E43: Alambre negro N 16 | F43: kg | G43: 0.06 | H43: =G43*$D$42
E44: Operario | F44: hh | G44: 0.032 | H44: =G44*$D$42
E45: Oficial | F45: hh | G45: 0.032 | H45: =G45*$D$42
A46: 6 | B46: 01.04.04.03.01 SOLADO f'c=100 e=0.05 | C46: m2 | D46: ='PLANILLA GENERAL DE METRADOS'!K226 | E46: Cemento Portland tipo I | F46: bol | G46: 0.3 | H46: =G46*$D$46
E47: Hormigon | F47: m3 | G47: 0.064 | H47: =G47*$D$46
E48: Agua | F48: m3 | G48: 0.01 | H48: =G48*$D$46
E49: Operario | F49: hh | G49: 0.1 | H49: =G49*$D$46
E50: Peon | F50: hh | G50: 0.4 | H50: =G50*$D$46
A51: 7 | B51: 01.04.04.02.01 EXCAVACION MANUAL DE ZANJAS | C51: m3 | D51: ='PLANILLA GENERAL DE METRADOS'!K185 | E51: Peon | F51: hh | G51: 2.67 | H51: =G51*$D$51
E52: Herramientas manuales | F52: %mo | G52: 0.03 | H52: =G52*$D$51
A53: 8 | B53: 01.04.04.02.03 RELLENO COMPACTADO CON MATERIAL PROPIO | C53: m3 | D53: ='PLANILLA GENERAL DE METRADOS'!K205 | E53: Agua | F53: m3 | G53: 0.05 | H53: =G53*$D$53
E54: Compactador vibratorio tipo plancha | F54: hm | G54: 0.4 | H54: =G54*$D$53
E55: Operario | F55: hh | G55: 0.4 | H55: =G55*$D$53
E56: Peon | F56: hh | G56: 1.6 | H56: =G56*$D$53
A57: 9 | B57: 01.04.04.02.04 ELIMINACION DE MATERIAL EXCEDENTE | C57: m3 | D57: ='PLANILLA GENERAL DE METRADOS'!K222 | E57: Volquete 6 m3 | F57: hm | G57: 0.133 | H57: =G57*$D$57
E58: Cargador frontal | F58: hm | G58: 0.033 | H58: =G58*$D$57
E59: Peon | F59: hh | G59: 0.133 | H59: =G59*$D$57
A60: 10 | B60: 01.04.04.05.03 ANGULOS METALICOS (marco y contramarco) | C60: kg | D60: ='PLANILLA GENERAL DE METRADOS'!K312 | E60: Angulo de acero (incluye corte y soldadura) | F60: kg | G60: 1.05 | H60: =G60*$D$60
E61: Soldadura cellocord | F61: kg | G61: 0.03 | H61: =G61*$D$60
E62: Operario | F62: hh | G62: 0.1 | H62: =G62*$D$60
E63: Oficial | F63: hh | G63: 0.1 | H63: =G63*$D$60
A64: 11 | B64: 01.04.04.05.07 PINTURA ANTICORROSIVA Y ESMALTE | C64: m2 | D64: ='PLANILLA GENERAL DE METRADOS'!K316 | E64: Pintura anticorrosiva | F64: gal | G64: 0.08 | H64: =G64*$D$64
E65: Esmalte sintetico | F65: gal | G65: 0.08 | H65: =G65*$D$64
E66: Lija y thinner | F66: glb | G66: 0.05 | H66: =G66*$D$64
E67: Operario | F67: hh | G67: 0.4 | H67: =G67*$D$64
A68: 12 | B68: 01.04.04.06.01 JUNTA DE DILATACION e=1" CON SELLADOR | C68: m | D68: ='PLANILLA GENERAL DE METRADOS'!K318 | E68: Tecnopor 1" | F68: m2 | G68: 0.25 | H68: =G68*$D$68
E69: Sello elastomerico de poliuretano | F69: kg | G69: 0.35 | H69: =G69*$D$68
E70: Operario | F70: hh | G70: 0.2 | H70: =G70*$D$68
E71: Peon | F71: hh | G71: 0.2 | H71: =G71*$D$68
A72: 13 | B72: 01.04.04.06.02 JUNTA DE TECNOPOR e=1" | C72: m | D72: ='PLANILLA GENERAL DE METRADOS'!K319 | E72: Tecnopor 1" | F72: m2 | G72: 0.15 | H72: =G72*$D$72
E73: Peon | F73: hh | G73: 0.1 | H73: =G73*$D$72
