Workbook

Sheet RESUMEN
A2: RESUMEN METRADOS DE DRENAJE PLUVIAL
A4: ENTIDAD | B4: GERENCIA TERRITORIAL BAJO MAYO - TARAPOTO
A5: PROYECTO | B5: CREACIÓN DEL SERVICIO DE PROTECCIÓN INTEGRAL A NIÑAS, NIÑOS Y ADOLESCENTES SIN CUIDADOS PARENTALES O EN RIESGO DE PERDERLOS EN CENTRO DE ACOGIDA RESIDENCIAL - VARONES DISTRITO DE MORALES DE LA PROVINCIA DE SAN MARTÍN DEL DEPARTAMENTO DE SAN MARTÍN, con CUI N.° 2705619
A6: UBICACIÓN | B6: SAN MARTIN - SAN MARTIN - MORALES
A7: FECHA | B7: 46266
A8: Item | B8: Descripción | C8: Unid. | D8: Total.
A9: 01.04.03 | B9: SISTEMA DE DRENAJE PLUVIAL
A10: 01.04.03.01 | B10: TRABAJOS PRELIMINARES
A11: 01.04.03.01.01 | B11: LIMPIEZA MANUAL DE TERRENO | C11: m² | D11: =+'PLANILLA GENERAL DE METRADOS'!K11 -> 753.536
A12: 01.04.03.01.02 | B12: TRAZO, NIVELES Y REPLANTEO PRELIMINAR | C12: m² | D12: =+'PLANILLA GENERAL DE METRADOS'!K21 -> 753.536
A13: 01.04.03.02 | B13: MOVIMIENTO DE TIERRAS
A14: 01.04.03.02.01 | B14: EXCAVACIÓN MANUAL DE ZANJAS P/CUNETAS | C14: m³ | D14: =+'PLANILLA GENERAL DE METRADOS'!K32 -> 513.90864
A15: 01.04.03.02.02 | B15: EXCAVACIÓN MANUAL DE ZANJAS P/DADOS DE CONCRETO | C15: m³ | D15: =+'PLANILLA GENERAL DE METRADOS'!K42 -> 3.136
A16: 01.04.03.02.03 | B16: REFINE, NIVELACIÓN Y COMPACTACIÓN EN TERRENO NORMAL | C16: m² | D16: =+'PLANILLA GENERAL DE METRADOS'!K45 -> 322.944
A17: 01.04.03.02.04 | B17: RELLENO COMPACTADO C/MATERIAL PROPIO SELECCIONADO | C17: m³ | D17: =+'PLANILLA GENERAL DE METRADOS'!K55 -> 293.66208
A18: 01.04.03.02.05 | B18: ELIMINACIÓN DE MATERIAL EXCEDENTE D<1Km | C18: m³ | D18: =+'PLANILLA GENERAL DE METRADOS'!K65 -> 264.29587
A19: 01.04.03.03 | B19: OBRAS DE CONCRETO SIMPLE
A20: 01.04.03.03.01 | B20: CONCRETO f'c=100 kg/cm2 PARA SOLADO E=4'' | C20: m² | D20: =+'PLANILLA GENERAL DE METRADOS'!K69 -> 322.944
A21: 01.04.03.03.02 | B21: CONCRETO f'c=140 Kg/cm2 PARA DADOS DE CONCRETO | C21: m³ | D21: =+'PLANILLA GENERAL DE METRADOS'!K79 -> 3.136
A22: 01.04.03.04 | B22: OBRAS DE CONCRETO ARMADO
A23: 01.04.03.04.02 | B23: CUNETAS
A24: 01.04.03.04.02.01 | B24: CONCRETO f'c=175 kg/cm2 PARA CUNETAS | C24: m³ | D24: =+'PLANILLA GENERAL DE METRADOS'!K83 -> 94.1398
A25: 01.04.03.04.02.02 | B25: ENCOFRADO Y DESENCOFRADO DE CUNETAS | C25: m² | D25: =+'PLANILLA GENERAL DE METRADOS'!K93 -> 1245.916
A26: 01.04.03.04.02.03 | B26: ACERO f'y=4200 kg/cm2 PARA CUNETA | C26: kg | D26: =+'PLANILLA GENERAL DE METRADOS'!K103 -> 3354.7297
A27: 01.04.03.04.02.04 | B27: CURADO DE CONCRETO EN CUNETA | C27: m² | D27: =+'METRADO DE CURADO'!M27 -> 801.5833
A28: 01.04.03.04.03 | B28: VARIOS
A29: 01.04.03.04.03.01 | B29: REJILLA METALICA P/CUNETA C/PL 1''x 3/16'' Y ANGULO 1'' x 1'' x 3/16'', S/DETALLE | C29: m | D29: =+'PLANILLA GENERAL DE METRADOS'!K108 -> 373.85
A30: 01.04.03.04.03.02 | B30: TAPA DE INSPECCION 0.60m x 0.60m | C30: und | D30: =+'PLANILLA GENERAL DE METRADOS'!K109 -> 18
A31: 01.04.03.04.03.03 | B31: JUNTA DE DILATACION E=1" CON SELLADOR ASFALTO | C31: m | D31: =+'PLANILLA GENERAL DE METRADOS'!K110 -> 252.28688
A32: 01.04.03.04.03.04 | B32: LLORADERO DE TUBERIA PVC Ø3" C/FILTRO DE GRAVA Y GEOTEXTIL @1.50 m (CUNETA COLINDANTE CON AREA VERDE) | C32: und | D32: =+'PLANILLA GENERAL DE METRADOS'!K111 -> 226
A33: 01.04.03.05 | B33: RED DE COLECCIÓN
A34: 01.04.03.05.01 | B34: RED DE RECOLECCION TECHO
A35: 01.04.03.05.01.01 | B35: MONTANTE CON TUBERÍA PVC DE 4" | C35: m | D35: =+'PLANILLA GENERAL DE METRADOS'!K115 -> 408.02
A36: 01.04.03.05.01.02 | B36: FALSA COLUMNA P/MONTANTE DE 0.20m x 0.15m x 1.30m | C36: und | D36: =+'PLANILLA GENERAL DE METRADOS'!K116 -> 56
A37: 01.04.03.05.01.02.01 | B37: CONCRETO F´C=175 KG/CM2 EN FALSA COLUMNA | C37: m³ | D37: =+'PLANILLA GENERAL DE METRADOS'!K117 -> 2.184
A38: 01.04.03.05.01.02.02 | B38: ENCOFRADO Y DESENCOFRADO EN FALSA COLUMNA - MONTANTE PLUVIAL | C38: m² | D38: =+'PLANILLA GENERAL DE METRADOS'!K119 -> 36.4
A39: 01.04.03.05.01.02.03 | B39: ACERO FY=4200 KG/CM2 EN FALSA COLUMNA (MONTANTE PLUVIAL) | C39: kg | D39: =+'PLANILLA GENERAL DE METRADOS'!K122 -> 314.2272
A40: 01.04.03.05.01.03 | B40: CANALETA DE PLANCHA DE ACERO GALVANIZADO e=0.9mm, SECCIÓN 0.25m x 0.20m | C40: m | D40: =+'PLANILLA GENERAL DE METRADOS'!K125 -> 523.16
A41: 01.04.03.05.01.04 | B41: SOPORTE DE PLATINA F°G° 1" x 1/8" P/CANALETA | C41: und | D41: =+'PLANILLA GENERAL DE METRADOS'!K126 -> 906
A42: 01.04.03.05.01.05 | B42: TAPA LATERAL DE PLANCHA GALVANIZADA P/CANALETA | C42: und | D42: =+'PLANILLA GENERAL DE METRADOS'!K127 -> 44
A43: 01.04.03.05.01.06 | B43: BOQUILLA DE PLANCHA GALVANIZADA P/CONEXIÓN DE CANALETA A MONTANTE Ø4" | C43: und | D43: =+'PLANILLA GENERAL DE METRADOS'!K128 -> 52
A44: 01.04.03.05.02 | B44: RED DE RECOLECCION PISO
A45: 01.04.03.05.02.01 | B45: TUBERIA DESAGÜE PVC-CP Ø4" | C45: m | D45: =+'PLANILLA GENERAL DE METRADOS'!K131 -> 92.08
A46: 01.04.03.05.02.02 | B46: SUMIDERO METALICO C/PLATINA 1" X 3/16" | C46: und | D46: =+'PLANILLA GENERAL DE METRADOS'!K132 -> 16
A47: 01.04.03.05.02.03 | B47: CODO DESAGÜE PVC Ø4" x 90° | C47: und | D47: =+'PLANILLA GENERAL DE METRADOS'!K133 -> 13
A48: 01.04.03.05.02.04 | B48: TEE SANITARIA DESAGÜE PVC Ø4" | C48: und | D48: =+'PLANILLA GENERAL DE METRADOS'!K134 -> 3
A49: 01.04.03.05.03 | B49: ACCESORIOS
A50: 01.04.03.05.03.02 | B50: CODO DESAGÜE PVC Ø4" x 90° | C50: und | D50: =+'PLANILLA GENERAL DE METRADOS'!K137 -> 168
A51: 01.04.03.05.03.04 | B51: COLGADOR F°G° P/TUBERIA PVC Ø4" | C51: und | D51: =+'PLANILLA GENERAL DE METRADOS'!K138 -> 100
A52: 01.04.03.05.03.05 | B52: ABRAZADERA DE F°G° P/TUBERIA PVC Ø4" | C52: und | D52: =+'PLANILLA GENERAL DE METRADOS'!K139 -> 80
A53: 01.04.04 | B53: COLECTOR PLUVIAL FRONTAL (TRAMO CAR VARONES - EMPALME CON LA CAJA CL DEL HOGAR DE REFUGIO)
A54: 01.04.04.01 | B54: TRABAJOS PRELIMINARES
A55: 01.04.04.01.01 | B55: LIMPIEZA MANUAL DE TERRENO | C55: m² | D55: =+'PLANILLA GENERAL DE METRADOS'!K143 -> 147.406
A56: 01.04.04.01.02 | B56: TRAZO, NIVELES Y REPLANTEO PRELIMINAR | C56: m² | D56: =+'PLANILLA GENERAL DE METRADOS'!K147 -> 147.406
A57: 01.04.04.02 | B57: MOVIMIENTO DE TIERRAS
A58: 01.04.04.02.01 | B58: EXCAVACIÓN MANUAL DE ZANJAS P/COLECTOR | C58: m³ | D58: =+'PLANILLA GENERAL DE METRADOS'!K152 -> 130.62232
A59: 01.04.04.02.02 | B59: REFINE, NIVELACIÓN Y COMPACTACIÓN EN TERRENO NORMAL | C59: m² | D59: =+'PLANILLA GENERAL DE METRADOS'!K156 -> 105.29
A60: 01.04.04.02.03 | B60: RELLENO COMPACTADO C/MATERIAL PROPIO SELECCIONADO | C60: m³ | D60: =+'PLANILLA GENERAL DE METRADOS'!K160 -> 91.51313
A61: 01.04.04.02.04 | B61: ELIMINACIÓN DE MATERIAL EXCEDENTE D<1Km | C61: m³ | D61: =+'PLANILLA GENERAL DE METRADOS'!K167 -> 46.931033
A62: 01.04.04.03 | B62: OBRAS DE CONCRETO SIMPLE
A63: 01.04.04.03.01 | B63: CONCRETO f'c=100 kg/cm2 PARA SOLADO E=2'' | C63: m² | D63: =+'PLANILLA GENERAL DE METRADOS'!K171 -> 105.29
A64: 01.04.04.04 | B64: OBRAS DE CONCRETO ARMADO - COLECTOR
A65: 01.04.04.04.01 | B65: CONCRETO f'c=210 kg/cm2 PARA COLECTOR | C65: m³ | D65: =+'PLANILLA GENERAL DE METRADOS'!K176 -> 55.748729
A66: 01.04.04.04.02 | B66: ENCOFRADO Y DESENCOFRADO DE COLECTOR | C66: m² | D66: =+'PLANILLA GENERAL DE METRADOS'!K190 -> 538.31072
A67: 01.04.04.04.03 | B67: ACERO f'y=4200 kg/cm2 PARA COLECTOR | C67: kg | D67: =+'PLANILLA GENERAL DE METRADOS'!K194 -> 2523.8377
A68: 01.04.04.04.04 | B68: ACABADO FROTACHADO DE LOSA SUPERIOR (VEREDA) | C68: m² | D68: =+'PLANILLA GENERAL DE METRADOS'!K198 -> 94.761
A69: 01.04.04.04.05 | B69: CURADO DE CONCRETO EN COLECTOR | C69: m² | D69: =+'PLANILLA GENERAL DE METRADOS'!K202 -> 368.26886
A70: 01.04.04.05 | B70: REGISTROS DE LIMPIEZA Y TAPAS
A71: 01.04.04.05.01 | B71: TAPA DE REGISTRO CIEGA DE CONCRETO ARMADO 0.68x0.68x0.08 | C71: und | D71: =+'PLANILLA GENERAL DE METRADOS'!K207 -> 11
A72: 01.04.04.06 | B72: JUNTAS
A73: 01.04.04.06.01 | B73: JUNTA DE DILATACION E=1" CON TECNOPOR Y SELLADOR ASFALTICO EN COLECTOR | C73: m | D73: =+'PLANILLA GENERAL DE METRADOS'!K215 -> 120.64
A74: 01.04.04.06.02 | B74: JUNTA E=1" CON TECNOPOR Y SELLADOR ASFALTICO ENTRE COLECTOR Y CAJA CL | C74: m | D74: =+'PLANILLA GENERAL DE METRADOS'!K216 -> 4.64

Sheet PLANILLA GENERAL DE METRADOS
A2: RESUMEN METRADOS DE DRENAJE PLUVIAL
A3: ENTIDAD | B3: =+RESUMEN!B4 -> GERENCIA TERRITORIAL BAJO MAYO - TARAPOTO
A4: PROYECTO | B4: =+RESUMEN!B5 -> CREACIÓN DEL SERVICIO DE PROTECCIÓN INTEGRAL A NIÑAS, NIÑOS Y ADOLESCENTES SIN CUIDADOS PARENTALES O EN RIESGO DE PERDERLOS EN CENTRO DE ACOGIDA RESIDENCIAL - VARONES DISTRITO DE MORALES DE LA PROVINCIA DE SAN MARTÍN DEL DEPARTAMENTO DE SAN MARTÍN, con CUI N.° 2705619
A5: UBICACIÓN | B5: =+RESUMEN!B6 -> SAN MARTIN - SAN MARTIN - MORALES
A6: FECHA | B6: =+RESUMEN!B7 -> 46266
A8: ITEM | B8: DESCRIPCION | C8: Nº DE VECES | D8: LARGO | E8: ANCHO | F8: ALTURA | G8: FACT. | H8: AREA | I8: VOLUMEN | J8: PARCIAL | K8: TOTAL | L8: UND
A9: 01.04.03 | B9: SISTEMA DE DRENAJE PLUVIAL
A10: 01.04.03.01 | B10: TRABAJOS PRELIMINARES
A11: 01.04.03.01.01 | B11: LIMPIEZA MANUAL DE TERRENO | K11: =SUM(J12:J20) -> 753.536 | L11: m²
B12: EJE 1 | C12: 1 | D12: 111.53 | E12: 1.4 | J12: =C12*D12*E12 -> 156.142
B13: EJE 2 | C13: 1 | D13: 34.25 | E13: 1.4 | J13: =C13*D13*E13 -> 47.95
B14: EJE 3 | C14: 1 | D14: 22.4 | E14: 1.4 | J14: =C14*D14*E14 -> 31.36
B15: EJE 4 | C15: 1 | D15: 102.31 | E15: 1.4 | J15: =C15*D15*E15 -> 143.234
B16: EJE 5 | C16: 1 | D16: 42.2 | E16: 1.4 | J16: =C16*D16*E16 -> 59.08
B17: EJE 6 | C17: 1 | D17: 98.69 | E17: 1.4 | J17: =C17*D17*E17 -> 138.166
B18: EJE 7 | C18: 1 | D18: 23.6 | E18: 1.4 | J18: =C18*D18*E18 -> 33.04
B19: EJE 8 | C19: 1 | D19: 60.6 | E19: 1.4 | J19: =C19*D19*E19 -> 84.84
B20: EJE 9 | C20: 1 | D20: 42.66 | E20: 1.4 | J20: =C20*D20*E20 -> 59.724
A21: 01.04.03.01.02 | B21: TRAZO, NIVELES Y REPLANTEO PRELIMINAR | K21: =SUM(J22:J30) -> 753.536 | L21: m²
B22: EJE 1 | C22: 1 | D22: 111.53 | E22: 1.4 | J22: =C22*D22*E22 -> 156.142
B23: EJE 2 | C23: 1 | D23: 34.25 | E23: 1.4 | J23: =C23*D23*E23 -> 47.95
B24: EJE 3 | C24: 1 | D24: 22.4 | E24: 1.4 | J24: =C24*D24*E24 -> 31.36
B25: EJE 4 | C25: 1 | D25: 102.31 | E25: 1.4 | J25: =C25*D25*E25 -> 143.234
B26: EJE 5 | C26: 1 | D26: 42.2 | E26: 1.4 | J26: =C26*D26*E26 -> 59.08
B27: EJE 6 | C27: 1 | D27: 98.69 | E27: 1.4 | J27: =C27*D27*E27 -> 138.166
B28: EJE 7 | C28: 1 | D28: 23.6 | E28: 1.4 | J28: =C28*D28*E28 -> 33.04
B29: EJE 8 | C29: 1 | D29: 60.6 | E29: 1.4 | J29: =C29*D29*E29 -> 84.84
B30: EJE 9 | C30: 1 | D30: 42.66 | E30: 1.4 | J30: =C30*D30*E30 -> 59.724
A31: 01.04.03.02 | B31: MOVIMIENTO DE TIERRAS
A32: 01.04.03.02.01 | B32: EXCAVACIÓN MANUAL DE ZANJAS P/CUNETAS | K32: =SUM(J33:J41) -> 513.90864 | L32: m³
B33: EJE 1 | C33: 1 | D33: 111.53 | E33: 1.4 | F33: 0.65 | J33: =C33*D33*E33*(F33+PARAMETROS!$B$15) -> 117.1065
B34: EJE 2 | C34: 1 | D34: 34.25 | E34: 1.4 | F34: 0.49 | J34: =C34*D34*E34*(F34+PARAMETROS!$B$15) -> 28.2905
B35: EJE 3 | C35: 1 | D35: 22.4 | E35: 1.4 | F35: 0.46 | J35: =C35*D35*E35*(F35+PARAMETROS!$B$15) -> 17.5616
B36: EJE 4 | C36: 1 | D36: 102.31 | E36: 1.4 | F36: 0.63 | J36: =C36*D36*E36*(F36+PARAMETROS!$B$15) -> 104.56082
B37: EJE 5 | C37: 1 | D37: 42.2 | E37: 1.4 | F37: 0.5 | J37: =C37*D37*E37*(F37+PARAMETROS!$B$15) -> 35.448
B38: EJE 6 | C38: 1 | D38: 98.69 | E38: 1.4 | F38: 0.63 | J38: =C38*D38*E38*(F38+PARAMETROS!$B$15) -> 100.86118
B39: EJE 7 | C39: 1 | D39: 23.6 | E39: 1.4 | F39: 0.46 | J39: =C39*D39*E39*(F39+PARAMETROS!$B$15) -> 18.5024
B40: EJE 8 | C40: 1 | D40: 60.6 | E40: 1.4 | F40: 0.55 | J40: =C40*D40*E40*(F40+PARAMETROS!$B$15) -> 55.146
B41: EJE 9 | C41: 1 | D41: 42.66 | E41: 1.4 | F41: 0.51 | J41: =C41*D41*E41*(F41+PARAMETROS!$B$15) -> 36.43164
A42: 01.04.03.02.02 | B42: EXCAVACIÓN MANUAL DE ZANJAS P/DADOS DE CONCRETO | C42: 56 | K42: =J43*C42 -> 3.136 | L42: m³
B43: DADO 0.40 X 0.40 | D43: 0.4 | E43: 0.35 | F43: 0.4 | J43: =D43*E43*F43 -> 0.056
A45: 01.04.03.02.03 | B45: REFINE, NIVELACIÓN Y COMPACTACIÓN EN TERRENO NORMAL | K45: =SUM(J46:J54) -> 322.944 | L45: m²
B46: EJE 1 | C46: 1 | D46: 111.53 | E46: 0.6 | J46: =C46*D46*E46 -> 66.918
B47: EJE 2 | C47: 1 | D47: 34.25 | E47: 0.6 | J47: =C47*D47*E47 -> 20.55
B48: EJE 3 | C48: 1 | D48: 22.4 | E48: 0.6 | J48: =C48*D48*E48 -> 13.44
B49: EJE 4 | C49: 1 | D49: 102.31 | E49: 0.6 | J49: =C49*D49*E49 -> 61.386
B50: EJE 5 | C50: 1 | D50: 42.2 | E50: 0.6 | J50: =C50*D50*E50 -> 25.32
B51: EJE 6 | C51: 1 | D51: 98.69 | E51: 0.6 | J51: =C51*D51*E51 -> 59.214
B52: EJE 7 | C52: 1 | D52: 23.6 | E52: 0.6 | J52: =C52*D52*E52 -> 14.16
B53: EJE 8 | C53: 1 | D53: 60.6 | E53: 0.6 | J53: =C53*D53*E53 -> 36.36
B54: EJE 9 | C54: 1 | D54: 42.66 | E54: 0.6 | J54: =C54*D54*E54 -> 25.596
A55: 01.04.03.02.04 | B55: RELLENO COMPACTADO C/MATERIAL PROPIO SELECCIONADO | K55: =SUM(J56:J64) -> 293.66208 | L55: m³
B56: EJE 1 | C56: 1 | D56: 111.53 | E56: 0.8 | F56: 0.65 | J56: =C56*D56*E56*(F56+PARAMETROS!$B$15) -> 66.918
B57: EJE 2 | C57: 1 | D57: 34.25 | E57: 0.8 | F57: 0.49 | J57: =C57*D57*E57*(F57+PARAMETROS!$B$15) -> 16.166
B58: EJE 3 | C58: 1 | D58: 22.4 | E58: 0.8 | F58: 0.46 | J58: =C58*D58*E58*(F58+PARAMETROS!$B$15) -> 10.0352
B59: EJE 4 | C59: 1 | D59: 102.31 | E59: 0.8 | F59: 0.63 | J59: =C59*D59*E59*(F59+PARAMETROS!$B$15) -> 59.74904
B60: EJE 5 | C60: 1 | D60: 42.2 | E60: 0.8 | F60: 0.5 | J60: =C60*D60*E60*(F60+PARAMETROS!$B$15) -> 20.256
B61: EJE 6 | C61: 1 | D61: 98.69 | E61: 0.8 | F61: 0.63 | J61: =C61*D61*E61*(F61+PARAMETROS!$B$15) -> 57.63496
B62: EJE 7 | C62: 1 | D62: 23.6 | E62: 0.8 | F62: 0.46 | J62: =C62*D62*E62*(F62+PARAMETROS!$B$15) -> 10.5728
B63: EJE 8 | C63: 1 | D63: 60.6 | E63: 0.8 | F63: 0.55 | J63: =C63*D63*E63*(F63+PARAMETROS!$B$15) -> 31.512
B64: EJE 9 | C64: 1 | D64: 42.66 | E64: 0.8 | F64: 0.51 | J64: =C64*D64*E64*(F64+PARAMETROS!$B$15) -> 20.81808
A65: 01.04.03.02.05 | B65: ELIMINACIÓN DE MATERIAL EXCEDENTE D<1Km | G65: =PARAMETROS!$B$16 -> 1.2 | K65: =(J66+J67)*G65 -> 264.29587 | L65: m³
B66: EXCAVACIÓN MANUAL DE ZANJA PARA CUNETA | G66: 1 | I66: =+K32 -> 513.90864 | J66: =G66*I66 -> 513.90864
B67: RELLENO COMPACTADO CON MATERIAL PROPIO | G67: -1 | I67: =+K55 -> 293.66208 | J67: =G67*I67 -> -293.66208
A68: 01.04.03.03 | B68: OBRAS DE CONCRETO SIMPLE
A69: 01.04.03.03.01 | B69: CONCRETO f'c=100 kg/cm2 PARA SOLADO E=4'' | K69: =SUM(J70:J78) -> 322.944 | L69: m²
B70: EJE 1 | C70: 1 | D70: 111.53 | E70: 0.6 | J70: =C70*D70*E70 -> 66.918
B71: EJE 2 | C71: 1 | D71: 34.25 | E71: 0.6 | J71: =C71*D71*E71 -> 20.55
B72: EJE 3 | C72: 1 | D72: 22.4 | E72: 0.6 | J72: =C72*D72*E72 -> 13.44
B73: EJE 4 | C73: 1 | D73: 102.31 | E73: 0.6 | J73: =C73*D73*E73 -> 61.386
B74: EJE 5 | C74: 1 | D74: 42.2 | E74: 0.6 | J74: =C74*D74*E74 -> 25.32
B75: EJE 6 | C75: 1 | D75: 98.69 | E75: 0.6 | J75: =C75*D75*E75 -> 59.214
B76: EJE 7 | C76: 1 | D76: 23.6 | E76: 0.6 | J76: =C76*D76*E76 -> 14.16
B77: EJE 8 | C77: 1 | D77: 60.6 | E77: 0.6 | J77: =C77*D77*E77 -> 36.36
B78: EJE 9 | C78: 1 | D78: 42.66 | E78: 0.6 | J78: =C78*D78*E78 -> 25.596
A79: 01.04.03.03.02 | B79: CONCRETO f'c=140 Kg/cm2 PARA DADOS DE CONCRETO | C79: 56 | K79: =J80*C79 -> 3.136 | L79: m³
B80: DADO 0.40 X 0.40 | D80: 0.4 | E80: 0.35 | F80: 0.4 | J80: =D80*E80*F80 -> 0.056
A81: 01.04.03.04 | B81: OBRAS DE CONCRETO ARMADO
A82: 01.04.03.04.02 | B82: CUNETAS
A83: 01.04.03.04.02.01 | B83: CONCRETO f'c=175 kg/cm2 PARA CUNETAS | K83: =SUM(J84:J92) -> 94.1398 | L83: m³
B84: EJE 1 | C84: 1 | J84: =+'CONCRETO EN CUNETAS'!G10 -> 21.3456
B85: EJE 2 | C85: 1 | J85: =+'CONCRETO EN CUNETAS'!G22 -> 4.693
B86: EJE 3 | C86: 1 | J86: =+'CONCRETO EN CUNETAS'!G34 -> 2.94
B87: EJE 4 | C87: 1 | J87: =+'CONCRETO EN CUNETAS'!G46 -> 18.8362
B88: EJE 5 | C88: 1 | J88: =+'CONCRETO EN CUNETAS'!G58 -> 6.54
B89: EJE 6 | C89: 1 | J89: =+'CONCRETO EN CUNETAS'!G70 -> 20.4348
B90: EJE 7 | C90: 1 | J90: =+'CONCRETO EN CUNETAS'!O10 -> 3.108
B91: EJE 8 | C91: 1 | J91: =+'CONCRETO EN CUNETAS'!O22 -> 9.749
B92: EJE 9 | C92: 1 | J92: =+'CONCRETO EN CUNETAS'!O34 -> 6.4932
A93: 01.04.03.04.02.02 | B93: ENCOFRADO Y DESENCOFRADO DE CUNETAS | K93: =SUM(J94:J102) -> 1245.916 | L93: m²
B94: EJE 1 | C94: 1 | J94: =+'ENCOFRADO Y DESENCOFRADO'!H12 -> 291.252
B95: EJE 2 | C95: 1 | J95: =+'ENCOFRADO Y DESENCOFRADO'!P12 -> 59.62
B96: EJE 3 | C96: 1 | J96: =+'ENCOFRADO Y DESENCOFRADO'!H23 -> 36.4
B97: EJE 4 | C97: 1 | J97: =+'ENCOFRADO Y DESENCOFRADO'!P23 -> 256.004
B98: EJE 5 | C98: 1 | J98: =+'ENCOFRADO Y DESENCOFRADO'!H34 -> 82.66
B99: EJE 6 | C99: 1 | J99: =+'ENCOFRADO Y DESENCOFRADO'!P34 -> 270.296
B100: EJE 7 | C100: 1 | J100: =+'ENCOFRADO Y DESENCOFRADO'!H45 -> 38.56
B101: EJE 8 | C101: 1 | J101: =+'ENCOFRADO Y DESENCOFRADO'!P45 -> 127.92
B102: EJE 9 | C102: 1 | J102: =+'ENCOFRADO Y DESENCOFRADO'!H57 -> 83.204
A103: 01.04.03.04.02.03 | B103: ACERO f'y=4200 kg/cm2 PARA CUNETA | K103: =+'METRADO ACERO'!AG28 -> 3354.7297 | L103: kg
...

Sheet CONCRETO EN CUNETAS
B2: CONCRETO F´C=175 KG/CM2 PARA CUNETAS - DRENAJE PLUVIAL
B3: ENTIDAD | C3: =+RESUMEN!B4 -> GERENCIA TERRITORIAL BAJO MAYO - TARAPOTO
B4: PROYECTO | C4: =+RESUMEN!B5 -> CREACIÓN DEL SERVICIO DE PROTECCIÓN INTEGRAL A NIÑAS, NIÑOS Y ADOLESCENTES SIN CUIDADOS PARENTALES O EN RIESGO DE PERDERLOS EN CENTRO DE ACOGIDA RESIDENCIAL - VARONES DISTRITO DE MORALES DE LA PROVINCIA DE SAN MARTÍN DEL DEPARTAMENTO DE SAN MARTÍN, con CUI N.° 2705619
B5: UBICACIÓN | C5: =+RESUMEN!B6 -> SAN MARTIN - SAN MARTIN - MORALES
B6: FECHA | C6: =+RESUMEN!B7 -> 46266
B7: OBRAS DE CONCRETO ARMADO
B9: LONGITUDES Y AREAS | E9: m3 | F9: Sub.TOTAL | G9: TOTAL (m3) | J9: LONGITUDES Y AREAS | M9: m3 | N9: Sub.TOTAL | O9: TOTAL (m3)
B10: CUNETA EJE 01 | C10: MUROS | D10: AREA | E10: 61.2 | F10: =E10*E11*E12 -> 12.24 | G10: =SUM(F10:F18) -> 21.3456 | J10: CUNETA EJE 07 | K10: MUROS | L10: AREA | M10: 8.46 | N10: =M10*M11*M12 -> 1.692 | O10: =SUM(N10:N18) -> 3.108
D11: ESPESOR | E11: 0.1 | L11: ESPESOR | M11: 0.1
D12: CANT. | E12: 2 | L12: CANT. | M12: 2
C13: LOSA | D13: ESPESOR | E13: 0.1 | F13: =E13*E14*E15 -> 6.6918 | K13: LOSA | L13: ESPESOR | M13: 0.1 | N13: =M13*M14*M15 -> 1.416
D14: LONGITUD | E14: 111.53 | L14: LONGITUD | M14: 23.6
D15: ANCHO | E15: 0.6 | L15: ANCHO | M15: 0.6
C16: TAPA | D16: LONGITUD | E16: 40.23 | F16: =E16*E17*E18 -> 2.4138 | K16: TAPA | L16: LONGITUD | M16: 0 | N16: =M16*M17*M18 -> 0
D17: ESPESOR | E17: 0.1 | L17: ESPESOR | M17: 0.1
D18: ANCHO | E18: 0.6 | L18: ANCHO | M18: 0.6
B21: LONGITUDES Y AREAS | E21: m3 | F21: Sub.TOTAL | G21: TOTAL (m3) | J21: LONGITUDES Y AREAS | M21: m3 | N21: Sub.TOTAL | O21: TOTAL (m3)
B22: CUNETA EJE 02 | C22: MUROS | D22: AREA | E22: 13.19 | F22: =E22*E23*E24 -> 2.638 | G22: =SUM(F22:F30) -> 4.693 | J22: CUNETA EJE 08 | K22: MUROS | L22: AREA | M22: 27.34 | N22: =M22*M23*M24 -> 5.468 | O22: =SUM(N22:N30) -> 9.749
D23: ESPESOR | E23: 0.1 | L23: ESPESOR | M23: 0.1
D24: CANT. | E24: 2 | L24: CANT. | M24: 2
C25: LOSA | D25: ESPESOR | E25: 0.1 | F25: =E25*E26*E27 -> 2.055 | K25: LOSA | L25: ESPESOR | M25: 0.1 | N25: =M25*M26*M27 -> 3.636
D26: LONGITUD | E26: 34.25 | L26: LONGITUD | M26: 60.6
D27: ANCHO | E27: 0.6 | L27: ANCHO | M27: 0.6
C28: TAPA | D28: LONGITUD | E28: 0 | F28: =E28*E29*E30 -> 0 | K28: TAPA | L28: LONGITUD | M28: 10.75 | N28: =M28*M29*M30 -> 0.645
D29: ESPESOR | E29: 0.1 | L29: ESPESOR | M29: 0.1
D30: ANCHO | E30: 0.6 | L30: ANCHO | M30: 0.6
B33: LONGITUDES Y AREAS | E33: m3 | F33: Sub.TOTAL | G33: TOTAL (m3) | J33: LONGITUDES Y AREAS | M33: m3 | N33: Sub.TOTAL | O33: TOTAL (m3)
B34: CUNETA EJE 03 | C34: MUROS | D34: AREA | E34: 7.98 | F34: =E34*E35*E36 -> 1.596 | G34: =SUM(F34:F42) -> 2.94 | J34: CUNETA EJE 09 | K34: MUROS | L34: AREA | M34: 17.67 | N34: =M34*M35*M36 -> 3.534 | O34: =SUM(N34:N42) -> 6.4932
D35: ESPESOR | E35: 0.1 | L35: ESPESOR | M35: 0.1
D36: CANT. | E36: 2 | L36: CANT. | M36: 2
C37: LOSA | D37: ESPESOR | E37: 0.1 | F37: =E37*E38*E39 -> 1.344 | K37: LOSA | L37: ESPESOR | M37: 0.1 | N37: =M37*M38*M39 -> 2.5596
D38: LONGITUD | E38: 22.4 | L38: LONGITUD | M38: 42.66
D39: ANCHO | E39: 0.6 | L39: ANCHO | M39: 0.6
C40: TAPA | D40: LONGITUD | E40: 0 | F40: =E40*E41*E42 -> 0 | K40: TAPA | L40: LONGITUD | M40: 6.66 | N40: =M40*M41*M42 -> 0.3996
D41: ESPESOR | E41: 0.1 | L41: ESPESOR | M41: 0.1
D42: ANCHO | E42: 0.6 | L42: ANCHO | M42: 0.6
B45: LONGITUDES Y AREAS | E45: m3 | F45: Sub.TOTAL | G45: TOTAL (m3) | J45: LONGITUDES Y AREAS | M45: m3 | N45: Sub.TOTAL | O45: TOTAL (m3)
B46: CUNETA EJE 04 | C46: MUROS | D46: AREA | E46: 54.29 | F46: =E46*E47*E48 -> 10.858 | G46: =SUM(F46:F54) -> 18.8362 | K46: MUROS | L46: AREA | M46: 0 | N46: =M46*M47*M48 -> 0 | O46: =SUM(N46:N54) -> 0
D47: ESPESOR | E47: 0.1 | L47: ESPESOR | M47: 0.1
D48: CANT. | E48: 2 | L48: CANT. | M48: 2
C49: LOSA | D49: ESPESOR | E49: 0.1 | F49: =E49*E50*E51 -> 6.1386 | K49: LOSA | L49: ESPESOR | M49: 0.1 | N49: =M49*M50*M51 -> 0
D50: LONGITUD | E50: 102.31 | L50: LONGITUD | M50: 0
D51: ANCHO | E51: 0.6 | L51: ANCHO | M51: 0.6
C52: TAPA | D52: LONGITUD | E52: 30.66 | F52: =E52*E53*E54 -> 1.8396 | K52: TAPA | L52: LONGITUD | M52: 0 | N52: =M52*M53*M54 -> 0
D53: ESPESOR | E53: 0.1 | L53: ESPESOR | M53: 0.1
D54: ANCHO | E54: 0.6 | L54: ANCHO | M54: 0.6
B57: LONGITUDES Y AREAS | E57: m3 | F57: Sub.TOTAL | G57: TOTAL (m3) | J57: LONGITUDES Y AREAS | M57: m3 | N57: Sub.TOTAL | O57: TOTAL (m3)
B58: CUNETA EJE 05 | C58: MUROS | D58: AREA | E58: 17.07 | F58: =E58*E59*E60 -> 3.414 | G58: =SUM(F58:F66) -> 6.54 | K58: MUROS | L58: AREA | M58: 0 | N58: =M58*M59*M60 -> 0 | O58: =SUM(N58:N66) -> 0
D59: ESPESOR | E59: 0.1 | L59: ESPESOR | M59: 0.1
D60: CANT. | E60: 2 | L60: CANT. | M60: 2
C61: LOSA | D61: ESPESOR | E61: 0.1 | F61: =E61*E62*E63 -> 2.532 | K61: LOSA | L61: ESPESOR | M61: 0.1 | N61: =M61*M62*M63 -> 0
D62: LONGITUD | E62: 42.2 | L62: LONGITUD | M62: 0
D63: ANCHO | E63: 0.6 | L63: ANCHO | M63: 0.6
C64: TAPA | D64: LONGITUD | E64: 9.9 | F64: =E64*E65*E66 -> 0.594 | K64: TAPA | L64: LONGITUD | M64: 0 | N64: =M64*M65*M66 -> 0
D65: ESPESOR | E65: 0.1 | L65: ESPESOR | M65: 0.1
D66: ANCHO | E66: 0.6 | L66: ANCHO | M66: 0.6
B69: LONGITUDES Y AREAS | E69: m3 | F69: Sub.TOTAL | G69: TOTAL (m3) | J69: LONGITUDES Y AREAS | M69: m3 | N69: Sub.TOTAL | O69: TOTAL (m3)
B70: CUNETA EJE 06 | C70: MUROS | D70: AREA | E70: 52.71 | F70: =E70*E71*E72 -> 10.542 | G70: =SUM(F70:F78) -> 20.4348 | K70: MUROS | L70: AREA | M70: 0 | N70: =M70*M71*M72 -> 0 | O70: =SUM(N70:N78) -> 0
D71: ESPESOR | E71: 0.1 | L71: ESPESOR | M71: 0.1
D72: CANT. | E72: 2 | L72: CANT. | M72: 2
C73: LOSA | D73: ESPESOR | E73: 0.1 | F73: =E73*E74*E75 -> 5.9214 | K73: LOSA | L73: ESPESOR | M73: 0.1 | N73: =M73*M74*M75 -> 0
D74: LONGITUD | E74: 98.69 | L74: LONGITUD | M74: 0
D75: ANCHO | E75: 0.6 | L75: ANCHO | M75: 0.6
C76: TAPA | D76: LONGITUD | E76: 66.19 | F76: =E76*E77*E78 -> 3.9714 | K76: TAPA | L76: LONGITUD | M76: 0 | N76: =M76*M77*M78 -> 0
D77: ESPESOR | E77: 0.1 | L77: ESPESOR | M77: 0.1
D78: ANCHO | E78: 0.6 | L78: ANCHO | M78: 0.6

Sheet ENCOFRADO Y DESENCOFRADO
B2: ENCOFRADO Y DESENCOFRADO CUNETAS - DRENAJE PLUVIAL
B3: ENTIDAD | C3: =+RESUMEN!B4 -> GERENCIA TERRITORIAL BAJO MAYO - TARAPOTO
B4: PROYECTO | C4: =+RESUMEN!B5 -> CREACIÓN DEL SERVICIO DE PROTECCIÓN INTEGRAL A NIÑAS, NIÑOS Y ADOLESCENTES SIN CUIDADOS PARENTALES O EN RIESGO DE PERDERLOS EN CENTRO DE ACOGIDA RESIDENCIAL - VARONES DISTRITO DE MORALES DE LA PROVINCIA DE SAN MARTÍN DEL DEPARTAMENTO DE SAN MARTÍN, con CUI N.° 2705619
B5: UBICACIÓN | C5: =+RESUMEN!B6 -> SAN MARTIN - SAN MARTIN - MORALES
B6: FECHA | C6: =+RESUMEN!B7 -> 46266
B8: OBRAS DE CONCRETO ARMADO - ENCOFRADO Y DESENCOFRADO CUNETAS
B11: LONGITUDES Y AREAS | G11: Sub.TOTAL | H11: TOTAL (m2) | J11: LONGITUDES Y AREAS | O11: Sub.TOTAL | P11: TOTAL (m2)
B12: EJE 1 | C12: ABIERTA | D12: MUROS EXTERNO | E12: AREA | F12: 42.85 | G12: =F12*F13 -> 85.7 | H12: =SUM(G12:G20) -> 291.252 | J12: EJE 2 | K12: ABIERTA | L12: MUROS EXTERNO | M12: AREA | N12: 16.62 | O12: =N12*N13 -> 33.24 | P12: =SUM(O12:O20) -> 59.62
E13: CANT. | F13: 2 | M13: CANT. | N13: 2
D14: MURO INTERNO | E14: AREA | F14: 35.72 | G14: =F14*F15 -> 71.44 | L14: MURO INTERNO | M14: AREA | N14: 13.19 | O14: =N14*N15 -> 26.38
E15: CANTIDAD | F15: 2 | M15: CANTIDAD | N15: 2
C16: TAPADO | D16: MURO EXTERNO | E16: AREA | F16: 33.53 | G16: =F16*F17 -> 67.06 | K16: TAPADO | L16: MURO EXTERNO | M16: AREA | N16: 0 | O16: =N16*N17 -> 0
E17: CANT. | F17: 2 | M17: CANT. | N17: 2
D18: MURO INTERNO | E18: AREA | F18: 25.48 | G18: =(F18*F19)+F20 -> 67.052 | L18: MURO INTERNO | M18: AREA | N18: 0 | O18: =N18*N19+N20 -> 0
E19: CANTIDAD | F19: 2 | M19: CANTIDAD | N19: 2
E20: TAPA | F20: =40.23*0.4 -> 16.092 | M20: TAPA | N20: 0
B22: LONGITUDES Y AREAS | G22: Sub.TOTAL | H22: TOTAL (m2) | J22: LONGITUDES Y AREAS | O22: Sub.TOTAL | P22: TOTAL (m2)
B23: EJE 3 | C23: ABIERTA | D23: MUROS EXTERNO | E23: AREA | F23: 10.22 | G23: =F23*F24 -> 20.44 | H23: =SUM(G23:G31) -> 36.4 | J23: EJE 4 | K23: ABIERTA | L23: MUROS EXTERNO | M23: AREA | N23: 42.88 | O23: =N23*N24 -> 85.76 | P23: =SUM(O23:O31) -> 256.004
E24: CANT. | F24: 2 | M24: CANT. | N24: 2
D25: MURO INTERNO | E25: AREA | F25: 7.98 | G25: =F25*F26 -> 15.96 | L25: MURO INTERNO | M25: AREA | N25: 35.72 | O25: =N25*N26 -> 71.44
E26: CANTIDAD | F26: 2 | M26: CANTIDAD | N26: 2
C27: TAPADO | D27: MURO EXTERNO | E27: AREA | F27: 0 | G27: =F27*F28 -> 0 | K27: TAPADO | L27: MURO EXTERNO | M27: AREA | N27: 24.7 | O27: =N27*N28 -> 49.4
E28: CANT. | F28: 2 | M28: CANT. | N28: 2
D29: MURO INTERNO | E29: AREA | F29: 0 | G29: =F29*F30+F31 -> 0 | L29: MURO INTERNO | M29: AREA | N29: 18.57 | O29: =N29*N30+N31 -> 49.404
E30: CANTIDAD | F30: 2 | M30: CANTIDAD | N30: 2
E31: TAPA | F31: 0 | M31: TAPA | N31: =30.66*0.4 -> 12.264
B33: LONGITUDES Y AREAS | G33: Sub.TOTAL | H33: TOTAL (m2) | J33: LONGITUDES Y AREAS | O33: Sub.TOTAL | P33: TOTAL (m2)
B34: EJE 5 | C34: ABIERTA | D34: MUROS EXTERNO | E34: AREA | F34: 15.51 | G34: =F34*F35 -> 31.02 | H34: =SUM(G34:G42) -> 82.66 | J34: EJE 6 | K34: ABIERTA | L34: MUROS EXTERNO | M34: AREA | N34: 15.61 | O34: =N34*N35 -> 31.22 | P34: =SUM(O34:O42) -> 270.296
E35: CANT. | F35: 2 | M35: CANT. | N35: 2
D36: MURO INTERNO | E36: AREA | F36: 12.28 | G36: =F36*F37 -> 24.56 | L36: MURO INTERNO | M36: AREA | N36: 12.36 | O36: =N36*N37 -> 24.72
E37: CANTIDAD | F37: 2 | M37: CANTIDAD | N37: 2
C38: TAPADO | D38: MURO EXTERNO | E38: AREA | F38: 6.77 | G38: =F38*F39 -> 13.54 | K38: TAPADO | L38: MURO EXTERNO | M38: AREA | N38: 53.59 | O38: =N38*N39 -> 107.18
E39: CANT. | F39: 2 | M39: CANT. | N39: 2
D40: MURO INTERNO | E40: AREA | F40: 4.79 | G40: =F40*F41+F42 -> 13.54 | L40: MURO INTERNO | M40: AREA | N40: 40.35 | O40: =N40*N41+N42 -> 107.176
E41: CANTIDAD | F41: 2 | M41: CANTIDAD | N41: 2
E42: TAPA | F42: =9.9*0.4 -> 3.96 | M42: TAPA | N42: =66.19*0.4 -> 26.476
B44: LONGITUDES Y AREAS | G44: Sub.TOTAL | H44: TOTAL (m2) | J44: LONGITUDES Y AREAS | O44: Sub.TOTAL | P44: TOTAL (m2)
B45: EJE 7 | C45: ABIERTA | D45: MUROS EXTERNO | E45: AREA | F45: 10.82 | G45: =F45*F46 -> 21.64 | H45: =SUM(G45:G53) -> 38.56 | J45: EJE 8 | K45: ABIERTA | L45: MUROS EXTERNO | M45: AREA | N45: 26.15 | O45: =N45*N46 -> 52.3 | P45: =SUM(O45:O53) -> 127.92
E46: CANT. | F46: 2 | M46: CANT. | N46: 2
D47: MURO INTERNO | E47: AREA | F47: 8.46 | G47: =F47*F48 -> 16.92 | L47: MURO INTERNO | M47: AREA | N47: 21.17 | O47: =N47*N48 -> 42.34
E48: CANTIDAD | F48: 2 | M48: CANTIDAD | N48: 2
C49: TAPADO | D49: MURO EXTERNO | E49: AREA | F49: 0 | G49: =F49*F50 -> 0 | K49: TAPADO | L49: MURO EXTERNO | M49: AREA | N49: 8.32 | O49: =N49*N50 -> 16.64
E50: CANT. | F50: 2 | M50: CANT. | N50: 2
D51: MURO INTERNO | E51: AREA | F51: 0 | G51: =F51*F52+F53 -> 0 | L51: MURO INTERNO | M51: AREA | N51: 6.17 | O51: =N51*N52+N53 -> 16.64
E52: CANTIDAD | F52: 2 | M52: CANTIDAD | N52: 2
E53: TAPA | F53: 0 | M53: TAPA | N53: =10.75*0.4 -> 4.3
B56: LONGITUDES Y AREAS | G56: Sub.TOTAL | H56: TOTAL (m2) | J56: LONGITUDES Y AREAS | O56: Sub.TOTAL | P56: TOTAL (m2)
B57: EJE 9 | C57: ABIERTA | D57: MUROS EXTERNO | E57: AREA | F57: 17.69 | G57: =F57*F58 -> 35.38 | H57: =SUM(G57:G65) -> 83.204 | L57: MUROS EXTERNO | M57: AREA | N57: 0 | O57: =N57*N58 -> 0 | P57: =SUM(O57:O65) -> 0
E58: CANT. | F58: 2 | M58: CANT. | N58: 2
D59: MURO INTERNO | E59: AREA | F59: 14.09 | G59: =F59*F60 -> 28.18 | L59: MURO INTERNO | M59: AREA | N59: 0 | O59: =N59*N60 -> 0
E60: CANTIDAD | F60: 2 | M60: CANTIDAD | N60: 2
C61: TAPADO | D61: MURO EXTERNO | E61: AREA | F61: 4.91 | G61: =F61*F62 -> 9.82 | K61: TAPADO | L61: MURO EXTERNO | M61: AREA | N61: 0 | O61: =N61*N62 -> 0
E62: CANT. | F62: 2 | M62: CANT. | N62: 2
D63: MURO INTERNO | E63: AREA | F63: 3.58 | G63: =F63*F64+F65 -> 9.824 | L63: MURO INTERNO | M63: AREA | N63: 0 | O63: =N63*N64+N65 -> 0
E64: CANTIDAD | F64: 2 | M64: CANTIDAD | N64: 2
E65: TAPA | F65: =6.66*0.4 -> 2.664 | M65: TAPA | N65: 0
B68: LONGITUDES Y AREAS | G68: Sub.TOTAL | H68: TOTAL (m2) | J68: LONGITUDES Y AREAS | O68: Sub.TOTAL | P68: TOTAL (m2)
D69: MUROS EXTERNO | E69: AREA | F69: 0 | G69: =F69*F70 -> 0 | H69: =SUM(G69:G77) -> 0 | L69: MUROS EXTERNO | M69: AREA | N69: 0 | O69: =N69*N70 -> 0 | P69: =SUM(O69:O77) -> 0
E70: CANT. | F70: 2 | M70: CANT. | N70: 2
D71: MURO INTERNO | E71: AREA | F71: 0 | G71: =F71*F72 -> 0 | L71: MURO INTERNO | M71: AREA | N71: 0 | O71: =N71*N72 -> 0
E72: CANTIDAD | F72: 2 | M72: CANTIDAD | N72: 2
C73: TAPADO | D73: MURO EXTERNO | E73: AREA | F73: 0 | G73: =F73*F74 -> 0 | K73: TAPADO | L73: MURO EXTERNO | M73: AREA | N73: 0 | O73: =N73*N74 -> 0
E74: CANT. | F74: 2 | M74: CANT. | N74: 2
D75: MURO INTERNO | E75: AREA | F75: 0 | G75: =F75*F76+F77 -> 0 | L75: MURO INTERNO | M75: AREA | N75: 0 | O75: =N75*N76+N77 -> 0
E76: CANTIDAD | F76: 2 | M76: CANTIDAD | N76: 2
E77: TAPA | F77: 0 | M77: TAPA | N77: 0

Sheet METRADO MONTANTES
B2: CALCULO DE MONTANTES POR EDIFICACION - DRENAJE PLUVIAL
B3: ENTIDAD | C3: =+RESUMEN!B4 -> GERENCIA TERRITORIAL BAJO MAYO - TARAPOTO
B4: PROYECTO | C4: =+RESUMEN!B5 -> CREACIÓN DEL SERVICIO DE PROTECCIÓN INTEGRAL A NIÑAS, NIÑOS Y ADOLESCENTES SIN CUIDADOS PARENTALES O EN RIESGO DE PERDERLOS EN CENTRO DE ACOGIDA RESIDENCIAL - VARONES DISTRITO DE MORALES DE LA PROVINCIA DE SAN MARTÍN DEL DEPARTAMENTO DE SAN MARTÍN, con CUI N.° 2705619
B5: UBICACIÓN | C5: =+RESUMEN!B6 -> SAN MARTIN - SAN MARTIN - MORALES
B6: FECHA | C6: =+RESUMEN!B7 -> 46266
C9: MONTANTES | D9: LONG. TUBERIA PVC 4" | G9: CODO PVC 90° 4" | J9: ABRAZADERA 4" | M9: COLGADOR 4"
D10: VECES | E10: LONGITUD | F10: TOTAL (m) | G10: CANTIDAD | H10: VECES | I10: TOTAL (und) | J10: CANTIDAD | K10: VECES | L10: TOTAL (und) | M10: CANTIDAD | N10: VECES | O10: TOTAL (und)
B11: EDIFICACION 01
B12: Lado A | C12: 2 | D12: 2 | E12: 6.22 | F12: =E12*D12 -> 12.44 | G12: 3 | H12: 2 | I12: =H12*G12 -> 6 | J12: 1 | K12: 2 | L12: =K12*J12 -> 2 | M12: 2 | N12: 2 | O12: =N12*M12 -> 4
B13: Lado B | C13: 2 | D13: 2 | E13: 6.22 | F13: =E13*D13 -> 12.44 | G13: 3 | H13: 2 | I13: =H13*G13 -> 6 | J13: 1 | K13: 2 | L13: =K13*J13 -> 2 | M13: 2 | N13: 2 | O13: =N13*M13 -> 4
B14: EDIFICACION 02
B15: Lado A | C15: 2 | D15: 2 | E15: 6.2 | F15: =E15*D15 -> 12.4 | G15: 3 | H15: 2 | I15: =H15*G15 -> 6 | J15: 1 | K15: 2 | L15: =K15*J15 -> 2 | M15: 2 | N15: 2 | O15: =N15*M15 -> 4
B16: Lado B | C16: 2 | D16: 2 | E16: 6.2 | F16: =E16*D16 -> 12.4 | G16: 3 | H16: 2 | I16: =H16*G16 -> 6 | J16: 1 | K16: 2 | L16: =K16*J16 -> 2 | M16: 2 | N16: 2 | O16: =N16*M16 -> 4
B17: EDIFICACION 03
B18: Lado A | C18: 2 | D18: 2 | E18: 6.26 | F18: =E18*D18 -> 12.52 | G18: 3 | H18: 2 | I18: =H18*G18 -> 6 | J18: 1 | K18: 2 | L18: =K18*J18 -> 2 | M18: 2 | N18: 2 | O18: =N18*M18 -> 4
B19: Lado B | C19: 2 | D19: 2 | E19: 6.26 | F19: =E19*D19 -> 12.52 | G19: 3 | H19: 2 | I19: =H19*G19 -> 6 | J19: 1 | K19: 2 | L19: =K19*J19 -> 2 | M19: 2 | N19: 2 | O19: =N19*M19 -> 4
B20: EDIFICACION 04
B21: Lado A | C21: 2 | D21: 2 | E21: 6.16 | F21: =E21*D21 -> 12.32 | G21: 3 | H21: 2 | I21: =H21*G21 -> 6 | J21: 1 | K21: 2 | L21: =K21*J21 -> 2 | M21: 2 | N21: 2 | O21: =N21*M21 -> 4
B22: Lado B | C22: 2 | D22: 2 | E22: 6.16 | F22: =E22*D22 -> 12.32 | G22: 3 | H22: 2 | I22: =H22*G22 -> 6 | J22: 1 | K22: 2 | L22: =K22*J22 -> 2 | M22: 2 | N22: 2 | O22: =N22*M22 -> 4
B23: EDIFICACION 05
B24: Lado A | C24: 2 | D24: 2 | E24: 6.24 | F24: =E24*D24 -> 12.48 | G24: 3 | H24: 2 | I24: =H24*G24 -> 6 | J24: 1 | K24: 2 | L24: =K24*J24 -> 2 | M24: 2 | N24: 2 | O24: =N24*M24 -> 4
B25: Lado B | C25: 2 | D25: 2 | E25: 6.24 | F25: =E25*D25 -> 12.48 | G25: 3 | H25: 2 | I25: =H25*G25 -> 6 | J25: 1 | K25: 2 | L25: =K25*J25 -> 2 | M25: 2 | N25: 2 | O25: =N25*M25 -> 4
B26: EDIFICACION 06
B27: Lado A | C27: 2 | D27: 2 | E27: 6.21 | F27: =E27*D27 -> 12.42 | G27: 3 | H27: 2 | I27: =H27*G27 -> 6 | J27: 1 | K27: 2 | L27: =K27*J27 -> 2 | M27: 2 | N27: 2 | O27: =N27*M27 -> 4
B28: Lado B | C28: 2 | D28: 2 | E28: 6.21 | F28: =E28*D28 -> 12.42 | G28: 3 | H28: 2 | I28: =H28*G28 -> 6 | J28: 1 | K28: 2 | L28: =K28*J28 -> 2 | M28: 2 | N28: 2 | O28: =N28*M28 -> 4
B29: EDIFICACION 07
B30: Lado A | C30: 2 | D30: 2 | E30: 6.17 | F30: =E30*D30 -> 12.34 | G30: 3 | H30: 2 | I30: =H30*G30 -> 6 | J30: 1 | K30: 2 | L30: =K30*J30 -> 2 | M30: 2 | N30: 2 | O30: =N30*M30 -> 4
B31: Lado B | C31: 2 | D31: 2 | E31: 6.17 | F31: =E31*D31 -> 12.34 | G31: 3 | H31: 2 | I31: =H31*G31 -> 6 | J31: 1 | K31: 2 | L31: =K31*J31 -> 2 | M31: 2 | N31: 2 | O31: =N31*M31 -> 4
B32: EDIFICACION 08
B33: Lado A | C33: 2 | D33: 2 | E33: 7.33 | F33: =E33*D33 -> 14.66 | G33: 3 | H33: 2 | I33: =H33*G33 -> 6 | J33: 2 | K33: 2 | L33: =K33*J33 -> 4 | M33: 2 | N33: 2 | O33: =N33*M33 -> 4
B34: Lado B | C34: 2 | D34: 2 | E34: 7.33 | F34: =E34*D34 -> 14.66 | G34: 3 | H34: 2 | I34: =H34*G34 -> 6 | J34: 2 | K34: 2 | L34: =K34*J34 -> 4 | M34: 2 | N34: 2 | O34: =N34*M34 -> 4
B35: Lado A" | C35: 2 | D35: 2 | E35: 9.96 | F35: =E35*D35 -> 19.92 | G35: 3 | H35: 2 | I35: =H35*G35 -> 6 | J35: 2 | K35: 2 | L35: =K35*J35 -> 4 | M35: 2 | N35: 2 | O35: =N35*M35 -> 4
B36: Lado B" | C36: 2 | D36: 2 | E36: 9.96 | F36: =E36*D36 -> 19.92 | G36: 3 | H36: 2 | I36: =H36*G36 -> 6 | J36: 2 | K36: 2 | L36: =K36*J36 -> 4 | M36: 2 | N36: 2 | O36: =N36*M36 -> 4
B37: EDIFICACION 09
B38: Lado A | C38: 2 | D38: 2 | E38: 6.25 | F38: =E38*D38 -> 12.5 | G38: 3 | H38: 2 | I38: =H38*G38 -> 6 | J38: 1 | K38: 2 | L38: =K38*J38 -> 2 | M38: 2 | N38: 2 | O38: =N38*M38 -> 4
B39: Lado B | C39: 2 | D39: 2 | E39: 6.26 | F39: =E39*D39 -> 12.52 | G39: 3 | H39: 2 | I39: =H39*G39 -> 6 | J39: 1 | K39: 2 | L39: =K39*J39 -> 2 | M39: 2 | N39: 2 | O39: =N39*M39 -> 4
B40: EDIFICACION 10
B41: Lado A | C41: 2 | D41: 2 | E41: 6.2 | F41: =E41*D41 -> 12.4 | G41: 3 | H41: 2 | I41: =H41*G41 -> 6 | J41: 1 | K41: 2 | L41: =K41*J41 -> 2 | M41: 2 | N41: 2 | O41: =N41*M41 -> 4
B42: Lado B | C42: 2 | D42: 2 | E42: 6.2 | F42: =E42*D42 -> 12.4 | G42: 3 | H42: 2 | I42: =H42*G42 -> 6 | J42: 1 | K42: 2 | L42: =K42*J42 -> 2 | M42: 2 | N42: 2 | O42: =N42*M42 -> 4
B43: LOSA DEPORTIVA | F43: =E43*D43 -> 0 | I43: =H43*G43 -> 0 | L43: =K43*J43 -> 0 | O43: =N43*M43 -> 0
B44: Lado A | C44: 4 | D44: 4 | E44: 11 | F44: =E44*D44 -> 44 | G44: 3 | H44: 4 | I44: =H44*G44 -> 12 | J44: 3 | K44: 4 | L44: =K44*J44 -> 12 | M44: 1 | N44: 4 | O44: =N44*M44 -> 4
B45: Lado B | C45: 4 | D45: 4 | E45: 11 | F45: =E45*D45 -> 44 | G45: 3 | H45: 4 | I45: =H45*G45 -> 12 | J45: 3 | K45: 4 | L45: =K45*J45 -> 12 | M45: 1 | N45: 4 | O45: =N45*M45 -> 4
B46: OBRA EXTERIOR 01 | C46: 1 | D46: 1 | E46: 6.9 | F46: =E46*D46 -> 6.9 | G46: 3 | H46: 1 | I46: =H46*G46 -> 3 | J46: 1 | K46: 1 | L46: =K46*J46 -> 1 | M46: 1 | N46: 1 | O46: =N46*M46 -> 1
B47: OBRA EXTERIOR03 | C47: 2 | D47: 2 | E47: 6.7 | F47: =E47*D47 -> 13.4 | G47: 3 | H47: 2 | I47: =H47*G47 -> 6 | J47: 1 | K47: 2 | L47: =K47*J47 -> 2 | M47: 1 | N47: 2 | O47: =N47*M47 -> 2
B48: OBRA EXTERIOR 01.1 | C48: 1 | D48: 1 | E48: 6.9 | F48: =E48*D48 -> 6.9 | G48: 3 | H48: 1 | I48: =H48*G48 -> 3 | J48: 1 | K48: 1 | L48: =K48*J48 -> 1 | M48: 1 | N48: 1 | O48: =N48*M48 -> 1
C49: =SUM(C11:C48) -> 56 | F49: =SUM(F11:F48) -> 408.02 | I49: =SUM(I11:I48) -> 168 | L49: =SUM(L11:L48) -> 80 | O49: =SUM(O11:O48) -> 100

Sheet METRADO CANALETAS
B2: METRADO DE CANALETAS DE TECHO - DRENAJE PLUVIAL
B3: ENTIDAD | C3: =+RESUMEN!B4 -> GERENCIA TERRITORIAL BAJO MAYO - TARAPOTO
B4: PROYECTO | C4: =+RESUMEN!B5 -> CREACIÓN DEL SERVICIO DE PROTECCIÓN INTEGRAL A NIÑAS, NIÑOS Y ADOLESCENTES SIN CUIDADOS PARENTALES O EN RIESGO DE PERDERLOS EN CENTRO DE ACOGIDA RESIDENCIAL - VARONES DISTRITO DE MORALES DE LA PROVINCIA DE SAN MARTÍN DEL DEPARTAMENTO DE SAN MARTÍN, con CUI N.° 2705619
B5: UBICACIÓN | C5: =+RESUMEN!B6 -> SAN MARTIN - SAN MARTIN - MORALES
B6: FECHA | C6: =+RESUMEN!B7 -> 46266
B8: CANALETA DE PLANCHA DE ACERO GALVANIZADO - SECCIÓN INTERIOR 0.25 m (FONDO) x 0.20 m (ALTO) - TECHOS A DOS AGUAS: UNA CANALETA POR CADA LADO
B9: EDIFICACIÓN | C9: N° DE CANALETAS | D9: CANALETA 0.25 x 0.20 m | F9: SOPORTE PLATINA F°G° 1" x 1/8" | H9: TAPA LATERAL | J9: BOQUILLA A MONTANTE Ø4"
D10: LONGITUD (m) | E10: TOTAL (m) | F10: CANTIDAD | G10: TOTAL (und) | H10: CANTIDAD | I10: TOTAL (und) | J10: CANTIDAD | K10: TOTAL (und)
B11: EDIFICACION 01
B12: Lado 01 | C12: 1 | D12: 25.78 | E12: =C12*D12 -> 25.78 | F12: =IF(D12>0,ROUNDUP(D12/$F$53,0)+1,0) -> 44 | G12: =C12*F12 -> 44 | H12: =$F$54 -> 2 | I12: =C12*H12 -> 2 | J12: ='METRADO MONTANTES'!C12 -> 2 | K12: =C12*J12 -> 2
B13: Lado 02 | C13: 1 | D13: =D12 -> 25.78 | E13: =C13*D13 -> 25.78 | F13: =IF(D13>0,ROUNDUP(D13/$F$53,0)+1,0) -> 44 | G13: =C13*F13 -> 44 | H13: =$F$54 -> 2 | I13: =C13*H13 -> 2 | J13: ='METRADO MONTANTES'!C13 -> 2 | K13: =C13*J13 -> 2
B14: EDIFICACION 02
B15: Lado 01 | C15: 1 | D15: 14.77 | E15: =C15*D15 -> 14.77 | F15: =IF(D15>0,ROUNDUP(D15/$F$53,0)+1,0) -> 26 | G15: =C15*F15 -> 26 | H15: =$F$54 -> 2 | I15: =C15*H15 -> 2 | J15: ='METRADO MONTANTES'!C15 -> 2 | K15: =C15*J15 -> 2
B16: Lado 02 | C16: 1 | D16: =D15 -> 14.77 | E16: =C16*D16 -> 14.77 | F16: =IF(D16>0,ROUNDUP(D16/$F$53,0)+1,0) -> 26 | G16: =C16*F16 -> 26 | H16: =$F$54 -> 2 | I16: =C16*H16 -> 2 | J16: ='METRADO MONTANTES'!C16 -> 2 | K16: =C16*J16 -> 2
B17: EDIFICACION 03
B18: Lado 01 | C18: 1 | D18: 16.05 | E18: =C18*D18 -> 16.05 | F18: =IF(D18>0,ROUNDUP(D18/$F$53,0)+1,0) -> 28 | G18: =C18*F18 -> 28 | H18: =$F$54 -> 2 | I18: =C18*H18 -> 2 | J18: ='METRADO MONTANTES'!C18 -> 2 | K18: =C18*J18 -> 2
B19: Lado 02 | C19: 1 | D19: =D18 -> 16.05 | E19: =C19*D19 -> 16.05 | F19: =IF(D19>0,ROUNDUP(D19/$F$53,0)+1,0) -> 28 | G19: =C19*F19 -> 28 | H19: =$F$54 -> 2 | I19: =C19*H19 -> 2 | J19: ='METRADO MONTANTES'!C19 -> 2 | K19: =C19*J19 -> 2
B20: EDIFICACION 04
B21: Lado 01 | C21: 1 | D21: 27.15 | E21: =C21*D21 -> 27.15 | F21: =IF(D21>0,ROUNDUP(D21/$F$53,0)+1,0) -> 47 | G21: =C21*F21 -> 47 | H21: =$F$54 -> 2 | I21: =C21*H21 -> 2 | J21: ='METRADO MONTANTES'!C21 -> 2 | K21: =C21*J21 -> 2
B22: Lado 02 | C22: 1 | D22: =D21 -> 27.15 | E22: =C22*D22 -> 27.15 | F22: =IF(D22>0,ROUNDUP(D22/$F$53,0)+1,0) -> 47 | G22: =C22*F22 -> 47 | H22: =$F$54 -> 2 | I22: =C22*H22 -> 2 | J22: ='METRADO MONTANTES'!C22 -> 2 | K22: =C22*J22 -> 2
B23: EDIFICACION 05
B24: Lado 01 | C24: 1 | D24: 27.15 | E24: =C24*D24 -> 27.15 | F24: =IF(D24>0,ROUNDUP(D24/$F$53,0)+1,0) -> 47 | G24: =C24*F24 -> 47 | H24: =$F$54 -> 2 | I24: =C24*H24 -> 2 | J24: ='METRADO MONTANTES'!C24 -> 2 | K24: =C24*J24 -> 2
B25: Lado 02 | C25: 1 | D25: =D24 -> 27.15 | E25: =C25*D25 -> 27.15 | F25: =IF(D25>0,ROUNDUP(D25/$F$53,0)+1,0) -> 47 | G25: =C25*F25 -> 47 | H25: =$F$54 -> 2 | I25: =C25*H25 -> 2 | J25: ='METRADO MONTANTES'!C25 -> 2 | K25: =C25*J25 -> 2
B26: EDIFICACION 06
B27: Lado 01 | C27: 1 | D27: 27.2 | E27: =C27*D27 -> 27.2 | F27: =IF(D27>0,ROUNDUP(D27/$F$53,0)+1,0) -> 47 | G27: =C27*F27 -> 47 | H27: =$F$54 -> 2 | I27: =C27*H27 -> 2 | J27: ='METRADO MONTANTES'!C27 -> 2 | K27: =C27*J27 -> 2
B28: Lado 02 | C28: 1 | D28: =D27 -> 27.2 | E28: =C28*D28 -> 27.2 | F28: =IF(D28>0,ROUNDUP(D28/$F$53,0)+1,0) -> 47 | G28: =C28*F28 -> 47 | H28: =$F$54 -> 2 | I28: =C28*H28 -> 2 | J28: ='METRADO MONTANTES'!C28 -> 2 | K28: =C28*J28 -> 2
B29: EDIFICACION 07
B30: Lado 01 | C30: 1 | D30: 27.15 | E30: =C30*D30 -> 27.15 | F30: =IF(D30>0,ROUNDUP(D30/$F$53,0)+1,0) -> 47 | G30: =C30*F30 -> 47 | H30: =$F$54 -> 2 | I30: =C30*H30 -> 2 | J30: ='METRADO MONTANTES'!C30 -> 2 | K30: =C30*J30 -> 2
B31: Lado 02 | C31: 1 | D31: =D30 -> 27.15 | E31: =C31*D31 -> 27.15 | F31: =IF(D31>0,ROUNDUP(D31/$F$53,0)+1,0) -> 47 | G31: =C31*F31 -> 47 | H31: =$F$54 -> 2 | I31: =C31*H31 -> 2 | J31: ='METRADO MONTANTES'!C31 -> 2 | K31: =C31*J31 -> 2
B32: EDIFICACION 08
B33: Lado 01 | C33: 1 | D33: 34.58 | E33: =C33*D33 -> 34.58 | F33: =IF(D33>0,ROUNDUP(D33/$F$53,0)+1,0) -> 59 | G33: =C33*F33 -> 59 | H33: =$F$54 -> 2 | I33: =C33*H33 -> 2 | J33: ='METRADO MONTANTES'!C33+'METRADO MONTANTES'!C35 -> 4 | K33: =C33*J33 -> 4
B34: Lado 02 | C34: 1 | D34: =D33 -> 34.58 | E34: =C34*D34 -> 34.58 | F34: =IF(D34>0,ROUNDUP(D34/$F$53,0)+1,0) -> 59 | G34: =C34*F34 -> 59 | H34: =$F$54 -> 2 | I34: =C34*H34 -> 2 | J34: ='METRADO MONTANTES'!C34+'METRADO MONTANTES'!C36 -> 4 | K34: =C34*J34 -> 4
B35: EDIFICACION 09
B36: Lado 01 | C36: 1 | D36: 9.7 | E36: =C36*D36 -> 9.7 | F36: =IF(D36>0,ROUNDUP(D36/$F$53,0)+1,0) -> 18 | G36: =C36*F36 -> 18 | H36: =$F$54 -> 2 | I36: =C36*H36 -> 2 | J36: ='METRADO MONTANTES'!C38 -> 2 | K36: =C36*J36 -> 2
B37: Lado 02 | C37: 1 | D37: =D36 -> 9.7 | E37: =C37*D37 -> 9.7 | F37: =IF(D37>0,ROUNDUP(D37/$F$53,0)+1,0) -> 18 | G37: =C37*F37 -> 18 | H37: =$F$54 -> 2 | I37: =C37*H37 -> 2 | J37: ='METRADO MONTANTES'!C39 -> 2 | K37: =C37*J37 -> 2
B38: EDIFICACION 10
B39: Lado 01 | C39: 1 | D39: 15.4 | E39: =C39*D39 -> 15.4 | F39: =IF(D39>0,ROUNDUP(D39/$F$53,0)+1,0) -> 27 | G39: =C39*F39 -> 27 | H39: =$F$54 -> 2 | I39: =C39*H39 -> 2 | J39: ='METRADO MONTANTES'!C41 -> 2 | K39: =C39*J39 -> 2
B40: Lado 02 | C40: 1 | D40: =D39 -> 15.4 | E40: =C40*D40 -> 15.4 | F40: =IF(D40>0,ROUNDUP(D40/$F$53,0)+1,0) -> 27 | G40: =C40*F40 -> 27 | H40: =$F$54 -> 2 | I40: =C40*H40 -> 2 | J40: ='METRADO MONTANTES'!C42 -> 2 | K40: =C40*J40 -> 2
B41: LOSA DEPORTIVA
B42: Lado 01 | C42: 1 | D42: 36.65 | E42: =C42*D42 -> 36.65 | F42: =IF(D42>0,ROUNDUP(D42/$F$53,0)+1,0) -> 63 | G42: =C42*F42 -> 63 | H42: =$F$54 -> 2 | I42: =C42*H42 -> 2 | J42: ='METRADO MONTANTES'!C44 -> 4 | K42: =C42*J42 -> 4
B43: Lado 02 | C43: 1 | D43: =D42 -> 36.65 | E43: =C43*D43 -> 36.65 | F43: =IF(D43>0,ROUNDUP(D43/$F$53,0)+1,0) -> 63 | G43: =C43*F43 -> 63 | H43: =$F$54 -> 2 | I43: =C43*H43 -> 2 | J43: ='METRADO MONTANTES'!C45 -> 4 | K43: =C43*J43 -> 4
B44: TOTAL | C44: =SUM(C11:C43) -> 22 | E44: =SUM(E11:E43) -> 523.16 | G44: =SUM(G11:G43) -> 906 | I44: =SUM(I11:I43) -> 44 | K44: =SUM(K11:K43) -> 52
B46: PARÁMETROS DE CÁLCULO - CANALETA
B47: DESCRIPCIÓN | F47: VALOR | G47: UNIDAD | H47: CRITERIO
B48: Fondo interior de canaleta | F48: 0.25 | G48: m | H48: Dato del proyecto
B49: Altura interior de canaleta | F49: 0.2 | G49: m | H49: Dato del proyecto
B50: Doblez o pestaña superior (por cada lado) | F50: 0.05 | G50: m | H50: Editable según detalle
B51: Desarrollo de plancha (fondo + 2 alturas + 2 dobleces) | F51: =F48+2*F49+2*F50 -> 0.75 | G51: m | H51: Calculado
B52: Espesor de plancha galvanizada | F52: 0.9 | G52: mm | H52: Editable según EE.TT. (cambiar también la descripción de la partida)
B53: Separación de soportes | F53: 0.6 | G53: m | H53: Editable. Soportes por canaleta = REDONDEAR.MAS(L / sep) + 1
B54: Tapas laterales por canaleta | F54: 2 | G54: und | H54: Una en cada extremo
B55: Área de plancha galvanizada (referencial) | F55: =E44*F51 -> 392.37 | G55: m² | H55: Total de canaleta x desarrollo. Solo referencia para el análisis de costos

Sheet METRADO  EN PISO (SUMIDERO)
A1: PLANILLA DE METRADOS - RED DE DRENAJE EN PISO Y SUMIDEROS
A2: ENTIDAD | B2: =+RESUMEN!B4 -> GERENCIA TERRITORIAL BAJO MAYO - TARAPOTO
A3: PROYECTO | B3: =+RESUMEN!B5 -> CREACIÓN DEL SERVICIO DE PROTECCIÓN INTEGRAL A NIÑAS, NIÑOS Y ADOLESCENTES SIN CUIDADOS PARENTALES O EN RIESGO DE PERDERLOS EN CENTRO DE ACOGIDA RESIDENCIAL - VARONES DISTRITO DE MORALES DE LA PROVINCIA DE SAN MARTÍN DEL DEPARTAMENTO DE SAN MARTÍN, con CUI N.° 2705619
A4: UBICACIÓN | B4: =+RESUMEN!B6 -> SAN MARTIN - SAN MARTIN - MORALES
A5: FECHA | B5: =+RESUMEN!B7 -> 46266
A7: SECTOR | B7: TUBERÍA 4" PVC-U Desagüe Clase Pesada (m) | C7: SUMIDERO DE 4" (und) | D7: CODO 90° x 4" (und) | E7: CODO 45° x 4" (und) | F7: TEE° x 4" (und) | G7: OBSERVACIÓN
A8: SECTOR 01 | B8: 19.1 | C8: 5 | D8: 5 | E8: 0 | F8: 0 | G8: Sin datos de Varones
A9: SECTOR 02 | B9: 57.98 | C9: 9 | D9: 6 | E9: 0 | F9: 3 | G9: Sin datos de Varones
A10: SECTOR 03 | B10: 15 | C10: 2 | D10: 2 | E10: 0 | F10: 0 | G10: Sin datos de Varones
A11: TOTAL | B11: =SUM(B8:B10) -> 92.08 | C11: =SUM(C8:C10) -> 16 | D11: =SUM(D8:D10) -> 13 | E11: =SUM(E8:E10) -> 0 | F11: =SUM(F8:F10) -> 3

Sheet METRADO ACERO
A2: METRADO DE ACERO EN CUNETAS - DRENAJE PLUVIAL
A3: ENTIDAD | B3: =+RESUMEN!B4 -> GERENCIA TERRITORIAL BAJO MAYO - TARAPOTO
A4: PROYECTO | B4: =+RESUMEN!B5 -> CREACIÓN DEL SERVICIO DE PROTECCIÓN INTEGRAL A NIÑAS, NIÑOS Y ADOLESCENTES SIN CUIDADOS PARENTALES O EN RIESGO DE PERDERLOS EN CENTRO DE ACOGIDA RESIDENCIAL - VARONES DISTRITO DE MORALES DE LA PROVINCIA DE SAN MARTÍN DEL DEPARTAMENTO DE SAN MARTÍN, con CUI N.° 2705619
A5: UBICACIÓN | B5: =+RESUMEN!B6 -> SAN MARTIN - SAN MARTIN - MORALES
A6: FECHA | B6: =+RESUMEN!B7 -> 46266
A8: METRADO DETALLADO POR EJE Y POR TRAMO
A9: IDENTIFICACIÓN Y GEOMETRÍA | H9: ACERO LONGITUDINAL DEL CUERPO U | P9: ACERO TRANSVERSAL DEL CUERPO U | X9: ACERO TRANSVERSAL DE LA TAPA (SOLO CUNETA TAPADA) | AG9: RESULTADO
A10: N° | B10: EJE | C10: TRAMO | D10: TIPO DE CUNETA | E10: SEC. INI | F10: SEC. FIN | G10: LONGITUD TRAMO (m) | H10: Ø CUERPO | I10: FACTOR CUERPO (kg/m) | J10: SEP. LONG. (m) | K10: BARRAS LONG. INI | L10: BARRAS LONG. FIN | M10: BARRAS PROM. | N10: LONG. ACERO LONG. (m) | O10: KG LONG. | P10: SEP. TRANSV. U (m) | Q10: DES. TRANSV. U INI (m) | R10: DES. TRANSV. U FIN (m) | S10: DES. PROM. U (m) | T10: CANT. TRANSV. U | U10: LONG. ACERO TRANSV. U (m) | V10: KG TRANSV. U | W10: TOTAL KG CUERPO U | X10: Ø TAPA | Y10: FACTOR TAPA (kg/m) | Z10: SEP. TRANSV. TAPA (m) | AA10: LONG. BARRA TAPA INI (m) | AB10: LONG. BARRA TAPA FIN (m) | AC10: LONG. PROM. TAPA (m) | AD10: CANT. BARRAS TAPA | AE10: LONG. ACERO TAPA (m) | AF10: KG ACERO TAPA | AG10: TOTAL KG TRAMO
A11: 1 | B11: EJE 01 | C11: TRAMO 01 | D11: TAPADA | E11: SEC 02 | F11: SEC 03 | G11: 6 | H11: 3/8" | I11: =IF(H11="","",IFERROR(VLOOKUP(H11,Listas!$A$4:$B$11,2,FALSE()),"")) -> 0.56 | J11: 0.2 | K11: 7 | L11: 7 | M11: =IF(B11="","",(K11+L11)/2) -> 7 | N11: =IF(B11="","",G11*M11) -> 42 | O11: =IF(B11="","",N11*I11) -> 23.52 | P11: 0.25 | Q11: 1.44 | R11: 1.5 | S11: =IF(B11="","",(Q11+R11)/2) -> 1.47 | T11: =IF(B11="","",IFERROR(IF($X$1="ENTERO (redondeo arriba)",ROUNDUP(G11/P11,0)+1,G11/P11+1),0)) -> 25 | U11: =IF(B11="","",S11*T11) -> 36.75 | V11: =IF(B11="","",U11*I11) -> 20.58 | W11: =IF(B11="","",O11+V11) -> 44.1 | X11: 3/8" | Y11: 0.56 | Z11: 0.25 | AA11: 0.56 | AB11: 0.56 | AC11: =IF(B11="","",IF(D11="TAPADA",(AA11+AB11)/2,0)) -> 0.56 | AD11: =IF(B11="","",IF(D11="TAPADA",IFERROR(IF($X$1="ENTERO (redondeo arriba)",ROUNDUP(G11/Z11,0)+1,G11/Z11+1),0),0)) -> 25 | AE11: =IF(B11="","",IF(D11="TAPADA",AC11*AD11,0)) -> 14 | AF11: =IF(B11="","",IF(D11="TAPADA",AE11*Y11,0)) -> 7.84 | AG11: =IF(B11="","",W11+AF11) -> 51.94
A12: 2 | B12: EJE 01 | C12: TRAMO 02 | D12: ABIERTA | E12: SEC 03 | F12: SEC 04 | G12: 58.1 | H12: 3/8" | I12: =IF(H12="","",IFERROR(VLOOKUP(H12,Listas!$A$4:$B$11,2,FALSE()),"")) -> 0.56 | J12: 0.22 | K12: 7 | L12: 9 | M12: =IF(B12="","",(K12+L12)/2) -> 8 | N12: =IF(B12="","",G12*M12) -> 464.8 | O12: =IF(B12="","",N12*I12) -> 260.288 | P12: 0.25 | Q12: 1.5 | R12: 2.06 | S12: =IF(B12="","",(Q12+R12)/2) -> 1.78 | T12: =IF(B12="","",IFERROR(IF($X$1="ENTERO (redondeo arriba)",ROUNDUP(G12/P12,0)+1,G12/P12+1),0)) -> 233.4 | U12: =IF(B12="","",S12*T12) -> 415.452 | V12: =IF(B12="","",U12*I12) -> 232.65312 | W12: =IF(B12="","",O12+V12) -> 492.94112 | AC12: =IF(B12="","",IF(D12="TAPADA",(AA12+AB12)/2,0)) -> 0 | AD12: =IF(B12="","",IF(D12="TAPADA",IFERROR(IF($X$1="ENTERO (redondeo arriba)",ROUNDUP(G12/Z12,0)+1,G12/Z12+1),0),0)) -> 0 | AE12: =IF(B12="","",IF(D12="TAPADA",AC12*AD12,0)) -> 0 | AF12: =IF(B12="","",IF(D12="TAPADA",AE12*Y12,0)) -> 0 | AG12: =IF(B12="","",W12+AF12) -> 492.94112
A13: 3 | B13: EJE 01 | C13: TRAMO 03 | D13: TAPADA | E13: SEC 04 | F13: SEC 07 | G13: 34.23 | H13: 3/8" | I13: =IF(H13="","",IFERROR(VLOOKUP(H13,Listas!$A$4:$B$11,2,FALSE()),"")) -> 0.56 | J13: 0.25 | K13: 8 | L13: 9 | M13: =IF(B13="","",(K13+L13)/2) -> 8.5 | N13: =IF(B13="","",G13*M13) -> 290.955 | O13: =IF(B13="","",N13*I13) -> 162.9348 | P13: 0.25 | Q13: 2.06 | R13: 2.2 | S13: =IF(B13="","",(Q13+R13)/2) -> 2.13 | T13: =IF(B13="","",IFERROR(IF($X$1="ENTERO (redondeo arriba)",ROUNDUP(G13/P13,0)+1,G13/P13+1),0)) -> 137.92 | U13: =IF(B13="","",S13*T13) -> 293.7696 | V13: =IF(B13="","",U13*I13) -> 164.51098 | W13: =IF(B13="","",O13+V13) -> 327.44578 | X13: 3/8" | Y13: 0.56 | Z13: 0.25 | AA13: 0.56 | AB13: 0.56 | AC13: =IF(B13="","",IF(D13="TAPADA",(AA13+AB13)/2,0)) -> 0.56 | AD13: =IF(B13="","",IF(D13="TAPADA",IFERROR(IF($X$1="ENTERO (redondeo arriba)",ROUNDUP(G13/Z13,0)+1,G13/Z13+1),0),0)) -> 137.92 | AE13: =IF(B13="","",IF(D13="TAPADA",AC13*AD13,0)) -> 77.2352 | AF13: =IF(B13="","",IF(D13="TAPADA",AE13*Y13,0)) -> 43.251712 | AG13: =IF(B13="","",W13+AF13) -> 370.69749
A14: 4 | B14: EJE 02 | C14: TRAMO 01 | D14: ABIERTA | E14: SEC 09 | F14: SEC 10 | G14: 14.25 | H14: 3/8" | I14: =IF(H14="","",IFERROR(VLOOKUP(H14,Listas!$A$4:$B$11,2,FALSE()),"")) -> 0.56 | J14: 0.2 | K14: 7 | L14: 8 | M14: =IF(B14="","",(K14+L14)/2) -> 7.5 | N14: =IF(B14="","",G14*M14) -> 106.875 | O14: =IF(B14="","",N14*I14) -> 59.85 | P14: 0.25 | Q14: 1.5 | R14: 1.64 | S14: =IF(B14="","",(Q14+R14)/2) -> 1.57 | T14: =IF(B14="","",IFERROR(IF($X$1="ENTERO (redondeo arriba)",ROUNDUP(G14/P14,0)+1,G14/P14+1),0)) -> 58 | U14: =IF(B14="","",S14*T14) -> 91.06 | V14: =IF(B14="","",U14*I14) -> 50.9936 | W14: =IF(B14="","",O14+V14) -> 110.8436 | AC14: =IF(B14="","",IF(D14="TAPADA",(AA14+AB14)/2,0)) -> 0 | AD14: =IF(B14="","",IF(D14="TAPADA",IFERROR(IF($X$1="ENTERO (redondeo arriba)",ROUNDUP(G14/Z14,0)+1,G14/Z14+1),0),0)) -> 0 | AE14: =IF(B14="","",IF(D14="TAPADA",AC14*AD14,0)) -> 0 | AF14: =IF(B14="","",IF(D14="TAPADA",AE14*Y14,0)) -> 0 | AG14: =IF(B14="","",W14+AF14) -> 110.8436
A15: 5 | B15: EJE 03 | C15: TRAMO 01 | D15: ABIERTA | E15: SEC 12 | F15: SEC 13 | G15: 2.4 | H15: 3/8" | I15: =IF(H15="","",IFERROR(VLOOKUP(H15,Listas!$A$4:$B$11,2,FALSE()),"")) -> 0.56 | J15: 0.2 | K15: 7 | L15: 8 | M15: =IF(B15="","",(K15+L15)/2) -> 7.5 | N15: =IF(B15="","",G15*M15) -> 18 | O15: =IF(B15="","",N15*I15) -> 10.08 | P15: 0.25 | Q15: 1.5 | R15: 1.54 | S15: =IF(B15="","",(Q15+R15)/2) -> 1.52 | T15: =IF(B15="","",IFERROR(IF($X$1="ENTERO (redondeo arriba)",ROUNDUP(G15/P15,0)+1,G15/P15+1),0)) -> 10.6 | U15: =IF(B15="","",S15*T15) -> 16.112 | V15: =IF(B15="","",U15*I15) -> 9.02272 | W15: =IF(B15="","",O15+V15) -> 19.10272 | AC15: =IF(B15="","",IF(D15="TAPADA",(AA15+AB15)/2,0)) -> 0 | AD15: =IF(B15="","",IF(D15="TAPADA",IFERROR(IF($X$1="ENTERO (redondeo arriba)",ROUNDUP(G15/Z15,0)+1,G15/Z15+1),0),0)) -> 0 | AE15: =IF(B15="","",IF(D15="TAPADA",AC15*AD15,0)) -> 0 | AF15: =IF(B15="","",IF(D15="TAPADA",AE15*Y15,0)) -> 0 | AG15: =IF(B15="","",W15+AF15) -> 19.10272
A16: 6 | B16: EJE 04 | C16: TRAMO 01 | D16: TAPADA | E16: SEC 15 | F16: SEC 16 | G16: 5.5 | H16: 3/8" | I16: =IF(H16="","",IFERROR(VLOOKUP(H16,Listas!$A$4:$B$11,2,FALSE()),"")) -> 0.56 | J16: 0.2 | K16: 7 | L16: 7 | M16: =IF(B16="","",(K16+L16)/2) -> 7 | N16: =IF(B16="","",G16*M16) -> 38.5 | O16: =IF(B16="","",N16*I16) -> 21.56 | P16: 0.25 | Q16: 1.42 | R16: 1.5 | S16: =IF(B16="","",(Q16+R16)/2) -> 1.46 | T16: =IF(B16="","",IFERROR(IF($X$1="ENTERO (redondeo arriba)",ROUNDUP(G16/P16,0)+1,G16/P16+1),0)) -> 23 | U16: =IF(B16="","",S16*T16) -> 33.58 | V16: =IF(B16="","",U16*I16) -> 18.8048 | W16: =IF(B16="","",O16+V16) -> 40.3648 | X16: 3/8" | Y16: 0.56 | Z16: 0.25 | AA16: 0.56 | AB16: 0.56 | AC16: =IF(B16="","",IF(D16="TAPADA",(AA16+AB16)/2,0)) -> 0.56 | AD16: =IF(B16="","",IF(D16="TAPADA",IFERROR(IF($X$1="ENTERO (redondeo arriba)",ROUNDUP(G16/Z16,0)+1,G16/Z16+1),0),0)) -> 23 | AE16: =IF(B16="","",IF(D16="TAPADA",AC16*AD16,0)) -> 12.88 | AF16: =IF(B16="","",IF(D16="TAPADA",AE16*Y16,0)) -> 7.2128 | AG16: =IF(B16="","",W16+AF16) -> 47.5776
A17: 7 | B17: EJE 04 | C17: TRAMO 02 | D17: ABIERTA | E17: SEC 16 | F17: SEC 17 | G17: 58 | H17: 3/8" | I17: =IF(H17="","",IFERROR(VLOOKUP(H17,Listas!$A$4:$B$11,2,FALSE()),"")) -> 0.56 | J17: 0.22 | K17: 7 | L17: 9 | M17: =IF(B17="","",(K17+L17)/2) -> 8 | N17: =IF(B17="","",G17*M17) -> 464 | O17: =IF(B17="","",N17*I17) -> 259.84 | P17: 0.25 | Q17: 1.5 | R17: 2.06 | S17: =IF(B17="","",(Q17+R17)/2) -> 1.78 | T17: =IF(B17="","",IFERROR(IF($X$1="ENTERO (redondeo arriba)",ROUNDUP(G17/P17,0)+1,G17/P17+1),0)) -> 233 | U17: =IF(B17="","",S17*T17) -> 414.74 | V17: =IF(B17="","",U17*I17) -> 232.2544 | W17: =IF(B17="","",O17+V17) -> 492.0944 | AC17: =IF(B17="","",IF(D17="TAPADA",(AA17+AB17)/2,0)) -> 0 | AD17: =IF(B17="","",IF(D17="TAPADA",IFERROR(IF($X$1="ENTERO (redondeo arriba)",ROUNDUP(G17/Z17,0)+1,G17/Z17+1),0),0)) -> 0 | AE17: =IF(B17="","",IF(D17="TAPADA",AC17*AD17,0)) -> 0 | AF17: =IF(B17="","",IF(D17="TAPADA",AE17*Y17,0)) -> 0 | AG17: =IF(B17="","",W17+AF17) -> 492.0944
A18: 8 | B18: EJE 04 | C18: TRAMO 03 | D18: TAPADA | E18: SEC 17 | F18: SEC 20 | G18: 25.16 | H18: 3/8" | I18: =IF(H18="","",IFERROR(VLOOKUP(H18,Listas!$A$4:$B$11,2,FALSE()),"")) -> 0.56 | J18: 0.25 | K18: 8 | L18: 8 | M18: =IF(B18="","",(K18+L18)/2) -> 8 | N18: =IF(B18="","",G18*M18) -> 201.28 | O18: =IF(B18="","",N18*I18) -> 112.7168 | P18: 0.25 | Q18: 2.06 | R18: 2.1 | S18: =IF(B18="","",(Q18+R18)/2) -> 2.08 | T18: =IF(B18="","",IFERROR(IF($X$1="ENTERO (redondeo arriba)",ROUNDUP(G18/P18,0)+1,G18/P18+1),0)) -> 101.64 | U18: =IF(B18="","",S18*T18) -> 211.4112 | V18: =IF(B18="","",U18*I18) -> 118.39027 | W18: =IF(B18="","",O18+V18) -> 231.10707 | X18: 3/8" | Y18: 0.56 | Z18: 0.25 | AA18: 0.56 | AB18: 0.56 | AC18: =IF(B18="","",IF(D18="TAPADA",(AA18+AB18)/2,0)) -> 0.56 | AD18: =IF(B18="","",IF(D18="TAPADA",IFERROR(IF($X$1="ENTERO (redondeo arriba)",ROUNDUP(G18/Z18,0)+1,G18/Z18+1),0),0)) -> 101.64 | AE18: =IF(B18="","",IF(D18="TAPADA",AC18*AD18,0)) -> 56.9184 | AF18: =IF(B18="","",IF(D18="TAPADA",AE18*Y18,0)) -> 31.874304 | AG18: =IF(B18="","",W18+AF18) -> 262.98138
A19: 9 | B19: EJE 05 | C19: TRAMO 01 | D19: ABIERTA | E19: SEC 22 | F19: SEC 23 | G19: 12.3 | H19: 3/8" | I19: =IF(H19="","",IFERROR(VLOOKUP(H19,Listas!$A$4:$B$11,2,FALSE()),"")) -> 0.56 | J19: 0.2 | K19: 7 | L19: 8 | M19: =IF(B19="","",(K19+L19)/2) -> 7.5 | N19: =IF(B19="","",G19*M19) -> 92.25 | O19: =IF(B19="","",N19*I19) -> 51.66 | P19: 0.25 | Q19: 1.5 | R19: 1.62 | S19: =IF(B19="","",(Q19+R19)/2) -> 1.56 | T19: =IF(B19="","",IFERROR(IF($X$1="ENTERO (redondeo arriba)",ROUNDUP(G19/P19,0)+1,G19/P19+1),0)) -> 50.2 | U19: =IF(B19="","",S19*T19) -> 78.312 | V19: =IF(B19="","",U19*I19) -> 43.85472 | W19: =IF(B19="","",O19+V19) -> 95.51472 | AC19: =IF(B19="","",IF(D19="TAPADA",(AA19+AB19)/2,0)) -> 0 | AD19: =IF(B19="","",IF(D19="TAPADA",IFERROR(IF($X$1="ENTERO (redondeo arriba)",ROUNDUP(G19/Z19,0)+1,G19/Z19+1),0),0)) -> 0 | AE19: =IF(B19="","",IF(D19="TAPADA",AC19*AD19,0)) -> 0 | AF19: =IF(B19="","",IF(D19="TAPADA",AE19*Y19,0)) -> 0 | AG19: =IF(B19="","",W19+AF19) -> 95.51472
A20: 10 | B20: EJE 05 | C20: TRAMO 02 | D20: TAPADA | E20: SEC 23 | F20: SEC 24 | G20: 9.9 | H20: 3/8" | I20: =IF(H20="","",IFERROR(VLOOKUP(H20,Listas!$A$4:$B$11,2,FALSE()),"")) -> 0.56 | J20: 0.22 | K20: 7 | L20: 8 | M20: =IF(B20="","",(K20+L20)/2) -> 7.5 | N20: =IF(B20="","",G20*M20) -> 74.25 | O20: =IF(B20="","",N20*I20) -> 41.58 | P20: 0.25 | Q20: 1.62 | R20: 1.72 | S20: =IF(B20="","",(Q20+R20)/2) -> 1.67 | T20: =IF(B20="","",IFERROR(IF($X$1="ENTERO (redondeo arriba)",ROUNDUP(G20/P20,0)+1,G20/P20+1),0)) -> 40.6 | U20: =IF(B20="","",S20*T20) -> 67.802 | V20: =IF(B20="","",U20*I20) -> 37.96912 | W20: =IF(B20="","",O20+V20) -> 79.54912 | X20: 3/8" | Y20: 0.56 | Z20: 0.25 | AA20: 0.56 | AB20: 0.56 | AC20: =IF(B20="","",IF(D20="TAPADA",(AA20+AB20)/2,0)) -> 0.56 | AD20: =IF(B20="","",IF(D20="TAPADA",IFERROR(IF($X$1="ENTERO (redondeo arriba)",ROUNDUP(G20/Z20,0)+1,G20/Z20+1),0),0)) -> 40.6 | AE20: =IF(B20="","",IF(D20="TAPADA",AC20*AD20,0)) -> 22.736 | AF20: =IF(B20="","",IF(D20="TAPADA",AE20*Y20,0)) -> 12.73216 | AG20: =IF(B20="","",W20+AF20) -> 92.28128
A21: 11 | B21: EJE 06 | C21: TRAMO 01 | D21: ABIERTA | E21: SEC 26 | F21: SEC 27 | G21: 12.5 | H21: 3/8" | I21: =IF(H21="","",IFERROR(VLOOKUP(H21,Listas!$A$4:$B$11,2,FALSE()),"")) -> 0.56 | J21: 0.2 | K21: 7 | L21: 8 | M21: =IF(B21="","",(K21+L21)/2) -> 7.5 | N21: =IF(B21="","",G21*M21) -> 93.75 | O21: =IF(B21="","",N21*I21) -> 52.5 | P21: 0.25 | Q21: 1.5 | R21: 1.62 | S21: =IF(B21="","",(Q21+R21)/2) -> 1.56 | T21: =IF(B21="","",IFERROR(IF($X$1="ENTERO (redondeo arriba)",ROUNDUP(G21/P21,0)+1,G21/P21+1),0)) -> 51 | U21: =IF(B21="","",S21*T21) -> 79.56 | V21: =IF(B21="","",U21*I21) -> 44.5536 | W21: =IF(B21="","",O21+V21) -> 97.0536 | AC21: =IF(B21="","",IF(D21="TAPADA",(AA21+AB21)/2,0)) -> 0 | AD21: =IF(B21="","",IF(D21="TAPADA",IFERROR(IF($X$1="ENTERO (redondeo arriba)",ROUNDUP(G21/Z21,0)+1,G21/Z21+1),0),0)) -> 0 | AE21: =IF(B21="","",IF(D21="TAPADA",AC21*AD21,0)) -> 0 | AF21: =IF(B21="","",IF(D21="TAPADA",AE21*Y21,0)) -> 0 | AG21: =IF(B21="","",W21+AF21) -> 97.0536
A22: 12 | B22: EJE 06 | C22: TRAMO 02 | D22: TAPADA | E22: SEC 27 | F22: SEC 30 | G22: 66.19 | H22: 3/8" | I22: =IF(H22="","",IFERROR(VLOOKUP(H22,Listas!$A$4:$B$11,2,FALSE()),"")) -> 0.56 | J22: 0.22 | K22: 7 | L22: 9 | M22: =IF(B22="","",(K22+L22)/2) -> 8 | N22: =IF(B22="","",G22*M22) -> 529.52 | O22: =IF(B22="","",N22*I22) -> 296.5312 | P22: 0.25 | Q22: 1.62 | R22: 2.08 | S22: =IF(B22="","",(Q22+R22)/2) -> 1.85 | T22: =IF(B22="","",IFERROR(IF($X$1="ENTERO (redondeo arriba)",ROUNDUP(G22/P22,0)+1,G22/P22+1),0)) -> 265.76 | U22: =IF(B22="","",S22*T22) -> 491.656 | V22: =IF(B22="","",U22*I22) -> 275.32736 | W22: =IF(B22="","",O22+V22) -> 571.85856 | X22: 3/8" | Y22: 0.56 | Z22: 0.25 | AA22: 0.56 | AB22: 0.56 | AC22: =IF(B22="","",IF(D22="TAPADA",(AA22+AB22)/2,0)) -> 0.56 | AD22: =IF(B22="","",IF(D22="TAPADA",IFERROR(IF($X$1="ENTERO (redondeo arriba)",ROUNDUP(G22/Z22,0)+1,G22/Z22+1),0),0)) -> 265.76 | AE22: =IF(B22="","",IF(D22="TAPADA",AC22*AD22,0)) -> 148.8256 | AF22: =IF(B22="","",IF(D22="TAPADA",AE22*Y22,0)) -> 83.342336 | AG22: =IF(B22="","",W22+AF22) -> 655.2009
A23: 13 | B23: EJE 07 | C23: TRAMO 01 | D23: ABIERTA | E23: SEC 32 | F23: SEC 33 | G23: 3.6 | H23: 3/8" | I23: =IF(H23="","",IFERROR(VLOOKUP(H23,Listas!$A$4:$B$11,2,FALSE()),"")) -> 0.56 | J23: 0.2 | K23: 7 | L23: 8 | M23: =IF(B23="","",(K23+L23)/2) -> 7.5 | N23: =IF(B23="","",G23*M23) -> 27 | O23: =IF(B23="","",N23*I23) -> 15.12 | P23: 0.25 | Q23: 1.5 | R23: 1.52 | S23: =IF(B23="","",(Q23+R23)/2) -> 1.51 | T23: =IF(B23="","",IFERROR(IF($X$1="ENTERO (redondeo arriba)",ROUNDUP(G23/P23,0)+1,G23/P23+1),0)) -> 15.4 | U23: =IF(B23="","",S23*T23) -> 23.254 | V23: =IF(B23="","",U23*I23) -> 13.02224 | W23: =IF(B23="","",O23+V23) -> 28.14224 | AC23: =IF(B23="","",IF(D23="TAPADA",(AA23+AB23)/2,0)) -> 0 | AD23: =IF(B23="","",IF(D23="TAPADA",IFERROR(IF($X$1="ENTERO (redondeo arriba)",ROUNDUP(G23/Z23,0)+1,G23/Z23+1),0),0)) -> 0 | AE23: =IF(B23="","",IF(D23="TAPADA",AC23*AD23,0)) -> 0 | AF23: =IF(B23="","",IF(D23="TAPADA",AE23*Y23,0)) -> 0 | AG23: =IF(B23="","",W23+AF23) -> 28.14224
A24: 14 | B24: EJE 08 | C24: TRAMO 01 | D24: ABIERTA | E24: SEC 35 | F24: SEC 36 | G24: 29.85 | H24: 3/8" | I24: =IF(H24="","",IFERROR(VLOOKUP(H24,Listas!$A$4:$B$11,2,FALSE()),"")) -> 0.56 | J24: 0.22 | K24: 7 | L24: 8 | M24: =IF(B24="","",(K24+L24)/2) -> 7.5 | N24: =IF(B24="","",G24*M24) -> 223.875 | O24: =IF(B24="","",N24*I24) -> 125.37 | P24: 0.25 | Q24: 1.5 | R24: 1.8 | S24: =IF(B24="","",(Q24+R24)/2) -> 1.65 | T24: =IF(B24="","",IFERROR(IF($X$1="ENTERO (redondeo arriba)",ROUNDUP(G24/P24,0)+1,G24/P24+1),0)) -> 120.4 | U24: =IF(B24="","",S24*T24) -> 198.66 | V24: =IF(B24="","",U24*I24) -> 111.2496 | W24: =IF(B24="","",O24+V24) -> 236.6196 | AC24: =IF(B24="","",IF(D24="TAPADA",(AA24+AB24)/2,0)) -> 0 | AD24: =IF(B24="","",IF(D24="TAPADA",IFERROR(IF($X$1="ENTERO (redondeo arriba)",ROUNDUP(G24/Z24,0)+1,G24/Z24+1),0),0)) -> 0 | AE24: =IF(B24="","",IF(D24="TAPADA",AC24*AD24,0)) -> 0 | AF24: =IF(B24="","",IF(D24="TAPADA",AE24*Y24,0)) -> 0 | AG24: =IF(B24="","",W24+AF24) -> 236.6196
A25: 15 | B25: EJE 08 | C25: TRAMO 02 | D25: TAPADA | E25: SEC 36 | F25: SEC 37 | G25: 10.75 | H25: 3/8" | I25: =IF(H25="","",IFERROR(VLOOKUP(H25,Listas!$A$4:$B$11,2,FALSE()),"")) -> 0.56 | J25: 0.22 | K25: 8 | L25: 9 | M25: =IF(B25="","",(K25+L25)/2) -> 8.5 | N25: =IF(B25="","",G25*M25) -> 91.375 | O25: =IF(B25="","",N25*I25) -> 51.17 | P25: 0.25 | Q25: 1.8 | R25: 1.9 | S25: =IF(B25="","",(Q25+R25)/2) -> 1.85 | T25: =IF(B25="","",IFERROR(IF($X$1="ENTERO (redondeo arriba)",ROUNDUP(G25/P25,0)+1,G25/P25+1),0)) -> 44 | U25: =IF(B25="","",S25*T25) -> 81.4 | V25: =IF(B25="","",U25*I25) -> 45.584 | W25: =IF(B25="","",O25+V25) -> 96.754 | X25: 3/8" | Y25: 0.56 | Z25: 0.25 | AA25: 0.56 | AB25: 0.56 | AC25: =IF(B25="","",IF(D25="TAPADA",(AA25+AB25)/2,0)) -> 0.56 | AD25: =IF(B25="","",IF(D25="TAPADA",IFERROR(IF($X$1="ENTERO (redondeo arriba)",ROUNDUP(G25/Z25,0)+1,G25/Z25+1),0),0)) -> 44 | AE25: =IF(B25="","",IF(D25="TAPADA",AC25*AD25,0)) -> 24.64 | AF25: =IF(B25="","",IF(D25="TAPADA",AE25*Y25,0)) -> 13.7984 | AG25: =IF(B25="","",W25+AF25) -> 110.5524
A26: 16 | B26: EJE 09 | C26: TRAMO 01 | D26: ABIERTA | E26: SEC 39 | F26: SEC 40 | G26: 16 | H26: 3/8" | I26: =IF(H26="","",IFERROR(VLOOKUP(H26,Listas!$A$4:$B$11,2,FALSE()),"")) -> 0.56 | J26: 0.22 | K26: 7 | L26: 8 | M26: =IF(B26="","",(K26+L26)/2) -> 7.5 | N26: =IF(B26="","",G26*M26) -> 120 | O26: =IF(B26="","",N26*I26) -> 67.2 | P26: 0.25 | Q26: 1.5 | R26: 1.7 | S26: =IF(B26="","",(Q26+R26)/2) -> 1.6 | T26: =IF(B26="","",IFERROR(IF($X$1="ENTERO (redondeo arriba)",ROUNDUP(G26/P26,0)+1,G26/P26+1),0)) -> 65 | U26: =IF(B26="","",S26*T26) -> 104 | V26: =IF(B26="","",U26*I26) -> 58.24 | W26: =IF(B26="","",O26+V26) -> 125.44 | AC26: =IF(B26="","",IF(D26="TAPADA",(AA26+AB26)/2,0)) -> 0 | AD26: =IF(B26="","",IF(D26="TAPADA",IFERROR(IF($X$1="ENTERO (redondeo arriba)",ROUNDUP(G26/Z26,0)+1,G26/Z26+1),0),0)) -> 0 | AE26: =IF(B26="","",IF(D26="TAPADA",AC26*AD26,0)) -> 0 | AF26: =IF(B26="","",IF(D26="TAPADA",AE26*Y26,0)) -> 0 | AG26: =IF(B26="","",W26+AF26) -> 125.44
A27: 17 | B27: EJE 09 | C27: TRAMO 02 | D27: TAPADA | E27: SEC 40 | F27: SEC 42 | G27: 6.66 | H27: 3/8" | I27: =IF(H27="","",IFERROR(VLOOKUP(H27,Listas!$A$4:$B$11,2,FALSE()),"")) -> 0.56 | J27: 0.22 | K27: 8 | L27: 8 | M27: =IF(B27="","",(K27+L27)/2) -> 8 | N27: =IF(B27="","",G27*M27) -> 53.28 | O27: =IF(B27="","",N27*I27) -> 29.8368 | P27: 0.25 | Q27: 1.7 | R27: 1.82 | S27: =IF(B27="","",(Q27+R27)/2) -> 1.76 | T27: =IF(B27="","",IFERROR(IF($X$1="ENTERO (redondeo arriba)",ROUNDUP(G27/P27,0)+1,G27/P27+1),0)) -> 27.64 | U27: =IF(B27="","",S27*T27) -> 48.6464 | V27: =IF(B27="","",U27*I27) -> 27.241984 | W27: =IF(B27="","",O27+V27) -> 57.078784 | X27: 3/8" | Y27: 0.56 | Z27: 0.25 | AA27: 0.56 | AB27: 0.56 | AC27: =IF(B27="","",IF(D27="TAPADA",(AA27+AB27)/2,0)) -> 0.56 | AD27: =IF(B27="","",IF(D27="TAPADA",IFERROR(IF($X$1="ENTERO (redondeo arriba)",ROUNDUP(G27/Z27,0)+1,G27/Z27+1),0),0)) -> 27.64 | AE27: =IF(B27="","",IF(D27="TAPADA",AC27*AD27,0)) -> 15.4784 | AF27: =IF(B27="","",IF(D27="TAPADA",AE27*Y27,0)) -> 8.667904 | AG27: =IF(B27="","",W27+AF27) -> 65.746688
A28: TOTALES DE LA PLANILLA | G28: =SUM(G11:G27) -> 371.39 | N28: =SUM(N11:N27) -> 2931.71 | O28: =SUM(O11:O27) -> 1641.7576 | U28: =SUM(U11:U27) -> 2686.1652 | V28: =SUM(V11:V27) -> 1504.2525 | W28: =SUM(W11:W27) -> 3146.0101 | AE28: =SUM(AE11:AE27) -> 372.7136 | AF28: =SUM(AF11:AF27) -> 208.71962 | AG28: =SUM(AG11:AG27) -> 3354.7297

Sheet METRADO DE CURADO
A1: METRADO DE CURADO DE CONCRETO EN CUNETAS
A2: ENTIDAD | C2: GERENCIA TERRITORIAL BAJO MAYO - TARAPOTO
A3: PROYECTO | C3: =+RESUMEN!B5 -> CREACIÓN DEL SERVICIO DE PROTECCIÓN INTEGRAL A NIÑAS, NIÑOS Y ADOLESCENTES SIN CUIDADOS PARENTALES O EN RIESGO DE PERDERLOS EN CENTRO DE ACOGIDA RESIDENCIAL - VARONES DISTRITO DE MORALES DE LA PROVINCIA DE SAN MARTÍN DEL DEPARTAMENTO DE SAN MARTÍN, con CUI N.° 2705619
A4: UBICACIÓN | C4: =+RESUMEN!B6 -> SAN MARTIN - SAN MARTIN - MORALES | K4: FECHA | L4: =+RESUMEN!B7 -> 46266
A6: N° | B6: EJE | C6: TRAMO | D6: TIPO DE CUNETA | E6: LONGITUD (m) | F6: ANCHO INTERIOR (m) | G6: ALTURA INT. INI (m) | H6: ALTURA INT. FIN (m) | I6: ALTURA PROM. (m) | J6: ÁREA 2 MUROS (m²) | K6: ÁREA FONDO (m²) | L6: ÁREA TAPA / TECHO (m²) | M6: TOTAL CURADO (m²) | N6: N° CARAS | O6: UND.
A7: 1 | B7: EJE 01 | C7: TRAMO 01 | D7: ABIERTA | E7: 13.2 | F7: 0.4 | G7: 0.3 | H7: 0.37 | I7: =IF(B7="","",(G7+H7)/2) -> 0.335 | J7: =IF(B7="","",2*E7*I7) -> 8.844 | K7: =IF(B7="","",E7*F7) -> 5.28 | L7: =IF(B7="","",IF(D7="TAPADA",E7*F7,0)) -> 0 | M7: =SUM(J7:L7) -> 14.124 | N7: =IF(B7="","",IF(D7="TAPADA",4,3)) -> 3 | O7: m²
A8: 2 | B8: EJE 01 | C8: TRAMO 02 | D8: TAPADA | E8: 6 | F8: 0.4 | G8: 0.37 | H8: 0.4 | I8: =IF(B8="","",(G8+H8)/2) -> 0.385 | J8: =IF(B8="","",2*E8*I8) -> 4.62 | K8: =IF(B8="","",E8*F8) -> 2.4 | L8: =IF(B8="","",IF(D8="TAPADA",E8*F8,0)) -> 2.4 | M8: =SUM(J8:L8) -> 9.42 | N8: =IF(B8="","",IF(D8="TAPADA",4,3)) -> 4 | O8: m²
A9: 3 | B9: EJE 01 | C9: TRAMO 03 | D9: ABIERTA | E9: 58.1 | F9: 0.4 | G9: 0.4 | H9: 0.68 | I9: =IF(B9="","",(G9+H9)/2) -> 0.54 | J9: =IF(B9="","",2*E9*I9) -> 62.748 | K9: =IF(B9="","",E9*F9) -> 23.24 | L9: =IF(B9="","",IF(D9="TAPADA",E9*F9,0)) -> 0 | M9: =SUM(J9:L9) -> 85.988 | N9: =IF(B9="","",IF(D9="TAPADA",4,3)) -> 3 | O9: m²
A10: 4 | B10: EJE 01 | C10: TRAMO 04 | D10: TAPADA | E10: 34.23 | F10: 0.4 | G10: 0.68 | H10: 0.75 | I10: =IF(B10="","",(G10+H10)/2) -> 0.715 | J10: =IF(B10="","",2*E10*I10) -> 48.9489 | K10: =IF(B10="","",E10*F10) -> 13.692 | L10: =IF(B10="","",IF(D10="TAPADA",E10*F10,0)) -> 13.692 | M10: =SUM(J10:L10) -> 76.3329 | N10: =IF(B10="","",IF(D10="TAPADA",4,3)) -> 4 | O10: m²
A11: 5 | B11: EJE 02 | C11: TRAMO 01 | D11: ABIERTA | E11: 34.25 | F11: 0.4 | G11: 0.3 | H11: 0.47 | I11: =IF(B11="","",(G11+H11)/2) -> 0.385 | J11: =IF(B11="","",2*E11*I11) -> 26.3725 | K11: =IF(B11="","",E11*F11) -> 13.7 | L11: =IF(B11="","",IF(D11="TAPADA",E11*F11,0)) -> 0 | M11: =SUM(J11:L11) -> 40.0725 | N11: =IF(B11="","",IF(D11="TAPADA",4,3)) -> 3 | O11: m²
A12: 6 | B12: EJE 03 | C12: TRAMO 01 | D12: ABIERTA | E12: 22.4 | F12: 0.4 | G12: 0.3 | H12: 0.42 | I12: =IF(B12="","",(G12+H12)/2) -> 0.36 | J12: =IF(B12="","",2*E12*I12) -> 16.128 | K12: =IF(B12="","",E12*F12) -> 8.96 | L12: =IF(B12="","",IF(D12="TAPADA",E12*F12,0)) -> 0 | M12: =SUM(J12:L12) -> 25.088 | N12: =IF(B12="","",IF(D12="TAPADA",4,3)) -> 3 | O12: m²
A13: 7 | B13: EJE 04 | C13: TRAMO 01 | D13: ABIERTA | E13: 13.65 | F13: 0.4 | G13: 0.3 | H13: 0.36 | I13: =IF(B13="","",(G13+H13)/2) -> 0.33 | J13: =IF(B13="","",2*E13*I13) -> 9.009 | K13: =IF(B13="","",E13*F13) -> 5.46 | L13: =IF(B13="","",IF(D13="TAPADA",E13*F13,0)) -> 0 | M13: =SUM(J13:L13) -> 14.469 | N13: =IF(B13="","",IF(D13="TAPADA",4,3)) -> 3 | O13: m²
A14: 8 | B14: EJE 04 | C14: TRAMO 02 | D14: TAPADA | E14: 5.5 | F14: 0.4 | G14: 0.36 | H14: 0.4 | I14: =IF(B14="","",(G14+H14)/2) -> 0.38 | J14: =IF(B14="","",2*E14*I14) -> 4.18 | K14: =IF(B14="","",E14*F14) -> 2.2 | L14: =IF(B14="","",IF(D14="TAPADA",E14*F14,0)) -> 2.2 | M14: =SUM(J14:L14) -> 8.58 | N14: =IF(B14="","",IF(D14="TAPADA",4,3)) -> 4 | O14: m²
A15: 9 | B15: EJE 04 | C15: TRAMO 03 | D15: ABIERTA | E15: 58 | F15: 0.4 | G15: 0.4 | H15: 0.68 | I15: =IF(B15="","",(G15+H15)/2) -> 0.54 | J15: =IF(B15="","",2*E15*I15) -> 62.64 | K15: =IF(B15="","",E15*F15) -> 23.2 | L15: =IF(B15="","",IF(D15="TAPADA",E15*F15,0)) -> 0 | M15: =SUM(J15:L15) -> 85.84 | N15: =IF(B15="","",IF(D15="TAPADA",4,3)) -> 3 | O15: m²
A16: 10 | B16: EJE 04 | C16: TRAMO 04 | D16: TAPADA | E16: 25.16 | F16: 0.4 | G16: 0.68 | H16: 0.7 | I16: =IF(B16="","",(G16+H16)/2) -> 0.69 | J16: =IF(B16="","",2*E16*I16) -> 34.7208 | K16: =IF(B16="","",E16*F16) -> 10.064 | L16: =IF(B16="","",IF(D16="TAPADA",E16*F16,0)) -> 10.064 | M16: =SUM(J16:L16) -> 54.8488 | N16: =IF(B16="","",IF(D16="TAPADA",4,3)) -> 4 | O16: m²
A17: 11 | B17: EJE 05 | C17: TRAMO 01 | D17: ABIERTA | E17: 32.3 | F17: 0.4 | G17: 0.3 | H17: 0.46 | I17: =IF(B17="","",(G17+H17)/2) -> 0.38 | J17: =IF(B17="","",2*E17*I17) -> 24.548 | K17: =IF(B17="","",E17*F17) -> 12.92 | L17: =IF(B17="","",IF(D17="TAPADA",E17*F17,0)) -> 0 | M17: =SUM(J17:L17) -> 37.468 | N17: =IF(B17="","",IF(D17="TAPADA",4,3)) -> 3 | O17: m²
A18: 12 | B18: EJE 05 | C18: TRAMO 02 | D18: TAPADA | E18: 9.9 | F18: 0.4 | G18: 0.46 | H18: 0.51 | I18: =IF(B18="","",(G18+H18)/2) -> 0.485 | J18: =IF(B18="","",2*E18*I18) -> 9.603 | K18: =IF(B18="","",E18*F18) -> 3.96 | L18: =IF(B18="","",IF(D18="TAPADA",E18*F18,0)) -> 3.96 | M18: =SUM(J18:L18) -> 17.523 | N18: =IF(B18="","",IF(D18="TAPADA",4,3)) -> 4 | O18: m²
... A25: 19 | B25: EJE 09 | C25: TRAMO 02 | D25: TAPADA | E25: 6.66 | F25: 0.4 | G25: 0.5 | H25: 0.56 | I25: =IF(B25="","",(G25+H25)/2) -> 0.53 | J25: =IF(B25="","",2*E25*I25) -> 7.0596 | K25: =IF(B25="","",E25*F25) -> 2.664 | L25: =IF(B25="","",IF(D25="TAPADA",E25*F25,0)) -> 2.664 | M25: =SUM(J25:L25) -> 12.3876 | N25: =IF(B25="","",IF(D25="TAPADA",4,3)) -> 4 | O25: m²
A27: TOTAL DE CURADO DE CONCRETO EN CUNETAS | M27: =SUM(M7:M25) -> 801.5833 | O27: m²

Sheet METRADO DE REJILLAS
A1: METRADO DE REJILLAS PARA CUNETAS
A2: ENTIDAD | C2: GERENCIA TERRITORIAL BAJO MAYO - TARAPOTO
A3: PROYECTO | C3: =+RESUMEN!B5 -> CREACIÓN DEL SERVICIO DE PROTECCIÓN INTEGRAL A NIÑAS, NIÑOS Y ADOLESCENTES SIN CUIDADOS PARENTALES O EN RIESGO DE PERDERLOS EN CENTRO DE ACOGIDA RESIDENCIAL - VARONES DISTRITO DE MORALES DE LA PROVINCIA DE SAN MARTÍN DEL DEPARTAMENTO DE SAN MARTÍN, con CUI N.° 2705619
A4: UBICACIÓN | C4: =+RESUMEN!B6 -> SAN MARTIN - SAN MARTIN - MORALES | G4: FECHA | H4: =+RESUMEN!B7 -> 46266
A6: N° | B6: EJE | C6: TRAMO | D6: TIPO DE CUNETA | E6: LONGITUD DEL TRAMO (m) | F6: DESCUENTO SIN REJILLA (m) | G6: LONGITUD CON REJILLA (m) | H6: UND.
A7: 1 | B7: EJE 01 | C7: TRAMO 01 | D7: ABIERTA | E7: 13.2 | F7: 0 | G7: =IF(B7="","",IF(D7="ABIERTA",IF(E7-F7<0,0,E7-F7),0)) -> 13.2 | H7: m
A8: 2 | B8: EJE 01 | C8: TRAMO 02 | D8: TAPADA | E8: 6 | F8: 0 | G8: =IF(B8="","",IF(D8="ABIERTA",IF(E8-F8<0,0,E8-F8),0)) -> 0 | H8: m
A9: 3 | B9: EJE 01 | C9: TRAMO 03 | D9: ABIERTA | E9: 58.1 | F9: 0 | G9: =IF(B9="","",IF(D9="ABIERTA",IF(E9-F9<0,0,E9-F9),0)) -> 58.1 | H9: m
A10: 4 | B10: EJE 01 | C10: TRAMO 04 | D10: TAPADA | E10: 34.23 | F10: 0 | G10: =IF(B10="","",IF(D10="ABIERTA",IF(E10-F10<0,0,E10-F10),0)) -> 0 | H10: m
A11: 5 | B11: EJE 02 | C11: TRAMO 01 | D11: ABIERTA | E11: 34.25 | F11: 0 | G11: =IF(B11="","",IF(D11="ABIERTA",IF(E11-F11<0,0,E11-F11),0)) -> 34.25 | H11: m
A12: 6 | B12: EJE 03 | C12: TRAMO 01 | D12: ABIERTA | E12: 22.4 | F12: 0 | G12: =IF(B12="","",IF(D12="ABIERTA",IF(E12-F12<0,0,E12-F12),0)) -> 22.4 | H12: m
A13: 7 | B13: EJE 04 | C13: TRAMO 01 | D13: ABIERTA | E13: 13.65 | F13: 0 | G13: =IF(B13="","",IF(D13="ABIERTA",IF(E13-F13<0,0,E13-F13),0)) -> 13.65 | H13: m
A14: 8 | B14: EJE 04 | C14: TRAMO 02 | D14: TAPADA | E14: 5.5 | F14: 0 | G14: =IF(B14="","",IF(D14="ABIERTA",IF(E14-F14<0,0,E14-F14),0)) -> 0 | H14: m
A15: 9 | B15: EJE 04 | C15: TRAMO 03 | D15: ABIERTA | E15: 58 | F15: 0 | G15: =IF(B15="","",IF(D15="ABIERTA",IF(E15-F15<0,0,E15-F15),0)) -> 58 | H15: m
A16: 10 | B16: EJE 04 | C16: TRAMO 04 | D16: TAPADA | E16: 25.16 | F16: 0 | G16: =IF(B16="","",IF(D16="ABIERTA",IF(E16-F16<0,0,E16-F16),0)) -> 0 | H16: m
A17: 11 | B17: EJE 05 | C17: TRAMO 01 | D17: ABIERTA | E17: 32.3 | F17: 0 | G17: =IF(B17="","",IF(D17="ABIERTA",IF(E17-F17<0,0,E17-F17),0)) -> 32.3 | H17: m
A18: 12 | B18: EJE 05 | C18: TRAMO 02 | D18: TAPADA | E18: 9.9 | F18: 0 | G18: =IF(B18="","",IF(D18="ABIERTA",IF(E18-F18<0,0,E18-F18),0)) -> 0 | H18: m
... A25: 19 | B25: EJE 09 | C25: TRAMO 02 | D25: TAPADA | E25: 6.66 | F25: 0 | G25: =IF(B25="","",IF(D25="ABIERTA",IF(E25-F25<0,0,E25-F25),0)) -> 0 | H25: m
A27: TOTAL CALCULADO DE REJILLA EN CUNETAS ABIERTAS | G27: =SUM(G7:G25) -> 373.85 | H27: m

Sheet METRADO JUNTA DE DILATACION
A1: PLANILLA DE METRADOS - JUNTA DE DILATACIÓN E=1" (0.0254 m) CON SELLADOR ASFÁLTICO EN CUNETAS: TODA LA SECCIÓN (2 MUROS + LOSA DE FONDO)
A2: ENTIDAD | B2: GERENCIA TERRITORIAL BAJO MAYO - TARAPOTO
A3: PROYECTO | B3: =+RESUMEN!B5 -> CREACIÓN DEL SERVICIO DE PROTECCIÓN INTEGRAL A NIÑAS, NIÑOS Y ADOLESCENTES SIN CUIDADOS PARENTALES O EN RIESGO DE PERDERLOS EN CENTRO DE ACOGIDA RESIDENCIAL - VARONES DISTRITO DE MORALES DE LA PROVINCIA DE SAN MARTÍN DEL DEPARTAMENTO DE SAN MARTÍN, con CUI N.° 2705619
A4: UBICACIÓN | B4: =+RESUMEN!B6 -> SAN MARTIN - SAN MARTIN - MORALES
A5: FECHA | B5: =+RESUMEN!B7 -> 46266
A7: PARÁMETROS
A8: Espaciamiento entre juntas (m) | B8: 3
A9: N° de muros con junta por cuneta | B9: 2
A10: Ancho interior del fondo (m) | B10: 0.4
A11: ITEM | B11: EJE / DESCRIPCIÓN | C11: UND. | D11: LONGITUD EJE (m) | E11: ÁREA MURO (m²) | F11: ALTURA MURO (m) | G11: ESPACIAMIENTO (m) | H11: N° DE JUNTAS | I11: LONG. POR JUNTA (m) 2 muros + fondo | J11: PARCIAL (ml)
A12: Descripccion | B12: JUNTA DE DILATACION E=1" CON SELLADOR ASFALTO | C12: ml | J12: =SUM(J13:J21) -> 252.28688
A13: 1 | B13: EJE 01 | D13: 111.53 | E13: =+'CONCRETO EN CUNETAS'!E10 -> 61.2 | F13: =E13/D13 -> 0.54873128 | G13: =B8 -> 3 | H13: =ROUNDUP(D13/G13,0) -> 38 | I13: =$B$9*F13+$B$10 -> 1.4974626 | J13: =H13*I13 -> 56.903578
A14: 2 | B14: EJE 02 | D14: 34.25 | E14: =+'CONCRETO EN CUNETAS'!E22 -> 13.19 | F14: =E14/D14 -> 0.38510949 | G14: =B8 -> 3 | H14: =ROUNDUP(D14/G14,0) -> 12 | I14: =$B$9*F14+$B$10 -> 1.170219 | J14: =H14*I14 -> 14.042628
A15: 3 | B15: EJE 03 | D15: 22.4 | E15: =+'CONCRETO EN CUNETAS'!E34 -> 7.98 | F15: =E15/D15 -> 0.35625 | G15: =B8 -> 3 | H15: =ROUNDUP(D15/G15,0) -> 8 | I15: =$B$9*F15+$B$10 -> 1.1125 | J15: =H15*I15 -> 8.9
A16: 4 | B16: EJE 04 | D16: 102.31 | E16: =+'CONCRETO EN CUNETAS'!E46 -> 54.29 | F16: =E16/D16 -> 0.53064217 | G16: =B8 -> 3 | H16: =ROUNDUP(D16/G16,0) -> 35 | I16: =$B$9*F16+$B$10 -> 1.4612843 | J16: =H16*I16 -> 51.144952
A17: 5 | B17: EJE 05 | D17: 42.2 | E17: =+'CONCRETO EN CUNETAS'!E58 -> 17.07 | F17: =E17/D17 -> 0.40450237 | G17: =B8 -> 3 | H17: =ROUNDUP(D17/G17,0) -> 15 | I17: =$B$9*F17+$B$10 -> 1.2090047 | J17: =H17*I17 -> 18.135071
A18: 6 | B18: EJE 06 | D18: 98.69 | E18: =+'CONCRETO EN CUNETAS'!E70 -> 52.71 | F18: =E18/D18 -> 0.53409667 | G18: =B8 -> 3 | H18: =ROUNDUP(D18/G18,0) -> 33 | I18: =$B$9*F18+$B$10 -> 1.4681933 | J18: =H18*I18 -> 48.45038
A19: 7 | B19: EJE 07 | D19: 23.6 | E19: =+'CONCRETO EN CUNETAS'!M10 -> 8.46 | F19: =E19/D19 -> 0.35847458 | G19: =B8 -> 3 | H19: =ROUNDUP(D19/G19,0) -> 8 | I19: =$B$9*F19+$B$10 -> 1.1169492 | J19: =H19*I19 -> 8.9355932
A20: 8 | B20: EJE 08 | D20: 60.6 | E20: =+'CONCRETO EN CUNETAS'!M22 -> 27.34 | F20: =E20/D20 -> 0.45115512 | G20: =B8 -> 3 | H20: =ROUNDUP(D20/G20,0) -> 21 | I20: =$B$9*F20+$B$10 -> 1.3023102 | J20: =H20*I20 -> 27.348515
A21: 9 | B21: EJE 09 | D21: 42.66 | E21: =+'CONCRETO EN CUNETAS'!M34 -> 17.67 | F21: =E21/D21 -> 0.41420534 | G21: =B8 -> 3 | H21: =ROUNDUP(D21/G21,0) -> 15 | I21: =$B$9*F21+$B$10 -> 1.2284107 | J21: =H21*I21 -> 18.42616
A23: NOTAS:
A24: 1. EG-2013 MTC, Seccion 510 (cunetas revestidas de concreto): la junta corta toda la seccion en U, es decir los dos muros y la losa de fondo, para que cada paño de 3.00 m trabaje independiente.
A25: 2. Longitud por junta = 2 x altura del muro (area del muro / longitud del eje, hoja CONCRETO EN CUNETAS) + ancho interior del fondo 0.40 m.
A26: 3. Junta e = 1" (0.0254 m): tecnopor de 1" en todo el espesor y sellador asfaltico (RC-250 + arena) en la cara interior; se mide en metros lineales de junta sellada. Detalle en la lamina DPLV-31.

Sheet METRADO LLORADEROS
A1: METRADO DE LLORADEROS DE PVC Ø3" EN MUROS DE CUNETA COLINDANTES CON ÁREA VERDE
A2: ENTIDAD | C2: GERENCIA TERRITORIAL BAJO MAYO - TARAPOTO
A3: PROYECTO | C3: =+RESUMEN!B5 -> CREACIÓN DEL SERVICIO DE PROTECCIÓN INTEGRAL A NIÑAS, NIÑOS Y ADOLESCENTES SIN CUIDADOS PARENTALES O EN RIESGO DE PERDERLOS EN CENTRO DE ACOGIDA RESIDENCIAL - VARONES DISTRITO DE MORALES DE LA PROVINCIA DE SAN MARTÍN DEL DEPARTAMENTO DE SAN MARTÍN, con CUI N.° 2705619
A4: UBICACIÓN | C4: =+RESUMEN!B6 -> SAN MARTIN - SAN MARTIN - MORALES | G4: FECHA | H4: =+RESUMEN!B7 -> 46266
A6: N° | B6: EJE | C6: PROGRESIVA DEL TRAMO (desde - hasta) | D6: LADO DEL MURO | E6: LONGITUD JUNTO A ÁREA VERDE (m) | F6: ESPACIAMIENTO (m) | G6: N° DE LLORADEROS | H6: UND.
A7: 1 | B7: EJE 01 | C7: 0+013.50 a 0+019.00 | D7: LADO ESTE | E7: 5.5 | F7: 1.5 | G7: =IF(B7="","",ROUNDUP(E7/F7,0)) -> 4 | H7: und
A8: 2 | B8: EJE 01 | C8: 0+054.75 a 0+077.25 | D8: LADO ESTE | E8: 22.5 | F8: 1.5 | G8: =IF(B8="","",ROUNDUP(E8/F8,0)) -> 15 | H8: und
A9: 3 | B9: EJE 01 | C9: 0+080.75 a 0+111.53 | D9: LADO ESTE | E9: 30.78 | F9: 1.5 | G9: =IF(B9="","",ROUNDUP(E9/F9,0)) -> 21 | H9: und
A10: 4 | B10: EJE 02 | C10: 0+000.00 a 0+013.25 | D10: LADO ESTE | E10: 13.25 | F10: 1.5 | G10: =IF(B10="","",ROUNDUP(E10/F10,0)) -> 9 | H10: und
A11: 5 | B11: EJE 02 | C11: 0+021.00 a 0+023.03 | D11: LADO OESTE | E11: 2.03 | F11: 1.5 | G11: =IF(B11="","",ROUNDUP(E11/F11,0)) -> 2 | H11: und
A12: 6 | B12: EJE 02 | C12: 0+023.03 a 0+033.78 | D12: LADO SUR | E12: 10.75 | F12: 1.5 | G12: =IF(B12="","",ROUNDUP(E12/F12,0)) -> 8 | H12: und
A13: 7 | B13: EJE 03 | C13: 0+000.00 a 0+005.50 | D13: LADO OESTE | E13: 5.5 | F13: 1.5 | G13: =IF(B13="","",ROUNDUP(E13/F13,0)) -> 4 | H13: und
A14: 8 | B14: EJE 03 | C14: 0+007.00 a 0+015.48 | D14: LADO OESTE | E14: 8.48 | F14: 1.5 | G14: =IF(B14="","",ROUNDUP(E14/F14,0)) -> 6 | H14: und
A15: 9 | B15: EJE 03 | C15: 0+017.73 a 0+021.48 | D15: LADO SUR | E15: 3.75 | F15: 1.5 | G15: =IF(B15="","",ROUNDUP(E15/F15,0)) -> 3 | H15: und
A16: 10 | B16: EJE 04 | C16: 0+020.50 a 0+024.25 | D16: LADO ESTE | E16: 3.75 | F16: 1.5 | G16: =IF(B16="","",ROUNDUP(E16/F16,0)) -> 3 | H16: und
A17: 11 | B17: EJE 04 | C17: 0+034.75 a 0+038.50 | D17: LADO ESTE | E17: 3.75 | F17: 1.5 | G17: =IF(B17="","",ROUNDUP(E17/F17,0)) -> 3 | H17: und
A18: 12 | B18: EJE 04 | C18: 0+045.00 a 0+048.75 | D18: LADO ESTE | E18: 3.75 | F18: 1.5 | G18: =IF(B18="","",ROUNDUP(E18/F18,0)) -> 3 | H18: und
... A40: 34 | B40: EJE 09 | C40: 0+000.25 a 0+021.75 | D40: LADO OESTE | E40: 21.5 | F40: 1.5 | G40: =IF(B40="","",ROUNDUP(E40/F40,0)) -> 15 | H40: und
A42: TOTAL DE LLORADEROS EN CUNETAS COLINDANTES CON ÁREA VERDE | E42: =SUM(E7:E40) -> 320.53 | G42: =SUM(G7:G40) -> 226 | H42: und
A44: CRITERIO DE METRADO
A45: 1. Solo llevan lloraderos los muros de cuneta colindantes con área verde (detalle de instalación de lloraderos en cunetas de evacuación pluvial y especificación técnica del plano de drenaje: lloraderos de tubería PVC Ø3", espaciamiento típico L = 1.50 m, en muros de contención de la cuneta colindantes con áreas verdes).
A46: 2. Tramos medidos en la planta general de drenaje: muro cuya franja exterior de 0.30 m queda dentro del achurado de área verde; no se cuentan tramos menores de 1.50 m. Progresivas desde el inicio de cada eje (igual que los perfiles), recortadas a la longitud del eje de este metrado.
A47: 3. N° de lloraderos por tramo = REDONDEAR.MAS(longitud / 1.50). Cada unidad comprende: pase de tubería PVC-U Ø3" (L = 0.30 m) a media altura del muro con pendiente S = 0.5 % hacia la cuneta; filtro localizado de grava 20-40 mm de 0.30 x 0.30 x 0.30 m (0.027 m³) envuelto en geotextil no tejido (0.60 m² con traslapes); excavación local y relleno del filtro.
A48: 4. Partida nueva: no modifica ninguna otra partida del metrado.

Sheet PLANILLA TAPAS REGISTRO INTERNO
A1: METRADO DE TAPAS DE REGISTRO EN CUNETAS TAPADAS
A2: ENTIDAD | B2: GERENCIA TERRITORIAL BAJO MAYO - TARAPOTO
A3: PROYECTO | B3: =+RESUMEN!B5 -> CREACIÓN DEL SERVICIO DE PROTECCIÓN INTEGRAL A NIÑAS, NIÑOS Y ADOLESCENTES SIN CUIDADOS PARENTALES O EN RIESGO DE PERDERLOS EN CENTRO DE ACOGIDA RESIDENCIAL - VARONES DISTRITO DE MORALES DE LA PROVINCIA DE SAN MARTÍN DEL DEPARTAMENTO DE SAN MARTÍN, con CUI N.° 2705619
A4: UBICACIÓN | B4: =+RESUMEN!B6 -> SAN MARTIN - SAN MARTIN - MORALES
A5: FECHA | B5: =+RESUMEN!B7 -> 46266
A7: ITEM | B7: DESCRIPCIÓN | C7: Nº DE VECES | D7: DIMENSIONES | I7: PARCIAL | J7: TOTAL | K7: UND
D8: LARGO | E8: ANCHO | F8: ALTURA | G8: FACT. | H8: AREA | I8: VOLUMEN / PARCIAL
A9: 01.04.03.04.03.02 | B9: TAPA DE REGISTRO (DE CONCRETO) | J9: =+PARAMETROS!B4 -> 18 | K9: und
B11: CONCRETO F´C=210 KG/CM2 EN TAPA DE REGISTRO | I11: TOTAL
B12: TAPA 0.60 x 0.60 x 0.10 m | C12: =PARAMETROS!B4 -> 18 | D12: =PARAMETROS!B5 -> 0.6 | E12: =PARAMETROS!B6 -> 0.6 | F12: =PARAMETROS!B7 -> 0.1 | I12: =C12*D12*E12*F12 -> 0.648 | J12: =I12 -> 0.648 | K12: m3
B14: ENCOFRADO Y DESENCOFRADO EN TAPA DE REGISTRO | I14: TOTAL
B15: LATERALES DE TAPA | C15: =PARAMETROS!B4 -> 18 | D15: =2*(PARAMETROS!B5+PARAMETROS!B6) -> 2.4 | F15: =PARAMETROS!B7 -> 0.1 | H15: =D15*F15 -> 0.24 | I15: =C15*H15 -> 4.32 | J15: =I15 -> 4.32 | K15: m2
B16: FONDO DE MOLDE / BASE DE PREFABRICADO | C16: =PARAMETROS!B4 -> 18 | D16: =PARAMETROS!B5 -> 0.6 | E16: =PARAMETROS!B6 -> 0.6 | H16: =D16*E16 -> 0.36 | I16: =C16*H16 -> 6.48 | J16: =I16 -> 6.48 | K16: m2
B17: TOTAL ENCOFRADO FONDO + LATERALES | J17: =J15+J16 -> 10.8 | K17: m2
B19: ACERO FY=4200 KG/CM2 EN TAPA DE REGISTRO - VARILLA 3/8 | D19: LONGITUD DE CADA BARRA | E19: CANTIDAD DE BARRAS POR TAPA | I19: TOTAL
B20: Acero longitudinal 3/8 - parrilla simple | C20: =PARAMETROS!B4 -> 18 | D20: =PARAMETROS!B5-2*PARAMETROS!B8 -> 0.55 | E20: =ROUND((PARAMETROS!B6-2*PARAMETROS!B8)/PARAMETROS!B9,0)+1 -> 5 | G20: =PARAMETROS!B10 -> 0.56 | I20: =C20*D20*E20*G20 -> 27.72 | J20: =I20 -> 27.72 | K20: kg
B21: Acero transversal 3/8 - parrilla simple | C21: =PARAMETROS!B4 -> 18 | D21: =PARAMETROS!B6-2*PARAMETROS!B8 -> 0.55 | E21: =ROUND((PARAMETROS!B5-2*PARAMETROS!B8)/PARAMETROS!B9,0)+1 -> 5 | G21: =PARAMETROS!B10 -> 0.56 | I21: =C21*D21*E21*G21 -> 27.72 | J21: =I21 -> 27.72 | K21: kg
B22: TOTAL ACERO 3/8 | J22: =J20+J21 -> 55.44 | K22: kg

Sheet CUNETAS - LLEGADA AL COLECTOR
A1: CUNETAS - ACORTAMIENTO EN LA LLEGADA AL COLECTOR PLUVIAL FRONTAL
A2: ENTIDAD | C2: =+RESUMEN!B4 -> GERENCIA TERRITORIAL BAJO MAYO - TARAPOTO
A3: PROYECTO | C3: =+RESUMEN!B5 -> CREACIÓN DEL SERVICIO DE PROTECCIÓN INTEGRAL A NIÑAS, NIÑOS Y ADOLESCENTES SIN CUIDADOS PARENTALES O EN RIESGO DE PERDERLOS EN CENTRO DE ACOGIDA RESIDENCIAL - VARONES DISTRITO DE MORALES DE LA PROVINCIA DE SAN MARTÍN DEL DEPARTAMENTO DE SAN MARTÍN, con CUI N.° 2705619
A4: UBICACIÓN | C4: =+RESUMEN!B6 -> SAN MARTIN - SAN MARTIN - MORALES
A5: FECHA | C5: =+RESUMEN!B7 -> 46266
A7: Las cunetas estan dibujadas hasta la franja exterior del frente. El colector pluvial frontal ocupa esa franja, por lo que cada cuneta termina en la cara del muro lado predio del colector (ventana de empalme, lamina DPLV-24) o en el muro norte de la caja de llegada CL del Hogar de Refugio (Eje 01, lamina DPLV-25). El tramo que caia dentro del colector se descuenta de la longitud de la cuneta en todas las hojas de este metrado (concreto, encofrado, acero, curado, rejillas, juntas, movimiento de tierras).
A9: N° | B9: CUNETA | C9: LONGITUD DIBUJADA (m) | D9: ACORTAMIENTO (m) | E9: LONGITUD METRADA (m) | F9: TERMINA EN | G9: SUSTENTO
A10: 1 | B10: EJE 01 | C10: 114.3 | D10: 2.77 | E10: =C10-D10 -> 111.53 | F10: muro norte de la caja CL | G10: Lamina DPLV-17 del colector (planta: tramo de cuneta que se descuenta) y memoria de calculo del colector, hoja CUNETAS
A11: 2 | B11: EJE 04 | C11: 105.7 | D11: 3.39 | E11: =C11-D11 -> 102.31 | F11: muro del colector (ventana) | G11: Lamina DPLV-17 del colector (planta: tramo de cuneta que se descuenta) y memoria de calculo del colector, hoja CUNETAS
A12: 3 | B12: EJE 06 | C12: 98.95 | D12: 0.26 | E12: =C12-D12 -> 98.69 | F12: muro del colector (ventana) | G12: Lamina DPLV-17 del colector (planta: tramo de cuneta que se descuenta) y memoria de calculo del colector, hoja CUNETAS
A13: 4 | B13: EJE 08 | C13: 60.7 | D13: 0.1 | E13: =C13-D13 -> 60.6 | F13: muro del colector (ventana) | G13: Lamina DPLV-17 del colector (planta: tramo de cuneta que se descuenta) y memoria de calculo del colector, hoja CUNETAS
A14: 5 | B14: EJE 09 | C14: 42.7 | D14: 0.04 | E14: =C14-D14 -> 42.66 | F14: muro del colector (ventana) | G14: Lamina DPLV-17 del colector (planta: tramo de cuneta que se descuenta) y memoria de calculo del colector, hoja CUNETAS
A16: Nota: el acortamiento se aplica al ultimo tramo de cada eje (el que llega al frente); las alturas H se mantienen las del perfil. Las cunetas de los Ejes 02, 03, 05 y 07 no llegan al frente y no cambian.

Sheet PARAMETROS
A1: PARÁMETROS - TAPA DE REGISTRO DE CONCRETO
A3: Descripción | B3: Valor | C3: Unidad | D3: Criterio
A4: Cantidad de tapas | B4: 18 | C4: und | D4: Provisional: 1 tapa por tramo tapado (8 tramos); confirmar con el plano
A5: Largo de tapa | B5: 0.6 | C5: m | D5: Según detalle
A6: Ancho de tapa | B6: 0.6 | C6: m | D6: Según detalle
A7: Espesor de tapa | B7: 0.1 | C7: m | D7: Según detalle
A8: Recubrimiento considerado | B8: 0.025 | C8: m | D8: Editable según plano estructural
A9: Separación de varillas 3/8 | B9: 0.15 | C9: m | D9: Parrilla simple en ambos sentidos
A10: Peso varilla 3/8 | B10: 0.56 | C10: kg/m | D10: Peso unitario usado para metrado
A11: Longitud varilla comercial | B11: 9 | C11: m | D11: Solo equivalente de longitud, sin redondeo
A13: PARÁMETROS - MOVIMIENTO DE TIERRAS
A14: Descripción | B14: Valor | C14: Unidad | D14: Criterio
A15: Espesor de solado sumado a excavación y relleno | B15: 0.1 | C15: m | D15: Solado e=4" bajo la losa. Poner 0 si la altura ya lo incluye
A16: Factor de esponjamiento | B16: 1.2 | C16: - | D16: Eliminación = (excavación − relleno) × factor

Sheet Listas
A1: LISTAS, FACTORES Y PARÁMETROS EDITABLES
A3: DIÁMETRO | B3: FACTOR kg/m | D3: TIPO DE CUNETA | F3: CRITERIO DE CONTEO
A4: 6 mm | B4: 0.222 | D4: ABIERTA | F4: TEÓRICO (L/s+1)
A5: 8 mm | B5: 0.395 | D5: TAPADA | F5: ENTERO (redondeo arriba)
A6: 3/8" | B6: 0.56
A7: 12 mm | B7: 0.888
A8: 1/2" | B8: 0.994
A9: 5/8" | B9: 1.552
A10: 3/4" | B10: 2.235
A11: 1" | B11: 3.973
A13: NOTA
A14: Los factores kg/m son editables. Si el proyecto usa otro factor, cámbialo aquí.
A15: La opción TEÓRICO mantiene cantidades decimales: Longitud / separación + 1.
A16: La opción ENTERO redondea hacia arriba antes de sumar la barra final.

Sheet COLECTOR PARAMETROS
A1: COLECTOR PLUVIAL FRONTAL - PARAMETROS DE METRADO
A2: ENTIDAD | C2: =+RESUMEN!B4 -> GERENCIA TERRITORIAL BAJO MAYO - TARAPOTO
A3: PROYECTO | C3: =+RESUMEN!B5 -> CREACIÓN DEL SERVICIO DE PROTECCIÓN INTEGRAL A NIÑAS, NIÑOS Y ADOLESCENTES SIN CUIDADOS PARENTALES O EN RIESGO DE PERDERLOS EN CENTRO DE ACOGIDA RESIDENCIAL - VARONES DISTRITO DE MORALES DE LA PROVINCIA DE SAN MARTÍN DEL DEPARTAMENTO DE SAN MARTÍN, con CUI N.° 2705619
A4: UBICACIÓN | C4: =+RESUMEN!B6 -> SAN MARTIN - SAN MARTIN - MORALES
A5: FECHA | C5: =+RESUMEN!B7 -> 46266
A7: Tramo CAR Varones (CUI 2705619), empalme con la caja de llegada CL del colector del Hogar de Refugio Temporal (CUI 2675514). Valores tomados de las laminas DPLV-17 a DPLV-30 y de la memoria de calculo del colector. Celda amarilla = dato; verde = formula.
A9: N° | B9: PARAMETRO | C9: VALOR | D9: UND | E9: SUSTENTO (lamina / norma / criterio)
A10: 1 | B10: Ancho interior del colector b | C10: 0.6 | D10: m | E10: Laminas DPLV-21 y DPLV-22 (secciones); memoria de calculo, hoja DATOS
A11: 2 | B11: Espesor de muros | C11: 0.15 | D11: m | E11: Laminas DPLV-21 y DPLV-22; memoria, hoja ESTRUCTURAL
A12: 3 | B12: Espesor de losa de fondo | C12: 0.15 | D12: m | E12: Laminas DPLV-21 y DPLV-22
A13: 4 | B13: Espesor de losa superior (tramo normal) | C13: 0.1 | D13: m | E13: Laminas DPLV-21 y DPLV-22 (secciones S-02 a S-08)
A14: 5 | B14: Espesor de losa superior (cruce de camiones cisterna) | C14: 0.25 | D14: m | E14: Lamina DPLV-21 (seccion S-01); memoria, hoja ESTRUCTURAL (carga HL-93)
A15: 6 | B15: Espesor de solado | C15: 0.05 | D15: m | E15: Laminas DPLV-21 y DPLV-22
A16: 7 | B16: Nivel de piso terminado del frente (cara superior de la losa) | C16: 261.15 | D16: msnm | E16: Lamina DPLV-18 (perfil) y plano de arquitectura (+261.15)
A17: 8 | B17: Sobreancho de excavacion a cada lado del colector | C17: 0.25 | D17: m | E17: Zanja de 1.40 m (0.90 + 2 x 0.25)
A18: 9 | B18: Franja de relleno de nivelacion del retiro, lado via | C18: 1 | D18: m
A19: 10 | B19: Recubrimiento del acero | C19: 0.04 | D19: m | E19: Norma E.060, tabla 7.7.1 (concreto en contacto con el suelo)
A20: 11 | B20: Peso de la barra de 3/8" | C20: 0.56 | D20: kg/m | E20: Igual a PARAMETROS!B10 de esta planilla
A21: 12 | B21: Peso de la barra de 1/2" | C21: 0.994 | D21: kg/m | E21: Catalogo del fabricante (0.994 kg/m)
A22: 13 | B22: Traslape de barras longitudinales | C22: 0.4 | D22: m | E22: Norma E.060, 12.15 (clase B, 3/8"): 0.40 m
A23: 14 | B23: Longitud comercial de barra | C23: 9 | D23: m | E23: Igual a PARAMETROS!B11 de esta planilla
A24: 15 | B24: Ganchos de cierre del marco (2 x 0.15) | C24: 0.3 | D24: m
A25: 16 | B25: Factor de esponjamiento | C25: =PARAMETROS!$B$16 -> 1.2 | D25: - | E25: Igual a PARAMETROS!B16 de esta planilla
A26: 17 | B26: Espaciamiento de marcos en tramo normal | C26: 0.2 | D26: m | E26: Laminas DPLV-21 y DPLV-22
A27: 18 | B27: Espaciamiento de marcos en el cruce de camiones | C27: 0.15 | D27: m | E27: Lamina DPLV-21 (seccion S-01)
A28: 19 | B28: Espaciamiento de barras longitudinales (tramo normal) | C28: 0.25 | D28: m | E28: Laminas DPLV-21 y DPLV-22
A29: 20 | B29: Espaciamiento de barras longitudinales (camiones) | C29: 0.2 | D29: m | E29: Lamina DPLV-21 (seccion S-01)
A30: 21 | B30: Numero de registros de limpieza con tapa | C30: 11 | D30: und | E30: Lamina DPLV-17 (RV-01 a RV-11), todos en la losa del colector; hoja COLECTOR REGISTROS Y TAPAS
A31: 22 | B31: Lado de la tapa de concreto | C31: 0.68 | D31: m | E31: Lamina DPLV-23 (tapa ciega de concreto armado)
A32: 23 | B32: Espesor de la tapa | C32: 0.08 | D32: m | E32: Lamina DPLV-23 (= profundidad del rebaje)
A33: 24 | B33: Lado del rebaje de asiento de la tapa en la losa (0.70 x 0.70 x 0.08) | C33: 0.7 | D33: m | E33: Lamina DPLV-23 (tapa ciega)
A34: 25 | B34: Luz libre del registro bajo el rebaje (0.60 x 0.60) | C34: 0.6 | D34: m | E34: Lamina DPLV-23
A35: 26 | B35: Perimetro del encofrado lateral de la tapa (4 x 0.68) | C35: 2.72 | D35: m | E35: Lamina DPLV-23
A36: 27 | B36: Asas de izaje por tapa (fierro liso 1/2" en cajuelas) | C36: 2 | D36: und | E36: Lamina DPLV-23
A37: 28 | B37: Desarrollo de cada asa de fierro liso 1/2" | C37: 0.5 | D37: m | E37: Lamina DPLV-23: agarre 0.15 + 2 patas de 0.02 + 2 ganchos de 0.15 (0.49, se toma 0.50)
... A39: 30 | B39: Bisel de los cantos superiores de la tapa | C39: 0.01 | D39: m | E39: Lamina DPLV-23
A40: 31 | B40: Borde engrosado de la abertura: perimetro (solo los 2 lados transversales, entre muros) | C40: =2*C10 -> 1.2 | D40: m | E40: Lamina DPLV-23: 2 x b; b = 0.60 es menor que la abertura de 0.70, en los lados largos el asiento es la cabeza del muro
A41: 32 | B41: Borde engrosado: seccion (0.15 x 0.10) | C41: 0.015 | D41: m2 | E41: Lamina DPLV-23
A42: 33 | B42: Cota de fondo del colector en el arranque (0+000) | C42: 260.2 | D42: msnm | E42: Lamina DPLV-18; memoria, hoja PERFIL_FLUJO
A43: 34 | B43: Cota de fondo del colector en la llegada a la CL (0+105.29) | C43: 259.884 | D43: msnm | E43: Laminas DPLV-18 y DPLV-25; memoria, hoja EMPALME_CL
A44: 35 | B44: Espaciamiento de juntas de dilatacion | C44: 4 | D44: m | E44: Lamina DPLV-17, nota; DPLV-18
A45: 36 | B45: Altura interior maxima del colector (para el perimetro de la junta) | C45: 1.17 | D45: m | E45: Lamina DPLV-18 (perfil): llegada a la CL
A46: 37 | B46: Progresiva final (cara este de la caja CL) | C46: 105.29 | D46: m | E46: Lamina DPLV-17
A47: 38 | B47: Progresiva del quiebre (inicio del tramo de empalme) | C47: 100.9 | D47: m | E47: Lamina DPLV-17
A48: 39 | B48: Ancho exterior del muro este de la caja CL (contacto con el colector) | C48: 1.3 | D48: m | E48: Lamina DPLV-25

Sheet COLECTOR MOV. TIERRAS
A1: COLECTOR PLUVIAL FRONTAL - METRADO DE MOVIMIENTO DE TIERRAS
A2: ENTIDAD | C2: =+RESUMEN!B4 -> GERENCIA TERRITORIAL BAJO MAYO - TARAPOTO
A3: PROYECTO | C3: =+RESUMEN!B5 -> CREACIÓN DEL SERVICIO DE PROTECCIÓN INTEGRAL A NIÑAS, NIÑOS Y ADOLESCENTES SIN CUIDADOS PARENTALES O EN RIESGO DE PERDERLOS EN CENTRO DE ACOGIDA RESIDENCIAL - VARONES DISTRITO DE MORALES DE LA PROVINCIA DE SAN MARTÍN DEL DEPARTAMENTO DE SAN MARTÍN, con CUI N.° 2705619
A4: UBICACIÓN | C4: =+RESUMEN!B6 -> SAN MARTIN - SAN MARTIN - MORALES
A5: FECHA | C5: =+RESUMEN!B7 -> 46266
A7: Criterio: LIMPIEZA Y TRAZO = ancho de zanja x L. EXCAVACION = ancho de zanja x Hz x L, con Hz = terreno existente (topografia) - fondo del solado. REFINE = (ancho exterior + 0.10) x L (fondo del solado). RELLENO LATERAL = 2 x sobreancho x Hz x L. RELLENO FRANJA = 1.00 x (NPT - terreno) x L (nivelacion del retiro lado via). h y Hz son valores medios ponderados del tramo (perfil DPLV-18 y topografia); el detalle cada 2.00 m esta en la memoria de calculo.
A9: N° | B9: TRAMO | C9: ZONA | D9: PROG. INICIO | E9: PROG. FIN | F9: LONGITUD (m) | G9: ALTURA INTERIOR h (m) | H9: e LOSA SUP. (m) | I9: ANCHO EXT. b + 2e (m) | J9: ANCHO DE ZANJA (m) | K9: Hz: TERRENO - FONDO DE SOLADO (m) | L9: NPT - TERRENO (m) | M9: LIMPIEZA Y TRAZO (m2) | N9: EXCAVACION (m3) | O9: REFINE Y NIVELACION (m2) | P9: RELLENO LATERAL DE ZANJA (m3) | Q9: RELLENO FRANJA DE NIVELACION (m3) | R9: SUSTENTO
A10: 1 | B10: cruce de camiones | C10: CAMION | D10: 0+000.00 | E10: 0+006.08 | F10: 6.08 | G10: 0.709 | H10: 0.25 | I10: ='COLECTOR PARAMETROS'!$C$10+2*'COLECTOR PARAMETROS'!$C$11 -> 0.9 | J10: =I10+2*'COLECTOR PARAMETROS'!$C$17 -> 1.4 | K10: 1.209 | L10: 0 | M10: =J10*F10 -> 8.512 | N10: =J10*K10*F10 -> 10.291008 | O10: =(I10+0.1)*F10 -> 6.08 | P10: =2*'COLECTOR PARAMETROS'!$C$17*K10*F10 -> 3.67536 | Q10: ='COLECTOR PARAMETROS'!$C$18*L10*F10 -> 0 | R10: DPLV-17 (planta), DPLV-18 (perfil: fondo y terreno), DPLV-21 y DPLV-22 (seccion)
A11: 2 | B11: tramo normal | C11: NORMAL | D11: 0+006.08 | E11: 0+100.90 | F11: 94.82 | G11: 1.01 | H11: 0.1 | I11: ='COLECTOR PARAMETROS'!$C$10+2*'COLECTOR PARAMETROS'!$C$11 -> 0.9 | J11: =I11+2*'COLECTOR PARAMETROS'!$C$17 -> 1.4 | K11: 0.876 | L11: 0.436 | M11: =J11*F11 -> 132.748 | N11: =J11*K11*F11 -> 116.28725 | O11: =(I11+0.1)*F11 -> 94.82 | P11: =2*'COLECTOR PARAMETROS'!$C$17*K11*F11 -> 41.53116 | Q11: ='COLECTOR PARAMETROS'!$C$18*L11*F11 -> 41.34152 | R11: DPLV-17 (planta), DPLV-18 (perfil: fondo y terreno), DPLV-21 y DPLV-22 (seccion)
A12: 3 | B12: tramo de empalme con la CL (horizontal) | C12: NORMAL | D12: 0+100.90 | E12: 0+105.29 | F12: 4.39 | G12: 1.159 | H12: 0.1 | I12: ='COLECTOR PARAMETROS'!$C$10+2*'COLECTOR PARAMETROS'!$C$11 -> 0.9 | J12: =I12+2*'COLECTOR PARAMETROS'!$C$17 -> 1.4 | K12: 0.658 | L12: 0.802 | M12: =J12*F12 -> 6.146 | N12: =J12*K12*F12 -> 4.044068 | O12: =(I12+0.1)*F12 -> 4.39 | P12: =2*'COLECTOR PARAMETROS'!$C$17*K12*F12 -> 1.44431 | Q12: ='COLECTOR PARAMETROS'!$C$18*L12*F12 -> 3.52078 | R12: DPLV-17 (planta), DPLV-18 (perfil: fondo y terreno), DPLV-21 y DPLV-22 (seccion)
A13: TOTAL COLECTOR | F13: =SUM(F10:F12) -> 105.29 | M13: =SUM(M10:M12) -> 147.406 | N13: =SUM(N10:N12) -> 130.62232 | O13: =SUM(O10:O12) -> 105.29 | P13: =SUM(P10:P12) -> 46.65083 | Q13: =SUM(Q10:Q12) -> 44.8623
A15: RESUMEN PARA LA PLANILLA GENERAL (partidas 01.04.04.01 y 01.04.04.02)
A16: 1 | B16: LIMPIEZA MANUAL DE TERRENO / TRAZO Y REPLANTEO | F16: m2 | G16: =M13 -> 147.406
A17: 2 | B17: EXCAVACION MANUAL DE ZANJAS | F17: m3 | G17: =N13 -> 130.62232
A18: 3 | B18: REFINE, NIVELACION Y COMPACTACION | F18: m2 | G18: =O13 -> 105.29
A19: 4 | B19: RELLENO COMPACTADO (lateral + franja) | F19: m3 | G19: =P13+Q13 -> 91.51313
A20: 5 | B20: ELIMINACION DE MATERIAL EXCEDENTE = (excavacion - relleno) x esponjamiento | F20: m3 | G20: =(G17-G19)*'COLECTOR PARAMETROS'!$C$25 -> 46.931033
A22: Nota: el acortamiento de las cunetas que llegan al colector (Ejes 09, 08, 06, 04 y 01) esta aplicado en las hojas de cunetas de esta planilla (hoja CUNETAS - LLEGADA AL COLECTOR); no forma parte de esta partida. La caja CL pertenece al expediente del Hogar de Refugio.

Sheet COLECTOR CONCRETO
A1: COLECTOR PLUVIAL FRONTAL - METRADO DE CONCRETO SIMPLE Y ARMADO
A2: ENTIDAD | C2: =+RESUMEN!B4 -> GERENCIA TERRITORIAL BAJO MAYO - TARAPOTO
A3: PROYECTO | C3: =+RESUMEN!B5 -> CREACIÓN DEL SERVICIO DE PROTECCIÓN INTEGRAL A NIÑAS, NIÑOS Y ADOLESCENTES SIN CUIDADOS PARENTALES O EN RIESGO DE PERDERLOS EN CENTRO DE ACOGIDA RESIDENCIAL - VARONES DISTRITO DE MORALES DE LA PROVINCIA DE SAN MARTÍN DEL DEPARTAMENTO DE SAN MARTÍN, con CUI N.° 2705619
A4: UBICACIÓN | C4: =+RESUMEN!B6 -> SAN MARTIN - SAN MARTIN - MORALES
A5: FECHA | C5: =+RESUMEN!B7 -> 46266
A7: Criterio: SOLADO = (ancho exterior + 0.10) x L. LOSA DE FONDO = ancho exterior x e fondo x L. MUROS = 2 x e muro x h x L. LOSA SUPERIOR = ancho exterior x e losa x L. ACABADO = ancho exterior x L (losa superior frotachada y brunada). CURADO = 2 caras interiores de muros (2 x h x L) + fondo interior (b x L) + losa superior (ancho exterior x L), igual al criterio de la hoja METRADO DE CURADO.
A9: N° | B9: TRAMO | C9: ZONA | D9: LONGITUD (m) | E9: ALTURA INTERIOR h (m) | F9: e LOSA SUP. (m) | G9: ANCHO EXT. (m) | H9: SOLADO f'c=100 (m2) | I9: LOSA DE FONDO (m3) | J9: MUROS (m3) | K9: LOSA SUPERIOR (m3) | L9: ACABADO DE LOSA SUP. (m2) | M9: CURADO (m2) | N9: SUSTENTO
A10: 1 | B10: cruce de camiones | C10: CAMION | D10: ='COLECTOR MOV. TIERRAS'!F10 -> 6.08 | E10: ='COLECTOR MOV. TIERRAS'!G10 -> 0.709 | F10: ='COLECTOR MOV. TIERRAS'!H10 -> 0.25 | G10: ='COLECTOR MOV. TIERRAS'!I10 -> 0.9 | H10: =(G10+0.1)*D10 -> 6.08 | I10: =G10*'COLECTOR PARAMETROS'!$C$12*D10 -> 0.8208 | J10: =2*'COLECTOR PARAMETROS'!$C$11*E10*D10 -> 1.293216 | K10: =G10*F10*D10 -> 1.368 | L10: =G10*D10 -> 5.472 | M10: =(2*E10+'COLECTOR PARAMETROS'!$C$10+G10)*D10 -> 17.74144 | N10: DPLV-21 y DPLV-22 (secciones), DPLV-18 (h por tramo)
A11: 2 | B11: tramo normal | C11: NORMAL | D11: ='COLECTOR MOV. TIERRAS'!F11 -> 94.82 | E11: ='COLECTOR MOV. TIERRAS'!G11 -> 1.01 | F11: ='COLECTOR MOV. TIERRAS'!H11 -> 0.1 | G11: ='COLECTOR MOV. TIERRAS'!I11 -> 0.9 | H11: =(G11+0.1)*D11 -> 94.82 | I11: =G11*'COLECTOR PARAMETROS'!$C$12*D11 -> 12.8007 | J11: =2*'COLECTOR PARAMETROS'!$C$11*E11*D11 -> 28.73046 | K11: =G11*F11*D11 -> 8.5338 | L11: =G11*D11 -> 85.338 | M11: =(2*E11+'COLECTOR PARAMETROS'!$C$10+G11)*D11 -> 333.7664 | N11: DPLV-21 y DPLV-22 (secciones), DPLV-18 (h por tramo)
A12: 3 | B12: tramo de empalme con la CL (horizontal) | C12: NORMAL | D12: ='COLECTOR MOV. TIERRAS'!F12 -> 4.39 | E12: ='COLECTOR MOV. TIERRAS'!G12 -> 1.159 | F12: ='COLECTOR MOV. TIERRAS'!H12 -> 0.1 | G12: ='COLECTOR MOV. TIERRAS'!I12 -> 0.9 | H12: =(G12+0.1)*D12 -> 4.39 | I12: =G12*'COLECTOR PARAMETROS'!$C$12*D12 -> 0.59265 | J12: =2*'COLECTOR PARAMETROS'!$C$11*E12*D12 -> 1.526403 | K12: =G12*F12*D12 -> 0.3951 | L12: =G12*D12 -> 3.951 | M12: =(2*E12+'COLECTOR PARAMETROS'!$C$10+G12)*D12 -> 16.76102 | N12: DPLV-21 y DPLV-22 (secciones), DPLV-18 (h por tramo)
A13: TOTAL COLECTOR (tramos) | D13: =SUM(D10:D12) -> 105.29 | H13: =SUM(H10:H12) -> 105.29 | I13: =SUM(I10:I12) -> 14.21415 | J13: =SUM(J10:J12) -> 31.550079 | K13: =SUM(K10:K12) -> 10.2969 | L13: =SUM(L10:L12) -> 94.761 | M13: =SUM(M10:M12) -> 368.26886
A15: REGISTROS DE LIMPIEZA EN LA LOSA DEL COLECTOR - lamina DPLV-23 (borde engrosado 0.15 x 0.10 solo en los 2 lados transversales, entre muros: en los lados largos la abertura apoya en la cabeza de los muros; descuento de la abertura 0.70 x 0.70 en la losa superior)
A16: N° | B16: ELEMENTO | C16: DETALLE | D16: LARGO (m) | E16: ANCHO (m) | F16: ALTO / ESPESOR (m) | G16: VECES | H16: SOLADO (m2) | I16: LOSA DE FONDO (m3) | J16: MUROS (m3) | K16: LOSA SUPERIOR (m3) | L16: ACABADO (m2) | M16: CURADO (m2) | N16: SUSTENTO
A17: 1 | B17: Registros RV-01 a RV-11: borde engrosado de la abertura (2 lados, entre muros) | C17: perimetro x seccion | D17: ='COLECTOR PARAMETROS'!$C$40 -> 1.2 | E17: ='COLECTOR PARAMETROS'!$C$41 -> 0.015 | F17: 1 | G17: ='COLECTOR PARAMETROS'!$C$30 -> 11 | K17: =D17*E17*F17*G17 -> 0.198 | N17: DPLV-23, DPLV-27: 2 x 0.60 m por registro, en los 11 registros
A18: 2 | B18: Registros RV-01 a RV-11: descuento del rebaje y de la abertura en la losa superior | C18: rebaje 0.70 x 0.70 x 0.08 + luz 0.60 x 0.60 en el resto (e equivalente) | D18: ='COLECTOR PARAMETROS'!$C$33 -> 0.7 | E18: ='COLECTOR PARAMETROS'!$C$33 -> 0.7 | F18: ='COLECTOR PARAMETROS'!$C$32+('COLECTOR PARAMETROS'!$C$13-'COLECTOR PARAMETROS'!$C$32)*('COLECTOR PARAMETROS'!$C$34/'COLECTOR PARAMETROS'!$C$33)^2 -> 0.094693878 | G18: =-'COLECTOR PARAMETROS'!$C$30 -> -11 | K18: =D18*E18*F18*G18 -> -0.5104 | N18: DPLV-23
A19: TOTAL REGISTROS | H19: =SUM(H17:H18) -> 0 | I19: =SUM(I17:I18) -> 0 | J19: =SUM(J17:J18) -> 0 | K19: =SUM(K17:K18) -> -0.3124 | L19: =SUM(L17:L18) -> 0 | M19: =SUM(M17:M18) -> 0
A21: RESUMEN PARA LA PLANILLA GENERAL (partidas 01.04.04.03 y 01.04.04.04)
A22: 1 | B22: CONCRETO f'c=100 PARA SOLADO e=0.05 | F22: m2 | G22: =H13 -> 105.29 | H22: =H19 -> 0 | I22: =G22+H22 -> 105.29
A23: 2 | B23: CONCRETO f'c=210 EN LOSA DE FONDO | F23: m3 | G23: =I13 -> 14.21415 | H23: =I19 -> 0 | I23: =G23+H23 -> 14.21415
A24: 3 | B24: CONCRETO f'c=210 EN MUROS | F24: m3 | G24: =J13 -> 31.550079 | H24: =J19 -> 0 | I24: =G24+H24 -> 31.550079
A25: 4 | B25: CONCRETO f'c=210 EN LOSA SUPERIOR | F25: m3 | G25: =K13 -> 10.2969 | H25: =K19 -> -0.3124 | I25: =G25+H25 -> 9.9845
A26: 5 | B26: ACABADO FROTACHADO Y BRUÑADO DE LOSA SUPERIOR | F26: m2 | G26: =L13 -> 94.761 | H26: =L19 -> 0 | I26: =G26+H26 -> 94.761
A27: 6 | B27: CURADO DE CONCRETO | F27: m2 | G27: =M13 -> 368.26886 | H27: =M19 -> 0 | I27: =G27+H27 -> 368.26886

Sheet COLECTOR ENCOFRADO
A1: COLECTOR PLUVIAL FRONTAL - METRADO DE ENCOFRADO Y DESENCOFRADO
A2: ENTIDAD | C2: =+RESUMEN!B4 -> GERENCIA TERRITORIAL BAJO MAYO - TARAPOTO
A3: PROYECTO | C3: =+RESUMEN!B5 -> CREACIÓN DEL SERVICIO DE PROTECCIÓN INTEGRAL A NIÑAS, NIÑOS Y ADOLESCENTES SIN CUIDADOS PARENTALES O EN RIESGO DE PERDERLOS EN CENTRO DE ACOGIDA RESIDENCIAL - VARONES DISTRITO DE MORALES DE LA PROVINCIA DE SAN MARTÍN DEL DEPARTAMENTO DE SAN MARTÍN, con CUI N.° 2705619
A4: UBICACIÓN | C4: =+RESUMEN!B6 -> SAN MARTIN - SAN MARTIN - MORALES
A5: FECHA | C5: =+RESUMEN!B7 -> 46266
A7: Criterio: se encofran las dos caras interiores de los muros, las dos caras exteriores en toda la altura del cajon (losa de fondo + muro + losa superior) y el fondo de la losa superior (ancho interior b). La losa de fondo se vacia sobre el solado y la cara superior de la losa queda libre (acabado).
A9: N° | B9: TRAMO | C9: ZONA | D9: LONGITUD (m) | E9: ALTURA INTERIOR h (m) | F9: e LOSA SUP. (m) | G9: ANCHO INT. b (m) | H9: CARAS INTERIORES DE MUROS 2 x h x L (m2) | I9: CARAS EXTERIORES 2 x (e fondo + h + e losa) x L (m2) | J9: FONDO DE LOSA SUPERIOR b x L (m2) | K9: TOTAL ENCOFRADO (m2) | L9: SUSTENTO
A10: 1 | B10: cruce de camiones | C10: CAMION | D10: ='COLECTOR MOV. TIERRAS'!F10 -> 6.08 | E10: ='COLECTOR MOV. TIERRAS'!G10 -> 0.709 | F10: ='COLECTOR MOV. TIERRAS'!H10 -> 0.25 | G10: ='COLECTOR PARAMETROS'!$C$10 -> 0.6 | H10: =2*E10*D10 -> 8.62144 | I10: =2*('COLECTOR PARAMETROS'!$C$12+E10+F10)*D10 -> 13.48544 | J10: =G10*D10 -> 3.648 | K10: =SUM(H10:J10) -> 25.75488 | L10: DPLV-21 y DPLV-22 (secciones)
A11: 2 | B11: tramo normal | C11: NORMAL | D11: ='COLECTOR MOV. TIERRAS'!F11 -> 94.82 | E11: ='COLECTOR MOV. TIERRAS'!G11 -> 1.01 | F11: ='COLECTOR MOV. TIERRAS'!H11 -> 0.1 | G11: ='COLECTOR PARAMETROS'!$C$10 -> 0.6 | H11: =2*E11*D11 -> 191.5364 | I11: =2*('COLECTOR PARAMETROS'!$C$12+E11+F11)*D11 -> 238.9464 | J11: =G11*D11 -> 56.892 | K11: =SUM(H11:J11) -> 487.3748 | L11: DPLV-21 y DPLV-22 (secciones)
A12: 3 | B12: tramo de empalme con la CL (horizontal) | C12: NORMAL | D12: ='COLECTOR MOV. TIERRAS'!F12 -> 4.39 | E12: ='COLECTOR MOV. TIERRAS'!G12 -> 1.159 | F12: ='COLECTOR MOV. TIERRAS'!H12 -> 0.1 | G12: ='COLECTOR PARAMETROS'!$C$10 -> 0.6 | H12: =2*E12*D12 -> 10.17602 | I12: =2*('COLECTOR PARAMETROS'!$C$12+E12+F12)*D12 -> 12.37102 | J12: =G12*D12 -> 2.634 | K12: =SUM(H12:J12) -> 25.18104 | L12: DPLV-21 y DPLV-22 (secciones)
A13: TOTAL COLECTOR | D13: =SUM(D10:D12) -> 105.29 | H13: =SUM(H10:H12) -> 210.33386 | I13: =SUM(I10:I12) -> 264.80286 | J13: =SUM(J10:J12) -> 63.174 | K13: =SUM(K10:K12) -> 538.31072
A15: RESUMEN PARA LA PLANILLA GENERAL (partida 01.04.04.04.04)
A16: 1 | B16: ENCOFRADO Y DESENCOFRADO NORMAL EN COLECTOR | F16: m2 | G16: =K13 -> 538.31072

Sheet COLECTOR ACERO
A1: COLECTOR PLUVIAL FRONTAL - METRADO DE ACERO DE REFUERZO fy=4200 kg/cm2
A2: ENTIDAD | C2: =+RESUMEN!B4 -> GERENCIA TERRITORIAL BAJO MAYO - TARAPOTO
A3: PROYECTO | C3: =+RESUMEN!B5 -> CREACIÓN DEL SERVICIO DE PROTECCIÓN INTEGRAL A NIÑAS, NIÑOS Y ADOLESCENTES SIN CUIDADOS PARENTALES O EN RIESGO DE PERDERLOS EN CENTRO DE ACOGIDA RESIDENCIAL - VARONES DISTRITO DE MORALES DE LA PROVINCIA DE SAN MARTÍN DEL DEPARTAMENTO DE SAN MARTÍN, con CUI N.° 2705619
A4: UBICACIÓN | C4: =+RESUMEN!B6 -> SAN MARTIN - SAN MARTIN - MORALES
A5: FECHA | C5: =+RESUMEN!B7 -> 46266
A7: Criterio (laminas DPLV-21 y DPLV-22, norma E.060 14.3.4): el tramo normal lleva un solo marco cerrado en el eje de muros y losas (perimetro = 2 x (ancho ext. - e) + 2 x (e fondo/2 + h + e losa/2) + ganchos); el cruce de camiones cisterna lleva marco exterior + marco interior de 1/2" (perimetros con recubrimiento 0.04). Barras longitudinales 3/8" en cada marco, con traslape de 0.40 cada 9.00 m. Peso: 3/8" = 0.56 kg/m, 1/2" = 0.994 kg/m.
A9: N° | B9: TRAMO | C9: ZONA | D9: LONGITUD (m) | E9: ALTURA INTERIOR h (m) | F9: e LOSA SUP. (m) | G9: ANCHO EXT. (m) | H9: ESPAC. MARCOS s (m) | I9: CAPAS (1 = marco unico; 2 = ext. + int.) | J9: DIAM. MARCOS | K9: N° DE JUEGOS (L / s, redondeado arriba) | L9: PERIMETRO MARCO 1 (m) | M9: PERIMETRO MARCO 2 (m) | N9: LONGITUD DE MARCOS (m) | O9: PESO (kg/m) | P9: ACERO EN MARCOS (kg) | Q9: ESPAC. LONGIT. (m) | R9: N° BARRAS LONGIT. (perimetro / espac.) | S9: LONGITUD LONGIT. CON TRASLAPE (m) | T9: ACERO LONGIT. 3/8" (kg) | U9: TOTAL (kg) | V9: SUSTENTO
A10: 1 | B10: cruce de camiones | C10: CAMION | D10: ='COLECTOR MOV. TIERRAS'!F10 -> 6.08 | E10: ='COLECTOR MOV. TIERRAS'!G10 -> 0.709 | F10: ='COLECTOR MOV. TIERRAS'!H10 -> 0.25 | G10: ='COLECTOR MOV. TIERRAS'!I10 -> 0.9 | H10: ='COLECTOR PARAMETROS'!$C$27 -> 0.15 | I10: 2 | J10: 1/2" | K10: =ROUNDUP(D10/H10,0) -> 41 | L10: =IF(I10=2,2*(G10-2*'COLECTOR PARAMETROS'!$C$19)+2*('COLECTOR PARAMETROS'!$C$12+E10+F10-2*'COLECTOR PARAMETROS'!$C$19)+'COLECTOR PARAMETROS'!$C$24,2*(G10-'COLECTOR PARAMETROS'!$C$11)+2*('COLECTOR PARAMETROS'!$C$12/2+E10+F10/2)+'COLECTOR PARAMETROS'!$C$24) -> 3.998 | M10: =IF(I10=2,2*('COLECTOR PARAMETROS'!$C$10+2*('COLECTOR PARAMETROS'!$C$11-'COLECTOR PARAMETROS'!$C$19))+2*(E10+2*('COLECTOR PARAMETROS'!$C$11-'COLECTOR PARAMETROS'!$C$19))+'COLECTOR PARAMETROS'!$C$24,0) -> 3.798 | N10: =K10*(L10+M10) -> 319.636 | O10: =IF(J10="1/2""",'COLECTOR PARAMETROS'!$C$21,'COLECTOR PARAMETROS'!$C$20) -> 0.994 | P10: =N10*O10 -> 317.71818 | Q10: ='COLECTOR PARAMETROS'!$C$29 -> 0.2 | R10: =ROUND(L10/Q10,0)+IF(M10>0,ROUND(M10/Q10,0),0) -> 39 | S10: =R10*D10*(1+'COLECTOR PARAMETROS'!$C$22/'COLECTOR PARAMETROS'!$C$23) -> 247.65867 | T10: =S10*'COLECTOR PARAMETROS'!$C$20 -> 138.68885 | U10: =P10+T10 -> 456.40704 | V10: DPLV-21 (seccion S-01)
A11: 2 | B11: tramo normal | C11: NORMAL | D11: ='COLECTOR MOV. TIERRAS'!F11 -> 94.82 | E11: ='COLECTOR MOV. TIERRAS'!G11 -> 1.01 | F11: ='COLECTOR MOV. TIERRAS'!H11 -> 0.1 | G11: ='COLECTOR MOV. TIERRAS'!I11 -> 0.9 | H11: ='COLECTOR PARAMETROS'!$C$26 -> 0.2 | I11: 1 | J11: 3/8" | K11: =ROUNDUP(D11/H11,0) -> 475 | L11: =IF(I11=2,2*(G11-2*'COLECTOR PARAMETROS'!$C$19)+2*('COLECTOR PARAMETROS'!$C$12+E11+F11-2*'COLECTOR PARAMETROS'!$C$19)+'COLECTOR PARAMETROS'!$C$24,2*(G11-'COLECTOR PARAMETROS'!$C$11)+2*('COLECTOR PARAMETROS'!$C$12/2+E11+F11/2)+'COLECTOR PARAMETROS'!$C$24) -> 4.07 | M11: =IF(I11=2,2*('COLECTOR PARAMETROS'!$C$10+2*('COLECTOR PARAMETROS'!$C$11-'COLECTOR PARAMETROS'!$C$19))+2*(E11+2*('COLECTOR PARAMETROS'!$C$11-'COLECTOR PARAMETROS'!$C$19))+'COLECTOR PARAMETROS'!$C$24,0) -> 0 | N11: =K11*(L11+M11) -> 1933.25 | O11: =IF(J11="1/2""",'COLECTOR PARAMETROS'!$C$21,'COLECTOR PARAMETROS'!$C$20) -> 0.56 | P11: =N11*O11 -> 1082.62 | Q11: ='COLECTOR PARAMETROS'!$C$28 -> 0.25 | R11: =ROUND(L11/Q11,0)+IF(M11>0,ROUND(M11/Q11,0),0) -> 16 | S11: =R11*D11*(1+'COLECTOR PARAMETROS'!$C$22/'COLECTOR PARAMETROS'!$C$23) -> 1584.5476 | T11: =S11*'COLECTOR PARAMETROS'!$C$20 -> 887.34663 | U11: =P11+T11 -> 1969.9666 | V11: DPLV-21 y DPLV-22 (seccion S-02 a S-08)
A12: 3 | B12: tramo de empalme con la CL (horizontal) | C12: NORMAL | D12: ='COLECTOR MOV. TIERRAS'!F12 -> 4.39 | E12: ='COLECTOR MOV. TIERRAS'!G12 -> 1.159 | F12: ='COLECTOR MOV. TIERRAS'!H12 -> 0.1 | G12: ='COLECTOR MOV. TIERRAS'!I12 -> 0.9 | H12: ='COLECTOR PARAMETROS'!$C$26 -> 0.2 | I12: 1 | J12: 3/8" | K12: =ROUNDUP(D12/H12,0) -> 22 | L12: =IF(I12=2,2*(G12-2*'COLECTOR PARAMETROS'!$C$19)+2*('COLECTOR PARAMETROS'!$C$12+E12+F12-2*'COLECTOR PARAMETROS'!$C$19)+'COLECTOR PARAMETROS'!$C$24,2*(G12-'COLECTOR PARAMETROS'!$C$11)+2*('COLECTOR PARAMETROS'!$C$12/2+E12+F12/2)+'COLECTOR PARAMETROS'!$C$24) -> 4.368 | M12: =IF(I12=2,2*('COLECTOR PARAMETROS'!$C$10+2*('COLECTOR PARAMETROS'!$C$11-'COLECTOR PARAMETROS'!$C$19))+2*(E12+2*('COLECTOR PARAMETROS'!$C$11-'COLECTOR PARAMETROS'!$C$19))+'COLECTOR PARAMETROS'!$C$24,0) -> 0 | N12: =K12*(L12+M12) -> 96.096 | O12: =IF(J12="1/2""",'COLECTOR PARAMETROS'!$C$21,'COLECTOR PARAMETROS'!$C$20) -> 0.56 | P12: =N12*O12 -> 53.81376 | Q12: ='COLECTOR PARAMETROS'!$C$28 -> 0.25 | R12: =ROUND(L12/Q12,0)+IF(M12>0,ROUND(M12/Q12,0),0) -> 17 | S12: =R12*D12*(1+'COLECTOR PARAMETROS'!$C$22/'COLECTOR PARAMETROS'!$C$23) -> 77.946889 | T12: =S12*'COLECTOR PARAMETROS'!$C$20 -> 43.650258 | U12: =P12+T12 -> 97.464018 | V12: DPLV-21 y DPLV-22 (seccion S-02 a S-08)
A13: TOTAL COLECTOR | D13: =SUM(D10:D12) -> 105.29 | N13: =SUM(N10:N12) -> 2348.982 | P13: =SUM(P10:P12) -> 1454.1519 | S13: =SUM(S10:S12) -> 1910.1531 | T13: =SUM(T10:T12) -> 1069.6857 | U13: =SUM(U10:U12) -> 2523.8377
A15: REGISTROS DE LIMPIEZA Y TAPAS - laminas DPLV-23, DPLV-27 y DPLV-28: refuerzo de borde de la abertura, parrilla de la tapa, asas de la tapa ciega (cantidad de registros de la hoja COLECTOR REGISTROS Y TAPAS)
A16: N° | B16: ELEMENTO | C16: DIAM. | D16: FORMA | E16: PIEZAS POR REGISTRO | F16: REGISTROS | G16: LONG. POR PIEZA (m) | H16: LONG. TOTAL (m) | I16: PESO (kg/m) | U16: ACERO (kg) | V16: SUSTENTO
A17: 1 | B17: Refuerzo de borde de la abertura | C17: 1/2" | D17: recta | E17: 8 | F17: ='COLECTOR PARAMETROS'!$C$30 -> 11 | G17: 1.4 | H17: =E17*F17*G17 -> 123.2 | I17: ='COLECTOR PARAMETROS'!$C$21 -> 0.994 | U17: =H17*I17 -> 122.4608 | V17: DPLV-23, DPLV-27: 2 barras de 1/2" por lado, L = 1.40
A18: 2 | B18: Parrilla de la tapa de concreto | C18: 3/8" | D18: recta | E18: 14 | F18: ='COLECTOR PARAMETROS'!$C$30 -> 11 | G18: 0.62 | H18: =E18*F18*G18 -> 95.48 | I18: ='COLECTOR PARAMETROS'!$C$20 -> 0.56 | U18: =H18*I18 -> 53.4688 | V18: DPLV-23: 7 + 7 barras de 3/8" @0.10, L = 0.62
A19: 3 | B19: Asas de izaje de la tapa (en cajuelas) | C19: 1/2" liso | D19: U | E19: ='COLECTOR PARAMETROS'!$C$36 -> 2 | F19: ='COLECTOR PARAMETROS'!$C$30 -> 11 | G19: ='COLECTOR PARAMETROS'!$C$37 -> 0.5 | H19: =E19*F19*G19 -> 11 | I19: ='COLECTOR PARAMETROS'!$C$21 -> 0.994 | U19: =H19*I19 -> 10.934 | V19: DPLV-23: 2 asas de fierro liso 1/2" por tapa, desarrollo 0.50
A21: TOTAL REGISTROS Y TAPAS | U21: =SUM(U17:U20) -> 186.8636
A23: RESUMEN PARA LA PLANILLA GENERAL (partidas 01.04.04.04.05 y 01.04.04.05.06)
A24: 1 | B24: ACERO DE REFUERZO EN COLECTOR | F24: kg | G24: =SUMIF(J10:J12,"3/8""",P10:P12)+T13 -> 2206.1195 | H24: =SUMIF(J10:J12,"1/2""",P10:P12) -> 317.71818 | I24: =U13 -> 2523.8377
A25: 2 | B25: ACERO DE REFUERZO EN TAPAS, BORDES Y ASAS | F25: kg | G25: =SUMIF(C17:C20,"3/8*",U17:U20) -> 53.4688 | H25: =SUMIF(C17:C20,"1/2*",U17:U20) -> 133.3948 | I25: =U21 -> 186.8636

Sheet COLECTOR REGISTROS Y TAPAS
A1: COLECTOR PLUVIAL FRONTAL - REGISTROS DE LIMPIEZA Y TAPAS
A2: ENTIDAD | C2: =+RESUMEN!B4 -> GERENCIA TERRITORIAL BAJO MAYO - TARAPOTO
A3: PROYECTO | C3: =+RESUMEN!B5 -> CREACIÓN DEL SERVICIO DE PROTECCIÓN INTEGRAL A NIÑAS, NIÑOS Y ADOLESCENTES SIN CUIDADOS PARENTALES O EN RIESGO DE PERDERLOS EN CENTRO DE ACOGIDA RESIDENCIAL - VARONES DISTRITO DE MORALES DE LA PROVINCIA DE SAN MARTÍN DEL DEPARTAMENTO DE SAN MARTÍN, con CUI N.° 2705619
A4: UBICACIÓN | C4: =+RESUMEN!B6 -> SAN MARTIN - SAN MARTIN - MORALES
A5: FECHA | C5: =+RESUMEN!B7 -> 46266
A7: Lamina DPLV-17 (ubicacion) y DPLV-23 (detalle): tapa ciega de concreto armado 0.68 x 0.68 x 0.08, vaciada aparte en obra, con 2 asas de fierro liso 1/2", apoyada en un rebaje de concreto de 0.70 x 0.70 x 0.08 de la losa (luz libre 0.60 x 0.60). Sin marco ni contramarco metalico.
A9: N° | B9: REGISTRO | C9: PROGRESIVA | D9: UBICACION | E9: TAPA 0.68 x 0.68 (und) | F9: SUSTENTO
A10: 1 | B10: RV-01 | C10: 0+007.01 | D10: Registro en la losa del colector; empalme cuneta Eje 09 | E10: 1 | F10: DPLV-17, DPLV-23
A11: 2 | B11: RV-02 | C11: 0+013.52 | D11: Registro en la losa del colector; limpieza | E11: 1 | F11: DPLV-17, DPLV-23
A12: 3 | B12: RV-03 | C12: 0+020.02 | D12: Registro en la losa del colector; empalme cuneta Eje 08 | E12: 1 | F12: DPLV-17, DPLV-23
A13: 4 | B13: RV-04 | C13: 0+028.72 | D13: Registro en la losa del colector; limpieza | E13: 1 | F13: DPLV-17, DPLV-23
A14: 5 | B14: RV-05 | C14: 0+037.41 | D14: Registro en la losa del colector; limpieza | E14: 1 | F14: DPLV-17, DPLV-23
A15: 6 | B15: RV-06 | C15: 0+046.11 | D15: Registro en la losa del colector; empalme cuneta Eje 06 | E15: 1 | F15: DPLV-17, DPLV-23
A16: 7 | B16: RV-07 | C16: 0+056.47 | D16: Registro en la losa del colector; limpieza | E16: 1 | F16: DPLV-17, DPLV-23
A17: 8 | B17: RV-08 | C17: 0+066.84 | D17: Registro en la losa del colector; limpieza | E17: 1 | F17: DPLV-17, DPLV-23
A18: 9 | B18: RV-09 | C18: 0+077.20 | D18: Registro en la losa del colector; empalme cuneta Eje 04 | E18: 1 | F18: DPLV-17, DPLV-23
A19: 10 | B19: RV-10 | C19: 0+089.05 | D19: Registro en la losa del colector; limpieza | E19: 1 | F19: DPLV-17, DPLV-23
A20: 11 | B20: RV-11 | C20: 0+100.90 | D20: Registro en la losa del colector; quiebre; inicio del tramo de empalme con la CL | E20: 1 | F20: DPLV-17, DPLV-23
A21: TOTAL DE REGISTROS CON TAPA | E21: =SUM(E10:E20) -> 11
A23: METRADO DE LAS PARTIDAS DE REGISTROS (cantidad = total de registros; dimensiones de la hoja COLECTOR PARAMETROS)
A24: N° | B24: PARTIDA | C24: UND | D24: CALCULO | E24: TOTAL | F24: SUSTENTO
A25: 1 | B25: TAPA DE REGISTRO CIEGA DE CONCRETO ARMADO 0.68x0.68x0.08 (vaciada aparte en obra) | C25: und | D25: 1 por registro | E25: =E21 -> 11 | F25: DPLV-23
A26: 2 | B26: ENCOFRADO LATERAL DE LA TAPA (molde de madera) | C26: m2 | D26: registros x 4 x 0.68 x 0.08 | E26: =E21*'COLECTOR PARAMETROS'!$C$35*'COLECTOR PARAMETROS'!$C$32 -> 2.3936 | F26: DPLV-23
A27: 3 | B27: ACERO EN TAPAS: PARRILLA 3/8" Y ASAS 1/2" LISO | C27: kg | D27: hoja COLECTOR ACERO | E27: ='COLECTOR ACERO'!U18+'COLECTOR ACERO'!U19 -> 64.4028 | F27: DPLV-23; COLECTOR ACERO
A28: 4 | B28: CONCRETO f'c=210 EN TAPAS | C28: m3 | D28: registros x 0.68 x 0.68 x 0.08 | E28: =E21*'COLECTOR PARAMETROS'!$C$31*'COLECTOR PARAMETROS'!$C$31*'COLECTOR PARAMETROS'!$C$32 -> 0.406912 | F28: DPLV-23
A29: 5 | B29: ASIENTO DE LA TAPA: REBAJE DE CONCRETO 0.70 x 0.70 x 0.08 EN LA LOSA | C29: und | D29: 1 por registro (concreto incluido en la losa) | E29: =E21 -> 11 | F29: DPLV-23; COLECTOR CONCRETO
A30: 6 | B30: COLOCACION DE LA TAPA EN EL REBAJE (izaje con las asas) | C30: und | D30: 1 por registro | E30: =E21 -> 11 | F30: DPLV-23

Sheet COLECTOR JUNTAS Y EMPALMES
A1: COLECTOR PLUVIAL FRONTAL - JUNTAS Y EMPALMES DE CUNETAS
A2: ENTIDAD | C2: =+RESUMEN!B4 -> GERENCIA TERRITORIAL BAJO MAYO - TARAPOTO
A3: PROYECTO | C3: =+RESUMEN!B5 -> CREACIÓN DEL SERVICIO DE PROTECCIÓN INTEGRAL A NIÑAS, NIÑOS Y ADOLESCENTES SIN CUIDADOS PARENTALES O EN RIESGO DE PERDERLOS EN CENTRO DE ACOGIDA RESIDENCIAL - VARONES DISTRITO DE MORALES DE LA PROVINCIA DE SAN MARTÍN DEL DEPARTAMENTO DE SAN MARTÍN, con CUI N.° 2705619
A4: UBICACIÓN | C4: =+RESUMEN!B6 -> SAN MARTIN - SAN MARTIN - MORALES
A5: FECHA | C5: =+RESUMEN!B7 -> 46266
A7: Laminas DPLV-17, DPLV-18, DPLV-24, DPLV-25 y DPLV-29. Junta de dilatacion de 1" cada 4.00 m en todo el perimetro de la seccion (tecnopor de 1" en todo el perimetro + sellador asfaltico RC-250 con arena de 1" x 2" en la cara expuesta, EG-2013 MTC). A ambos lados del colector hay terreno natural (sin piso): no lleva junta longitudinal; la losa superior sirve de vereda. Junta de tecnopor de 1" con sellador asfaltico en el contacto con la caja CL. Empalme de cada cuneta por ventana en el muro lado predio con caida libre al fondo (sin dintel adicional).
A9: N° | B9: ELEMENTO | C9: PROGRESIVA / DETALLE | D9: VECES | E9: LONGITUD (m) | F9: PARCIAL (m) | G9: SUSTENTO
A10: JUNTA DE DILATACION e=1" CON TECNOPOR Y SELLADOR ASFALTICO EN COLECTOR (perimetro = 2 x ancho exterior + 2 x (e fondo + h max + e losa))
A11: 1 | B11: Juntas de dilatacion cada 4.00 m entre 0+004.00 y 0+104.00 | C11: ="n = ENTERO("&TEXT('COLECTOR PARAMETROS'!$C$46,"0.00")&" / 4.00)" -> n = ENTERO(105.29 / 4.00) | D11: =INT('COLECTOR PARAMETROS'!$C$46/'COLECTOR PARAMETROS'!$C$44) -> 26 | E11: =2*('COLECTOR PARAMETROS'!$C$10+2*'COLECTOR PARAMETROS'!$C$11)+2*('COLECTOR PARAMETROS'!$C$12+'COLECTOR PARAMETROS'!$C$45+'COLECTOR PARAMETROS'!$C$13) -> 4.64 | F11: =D11*E11 -> 120.64 | G11: DPLV-17; DPLV-18 (juntas en el perfil); DPLV-29; perimetro de la seccion
A12: TOTAL JUNTA DE DILATACION (m) | F12: =SUM(F11:F11) -> 120.64
A14: JUNTA e=1" CON TECNOPOR Y SELLADOR ASFALTICO ENTRE COLECTOR Y CAJA CL (a ambos lados del colector hay terreno natural: no lleva junta longitudinal)
A15: 1 | B15: Bordes de la losa: terreno natural a ambos lados (sin piso): no lleva junta | C15: - | D15: 0 | E15: ='COLECTOR PARAMETROS'!$C$46 -> 105.29 | F15: =D15*E15 -> 0 | G15: DPLV-21, DPLV-22 y DPLV-29
A16: 2 | B16: Contacto del colector con el muro este de la caja CL (perimetro de la seccion) | C16: 0+105.29 | D16: 1 | E16: =2*('COLECTOR PARAMETROS'!$C$10+2*'COLECTOR PARAMETROS'!$C$11)+2*('COLECTOR PARAMETROS'!$C$12+'COLECTOR PARAMETROS'!$C$45+'COLECTOR PARAMETROS'!$C$13) -> 4.64 | F16: =D16*E16 -> 4.64 | G16: DPLV-25 y DPLV-29: tecnopor y sellador en todo el contacto colector - CL
A17: TOTAL JUNTA CON LA CAJA CL (m) | F17: =SUM(F15:F16) -> 4.64
A19: EMPALME DE CUNETA AL COLECTOR (ventana 0.40 x H en el muro lado predio, caida libre y registro encima) - laminas DPLV-24 y DPLV-30
A20: 1 | B20: Cuneta Eje 09 (registro RV-01) | C20: 0+007.01 | D20: 1 | F20: =D20 -> 1 | G20: DPLV-24 (cuadro de empalmes); DPLV-17
A21: 2 | B21: Cuneta Eje 08 (registro RV-03) | C21: 0+020.02 | D21: 1 | F21: =D21 -> 1 | G21: DPLV-24 (cuadro de empalmes); DPLV-17
A22: 3 | B22: Cuneta Eje 06 (registro RV-06) | C22: 0+046.11 | D22: 1 | F22: =D22 -> 1 | G22: DPLV-24 (cuadro de empalmes); DPLV-17
A23: 4 | B23: Cuneta Eje 04 (registro RV-09) | C23: 0+077.20 | D23: 1 | F23: =D23 -> 1 | G23: DPLV-24 (cuadro de empalmes); DPLV-17
A24: TOTAL EMPALMES (und) | F24: =SUM(F20:F23) -> 4
A26: Nota: la cuneta del Eje 01 no entra al colector: cae directamente a la caja CL por una ventana en su muro norte (DPLV-25); esa ventana y la del muro este (llegada del colector) se dejan en la caja CL del expediente del Hogar de Refugio. Las cunetas se acortan hasta el muro (hoja CUNETAS - LLEGADA AL COLECTOR).

Sheet COLECTOR INSUMOS
A1: COLECTOR PLUVIAL FRONTAL - DESGLOSE DE INSUMOS POR PARTIDA
A2: ENTIDAD | C2: =+RESUMEN!B4 -> GERENCIA TERRITORIAL BAJO MAYO - TARAPOTO
A3: PROYECTO | C3: =+RESUMEN!B5 -> CREACIÓN DEL SERVICIO DE PROTECCIÓN INTEGRAL A NIÑAS, NIÑOS Y ADOLESCENTES SIN CUIDADOS PARENTALES O EN RIESGO DE PERDERLOS EN CENTRO DE ACOGIDA RESIDENCIAL - VARONES DISTRITO DE MORALES DE LA PROVINCIA DE SAN MARTÍN DEL DEPARTAMENTO DE SAN MARTÍN, con CUI N.° 2705619
A4: UBICACIÓN | C4: =+RESUMEN!B6 -> SAN MARTIN - SAN MARTIN - MORALES
A5: FECHA | C5: =+RESUMEN!B7 -> 46266
A7: Rendimientos unitarios referenciales (celdas amarillas, editar segun el analisis de costos unitarios adoptado). El metrado se toma de la PLANILLA GENERAL DE METRADOS.
A9: N° | B9: PARTIDA | C9: UND | D9: METRADO | E9: INSUMO | F9: UND INSUMO | G9: CANTIDAD POR UND DE PARTIDA | H9: CANTIDAD TOTAL
A10: 1 | B10: 01.04.04.04.01 CONCRETO f'c=210 PARA COLECTOR - losa de fondo | C10: m3 | D10: =SUM('PLANILLA GENERAL DE METRADOS'!J177:J179) -> 14.21415 | E10: Cemento Portland tipo I | F10: bol | G10: 9.73 | H10: =G10*$D$10 -> 138.30368
E11: Arena gruesa | F11: m3 | G11: 0.52 | H11: =G11*$D$10 -> 7.391358
E12: Piedra chancada 1/2" | F12: m3 | G12: 0.53 | H12: =G12*$D$10 -> 7.5334995
E13: Agua | F13: m3 | G13: 0.186 | H13: =G13*$D$10 -> 2.6438319
E14: Mezcladora 9-11 p3 | F14: hm | G14: 0.8 | H14: =G14*$D$10 -> 11.37132
E15: Vibrador de concreto | F15: hm | G15: 0.8 | H15: =G15*$D$10 -> 11.37132
E16: Operario | F16: hh | G16: 0.8 | H16: =G16*$D$10 -> 11.37132
E17: Oficial | F17: hh | G17: 0.8 | H17: =G17*$D$10 -> 11.37132
E18: Peon | F18: hh | G18: 6.4 | H18: =G18*$D$10 -> 90.97056
A19: 2 | B19: 01.04.04.04.01 CONCRETO f'c=210 PARA COLECTOR - muros | C19: m3 | D19: =SUM('PLANILLA GENERAL DE METRADOS'!J181:J183) -> 31.550079 | E19: Cemento Portland tipo I | F19: bol | G19: 9.73 | H19: =G19*$D$19 -> 306.98227
E20: Arena gruesa | F20: m3 | G20: 0.52 | H20: =G20*$D$19 -> 16.406041
E21: Piedra chancada 1/2" | F21: m3 | G21: 0.53 | H21: =G21*$D$19 -> 16.721542
E22: Agua | F22: m3 | G22: 0.186 | H22: =G22*$D$19 -> 5.8683147
E23: Mezcladora 9-11 p3 | F23: hm | G23: 1 | H23: =G23*$D$19 -> 31.550079
E24: Vibrador de concreto | F24: hm | G24: 1 | H24: =G24*$D$19 -> 31.550079
E25: Operario | F25: hh | G25: 1 | H25: =G25*$D$19 -> 31.550079
E26: Oficial | F26: hh | G26: 1 | H26: =G26*$D$19 -> 31.550079
E27: Peon | F27: hh | G27: 8 | H27: =G27*$D$19 -> 252.40063
A28: 3 | B28: 01.04.04.04.01 CONCRETO f'c=210 PARA COLECTOR - losa superior | C28: m3 | D28: =SUM('PLANILLA GENERAL DE METRADOS'!J185:J189) -> 9.9845 | E28: Cemento Portland tipo I | F28: bol | G28: 9.73 | H28: =G28*$D$28 -> 97.149185
E29: Arena gruesa | F29: m3 | G29: 0.52 | H29: =G29*$D$28 -> 5.19194
E30: Piedra chancada 1/2" | F30: m3 | G30: 0.53 | H30: =G30*$D$28 -> 5.291785
E31: Agua | F31: m3 | G31: 0.186 | H31: =G31*$D$28 -> 1.857117
E32: Mezcladora 9-11 p3 | F32: hm | G32: 0.8 | H32: =G32*$D$28 -> 7.9876
E33: Vibrador de concreto | F33: hm | G33: 0.8 | H33: =G33*$D$28 -> 7.9876
E34: Operario | F34: hh | G34: 0.8 | H34: =G34*$D$28 -> 7.9876
E35: Oficial | F35: hh | G35: 0.8 | H35: =G35*$D$28 -> 7.9876
E36: Peon | F36: hh | G36: 6.4 | H36: =G36*$D$28 -> 63.9008
A37: 4 | B37: 01.04.04.04.02 ENCOFRADO Y DESENCOFRADO DE COLECTOR | C37: m2 | D37: ='PLANILLA GENERAL DE METRADOS'!K190 -> 538.31072 | E37: Madera tornillo | F37: p2 | G37: 4.24 | H37: =G37*$D$37 -> 2282.4375
E38: Clavos 3" | F38: kg | G38: 0.2 | H38: =G38*$D$37 -> 107.66214
E39: Alambre negro N 8 | F39: kg | G39: 0.2 | H39: =G39*$D$37 -> 107.66214
E40: Operario | F40: hh | G40: 0.8 | H40: =G40*$D$37 -> 430.64858
E41: Oficial | F41: hh | G41: 0.8 | H41: =G41*$D$37 -> 430.64858
A42: 5 | B42: 01.04.04.04.03 ACERO f'y=4200 PARA COLECTOR | C42: kg | D42: ='PLANILLA GENERAL DE METRADOS'!K194 -> 2523.8377 | E42: Acero corrugado fy=4200 (incluye 5 % desperdicio) | F42: kg | G42: 1.05 | H42: =G42*$D$42 -> 2650.0296
E43: Alambre negro N 16 | F43: kg | G43: 0.06 | H43: =G43*$D$42 -> 151.43026
E44: Operario | F44: hh | G44: 0.032 | H44: =G44*$D$42 -> 80.762806
E45: Oficial | F45: hh | G45: 0.032 | H45: =G45*$D$42 -> 80.762806
A46: 6 | B46: 01.04.04.03.01 SOLADO f'c=100 e=0.05 | C46: m2 | D46: ='PLANILLA GENERAL DE METRADOS'!K171 -> 105.29 | E46: Cemento Portland tipo I | F46: bol | G46: 0.3 | H46: =G46*$D$46 -> 31.587
E47: Hormigon | F47: m3 | G47: 0.064 | H47: =G47*$D$46 -> 6.73856
E48: Agua | F48: m3 | G48: 0.01 | H48: =G48*$D$46 -> 1.0529
E49: Operario | F49: hh | G49: 0.1 | H49: =G49*$D$46 -> 10.529
E50: Peon | F50: hh | G50: 0.4 | H50: =G50*$D$46 -> 42.116
A51: 7 | B51: 01.04.04.02.01 EXCAVACION MANUAL DE ZANJAS | C51: m3 | D51: ='PLANILLA GENERAL DE METRADOS'!K152 -> 130.62232 | E51: Peon | F51: hh | G51: 2.67 | H51: =G51*$D$51 -> 348.76161
E52: Herramientas manuales | F52: %mo | G52: 0.03 | H52: =G52*$D$51 -> 3.9186697
A53: 8 | B53: 01.04.04.02.03 RELLENO COMPACTADO CON MATERIAL PROPIO | C53: m3 | D53: ='PLANILLA GENERAL DE METRADOS'!K160 -> 91.51313 | E53: Agua | F53: m3 | G53: 0.05 | H53: =G53*$D$53 -> 4.5756565
E54: Compactador vibratorio tipo plancha | F54: hm | G54: 0.4 | H54: =G54*$D$53 -> 36.605252
E55: Operario | F55: hh | G55: 0.4 | H55: =G55*$D$53 -> 36.605252
E56: Peon | F56: hh | G56: 1.6 | H56: =G56*$D$53 -> 146.42101
A57: 9 | B57: 01.04.04.02.04 ELIMINACION DE MATERIAL EXCEDENTE | C57: m3 | D57: ='PLANILLA GENERAL DE METRADOS'!K167 -> 46.931033 | E57: Volquete 6 m3 | F57: hm | G57: 0.133 | H57: =G57*$D$57 -> 6.2418274
E58: Cargador frontal | F58: hm | G58: 0.033 | H58: =G58*$D$57 -> 1.5487241
E59: Peon | F59: hh | G59: 0.133 | H59: =G59*$D$57 -> 6.2418274
A60: 10 | B60: 01.04.04.05.01 TAPA DE REGISTRO: encofrado lateral de la tapa (molde de madera, 6 usos) | C60: m2 | D60: ='COLECTOR REGISTROS Y TAPAS'!E26 -> 2.3936 | E60: Madera tornillo | F60: p2 | G60: 0.7067 | H60: =G60*$D$60 -> 1.6915571
E61: Clavos 3" | F61: kg | G61: 0.0333 | H61: =G61*$D$60 -> 0.07970688
E62: Operario | F62: hh | G62: 0.8 | H62: =G62*$D$60 -> 1.91488
E63: Oficial | F63: hh | G63: 0.8 | H63: =G63*$D$60 -> 1.91488
A64: 11 | B64: 01.04.04.05.01 TAPA DE REGISTRO: colocacion de la tapa en el rebaje y curado | C64: und | D64: ='COLECTOR REGISTROS Y TAPAS'!E30 -> 11 | E64: Operario | F64: hh | G64: 1 | H64: =G64*$D$64 -> 11
E65: Peon | F65: hh | G65: 1 | H65: =G65*$D$64 -> 11
E66: Agua | F66: m3 | G66: 0.01 | H66: =G66*$D$64 -> 0.11
A69: 12 | B69: 01.04.04.06.01 JUNTA DE DILATACION e=1" CON TECNOPOR Y SELLADOR ASFALTICO | C69: m | D69: ='PLANILLA GENERAL DE METRADOS'!K215 -> 120.64 | E69: Tecnopor 1" | F69: m2 | G69: ='ACU JUNTA DILATACION'!$D$14*(1+'ACU JUNTA DILATACION'!$D$15) -> 0.13655172 | H69: =G69*$D$69 -> 16.4736
E70: Sellador asfaltico: asfalto liquido RC-250 + arena gruesa (sello de 1" x 2") | F70: m3 | G70: ='ACU JUNTA DILATACION'!$D$20 -> 0.001067851 | H70: =G70*$D$69 -> 0.12882555
E71: Operario | F71: hh | G71: 0.2 | H71: =G71*$D$69 -> 24.128
E72: Peon | F72: hh | G72: 0.2 | H72: =G72*$D$69 -> 24.128
A73: 13 | B73: 01.04.04.06.02 JUNTA e=1" CON TECNOPOR Y SELLADOR ASFALTICO ENTRE COLECTOR Y CAJA CL | C73: m | D73: ='PLANILLA GENERAL DE METRADOS'!K216 -> 4.64 | E73: Tecnopor 1" | F73: m2 | G73: ='ACU JUNTA CAJA CL'!$D$14*(1+'ACU JUNTA CAJA CL'!$D$15) -> 0.13655172 | H73: =G73*$D$73 -> 0.6336
E74: Sellador asfaltico: asfalto liquido RC-250 + arena gruesa (sello de 1" x 2") | F74: m3 | G74: ='ACU JUNTA CAJA CL'!$D$20 -> 0.001067851 | H74: =G74*$D$73 -> 0.0049548288
E75: Operario | F75: hh | G75: 0.2 | H75: =G75*$D$73 -> 0.928
E76: Peon | F76: hh | G76: 0.2 | H76: =G76*$D$73 -> 0.928

Sheet COSTO HORA HOMBRE 2026
A1: COSTO DE LA HORA-HOMBRE 2026 - REGIMEN DE CONSTRUCCION CIVIL (TABLA OFICIAL CAPECO - FTCCP)
A2: ENTIDAD | C2: =+RESUMEN!B4 -> GERENCIA TERRITORIAL BAJO MAYO - TARAPOTO
A3: PROYECTO | C3: =+RESUMEN!B5 -> CREACIÓN DEL SERVICIO DE PROTECCIÓN INTEGRAL A NIÑAS, NIÑOS Y ADOLESCENTES SIN CUIDADOS PARENTALES O EN RIESGO DE PERDERLOS EN CENTRO DE ACOGIDA RESIDENCIAL - VARONES DISTRITO DE MORALES DE LA PROVINCIA DE SAN MARTÍN DEL DEPARTAMENTO DE SAN MARTÍN, con CUI N.° 2705619
A4: UBICACIÓN | C4: =+RESUMEN!B6 -> SAN MARTIN - SAN MARTIN - MORALES
A5: FECHA | C5: =+RESUMEN!B7 -> 46266
A7: Costo de la hora-hombre en edificacion del 01.01.2026 al 31.12.2026, segun la tabla oficial elaborada entre CAPECO y la FTCCP (Remuneracion y condiciones de trabajo en construccion civil 2026, Acta final de negociacion colectiva, Exp. N° 339-2025-MTPE/2.14-NC). El resumen de la parte 1 es el que usan todas las ACU de la planilla. Celda amarilla = dato de la tabla oficial; verde = formula.
A9: 1. COSTO HORA-HOMBRE 2026 POR CATEGORIA (lo usan todas las ACU)
A10: N° | B10: CATEGORIA | C10: JORNAL BASICO (S/ dia) | D10: TOTAL POR DIA DE 8 h (S/) | G10: COSTO HH 2026 (S/ hh) | H10: FUENTE
A11: 1 | B11: Operario | C11: =D17 -> 89.3 | D11: =D25 -> 231.62 | G11: =D26 -> 28.95 | H11: Tabla oficial CAPECO - FTCCP 2026 (Exp. N° 339-2025-MTPE/2.14-NC)
A12: 2 | B12: Oficial | C12: =E17 -> 69.75 | D12: =E25 -> 181.46 | G12: =E26 -> 22.68 | H12: Tabla oficial CAPECO - FTCCP 2026 (Exp. N° 339-2025-MTPE/2.14-NC)
A13: 3 | B13: Peon | C13: =F17 -> 62.8 | D13: =F25 -> 164.34 | G13: =F26 -> 20.54 | H13: Tabla oficial CAPECO - FTCCP 2026 (Exp. N° 339-2025-MTPE/2.14-NC)
A15: 2. COSTO HORA-HOMBRE EN EDIFICACION DEL 01.01.2026 AL 31.12.2026
A16: N° | B16: CONCEPTO | C16: BASE | D16: OPERARIO | E16: OFICIAL | F16: PEON | H16: SUSTENTO
A17: 1 | B17: Remuneracion basica del 01/01/2026 al 31/12/2026 | C17: jornal | D17: 89.3 | E17: 69.75 | F17: 62.8 | H17: R.M. 197-2025-TR; tabla oficial CAPECO - FTCCP 2026
A18: 2 | B18: Beneficios y leyes sociales sobre el jornal basico (%) | C18: =$D$50 -> 112.2 | D18: =ROUND(D17*$C$18/100,2) -> 100.19 | E18: =ROUND(E17*$C$18/100,2) -> 78.26 | F18: =ROUND(F17*$C$18/100,2) -> 70.46 | H18: parte 3: 112.20 % sobre el jornal basico
A19: 3 | B19: Bonificacion unificada de construccion (BUC) | C19: 32/30/30 % | D19: =ROUND(D17*0.32,2) -> 28.58 | E19: =ROUND(E17*0.3,2) -> 20.93 | F19: =ROUND(F17*0.3,2) -> 18.84 | H19: 32 % operario; 30 % oficial y peon
A20: 4 | B20: Beneficios y leyes sociales sobre el BUC (%) | C20: =$E$50 -> 12.25 | D20: =ROUND(D19*$C$20/100,2) -> 3.5 | E20: =ROUND(E19*$C$20/100,2) -> 2.56 | F20: =ROUND(F19*$C$20/100,2) -> 2.31 | H20: parte 3: 12.25 % sobre el BUC
A21: 5 | B21: Seguro de vida ESSALUD + Vida (S/ 5.00 por mes) | C21: dia | D21: 0.16 | E21: 0.16 | F21: 0.16 | H21: tabla oficial
A22: 6 | B22: Fondo de capacitacion (Exp. N° 339-2025-MTPE/2.14-NC) | C22: dia | D22: 0.4 | E22: 0.31 | F22: 0.28 | H22: tabla oficial
A23: 7 | B23: Bonificacion por movilidad (R.M. N° 139-2024-TR) | C23: dia | D23: 8.6 | E23: 8.6 | F23: 8.6 | H23: S/ 8.60 por dia laborado en todo el pais
A24: 8 | B24: Overol (R.D. N° 777-87-DR-LIM): (2 x S/ 132.80) / 300 | C24: dia | D24: =ROUND(2*132.8/300,2) -> 0.89 | E24: =ROUND(2*132.8/300,2) -> 0.89 | F24: =ROUND(2*132.8/300,2) -> 0.89 | H24: tabla oficial
B25: Total por dia de 8 horas (S/) | D25: =SUM(D17:D24) -> 231.62 | E25: =SUM(E17:E24) -> 181.46 | F25: =SUM(F17:F24) -> 164.34
B26: Costo de la hora-hombre (S/ hh) | D26: =ROUND(D25/8,2) -> 28.95 | E26: =ROUND(E25/8,2) -> 22.68 | F26: =ROUND(F25/8,2) -> 20.54 | H26: total por dia / 8 horas
A28: 3. PORCENTAJES DE BENEFICIOS Y LEYES SOCIALES EN EDIFICACION (tabla oficial CAPECO - FTCCP 2026)
A29: N° | B29: CONCEPTO | D29: SOBRE JORNAL BASICO (%) | E29: SOBRE BUC (%) | H29: SUSTENTO
A30: 1 | B30: 1.01 Indemnizacion por tiempo de servicios | D30: 12 | H30: tabla oficial
A31: 2 | B31: 1.01 Indemnizacion por participacion de utilidades | D31: 3 | H31: tabla oficial
A32: 3 | B32: 1.02 SCTR: prestaciones asistenciales (Ley 26790) | D32: 1.3 | E32: 1.3 | H32: tabla oficial
A33: 4 | B33: 1.02 SCTR: prestaciones economicas | D33: 1.05 | E33: 1.05 | H33: tabla oficial
A34: 5 | B34: 1.04 Regimen de prestaciones de salud (ESSALUD) | D34: 9 | E34: 9 | H34: tabla oficial
A35: 6 | B35: 1.05 Seguro de vida ley | D35: 0.9 | E35: 0.9 | H35: tabla oficial
A36: 7 | B36: 2.01 Salario dominical | D36: 17.58 | H36: tabla oficial
A37: 8 | B37: 2.02 Vacaciones record (30 dias) | D37: 10 | H37: tabla oficial
A38: 9 | B38: 2.03 Gratificacion por Fiestas Patrias y Navidad | D38: 22.22 | H38: tabla oficial
A39: 10 | B39: 2.04 Jornales por dias feriados no laborables | D39: 4.33 | H39: tabla oficial
A40: 11 | B40: 2.05 Asignacion escolar (promedio 3 hijos) | D40: 25 | H40: tabla oficial
A41: 12 | B41: 3.01 ESSALUD sobre salario dominical (9 % de 17.58 %) | D41: 1.58 | H41: tabla oficial
A42: 13 | B42: 3.02 ESSALUD sobre vacaciones (9 % de 10.00 %) | D42: 0.9 | H42: tabla oficial
A43: 14 | B43: 3.03 ESSALUD sobre feriados (9 % de 4.33 %) | D43: 0.39 | H43: tabla oficial
A44: 15 | B44: 4.01 SCTR sobre salario dominical (2.35 % de 17.58 %) | D44: 0.41 | H44: tabla oficial
A45: 16 | B45: 4.02 SCTR sobre vacaciones (2.35 % de 10.00 %) | D45: 0.24 | H45: tabla oficial
A46: 17 | B46: 4.03 SCTR sobre feriados (2.35 % de 4.33 %) | D46: 0.1 | H46: tabla oficial
A47: 18 | B47: 5.01 Seguro de vida ley sobre salario dominical (0.90 % de 17.58 %) | D47: 0.16 | H47: tabla oficial
... A49: 20 | B49: 6.01 Bonificacion extraordinaria Ley 30334 (9 % de 22.22 %) | D49: 2 | H49: tabla oficial
B50: PORCENTAJE TOTAL DE LEYES Y BENEFICIOS SOCIALES | D50: =SUM(D30:D49) -> 112.2 | E50: =SUM(E30:E49) -> 12.25 | H50: 112.20 % y 12.25 %

Sheet ACU TAPA REGISTRO
A1: ANALISIS DE COSTO UNITARIO - TAPA DE REGISTRO CIEGA DE CONCRETO ARMADO 0.68x0.68x0.08
A2: ENTIDAD | C2: =+RESUMEN!B4 -> GERENCIA TERRITORIAL BAJO MAYO - TARAPOTO
A3: PROYECTO | C3: =+RESUMEN!B5 -> CREACIÓN DEL SERVICIO DE PROTECCIÓN INTEGRAL A NIÑAS, NIÑOS Y ADOLESCENTES SIN CUIDADOS PARENTALES O EN RIESGO DE PERDERLOS EN CENTRO DE ACOGIDA RESIDENCIAL - VARONES DISTRITO DE MORALES DE LA PROVINCIA DE SAN MARTÍN DEL DEPARTAMENTO DE SAN MARTÍN, con CUI N.° 2705619
A4: UBICACIÓN | C4: =+RESUMEN!B6 -> SAN MARTIN - SAN MARTIN - MORALES
A5: FECHA | C5: =+RESUMEN!B7 -> 46266
A7: Partida de Delphin 01.04.04.06.05.01 TAPA DE REGISTRO CIEGA DE CONCRETO ARMADO 0.68x0.68x0.08 (metrado 01.04.04.05.01, hojas COLECTOR REGISTROS Y TAPAS y COLECTOR ACERO). Tapa ciega de concreto armado vaciada aparte en obra sobre tablero, con parrilla 3/8" @0.10, 2 asas de fierro liso 1/2" en cajuelas y cantos biselados; se coloca en el rebaje de concreto de 0.70 x 0.70 x 0.08 de la losa (el rebaje y el borde engrosado se metran con el concreto del colector). Incluye el refuerzo de borde de la abertura (2 barras de 1/2" por lado). Sin marco ni contramarco metalico. Celda amarilla = dato; verde = formula. Precios sin IGV.
A9: 1. CANTIDADES POR TAPA (hojas COLECTOR PARAMETROS, COLECTOR REGISTROS Y TAPAS y COLECTOR ACERO)
A10: N° | B10: CONCEPTO | C10: UND | D10: VALOR | H10: SUSTENTO
A11: 1 | B11: Numero de tapas (registros) | C11: und | D11: ='COLECTOR REGISTROS Y TAPAS'!E21 -> 11 | H11: COLECTOR REGISTROS Y TAPAS
A12: 2 | B12: Concreto f'c=210 por tapa: 0.68 x 0.68 x 0.08 | C12: m3 | D12: ='COLECTOR PARAMETROS'!$C$31^2*'COLECTOR PARAMETROS'!$C$32 -> 0.036992 | H12: DPLV-23
A13: 3 | B13: Encofrado lateral por tapa: 4 x 0.68 x 0.08 (molde de madera) | C13: m2 | D13: ='COLECTOR PARAMETROS'!$C$35*'COLECTOR PARAMETROS'!$C$32 -> 0.2176 | H13: DPLV-23
A14: 4 | B14: Tablero de vaciado: 0.80 x 0.80 x 1" = 6.89 p2 en 6 usos | C14: p2 | D14: 1.15 | H14: criterio de obra
A15: 5 | B15: Acero 3/8" de la parrilla por tapa (7 + 7 barras, L = 0.62) | C15: kg | D15: ='COLECTOR ACERO'!U18/'COLECTOR ACERO'!F18 -> 4.8608 | H15: COLECTOR ACERO
A16: 6 | B16: Acero 1/2" de borde de la abertura por registro (8 barras, L = 1.40) | C16: kg | D16: ='COLECTOR ACERO'!U17/'COLECTOR ACERO'!F17 -> 11.1328 | H16: COLECTOR ACERO
A17: 7 | B17: Fierro liso 1/2" de las 2 asas por tapa (desarrollo 0.50 c/u) | C17: kg | D17: ='COLECTOR ACERO'!U19/'COLECTOR ACERO'!F19 -> 0.994 | H17: COLECTOR ACERO
A18: 8 | B18: Desperdicio de acero | C18: - | D18: 0.05 | H18: criterio
A19: 9 | B19: Cemento por m3 de concreto f'c=210 | C19: bol/m3 | D19: ='COLECTOR INSUMOS'!G10 -> 9.73 | H19: COLECTOR INSUMOS (diseno de mezcla)
A20: 10 | B20: Arena gruesa por m3 | C20: m3/m3 | D20: ='COLECTOR INSUMOS'!G11 -> 0.52 | H20: COLECTOR INSUMOS
A21: 11 | B21: Piedra chancada 1/2" por m3 | C21: m3/m3 | D21: ='COLECTOR INSUMOS'!G12 -> 0.53 | H21: COLECTOR INSUMOS
A22: 12 | B22: Agua por m3 (mezcla) + curado de la tapa (0.01 m3) | C22: m3/m3 | D22: ='COLECTOR INSUMOS'!G13 -> 0.186 | H22: COLECTOR INSUMOS
A23: 13 | B23: Mano de obra del concreto: operario / oficial / peon por m3 | C23: hh/m3 | D23: ='COLECTOR INSUMOS'!G16 -> 0.8 | H23: COLECTOR INSUMOS (0.8 / 0.8 / 6.4)
A24: 14 | B24: Peon por m3 de concreto | C24: hh/m3 | D24: ='COLECTOR INSUMOS'!G18 -> 6.4 | H24: COLECTOR INSUMOS
A25: 15 | B25: Mano de obra del acero: operario / oficial por kg | C25: hh/kg | D25: ='COLECTOR INSUMOS'!G44 -> 0.032 | H25: COLECTOR INSUMOS
A26: 16 | B26: Mano de obra del encofrado: operario / oficial por m2 | C26: hh/m2 | D26: 0.8 | H26: COLECTOR INSUMOS (encofrado)
A27: 17 | B27: Colocacion de la tapa en el rebaje: operario + peon | C27: hh/und | D27: 1 | H27: criterio de obra: 1 hh por tapa
A29: 2. ANALISIS DE COSTO UNITARIO (formato Delphin)
A30: Partida | C30: 01.04.04.06.05.01 TAPA DE REGISTRO CIEGA DE CONCRETO ARMADO 0.68x0.68x0.08
A31: Partida del metrado | C31: 01.04.04.05.01 (hoja COLECTOR REGISTROS Y TAPAS)
A32: Unidad | C32: und
A33: Metrado | C33: ='COLECTOR REGISTROS Y TAPAS'!E25 -> 11
A34: Rendimiento (und/dia, cuadrilla de 1 operario) | C34: =8/E37 -> 4.5785533
A35: N° | B35: RECURSO | C35: UND | D35: CUADRILLA | E35: CANTIDAD POR TAPA | F35: PRECIO S/ | G35: PARCIAL S/ | H35: FUENTE DEL PRECIO
B36: MANO DE OBRA
A37: 1 | B37: Operario | C37: hh | D37: =E37*$C$34/8 -> 1 | E37: =$D$12*$D$23+($D$15+$D$16+$D$17)*$D$25+$D$13*$D$26+$D$27 -> 1.7472768 | F37: ='COSTO HORA HOMBRE 2026'!$G$11 -> 28.95 | G37: =E37*F37 -> 50.583663 | H37: hoja COSTO HORA HOMBRE 2026 (tabla oficial CAPECO - FTCCP 2026)
A38: 2 | B38: Oficial | C38: hh | D38: =E38*$C$34/8 -> 0.42768083 | E38: =$D$12*$D$23+($D$15+$D$16+$D$17)*$D$25+$D$13*$D$26 -> 0.7472768 | F38: ='COSTO HORA HOMBRE 2026'!$G$12 -> 22.68 | G38: =E38*F38 -> 16.948238 | H38: hoja COSTO HORA HOMBRE 2026 (tabla oficial CAPECO - FTCCP 2026)
A39: 3 | B39: Peon | C39: hh | D39: =E39*$C$34/8 -> 0.70781504 | E39: =$D$12*$D$24+$D$27 -> 1.2367488 | F39: ='COSTO HORA HOMBRE 2026'!$G$13 -> 20.54 | G39: =E39*F39 -> 25.40282 | H39: hoja COSTO HORA HOMBRE 2026 (tabla oficial CAPECO - FTCCP 2026)
B40: Subtotal mano de obra | G40: =SUM(G37:G39) -> 92.934722
B41: MATERIALES
A42: 4 | B42: Cemento Portland tipo I | C42: bol | E42: =$D$12*$D$19 -> 0.35993216 | F42: 30.93 | G42: =E42*F42 -> 11.132702 | H42: Cemento Pacasmayo tipo I 42.5 kg: S/ 36.50 con IGV
A43: 5 | B43: Arena gruesa | C43: m3 | E43: =$D$12*$D$20 -> 0.01923584 | F43: 40.68 | G43: =E43*F43 -> 0.78251397 | H43: Agregados Tarapoto (Morales): S/ 48.00 el m3
A44: 6 | B44: Piedra chancada 1/2" | C44: m3 | E44: =$D$12*$D$21 -> 0.01960576 | F44: 101.69 | G44: =E44*F44 -> 1.9937097 | H44: Por cotizar en Tarapoto: no hay precio publicado de la piedra de 1/2"
A45: 7 | B45: Agua | C45: m3 | E45: =$D$12*$D$22+0.01 -> 0.016880512 | F45: 8.33 | G45: =E45*F45 -> 0.14061466 | H45: EMAPA San Martin: tarifa comercial de 30 m3 a mas, agua 6.80 + alcantarillado 1.53
A46: 8 | B46: Madera tornillo | C46: p2 | E46: =$D$13*4.24/6+$D$14 -> 1.3037707 | F46: 4.41 | G46: =E46*F46 -> 5.7496286 | H46: Maderas del Norte: S/ 5.20 el p2 con IGV
A47: 9 | B47: Acero corrugado fy=4200 | C47: kg | E47: =($D$15+$D$16)*(1+$D$18) -> 16.79328 | F47: 3.44 | G47: =E47*F47 -> 57.768883 | H47: Sodimac Peru, Aceros Arequipa: 1/2" x 9 m S/ 36.50 y 3/8" x 9 m S/ 20.35 con IGV (ponderado)
A48: 10 | B48: Fierro liso 1/2" (asas) | C48: kg | E48: =$D$17*(1+$D$18) -> 1.0437 | F48: 3.44 | G48: =E48*F48 -> 3.590328 | H48: mismo precio por kg del acero corrugado (referencial): Sodimac Peru, Aceros Arequipa: 1/2" x 9 m S/ 36.50 y 3/8" x 9 m S/ 20.35 con IGV (ponderado)
A49: 11 | B49: Alambre negro N 16 | C49: kg | E49: =($D$15+$D$16+$D$17)*0.06 -> 1.019256 | F49: 5.08 | G49: =E49*F49 -> 5.1778205 | H49: Sodimac Peru: rollo de 10 kg S/ 59.90 con IGV
B50: Subtotal materiales | G50: =SUM(G42:G49) -> 86.3362
B51: EQUIPOS
A52: 12 | B52: Herramientas manuales | C52: %mo | E52: 0.03 | F52: =+G40 -> 92.934722 | G52: =E52*F52 -> 2.7880416 | H52: 3 % del costo de mano de obra (incluye mezcla y vibrado manual del concreto de la tapa)
B53: Subtotal equipos | G53: =SUM(G52:G52) -> 2.7880416
A54: COSTO UNITARIO DIRECTO (S/ por und) | G54: =+G40+G50+G53 -> 182.05896
A55: COSTO DIRECTO DE LA PARTIDA (metrado x costo unitario, S/) | G55: =G54*C33 -> 2002.6486

Sheet ACU CANALETAS
A1: ANALISIS DE COSTOS UNITARIOS - CANALETAS DE TECHO DE PLANCHA GALVANIZADA
A2: ENTIDAD | C2: =+RESUMEN!B4 -> GERENCIA TERRITORIAL BAJO MAYO - TARAPOTO
A3: PROYECTO | C3: =+RESUMEN!B5 -> CREACIÓN DEL SERVICIO DE PROTECCIÓN INTEGRAL A NIÑAS, NIÑOS Y ADOLESCENTES SIN CUIDADOS PARENTALES O EN RIESGO DE PERDERLOS EN CENTRO DE ACOGIDA RESIDENCIAL - VARONES DISTRITO DE MORALES DE LA PROVINCIA DE SAN MARTÍN DEL DEPARTAMENTO DE SAN MARTÍN, con CUI N.° 2705619
A4: UBICACIÓN | C4: =+RESUMEN!B6 -> SAN MARTIN - SAN MARTIN - MORALES
A5: FECHA | C5: =+RESUMEN!B7 -> 46266
A7: Analisis de las partidas 01.04.03.05.01.03 a 01.04.03.05.01.06 (red de recoleccion de techo). Las cantidades de insumos salen de los parametros de la hoja METRADO CANALETAS (seccion 0.25 x 0.20, pestana 0.05, plancha e=0.9 mm, soportes @0.60). Celda amarilla = dato (cuadrilla, rendimiento, aporte o precio); verde = formula. Precios sin IGV, referenciales: al pasar a Delphin rigen los de la base de precios del presupuesto.
A9: DATOS DE CALCULO (de la hoja METRADO CANALETAS y de catalogo)
A10: N° | B10: DATO | C10: UND | D10: VALOR | H10: SUSTENTO
A11: 1 | B11: Fondo interior de la canaleta | C11: m | D11: =+'METRADO CANALETAS'!F48 -> 0.25 | H11: METRADO CANALETAS F48
A12: 2 | B12: Altura interior de la canaleta | C12: m | D12: =+'METRADO CANALETAS'!F49 -> 0.2 | H12: METRADO CANALETAS F49
A13: 3 | B13: Pestana superior (cada lado) | C13: m | D13: =+'METRADO CANALETAS'!F50 -> 0.05 | H13: METRADO CANALETAS F50
A14: 4 | B14: Desarrollo de plancha por metro de canaleta | C14: m2/m | D14: =+'METRADO CANALETAS'!F51 -> 0.75 | H14: fondo + 2 alturas + 2 pestanas
A15: 5 | B15: Espesor de plancha galvanizada | C15: mm | D15: =+'METRADO CANALETAS'!F52 -> 0.9 | H15: METRADO CANALETAS F52
A16: 6 | B16: Separacion de soportes | C16: m | D16: =+'METRADO CANALETAS'!F53 -> 0.6 | H16: METRADO CANALETAS F53
A17: 7 | B17: Peso de la plancha galvanizada | C17: kg/m2 | D17: =D15*7.85+0.3 -> 7.365 | H17: espesor x 7.85 kg/m2 por mm + zinc (0.3 kg/m2)
A18: 8 | B18: Largo de la plancha comercial (1.22 x 2.44) | C18: m | D18: 2.44 | H18: catalogo; la canaleta se fabrica en tramos de 2.44 m
A19: 9 | B19: Traslape entre tramos | C19: m | D19: 0.05 | H19: criterio de obra (remachado y sellado)
A20: 10 | B20: Desarrollo de la platina de un soporte | C20: m | D20: =D11+2*D12+2*0.1 -> 0.85 | H20: abraza la canaleta (fondo + 2 lados) + 2 orejas de fijacion de 0.10
A21: 11 | B21: Peso de la platina 1" x 1/8" | C21: kg/m | D21: 0.633 | H21: 25.4 x 3.18 mm x 7.85 = 0.633 kg/m
A22: 12 | B22: Largo de la platina comercial | C22: m | D22: 6 | H22: catalogo
A25: ACU 1: 01.04.03.05.01.03 CANALETA DE PLANCHA DE ACERO GALVANIZADO e=0.9mm, SECCION 0.25m x 0.20m
A26: Unidad | C26: m
A27: Metrado | C27: =+'PLANILLA GENERAL DE METRADOS'!K125 -> 523.16
A28: Rendimiento (m/dia) | C28: 25 | E28: fabricacion (corte y doblado en obra), remachado, sellado y colocacion sobre los soportes; cuadrilla 1 op + 1 peon
A29: N° | B29: RECURSO | C29: UND | D29: CUADRILLA | E29: CANTIDAD | F29: PRECIO S/ | G29: PARCIAL S/ | H29: SUSTENTO / FUENTE
B30: MANO DE OBRA
A31: 1 | B31: Operario (hojalatero) | C31: hh | D31: 1 | E31: =D31*8/$C$28 -> 0.32 | F31: ='COSTO HORA HOMBRE 2026'!$G$11 -> 28.95 | G31: =E31*F31 -> 9.264 | H31: hoja COSTO HORA HOMBRE 2026 (tabla oficial CAPECO - FTCCP 2026)
A32: 2 | B32: Peon | C32: hh | D32: 1 | E32: =D32*8/$C$28 -> 0.32 | F32: ='COSTO HORA HOMBRE 2026'!$G$13 -> 20.54 | G32: =E32*F32 -> 6.5728 | H32: hoja COSTO HORA HOMBRE 2026 (tabla oficial CAPECO - FTCCP 2026)
B33: Subtotal mano de obra | G33: =SUM(G31:G32) -> 15.8368
B34: MATERIALES
A35: 3 | B35: Plancha de acero galvanizado e=0.9 mm | C35: m2 | E35: =$D$14*(1+$D$19/$D$18)*1.05 -> 0.8036373 | F35: 26.95 | G35: =E35*F35 -> 21.658025 | H35: desarrollo x (1 + traslape/2.44) x 1.05 desperdicio; Mercado Tarapoto 2026, sin IGV (referencial)
A36: 4 | B36: Remache pop 1/8" | C36: und | E36: =2*($D$11+2*$D$12)/0.05/$D$18 -> 10.655738 | F36: 0.1 | G36: =E36*F36 -> 1.0655738 | H36: 2 filas a @0.05 en cada traslape (cada 2.44 m)
A37: 5 | B37: Sellador de poliuretano (cartucho 300 ml) | C37: und | E37: =($D$11+2*$D$12)/$D$18/8 -> 0.03329918 | F37: 21.19 | G37: =E37*F37 -> 0.70560963 | H37: 1 cartucho = 8 m de cordon de 6 mm; una junta (0.65 m) cada 2.44 m
B38: Subtotal materiales | G38: =SUM(G35:G37) -> 23.429209
B39: EQUIPOS
A40: 6 | B40: Herramientas manuales | C40: %mo | E40: 0.05 | F40: =+G33 -> 15.8368 | G40: =E40*F40 -> 0.79184 | H40: 5 % del costo de mano de obra (hojalateria)
B41: Subtotal equipos | G41: =SUM(G40:G40) -> 0.79184
A42: COSTO UNITARIO DIRECTO (S/ por m) | G42: =+G33+G38+G41 -> 40.057849
A43: COSTO DIRECTO DE LA PARTIDA (metrado x costo unitario) | G43: =G42*C27 -> 20956.664
A45: ACU 2: 01.04.03.05.01.04 SOPORTE DE PLATINA F°G° 1" x 1/8" P/CANALETA
A46: Unidad | C46: und
A47: Metrado | C47: =+'PLANILLA GENERAL DE METRADOS'!K126 -> 906
A48: Rendimiento (und/dia) | C48: 40 | E48: corte, doblado en U con orejas, perforado y fijacion al alero o viga; cuadrilla 1 op + 0.5 peon
A49: N° | B49: RECURSO | C49: UND | D49: CUADRILLA | E49: CANTIDAD | F49: PRECIO S/ | G49: PARCIAL S/ | H49: SUSTENTO / FUENTE
B50: MANO DE OBRA
A51: 1 | B51: Operario | C51: hh | D51: 1 | E51: =D51*8/$C$48 -> 0.2 | F51: ='COSTO HORA HOMBRE 2026'!$G$11 -> 28.95 | G51: =E51*F51 -> 5.79 | H51: hoja COSTO HORA HOMBRE 2026 (tabla oficial CAPECO - FTCCP 2026)
A52: 2 | B52: Peon | C52: hh | D52: 0.5 | E52: =D52*8/$C$48 -> 0.1 | F52: ='COSTO HORA HOMBRE 2026'!$G$13 -> 20.54 | G52: =E52*F52 -> 2.054 | H52: hoja COSTO HORA HOMBRE 2026 (tabla oficial CAPECO - FTCCP 2026)
B53: Subtotal mano de obra | G53: =SUM(G51:G52) -> 7.844
B54: MATERIALES
A55: 3 | B55: Platina de fierro galvanizado 1" x 1/8" | C55: m | E55: =$D$20*1.05 -> 0.8925 | F55: 6.36 | G55: =E55*F55 -> 5.6763 | H55: desarrollo del soporte x 1.05 desperdicio; Mercado Tarapoto 2026, sin IGV (referencial)
A56: 4 | B56: Perno de expansion 1/4" x 2 1/2" con tarugo | C56: und | E56: 2 | F56: 1.02 | G56: =E56*F56 -> 2.04 | H56: 2 por soporte (una oreja a cada lado)
A57: 5 | B57: Tornillo autorroscante 1/4" x 3/4" (soporte a canaleta) | C57: und | E57: 2 | F57: 0.25 | G57: =E57*F57 -> 0.5 | H57: 2 por soporte
B58: Subtotal materiales | G58: =SUM(G55:G57) -> 8.2163
B59: EQUIPOS
A60: 6 | B60: Herramientas manuales | C60: %mo | E60: 0.05 | F60: =+G53 -> 7.844 | G60: =E60*F60 -> 0.3922 | H60: 5 % del costo de mano de obra (hojalateria)
B61: Subtotal equipos | G61: =SUM(G60:G60) -> 0.3922
A62: COSTO UNITARIO DIRECTO (S/ por und) | G62: =+G53+G58+G61 -> 16.4525
A63: COSTO DIRECTO DE LA PARTIDA (metrado x costo unitario) | G63: =G62*C47 -> 14905.965
A65: ACU 3: 01.04.03.05.01.05 TAPA LATERAL DE PLANCHA GALVANIZADA P/CANALETA
A66: Unidad | C66: und
A67: Metrado | C67: =+'PLANILLA GENERAL DE METRADOS'!K127 -> 44
A68: Rendimiento (und/dia) | C68: 30 | E68: trazo, corte, doblez de pestanas, remachado y sellado en el extremo de la canaleta; cuadrilla 1 op + 0.5 peon
A69: N° | B69: RECURSO | C69: UND | D69: CUADRILLA | E69: CANTIDAD | F69: PRECIO S/ | G69: PARCIAL S/ | H69: SUSTENTO / FUENTE
B70: MANO DE OBRA
A71: 1 | B71: Operario (hojalatero) | C71: hh | D71: 1 | E71: =D71*8/$C$68 -> 0.26666667 | F71: ='COSTO HORA HOMBRE 2026'!$G$11 -> 28.95 | G71: =E71*F71 -> 7.72 | H71: hoja COSTO HORA HOMBRE 2026 (tabla oficial CAPECO - FTCCP 2026)
A72: 2 | B72: Peon | C72: hh | D72: 0.5 | E72: =D72*8/$C$68 -> 0.13333333 | F72: ='COSTO HORA HOMBRE 2026'!$G$13 -> 20.54 | G72: =E72*F72 -> 2.7386667 | H72: hoja COSTO HORA HOMBRE 2026 (tabla oficial CAPECO - FTCCP 2026)
B73: Subtotal mano de obra | G73: =SUM(G71:G72) -> 10.458667
B74: MATERIALES
A75: 3 | B75: Plancha de acero galvanizado e=0.9 mm | C75: m2 | E75: =($D$11*$D$12+2*($D$11+$D$12)*0.03)*1.1 -> 0.0847 | F75: 26.95 | G75: =E75*F75 -> 2.282665 | H75: tapa 0.25 x 0.20 + pestana de 0.03 en el contorno, 10 % desperdicio
A76: 4 | B76: Remache pop 1/8" | C76: und | E76: 6 | F76: 0.1 | G76: =E76*F76 -> 0.6 | H76: 6 por tapa
A77: 5 | B77: Sellador de poliuretano (cartucho 300 ml) | C77: und | E77: =($D$11+2*$D$12)/8 -> 0.08125 | F77: 21.19 | G77: =E77*F77 -> 1.7216875 | H77: contorno de la tapa (0.65 m) / 8 m por cartucho
B78: Subtotal materiales | G78: =SUM(G75:G77) -> 4.6043525
B79: EQUIPOS
A80: 6 | B80: Herramientas manuales | C80: %mo | E80: 0.05 | F80: =+G73 -> 10.458667 | G80: =E80*F80 -> 0.52293333 | H80: 5 % del costo de mano de obra (hojalateria)
B81: Subtotal equipos | G81: =SUM(G80:G80) -> 0.52293333
A82: COSTO UNITARIO DIRECTO (S/ por und) | G82: =+G73+G78+G81 -> 15.585952
A83: COSTO DIRECTO DE LA PARTIDA (metrado x costo unitario) | G83: =G82*C67 -> 685.78191
A85: ACU 4: 01.04.03.05.01.06 BOQUILLA DE PLANCHA GALVANIZADA P/CONEXION DE CANALETA A MONTANTE Ø4"
A86: Unidad | C86: und
A87: Metrado | C87: =+'PLANILLA GENERAL DE METRADOS'!K128 -> 52
A88: Rendimiento (und/dia) | C88: 16 | E88: corte de la abertura en el fondo, fabricacion del tubo y la brida, remachado, sellado y embone al montante; cuadrilla 1 op + 0.5 peon
A89: N° | B89: RECURSO | C89: UND | D89: CUADRILLA | E89: CANTIDAD | F89: PRECIO S/ | G89: PARCIAL S/ | H89: SUSTENTO / FUENTE
B90: MANO DE OBRA
A91: 1 | B91: Operario (hojalatero) | C91: hh | D91: 1 | E91: =D91*8/$C$88 -> 0.5 | F91: ='COSTO HORA HOMBRE 2026'!$G$11 -> 28.95 | G91: =E91*F91 -> 14.475 | H91: hoja COSTO HORA HOMBRE 2026 (tabla oficial CAPECO - FTCCP 2026)
A92: 2 | B92: Peon | C92: hh | D92: 0.5 | E92: =D92*8/$C$88 -> 0.25 | F92: ='COSTO HORA HOMBRE 2026'!$G$13 -> 20.54 | G92: =E92*F92 -> 5.135 | H92: hoja COSTO HORA HOMBRE 2026 (tabla oficial CAPECO - FTCCP 2026)
B93: Subtotal mano de obra | G93: =SUM(G91:G92) -> 19.61
B94: MATERIALES
A95: 3 | B95: Plancha de acero galvanizado e=0.9 mm | C95: m2 | E95: =(PI()*0.1016*0.15+0.2*0.2)*1.15 -> 0.10105955 | F95: 26.95 | G95: =E95*F95 -> 2.7235549 | H95: tubo de 4" x 0.15 m (embone en el montante) + brida 0.20 x 0.20 en el fondo de la canaleta; 15 % desperdicio
A96: 4 | B96: Remache pop 1/8" | C96: und | E96: 8 | F96: 0.1 | G96: =E96*F96 -> 0.8 | H96: 8 por boquilla (brida al fondo de la canaleta)
A97: 5 | B97: Sellador de poliuretano (cartucho 300 ml) | C97: und | E97: =(4*0.2+PI()*0.1016)/8 -> 0.13989823 | F97: 21.19 | G97: =E97*F97 -> 2.9644434 | H97: contorno de la brida + embone (1.12 m) / 8 m por cartucho
B98: Subtotal materiales | G98: =SUM(G95:G97) -> 6.4879984
B99: EQUIPOS
A100: 6 | B100: Herramientas manuales | C100: %mo | E100: 0.05 | F100: =+G93 -> 19.61 | G100: =E100*F100 -> 0.9805 | H100: 5 % del costo de mano de obra (hojalateria)
B101: Subtotal equipos | G101: =SUM(G100:G100) -> 0.9805
A102: COSTO UNITARIO DIRECTO (S/ por und) | G102: =+G93+G98+G101 -> 27.078498
A103: COSTO DIRECTO DE LA PARTIDA (metrado x costo unitario) | G103: =G102*C87 -> 1408.0819
A105: RESUMEN DE COSTOS DIRECTOS (referencial)
B106: PARTIDA | C106: UND | D106: METRADO | E106: C.U. S/ | F106: PARCIAL S/
A107: 01.04.03.05.01.03 | B107: CANALETA DE PLANCHA DE ACERO GALVANIZADO e=0.9mm, SECCION 0.25m x 0.20m | C107: m | D107: =+C27 -> 523.16 | E107: =+G42 -> 40.057849 | F107: =+G43 -> 20956.664
A108: 01.04.03.05.01.04 | B108: SOPORTE DE PLATINA F°G° 1" x 1/8" P/CANALETA | C108: und | D108: =+C47 -> 906 | E108: =+G62 -> 16.4525 | F108: =+G63 -> 14905.965
...

Sheet DESAGREGADO TAPA REGISTRO
A1: DESAGREGADO DE LA PARTIDA 01.04.04.05.01 - TAPA DE REGISTRO CIEGA DE CONCRETO ARMADO 0.68x0.68x0.08
A2: ENTIDAD | C2: =+RESUMEN!B4 -> GERENCIA TERRITORIAL BAJO MAYO - TARAPOTO
A3: PROYECTO | C3: =+RESUMEN!B5 -> CREACIÓN DEL SERVICIO DE PROTECCIÓN INTEGRAL A NIÑAS, NIÑOS Y ADOLESCENTES SIN CUIDADOS PARENTALES O EN RIESGO DE PERDERLOS EN CENTRO DE ACOGIDA RESIDENCIAL - VARONES DISTRITO DE MORALES DE LA PROVINCIA DE SAN MARTÍN DEL DEPARTAMENTO DE SAN MARTÍN, con CUI N.° 2705619
A4: UBICACIÓN | C4: =+RESUMEN!B6 -> SAN MARTIN - SAN MARTIN - MORALES
A5: FECHA | C5: =+RESUMEN!B7 -> 46266
A7: La partida se mide por unidad de registro. Cada tapa ciega de concreto armado se vacia aparte en obra y se coloca en el rebaje de 0.70 x 0.70 x 0.08 de la losa (luz libre 0.60 x 0.60). Sin marco ni contramarco metalico. Componentes tomados de las hojas COLECTOR REGISTROS Y TAPAS y COLECTOR ACERO.
A9: A. UBICACION DE LOS REGISTROS
A10: N° | B10: REGISTRO | C10: PROGRESIVA | D10: UBICACION | F10: CANT. (und) | G10: SUSTENTO
A11: 1 | B11: =+'COLECTOR REGISTROS Y TAPAS'!B10 -> RV-01 | C11: =+'COLECTOR REGISTROS Y TAPAS'!C10 -> 0+007.01 | D11: =+'COLECTOR REGISTROS Y TAPAS'!D10 -> Registro en la losa del colector; empalme cuneta Eje 09 | F11: =+'COLECTOR REGISTROS Y TAPAS'!E10 -> 1 | G11: =+'COLECTOR REGISTROS Y TAPAS'!F10 -> DPLV-17, DPLV-23
A12: 2 | B12: =+'COLECTOR REGISTROS Y TAPAS'!B11 -> RV-02 | C12: =+'COLECTOR REGISTROS Y TAPAS'!C11 -> 0+013.52 | D12: =+'COLECTOR REGISTROS Y TAPAS'!D11 -> Registro en la losa del colector; limpieza | F12: =+'COLECTOR REGISTROS Y TAPAS'!E11 -> 1 | G12: =+'COLECTOR REGISTROS Y TAPAS'!F11 -> DPLV-17, DPLV-23
A13: 3 | B13: =+'COLECTOR REGISTROS Y TAPAS'!B12 -> RV-03 | C13: =+'COLECTOR REGISTROS Y TAPAS'!C12 -> 0+020.02 | D13: =+'COLECTOR REGISTROS Y TAPAS'!D12 -> Registro en la losa del colector; empalme cuneta Eje 08 | F13: =+'COLECTOR REGISTROS Y TAPAS'!E12 -> 1 | G13: =+'COLECTOR REGISTROS Y TAPAS'!F12 -> DPLV-17, DPLV-23
A14: 4 | B14: =+'COLECTOR REGISTROS Y TAPAS'!B13 -> RV-04 | C14: =+'COLECTOR REGISTROS Y TAPAS'!C13 -> 0+028.72 | D14: =+'COLECTOR REGISTROS Y TAPAS'!D13 -> Registro en la losa del colector; limpieza | F14: =+'COLECTOR REGISTROS Y TAPAS'!E13 -> 1 | G14: =+'COLECTOR REGISTROS Y TAPAS'!F13 -> DPLV-17, DPLV-23
A15: 5 | B15: =+'COLECTOR REGISTROS Y TAPAS'!B14 -> RV-05 | C15: =+'COLECTOR REGISTROS Y TAPAS'!C14 -> 0+037.41 | D15: =+'COLECTOR REGISTROS Y TAPAS'!D14 -> Registro en la losa del colector; limpieza | F15: =+'COLECTOR REGISTROS Y TAPAS'!E14 -> 1 | G15: =+'COLECTOR REGISTROS Y TAPAS'!F14 -> DPLV-17, DPLV-23
A16: 6 | B16: =+'COLECTOR REGISTROS Y TAPAS'!B15 -> RV-06 | C16: =+'COLECTOR REGISTROS Y TAPAS'!C15 -> 0+046.11 | D16: =+'COLECTOR REGISTROS Y TAPAS'!D15 -> Registro en la losa del colector; empalme cuneta Eje 06 | F16: =+'COLECTOR REGISTROS Y TAPAS'!E15 -> 1 | G16: =+'COLECTOR REGISTROS Y TAPAS'!F15 -> DPLV-17, DPLV-23
A17: 7 | B17: =+'COLECTOR REGISTROS Y TAPAS'!B16 -> RV-07 | C17: =+'COLECTOR REGISTROS Y TAPAS'!C16 -> 0+056.47 | D17: =+'COLECTOR REGISTROS Y TAPAS'!D16 -> Registro en la losa del colector; limpieza | F17: =+'COLECTOR REGISTROS Y TAPAS'!E16 -> 1 | G17: =+'COLECTOR REGISTROS Y TAPAS'!F16 -> DPLV-17, DPLV-23
A18: 8 | B18: =+'COLECTOR REGISTROS Y TAPAS'!B17 -> RV-08 | C18: =+'COLECTOR REGISTROS Y TAPAS'!C17 -> 0+066.84 | D18: =+'COLECTOR REGISTROS Y TAPAS'!D17 -> Registro en la losa del colector; limpieza | F18: =+'COLECTOR REGISTROS Y TAPAS'!E17 -> 1 | G18: =+'COLECTOR REGISTROS Y TAPAS'!F17 -> DPLV-17, DPLV-23
A19: 9 | B19: =+'COLECTOR REGISTROS Y TAPAS'!B18 -> RV-09 | C19: =+'COLECTOR REGISTROS Y TAPAS'!C18 -> 0+077.20 | D19: =+'COLECTOR REGISTROS Y TAPAS'!D18 -> Registro en la losa del colector; empalme cuneta Eje 04 | F19: =+'COLECTOR REGISTROS Y TAPAS'!E18 -> 1 | G19: =+'COLECTOR REGISTROS Y TAPAS'!F18 -> DPLV-17, DPLV-23
A20: 10 | B20: =+'COLECTOR REGISTROS Y TAPAS'!B19 -> RV-10 | C20: =+'COLECTOR REGISTROS Y TAPAS'!C19 -> 0+089.05 | D20: =+'COLECTOR REGISTROS Y TAPAS'!D19 -> Registro en la losa del colector; limpieza | F20: =+'COLECTOR REGISTROS Y TAPAS'!E19 -> 1 | G20: =+'COLECTOR REGISTROS Y TAPAS'!F19 -> DPLV-17, DPLV-23
A21: 11 | B21: =+'COLECTOR REGISTROS Y TAPAS'!B20 -> RV-11 | C21: =+'COLECTOR REGISTROS Y TAPAS'!C20 -> 0+100.90 | D21: =+'COLECTOR REGISTROS Y TAPAS'!D20 -> Registro en la losa del colector; quiebre; inicio del tramo de empalme con la CL | F21: =+'COLECTOR REGISTROS Y TAPAS'!E20 -> 1 | G21: =+'COLECTOR REGISTROS Y TAPAS'!F20 -> DPLV-17, DPLV-23
B22: TOTAL DE REGISTROS (und de la partida) | F22: =SUM(F11:F21) -> 11
A24: B. COMPONENTES DE UNA TAPA DE REGISTRO Y TOTAL DE LA PARTIDA
A25: N° | B25: COMPONENTE | C25: UND | D25: POR REGISTRO | E25: N° REGISTROS | F25: TOTAL | G25: SUSTENTO
B26: CONCRETO
A27: 1 | B27: Tapa ciega de concreto f'c=210: 0.68 x 0.68 x 0.08 | C27: m3 | D27: ='COLECTOR PARAMETROS'!$C$31^2*'COLECTOR PARAMETROS'!$C$32 -> 0.036992 | E27: =+$F$22 -> 11 | F27: =D27*E27 -> 0.406912 | G27: lamina DPLV-23
B28: Subtotal concreto | C28: m3 | D28: =SUM(D27:D27) -> 0.036992 | F28: =SUM(F27:F27) -> 0.406912
B29: ENCOFRADO
A30: 2 | B30: Encofrado lateral de la tapa: 4 x 0.68 x 0.08 (molde de madera) | C30: m2 | D30: ='COLECTOR PARAMETROS'!$C$35*'COLECTOR PARAMETROS'!$C$32 -> 0.2176 | E30: =+$F$22 -> 11 | F30: =D30*E30 -> 2.3936 | G30: lamina DPLV-23
B31: Subtotal encofrado | C31: m2 | D31: =SUM(D30:D30) -> 0.2176 | F31: =SUM(F30:F30) -> 2.3936
B32: ACERO DE REFUERZO
A33: 3 | B33: Parrilla de la tapa: 7 + 7 barras 3/8" @0.10, L = 0.62 | C33: kg | D33: ='COLECTOR ACERO'!U18/'COLECTOR ACERO'!F18 -> 4.8608 | E33: =+$F$22 -> 11 | F33: =D33*E33 -> 53.4688 | G33: COLECTOR ACERO fila 18
A34: 4 | B34: Asas de izaje: 2 barras de fierro liso 1/2", desarrollo 0.50 | C34: kg | D34: ='COLECTOR ACERO'!U19/'COLECTOR ACERO'!F19 -> 0.994 | E34: =+$F$22 -> 11 | F34: =D34*E34 -> 10.934 | G34: COLECTOR ACERO fila 19
A35: 5 | B35: Refuerzo de borde de la abertura: 8 barras 1/2", L = 1.40 | C35: kg | D35: ='COLECTOR ACERO'!U17/'COLECTOR ACERO'!F17 -> 11.1328 | E35: =+$F$22 -> 11 | F35: =D35*E35 -> 122.4608 | G35: COLECTOR ACERO fila 17
B36: Subtotal acero de refuerzo | C36: kg | D36: =SUM(D33:D35) -> 16.9876 | F36: =SUM(F33:F35) -> 186.8636
A38: C. CONTROL CON EL METRADO DE LOS COMPONENTES (hojas del colector)
B39: COMPONENTE | C39: UND | E39: ESTA HOJA | F39: HOJA DEL COLECTOR | G39: CONTROL
B40: Concreto en tapas | C40: m3 | E40: =+F28 -> 0.406912 | F40: ='COLECTOR REGISTROS Y TAPAS'!E28 -> 0.406912 | G40: =IF(ABS(E40-F40)<0.0005,"CONFORME","REVISAR") -> CONFORME
B41: Encofrado lateral de tapas | C41: m2 | E41: =+F31 -> 2.3936 | F41: ='COLECTOR REGISTROS Y TAPAS'!E26 -> 2.3936 | G41: =IF(ABS(E41-F41)<0.0005,"CONFORME","REVISAR") -> CONFORME
B42: Acero en tapas, asas y bordes | C42: kg | E42: =+F36 -> 186.8636 | F42: ='COLECTOR ACERO'!U17+'COLECTOR REGISTROS Y TAPAS'!E27 -> 186.8636 | G42: =IF(ABS(E42-F42)<0.0005,"CONFORME","REVISAR") -> CONFORME
A44: No hay angulos, soldadura ni pintura: la tapa es ciega de concreto armado (lamina DPLV-23). El rebaje de asiento y el borde engrosado de la abertura se metran con el concreto de la losa del colector (hoja COLECTOR CONCRETO).

Sheet ACU JUNTA DILATACION
A1: ANALISIS DE COSTO UNITARIO - JUNTA DE DILATACION E=1" CON TECNOPOR Y SELLADOR ASFALTICO EN COLECTOR
A2: ENTIDAD | C2: =+RESUMEN!B4 -> GERENCIA TERRITORIAL BAJO MAYO - TARAPOTO
A3: PROYECTO | C3: =+RESUMEN!B5 -> CREACIÓN DEL SERVICIO DE PROTECCIÓN INTEGRAL A NIÑAS, NIÑOS Y ADOLESCENTES SIN CUIDADOS PARENTALES O EN RIESGO DE PERDERLOS EN CENTRO DE ACOGIDA RESIDENCIAL - VARONES DISTRITO DE MORALES DE LA PROVINCIA DE SAN MARTÍN DEL DEPARTAMENTO DE SAN MARTÍN, con CUI N.° 2705619
A4: UBICACIÓN | C4: =+RESUMEN!B6 -> SAN MARTIN - SAN MARTIN - MORALES
A5: FECHA | C5: =+RESUMEN!B7 -> 46266
A7: Partida de Delphin 01.04.04.06.01 JUNTA DE DILATACION E=1" CON TECNOPOR Y SELLADOR ASFALTICO EN COLECTOR (metrado 01.04.04.06.01, hoja COLECTOR JUNTAS Y EMPALMES). Se mide por metro de junta a lo largo del perimetro de la seccion. Cantidades de la lamina DPLV-29: plancha de tecnopor de 1" en toda la seccion y sellador asfaltico 1" x 2" (asfalto liquido RC-250 + arena gruesa) en las caras interiores y en la cara superior (EG-2013 MTC, 510). Celda amarilla = dato; verde = formula. Precios sin IGV.
A9: 1. CANTIDADES POR METRO DE JUNTA (lamina DPLV-29 y hoja COLECTOR JUNTAS Y EMPALMES)
A10: N° | B10: CONCEPTO | C10: UND | D10: VALOR | H10: SUSTENTO
A11: 1 | B11: Perimetro de la seccion en cada junta: 2 x 0.90 + 2 x (0.15 + 1.17 + 0.10) | C11: m | D11: ='COLECTOR JUNTAS Y EMPALMES'!E11 -> 4.64 | H11: COLECTOR JUNTAS Y EMPALMES fila 11; DPLV-29 A
A12: 2 | B12: Numero de juntas de dilatacion (cada 4.00 m) | C12: und | D12: ='COLECTOR JUNTAS Y EMPALMES'!D11 -> 26 | H12: COLECTOR JUNTAS Y EMPALMES fila 11; DPLV-29 E
A13: 3 | B13: Area de tecnopor por junta: seccion 0.90 x 1.42 menos el hueco 0.60 x 1.17 | C13: m2 | D13: =0.9*(0.15+1.17+0.1)-0.6*1.17 -> 0.576 | H13: DPLV-29, cuadro de componentes
A14: 4 | B14: Tecnopor por metro de junta (area neta) | C14: m2/m | D14: =D13/D11 -> 0.12413793 | H14: formula
A15: 5 | B15: Desperdicio por el corte del anillo en planchas de 1.20 x 2.40 | C15: - | D15: 0.1 | H15: criterio: recortes del hueco interior y de las esquinas
A16: 6 | B16: Area de una plancha de tecnopor 1" (1.20 x 2.40 m) | C16: m2 | D16: 2.88 | H16: medida comercial
A17: 7 | B17: Planchas de tecnopor por metro de junta | C17: pln/m | D17: =D14*(1+D15)/D16 -> 0.047413793 | H17: formula
A18: 8 | B18: Longitud sellada por junta: caras interiores 2 x 1.17 + 0.60 y cara superior 0.90 | C18: m | D18: =2*1.17+0.6+0.9 -> 3.84 | H18: DPLV-29, cuadro de componentes
A19: 9 | B19: Seccion del sellador 1" x 2" (0.0254 x 0.0508) | C19: m2 | D19: =0.0254*0.0508 -> 0.00129032 | H19: DPLV-29 B; EG-2013 MTC, Seccion 510
A20: 10 | B20: Mezcla de sellador por metro de junta | C20: m3/m | D20: =D19*D18/D11 -> 0.001067851 | H20: formula
A21: 11 | B21: Asfalto liquido RC-250 por m3 de mezcla | C21: gal/m3 | D21: 50 | H21: criterio: mezcla de ~2,000 kg/m3 con ~9 % de asfalto = 180 kg / 3.6 kg/gal
A22: 12 | B22: Arena gruesa por m3 de mezcla | C22: m3/m3 | D22: 1.05 | H22: criterio: arena suelta con 5 % de desperdicio
A23: 13 | B23: Operario por metro de junta (colocacion del tecnopor y sellado) | C23: hh/m | D23: ='COLECTOR INSUMOS'!G71 -> 0.2 | H23: COLECTOR INSUMOS fila 71
A24: 14 | B24: Peon por metro de junta | C24: hh/m | D24: ='COLECTOR INSUMOS'!G72 -> 0.2 | H24: COLECTOR INSUMOS fila 72
A26: 2. ANALISIS DE COSTO UNITARIO (formato Delphin)
A27: Partida | C27: 01.04.04.06.01 JUNTA DE DILATACION E=1" CON TECNOPOR Y SELLADOR ASFALTICO EN COLECTOR
A28: Partida del metrado | C28: 01.04.04.06.01 (hoja COLECTOR JUNTAS Y EMPALMES)
A29: Unidad | C29: m
A30: Metrado | C30: ='COLECTOR JUNTAS Y EMPALMES'!F12 -> 120.64
A31: Rendimiento (m/dia, cuadrilla de 1 operario) | C31: =8/E34 -> 40
A32: N° | B32: RECURSO | C32: UND | D32: CUADRILLA | E32: CANTIDAD POR M | F32: PRECIO S/ | G32: PARCIAL S/ | H32: FUENTE DEL PRECIO
B33: MANO DE OBRA
A34: 1 | B34: Operario | C34: hh | D34: =E34*$C$31/8 -> 1 | E34: =$D$23 -> 0.2 | F34: ='COSTO HORA HOMBRE 2026'!$G$11 -> 28.95 | G34: =E34*F34 -> 5.79 | H34: hoja COSTO HORA HOMBRE 2026 (tabla oficial CAPECO - FTCCP 2026)
A35: 2 | B35: Peon | C35: hh | D35: =E35*$C$31/8 -> 1 | E35: =$D$24 -> 0.2 | F35: ='COSTO HORA HOMBRE 2026'!$G$13 -> 20.54 | G35: =E35*F35 -> 4.108 | H35: hoja COSTO HORA HOMBRE 2026 (tabla oficial CAPECO - FTCCP 2026)
B36: Subtotal mano de obra | G36: =SUM(G34:G35) -> 9.898
B37: MATERIALES
A38: 3 | B38: Plancha de tecnopor 1" x 1.20 x 2.40 m | C38: pln | E38: =$D$17 -> 0.047413793 | F38: =13.9/1.18 -> 11.779661 | G38: =E38*F38 -> 0.55851841 | H38: Sodimac Peru: plancha de poliestireno expandido 1" x 1.20 x 2.40 m (Dipropor) S/ 13.90 con IGV
A39: 4 | B39: Asfalto liquido RC-250 | C39: gal | E39: =$D$20*$D$21 -> 0.053392552 | F39: =17.7/1.18 -> 15 | G39: =E39*F39 -> 0.80088828 | H39: Conselva: asfalto liquido RC-250 por galon S/ 17.70 con IGV (Petroperu publica su lista ex planta; confirmar en Tarapoto)
A40: 5 | B40: Arena gruesa | C40: m3 | E40: =$D$20*$D$22 -> 0.0011212436 | F40: ='ACU TAPA REGISTRO'!F43 -> 40.68 | G40: =E40*F40 -> 0.045612189 | H40: precio de la ACU TAPA REGISTRO (Agregados Tarapoto, Morales)
B41: Subtotal materiales | G41: =SUM(G38:G40) -> 1.4050189
B42: EQUIPOS
A43: 6 | B43: Herramientas manuales | C43: %mo | E43: 0.03 | F43: =+G36 -> 9.898 | G43: =E43*F43 -> 0.29694 | H43: 3 % del costo de mano de obra (incluye recipiente para calentar el asfalto)
B44: Subtotal equipos | G44: =SUM(G43:G43) -> 0.29694
A45: COSTO UNITARIO DIRECTO (S/ por m) | G45: =+G36+G41+G44 -> 11.599959
A46: COSTO DIRECTO DE LA PARTIDA (metrado x costo unitario, S/) | G46: =G45*C30 -> 1399.419

Sheet ACU JUNTA CAJA CL
A1: ANALISIS DE COSTO UNITARIO - JUNTA E=1" CON TECNOPOR Y SELLADOR ASFALTICO ENTRE COLECTOR Y CAJA CL
A2: ENTIDAD | C2: =+RESUMEN!B4 -> GERENCIA TERRITORIAL BAJO MAYO - TARAPOTO
A3: PROYECTO | C3: =+RESUMEN!B5 -> CREACIÓN DEL SERVICIO DE PROTECCIÓN INTEGRAL A NIÑAS, NIÑOS Y ADOLESCENTES SIN CUIDADOS PARENTALES O EN RIESGO DE PERDERLOS EN CENTRO DE ACOGIDA RESIDENCIAL - VARONES DISTRITO DE MORALES DE LA PROVINCIA DE SAN MARTÍN DEL DEPARTAMENTO DE SAN MARTÍN, con CUI N.° 2705619
A4: UBICACIÓN | C4: =+RESUMEN!B6 -> SAN MARTIN - SAN MARTIN - MORALES
A5: FECHA | C5: =+RESUMEN!B7 -> 46266
A7: Partida de Delphin 01.04.04.06.02 JUNTA E=1" CON TECNOPOR Y SELLADOR ASFALTICO ENTRE COLECTOR Y CAJA CL (metrado 01.04.04.06.02, hoja COLECTOR JUNTAS Y EMPALMES). Se mide por metro de junta a lo largo del perimetro de la seccion, en el contacto del colector con el muro este de la caja CL. Cantidades de la lamina DPLV-29: plancha de tecnopor de 1" en toda la seccion y sellador asfaltico 1" x 2" (RC-250 + arena) en las caras interiores y en la cara superior. A ambos lados del colector hay terreno natural: no lleva junta longitudinal. Celda amarilla = dato; verde = formula. Precios sin IGV.
A9: 1. CANTIDADES POR METRO DE JUNTA (lamina DPLV-29 y hoja COLECTOR JUNTAS Y EMPALMES)
A10: N° | B10: CONCEPTO | C10: UND | D10: VALOR | H10: SUSTENTO
A11: 1 | B11: Perimetro de la seccion en el contacto con la caja CL: 2 x 0.90 + 2 x (0.15 + 1.17 + 0.10) | C11: m | D11: =+'COLECTOR JUNTAS Y EMPALMES'!E16 -> 4.64 | H11: COLECTOR JUNTAS Y EMPALMES fila 16; DPLV-29
A12: 2 | B12: Numero de juntas en el contacto con la caja CL | C12: und | D12: =+'COLECTOR JUNTAS Y EMPALMES'!D16 -> 1 | H12: COLECTOR JUNTAS Y EMPALMES fila 16
A13: 3 | B13: Area de tecnopor de la junta: seccion 0.90 x 1.42 menos el hueco 0.60 x 1.17 | C13: m2 | D13: =0.9*(0.15+1.17+0.1)-0.6*1.17 -> 0.576 | H13: DPLV-29, cuadro de componentes
A14: 4 | B14: Tecnopor por metro de junta (area neta) | C14: m2/m | D14: =D13/D11 -> 0.12413793 | H14: formula
A15: 5 | B15: Desperdicio por el corte del anillo en planchas de 1.20 x 2.40 | C15: - | D15: 0.1 | H15: criterio: recortes del hueco interior y de las esquinas
A16: 6 | B16: Area de una plancha de tecnopor 1" (1.20 x 2.40 m) | C16: m2 | D16: 2.88 | H16: medida comercial
A17: 7 | B17: Planchas de tecnopor por metro de junta | C17: pln/m | D17: =D14*(1+D15)/D16 -> 0.047413793 | H17: formula
A18: 8 | B18: Longitud sellada: caras interiores 2 x 1.17 + 0.60 y cara superior 0.90 | C18: m | D18: =2*1.17+0.6+0.9 -> 3.84 | H18: DPLV-29, cuadro de componentes
A19: 9 | B19: Seccion del sellador 1" x 2" (0.0254 x 0.0508) | C19: m2 | D19: =0.0254*0.0508 -> 0.00129032 | H19: DPLV-29 B; EG-2013 MTC, Seccion 510
A20: 10 | B20: Mezcla de sellador por metro de junta | C20: m3/m | D20: =D19*D18/D11 -> 0.001067851 | H20: formula
A21: 11 | B21: Asfalto liquido RC-250 por m3 de mezcla | C21: gal/m3 | D21: 50 | H21: criterio: mezcla de ~2,000 kg/m3 con ~9 % de asfalto = 180 kg / 3.6 kg/gal
A22: 12 | B22: Arena gruesa por m3 de mezcla | C22: m3/m3 | D22: 1.05 | H22: criterio: arena suelta con 5 % de desperdicio
A23: 13 | B23: Operario por metro de junta (colocacion del tecnopor y sellado) | C23: hh/m | D23: ='COLECTOR INSUMOS'!G75 -> 0.2 | H23: COLECTOR INSUMOS fila 75
A24: 14 | B24: Peon por metro de junta | C24: hh/m | D24: ='COLECTOR INSUMOS'!G76 -> 0.2 | H24: COLECTOR INSUMOS fila 76
A26: 2. ANALISIS DE COSTO UNITARIO (formato Delphin)
A27: Partida | C27: 01.04.04.06.02 JUNTA E=1" CON TECNOPOR Y SELLADOR ASFALTICO ENTRE COLECTOR Y CAJA CL
A28: Partida del metrado | C28: 01.04.04.06.02 (hoja COLECTOR JUNTAS Y EMPALMES)
A29: Unidad | C29: m
A30: Metrado | C30: =+'COLECTOR JUNTAS Y EMPALMES'!F17 -> 4.64
A31: Rendimiento (m/dia, cuadrilla de 1 operario) | C31: =8/E34 -> 40
A32: N° | B32: RECURSO | C32: UND | D32: CUADRILLA | E32: CANTIDAD POR M | F32: PRECIO S/ | G32: PARCIAL S/ | H32: FUENTE DEL PRECIO
B33: MANO DE OBRA
A34: 1 | B34: Operario | C34: hh | D34: =E34*$C$31/8 -> 1 | E34: =$D$23 -> 0.2 | F34: ='COSTO HORA HOMBRE 2026'!$G$11 -> 28.95 | G34: =E34*F34 -> 5.79 | H34: hoja COSTO HORA HOMBRE 2026 (tabla oficial CAPECO - FTCCP 2026)
A35: 2 | B35: Peon | C35: hh | D35: =E35*$C$31/8 -> 1 | E35: =$D$24 -> 0.2 | F35: ='COSTO HORA HOMBRE 2026'!$G$13 -> 20.54 | G35: =E35*F35 -> 4.108 | H35: hoja COSTO HORA HOMBRE 2026 (tabla oficial CAPECO - FTCCP 2026)
B36: Subtotal mano de obra | G36: =SUM(G34:G35) -> 9.898
B37: MATERIALES
A38: 3 | B38: Plancha de tecnopor 1" x 1.20 x 2.40 m | C38: pln | E38: =$D$17 -> 0.047413793 | F38: =13.9/1.18 -> 11.779661 | G38: =E38*F38 -> 0.55851841 | H38: Sodimac Peru: plancha de poliestireno expandido 1" x 1.20 x 2.40 m (Dipropor) S/ 13.90 con IGV
A39: 4 | B39: Asfalto liquido RC-250 | C39: gal | E39: =$D$20*$D$21 -> 0.053392552 | F39: =17.7/1.18 -> 15 | G39: =E39*F39 -> 0.80088828 | H39: Conselva: asfalto liquido RC-250 por galon S/ 17.70 con IGV (Petroperu publica su lista ex planta; confirmar en Tarapoto)
A40: 5 | B40: Arena gruesa | C40: m3 | E40: =$D$20*$D$22 -> 0.0011212436 | F40: ='ACU TAPA REGISTRO'!F43 -> 40.68 | G40: =E40*F40 -> 0.045612189 | H40: precio de la ACU TAPA REGISTRO (Agregados Tarapoto, Morales)
B41: Subtotal materiales | G41: =SUM(G38:G40) -> 1.4050189
B42: EQUIPOS
A43: 6 | B43: Herramientas manuales | C43: %mo | E43: 0.03 | F43: =+G36 -> 9.898 | G43: =E43*F43 -> 0.29694 | H43: 3 % del costo de mano de obra (incluye recipiente para calentar el asfalto)
B44: Subtotal equipos | G44: =SUM(G43:G43) -> 0.29694
A45: COSTO UNITARIO DIRECTO (S/ por m) | G45: =+G36+G41+G44 -> 11.599959
A46: COSTO DIRECTO DE LA PARTIDA (metrado x costo unitario, S/) | G46: =G45*C30 -> 53.823809

Sheet DESAGREGADO LLORADEROS
A1: DESAGREGADO DE LA PARTIDA 01.04.03.04.03.04 - LLORADERO DE TUBERIA PVC Ø3" C/FILTRO DE GRAVA Y GEOTEXTIL @1.50 m
A2: ENTIDAD | C2: =+RESUMEN!B4 -> GERENCIA TERRITORIAL BAJO MAYO - TARAPOTO
A3: PROYECTO | C3: =+RESUMEN!B5 -> CREACIÓN DEL SERVICIO DE PROTECCIÓN INTEGRAL A NIÑAS, NIÑOS Y ADOLESCENTES SIN CUIDADOS PARENTALES O EN RIESGO DE PERDERLOS EN CENTRO DE ACOGIDA RESIDENCIAL - VARONES DISTRITO DE MORALES DE LA PROVINCIA DE SAN MARTÍN DEL DEPARTAMENTO DE SAN MARTÍN, con CUI N.° 2705619
A4: UBICACIÓN | C4: =+RESUMEN!B6 -> SAN MARTIN - SAN MARTIN - MORALES
A5: FECHA | C5: =+RESUMEN!B7 -> 46266
A7: La partida se mide por unidad de lloradero. A: ubicacion y numero, de la hoja METRADO LLORADEROS (muros de cuneta colindantes con area verde, medidos en la planta general de drenaje; un lloradero cada 1.50 m). B: componentes de un lloradero segun las laminas DPLV-34 y DPLV-35 (tubo PVC-U Ø 3" de 0.30 m con 8 perforaciones Ø 3/8", filtro de grava de 0.30 x 0.30 x 0.30 m forrado con geotextil no tejido) por el numero de lloraderos. Celda amarilla = dato; verde = formula.
A9: A. UBICACION Y NUMERO DE LLORADEROS (hoja METRADO LLORADEROS)
A10: N° | B10: EJE Y TRAMO (progresivas de la cuneta) | C10: LADO DEL MURO | D10: LONGITUD JUNTO A AREA VERDE (m) | E10: ESPACIAM. (m) | F10: N° DE LLORADEROS | H10: SUSTENTO
A11: 1 | B11: ='METRADO LLORADEROS'!B7&": "&'METRADO LLORADEROS'!C7 -> EJE 01: 0+013.50 a 0+019.00 | C11: ='METRADO LLORADEROS'!D7 -> LADO ESTE | D11: ='METRADO LLORADEROS'!E7 -> 5.5 | E11: ='METRADO LLORADEROS'!F7 -> 1.5 | F11: ='METRADO LLORADEROS'!G7 -> 4 | H11: planta general de drenaje; N° = REDONDEAR.MAS(L / 1.50)
A12: 2 | B12: ='METRADO LLORADEROS'!B8&": "&'METRADO LLORADEROS'!C8 -> EJE 01: 0+054.75 a 0+077.25 | C12: ='METRADO LLORADEROS'!D8 -> LADO ESTE | D12: ='METRADO LLORADEROS'!E8 -> 22.5 | E12: ='METRADO LLORADEROS'!F8 -> 1.5 | F12: ='METRADO LLORADEROS'!G8 -> 15 | H12: planta general de drenaje; N° = REDONDEAR.MAS(L / 1.50)
A13: 3 | B13: ='METRADO LLORADEROS'!B9&": "&'METRADO LLORADEROS'!C9 -> EJE 01: 0+080.75 a 0+111.53 | C13: ='METRADO LLORADEROS'!D9 -> LADO ESTE | D13: ='METRADO LLORADEROS'!E9 -> 30.78 | E13: ='METRADO LLORADEROS'!F9 -> 1.5 | F13: ='METRADO LLORADEROS'!G9 -> 21 | H13: planta general de drenaje; N° = REDONDEAR.MAS(L / 1.50)
A14: 4 | B14: ='METRADO LLORADEROS'!B10&": "&'METRADO LLORADEROS'!C10 -> EJE 02: 0+000.00 a 0+013.25 | C14: ='METRADO LLORADEROS'!D10 -> LADO ESTE | D14: ='METRADO LLORADEROS'!E10 -> 13.25 | E14: ='METRADO LLORADEROS'!F10 -> 1.5 | F14: ='METRADO LLORADEROS'!G10 -> 9 | H14: planta general de drenaje; N° = REDONDEAR.MAS(L / 1.50)
A15: 5 | B15: ='METRADO LLORADEROS'!B11&": "&'METRADO LLORADEROS'!C11 -> EJE 02: 0+021.00 a 0+023.03 | C15: ='METRADO LLORADEROS'!D11 -> LADO OESTE | D15: ='METRADO LLORADEROS'!E11 -> 2.03 | E15: ='METRADO LLORADEROS'!F11 -> 1.5 | F15: ='METRADO LLORADEROS'!G11 -> 2 | H15: planta general de drenaje; N° = REDONDEAR.MAS(L / 1.50)
A16: 6 | B16: ='METRADO LLORADEROS'!B12&": "&'METRADO LLORADEROS'!C12 -> EJE 02: 0+023.03 a 0+033.78 | C16: ='METRADO LLORADEROS'!D12 -> LADO SUR | D16: ='METRADO LLORADEROS'!E12 -> 10.75 | E16: ='METRADO LLORADEROS'!F12 -> 1.5 | F16: ='METRADO LLORADEROS'!G12 -> 8 | H16: planta general de drenaje; N° = REDONDEAR.MAS(L / 1.50)
A17: 7 | B17: ='METRADO LLORADEROS'!B13&": "&'METRADO LLORADEROS'!C13 -> EJE 03: 0+000.00 a 0+005.50 | C17: ='METRADO LLORADEROS'!D13 -> LADO OESTE | D17: ='METRADO LLORADEROS'!E13 -> 5.5 | E17: ='METRADO LLORADEROS'!F13 -> 1.5 | F17: ='METRADO LLORADEROS'!G13 -> 4 | H17: planta general de drenaje; N° = REDONDEAR.MAS(L / 1.50)
A18: 8 | B18: ='METRADO LLORADEROS'!B14&": "&'METRADO LLORADEROS'!C14 -> EJE 03: 0+007.00 a 0+015.48 | C18: ='METRADO LLORADEROS'!D14 -> LADO OESTE | D18: ='METRADO LLORADEROS'!E14 -> 8.48 | E18: ='METRADO LLORADEROS'!F14 -> 1.5 | F18: ='METRADO LLORADEROS'!G14 -> 6 | H18: planta general de drenaje; N° = REDONDEAR.MAS(L / 1.50)
A19: 9 | B19: ='METRADO LLORADEROS'!B15&": "&'METRADO LLORADEROS'!C15 -> EJE 03: 0+017.73 a 0+021.48 | C19: ='METRADO LLORADEROS'!D15 -> LADO SUR | D19: ='METRADO LLORADEROS'!E15 -> 3.75 | E19: ='METRADO LLORADEROS'!F15 -> 1.5 | F19: ='METRADO LLORADEROS'!G15 -> 3 | H19: planta general de drenaje; N° = REDONDEAR.MAS(L / 1.50)
A20: 10 | B20: ='METRADO LLORADEROS'!B16&": "&'METRADO LLORADEROS'!C16 -> EJE 04: 0+020.50 a 0+024.25 | C20: ='METRADO LLORADEROS'!D16 -> LADO ESTE | D20: ='METRADO LLORADEROS'!E16 -> 3.75 | E20: ='METRADO LLORADEROS'!F16 -> 1.5 | F20: ='METRADO LLORADEROS'!G16 -> 3 | H20: planta general de drenaje; N° = REDONDEAR.MAS(L / 1.50)
A21: 11 | B21: ='METRADO LLORADEROS'!B17&": "&'METRADO LLORADEROS'!C17 -> EJE 04: 0+034.75 a 0+038.50 | C21: ='METRADO LLORADEROS'!D17 -> LADO ESTE | D21: ='METRADO LLORADEROS'!E17 -> 3.75 | E21: ='METRADO LLORADEROS'!F17 -> 1.5 | F21: ='METRADO LLORADEROS'!G17 -> 3 | H21: planta general de drenaje; N° = REDONDEAR.MAS(L / 1.50)
A22: 12 | B22: ='METRADO LLORADEROS'!B18&": "&'METRADO LLORADEROS'!C18 -> EJE 04: 0+045.00 a 0+048.75 | C22: ='METRADO LLORADEROS'!D18 -> LADO ESTE | D22: ='METRADO LLORADEROS'!E18 -> 3.75 | E22: ='METRADO LLORADEROS'!F18 -> 1.5 | F22: ='METRADO LLORADEROS'!G18 -> 3 | H22: planta general de drenaje; N° = REDONDEAR.MAS(L / 1.50)
... A44: 34 | B44: ='METRADO LLORADEROS'!B40&": "&'METRADO LLORADEROS'!C40 -> EJE 09: 0+000.25 a 0+021.75 | C44: ='METRADO LLORADEROS'!D40 -> LADO OESTE | D44: ='METRADO LLORADEROS'!E40 -> 21.5 | E44: ='METRADO LLORADEROS'!F40 -> 1.5 | F44: ='METRADO LLORADEROS'!G40 -> 15 | H44: planta general de drenaje; N° = REDONDEAR.MAS(L / 1.50)
B45: TOTAL (und de la partida) | D45: =SUM(D11:D44) -> 320.53 | F45: =SUM(F11:F44) -> 226
A47: B. DATOS DEL DETALLE (laminas DPLV-34 y DPLV-35)
A48: N° | B48: DATO | C48: UND | D48: VALOR | H48: SUSTENTO
A49: 1 | B49: Lado del filtro localizado (cubo de grava forrado con geotextil) | C49: m | D49: 0.3 | H49: DPLV-35 A: filtro 0.30 x 0.30 x 0.30 m
A50: 2 | B50: Longitud del tubo PVC-U Ø 3" por lloradero | C50: m | D50: 0.3 | H50: DPLV-35 B: 0.10 en el muro + 0.20 perforado dentro del filtro
A51: 3 | B51: Perforaciones Ø 3/8" por fila | C51: und | D51: 4 | H51: DPLV-35 B: 4 perforaciones @0.05 por fila
A52: 4 | B52: Filas de perforaciones | C52: und | D52: 2 | H52: DPLV-35 B: 2 filas a 120 grados, simetricas respecto al fondo
A53: 5 | B53: Desperdicio de grava (acomodo y perdidas) | C53: - | D53: 0.1 | H53: criterio de obra
A54: 6 | B54: Traslapes del geotextil | C54: - | D54: 0.1 | H54: DPLV-34 etapa 3: traslape de 0.10 m al cerrar el filtro
A55: 7 | B55: Mortero 1:3 de sellado alrededor del tubo | C55: m3 | D55: 0.0005 | H55: anillo de 0.02 m en las dos caras del muro (DPLV-35)
A57: C. COMPONENTES DE UN LLORADERO Y TOTAL DE LA PARTIDA
A58: N° | B58: COMPONENTE | C58: UND | D58: POR LLORADERO | E58: N° LLORADEROS | F58: TOTAL | H58: SUSTENTO
A59: 1 | B59: Tubo PVC-U Ø 3" para desague (NTP 399.003) | C59: m | D59: =$D$50 -> 0.3 | E59: =+$F$45 -> 226 | F59: =D59*E59 -> 67.8 | H59: DPLV-35 B; sale de tubos de 3 m (10 lloraderos por tubo)
A60: 2 | B60: Perforaciones Ø 3/8" en el tramo dentro del filtro | C60: und | D60: =$D$51*$D$52 -> 8 | E60: =+$F$45 -> 226 | F60: =D60*E60 -> 1808 | H60: DPLV-35 B
A61: 3 | B61: Excavacion local del hueco del filtro (lado^3) | C61: m3 | D61: =$D$49^3 -> 0.027 | E61: =+$F$45 -> 226 | F61: =D61*E61 -> 6.102 | H61: DPLV-34 etapa 1; incluida en la mano de obra del ACU
A62: 4 | B62: Grava filtrante (ripio) 20 a 40 mm: lado^3 + desperdicio | C62: m3 | D62: =$D$49^3*(1+$D$53) -> 0.0297 | E62: =+$F$45 -> 226 | F62: =D62*E62 -> 6.7122 | H62: DPLV-34 etapa 2; DPLV-35 A
A63: 5 | B63: Geotextil no tejido clase 2: 6 caras del cubo + traslapes | C63: m2 | D63: =6*$D$49^2*(1+$D$54) -> 0.594 | E63: =+$F$45 -> 226 | F63: =D63*E63 -> 134.244 | H63: DPLV-34 etapa 3; DPLV-35 A
A64: 6 | B64: Mortero 1:3 de sellado alrededor del tubo | C64: m3 | D64: =$D$55 -> 0.0005 | E64: =+$F$45 -> 226 | F64: =D64*E64 -> 0.113 | H64: DPLV-35
A66: D. CONTROL CON EL RESUMEN
B67: PARTIDA | C67: UND | E67: ESTA HOJA | F67: RESUMEN | G67: CONTROL
B68: 01.04.03.04.03.04 LLORADERO DE TUBERIA PVC Ø3" C/FILTRO DE GRAVA Y GEOTEXTIL @1.50 m | C68: und | E68: =+$F$45 -> 226 | F68: =+RESUMEN!D32 -> 226 | G68: =IF(ABS(E68-F68)<0.001,"CONFORME","REVISAR") -> CONFORME

Sheet ACU LLORADEROS
A1: ANALISIS DE COSTO UNITARIO - LLORADERO DE TUBERIA PVC Ø3" C/FILTRO DE GRAVA Y GEOTEXTIL @1.50 m
A2: ENTIDAD | C2: =+RESUMEN!B4 -> GERENCIA TERRITORIAL BAJO MAYO - TARAPOTO
A3: PROYECTO | C3: =+RESUMEN!B5 -> CREACIÓN DEL SERVICIO DE PROTECCIÓN INTEGRAL A NIÑAS, NIÑOS Y ADOLESCENTES SIN CUIDADOS PARENTALES O EN RIESGO DE PERDERLOS EN CENTRO DE ACOGIDA RESIDENCIAL - VARONES DISTRITO DE MORALES DE LA PROVINCIA DE SAN MARTÍN DEL DEPARTAMENTO DE SAN MARTÍN, con CUI N.° 2705619
A4: UBICACIÓN | C4: =+RESUMEN!B6 -> SAN MARTIN - SAN MARTIN - MORALES
A5: FECHA | C5: =+RESUMEN!B7 -> 46266
A7: Partida de Delphin 01.04.03.04.03.04 LLORADERO DE TUBERIA PVC Ø3" C/FILTRO DE GRAVA Y GEOTEXTIL @1.50 m (CUNETA COLINDANTE CON AREA VERDE) (metrado: hojas METRADO LLORADEROS y DESAGREGADO LLORADEROS). Cantidades por lloradero de las laminas DPLV-34 y DPLV-35: tubo PVC-U Ø 3" de 0.30 m con 8 perforaciones Ø 3/8", filtro de grava de 0.30 x 0.30 x 0.30 m forrado con geotextil no tejido y mortero 1:3 de sellado. Mano de obra de la hoja COSTO HORA HOMBRE 2026. Celda amarilla = dato; verde = formula. Precios sin IGV.
A9: 1. CANTIDADES POR LLORADERO (hoja DESAGREGADO LLORADEROS)
A10: N° | B10: CONCEPTO | C10: UND | D10: VALOR | H10: SUSTENTO
A11: 1 | B11: Numero de lloraderos de la partida | C11: und | D11: ='DESAGREGADO LLORADEROS'!F45 -> 226 | H11: DESAGREGADO LLORADEROS fila 45
A12: 2 | B12: Tubo PVC-U Ø 3" por lloradero | C12: m | D12: ='DESAGREGADO LLORADEROS'!D59 -> 0.3 | H12: DESAGREGADO LLORADEROS fila 59 (DPLV-35 B)
A13: 3 | B13: Desperdicio del tubo (corte de 10 piezas por tubo de 3 m) | C13: - | D13: 0.05 | H13: criterio de obra
A14: 4 | B14: Grava filtrante por lloradero (incluye 10 % de desperdicio) | C14: m3 | D14: ='DESAGREGADO LLORADEROS'!D62 -> 0.0297 | H14: DESAGREGADO LLORADEROS fila 62 (DPLV-35 A)
A15: 5 | B15: Geotextil por lloradero (6 caras + 10 % de traslapes) | C15: m2 | D15: ='DESAGREGADO LLORADEROS'!D63 -> 0.594 | H15: DESAGREGADO LLORADEROS fila 63 (DPLV-34 etapa 3)
A16: 6 | B16: Desperdicio del geotextil (corte del rollo) | C16: - | D16: 0.05 | H16: criterio de obra
A17: 7 | B17: Mortero 1:3 de sellado alrededor del tubo | C17: m3 | D17: ='DESAGREGADO LLORADEROS'!D64 -> 0.0005 | H17: DESAGREGADO LLORADEROS fila 64 (DPLV-35)
A18: 8 | B18: Cemento por m3 de mortero 1:3 | C18: bol/m3 | D18: 10.5 | H18: dosificacion usual del mortero 1:3
A19: 9 | B19: Arena gruesa por m3 de mortero 1:3 | C19: m3/m3 | D19: 1.05 | H19: arena suelta con 5 % de desperdicio
A20: 10 | B20: Agua por m3 de mortero 1:3 | C20: m3/m3 | D20: 0.27 | H20: dosificacion usual del mortero 1:3
A21: 11 | B21: Rendimiento de la cuadrilla | C21: und/dia | D21: 24 | H21: excavacion local de 0.027 m3, forrado, grava y cierre; el tubo se deja al vaciar el muro
A22: 12 | B22: Operarios en la cuadrilla | C22: - | D22: 0.5 | H22: colocacion del tubo, sellado y control
A23: 13 | B23: Peones en la cuadrilla | C23: - | D23: 1 | H23: excavacion, grava y relleno
A25: 2. ANALISIS DE COSTO UNITARIO (formato Delphin)
A26: Partida | C26: 01.04.03.04.03.04 LLORADERO DE TUBERIA PVC Ø3" C/FILTRO DE GRAVA Y GEOTEXTIL @1.50 m (CUNETA COLINDANTE CON AREA VERDE)
A27: Partida del metrado | C27: 01.04.03.04.03.04 (hojas METRADO LLORADEROS y DESAGREGADO LLORADEROS)
A28: Unidad | C28: und
A29: Metrado | C29: ='DESAGREGADO LLORADEROS'!F45 -> 226
A30: Rendimiento (und/dia, cuadrilla 0.5 operario + 1 peon) | C30: =$D$21 -> 24
A31: N° | B31: RECURSO | C31: UND | D31: CUADRILLA | E31: CANTIDAD POR UND | F31: PRECIO S/ | G31: PARCIAL S/ | H31: FUENTE DEL PRECIO
B32: MANO DE OBRA
A33: 1 | B33: Operario | C33: hh | D33: =E33*$C$30/8 -> 0.5 | E33: =$D$22*8/$D$21 -> 0.16666667 | F33: ='COSTO HORA HOMBRE 2026'!$G$11 -> 28.95 | G33: =E33*F33 -> 4.825 | H33: hoja COSTO HORA HOMBRE 2026 (tabla oficial CAPECO - FTCCP 2026)
A34: 2 | B34: Peon | C34: hh | D34: =E34*$C$30/8 -> 1 | E34: =$D$23*8/$D$21 -> 0.33333333 | F34: ='COSTO HORA HOMBRE 2026'!$G$13 -> 20.54 | G34: =E34*F34 -> 6.8466667 | H34: hoja COSTO HORA HOMBRE 2026 (tabla oficial CAPECO - FTCCP 2026)
B35: Subtotal mano de obra | G35: =SUM(G33:G34) -> 11.671667
B36: MATERIALES
A37: 3 | B37: Tubo PVC-U Ø 3" desague (NTP 399.003) | C37: m | E37: =$D$12*(1+$D$13) -> 0.315 | F37: =39.9/1.18/3 -> 11.271186 | G37: =E37*F37 -> 3.5504237 | H37: Sodimac Peru y Promart: tubo desague PVC 3" x 3 m liviano Pavco S/ 39.90 con IGV (S/ 11.27 el m sin IGV)
A38: 4 | B38: Grava filtrante 20 a 40 mm | C38: m3 | E38: =$D$14 -> 0.0297 | F38: =70/1.18 -> 59.322034 | G38: =E38*F38 -> 1.7618644 | H38: Agregados Tarapoto (Morales): piedra chancada 3/4" S/ 70.00 el m3 puesto en obra (precio publicado mas cercano a la grava 20 a 40 mm)
A39: 5 | B39: Geotextil no tejido 200 g/m2 | C39: m2 | E39: =$D$15*(1+$D$16) -> 0.6237 | F39: =2300/400/1.18 -> 4.8728814 | G39: =E39*F39 -> 3.0392161 | H39: Ferropolis Peru: geotextil no tejido 200 g/m2, rollo de 4 x 100 m S/ 2,300.00 (S/ 5.75 el m2 con IGV)
A40: 6 | B40: Cemento Portland tipo I | C40: bol | E40: =$D$17*$D$18 -> 0.00525 | F40: ='ACU TAPA REGISTRO'!F42 -> 30.93 | G40: =E40*F40 -> 0.1623825 | H40: precio de la ACU TAPA REGISTRO (Cemento Pacasmayo tipo I S/ 36.50 con IGV)
A41: 7 | B41: Arena gruesa | C41: m3 | E41: =$D$17*$D$19 -> 0.000525 | F41: ='ACU TAPA REGISTRO'!F43 -> 40.68 | G41: =E41*F41 -> 0.021357 | H41: precio de la ACU TAPA REGISTRO (Agregados Tarapoto, Morales)
A42: 8 | B42: Agua | C42: m3 | E42: =$D$17*$D$20 -> 0.000135 | F42: ='ACU TAPA REGISTRO'!F45 -> 8.33 | G42: =E42*F42 -> 0.00112455 | H42: precio de la ACU TAPA REGISTRO (EMAPA San Martin)
B43: Subtotal materiales | G43: =SUM(G37:G42) -> 8.5363683
B44: EQUIPOS
A45: 9 | B45: Herramientas manuales | C45: %mo | E45: 0.03 | F45: =+G35 -> 11.671667 | G45: =E45*F45 -> 0.35015 | H45: 3 % del costo de mano de obra (pala, pico, barreta, sierra para PVC y taladro para las perforaciones)
B46: Subtotal equipos | G46: =SUM(G45:G45) -> 0.35015
A47: COSTO UNITARIO DIRECTO (S/ por und) | G47: =+G35+G43+G46 -> 20.558185
A48: COSTO DIRECTO DE LA PARTIDA (metrado x costo unitario, S/) | G48: =G47*C29 -> 4646.1498
